begin_compilation
  name " HotSpotCompilation-87[Towers$TowersDisk.<init>(int)]"
  method "HotSpotCompilation-87[Towers$TowersDisk.<init>(int)]"
  date 1731420413659
end_compilation
begin_cfg
  name "Final HIR schedule"
  begin_block
    name "B0"
    from_bci -1
    to_bci -1
    predecessors 
    successors 
    xhandlers
    flags 
    probability 4607182418800017408
    begin_IR
      HIR
f <@#|@fixed with next>@ <|@
tid v0 <|@
d <@d|@=== Debug Properties ===
hasSpeculationFence: false
stamp: void
=== Inputs ===
stateAfter: - 
=== Succesors ===
next: v5 
=== Usages ===
=== Predecessor ===
- >@ <|@
instruction <@StartNode|@jdk.graal.compiler.nodes.StartNode>@ stateAfter: - #next: v5  <|@  <|@
f <@~|@floating>@ <|@
tid a1 <|@
d <@d|@=== Debug Properties ===
index: 0
stamp: a!# Towers$TowersDisk
uncheckedStamp: [null]
=== Inputs ===
=== Succesors ===
=== Usages ===
v17 v11 ?16 
=== Predecessor ===
- >@ <|@
instruction <@Parameter|@jdk.graal.compiler.nodes.ParameterNode>@  <|@  <|@
tid v11 <|@
d <@d|@=== Debug Properties ===
callType: JavaCall
invokeKind: Special
nodeSourcePosition: at Towers$TowersDisk.<init>(int) [bci: 1]
referencedType: [null]
returnStamp: void
signature: [HotSpotType<Ljava/lang/Object;, resolved>]
stamp: void
targetMethod: HotSpotMethod<Object.<init>()>
=== Inputs ===
arguments: a1 
=== Succesors ===
=== Usages ===
v5 
=== Predecessor ===
- >@ <|@
instruction <@HotSpotDirectCallTarget|@jdk.graal.compiler.hotspot.nodes.HotSpotDirectCallTargetNode>@ arguments: a1  <|@  <|@
f <@~|@floating>@ <|@
tid i2 <|@
d <@d|@=== Debug Properties ===
index: 1
stamp: i32
uncheckedStamp: [null]
=== Inputs ===
=== Succesors ===
=== Usages ===
v14 ?16 
=== Predecessor ===
- >@ <|@
instruction <@Parameter|@jdk.graal.compiler.nodes.ParameterNode>@  <|@  <|@
tid ?16 <|@
d <@d|@=== Debug Properties ===
bci: 1
bytecode: invokespecial
code: ResolvedJavaMethodBytecode<Towers$TowersDisk.<init>(int)>
localsSize: 2
locksSize: 0
stackSize: 0
stackState: AfterPop
validForDeoptimization: true
=== Inputs ===
outerFrameState: - 
values: a1 i2 
=== Succesors ===
=== Usages ===
v5 
=== Predecessor ===
- >@ <|@
instruction <@FrameState|@jdk.graal.compiler.nodes.FrameState>@ outerFrameState: - values: a1 i2  <|@  <|@
f <@#|@fixed with next>@ <|@
tid v5 <|@
d <@d|@=== Debug Properties ===
bci: 1
identity: ANY_LOCATION
inlineControl: Normal
isInOOMETry: false
nodeSourcePosition: at Towers$TowersDisk.<init>(int) [bci: 1]
polymorphic: false
stamp: void
targetMethod: Direct#Object.<init>
=== Inputs ===
stateAfter: - 
classInit: - 
callTarget: v11 
stateDuring: ?16 
=== Succesors ===
next: v14 
=== Usages ===
=== Predecessor ===
v0 >@ <|@
instruction <@Invoke|@jdk.graal.compiler.nodes.InvokeNode>@ stateAfter: - classInit: - callTarget: v11 stateDuring: ?16 #next: v14  <|@  <|@
f <@~|@floating>@ <|@
tid v17 <|@
d <@d|@=== Debug Properties ===
displacement: 12
stamp: void*
stride: S1
=== Inputs ===
base: a1 
index: - 
=== Succesors ===
=== Usages ===
v14 
=== Predecessor ===
- >@ <|@
instruction <@AMD64Address|@jdk.graal.compiler.core.amd64.AMD64AddressNode>@ base: a1 index: -  <|@  <|@
f <@#|@fixed with next>@ <|@
tid v14 <|@
d <@d|@=== Debug Properties ===
barrierType: NONE
deoptReasonAndAction: [null]
deoptSpeculation: [null]
killedLocationIdentity: Towers$TowersDisk.size
location: Towers$TowersDisk.size
memoryOrder: PLAIN
nodeSourcePosition: at Towers$TowersDisk.<init>(int) [bci: 6]
stamp: void
usedAsNullCheck: false
=== Inputs ===
stateBefore: - 
guard: - 
address: v17 
lastLocationAccess: - 
value: i2 
stateAfter: - 
=== Succesors ===
next: v15 
=== Usages ===
=== Predecessor ===
v5 >@ <|@
instruction <@Write|@jdk.graal.compiler.nodes.memory.WriteNode>@ stateBefore: - guard: - address: v17 lastLocationAccess: - value: i2 stateAfter: - #next: v15  <|@  <|@
f <@#|@fixed with next>@ <|@
tid v15 <|@
d <@d|@=== Debug Properties ===
barriersString: STORE_STORE
fence: CONSTRUCTOR_FREEZE
location: ANY_LOCATION
nodeSourcePosition: at Towers$TowersDisk.<init>(int) [bci: 9]
stamp: void
=== Inputs ===
=== Succesors ===
next: v10 
=== Usages ===
=== Predecessor ===
v14 >@ <|@
instruction <@Membar|@jdk.graal.compiler.nodes.extended.MembarNode>@ #next: v10  <|@  <|@
f <@*|@fixed>@ <|@
tid v10 <|@
d <@d|@=== Debug Properties ===
nodeSourcePosition: at Towers$TowersDisk.<init>(int) [bci: 9]
stamp: void
=== Inputs ===
memoryMap: - 
result: - 
=== Succesors ===
=== Usages ===
=== Predecessor ===
v15 >@ <|@
instruction <@Return|@jdk.graal.compiler.nodes.ReturnNode>@ memoryMap: - result: -  <|@  <|@
    end_IR
  end_block
end_cfg
begin_cfg
  name "After LIRGeneration"
  begin_block
    name "B0"
    from_bci -1
    to_bci -1
    predecessors 
    successors 
    xhandlers
    flags 
    probability 4607182418800017408
    begin_IR
      LIR
      nr   -1  <|@ instruction [rsi|QWORD[.], rdx|DWORD, rbp|QWORD] = LABEL alignment: 0 numbPhis: 0 label: ? <|@ <|@
      nr   -1  <|@ instruction stack:16|QWORD = MOVE input: rbp|QWORD moveKind: QWORD <|@ <|@
      nr   -1  <|@ instruction [] = HOTSPOTLOCKSTACK frameMapBuilder: jdk.graal.compiler.hotspot.amd64.AMD64HotSpotFrameMapBuilder@3579649f slotKind: QWORD <|@ <|@
      nr   -1  <|@ instruction v0|QWORD[.] = MOVE input: rsi|QWORD[.] moveKind: QWORD <|@ <|@
      nr   -1  <|@ instruction v1|DWORD = MOVE input: rdx|DWORD moveKind: DWORD <|@ <|@
      nr   -1  <|@ instruction rsi|QWORD[.] = MOVE input: v0|QWORD[.] moveKind: QWORD <|@ <|@
      nr   -1  <|@ st <@st|@Towers$TowersDisk.<init>(int) [bci: 1]
locals: v0|QWORD[.] v1|DWORD 
>@ <|@ instruction - = CALL_DIRECT parameters: [rsi|QWORD[.]] temps: [] callTarget: HotSpotMethod<Object.<init>()> invokeKind: Special config: jdk.graal.compiler.hotspot.GraalHotSpotVMConfig@5be2b2dd state [bci:1] <|@ <|@
      nr   -1  <|@ instruction MOV (x: [v0|QWORD[.] + 12], y: v1|DWORD) size: DWORD <|@ <|@
      nr   -1  <|@ instruction RETURN (savedRbp: stack:16|QWORD, value: -) isStub: false requiresReservedStackAccessCheck: false thread: r15 scratchForSafepointOnReturn: rcx config: jdk.graal.compiler.hotspot.GraalHotSpotVMConfig@5be2b2dd <|@ <|@
    end_IR
  end_block
end_cfg
begin_bytecodes
     0: aload_0       
     1: invokespecial #0          // java.lang.Object.<init>:()void
     4: aload_0       
     5: iload_1       
     6: putfield      #1          // size:int
     9: return        
   <|@
end_bytecodes
begin_cfg
  name "After LIR generation"
  begin_block
    name "B0"
    from_bci -1
    to_bci -1
    predecessors 
    successors 
    xhandlers
    flags 
    probability 4607182418800017408
    begin_IR
      HIR
f <@#|@fixed with next>@ <|@
tid v0 <|@
d <@d|@=== Debug Properties ===
hasSpeculationFence: false
stamp: void
=== Inputs ===
stateAfter: - 
=== Succesors ===
next: v5 
=== Usages ===
=== Predecessor ===
- >@ <|@
instruction <@StartNode|@jdk.graal.compiler.nodes.StartNode>@ stateAfter: - #next: v5  <|@  <|@
f <@~|@floating>@ <|@
tid a1 <|@
result v0|QWORD[.] <|@
d <@d|@=== Debug Properties ===
index: 0
stamp: a!# Towers$TowersDisk
uncheckedStamp: [null]
=== Inputs ===
=== Succesors ===
=== Usages ===
v17 v11 ?16 
=== Predecessor ===
- >@ <|@
instruction <@Parameter|@jdk.graal.compiler.nodes.ParameterNode>@  <|@  <|@
tid v11 <|@
d <@d|@=== Debug Properties ===
callType: JavaCall
invokeKind: Special
nodeSourcePosition: at Towers$TowersDisk.<init>(int) [bci: 1]
referencedType: [null]
returnStamp: void
signature: [HotSpotType<Ljava/lang/Object;, resolved>]
stamp: void
targetMethod: HotSpotMethod<Object.<init>()>
=== Inputs ===
arguments: a1 
=== Succesors ===
=== Usages ===
v5 
=== Predecessor ===
- >@ <|@
instruction <@HotSpotDirectCallTarget|@jdk.graal.compiler.hotspot.nodes.HotSpotDirectCallTargetNode>@ arguments: a1  <|@  <|@
f <@~|@floating>@ <|@
tid i2 <|@
result v1|DWORD <|@
d <@d|@=== Debug Properties ===
index: 1
stamp: i32
uncheckedStamp: [null]
=== Inputs ===
=== Succesors ===
=== Usages ===
v14 ?16 
=== Predecessor ===
- >@ <|@
instruction <@Parameter|@jdk.graal.compiler.nodes.ParameterNode>@  <|@  <|@
tid ?16 <|@
d <@d|@=== Debug Properties ===
bci: 1
bytecode: invokespecial
code: ResolvedJavaMethodBytecode<Towers$TowersDisk.<init>(int)>
localsSize: 2
locksSize: 0
stackSize: 0
stackState: AfterPop
validForDeoptimization: true
=== Inputs ===
outerFrameState: - 
values: a1 i2 
=== Succesors ===
=== Usages ===
v5 
=== Predecessor ===
- >@ <|@
instruction <@FrameState|@jdk.graal.compiler.nodes.FrameState>@ outerFrameState: - values: a1 i2  <|@  <|@
f <@#|@fixed with next>@ <|@
tid v5 <|@
d <@d|@=== Debug Properties ===
bci: 1
identity: ANY_LOCATION
inlineControl: Normal
isInOOMETry: false
nodeSourcePosition: at Towers$TowersDisk.<init>(int) [bci: 1]
polymorphic: false
stamp: void
targetMethod: Direct#Object.<init>
=== Inputs ===
stateAfter: - 
classInit: - 
callTarget: v11 
stateDuring: ?16 
=== Succesors ===
next: v14 
=== Usages ===
=== Predecessor ===
v0 >@ <|@
instruction <@Invoke|@jdk.graal.compiler.nodes.InvokeNode>@ stateAfter: - classInit: - callTarget: v11 stateDuring: ?16 #next: v14  <|@  <|@
f <@~|@floating>@ <|@
tid v17 <|@
result [v0|QWORD[.] + 12] <|@
d <@d|@=== Debug Properties ===
displacement: 12
stamp: void*
stride: S1
=== Inputs ===
base: a1 
index: - 
=== Succesors ===
=== Usages ===
v14 
=== Predecessor ===
- >@ <|@
instruction <@AMD64Address|@jdk.graal.compiler.core.amd64.AMD64AddressNode>@ base: a1 index: -  <|@  <|@
f <@#|@fixed with next>@ <|@
tid v14 <|@
d <@d|@=== Debug Properties ===
barrierType: NONE
deoptReasonAndAction: [null]
deoptSpeculation: [null]
killedLocationIdentity: Towers$TowersDisk.size
location: Towers$TowersDisk.size
memoryOrder: PLAIN
nodeSourcePosition: at Towers$TowersDisk.<init>(int) [bci: 6]
stamp: void
usedAsNullCheck: false
=== Inputs ===
stateBefore: - 
guard: - 
address: v17 
lastLocationAccess: - 
value: i2 
stateAfter: - 
=== Succesors ===
next: v15 
=== Usages ===
=== Predecessor ===
v5 >@ <|@
instruction <@Write|@jdk.graal.compiler.nodes.memory.WriteNode>@ stateBefore: - guard: - address: v17 lastLocationAccess: - value: i2 stateAfter: - #next: v15  <|@  <|@
f <@#|@fixed with next>@ <|@
tid v15 <|@
d <@d|@=== Debug Properties ===
barriersString: STORE_STORE
fence: CONSTRUCTOR_FREEZE
location: ANY_LOCATION
nodeSourcePosition: at Towers$TowersDisk.<init>(int) [bci: 9]
stamp: void
=== Inputs ===
=== Succesors ===
next: v10 
=== Usages ===
=== Predecessor ===
v14 >@ <|@
instruction <@Membar|@jdk.graal.compiler.nodes.extended.MembarNode>@ #next: v10  <|@  <|@
f <@*|@fixed>@ <|@
tid v10 <|@
d <@d|@=== Debug Properties ===
nodeSourcePosition: at Towers$TowersDisk.<init>(int) [bci: 9]
stamp: void
=== Inputs ===
memoryMap: - 
result: - 
=== Succesors ===
=== Usages ===
=== Predecessor ===
v15 >@ <|@
instruction <@Return|@jdk.graal.compiler.nodes.ReturnNode>@ memoryMap: - result: -  <|@  <|@
    end_IR
    begin_IR
      LIR
      nr   -1  <|@ instruction [rsi|QWORD[.], rdx|DWORD, rbp|QWORD] = LABEL alignment: 0 numbPhis: 0 label: ? <|@ <|@
      nr   -1  <|@ instruction stack:16|QWORD = MOVE input: rbp|QWORD moveKind: QWORD <|@ <|@
      nr   -1  <|@ instruction [] = HOTSPOTLOCKSTACK frameMapBuilder: jdk.graal.compiler.hotspot.amd64.AMD64HotSpotFrameMapBuilder@3579649f slotKind: QWORD <|@ <|@
      nr   -1  <|@ instruction v0|QWORD[.] = MOVE input: rsi|QWORD[.] moveKind: QWORD <|@ <|@
      nr   -1  <|@ instruction v1|DWORD = MOVE input: rdx|DWORD moveKind: DWORD <|@ <|@
      nr   -1  <|@ instruction rsi|QWORD[.] = MOVE input: v0|QWORD[.] moveKind: QWORD <|@ <|@
      nr   -1  <|@ st <@st|@Towers$TowersDisk.<init>(int) [bci: 1]
locals: v0|QWORD[.] v1|DWORD 
>@ <|@ instruction - = CALL_DIRECT parameters: [rsi|QWORD[.]] temps: [] callTarget: HotSpotMethod<Object.<init>()> invokeKind: Special config: jdk.graal.compiler.hotspot.GraalHotSpotVMConfig@5be2b2dd state [bci:1] <|@ <|@
      nr   -1  <|@ instruction MOV (x: [v0|QWORD[.] + 12], y: v1|DWORD) size: DWORD <|@ <|@
      nr   -1  <|@ instruction RETURN (savedRbp: stack:16|QWORD, value: -) isStub: false requiresReservedStackAccessCheck: false thread: r15 scratchForSafepointOnReturn: rcx config: jdk.graal.compiler.hotspot.GraalHotSpotVMConfig@5be2b2dd <|@ <|@
    end_IR
  end_block
end_cfg
begin_cfg
  name "After ConstantLoadOptimization"
  begin_block
    name "B0"
    from_bci -1
    to_bci -1
    predecessors 
    successors 
    xhandlers
    flags 
    probability 4607182418800017408
    begin_IR
      LIR
      nr   -1  <|@ instruction [rsi|QWORD[.], rdx|DWORD, rbp|QWORD] = LABEL alignment: 0 numbPhis: 0 label: ? <|@ <|@
      nr   -1  <|@ instruction stack:16|QWORD = MOVE input: rbp|QWORD moveKind: QWORD <|@ <|@
      nr   -1  <|@ instruction [] = HOTSPOTLOCKSTACK frameMapBuilder: jdk.graal.compiler.hotspot.amd64.AMD64HotSpotFrameMapBuilder@3579649f slotKind: QWORD <|@ <|@
      nr   -1  <|@ instruction v0|QWORD[.] = MOVE input: rsi|QWORD[.] moveKind: QWORD <|@ <|@
      nr   -1  <|@ instruction v1|DWORD = MOVE input: rdx|DWORD moveKind: DWORD <|@ <|@
      nr   -1  <|@ instruction rsi|QWORD[.] = MOVE input: v0|QWORD[.] moveKind: QWORD <|@ <|@
      nr   -1  <|@ st <@st|@Towers$TowersDisk.<init>(int) [bci: 1]
locals: v0|QWORD[.] v1|DWORD 
>@ <|@ instruction - = CALL_DIRECT parameters: [rsi|QWORD[.]] temps: [] callTarget: HotSpotMethod<Object.<init>()> invokeKind: Special config: jdk.graal.compiler.hotspot.GraalHotSpotVMConfig@5be2b2dd state [bci:1] <|@ <|@
      nr   -1  <|@ instruction MOV (x: [v0|QWORD[.] + 12], y: v1|DWORD) size: DWORD <|@ <|@
      nr   -1  <|@ instruction RETURN (savedRbp: stack:16|QWORD, value: -) isStub: false requiresReservedStackAccessCheck: false thread: r15 scratchForSafepointOnReturn: rcx config: jdk.graal.compiler.hotspot.GraalHotSpotVMConfig@5be2b2dd <|@ <|@
    end_IR
  end_block
end_cfg
begin_bytecodes
     0: aload_0       
     1: invokespecial #0          // java.lang.Object.<init>:()void
     4: aload_0       
     5: iload_1       
     6: putfield      #1          // size:int
     9: return        
   <|@
end_bytecodes
begin_cfg
  name "After SaveCalleeSaveRegisters"
  begin_block
    name "B0"
    from_bci -1
    to_bci -1
    predecessors 
    successors 
    xhandlers
    flags 
    probability 4607182418800017408
    begin_IR
      LIR
      nr   -1  <|@ instruction [rsi|QWORD[.], rdx|DWORD, rbp|QWORD] = LABEL alignment: 0 numbPhis: 0 label: ? <|@ <|@
      nr   -1  <|@ instruction stack:16|QWORD = MOVE input: rbp|QWORD moveKind: QWORD <|@ <|@
      nr   -1  <|@ instruction [] = HOTSPOTLOCKSTACK frameMapBuilder: jdk.graal.compiler.hotspot.amd64.AMD64HotSpotFrameMapBuilder@3579649f slotKind: QWORD <|@ <|@
      nr   -1  <|@ instruction v0|QWORD[.] = MOVE input: rsi|QWORD[.] moveKind: QWORD <|@ <|@
      nr   -1  <|@ instruction v1|DWORD = MOVE input: rdx|DWORD moveKind: DWORD <|@ <|@
      nr   -1  <|@ instruction rsi|QWORD[.] = MOVE input: v0|QWORD[.] moveKind: QWORD <|@ <|@
      nr   -1  <|@ st <@st|@Towers$TowersDisk.<init>(int) [bci: 1]
locals: v0|QWORD[.] v1|DWORD 
>@ <|@ instruction - = CALL_DIRECT parameters: [rsi|QWORD[.]] temps: [] callTarget: HotSpotMethod<Object.<init>()> invokeKind: Special config: jdk.graal.compiler.hotspot.GraalHotSpotVMConfig@5be2b2dd state [bci:1] <|@ <|@
      nr   -1  <|@ instruction MOV (x: [v0|QWORD[.] + 12], y: v1|DWORD) size: DWORD <|@ <|@
      nr   -1  <|@ instruction RETURN (savedRbp: stack:16|QWORD, value: -) isStub: false requiresReservedStackAccessCheck: false thread: r15 scratchForSafepointOnReturn: rcx config: jdk.graal.compiler.hotspot.GraalHotSpotVMConfig@5be2b2dd <|@ <|@
    end_IR
  end_block
end_cfg
begin_bytecodes
     0: aload_0       
     1: invokespecial #0          // java.lang.Object.<init>:()void
     4: aload_0       
     5: iload_1       
     6: putfield      #1          // size:int
     9: return        
   <|@
end_bytecodes
begin_cfg
  name "After PreAllocationOptimizationStage"
  begin_block
    name "B0"
    from_bci -1
    to_bci -1
    predecessors 
    successors 
    xhandlers
    flags 
    probability 4607182418800017408
    begin_IR
      LIR
      nr   -1  <|@ instruction [rsi|QWORD[.], rdx|DWORD, rbp|QWORD] = LABEL alignment: 0 numbPhis: 0 label: ? <|@ <|@
      nr   -1  <|@ instruction stack:16|QWORD = MOVE input: rbp|QWORD moveKind: QWORD <|@ <|@
      nr   -1  <|@ instruction [] = HOTSPOTLOCKSTACK frameMapBuilder: jdk.graal.compiler.hotspot.amd64.AMD64HotSpotFrameMapBuilder@3579649f slotKind: QWORD <|@ <|@
      nr   -1  <|@ instruction v0|QWORD[.] = MOVE input: rsi|QWORD[.] moveKind: QWORD <|@ <|@
      nr   -1  <|@ instruction v1|DWORD = MOVE input: rdx|DWORD moveKind: DWORD <|@ <|@
      nr   -1  <|@ instruction rsi|QWORD[.] = MOVE input: v0|QWORD[.] moveKind: QWORD <|@ <|@
      nr   -1  <|@ st <@st|@Towers$TowersDisk.<init>(int) [bci: 1]
locals: v0|QWORD[.] v1|DWORD 
>@ <|@ instruction - = CALL_DIRECT parameters: [rsi|QWORD[.]] temps: [] callTarget: HotSpotMethod<Object.<init>()> invokeKind: Special config: jdk.graal.compiler.hotspot.GraalHotSpotVMConfig@5be2b2dd state [bci:1] <|@ <|@
      nr   -1  <|@ instruction MOV (x: [v0|QWORD[.] + 12], y: v1|DWORD) size: DWORD <|@ <|@
      nr   -1  <|@ instruction RETURN (savedRbp: stack:16|QWORD, value: -) isStub: false requiresReservedStackAccessCheck: false thread: r15 scratchForSafepointOnReturn: rcx config: jdk.graal.compiler.hotspot.GraalHotSpotVMConfig@5be2b2dd <|@ <|@
    end_IR
  end_block
end_cfg
begin_bytecodes
     0: aload_0       
     1: invokespecial #0          // java.lang.Object.<init>:()void
     4: aload_0       
     5: iload_1       
     6: putfield      #1          // size:int
     9: return        
   <|@
end_bytecodes
begin_cfg
  name "After MarkBasePointers"
  begin_block
    name "B0"
    from_bci -1
    to_bci -1
    predecessors 
    successors 
    xhandlers
    flags 
    probability 4607182418800017408
    begin_IR
      LIR
      nr   -1  <|@ instruction [rsi|QWORD[.], rdx|DWORD, rbp|QWORD] = LABEL alignment: 0 numbPhis: 0 label: ? <|@ <|@
      nr   -1  <|@ instruction stack:16|QWORD = MOVE input: rbp|QWORD moveKind: QWORD <|@ <|@
      nr   -1  <|@ instruction [] = HOTSPOTLOCKSTACK frameMapBuilder: jdk.graal.compiler.hotspot.amd64.AMD64HotSpotFrameMapBuilder@3579649f slotKind: QWORD <|@ <|@
      nr   -1  <|@ instruction v0|QWORD[.] = MOVE input: rsi|QWORD[.] moveKind: QWORD <|@ <|@
      nr   -1  <|@ instruction v1|DWORD = MOVE input: rdx|DWORD moveKind: DWORD <|@ <|@
      nr   -1  <|@ instruction rsi|QWORD[.] = MOVE input: v0|QWORD[.] moveKind: QWORD <|@ <|@
      nr   -1  <|@ st <@st|@live-base-pointers: []
Towers$TowersDisk.<init>(int) [bci: 1]
locals: v0|QWORD[.] v1|DWORD 
>@ <|@ instruction - = CALL_DIRECT parameters: [rsi|QWORD[.]] temps: [] callTarget: HotSpotMethod<Object.<init>()> invokeKind: Special config: jdk.graal.compiler.hotspot.GraalHotSpotVMConfig@5be2b2dd state [bci:1] <|@ <|@
      nr   -1  <|@ instruction MOV (x: [v0|QWORD[.] + 12], y: v1|DWORD) size: DWORD <|@ <|@
      nr   -1  <|@ instruction RETURN (savedRbp: stack:16|QWORD, value: -) isStub: false requiresReservedStackAccessCheck: false thread: r15 scratchForSafepointOnReturn: rcx config: jdk.graal.compiler.hotspot.GraalHotSpotVMConfig@5be2b2dd <|@ <|@
    end_IR
  end_block
end_cfg
begin_bytecodes
     0: aload_0       
     1: invokespecial #0          // java.lang.Object.<init>:()void
     4: aload_0       
     5: iload_1       
     6: putfield      #1          // size:int
     9: return        
   <|@
end_bytecodes
begin_cfg
  name "Before register allocation"
  begin_block
    name "B0"
    from_bci -1
    to_bci -1
    predecessors 
    successors 
    xhandlers
    flags 
    probability 4607182418800017408
    begin_IR
      LIR
      nr    0  <|@ instruction [rsi|QWORD[.], rdx|DWORD, rbp|QWORD] = LABEL alignment: 0 numbPhis: 0 label: ? <|@ <|@
      nr    2  <|@ instruction stack:16|QWORD = MOVE input: rbp|QWORD moveKind: QWORD <|@ <|@
      nr    4  <|@ instruction [] = HOTSPOTLOCKSTACK frameMapBuilder: jdk.graal.compiler.hotspot.amd64.AMD64HotSpotFrameMapBuilder@3579649f slotKind: QWORD <|@ <|@
      nr    6  <|@ instruction v0|QWORD[.] = MOVE input: rsi|QWORD[.] moveKind: QWORD <|@ <|@
      nr    8  <|@ instruction v1|DWORD = MOVE input: rdx|DWORD moveKind: DWORD <|@ <|@
      nr   10  <|@ instruction rsi|QWORD[.] = MOVE input: v0|QWORD[.] moveKind: QWORD <|@ <|@
      nr   12  <|@ st <@st|@live-base-pointers: []
Towers$TowersDisk.<init>(int) [bci: 1]
locals: v0|QWORD[.] v1|DWORD 
>@ <|@ instruction - = CALL_DIRECT parameters: [rsi|QWORD[.]] temps: [] callTarget: HotSpotMethod<Object.<init>()> invokeKind: Special config: jdk.graal.compiler.hotspot.GraalHotSpotVMConfig@5be2b2dd state [bci:1] <|@ <|@
      nr   14  <|@ instruction MOV (x: [v0|QWORD[.] + 12], y: v1|DWORD) size: DWORD <|@ <|@
      nr   16  <|@ instruction RETURN (savedRbp: stack:16|QWORD, value: -) isStub: false requiresReservedStackAccessCheck: false thread: r15 scratchForSafepointOnReturn: rcx config: jdk.graal.compiler.hotspot.GraalHotSpotVMConfig@5be2b2dd <|@ <|@
    end_IR
  end_block
end_cfg
begin_bytecodes
     0: aload_0       
     1: invokespecial #0          // java.lang.Object.<init>:()void
     4: aload_0       
     5: iload_1       
     6: putfield      #1          // size:int
     9: return        
   <|@
end_bytecodes
begin_cfg
  name "After SSALinearScanLifetimeAnalysis"
  begin_block
    name "B0"
    from_bci -1
    to_bci -1
    predecessors 
    successors 
    xhandlers
    flags 
    probability 4607182418800017408
    begin_IR
      LIR
      nr    0  <|@ instruction [rsi|QWORD[.], rdx|DWORD, rbp|QWORD] = LABEL alignment: 0 numbPhis: 0 label: ? <|@ <|@
      nr    2  <|@ instruction stack:16|QWORD = MOVE input: rbp|QWORD moveKind: QWORD <|@ <|@
      nr    4  <|@ instruction [] = HOTSPOTLOCKSTACK frameMapBuilder: jdk.graal.compiler.hotspot.amd64.AMD64HotSpotFrameMapBuilder@3579649f slotKind: QWORD <|@ <|@
      nr    6  <|@ instruction v0|QWORD[.] = MOVE input: rsi|QWORD[.] moveKind: QWORD <|@ <|@
      nr    8  <|@ instruction v1|DWORD = MOVE input: rdx|DWORD moveKind: DWORD <|@ <|@
      nr   10  <|@ instruction rsi|QWORD[.] = MOVE input: v0|QWORD[.] moveKind: QWORD <|@ <|@
      nr   12  <|@ st <@st|@live-base-pointers: []
Towers$TowersDisk.<init>(int) [bci: 1]
locals: v0|QWORD[.] v1|DWORD 
>@ <|@ instruction - = CALL_DIRECT parameters: [rsi|QWORD[.]] temps: [] callTarget: HotSpotMethod<Object.<init>()> invokeKind: Special config: jdk.graal.compiler.hotspot.GraalHotSpotVMConfig@5be2b2dd state [bci:1] <|@ <|@
      nr   14  <|@ instruction MOV (x: [v0|QWORD[.] + 12], y: v1|DWORD) size: DWORD <|@ <|@
      nr   16  <|@ instruction RETURN (savedRbp: stack:16|QWORD, value: -) isStub: false requiresReservedStackAccessCheck: false thread: r15 scratchForSafepointOnReturn: rcx config: jdk.graal.compiler.hotspot.GraalHotSpotVMConfig@5be2b2dd <|@ <|@
    end_IR
  end_block
end_cfg
begin_bytecodes
     0: aload_0       
     1: invokespecial #0          // java.lang.Object.<init>:()void
     4: aload_0       
     5: iload_1       
     6: putfield      #1          // size:int
     9: return        
   <|@
end_bytecodes
begin_intervals
  name "Before register allocation"
  rax|- fixed "[rax|-]" rax|- -1 [0, 1[[12, 13[ "NoDefinitionFound"
  rcx|- fixed "[rcx|-]" rcx|- -1 [0, 1[[12, 13[ "NoDefinitionFound"
  rdx|- fixed "[rdx|-]" rdx|- -1 [0, 8[[12, 13[ "NoSpillStore"
  rbx|- fixed "[rbx|-]" rbx|- -1 [0, 1[[12, 13[ "NoDefinitionFound"
  rbp|- fixed "[rbp|-]" rbp|- -1 [0, 2[[12, 13[ "NoSpillStore"
  rsi|- fixed "[rsi|-]" rsi|- v0|q [0, 6[[10, 13[ "NoOptimization"
  rdi|- fixed "[rdi|-]" rdi|- -1 [0, 1[[12, 13[ "NoDefinitionFound"
  r8|- fixed "[r8|-]" r8|- -1 [0, 1[[12, 13[ "NoDefinitionFound"
  r9|- fixed "[r9|-]" r9|- -1 [0, 1[[12, 13[ "NoDefinitionFound"
  r10|- fixed "[r10|-]" r10|- -1 [0, 1[[12, 13[ "NoDefinitionFound"
  r11|- fixed "[r11|-]" r11|- -1 [0, 1[[12, 13[ "NoDefinitionFound"
  r13|- fixed "[r13|-]" r13|- -1 [0, 1[[12, 13[ "NoDefinitionFound"
  r14|- fixed "[r14|-]" r14|- -1 [0, 1[[12, 13[ "NoDefinitionFound"
  xmm0|- fixed "[xmm0|-]" xmm0|- -1 [0, 1[[12, 13[ "NoDefinitionFound"
  xmm1|- fixed "[xmm1|-]" xmm1|- -1 [0, 1[[12, 13[ "NoDefinitionFound"
  xmm2|- fixed "[xmm2|-]" xmm2|- -1 [0, 1[[12, 13[ "NoDefinitionFound"
  xmm3|- fixed "[xmm3|-]" xmm3|- -1 [0, 1[[12, 13[ "NoDefinitionFound"
  xmm4|- fixed "[xmm4|-]" xmm4|- -1 [0, 1[[12, 13[ "NoDefinitionFound"
  xmm5|- fixed "[xmm5|-]" xmm5|- -1 [0, 1[[12, 13[ "NoDefinitionFound"
  xmm6|- fixed "[xmm6|-]" xmm6|- -1 [0, 1[[12, 13[ "NoDefinitionFound"
  xmm7|- fixed "[xmm7|-]" xmm7|- -1 [0, 1[[12, 13[ "NoDefinitionFound"
  xmm8|- fixed "[xmm8|-]" xmm8|- -1 [0, 1[[12, 13[ "NoDefinitionFound"
  xmm9|- fixed "[xmm9|-]" xmm9|- -1 [0, 1[[12, 13[ "NoDefinitionFound"
  xmm10|- fixed "[xmm10|-]" xmm10|- -1 [0, 1[[12, 13[ "NoDefinitionFound"
  xmm11|- fixed "[xmm11|-]" xmm11|- -1 [0, 1[[12, 13[ "NoDefinitionFound"
  xmm12|- fixed "[xmm12|-]" xmm12|- -1 [0, 1[[12, 13[ "NoDefinitionFound"
  xmm13|- fixed "[xmm13|-]" xmm13|- -1 [0, 1[[12, 13[ "NoDefinitionFound"
  xmm14|- fixed "[xmm14|-]" xmm14|- -1 [0, 1[[12, 13[ "NoDefinitionFound"
  xmm15|- fixed "[xmm15|-]" xmm15|- -1 [0, 1[[12, 13[ "NoDefinitionFound"
  v0|q QWORD "[v0|q]" v0|q rsi|- [6, 14[6 MustHaveRegister 10 ShouldHaveRegister 14 MustHaveRegister  "NoSpillStore"
  v1|d DWORD "[v1|d]" v1|d rdx|- [8, 14[8 MustHaveRegister 14 MustHaveRegister  "NoSpillStore"
end_intervals
begin_intervals
  name "After register allocation"
  rax|- fixed "[rax|-]" rax|- -1 [0, 1[[12, 13[ "NoDefinitionFound"
  rcx|- fixed "[rcx|-]" rcx|- -1 [0, 1[[12, 13[ "NoDefinitionFound"
  rdx|- fixed "[rdx|-]" rdx|- -1 [0, 8[[12, 13[ "NoSpillStore"
  rbx|- fixed "[rbx|-]" rbx|- -1 [0, 1[[12, 13[ "NoDefinitionFound"
  rbp|- fixed "[rbp|-]" rbp|- -1 [0, 2[[12, 13[ "NoSpillStore"
  rsi|- fixed "[rsi|-]" rsi|- v0|q [0, 6[[10, 13[ "NoOptimization"
  rdi|- fixed "[rdi|-]" rdi|- -1 [0, 1[[12, 13[ "NoDefinitionFound"
  r8|- fixed "[r8|-]" r8|- -1 [0, 1[[12, 13[ "NoDefinitionFound"
  r9|- fixed "[r9|-]" r9|- -1 [0, 1[[12, 13[ "NoDefinitionFound"
  r10|- fixed "[r10|-]" r10|- -1 [0, 1[[12, 13[ "NoDefinitionFound"
  r11|- fixed "[r11|-]" r11|- -1 [0, 1[[12, 13[ "NoDefinitionFound"
  r13|- fixed "[r13|-]" r13|- -1 [0, 1[[12, 13[ "NoDefinitionFound"
  r14|- fixed "[r14|-]" r14|- -1 [0, 1[[12, 13[ "NoDefinitionFound"
  xmm0|- fixed "[xmm0|-]" xmm0|- -1 [0, 1[[12, 13[ "NoDefinitionFound"
  xmm1|- fixed "[xmm1|-]" xmm1|- -1 [0, 1[[12, 13[ "NoDefinitionFound"
  xmm2|- fixed "[xmm2|-]" xmm2|- -1 [0, 1[[12, 13[ "NoDefinitionFound"
  xmm3|- fixed "[xmm3|-]" xmm3|- -1 [0, 1[[12, 13[ "NoDefinitionFound"
  xmm4|- fixed "[xmm4|-]" xmm4|- -1 [0, 1[[12, 13[ "NoDefinitionFound"
  xmm5|- fixed "[xmm5|-]" xmm5|- -1 [0, 1[[12, 13[ "NoDefinitionFound"
  xmm6|- fixed "[xmm6|-]" xmm6|- -1 [0, 1[[12, 13[ "NoDefinitionFound"
  xmm7|- fixed "[xmm7|-]" xmm7|- -1 [0, 1[[12, 13[ "NoDefinitionFound"
  xmm8|- fixed "[xmm8|-]" xmm8|- -1 [0, 1[[12, 13[ "NoDefinitionFound"
  xmm9|- fixed "[xmm9|-]" xmm9|- -1 [0, 1[[12, 13[ "NoDefinitionFound"
  xmm10|- fixed "[xmm10|-]" xmm10|- -1 [0, 1[[12, 13[ "NoDefinitionFound"
  xmm11|- fixed "[xmm11|-]" xmm11|- -1 [0, 1[[12, 13[ "NoDefinitionFound"
  xmm12|- fixed "[xmm12|-]" xmm12|- -1 [0, 1[[12, 13[ "NoDefinitionFound"
  xmm13|- fixed "[xmm13|-]" xmm13|- -1 [0, 1[[12, 13[ "NoDefinitionFound"
  xmm14|- fixed "[xmm14|-]" xmm14|- -1 [0, 1[[12, 13[ "NoDefinitionFound"
  xmm15|- fixed "[xmm15|-]" xmm15|- -1 [0, 1[[12, 13[ "NoDefinitionFound"
  v0|q QWORD "[rsi|q]" v0|q rsi|- [6, 9[6 MustHaveRegister  "OneSpillStore"
  v1|d DWORD "[rdx|d]" v1|d rdx|- [8, 11[8 MustHaveRegister  "OneSpillStore"
  v2|q QWORD "[r10|q]" v0|q v0|q [9, 11[10 ShouldHaveRegister  "OneSpillStore"
  v3|d DWORD "[vstack:1|d]" v1|d v1|d [11, 13[ "OneSpillStore"
  v4|q QWORD "[vstack:0|q]" v0|q v0|q [11, 13[ "OneSpillStore"
  v5|q QWORD "[rsi|q]" v0|q v0|q [13, 14[14 MustHaveRegister  "OneSpillStore"
  v6|d DWORD "[rdx|d]" v1|d v1|d [13, 14[14 MustHaveRegister  "OneSpillStore"
end_intervals
begin_cfg
  name "After LinearScanRegisterAllocation"
  begin_block
    name "B0"
    from_bci -1
    to_bci -1
    predecessors 
    successors 
    xhandlers
    flags 
    probability 4607182418800017408
    begin_IR
      LIR
      nr    0  <|@ instruction [rsi|QWORD[.], rdx|DWORD, rbp|QWORD] = LABEL alignment: 0 numbPhis: 0 label: ? <|@ <|@
      nr    2  <|@ instruction stack:16|QWORD = MOVE input: rbp|QWORD moveKind: QWORD <|@ <|@
      nr    4  <|@ instruction [] = HOTSPOTLOCKSTACK frameMapBuilder: jdk.graal.compiler.hotspot.amd64.AMD64HotSpotFrameMapBuilder@3579649f slotKind: QWORD <|@ <|@
      nr    6  <|@ instruction v0|QWORD[.] = MOVE input: rsi|QWORD[.] moveKind: QWORD <|@ <|@
      nr    8  <|@ instruction v1|DWORD = MOVE input: rdx|DWORD moveKind: DWORD <|@ <|@
      nr   -1  <|@ instruction v2|QWORD[.] = MOVE input: v0|QWORD[.] moveKind: QWORD // MoveResolver resolve mapping <|@ <|@
      nr   10  <|@ instruction rsi|QWORD[.] = MOVE input: v0|QWORD[.] moveKind: QWORD <|@ <|@
      nr   -1  <|@ instruction v3|DWORD = MOVE input: v1|DWORD moveKind: DWORD // MoveResolver resolve mapping <|@ <|@
      nr   -1  <|@ instruction v4|QWORD[.] = MOVE input: v2|QWORD[.] moveKind: QWORD // MoveResolver resolve mapping <|@ <|@
      nr   12  <|@ st <@st|@live-base-pointers: []
Towers$TowersDisk.<init>(int) [bci: 1]
locals: v0|QWORD[.] v1|DWORD 
>@ <|@ instruction - = CALL_DIRECT parameters: [rsi|QWORD[.]] temps: [] callTarget: HotSpotMethod<Object.<init>()> invokeKind: Special config: jdk.graal.compiler.hotspot.GraalHotSpotVMConfig@5be2b2dd state [bci:1] <|@ <|@
      nr   -1  <|@ instruction v5|QWORD[.] = MOVE input: v4|QWORD[.] moveKind: QWORD // MoveResolver resolve mapping <|@ <|@
      nr   -1  <|@ instruction v6|DWORD = MOVE input: v3|DWORD moveKind: DWORD // MoveResolver resolve mapping <|@ <|@
      nr   14  <|@ instruction MOV (x: [v0|QWORD[.] + 12], y: v1|DWORD) size: DWORD <|@ <|@
      nr   16  <|@ instruction RETURN (savedRbp: stack:16|QWORD, value: -) isStub: false requiresReservedStackAccessCheck: false thread: r15 scratchForSafepointOnReturn: rcx config: jdk.graal.compiler.hotspot.GraalHotSpotVMConfig@5be2b2dd <|@ <|@
    end_IR
  end_block
end_cfg
begin_bytecodes
     0: aload_0       
     1: invokespecial #0          // java.lang.Object.<init>:()void
     4: aload_0       
     5: iload_1       
     6: putfield      #1          // size:int
     9: return        
   <|@
end_bytecodes
begin_intervals
  name "After optimize spill position"
  rax|- fixed "[rax|-]" rax|- -1 [0, 1[[12, 13[ "NoDefinitionFound"
  rcx|- fixed "[rcx|-]" rcx|- -1 [0, 1[[12, 13[ "NoDefinitionFound"
  rdx|- fixed "[rdx|-]" rdx|- -1 [0, 8[[12, 13[ "NoSpillStore"
  rbx|- fixed "[rbx|-]" rbx|- -1 [0, 1[[12, 13[ "NoDefinitionFound"
  rbp|- fixed "[rbp|-]" rbp|- -1 [0, 2[[12, 13[ "NoSpillStore"
  rsi|- fixed "[rsi|-]" rsi|- v0|q [0, 6[[10, 13[ "NoOptimization"
  rdi|- fixed "[rdi|-]" rdi|- -1 [0, 1[[12, 13[ "NoDefinitionFound"
  r8|- fixed "[r8|-]" r8|- -1 [0, 1[[12, 13[ "NoDefinitionFound"
  r9|- fixed "[r9|-]" r9|- -1 [0, 1[[12, 13[ "NoDefinitionFound"
  r10|- fixed "[r10|-]" r10|- -1 [0, 1[[12, 13[ "NoDefinitionFound"
  r11|- fixed "[r11|-]" r11|- -1 [0, 1[[12, 13[ "NoDefinitionFound"
  r13|- fixed "[r13|-]" r13|- -1 [0, 1[[12, 13[ "NoDefinitionFound"
  r14|- fixed "[r14|-]" r14|- -1 [0, 1[[12, 13[ "NoDefinitionFound"
  xmm0|- fixed "[xmm0|-]" xmm0|- -1 [0, 1[[12, 13[ "NoDefinitionFound"
  xmm1|- fixed "[xmm1|-]" xmm1|- -1 [0, 1[[12, 13[ "NoDefinitionFound"
  xmm2|- fixed "[xmm2|-]" xmm2|- -1 [0, 1[[12, 13[ "NoDefinitionFound"
  xmm3|- fixed "[xmm3|-]" xmm3|- -1 [0, 1[[12, 13[ "NoDefinitionFound"
  xmm4|- fixed "[xmm4|-]" xmm4|- -1 [0, 1[[12, 13[ "NoDefinitionFound"
  xmm5|- fixed "[xmm5|-]" xmm5|- -1 [0, 1[[12, 13[ "NoDefinitionFound"
  xmm6|- fixed "[xmm6|-]" xmm6|- -1 [0, 1[[12, 13[ "NoDefinitionFound"
  xmm7|- fixed "[xmm7|-]" xmm7|- -1 [0, 1[[12, 13[ "NoDefinitionFound"
  xmm8|- fixed "[xmm8|-]" xmm8|- -1 [0, 1[[12, 13[ "NoDefinitionFound"
  xmm9|- fixed "[xmm9|-]" xmm9|- -1 [0, 1[[12, 13[ "NoDefinitionFound"
  xmm10|- fixed "[xmm10|-]" xmm10|- -1 [0, 1[[12, 13[ "NoDefinitionFound"
  xmm11|- fixed "[xmm11|-]" xmm11|- -1 [0, 1[[12, 13[ "NoDefinitionFound"
  xmm12|- fixed "[xmm12|-]" xmm12|- -1 [0, 1[[12, 13[ "NoDefinitionFound"
  xmm13|- fixed "[xmm13|-]" xmm13|- -1 [0, 1[[12, 13[ "NoDefinitionFound"
  xmm14|- fixed "[xmm14|-]" xmm14|- -1 [0, 1[[12, 13[ "NoDefinitionFound"
  xmm15|- fixed "[xmm15|-]" xmm15|- -1 [0, 1[[12, 13[ "NoDefinitionFound"
  v0|q QWORD "[rsi|q]" v0|q rsi|- [6, 9[6 MustHaveRegister  "OneSpillStore"
  v1|d DWORD "[rdx|d]" v1|d rdx|- [8, 11[8 MustHaveRegister  "OneSpillStore"
  v2|q QWORD "[r10|q]" v0|q v0|q [9, 11[10 ShouldHaveRegister  "OneSpillStore"
  v3|d DWORD "[vstack:1|d]" v1|d v1|d [11, 13[ "OneSpillStore"
  v4|q QWORD "[vstack:0|q]" v0|q v0|q [11, 13[ "OneSpillStore"
  v5|q QWORD "[rsi|q]" v0|q v0|q [13, 14[14 MustHaveRegister  "OneSpillStore"
  v6|d DWORD "[rdx|d]" v1|d v1|d [13, 14[14 MustHaveRegister  "OneSpillStore"
end_intervals
begin_cfg
  name "After LinearScanOptimizeSpillPosition"
  begin_block
    name "B0"
    from_bci -1
    to_bci -1
    predecessors 
    successors 
    xhandlers
    flags 
    probability 4607182418800017408
    begin_IR
      LIR
      nr    0  <|@ instruction [rsi|QWORD[.], rdx|DWORD, rbp|QWORD] = LABEL alignment: 0 numbPhis: 0 label: ? <|@ <|@
      nr    2  <|@ instruction stack:16|QWORD = MOVE input: rbp|QWORD moveKind: QWORD <|@ <|@
      nr    4  <|@ instruction [] = HOTSPOTLOCKSTACK frameMapBuilder: jdk.graal.compiler.hotspot.amd64.AMD64HotSpotFrameMapBuilder@3579649f slotKind: QWORD <|@ <|@
      nr    6  <|@ instruction v0|QWORD[.] = MOVE input: rsi|QWORD[.] moveKind: QWORD <|@ <|@
      nr    8  <|@ instruction v1|DWORD = MOVE input: rdx|DWORD moveKind: DWORD <|@ <|@
      nr   -1  <|@ instruction v2|QWORD[.] = MOVE input: v0|QWORD[.] moveKind: QWORD // MoveResolver resolve mapping <|@ <|@
      nr   10  <|@ instruction rsi|QWORD[.] = MOVE input: v0|QWORD[.] moveKind: QWORD <|@ <|@
      nr   -1  <|@ instruction v3|DWORD = MOVE input: v1|DWORD moveKind: DWORD // MoveResolver resolve mapping <|@ <|@
      nr   -1  <|@ instruction v4|QWORD[.] = MOVE input: v2|QWORD[.] moveKind: QWORD // MoveResolver resolve mapping <|@ <|@
      nr   12  <|@ st <@st|@live-base-pointers: []
Towers$TowersDisk.<init>(int) [bci: 1]
locals: v0|QWORD[.] v1|DWORD 
>@ <|@ instruction - = CALL_DIRECT parameters: [rsi|QWORD[.]] temps: [] callTarget: HotSpotMethod<Object.<init>()> invokeKind: Special config: jdk.graal.compiler.hotspot.GraalHotSpotVMConfig@5be2b2dd state [bci:1] <|@ <|@
      nr   -1  <|@ instruction v5|QWORD[.] = MOVE input: v4|QWORD[.] moveKind: QWORD // MoveResolver resolve mapping <|@ <|@
      nr   -1  <|@ instruction v6|DWORD = MOVE input: v3|DWORD moveKind: DWORD // MoveResolver resolve mapping <|@ <|@
      nr   14  <|@ instruction MOV (x: [v0|QWORD[.] + 12], y: v1|DWORD) size: DWORD <|@ <|@
      nr   16  <|@ instruction RETURN (savedRbp: stack:16|QWORD, value: -) isStub: false requiresReservedStackAccessCheck: false thread: r15 scratchForSafepointOnReturn: rcx config: jdk.graal.compiler.hotspot.GraalHotSpotVMConfig@5be2b2dd <|@ <|@
    end_IR
  end_block
end_cfg
begin_bytecodes
     0: aload_0       
     1: invokespecial #0          // java.lang.Object.<init>:()void
     4: aload_0       
     5: iload_1       
     6: putfield      #1          // size:int
     9: return        
   <|@
end_bytecodes
begin_intervals
  name "After resolve data flow"
  rax|- fixed "[rax|-]" rax|- -1 [0, 1[[12, 13[ "NoDefinitionFound"
  rcx|- fixed "[rcx|-]" rcx|- -1 [0, 1[[12, 13[ "NoDefinitionFound"
  rdx|- fixed "[rdx|-]" rdx|- -1 [0, 8[[12, 13[ "NoSpillStore"
  rbx|- fixed "[rbx|-]" rbx|- -1 [0, 1[[12, 13[ "NoDefinitionFound"
  rbp|- fixed "[rbp|-]" rbp|- -1 [0, 2[[12, 13[ "NoSpillStore"
  rsi|- fixed "[rsi|-]" rsi|- v0|q [0, 6[[10, 13[ "NoOptimization"
  rdi|- fixed "[rdi|-]" rdi|- -1 [0, 1[[12, 13[ "NoDefinitionFound"
  r8|- fixed "[r8|-]" r8|- -1 [0, 1[[12, 13[ "NoDefinitionFound"
  r9|- fixed "[r9|-]" r9|- -1 [0, 1[[12, 13[ "NoDefinitionFound"
  r10|- fixed "[r10|-]" r10|- -1 [0, 1[[12, 13[ "NoDefinitionFound"
  r11|- fixed "[r11|-]" r11|- -1 [0, 1[[12, 13[ "NoDefinitionFound"
  r13|- fixed "[r13|-]" r13|- -1 [0, 1[[12, 13[ "NoDefinitionFound"
  r14|- fixed "[r14|-]" r14|- -1 [0, 1[[12, 13[ "NoDefinitionFound"
  xmm0|- fixed "[xmm0|-]" xmm0|- -1 [0, 1[[12, 13[ "NoDefinitionFound"
  xmm1|- fixed "[xmm1|-]" xmm1|- -1 [0, 1[[12, 13[ "NoDefinitionFound"
  xmm2|- fixed "[xmm2|-]" xmm2|- -1 [0, 1[[12, 13[ "NoDefinitionFound"
  xmm3|- fixed "[xmm3|-]" xmm3|- -1 [0, 1[[12, 13[ "NoDefinitionFound"
  xmm4|- fixed "[xmm4|-]" xmm4|- -1 [0, 1[[12, 13[ "NoDefinitionFound"
  xmm5|- fixed "[xmm5|-]" xmm5|- -1 [0, 1[[12, 13[ "NoDefinitionFound"
  xmm6|- fixed "[xmm6|-]" xmm6|- -1 [0, 1[[12, 13[ "NoDefinitionFound"
  xmm7|- fixed "[xmm7|-]" xmm7|- -1 [0, 1[[12, 13[ "NoDefinitionFound"
  xmm8|- fixed "[xmm8|-]" xmm8|- -1 [0, 1[[12, 13[ "NoDefinitionFound"
  xmm9|- fixed "[xmm9|-]" xmm9|- -1 [0, 1[[12, 13[ "NoDefinitionFound"
  xmm10|- fixed "[xmm10|-]" xmm10|- -1 [0, 1[[12, 13[ "NoDefinitionFound"
  xmm11|- fixed "[xmm11|-]" xmm11|- -1 [0, 1[[12, 13[ "NoDefinitionFound"
  xmm12|- fixed "[xmm12|-]" xmm12|- -1 [0, 1[[12, 13[ "NoDefinitionFound"
  xmm13|- fixed "[xmm13|-]" xmm13|- -1 [0, 1[[12, 13[ "NoDefinitionFound"
  xmm14|- fixed "[xmm14|-]" xmm14|- -1 [0, 1[[12, 13[ "NoDefinitionFound"
  xmm15|- fixed "[xmm15|-]" xmm15|- -1 [0, 1[[12, 13[ "NoDefinitionFound"
  v0|q QWORD "[rsi|q]" v0|q rsi|- [6, 9[6 MustHaveRegister  "OneSpillStore"
  v1|d DWORD "[rdx|d]" v1|d rdx|- [8, 11[8 MustHaveRegister  "OneSpillStore"
  v2|q QWORD "[r10|q]" v0|q v0|q [9, 11[10 ShouldHaveRegister  "OneSpillStore"
  v3|d DWORD "[vstack:1|d]" v1|d v1|d [11, 13[ "OneSpillStore"
  v4|q QWORD "[vstack:0|q]" v0|q v0|q [11, 13[ "OneSpillStore"
  v5|q QWORD "[rsi|q]" v0|q v0|q [13, 14[14 MustHaveRegister  "OneSpillStore"
  v6|d DWORD "[rdx|d]" v1|d v1|d [13, 14[14 MustHaveRegister  "OneSpillStore"
end_intervals
begin_cfg
  name "After SSALinearScanResolveDataFlow"
  begin_block
    name "B0"
    from_bci -1
    to_bci -1
    predecessors 
    successors 
    xhandlers
    flags 
    probability 4607182418800017408
    begin_IR
      LIR
      nr    0  <|@ instruction [rsi|QWORD[.], rdx|DWORD, rbp|QWORD] = LABEL alignment: 0 numbPhis: 0 label: ? <|@ <|@
      nr    2  <|@ instruction stack:16|QWORD = MOVE input: rbp|QWORD moveKind: QWORD <|@ <|@
      nr    4  <|@ instruction [] = HOTSPOTLOCKSTACK frameMapBuilder: jdk.graal.compiler.hotspot.amd64.AMD64HotSpotFrameMapBuilder@3579649f slotKind: QWORD <|@ <|@
      nr    6  <|@ instruction v0|QWORD[.] = MOVE input: rsi|QWORD[.] moveKind: QWORD <|@ <|@
      nr    8  <|@ instruction v1|DWORD = MOVE input: rdx|DWORD moveKind: DWORD <|@ <|@
      nr   -1  <|@ instruction v2|QWORD[.] = MOVE input: v0|QWORD[.] moveKind: QWORD // MoveResolver resolve mapping <|@ <|@
      nr   10  <|@ instruction rsi|QWORD[.] = MOVE input: v0|QWORD[.] moveKind: QWORD <|@ <|@
      nr   -1  <|@ instruction v3|DWORD = MOVE input: v1|DWORD moveKind: DWORD // MoveResolver resolve mapping <|@ <|@
      nr   -1  <|@ instruction v4|QWORD[.] = MOVE input: v2|QWORD[.] moveKind: QWORD // MoveResolver resolve mapping <|@ <|@
      nr   12  <|@ st <@st|@live-base-pointers: []
Towers$TowersDisk.<init>(int) [bci: 1]
locals: v0|QWORD[.] v1|DWORD 
>@ <|@ instruction - = CALL_DIRECT parameters: [rsi|QWORD[.]] temps: [] callTarget: HotSpotMethod<Object.<init>()> invokeKind: Special config: jdk.graal.compiler.hotspot.GraalHotSpotVMConfig@5be2b2dd state [bci:1] <|@ <|@
      nr   -1  <|@ instruction v5|QWORD[.] = MOVE input: v4|QWORD[.] moveKind: QWORD // MoveResolver resolve mapping <|@ <|@
      nr   -1  <|@ instruction v6|DWORD = MOVE input: v3|DWORD moveKind: DWORD // MoveResolver resolve mapping <|@ <|@
      nr   14  <|@ instruction MOV (x: [v0|QWORD[.] + 12], y: v1|DWORD) size: DWORD <|@ <|@
      nr   16  <|@ instruction RETURN (savedRbp: stack:16|QWORD, value: -) isStub: false requiresReservedStackAccessCheck: false thread: r15 scratchForSafepointOnReturn: rcx config: jdk.graal.compiler.hotspot.GraalHotSpotVMConfig@5be2b2dd <|@ <|@
    end_IR
  end_block
end_cfg
begin_bytecodes
     0: aload_0       
     1: invokespecial #0          // java.lang.Object.<init>:()void
     4: aload_0       
     5: iload_1       
     6: putfield      #1          // size:int
     9: return        
   <|@
end_bytecodes
begin_cfg
  name "After SSALinearScanEliminateSpillMove"
  begin_block
    name "B0"
    from_bci -1
    to_bci -1
    predecessors 
    successors 
    xhandlers
    flags 
    probability 4607182418800017408
    begin_IR
      LIR
      nr    0  <|@ instruction [rsi|QWORD[.], rdx|DWORD, rbp|QWORD] = LABEL alignment: 0 numbPhis: 0 label: ? <|@ <|@
      nr    2  <|@ instruction stack:16|QWORD = MOVE input: rbp|QWORD moveKind: QWORD <|@ <|@
      nr    4  <|@ instruction [] = HOTSPOTLOCKSTACK frameMapBuilder: jdk.graal.compiler.hotspot.amd64.AMD64HotSpotFrameMapBuilder@3579649f slotKind: QWORD <|@ <|@
      nr    6  <|@ instruction v0|QWORD[.] = MOVE input: rsi|QWORD[.] moveKind: QWORD <|@ <|@
      nr    8  <|@ instruction v1|DWORD = MOVE input: rdx|DWORD moveKind: DWORD <|@ <|@
      nr   -1  <|@ instruction v2|QWORD[.] = MOVE input: v0|QWORD[.] moveKind: QWORD // MoveResolver resolve mapping <|@ <|@
      nr   10  <|@ instruction rsi|QWORD[.] = MOVE input: v0|QWORD[.] moveKind: QWORD <|@ <|@
      nr   -1  <|@ instruction v3|DWORD = MOVE input: v1|DWORD moveKind: DWORD // MoveResolver resolve mapping <|@ <|@
      nr   -1  <|@ instruction v4|QWORD[.] = MOVE input: v2|QWORD[.] moveKind: QWORD // MoveResolver resolve mapping <|@ <|@
      nr   12  <|@ st <@st|@live-base-pointers: []
Towers$TowersDisk.<init>(int) [bci: 1]
locals: v0|QWORD[.] v1|DWORD 
>@ <|@ instruction - = CALL_DIRECT parameters: [rsi|QWORD[.]] temps: [] callTarget: HotSpotMethod<Object.<init>()> invokeKind: Special config: jdk.graal.compiler.hotspot.GraalHotSpotVMConfig@5be2b2dd state [bci:1] <|@ <|@
      nr   -1  <|@ instruction v5|QWORD[.] = MOVE input: v4|QWORD[.] moveKind: QWORD // MoveResolver resolve mapping <|@ <|@
      nr   -1  <|@ instruction v6|DWORD = MOVE input: v3|DWORD moveKind: DWORD // MoveResolver resolve mapping <|@ <|@
      nr   14  <|@ instruction MOV (x: [v0|QWORD[.] + 12], y: v1|DWORD) size: DWORD <|@ <|@
      nr   16  <|@ instruction RETURN (savedRbp: stack:16|QWORD, value: -) isStub: false requiresReservedStackAccessCheck: false thread: r15 scratchForSafepointOnReturn: rcx config: jdk.graal.compiler.hotspot.GraalHotSpotVMConfig@5be2b2dd <|@ <|@
    end_IR
  end_block
end_cfg
begin_bytecodes
     0: aload_0       
     1: invokespecial #0          // java.lang.Object.<init>:()void
     4: aload_0       
     5: iload_1       
     6: putfield      #1          // size:int
     9: return        
   <|@
end_bytecodes
begin_cfg
  name "After LinearScanAssignLocations"
  begin_block
    name "B0"
    from_bci -1
    to_bci -1
    predecessors 
    successors 
    xhandlers
    flags 
    probability 4607182418800017408
    begin_IR
      LIR
      nr    0  <|@ instruction [rsi|QWORD[.], rdx|DWORD, rbp|QWORD] = LABEL alignment: 0 numbPhis: 0 label: ? <|@ <|@
      nr    2  <|@ instruction stack:16|QWORD = MOVE input: rbp|QWORD moveKind: QWORD <|@ <|@
      nr    4  <|@ instruction [] = HOTSPOTLOCKSTACK frameMapBuilder: jdk.graal.compiler.hotspot.amd64.AMD64HotSpotFrameMapBuilder@3579649f slotKind: QWORD <|@ <|@
      nr   -1  <|@ instruction r10|QWORD[.] = MOVE input: rsi|QWORD[.] moveKind: QWORD // MoveResolver resolve mapping <|@ <|@
      nr   10  <|@ instruction rsi|QWORD[.] = MOVE input: r10|QWORD[.] moveKind: QWORD <|@ <|@
      nr   -1  <|@ instruction vstack:1|DWORD = MOVE input: rdx|DWORD moveKind: DWORD // MoveResolver resolve mapping <|@ <|@
      nr   -1  <|@ instruction vstack:0|QWORD[.] = MOVE input: r10|QWORD[.] moveKind: QWORD // MoveResolver resolve mapping <|@ <|@
      nr   12  <|@ st <@st|@live-base-pointers: []
Towers$TowersDisk.<init>(int) [bci: 1]
locals: vstack:0|QWORD[.] vstack:1|DWORD 
>@ <|@ instruction - = CALL_DIRECT parameters: [rsi|QWORD[.]] temps: [] callTarget: HotSpotMethod<Object.<init>()> invokeKind: Special config: jdk.graal.compiler.hotspot.GraalHotSpotVMConfig@5be2b2dd state [bci:1] <|@ <|@
      nr   -1  <|@ instruction rsi|QWORD[.] = MOVE input: vstack:0|QWORD[.] moveKind: QWORD // MoveResolver resolve mapping <|@ <|@
      nr   -1  <|@ instruction rdx|DWORD = MOVE input: vstack:1|DWORD moveKind: DWORD // MoveResolver resolve mapping <|@ <|@
      nr   14  <|@ instruction MOV (x: [rsi|QWORD[.] + 12], y: rdx|DWORD) size: DWORD <|@ <|@
      nr   16  <|@ instruction RETURN (savedRbp: stack:16|QWORD, value: -) isStub: false requiresReservedStackAccessCheck: false thread: r15 scratchForSafepointOnReturn: rcx config: jdk.graal.compiler.hotspot.GraalHotSpotVMConfig@5be2b2dd <|@ <|@
    end_IR
  end_block
end_cfg
begin_bytecodes
     0: aload_0       
     1: invokespecial #0          // java.lang.Object.<init>:()void
     4: aload_0       
     5: iload_1       
     6: putfield      #1          // size:int
     9: return        
   <|@
end_bytecodes
begin_cfg
  name "After LinearScan"
  begin_block
    name "B0"
    from_bci -1
    to_bci -1
    predecessors 
    successors 
    xhandlers
    flags 
    probability 4607182418800017408
    begin_IR
      LIR
      nr    0  <|@ instruction [rsi|QWORD[.], rdx|DWORD, rbp|QWORD] = LABEL alignment: 0 numbPhis: 0 label: ? <|@ <|@
      nr    2  <|@ instruction stack:16|QWORD = MOVE input: rbp|QWORD moveKind: QWORD <|@ <|@
      nr    4  <|@ instruction [] = HOTSPOTLOCKSTACK frameMapBuilder: jdk.graal.compiler.hotspot.amd64.AMD64HotSpotFrameMapBuilder@3579649f slotKind: QWORD <|@ <|@
      nr   -1  <|@ instruction r10|QWORD[.] = MOVE input: rsi|QWORD[.] moveKind: QWORD // MoveResolver resolve mapping <|@ <|@
      nr   10  <|@ instruction rsi|QWORD[.] = MOVE input: r10|QWORD[.] moveKind: QWORD <|@ <|@
      nr   -1  <|@ instruction vstack:1|DWORD = MOVE input: rdx|DWORD moveKind: DWORD // MoveResolver resolve mapping <|@ <|@
      nr   -1  <|@ instruction vstack:0|QWORD[.] = MOVE input: r10|QWORD[.] moveKind: QWORD // MoveResolver resolve mapping <|@ <|@
      nr   12  <|@ st <@st|@live-base-pointers: []
Towers$TowersDisk.<init>(int) [bci: 1]
locals: vstack:0|QWORD[.] vstack:1|DWORD 
>@ <|@ instruction - = CALL_DIRECT parameters: [rsi|QWORD[.]] temps: [] callTarget: HotSpotMethod<Object.<init>()> invokeKind: Special config: jdk.graal.compiler.hotspot.GraalHotSpotVMConfig@5be2b2dd state [bci:1] <|@ <|@
      nr   -1  <|@ instruction rsi|QWORD[.] = MOVE input: vstack:0|QWORD[.] moveKind: QWORD // MoveResolver resolve mapping <|@ <|@
      nr   -1  <|@ instruction rdx|DWORD = MOVE input: vstack:1|DWORD moveKind: DWORD // MoveResolver resolve mapping <|@ <|@
      nr   14  <|@ instruction MOV (x: [rsi|QWORD[.] + 12], y: rdx|DWORD) size: DWORD <|@ <|@
      nr   16  <|@ instruction RETURN (savedRbp: stack:16|QWORD, value: -) isStub: false requiresReservedStackAccessCheck: false thread: r15 scratchForSafepointOnReturn: rcx config: jdk.graal.compiler.hotspot.GraalHotSpotVMConfig@5be2b2dd <|@ <|@
    end_IR
  end_block
end_cfg
begin_bytecodes
     0: aload_0       
     1: invokespecial #0          // java.lang.Object.<init>:()void
     4: aload_0       
     5: iload_1       
     6: putfield      #1          // size:int
     9: return        
   <|@
end_bytecodes
begin_cfg
  name "After StackSlot numbering"
  begin_block
    name "B0"
    from_bci -1
    to_bci -1
    predecessors 
    successors 
    xhandlers
    flags 
    probability 4607182418800017408
    begin_IR
      LIR
      nr    0  <|@ instruction [rsi|QWORD[.], rdx|DWORD, rbp|QWORD] = LABEL alignment: 0 numbPhis: 0 label: ? <|@ <|@
      nr    2  <|@ instruction stack:16|QWORD = MOVE input: rbp|QWORD moveKind: QWORD <|@ <|@
      nr    4  <|@ instruction [] = HOTSPOTLOCKSTACK frameMapBuilder: jdk.graal.compiler.hotspot.amd64.AMD64HotSpotFrameMapBuilder@3579649f slotKind: QWORD <|@ <|@
      nr    6  <|@ instruction r10|QWORD[.] = MOVE input: rsi|QWORD[.] moveKind: QWORD // MoveResolver resolve mapping <|@ <|@
      nr    8  <|@ instruction rsi|QWORD[.] = MOVE input: r10|QWORD[.] moveKind: QWORD <|@ <|@
      nr   10  <|@ instruction vstack:1|DWORD = MOVE input: rdx|DWORD moveKind: DWORD // MoveResolver resolve mapping <|@ <|@
      nr   12  <|@ instruction vstack:0|QWORD[.] = MOVE input: r10|QWORD[.] moveKind: QWORD // MoveResolver resolve mapping <|@ <|@
      nr   14  <|@ st <@st|@live-base-pointers: []
Towers$TowersDisk.<init>(int) [bci: 1]
locals: vstack:0|QWORD[.] vstack:1|DWORD 
>@ <|@ instruction - = CALL_DIRECT parameters: [rsi|QWORD[.]] temps: [] callTarget: HotSpotMethod<Object.<init>()> invokeKind: Special config: jdk.graal.compiler.hotspot.GraalHotSpotVMConfig@5be2b2dd state [bci:1] <|@ <|@
      nr   16  <|@ instruction rsi|QWORD[.] = MOVE input: vstack:0|QWORD[.] moveKind: QWORD // MoveResolver resolve mapping <|@ <|@
      nr   18  <|@ instruction rdx|DWORD = MOVE input: vstack:1|DWORD moveKind: DWORD // MoveResolver resolve mapping <|@ <|@
      nr   20  <|@ instruction MOV (x: [rsi|QWORD[.] + 12], y: rdx|DWORD) size: DWORD <|@ <|@
      nr   22  <|@ instruction RETURN (savedRbp: stack:16|QWORD, value: -) isStub: false requiresReservedStackAccessCheck: false thread: r15 scratchForSafepointOnReturn: rcx config: jdk.graal.compiler.hotspot.GraalHotSpotVMConfig@5be2b2dd <|@ <|@
    end_IR
  end_block
end_cfg
begin_bytecodes
     0: aload_0       
     1: invokespecial #0          // java.lang.Object.<init>:()void
     4: aload_0       
     5: iload_1       
     6: putfield      #1          // size:int
     9: return        
   <|@
end_bytecodes
begin_intervals
  name "Before stack slot allocation"
  vstack:0|q QWORD "[vstack:0|q]" vstack:0|q -1 [12, 16[ "NOT_SUPPORTED"
  vstack:1|d DWORD "[vstack:1|d]" vstack:1|d -1 [10, 18[ "NOT_SUPPORTED"
end_intervals
begin_intervals
  name "After stack slot allocation"
  vstack:0|q QWORD "[stack:40|q]" vstack:0|q -1 [12, 16[ "NOT_SUPPORTED"
  vstack:1|d DWORD "[stack:28|d]" vstack:1|d -1 [10, 18[ "NOT_SUPPORTED"
end_intervals
begin_cfg
  name "After LSStackSlotAllocator"
  begin_block
    name "B0"
    from_bci -1
    to_bci -1
    predecessors 
    successors 
    xhandlers
    flags 
    probability 4607182418800017408
    begin_IR
      LIR
      nr    0  <|@ instruction [rsi|QWORD[.], rdx|DWORD, rbp|QWORD] = LABEL alignment: 0 numbPhis: 0 label: ? <|@ <|@
      nr    2  <|@ instruction stack:16|QWORD = MOVE input: rbp|QWORD moveKind: QWORD <|@ <|@
      nr    4  <|@ instruction [] = HOTSPOTLOCKSTACK frameMapBuilder: jdk.graal.compiler.hotspot.amd64.AMD64HotSpotFrameMapBuilder@3579649f slotKind: QWORD <|@ <|@
      nr    6  <|@ instruction r10|QWORD[.] = MOVE input: rsi|QWORD[.] moveKind: QWORD // MoveResolver resolve mapping <|@ <|@
      nr    8  <|@ instruction rsi|QWORD[.] = MOVE input: r10|QWORD[.] moveKind: QWORD <|@ <|@
      nr   10  <|@ instruction stack:28|DWORD = MOVE input: rdx|DWORD moveKind: DWORD // MoveResolver resolve mapping <|@ <|@
      nr   12  <|@ instruction stack:40|QWORD[.] = MOVE input: r10|QWORD[.] moveKind: QWORD // MoveResolver resolve mapping <|@ <|@
      nr   14  <|@ st <@st|@live-base-pointers: []
Towers$TowersDisk.<init>(int) [bci: 1]
locals: stack:40|QWORD[.] stack:28|DWORD 
>@ <|@ instruction - = CALL_DIRECT parameters: [rsi|QWORD[.]] temps: [] callTarget: HotSpotMethod<Object.<init>()> invokeKind: Special config: jdk.graal.compiler.hotspot.GraalHotSpotVMConfig@5be2b2dd state [bci:1] <|@ <|@
      nr   16  <|@ instruction rsi|QWORD[.] = MOVE input: stack:40|QWORD[.] moveKind: QWORD // MoveResolver resolve mapping <|@ <|@
      nr   18  <|@ instruction rdx|DWORD = MOVE input: stack:28|DWORD moveKind: DWORD // MoveResolver resolve mapping <|@ <|@
      nr   20  <|@ instruction MOV (x: [rsi|QWORD[.] + 12], y: rdx|DWORD) size: DWORD <|@ <|@
      nr   22  <|@ instruction RETURN (savedRbp: stack:16|QWORD, value: -) isStub: false requiresReservedStackAccessCheck: false thread: r15 scratchForSafepointOnReturn: rcx config: jdk.graal.compiler.hotspot.GraalHotSpotVMConfig@5be2b2dd <|@ <|@
    end_IR
  end_block
end_cfg
begin_bytecodes
     0: aload_0       
     1: invokespecial #0          // java.lang.Object.<init>:()void
     4: aload_0       
     5: iload_1       
     6: putfield      #1          // size:int
     9: return        
   <|@
end_bytecodes
begin_cfg
  name "After AllocationStage"
  begin_block
    name "B0"
    from_bci -1
    to_bci -1
    predecessors 
    successors 
    xhandlers
    flags 
    probability 4607182418800017408
    begin_IR
      LIR
      nr    0  <|@ instruction [rsi|QWORD[.], rdx|DWORD, rbp|QWORD] = LABEL alignment: 0 numbPhis: 0 label: ? <|@ <|@
      nr    2  <|@ instruction stack:16|QWORD = MOVE input: rbp|QWORD moveKind: QWORD <|@ <|@
      nr    4  <|@ instruction [] = HOTSPOTLOCKSTACK frameMapBuilder: jdk.graal.compiler.hotspot.amd64.AMD64HotSpotFrameMapBuilder@3579649f slotKind: QWORD <|@ <|@
      nr    6  <|@ instruction r10|QWORD[.] = MOVE input: rsi|QWORD[.] moveKind: QWORD // MoveResolver resolve mapping <|@ <|@
      nr    8  <|@ instruction rsi|QWORD[.] = MOVE input: r10|QWORD[.] moveKind: QWORD <|@ <|@
      nr   10  <|@ instruction stack:28|DWORD = MOVE input: rdx|DWORD moveKind: DWORD // MoveResolver resolve mapping <|@ <|@
      nr   12  <|@ instruction stack:40|QWORD[.] = MOVE input: r10|QWORD[.] moveKind: QWORD // MoveResolver resolve mapping <|@ <|@
      nr   14  <|@ st <@st|@live-base-pointers: []
Towers$TowersDisk.<init>(int) [bci: 1]
locals: stack:40|QWORD[.] stack:28|DWORD 
>@ <|@ instruction - = CALL_DIRECT parameters: [rsi|QWORD[.]] temps: [] callTarget: HotSpotMethod<Object.<init>()> invokeKind: Special config: jdk.graal.compiler.hotspot.GraalHotSpotVMConfig@5be2b2dd state [bci:1] <|@ <|@
      nr   16  <|@ instruction rsi|QWORD[.] = MOVE input: stack:40|QWORD[.] moveKind: QWORD // MoveResolver resolve mapping <|@ <|@
      nr   18  <|@ instruction rdx|DWORD = MOVE input: stack:28|DWORD moveKind: DWORD // MoveResolver resolve mapping <|@ <|@
      nr   20  <|@ instruction MOV (x: [rsi|QWORD[.] + 12], y: rdx|DWORD) size: DWORD <|@ <|@
      nr   22  <|@ instruction RETURN (savedRbp: stack:16|QWORD, value: -) isStub: false requiresReservedStackAccessCheck: false thread: r15 scratchForSafepointOnReturn: rcx config: jdk.graal.compiler.hotspot.GraalHotSpotVMConfig@5be2b2dd <|@ <|@
    end_IR
  end_block
end_cfg
begin_bytecodes
     0: aload_0       
     1: invokespecial #0          // java.lang.Object.<init>:()void
     4: aload_0       
     5: iload_1       
     6: putfield      #1          // size:int
     9: return        
   <|@
end_bytecodes
begin_cfg
  name "After EdgeMoveOptimizer"
  begin_block
    name "B0"
    from_bci -1
    to_bci -1
    predecessors 
    successors 
    xhandlers
    flags 
    probability 4607182418800017408
    begin_IR
      LIR
      nr    0  <|@ instruction [rsi|QWORD[.], rdx|DWORD, rbp|QWORD] = LABEL alignment: 0 numbPhis: 0 label: ? <|@ <|@
      nr    2  <|@ instruction stack:16|QWORD = MOVE input: rbp|QWORD moveKind: QWORD <|@ <|@
      nr    4  <|@ instruction [] = HOTSPOTLOCKSTACK frameMapBuilder: jdk.graal.compiler.hotspot.amd64.AMD64HotSpotFrameMapBuilder@3579649f slotKind: QWORD <|@ <|@
      nr    6  <|@ instruction r10|QWORD[.] = MOVE input: rsi|QWORD[.] moveKind: QWORD // MoveResolver resolve mapping <|@ <|@
      nr    8  <|@ instruction rsi|QWORD[.] = MOVE input: r10|QWORD[.] moveKind: QWORD <|@ <|@
      nr   10  <|@ instruction stack:28|DWORD = MOVE input: rdx|DWORD moveKind: DWORD // MoveResolver resolve mapping <|@ <|@
      nr   12  <|@ instruction stack:40|QWORD[.] = MOVE input: r10|QWORD[.] moveKind: QWORD // MoveResolver resolve mapping <|@ <|@
      nr   14  <|@ st <@st|@live-base-pointers: []
Towers$TowersDisk.<init>(int) [bci: 1]
locals: stack:40|QWORD[.] stack:28|DWORD 
>@ <|@ instruction - = CALL_DIRECT parameters: [rsi|QWORD[.]] temps: [] callTarget: HotSpotMethod<Object.<init>()> invokeKind: Special config: jdk.graal.compiler.hotspot.GraalHotSpotVMConfig@5be2b2dd state [bci:1] <|@ <|@
      nr   16  <|@ instruction rsi|QWORD[.] = MOVE input: stack:40|QWORD[.] moveKind: QWORD // MoveResolver resolve mapping <|@ <|@
      nr   18  <|@ instruction rdx|DWORD = MOVE input: stack:28|DWORD moveKind: DWORD // MoveResolver resolve mapping <|@ <|@
      nr   20  <|@ instruction MOV (x: [rsi|QWORD[.] + 12], y: rdx|DWORD) size: DWORD <|@ <|@
      nr   22  <|@ instruction RETURN (savedRbp: stack:16|QWORD, value: -) isStub: false requiresReservedStackAccessCheck: false thread: r15 scratchForSafepointOnReturn: rcx config: jdk.graal.compiler.hotspot.GraalHotSpotVMConfig@5be2b2dd <|@ <|@
    end_IR
  end_block
end_cfg
begin_bytecodes
     0: aload_0       
     1: invokespecial #0          // java.lang.Object.<init>:()void
     4: aload_0       
     5: iload_1       
     6: putfield      #1          // size:int
     9: return        
   <|@
end_bytecodes
begin_cfg
  name "After RedundantMoveElimination"
  begin_block
    name "B0"
    from_bci -1
    to_bci -1
    predecessors 
    successors 
    xhandlers
    flags 
    probability 4607182418800017408
    begin_IR
      LIR
      nr    0  <|@ instruction [rsi|QWORD[.], rdx|DWORD, rbp|QWORD] = LABEL alignment: 0 numbPhis: 0 label: ? <|@ <|@
      nr    2  <|@ instruction stack:16|QWORD = MOVE input: rbp|QWORD moveKind: QWORD <|@ <|@
      nr    4  <|@ instruction [] = HOTSPOTLOCKSTACK frameMapBuilder: jdk.graal.compiler.hotspot.amd64.AMD64HotSpotFrameMapBuilder@3579649f slotKind: QWORD <|@ <|@
      nr    6  <|@ instruction r10|QWORD[.] = MOVE input: rsi|QWORD[.] moveKind: QWORD // MoveResolver resolve mapping <|@ <|@
      nr   10  <|@ instruction stack:28|DWORD = MOVE input: rdx|DWORD moveKind: DWORD // MoveResolver resolve mapping <|@ <|@
      nr   12  <|@ instruction stack:40|QWORD[.] = MOVE input: r10|QWORD[.] moveKind: QWORD // MoveResolver resolve mapping <|@ <|@
      nr   14  <|@ st <@st|@live-base-pointers: []
Towers$TowersDisk.<init>(int) [bci: 1]
locals: stack:40|QWORD[.] stack:28|DWORD 
>@ <|@ instruction - = CALL_DIRECT parameters: [rsi|QWORD[.]] temps: [] callTarget: HotSpotMethod<Object.<init>()> invokeKind: Special config: jdk.graal.compiler.hotspot.GraalHotSpotVMConfig@5be2b2dd state [bci:1] <|@ <|@
      nr   16  <|@ instruction rsi|QWORD[.] = MOVE input: stack:40|QWORD[.] moveKind: QWORD // MoveResolver resolve mapping <|@ <|@
      nr   18  <|@ instruction rdx|DWORD = MOVE input: stack:28|DWORD moveKind: DWORD // MoveResolver resolve mapping <|@ <|@
      nr   20  <|@ instruction MOV (x: [rsi|QWORD[.] + 12], y: rdx|DWORD) size: DWORD <|@ <|@
      nr   22  <|@ instruction RETURN (savedRbp: stack:16|QWORD, value: -) isStub: false requiresReservedStackAccessCheck: false thread: r15 scratchForSafepointOnReturn: rcx config: jdk.graal.compiler.hotspot.GraalHotSpotVMConfig@5be2b2dd <|@ <|@
    end_IR
  end_block
end_cfg
begin_bytecodes
     0: aload_0       
     1: invokespecial #0          // java.lang.Object.<init>:()void
     4: aload_0       
     5: iload_1       
     6: putfield      #1          // size:int
     9: return        
   <|@
end_bytecodes
begin_cfg
  name "After NullCheckOptimizer"
  begin_block
    name "B0"
    from_bci -1
    to_bci -1
    predecessors 
    successors 
    xhandlers
    flags 
    probability 4607182418800017408
    begin_IR
      LIR
      nr    0  <|@ instruction [rsi|QWORD[.], rdx|DWORD, rbp|QWORD] = LABEL alignment: 0 numbPhis: 0 label: ? <|@ <|@
      nr    2  <|@ instruction stack:16|QWORD = MOVE input: rbp|QWORD moveKind: QWORD <|@ <|@
      nr    4  <|@ instruction [] = HOTSPOTLOCKSTACK frameMapBuilder: jdk.graal.compiler.hotspot.amd64.AMD64HotSpotFrameMapBuilder@3579649f slotKind: QWORD <|@ <|@
      nr    6  <|@ instruction r10|QWORD[.] = MOVE input: rsi|QWORD[.] moveKind: QWORD // MoveResolver resolve mapping <|@ <|@
      nr   10  <|@ instruction stack:28|DWORD = MOVE input: rdx|DWORD moveKind: DWORD // MoveResolver resolve mapping <|@ <|@
      nr   12  <|@ instruction stack:40|QWORD[.] = MOVE input: r10|QWORD[.] moveKind: QWORD // MoveResolver resolve mapping <|@ <|@
      nr   14  <|@ st <@st|@live-base-pointers: []
Towers$TowersDisk.<init>(int) [bci: 1]
locals: stack:40|QWORD[.] stack:28|DWORD 
>@ <|@ instruction - = CALL_DIRECT parameters: [rsi|QWORD[.]] temps: [] callTarget: HotSpotMethod<Object.<init>()> invokeKind: Special config: jdk.graal.compiler.hotspot.GraalHotSpotVMConfig@5be2b2dd state [bci:1] <|@ <|@
      nr   16  <|@ instruction rsi|QWORD[.] = MOVE input: stack:40|QWORD[.] moveKind: QWORD // MoveResolver resolve mapping <|@ <|@
      nr   18  <|@ instruction rdx|DWORD = MOVE input: stack:28|DWORD moveKind: DWORD // MoveResolver resolve mapping <|@ <|@
      nr   20  <|@ instruction MOV (x: [rsi|QWORD[.] + 12], y: rdx|DWORD) size: DWORD <|@ <|@
      nr   22  <|@ instruction RETURN (savedRbp: stack:16|QWORD, value: -) isStub: false requiresReservedStackAccessCheck: false thread: r15 scratchForSafepointOnReturn: rcx config: jdk.graal.compiler.hotspot.GraalHotSpotVMConfig@5be2b2dd <|@ <|@
    end_IR
  end_block
end_cfg
begin_bytecodes
     0: aload_0       
     1: invokespecial #0          // java.lang.Object.<init>:()void
     4: aload_0       
     5: iload_1       
     6: putfield      #1          // size:int
     9: return        
   <|@
end_bytecodes
begin_cfg
  name "After ControlFlowOptimizer"
  begin_block
    name "B0"
    from_bci -1
    to_bci -1
    predecessors 
    successors 
    xhandlers
    flags 
    probability 4607182418800017408
    begin_IR
      LIR
      nr    0  <|@ instruction [rsi|QWORD[.], rdx|DWORD, rbp|QWORD] = LABEL alignment: 0 numbPhis: 0 label: ? <|@ <|@
      nr    2  <|@ instruction stack:16|QWORD = MOVE input: rbp|QWORD moveKind: QWORD <|@ <|@
      nr    4  <|@ instruction [] = HOTSPOTLOCKSTACK frameMapBuilder: jdk.graal.compiler.hotspot.amd64.AMD64HotSpotFrameMapBuilder@3579649f slotKind: QWORD <|@ <|@
      nr    6  <|@ instruction r10|QWORD[.] = MOVE input: rsi|QWORD[.] moveKind: QWORD // MoveResolver resolve mapping <|@ <|@
      nr   10  <|@ instruction stack:28|DWORD = MOVE input: rdx|DWORD moveKind: DWORD // MoveResolver resolve mapping <|@ <|@
      nr   12  <|@ instruction stack:40|QWORD[.] = MOVE input: r10|QWORD[.] moveKind: QWORD // MoveResolver resolve mapping <|@ <|@
      nr   14  <|@ st <@st|@live-base-pointers: []
Towers$TowersDisk.<init>(int) [bci: 1]
locals: stack:40|QWORD[.] stack:28|DWORD 
>@ <|@ instruction - = CALL_DIRECT parameters: [rsi|QWORD[.]] temps: [] callTarget: HotSpotMethod<Object.<init>()> invokeKind: Special config: jdk.graal.compiler.hotspot.GraalHotSpotVMConfig@5be2b2dd state [bci:1] <|@ <|@
      nr   16  <|@ instruction rsi|QWORD[.] = MOVE input: stack:40|QWORD[.] moveKind: QWORD // MoveResolver resolve mapping <|@ <|@
      nr   18  <|@ instruction rdx|DWORD = MOVE input: stack:28|DWORD moveKind: DWORD // MoveResolver resolve mapping <|@ <|@
      nr   20  <|@ instruction MOV (x: [rsi|QWORD[.] + 12], y: rdx|DWORD) size: DWORD <|@ <|@
      nr   22  <|@ instruction RETURN (savedRbp: stack:16|QWORD, value: -) isStub: false requiresReservedStackAccessCheck: false thread: r15 scratchForSafepointOnReturn: rcx config: jdk.graal.compiler.hotspot.GraalHotSpotVMConfig@5be2b2dd <|@ <|@
    end_IR
  end_block
end_cfg
begin_bytecodes
     0: aload_0       
     1: invokespecial #0          // java.lang.Object.<init>:()void
     4: aload_0       
     5: iload_1       
     6: putfield      #1          // size:int
     9: return        
   <|@
end_bytecodes
begin_cfg
  name "After ComputeCodeEmissionOrder"
  begin_block
    name "B0"
    from_bci -1
    to_bci -1
    predecessors 
    successors 
    xhandlers
    flags 
    probability 4607182418800017408
    begin_IR
      LIR
      nr    0  <|@ instruction [rsi|QWORD[.], rdx|DWORD, rbp|QWORD] = LABEL alignment: 0 numbPhis: 0 label: ? <|@ <|@
      nr    2  <|@ instruction stack:16|QWORD = MOVE input: rbp|QWORD moveKind: QWORD <|@ <|@
      nr    4  <|@ instruction [] = HOTSPOTLOCKSTACK frameMapBuilder: jdk.graal.compiler.hotspot.amd64.AMD64HotSpotFrameMapBuilder@3579649f slotKind: QWORD <|@ <|@
      nr    6  <|@ instruction r10|QWORD[.] = MOVE input: rsi|QWORD[.] moveKind: QWORD // MoveResolver resolve mapping <|@ <|@
      nr   10  <|@ instruction stack:28|DWORD = MOVE input: rdx|DWORD moveKind: DWORD // MoveResolver resolve mapping <|@ <|@
      nr   12  <|@ instruction stack:40|QWORD[.] = MOVE input: r10|QWORD[.] moveKind: QWORD // MoveResolver resolve mapping <|@ <|@
      nr   14  <|@ st <@st|@live-base-pointers: []
Towers$TowersDisk.<init>(int) [bci: 1]
locals: stack:40|QWORD[.] stack:28|DWORD 
>@ <|@ instruction - = CALL_DIRECT parameters: [rsi|QWORD[.]] temps: [] callTarget: HotSpotMethod<Object.<init>()> invokeKind: Special config: jdk.graal.compiler.hotspot.GraalHotSpotVMConfig@5be2b2dd state [bci:1] <|@ <|@
      nr   16  <|@ instruction rsi|QWORD[.] = MOVE input: stack:40|QWORD[.] moveKind: QWORD // MoveResolver resolve mapping <|@ <|@
      nr   18  <|@ instruction rdx|DWORD = MOVE input: stack:28|DWORD moveKind: DWORD // MoveResolver resolve mapping <|@ <|@
      nr   20  <|@ instruction MOV (x: [rsi|QWORD[.] + 12], y: rdx|DWORD) size: DWORD <|@ <|@
      nr   22  <|@ instruction RETURN (savedRbp: stack:16|QWORD, value: -) isStub: false requiresReservedStackAccessCheck: false thread: r15 scratchForSafepointOnReturn: rcx config: jdk.graal.compiler.hotspot.GraalHotSpotVMConfig@5be2b2dd <|@ <|@
    end_IR
  end_block
end_cfg
begin_bytecodes
     0: aload_0       
     1: invokespecial #0          // java.lang.Object.<init>:()void
     4: aload_0       
     5: iload_1       
     6: putfield      #1          // size:int
     9: return        
   <|@
end_bytecodes
begin_cfg
  name "After LIRGTSlowdownMarker"
  begin_block
    name "B0"
    from_bci -1
    to_bci -1
    predecessors 
    successors 
    xhandlers
    flags 
    probability 4607182418800017408
    begin_IR
      LIR
      nr    0  <|@ instruction [rsi|QWORD[.], rdx|DWORD, rbp|QWORD] = LABEL alignment: 0 numbPhis: 0 label: ? <|@ <|@
      nr   -1  <|@ instruction GTMARKER markerId: 0 <|@ <|@
      nr    2  <|@ instruction stack:16|QWORD = MOVE input: rbp|QWORD moveKind: QWORD <|@ <|@
      nr    4  <|@ instruction [] = HOTSPOTLOCKSTACK frameMapBuilder: jdk.graal.compiler.hotspot.amd64.AMD64HotSpotFrameMapBuilder@3579649f slotKind: QWORD <|@ <|@
      nr    6  <|@ instruction r10|QWORD[.] = MOVE input: rsi|QWORD[.] moveKind: QWORD // MoveResolver resolve mapping <|@ <|@
      nr   10  <|@ instruction stack:28|DWORD = MOVE input: rdx|DWORD moveKind: DWORD // MoveResolver resolve mapping <|@ <|@
      nr   12  <|@ instruction stack:40|QWORD[.] = MOVE input: r10|QWORD[.] moveKind: QWORD // MoveResolver resolve mapping <|@ <|@
      nr   14  <|@ st <@st|@live-base-pointers: []
Towers$TowersDisk.<init>(int) [bci: 1]
locals: stack:40|QWORD[.] stack:28|DWORD 
>@ <|@ instruction - = CALL_DIRECT parameters: [rsi|QWORD[.]] temps: [] callTarget: HotSpotMethod<Object.<init>()> invokeKind: Special config: jdk.graal.compiler.hotspot.GraalHotSpotVMConfig@5be2b2dd state [bci:1] <|@ <|@
      nr   -1  <|@ instruction GTMARKER markerId: 0 <|@ <|@
      nr   16  <|@ instruction rsi|QWORD[.] = MOVE input: stack:40|QWORD[.] moveKind: QWORD // MoveResolver resolve mapping <|@ <|@
      nr   18  <|@ instruction rdx|DWORD = MOVE input: stack:28|DWORD moveKind: DWORD // MoveResolver resolve mapping <|@ <|@
      nr   20  <|@ instruction MOV (x: [rsi|QWORD[.] + 12], y: rdx|DWORD) size: DWORD <|@ <|@
      nr   22  <|@ instruction RETURN (savedRbp: stack:16|QWORD, value: -) isStub: false requiresReservedStackAccessCheck: false thread: r15 scratchForSafepointOnReturn: rcx config: jdk.graal.compiler.hotspot.GraalHotSpotVMConfig@5be2b2dd <|@ <|@
    end_IR
  end_block
end_cfg
begin_bytecodes
     0: aload_0       
     1: invokespecial #0          // java.lang.Object.<init>:()void
     4: aload_0       
     5: iload_1       
     6: putfield      #1          // size:int
     9: return        
   <|@
end_bytecodes
begin_cfg
  name "After StackMoveOptimization"
  begin_block
    name "B0"
    from_bci -1
    to_bci -1
    predecessors 
    successors 
    xhandlers
    flags 
    probability 4607182418800017408
    begin_IR
      LIR
      nr    0  <|@ instruction [rsi|QWORD[.], rdx|DWORD, rbp|QWORD] = LABEL alignment: 0 numbPhis: 0 label: ? <|@ <|@
      nr   -1  <|@ instruction GTMARKER markerId: 0 <|@ <|@
      nr    2  <|@ instruction stack:16|QWORD = MOVE input: rbp|QWORD moveKind: QWORD <|@ <|@
      nr    4  <|@ instruction [] = HOTSPOTLOCKSTACK frameMapBuilder: jdk.graal.compiler.hotspot.amd64.AMD64HotSpotFrameMapBuilder@3579649f slotKind: QWORD <|@ <|@
      nr    6  <|@ instruction r10|QWORD[.] = MOVE input: rsi|QWORD[.] moveKind: QWORD // MoveResolver resolve mapping <|@ <|@
      nr   10  <|@ instruction stack:28|DWORD = MOVE input: rdx|DWORD moveKind: DWORD // MoveResolver resolve mapping <|@ <|@
      nr   12  <|@ instruction stack:40|QWORD[.] = MOVE input: r10|QWORD[.] moveKind: QWORD // MoveResolver resolve mapping <|@ <|@
      nr   14  <|@ st <@st|@live-base-pointers: []
Towers$TowersDisk.<init>(int) [bci: 1]
locals: stack:40|QWORD[.] stack:28|DWORD 
>@ <|@ instruction - = CALL_DIRECT parameters: [rsi|QWORD[.]] temps: [] callTarget: HotSpotMethod<Object.<init>()> invokeKind: Special config: jdk.graal.compiler.hotspot.GraalHotSpotVMConfig@5be2b2dd state [bci:1] <|@ <|@
      nr   -1  <|@ instruction GTMARKER markerId: 0 <|@ <|@
      nr   16  <|@ instruction rsi|QWORD[.] = MOVE input: stack:40|QWORD[.] moveKind: QWORD // MoveResolver resolve mapping <|@ <|@
      nr   18  <|@ instruction rdx|DWORD = MOVE input: stack:28|DWORD moveKind: DWORD // MoveResolver resolve mapping <|@ <|@
      nr   20  <|@ instruction MOV (x: [rsi|QWORD[.] + 12], y: rdx|DWORD) size: DWORD <|@ <|@
      nr   22  <|@ instruction RETURN (savedRbp: stack:16|QWORD, value: -) isStub: false requiresReservedStackAccessCheck: false thread: r15 scratchForSafepointOnReturn: rcx config: jdk.graal.compiler.hotspot.GraalHotSpotVMConfig@5be2b2dd <|@ <|@
    end_IR
  end_block
end_cfg
begin_bytecodes
     0: aload_0       
     1: invokespecial #0          // java.lang.Object.<init>:()void
     4: aload_0       
     5: iload_1       
     6: putfield      #1          // size:int
     9: return        
   <|@
end_bytecodes
begin_cfg
  name "After PostAllocationOptimizationStage"
  begin_block
    name "B0"
    from_bci -1
    to_bci -1
    predecessors 
    successors 
    xhandlers
    flags 
    probability 4607182418800017408
    begin_IR
      LIR
      nr    0  <|@ instruction [rsi|QWORD[.], rdx|DWORD, rbp|QWORD] = LABEL alignment: 0 numbPhis: 0 label: ? <|@ <|@
      nr   -1  <|@ instruction GTMARKER markerId: 0 <|@ <|@
      nr    2  <|@ instruction stack:16|QWORD = MOVE input: rbp|QWORD moveKind: QWORD <|@ <|@
      nr    4  <|@ instruction [] = HOTSPOTLOCKSTACK frameMapBuilder: jdk.graal.compiler.hotspot.amd64.AMD64HotSpotFrameMapBuilder@3579649f slotKind: QWORD <|@ <|@
      nr    6  <|@ instruction r10|QWORD[.] = MOVE input: rsi|QWORD[.] moveKind: QWORD // MoveResolver resolve mapping <|@ <|@
      nr   10  <|@ instruction stack:28|DWORD = MOVE input: rdx|DWORD moveKind: DWORD // MoveResolver resolve mapping <|@ <|@
      nr   12  <|@ instruction stack:40|QWORD[.] = MOVE input: r10|QWORD[.] moveKind: QWORD // MoveResolver resolve mapping <|@ <|@
      nr   14  <|@ st <@st|@live-base-pointers: []
Towers$TowersDisk.<init>(int) [bci: 1]
locals: stack:40|QWORD[.] stack:28|DWORD 
>@ <|@ instruction - = CALL_DIRECT parameters: [rsi|QWORD[.]] temps: [] callTarget: HotSpotMethod<Object.<init>()> invokeKind: Special config: jdk.graal.compiler.hotspot.GraalHotSpotVMConfig@5be2b2dd state [bci:1] <|@ <|@
      nr   -1  <|@ instruction GTMARKER markerId: 0 <|@ <|@
      nr   16  <|@ instruction rsi|QWORD[.] = MOVE input: stack:40|QWORD[.] moveKind: QWORD // MoveResolver resolve mapping <|@ <|@
      nr   18  <|@ instruction rdx|DWORD = MOVE input: stack:28|DWORD moveKind: DWORD // MoveResolver resolve mapping <|@ <|@
      nr   20  <|@ instruction MOV (x: [rsi|QWORD[.] + 12], y: rdx|DWORD) size: DWORD <|@ <|@
      nr   22  <|@ instruction RETURN (savedRbp: stack:16|QWORD, value: -) isStub: false requiresReservedStackAccessCheck: false thread: r15 scratchForSafepointOnReturn: rcx config: jdk.graal.compiler.hotspot.GraalHotSpotVMConfig@5be2b2dd <|@ <|@
    end_IR
  end_block
end_cfg
begin_bytecodes
     0: aload_0       
     1: invokespecial #0          // java.lang.Object.<init>:()void
     4: aload_0       
     5: iload_1       
     6: putfield      #1          // size:int
     9: return        
   <|@
end_bytecodes
begin_cfg
  name "After LocationMarker"
  begin_block
    name "B0"
    from_bci -1
    to_bci -1
    predecessors 
    successors 
    xhandlers
    flags 
    probability 4607182418800017408
    begin_IR
      LIR
      nr    0  <|@ instruction [rsi|QWORD[.], rdx|DWORD, rbp|QWORD] = LABEL alignment: 0 numbPhis: 0 label: ? <|@ <|@
      nr   -1  <|@ instruction GTMARKER markerId: 0 <|@ <|@
      nr    2  <|@ instruction stack:16|QWORD = MOVE input: rbp|QWORD moveKind: QWORD <|@ <|@
      nr    4  <|@ instruction [] = HOTSPOTLOCKSTACK frameMapBuilder: jdk.graal.compiler.hotspot.amd64.AMD64HotSpotFrameMapBuilder@3579649f slotKind: QWORD <|@ <|@
      nr    6  <|@ instruction r10|QWORD[.] = MOVE input: rsi|QWORD[.] moveKind: QWORD // MoveResolver resolve mapping <|@ <|@
      nr   10  <|@ instruction stack:28|DWORD = MOVE input: rdx|DWORD moveKind: DWORD // MoveResolver resolve mapping <|@ <|@
      nr   12  <|@ instruction stack:40|QWORD[.] = MOVE input: r10|QWORD[.] moveKind: QWORD // MoveResolver resolve mapping <|@ <|@
      nr   14  <|@ st <@st|@reference-map: [stack:8]
live-base-pointers: []
Towers$TowersDisk.<init>(int) [bci: 1]
locals: stack:40|QWORD[.] stack:28|DWORD 
>@ <|@ instruction - = CALL_DIRECT parameters: [rsi|QWORD[.]] temps: [] callTarget: HotSpotMethod<Object.<init>()> invokeKind: Special config: jdk.graal.compiler.hotspot.GraalHotSpotVMConfig@5be2b2dd state [bci:1] <|@ <|@
      nr   -1  <|@ instruction GTMARKER markerId: 0 <|@ <|@
      nr   16  <|@ instruction rsi|QWORD[.] = MOVE input: stack:40|QWORD[.] moveKind: QWORD // MoveResolver resolve mapping <|@ <|@
      nr   18  <|@ instruction rdx|DWORD = MOVE input: stack:28|DWORD moveKind: DWORD // MoveResolver resolve mapping <|@ <|@
      nr   20  <|@ instruction MOV (x: [rsi|QWORD[.] + 12], y: rdx|DWORD) size: DWORD <|@ <|@
      nr   22  <|@ instruction RETURN (savedRbp: stack:16|QWORD, value: -) isStub: false requiresReservedStackAccessCheck: false thread: r15 scratchForSafepointOnReturn: rcx config: jdk.graal.compiler.hotspot.GraalHotSpotVMConfig@5be2b2dd <|@ <|@
    end_IR
  end_block
end_cfg
begin_bytecodes
     0: aload_0       
     1: invokespecial #0          // java.lang.Object.<init>:()void
     4: aload_0       
     5: iload_1       
     6: putfield      #1          // size:int
     9: return        
   <|@
end_bytecodes
begin_cfg
  name "After FinalCodeAnalysisStage"
  begin_block
    name "B0"
    from_bci -1
    to_bci -1
    predecessors 
    successors 
    xhandlers
    flags 
    probability 4607182418800017408
    begin_IR
      LIR
      nr    0  <|@ instruction [rsi|QWORD[.], rdx|DWORD, rbp|QWORD] = LABEL alignment: 0 numbPhis: 0 label: ? <|@ <|@
      nr   -1  <|@ instruction GTMARKER markerId: 0 <|@ <|@
      nr    2  <|@ instruction stack:16|QWORD = MOVE input: rbp|QWORD moveKind: QWORD <|@ <|@
      nr    4  <|@ instruction [] = HOTSPOTLOCKSTACK frameMapBuilder: jdk.graal.compiler.hotspot.amd64.AMD64HotSpotFrameMapBuilder@3579649f slotKind: QWORD <|@ <|@
      nr    6  <|@ instruction r10|QWORD[.] = MOVE input: rsi|QWORD[.] moveKind: QWORD // MoveResolver resolve mapping <|@ <|@
      nr   10  <|@ instruction stack:28|DWORD = MOVE input: rdx|DWORD moveKind: DWORD // MoveResolver resolve mapping <|@ <|@
      nr   12  <|@ instruction stack:40|QWORD[.] = MOVE input: r10|QWORD[.] moveKind: QWORD // MoveResolver resolve mapping <|@ <|@
      nr   14  <|@ st <@st|@reference-map: [stack:8]
live-base-pointers: []
Towers$TowersDisk.<init>(int) [bci: 1]
locals: stack:40|QWORD[.] stack:28|DWORD 
>@ <|@ instruction - = CALL_DIRECT parameters: [rsi|QWORD[.]] temps: [] callTarget: HotSpotMethod<Object.<init>()> invokeKind: Special config: jdk.graal.compiler.hotspot.GraalHotSpotVMConfig@5be2b2dd state [bci:1] <|@ <|@
      nr   -1  <|@ instruction GTMARKER markerId: 0 <|@ <|@
      nr   16  <|@ instruction rsi|QWORD[.] = MOVE input: stack:40|QWORD[.] moveKind: QWORD // MoveResolver resolve mapping <|@ <|@
      nr   18  <|@ instruction rdx|DWORD = MOVE input: stack:28|DWORD moveKind: DWORD // MoveResolver resolve mapping <|@ <|@
      nr   20  <|@ instruction MOV (x: [rsi|QWORD[.] + 12], y: rdx|DWORD) size: DWORD <|@ <|@
      nr   22  <|@ instruction RETURN (savedRbp: stack:16|QWORD, value: -) isStub: false requiresReservedStackAccessCheck: false thread: r15 scratchForSafepointOnReturn: rcx config: jdk.graal.compiler.hotspot.GraalHotSpotVMConfig@5be2b2dd <|@ <|@
    end_IR
  end_block
end_cfg
begin_bytecodes
     0: aload_0       
     1: invokespecial #0          // java.lang.Object.<init>:()void
     4: aload_0       
     5: iload_1       
     6: putfield      #1          // size:int
     9: return        
   <|@
end_bytecodes
begin_cfg
  name "After code generation"
end_cfg
begin_nmethod
  <<<HexCodeFile
  Platform AMD64 64  <||@
  HexCode 0 448b560849bc000000974e7f00004d03d44d33e4493bc20f85e3ffffff6666900faef8c5f8c6c0ffc5f8c6c0ffc5f8c6c0ff0faef889842400c0feff4883ec2841817f20000000000f8566000000c5f8c6c000c5f8c6c000c5f8c6c00048896c24204c8bd6895424144c8954240890e8000000000f1f8400000000000faef8c5f8c6c000c5f8c6c000c5f8c6c0000faef8488b7424088b54241489560c488b6c24204883c428493ba7500400000f870e000000c348896c2420e800000000eb8ef4488d0ddeffffff49898f68040000e92cfffffff4e800000000f4e800000000f4  <||@
  Comment 0 UNVERIFIED_ENTRY  <||@
  Comment 23 {Field[name=CompilerToVM::Data::SharedRuntime_ic_miss_stub, type=address, offset=0, address=0x7f4f0aa335c8, value=139977128468608]:0x7f4ef704e080}  <||@
  Comment 32 VERIFIED_ENTRY  <||@
  Comment 53 [stack overflow check]  <||@
  Comment 64 FRAME_COMPLETE  <||@
  Comment 64 ENTRY_BARRIER_PATCH  <||@
  Comment 78 block B0 null  <||@
  Comment 78 0 [rsi|QWORD[.], rdx|DWORD, rbp|QWORD] = LABEL alignment: 0 numbPhis: 0 label: ?  <||@
  Comment 78 -1 GTMARKER markerId: 0  <||@
  Comment 93 2 stack:16|QWORD = MOVE input: rbp|QWORD moveKind: QWORD  <||@
  Comment 98 4 [] = HOTSPOTLOCKSTACK frameMapBuilder: jdk.graal.compiler.hotspot.amd64.AMD64HotSpotFrameMapBuilder@3579649f slotKind: QWORD  <||@
  Comment 98 6 r10|QWORD[.] = MOVE input: rsi|QWORD[.] moveKind: QWORD  <||@
  Comment 101 10 stack:28|DWORD = MOVE input: rdx|DWORD moveKind: DWORD  <||@
  Comment 105 12 stack:40|QWORD[.] = MOVE input: r10|QWORD[.] moveKind: QWORD  <||@
  Comment 110 14 - = CALL_DIRECT parameters: [rsi|QWORD[.]] temps: [] callTarget: HotSpotMethod<Object.<init>()> invokeKind: Special config: jdk.graal.compiler.hotspot.GraalHotSpotVMConfig@5be2b2dd state [bci:1]  <||@
  Comment 111 {HotSpotMethod<Object.<init>()>}  <||@
  Comment 111 INVOKESPECIAL  <||@
  Comment 116 [stack:8]at Towers$TowersDisk.<init>(int) [bci: 1, duringCall: true, rethrow: false]
              |0                  |1              
     locals:  |stack:40|QWORD[.]  |stack:28|DWORD   <||@
  Comment 124 -1 GTMARKER markerId: 0  <||@
  Comment 145 16 rsi|QWORD[.] = MOVE input: stack:40|QWORD[.] moveKind: QWORD  <||@
  Comment 150 18 rdx|DWORD = MOVE input: stack:28|DWORD moveKind: DWORD  <||@
  Comment 154 20 MOV (x: [rsi|QWORD[.] + 12], y: rdx|DWORD) size: DWORD  <||@
  Comment 157 22 RETURN (savedRbp: stack:16|QWORD, value: -) isStub: false requiresReservedStackAccessCheck: false thread: r15 scratchForSafepointOnReturn: rcx config: jdk.graal.compiler.hotspot.GraalHotSpotVMConfig@5be2b2dd  <||@
  Comment 166 POLL_RETURN_FAR  <||@
  Comment 185 {Field[name=CompilerToVM::Data::nmethod_entry_barrier, type=address, offset=0, address=0x7f4f0aa33598, value=139977128362528]:0x7f4ef7034220}  <||@
  Comment 207 {Field[name=CompilerToVM::Data::SharedRuntime_polling_page_return_handler, type=address, offset=0, address=0x7f4f0aa335a0, value=139977128497152]:0x7f4ef7055000}  <||@
  Comment 213 {Stub<ExceptionHandlerStub.exceptionHandler>@0x7f4ef70b4100:CallingConvention[rax|QWORD[.], rdx|QWORD]:CallingConvention[rax|QWORD[.], rdx|QWORD]; temps=rdi|ILLEGAL,xmm14|ILLEGAL,xmm15|ILLEGAL,xmm12|ILLEGAL,xmm13|ILLEGAL,xmm10|ILLEGAL,xmm11|ILLEGAL,xmm7|ILLEGAL,xmm8|ILLEGAL,xmm9|ILLEGAL,xmm0|ILLEGAL,xmm1|ILLEGAL,xmm2|ILLEGAL,xmm3|ILLEGAL,xmm4|ILLEGAL,xmm5|ILLEGAL,xmm6|ILLEGAL,rax|ILLEGAL,rcx|ILLEGAL,rdx|ILLEGAL,rsi|ILLEGAL,r8|ILLEGAL,r9|ILLEGAL,r10|ILLEGAL,r11|ILLEGAL}  <||@
  Comment 213 EXCEPTION_HANDLER_ENTRY  <||@
  Comment 219 {Field[name=CompilerToVM::Data::SharedRuntime_deopt_blob_unpack, type=address, offset=0, address=0x7f4f0aa335b8, value=139977128492832]:0x7f4ef7053f20}  <||@
  Comment 219 DEOPT_HANDLER_ENTRY  <||@
  HexCodeFile>>> <|@
end_nmethod
begin_compilation
  name " HotSpotCompilation-87[Towers$TowersDisk.<init>(int)]"
  method "HotSpotCompilation-87[Towers$TowersDisk.<init>(int)]"
  date 1731420413676
end_compilation
begin_cfg
  name "After code installation"
end_cfg
begin_nmethod
  <<<HexCodeFile
  Platform AMD64 64  <||@
  HexCode 7f4ef70c2d20 448b560849bc000000974e7f00004d03d44d33e4493bc20f8543b3f8ff6666900faef8c5f8c6c0ffc5f8c6c0ffc5f8c6c0ff0faef889842400c0feff4883ec2841817f20000000000f8566000000c5f8c6c000c5f8c6c000c5f8c6c00048896c24204c8bd6895424144c8954240890e8ecb5f8ff0f1f8400040200000faef8c5f8c6c000c5f8c6c000c5f8c6c0000faef8488b7424088b54241489560c488b6c24204883c428493ba7500400000f870e000000c348896c2420e84214f7ffeb8ef4488d0ddeffffff49898f68040000e90c22f9fff4e80613fffff4e82011f9fff4f4f4f4f4f4f4f448bb0000000000000000e9fbfffffff4  <||@
  Comment 0 UNVERIFIED_ENTRY  <||@
  Comment 23 {Field[name=CompilerToVM::Data::SharedRuntime_ic_miss_stub, type=address, offset=0, address=0x7f4f0aa335c8, value=139977128468608]:0x7f4ef704e080}  <||@
  Comment 32 VERIFIED_ENTRY  <||@
  Comment 53 [stack overflow check]  <||@
  Comment 64 FRAME_COMPLETE  <||@
  Comment 64 ENTRY_BARRIER_PATCH  <||@
  Comment 78 block B0 null  <||@
  Comment 78 0 [rsi|QWORD[.], rdx|DWORD, rbp|QWORD] = LABEL alignment: 0 numbPhis: 0 label: ?  <||@
  Comment 78 -1 GTMARKER markerId: 0  <||@
  Comment 93 2 stack:16|QWORD = MOVE input: rbp|QWORD moveKind: QWORD  <||@
  Comment 98 4 [] = HOTSPOTLOCKSTACK frameMapBuilder: jdk.graal.compiler.hotspot.amd64.AMD64HotSpotFrameMapBuilder@3579649f slotKind: QWORD  <||@
  Comment 98 6 r10|QWORD[.] = MOVE input: rsi|QWORD[.] moveKind: QWORD  <||@
  Comment 101 10 stack:28|DWORD = MOVE input: rdx|DWORD moveKind: DWORD  <||@
  Comment 105 12 stack:40|QWORD[.] = MOVE input: r10|QWORD[.] moveKind: QWORD  <||@
  Comment 110 14 - = CALL_DIRECT parameters: [rsi|QWORD[.]] temps: [] callTarget: HotSpotMethod<Object.<init>()> invokeKind: Special config: jdk.graal.compiler.hotspot.GraalHotSpotVMConfig@5be2b2dd state [bci:1]  <||@
  Comment 111 {HotSpotMethod<Object.<init>()>}  <||@
  Comment 111 INVOKESPECIAL  <||@
  Comment 116 [stack:8]at Towers$TowersDisk.<init>(int) [bci: 1, duringCall: true, rethrow: false]
              |0                  |1              
     locals:  |stack:40|QWORD[.]  |stack:28|DWORD   <||@
  Comment 124 -1 GTMARKER markerId: 0  <||@
  Comment 145 16 rsi|QWORD[.] = MOVE input: stack:40|QWORD[.] moveKind: QWORD  <||@
  Comment 150 18 rdx|DWORD = MOVE input: stack:28|DWORD moveKind: DWORD  <||@
  Comment 154 20 MOV (x: [rsi|QWORD[.] + 12], y: rdx|DWORD) size: DWORD  <||@
  Comment 157 22 RETURN (savedRbp: stack:16|QWORD, value: -) isStub: false requiresReservedStackAccessCheck: false thread: r15 scratchForSafepointOnReturn: rcx config: jdk.graal.compiler.hotspot.GraalHotSpotVMConfig@5be2b2dd  <||@
  Comment 166 POLL_RETURN_FAR  <||@
  Comment 185 {Field[name=CompilerToVM::Data::nmethod_entry_barrier, type=address, offset=0, address=0x7f4f0aa33598, value=139977128362528]:0x7f4ef7034220}  <||@
  Comment 207 {Field[name=CompilerToVM::Data::SharedRuntime_polling_page_return_handler, type=address, offset=0, address=0x7f4f0aa335a0, value=139977128497152]:0x7f4ef7055000}  <||@
  Comment 213 {Stub<ExceptionHandlerStub.exceptionHandler>@0x7f4ef70b4100:CallingConvention[rax|QWORD[.], rdx|QWORD]:CallingConvention[rax|QWORD[.], rdx|QWORD]; temps=rdi|ILLEGAL,xmm14|ILLEGAL,xmm15|ILLEGAL,xmm12|ILLEGAL,xmm13|ILLEGAL,xmm10|ILLEGAL,xmm11|ILLEGAL,xmm7|ILLEGAL,xmm8|ILLEGAL,xmm9|ILLEGAL,xmm0|ILLEGAL,xmm1|ILLEGAL,xmm2|ILLEGAL,xmm3|ILLEGAL,xmm4|ILLEGAL,xmm5|ILLEGAL,xmm6|ILLEGAL,rax|ILLEGAL,rcx|ILLEGAL,rdx|ILLEGAL,rsi|ILLEGAL,r8|ILLEGAL,r9|ILLEGAL,r10|ILLEGAL,r11|ILLEGAL}  <||@
  Comment 213 EXCEPTION_HANDLER_ENTRY  <||@
  Comment 219 {Field[name=CompilerToVM::Data::SharedRuntime_deopt_blob_unpack, type=address, offset=0, address=0x7f4f0aa335b8, value=139977128492832]:0x7f4ef7053f20}  <||@
  Comment 219 DEOPT_HANDLER_ENTRY  <||@
  HexCodeFile>>> <|@
end_nmethod
