begin_compilation
  name " HotSpotCompilation-9202[jdk.internal.misc.Unsafe.checkNativeAddress(long)]"
  method "HotSpotCompilation-9202[jdk.internal.misc.Unsafe.checkNativeAddress(long)]"
  date 1724269765430
end_compilation
begin_cfg
  name "Final HIR schedule"
  begin_block
    name "B0"
    from_bci -1
    to_bci -1
    predecessors 
    successors 
    xhandlers
    flags 
    probability 4607182418800017408
    begin_IR
      HIR
f <@#|@fixed with next>@ <|@
tid v0 <|@
d <@d|@=== Debug Properties ===
hasSpeculationFence: false
stamp: void
=== Inputs ===
stateAfter: - 
=== Succesors ===
next: v6 
=== Usages ===
=== Predecessor ===
- >@ <|@
instruction <@StartNode|@jdk.graal.compiler.nodes.StartNode>@ stateAfter: - #next: v6  <|@  <|@
f <@*|@fixed>@ <|@
tid v6 <|@
d <@d|@=== Debug Properties ===
nodeSourcePosition: at jdk.internal.misc.Unsafe.checkNativeAddress(Unsafe.java:491) [bci: 27]
stamp: void
=== Inputs ===
memoryMap: - 
result: - 
=== Succesors ===
=== Usages ===
=== Predecessor ===
v0 >@ <|@
instruction <@Return|@jdk.graal.compiler.nodes.ReturnNode>@ memoryMap: - result: -  <|@  <|@
    end_IR
  end_block
end_cfg
begin_cfg
  name "After LIRGeneration"
  begin_block
    name "B0"
    from_bci -1
    to_bci -1
    predecessors 
    successors 
    xhandlers
    flags 
    probability 4607182418800017408
    begin_IR
      LIR
      nr   -1  <|@ instruction [rsi|QWORD[.], rdx|QWORD, rbp|QWORD] = LABEL alignment: 0 numbPhis: 0 label: ? <|@ <|@
      nr   -1  <|@ instruction v0|QWORD = MOVE input: rbp|QWORD moveKind: QWORD <|@ <|@
      nr   -1  <|@ instruction [] = HOTSPOTLOCKSTACK frameMapBuilder: jdk.graal.compiler.hotspot.amd64.AMD64HotSpotFrameMapBuilder@e58d03c slotKind: QWORD <|@ <|@
      nr   -1  <|@ instruction RETURN (savedRbp: v0|QWORD, value: -) isStub: false requiresReservedStackAccessCheck: false thread: r15 scratchForSafepointOnReturn: rcx config: jdk.graal.compiler.hotspot.GraalHotSpotVMConfig@4817c460 <|@ <|@
    end_IR
  end_block
end_cfg
begin_bytecodes
     0: getstatic     #2          // ADDRESS_SIZE:int
     3: iconst_4      
     4: if_icmpne     27
     7: lload_1       
     8: bipush        32
    10: lshr          
    11: lconst_1      
    12: ladd          
    13: ldc2_w        #96         // -2
    16: land          
    17: lconst_0      
    18: lcmp          
    19: ifeq          27
    22: aload_0       
    23: invokevirtual #22         // invalidInput:()java.lang.RuntimeException
    26: athrow        
    27: return        
   <|@
end_bytecodes
begin_cfg
  name "After LIR generation"
  begin_block
    name "B0"
    from_bci -1
    to_bci -1
    predecessors 
    successors 
    xhandlers
    flags 
    probability 4607182418800017408
    begin_IR
      HIR
f <@#|@fixed with next>@ <|@
tid v0 <|@
d <@d|@=== Debug Properties ===
hasSpeculationFence: false
stamp: void
=== Inputs ===
stateAfter: - 
=== Succesors ===
next: v6 
=== Usages ===
=== Predecessor ===
- >@ <|@
instruction <@StartNode|@jdk.graal.compiler.nodes.StartNode>@ stateAfter: - #next: v6  <|@  <|@
f <@*|@fixed>@ <|@
tid v6 <|@
d <@d|@=== Debug Properties ===
nodeSourcePosition: at jdk.internal.misc.Unsafe.checkNativeAddress(Unsafe.java:491) [bci: 27]
stamp: void
=== Inputs ===
memoryMap: - 
result: - 
=== Succesors ===
=== Usages ===
=== Predecessor ===
v0 >@ <|@
instruction <@Return|@jdk.graal.compiler.nodes.ReturnNode>@ memoryMap: - result: -  <|@  <|@
    end_IR
    begin_IR
      LIR
      nr   -1  <|@ instruction [rsi|QWORD[.], rdx|QWORD, rbp|QWORD] = LABEL alignment: 0 numbPhis: 0 label: ? <|@ <|@
      nr   -1  <|@ instruction v0|QWORD = MOVE input: rbp|QWORD moveKind: QWORD <|@ <|@
      nr   -1  <|@ instruction [] = HOTSPOTLOCKSTACK frameMapBuilder: jdk.graal.compiler.hotspot.amd64.AMD64HotSpotFrameMapBuilder@e58d03c slotKind: QWORD <|@ <|@
      nr   -1  <|@ instruction RETURN (savedRbp: v0|QWORD, value: -) isStub: false requiresReservedStackAccessCheck: false thread: r15 scratchForSafepointOnReturn: rcx config: jdk.graal.compiler.hotspot.GraalHotSpotVMConfig@4817c460 <|@ <|@
    end_IR
  end_block
end_cfg
begin_cfg
  name "After LIRGTSlowdown"
  begin_block
    name "B0"
    from_bci -1
    to_bci -1
    predecessors 
    successors 
    xhandlers
    flags 
    probability 4607182418800017408
    begin_IR
      LIR
      nr   -1  <|@ instruction [rsi|QWORD[.], rdx|QWORD, rbp|QWORD] = LABEL alignment: 0 numbPhis: 0 label: ? <|@ <|@
      nr   -1  <|@ instruction NOP <|@ <|@
      nr   -1  <|@ instruction NOP <|@ <|@
      nr   -1  <|@ instruction NOP <|@ <|@
      nr   -1  <|@ instruction NOP <|@ <|@
      nr   -1  <|@ instruction NOP <|@ <|@
      nr   -1  <|@ instruction NOP <|@ <|@
      nr   -1  <|@ instruction NOP <|@ <|@
      nr   -1  <|@ instruction NOP <|@ <|@
      nr   -1  <|@ instruction NOP <|@ <|@
      nr   -1  <|@ instruction v0|QWORD = MOVE input: rbp|QWORD moveKind: QWORD <|@ <|@
      nr   -1  <|@ instruction [] = HOTSPOTLOCKSTACK frameMapBuilder: jdk.graal.compiler.hotspot.amd64.AMD64HotSpotFrameMapBuilder@e58d03c slotKind: QWORD <|@ <|@
      nr   -1  <|@ instruction RETURN (savedRbp: v0|QWORD, value: -) isStub: false requiresReservedStackAccessCheck: false thread: r15 scratchForSafepointOnReturn: rcx config: jdk.graal.compiler.hotspot.GraalHotSpotVMConfig@4817c460 <|@ <|@
    end_IR
  end_block
end_cfg
begin_bytecodes
     0: getstatic     #2          // ADDRESS_SIZE:int
     3: iconst_4      
     4: if_icmpne     27
     7: lload_1       
     8: bipush        32
    10: lshr          
    11: lconst_1      
    12: ladd          
    13: ldc2_w        #96         // -2
    16: land          
    17: lconst_0      
    18: lcmp          
    19: ifeq          27
    22: aload_0       
    23: invokevirtual #22         // invalidInput:()java.lang.RuntimeException
    26: athrow        
    27: return        
   <|@
end_bytecodes
begin_cfg
  name "After ConstantLoadOptimization"
  begin_block
    name "B0"
    from_bci -1
    to_bci -1
    predecessors 
    successors 
    xhandlers
    flags 
    probability 4607182418800017408
    begin_IR
      LIR
      nr   -1  <|@ instruction [rsi|QWORD[.], rdx|QWORD, rbp|QWORD] = LABEL alignment: 0 numbPhis: 0 label: ? <|@ <|@
      nr   -1  <|@ instruction NOP <|@ <|@
      nr   -1  <|@ instruction NOP <|@ <|@
      nr   -1  <|@ instruction NOP <|@ <|@
      nr   -1  <|@ instruction NOP <|@ <|@
      nr   -1  <|@ instruction NOP <|@ <|@
      nr   -1  <|@ instruction NOP <|@ <|@
      nr   -1  <|@ instruction NOP <|@ <|@
      nr   -1  <|@ instruction NOP <|@ <|@
      nr   -1  <|@ instruction NOP <|@ <|@
      nr   -1  <|@ instruction v0|QWORD = MOVE input: rbp|QWORD moveKind: QWORD <|@ <|@
      nr   -1  <|@ instruction [] = HOTSPOTLOCKSTACK frameMapBuilder: jdk.graal.compiler.hotspot.amd64.AMD64HotSpotFrameMapBuilder@e58d03c slotKind: QWORD <|@ <|@
      nr   -1  <|@ instruction RETURN (savedRbp: v0|QWORD, value: -) isStub: false requiresReservedStackAccessCheck: false thread: r15 scratchForSafepointOnReturn: rcx config: jdk.graal.compiler.hotspot.GraalHotSpotVMConfig@4817c460 <|@ <|@
    end_IR
  end_block
end_cfg
begin_bytecodes
     0: getstatic     #2          // ADDRESS_SIZE:int
     3: iconst_4      
     4: if_icmpne     27
     7: lload_1       
     8: bipush        32
    10: lshr          
    11: lconst_1      
    12: ladd          
    13: ldc2_w        #96         // -2
    16: land          
    17: lconst_0      
    18: lcmp          
    19: ifeq          27
    22: aload_0       
    23: invokevirtual #22         // invalidInput:()java.lang.RuntimeException
    26: athrow        
    27: return        
   <|@
end_bytecodes
begin_cfg
  name "After SaveCalleeSaveRegisters"
  begin_block
    name "B0"
    from_bci -1
    to_bci -1
    predecessors 
    successors 
    xhandlers
    flags 
    probability 4607182418800017408
    begin_IR
      LIR
      nr   -1  <|@ instruction [rsi|QWORD[.], rdx|QWORD, rbp|QWORD] = LABEL alignment: 0 numbPhis: 0 label: ? <|@ <|@
      nr   -1  <|@ instruction NOP <|@ <|@
      nr   -1  <|@ instruction NOP <|@ <|@
      nr   -1  <|@ instruction NOP <|@ <|@
      nr   -1  <|@ instruction NOP <|@ <|@
      nr   -1  <|@ instruction NOP <|@ <|@
      nr   -1  <|@ instruction NOP <|@ <|@
      nr   -1  <|@ instruction NOP <|@ <|@
      nr   -1  <|@ instruction NOP <|@ <|@
      nr   -1  <|@ instruction NOP <|@ <|@
      nr   -1  <|@ instruction v0|QWORD = MOVE input: rbp|QWORD moveKind: QWORD <|@ <|@
      nr   -1  <|@ instruction [] = HOTSPOTLOCKSTACK frameMapBuilder: jdk.graal.compiler.hotspot.amd64.AMD64HotSpotFrameMapBuilder@e58d03c slotKind: QWORD <|@ <|@
      nr   -1  <|@ instruction RETURN (savedRbp: v0|QWORD, value: -) isStub: false requiresReservedStackAccessCheck: false thread: r15 scratchForSafepointOnReturn: rcx config: jdk.graal.compiler.hotspot.GraalHotSpotVMConfig@4817c460 <|@ <|@
    end_IR
  end_block
end_cfg
begin_bytecodes
     0: getstatic     #2          // ADDRESS_SIZE:int
     3: iconst_4      
     4: if_icmpne     27
     7: lload_1       
     8: bipush        32
    10: lshr          
    11: lconst_1      
    12: ladd          
    13: ldc2_w        #96         // -2
    16: land          
    17: lconst_0      
    18: lcmp          
    19: ifeq          27
    22: aload_0       
    23: invokevirtual #22         // invalidInput:()java.lang.RuntimeException
    26: athrow        
    27: return        
   <|@
end_bytecodes
begin_cfg
  name "After PreAllocationOptimizationStage"
  begin_block
    name "B0"
    from_bci -1
    to_bci -1
    predecessors 
    successors 
    xhandlers
    flags 
    probability 4607182418800017408
    begin_IR
      LIR
      nr   -1  <|@ instruction [rsi|QWORD[.], rdx|QWORD, rbp|QWORD] = LABEL alignment: 0 numbPhis: 0 label: ? <|@ <|@
      nr   -1  <|@ instruction NOP <|@ <|@
      nr   -1  <|@ instruction NOP <|@ <|@
      nr   -1  <|@ instruction NOP <|@ <|@
      nr   -1  <|@ instruction NOP <|@ <|@
      nr   -1  <|@ instruction NOP <|@ <|@
      nr   -1  <|@ instruction NOP <|@ <|@
      nr   -1  <|@ instruction NOP <|@ <|@
      nr   -1  <|@ instruction NOP <|@ <|@
      nr   -1  <|@ instruction NOP <|@ <|@
      nr   -1  <|@ instruction v0|QWORD = MOVE input: rbp|QWORD moveKind: QWORD <|@ <|@
      nr   -1  <|@ instruction [] = HOTSPOTLOCKSTACK frameMapBuilder: jdk.graal.compiler.hotspot.amd64.AMD64HotSpotFrameMapBuilder@e58d03c slotKind: QWORD <|@ <|@
      nr   -1  <|@ instruction RETURN (savedRbp: v0|QWORD, value: -) isStub: false requiresReservedStackAccessCheck: false thread: r15 scratchForSafepointOnReturn: rcx config: jdk.graal.compiler.hotspot.GraalHotSpotVMConfig@4817c460 <|@ <|@
    end_IR
  end_block
end_cfg
begin_bytecodes
     0: getstatic     #2          // ADDRESS_SIZE:int
     3: iconst_4      
     4: if_icmpne     27
     7: lload_1       
     8: bipush        32
    10: lshr          
    11: lconst_1      
    12: ladd          
    13: ldc2_w        #96         // -2
    16: land          
    17: lconst_0      
    18: lcmp          
    19: ifeq          27
    22: aload_0       
    23: invokevirtual #22         // invalidInput:()java.lang.RuntimeException
    26: athrow        
    27: return        
   <|@
end_bytecodes
begin_cfg
  name "After MarkBasePointers"
  begin_block
    name "B0"
    from_bci -1
    to_bci -1
    predecessors 
    successors 
    xhandlers
    flags 
    probability 4607182418800017408
    begin_IR
      LIR
      nr   -1  <|@ instruction [rsi|QWORD[.], rdx|QWORD, rbp|QWORD] = LABEL alignment: 0 numbPhis: 0 label: ? <|@ <|@
      nr   -1  <|@ instruction NOP <|@ <|@
      nr   -1  <|@ instruction NOP <|@ <|@
      nr   -1  <|@ instruction NOP <|@ <|@
      nr   -1  <|@ instruction NOP <|@ <|@
      nr   -1  <|@ instruction NOP <|@ <|@
      nr   -1  <|@ instruction NOP <|@ <|@
      nr   -1  <|@ instruction NOP <|@ <|@
      nr   -1  <|@ instruction NOP <|@ <|@
      nr   -1  <|@ instruction NOP <|@ <|@
      nr   -1  <|@ instruction v0|QWORD = MOVE input: rbp|QWORD moveKind: QWORD <|@ <|@
      nr   -1  <|@ instruction [] = HOTSPOTLOCKSTACK frameMapBuilder: jdk.graal.compiler.hotspot.amd64.AMD64HotSpotFrameMapBuilder@e58d03c slotKind: QWORD <|@ <|@
      nr   -1  <|@ instruction RETURN (savedRbp: v0|QWORD, value: -) isStub: false requiresReservedStackAccessCheck: false thread: r15 scratchForSafepointOnReturn: rcx config: jdk.graal.compiler.hotspot.GraalHotSpotVMConfig@4817c460 <|@ <|@
    end_IR
  end_block
end_cfg
begin_bytecodes
     0: getstatic     #2          // ADDRESS_SIZE:int
     3: iconst_4      
     4: if_icmpne     27
     7: lload_1       
     8: bipush        32
    10: lshr          
    11: lconst_1      
    12: ladd          
    13: ldc2_w        #96         // -2
    16: land          
    17: lconst_0      
    18: lcmp          
    19: ifeq          27
    22: aload_0       
    23: invokevirtual #22         // invalidInput:()java.lang.RuntimeException
    26: athrow        
    27: return        
   <|@
end_bytecodes
begin_cfg
  name "Before register allocation"
  begin_block
    name "B0"
    from_bci -1
    to_bci -1
    predecessors 
    successors 
    xhandlers
    flags 
    probability 4607182418800017408
    begin_IR
      LIR
      nr    0  <|@ instruction [rsi|QWORD[.], rdx|QWORD, rbp|QWORD] = LABEL alignment: 0 numbPhis: 0 label: ? <|@ <|@
      nr    2  <|@ instruction NOP <|@ <|@
      nr    4  <|@ instruction NOP <|@ <|@
      nr    6  <|@ instruction NOP <|@ <|@
      nr    8  <|@ instruction NOP <|@ <|@
      nr   10  <|@ instruction NOP <|@ <|@
      nr   12  <|@ instruction NOP <|@ <|@
      nr   14  <|@ instruction NOP <|@ <|@
      nr   16  <|@ instruction NOP <|@ <|@
      nr   18  <|@ instruction NOP <|@ <|@
      nr   20  <|@ instruction v0|QWORD = MOVE input: rbp|QWORD moveKind: QWORD <|@ <|@
      nr   22  <|@ instruction [] = HOTSPOTLOCKSTACK frameMapBuilder: jdk.graal.compiler.hotspot.amd64.AMD64HotSpotFrameMapBuilder@e58d03c slotKind: QWORD <|@ <|@
      nr   24  <|@ instruction RETURN (savedRbp: v0|QWORD, value: -) isStub: false requiresReservedStackAccessCheck: false thread: r15 scratchForSafepointOnReturn: rcx config: jdk.graal.compiler.hotspot.GraalHotSpotVMConfig@4817c460 <|@ <|@
    end_IR
  end_block
end_cfg
begin_bytecodes
     0: getstatic     #2          // ADDRESS_SIZE:int
     3: iconst_4      
     4: if_icmpne     27
     7: lload_1       
     8: bipush        32
    10: lshr          
    11: lconst_1      
    12: ladd          
    13: ldc2_w        #96         // -2
    16: land          
    17: lconst_0      
    18: lcmp          
    19: ifeq          27
    22: aload_0       
    23: invokevirtual #22         // invalidInput:()java.lang.RuntimeException
    26: athrow        
    27: return        
   <|@
end_bytecodes
begin_cfg
  name "After SSALinearScanLifetimeAnalysis"
  begin_block
    name "B0"
    from_bci -1
    to_bci -1
    predecessors 
    successors 
    xhandlers
    flags 
    probability 4607182418800017408
    begin_IR
      LIR
      nr    0  <|@ instruction [rsi|QWORD[.], rdx|QWORD, rbp|QWORD] = LABEL alignment: 0 numbPhis: 0 label: ? <|@ <|@
      nr    2  <|@ instruction NOP <|@ <|@
      nr    4  <|@ instruction NOP <|@ <|@
      nr    6  <|@ instruction NOP <|@ <|@
      nr    8  <|@ instruction NOP <|@ <|@
      nr   10  <|@ instruction NOP <|@ <|@
      nr   12  <|@ instruction NOP <|@ <|@
      nr   14  <|@ instruction NOP <|@ <|@
      nr   16  <|@ instruction NOP <|@ <|@
      nr   18  <|@ instruction NOP <|@ <|@
      nr   20  <|@ instruction v0|QWORD = MOVE input: rbp|QWORD moveKind: QWORD <|@ <|@
      nr   22  <|@ instruction [] = HOTSPOTLOCKSTACK frameMapBuilder: jdk.graal.compiler.hotspot.amd64.AMD64HotSpotFrameMapBuilder@e58d03c slotKind: QWORD <|@ <|@
      nr   24  <|@ instruction RETURN (savedRbp: v0|QWORD, value: -) isStub: false requiresReservedStackAccessCheck: false thread: r15 scratchForSafepointOnReturn: rcx config: jdk.graal.compiler.hotspot.GraalHotSpotVMConfig@4817c460 <|@ <|@
    end_IR
  end_block
end_cfg
begin_bytecodes
     0: getstatic     #2          // ADDRESS_SIZE:int
     3: iconst_4      
     4: if_icmpne     27
     7: lload_1       
     8: bipush        32
    10: lshr          
    11: lconst_1      
    12: ladd          
    13: ldc2_w        #96         // -2
    16: land          
    17: lconst_0      
    18: lcmp          
    19: ifeq          27
    22: aload_0       
    23: invokevirtual #22         // invalidInput:()java.lang.RuntimeException
    26: athrow        
    27: return        
   <|@
end_bytecodes
begin_intervals
  name "Before register allocation"
  rdx|q fixed "[rdx|q]" rdx|q -1 [0, 1[ "NoSpillStore"
  rbp|q fixed "[rbp|q]" rbp|q -1 [0, 20[ "NoSpillStore"
  rsi|q fixed "[rsi|q]" rsi|q -1 [0, 1[ "NoSpillStore"
  v0|q QWORD "[v0|q]" v0|q rbp|q [20, 24[20 MustHaveRegister 24 ShouldHaveRegister  "NoSpillStore"
end_intervals
begin_intervals
  name "After register allocation"
  rdx|q fixed "[rdx|q]" rdx|q -1 [0, 1[ "NoSpillStore"
  rbp|q fixed "[rbp|q]" rbp|q -1 [0, 20[ "NoSpillStore"
  rsi|q fixed "[rsi|q]" rsi|q -1 [0, 1[ "NoSpillStore"
  v0|q QWORD "[rbp|q]" v0|q rbp|q [20, 24[20 MustHaveRegister 24 ShouldHaveRegister  "NoSpillStore"
end_intervals
begin_cfg
  name "After LinearScanRegisterAllocation"
  begin_block
    name "B0"
    from_bci -1
    to_bci -1
    predecessors 
    successors 
    xhandlers
    flags 
    probability 4607182418800017408
    begin_IR
      LIR
      nr    0  <|@ instruction [rsi|QWORD[.], rdx|QWORD, rbp|QWORD] = LABEL alignment: 0 numbPhis: 0 label: ? <|@ <|@
      nr    2  <|@ instruction NOP <|@ <|@
      nr    4  <|@ instruction NOP <|@ <|@
      nr    6  <|@ instruction NOP <|@ <|@
      nr    8  <|@ instruction NOP <|@ <|@
      nr   10  <|@ instruction NOP <|@ <|@
      nr   12  <|@ instruction NOP <|@ <|@
      nr   14  <|@ instruction NOP <|@ <|@
      nr   16  <|@ instruction NOP <|@ <|@
      nr   18  <|@ instruction NOP <|@ <|@
      nr   20  <|@ instruction v0|QWORD = MOVE input: rbp|QWORD moveKind: QWORD <|@ <|@
      nr   22  <|@ instruction [] = HOTSPOTLOCKSTACK frameMapBuilder: jdk.graal.compiler.hotspot.amd64.AMD64HotSpotFrameMapBuilder@e58d03c slotKind: QWORD <|@ <|@
      nr   24  <|@ instruction RETURN (savedRbp: v0|QWORD, value: -) isStub: false requiresReservedStackAccessCheck: false thread: r15 scratchForSafepointOnReturn: rcx config: jdk.graal.compiler.hotspot.GraalHotSpotVMConfig@4817c460 <|@ <|@
    end_IR
  end_block
end_cfg
begin_bytecodes
     0: getstatic     #2          // ADDRESS_SIZE:int
     3: iconst_4      
     4: if_icmpne     27
     7: lload_1       
     8: bipush        32
    10: lshr          
    11: lconst_1      
    12: ladd          
    13: ldc2_w        #96         // -2
    16: land          
    17: lconst_0      
    18: lcmp          
    19: ifeq          27
    22: aload_0       
    23: invokevirtual #22         // invalidInput:()java.lang.RuntimeException
    26: athrow        
    27: return        
   <|@
end_bytecodes
begin_intervals
  name "After optimize spill position"
  rdx|q fixed "[rdx|q]" rdx|q -1 [0, 1[ "NoSpillStore"
  rbp|q fixed "[rbp|q]" rbp|q -1 [0, 20[ "NoSpillStore"
  rsi|q fixed "[rsi|q]" rsi|q -1 [0, 1[ "NoSpillStore"
  v0|q QWORD "[rbp|q]" v0|q rbp|q [20, 24[20 MustHaveRegister 24 ShouldHaveRegister  "NoSpillStore"
end_intervals
begin_cfg
  name "After LinearScanOptimizeSpillPosition"
  begin_block
    name "B0"
    from_bci -1
    to_bci -1
    predecessors 
    successors 
    xhandlers
    flags 
    probability 4607182418800017408
    begin_IR
      LIR
      nr    0  <|@ instruction [rsi|QWORD[.], rdx|QWORD, rbp|QWORD] = LABEL alignment: 0 numbPhis: 0 label: ? <|@ <|@
      nr    2  <|@ instruction NOP <|@ <|@
      nr    4  <|@ instruction NOP <|@ <|@
      nr    6  <|@ instruction NOP <|@ <|@
      nr    8  <|@ instruction NOP <|@ <|@
      nr   10  <|@ instruction NOP <|@ <|@
      nr   12  <|@ instruction NOP <|@ <|@
      nr   14  <|@ instruction NOP <|@ <|@
      nr   16  <|@ instruction NOP <|@ <|@
      nr   18  <|@ instruction NOP <|@ <|@
      nr   20  <|@ instruction v0|QWORD = MOVE input: rbp|QWORD moveKind: QWORD <|@ <|@
      nr   22  <|@ instruction [] = HOTSPOTLOCKSTACK frameMapBuilder: jdk.graal.compiler.hotspot.amd64.AMD64HotSpotFrameMapBuilder@e58d03c slotKind: QWORD <|@ <|@
      nr   24  <|@ instruction RETURN (savedRbp: v0|QWORD, value: -) isStub: false requiresReservedStackAccessCheck: false thread: r15 scratchForSafepointOnReturn: rcx config: jdk.graal.compiler.hotspot.GraalHotSpotVMConfig@4817c460 <|@ <|@
    end_IR
  end_block
end_cfg
begin_bytecodes
     0: getstatic     #2          // ADDRESS_SIZE:int
     3: iconst_4      
     4: if_icmpne     27
     7: lload_1       
     8: bipush        32
    10: lshr          
    11: lconst_1      
    12: ladd          
    13: ldc2_w        #96         // -2
    16: land          
    17: lconst_0      
    18: lcmp          
    19: ifeq          27
    22: aload_0       
    23: invokevirtual #22         // invalidInput:()java.lang.RuntimeException
    26: athrow        
    27: return        
   <|@
end_bytecodes
begin_intervals
  name "After resolve data flow"
  rdx|q fixed "[rdx|q]" rdx|q -1 [0, 1[ "NoSpillStore"
  rbp|q fixed "[rbp|q]" rbp|q -1 [0, 20[ "NoSpillStore"
  rsi|q fixed "[rsi|q]" rsi|q -1 [0, 1[ "NoSpillStore"
  v0|q QWORD "[rbp|q]" v0|q rbp|q [20, 24[20 MustHaveRegister 24 ShouldHaveRegister  "NoSpillStore"
end_intervals
begin_cfg
  name "After SSALinearScanResolveDataFlow"
  begin_block
    name "B0"
    from_bci -1
    to_bci -1
    predecessors 
    successors 
    xhandlers
    flags 
    probability 4607182418800017408
    begin_IR
      LIR
      nr    0  <|@ instruction [rsi|QWORD[.], rdx|QWORD, rbp|QWORD] = LABEL alignment: 0 numbPhis: 0 label: ? <|@ <|@
      nr    2  <|@ instruction NOP <|@ <|@
      nr    4  <|@ instruction NOP <|@ <|@
      nr    6  <|@ instruction NOP <|@ <|@
      nr    8  <|@ instruction NOP <|@ <|@
      nr   10  <|@ instruction NOP <|@ <|@
      nr   12  <|@ instruction NOP <|@ <|@
      nr   14  <|@ instruction NOP <|@ <|@
      nr   16  <|@ instruction NOP <|@ <|@
      nr   18  <|@ instruction NOP <|@ <|@
      nr   20  <|@ instruction v0|QWORD = MOVE input: rbp|QWORD moveKind: QWORD <|@ <|@
      nr   22  <|@ instruction [] = HOTSPOTLOCKSTACK frameMapBuilder: jdk.graal.compiler.hotspot.amd64.AMD64HotSpotFrameMapBuilder@e58d03c slotKind: QWORD <|@ <|@
      nr   24  <|@ instruction RETURN (savedRbp: v0|QWORD, value: -) isStub: false requiresReservedStackAccessCheck: false thread: r15 scratchForSafepointOnReturn: rcx config: jdk.graal.compiler.hotspot.GraalHotSpotVMConfig@4817c460 <|@ <|@
    end_IR
  end_block
end_cfg
begin_bytecodes
     0: getstatic     #2          // ADDRESS_SIZE:int
     3: iconst_4      
     4: if_icmpne     27
     7: lload_1       
     8: bipush        32
    10: lshr          
    11: lconst_1      
    12: ladd          
    13: ldc2_w        #96         // -2
    16: land          
    17: lconst_0      
    18: lcmp          
    19: ifeq          27
    22: aload_0       
    23: invokevirtual #22         // invalidInput:()java.lang.RuntimeException
    26: athrow        
    27: return        
   <|@
end_bytecodes
begin_cfg
  name "After SSALinearScanEliminateSpillMove"
  begin_block
    name "B0"
    from_bci -1
    to_bci -1
    predecessors 
    successors 
    xhandlers
    flags 
    probability 4607182418800017408
    begin_IR
      LIR
      nr    0  <|@ instruction [rsi|QWORD[.], rdx|QWORD, rbp|QWORD] = LABEL alignment: 0 numbPhis: 0 label: ? <|@ <|@
      nr    2  <|@ instruction NOP <|@ <|@
      nr    4  <|@ instruction NOP <|@ <|@
      nr    6  <|@ instruction NOP <|@ <|@
      nr    8  <|@ instruction NOP <|@ <|@
      nr   10  <|@ instruction NOP <|@ <|@
      nr   12  <|@ instruction NOP <|@ <|@
      nr   14  <|@ instruction NOP <|@ <|@
      nr   16  <|@ instruction NOP <|@ <|@
      nr   18  <|@ instruction NOP <|@ <|@
      nr   20  <|@ instruction v0|QWORD = MOVE input: rbp|QWORD moveKind: QWORD <|@ <|@
      nr   22  <|@ instruction [] = HOTSPOTLOCKSTACK frameMapBuilder: jdk.graal.compiler.hotspot.amd64.AMD64HotSpotFrameMapBuilder@e58d03c slotKind: QWORD <|@ <|@
      nr   24  <|@ instruction RETURN (savedRbp: v0|QWORD, value: -) isStub: false requiresReservedStackAccessCheck: false thread: r15 scratchForSafepointOnReturn: rcx config: jdk.graal.compiler.hotspot.GraalHotSpotVMConfig@4817c460 <|@ <|@
    end_IR
  end_block
end_cfg
begin_bytecodes
     0: getstatic     #2          // ADDRESS_SIZE:int
     3: iconst_4      
     4: if_icmpne     27
     7: lload_1       
     8: bipush        32
    10: lshr          
    11: lconst_1      
    12: ladd          
    13: ldc2_w        #96         // -2
    16: land          
    17: lconst_0      
    18: lcmp          
    19: ifeq          27
    22: aload_0       
    23: invokevirtual #22         // invalidInput:()java.lang.RuntimeException
    26: athrow        
    27: return        
   <|@
end_bytecodes
begin_cfg
  name "After LinearScanAssignLocations"
  begin_block
    name "B0"
    from_bci -1
    to_bci -1
    predecessors 
    successors 
    xhandlers
    flags 
    probability 4607182418800017408
    begin_IR
      LIR
      nr    0  <|@ instruction [rsi|QWORD[.], rdx|QWORD, rbp|QWORD] = LABEL alignment: 0 numbPhis: 0 label: ? <|@ <|@
      nr    2  <|@ instruction NOP <|@ <|@
      nr    4  <|@ instruction NOP <|@ <|@
      nr    6  <|@ instruction NOP <|@ <|@
      nr    8  <|@ instruction NOP <|@ <|@
      nr   10  <|@ instruction NOP <|@ <|@
      nr   12  <|@ instruction NOP <|@ <|@
      nr   14  <|@ instruction NOP <|@ <|@
      nr   16  <|@ instruction NOP <|@ <|@
      nr   18  <|@ instruction NOP <|@ <|@
      nr   22  <|@ instruction [] = HOTSPOTLOCKSTACK frameMapBuilder: jdk.graal.compiler.hotspot.amd64.AMD64HotSpotFrameMapBuilder@e58d03c slotKind: QWORD <|@ <|@
      nr   24  <|@ instruction RETURN (savedRbp: rbp|QWORD, value: -) isStub: false requiresReservedStackAccessCheck: false thread: r15 scratchForSafepointOnReturn: rcx config: jdk.graal.compiler.hotspot.GraalHotSpotVMConfig@4817c460 <|@ <|@
    end_IR
  end_block
end_cfg
begin_bytecodes
     0: getstatic     #2          // ADDRESS_SIZE:int
     3: iconst_4      
     4: if_icmpne     27
     7: lload_1       
     8: bipush        32
    10: lshr          
    11: lconst_1      
    12: ladd          
    13: ldc2_w        #96         // -2
    16: land          
    17: lconst_0      
    18: lcmp          
    19: ifeq          27
    22: aload_0       
    23: invokevirtual #22         // invalidInput:()java.lang.RuntimeException
    26: athrow        
    27: return        
   <|@
end_bytecodes
begin_cfg
  name "After LinearScan"
  begin_block
    name "B0"
    from_bci -1
    to_bci -1
    predecessors 
    successors 
    xhandlers
    flags 
    probability 4607182418800017408
    begin_IR
      LIR
      nr    0  <|@ instruction [rsi|QWORD[.], rdx|QWORD, rbp|QWORD] = LABEL alignment: 0 numbPhis: 0 label: ? <|@ <|@
      nr    2  <|@ instruction NOP <|@ <|@
      nr    4  <|@ instruction NOP <|@ <|@
      nr    6  <|@ instruction NOP <|@ <|@
      nr    8  <|@ instruction NOP <|@ <|@
      nr   10  <|@ instruction NOP <|@ <|@
      nr   12  <|@ instruction NOP <|@ <|@
      nr   14  <|@ instruction NOP <|@ <|@
      nr   16  <|@ instruction NOP <|@ <|@
      nr   18  <|@ instruction NOP <|@ <|@
      nr   22  <|@ instruction [] = HOTSPOTLOCKSTACK frameMapBuilder: jdk.graal.compiler.hotspot.amd64.AMD64HotSpotFrameMapBuilder@e58d03c slotKind: QWORD <|@ <|@
      nr   24  <|@ instruction RETURN (savedRbp: rbp|QWORD, value: -) isStub: false requiresReservedStackAccessCheck: false thread: r15 scratchForSafepointOnReturn: rcx config: jdk.graal.compiler.hotspot.GraalHotSpotVMConfig@4817c460 <|@ <|@
    end_IR
  end_block
end_cfg
begin_bytecodes
     0: getstatic     #2          // ADDRESS_SIZE:int
     3: iconst_4      
     4: if_icmpne     27
     7: lload_1       
     8: bipush        32
    10: lshr          
    11: lconst_1      
    12: ladd          
    13: ldc2_w        #96         // -2
    16: land          
    17: lconst_0      
    18: lcmp          
    19: ifeq          27
    22: aload_0       
    23: invokevirtual #22         // invalidInput:()java.lang.RuntimeException
    26: athrow        
    27: return        
   <|@
end_bytecodes
begin_cfg
  name "After LSStackSlotAllocator"
  begin_block
    name "B0"
    from_bci -1
    to_bci -1
    predecessors 
    successors 
    xhandlers
    flags 
    probability 4607182418800017408
    begin_IR
      LIR
      nr    0  <|@ instruction [rsi|QWORD[.], rdx|QWORD, rbp|QWORD] = LABEL alignment: 0 numbPhis: 0 label: ? <|@ <|@
      nr    2  <|@ instruction NOP <|@ <|@
      nr    4  <|@ instruction NOP <|@ <|@
      nr    6  <|@ instruction NOP <|@ <|@
      nr    8  <|@ instruction NOP <|@ <|@
      nr   10  <|@ instruction NOP <|@ <|@
      nr   12  <|@ instruction NOP <|@ <|@
      nr   14  <|@ instruction NOP <|@ <|@
      nr   16  <|@ instruction NOP <|@ <|@
      nr   18  <|@ instruction NOP <|@ <|@
      nr   22  <|@ instruction [] = HOTSPOTLOCKSTACK frameMapBuilder: jdk.graal.compiler.hotspot.amd64.AMD64HotSpotFrameMapBuilder@e58d03c slotKind: QWORD <|@ <|@
      nr   24  <|@ instruction RETURN (savedRbp: rbp|QWORD, value: -) isStub: false requiresReservedStackAccessCheck: false thread: r15 scratchForSafepointOnReturn: rcx config: jdk.graal.compiler.hotspot.GraalHotSpotVMConfig@4817c460 <|@ <|@
    end_IR
  end_block
end_cfg
begin_bytecodes
     0: getstatic     #2          // ADDRESS_SIZE:int
     3: iconst_4      
     4: if_icmpne     27
     7: lload_1       
     8: bipush        32
    10: lshr          
    11: lconst_1      
    12: ladd          
    13: ldc2_w        #96         // -2
    16: land          
    17: lconst_0      
    18: lcmp          
    19: ifeq          27
    22: aload_0       
    23: invokevirtual #22         // invalidInput:()java.lang.RuntimeException
    26: athrow        
    27: return        
   <|@
end_bytecodes
begin_cfg
  name "After AllocationStage"
  begin_block
    name "B0"
    from_bci -1
    to_bci -1
    predecessors 
    successors 
    xhandlers
    flags 
    probability 4607182418800017408
    begin_IR
      LIR
      nr    0  <|@ instruction [rsi|QWORD[.], rdx|QWORD, rbp|QWORD] = LABEL alignment: 0 numbPhis: 0 label: ? <|@ <|@
      nr    2  <|@ instruction NOP <|@ <|@
      nr    4  <|@ instruction NOP <|@ <|@
      nr    6  <|@ instruction NOP <|@ <|@
      nr    8  <|@ instruction NOP <|@ <|@
      nr   10  <|@ instruction NOP <|@ <|@
      nr   12  <|@ instruction NOP <|@ <|@
      nr   14  <|@ instruction NOP <|@ <|@
      nr   16  <|@ instruction NOP <|@ <|@
      nr   18  <|@ instruction NOP <|@ <|@
      nr   22  <|@ instruction [] = HOTSPOTLOCKSTACK frameMapBuilder: jdk.graal.compiler.hotspot.amd64.AMD64HotSpotFrameMapBuilder@e58d03c slotKind: QWORD <|@ <|@
      nr   24  <|@ instruction RETURN (savedRbp: rbp|QWORD, value: -) isStub: false requiresReservedStackAccessCheck: false thread: r15 scratchForSafepointOnReturn: rcx config: jdk.graal.compiler.hotspot.GraalHotSpotVMConfig@4817c460 <|@ <|@
    end_IR
  end_block
end_cfg
begin_bytecodes
     0: getstatic     #2          // ADDRESS_SIZE:int
     3: iconst_4      
     4: if_icmpne     27
     7: lload_1       
     8: bipush        32
    10: lshr          
    11: lconst_1      
    12: ladd          
    13: ldc2_w        #96         // -2
    16: land          
    17: lconst_0      
    18: lcmp          
    19: ifeq          27
    22: aload_0       
    23: invokevirtual #22         // invalidInput:()java.lang.RuntimeException
    26: athrow        
    27: return        
   <|@
end_bytecodes
begin_cfg
  name "After EdgeMoveOptimizer"
  begin_block
    name "B0"
    from_bci -1
    to_bci -1
    predecessors 
    successors 
    xhandlers
    flags 
    probability 4607182418800017408
    begin_IR
      LIR
      nr    0  <|@ instruction [rsi|QWORD[.], rdx|QWORD, rbp|QWORD] = LABEL alignment: 0 numbPhis: 0 label: ? <|@ <|@
      nr    2  <|@ instruction NOP <|@ <|@
      nr    4  <|@ instruction NOP <|@ <|@
      nr    6  <|@ instruction NOP <|@ <|@
      nr    8  <|@ instruction NOP <|@ <|@
      nr   10  <|@ instruction NOP <|@ <|@
      nr   12  <|@ instruction NOP <|@ <|@
      nr   14  <|@ instruction NOP <|@ <|@
      nr   16  <|@ instruction NOP <|@ <|@
      nr   18  <|@ instruction NOP <|@ <|@
      nr   22  <|@ instruction [] = HOTSPOTLOCKSTACK frameMapBuilder: jdk.graal.compiler.hotspot.amd64.AMD64HotSpotFrameMapBuilder@e58d03c slotKind: QWORD <|@ <|@
      nr   24  <|@ instruction RETURN (savedRbp: rbp|QWORD, value: -) isStub: false requiresReservedStackAccessCheck: false thread: r15 scratchForSafepointOnReturn: rcx config: jdk.graal.compiler.hotspot.GraalHotSpotVMConfig@4817c460 <|@ <|@
    end_IR
  end_block
end_cfg
begin_bytecodes
     0: getstatic     #2          // ADDRESS_SIZE:int
     3: iconst_4      
     4: if_icmpne     27
     7: lload_1       
     8: bipush        32
    10: lshr          
    11: lconst_1      
    12: ladd          
    13: ldc2_w        #96         // -2
    16: land          
    17: lconst_0      
    18: lcmp          
    19: ifeq          27
    22: aload_0       
    23: invokevirtual #22         // invalidInput:()java.lang.RuntimeException
    26: athrow        
    27: return        
   <|@
end_bytecodes
begin_cfg
  name "After RedundantMoveElimination"
  begin_block
    name "B0"
    from_bci -1
    to_bci -1
    predecessors 
    successors 
    xhandlers
    flags 
    probability 4607182418800017408
    begin_IR
      LIR
      nr    0  <|@ instruction [rsi|QWORD[.], rdx|QWORD, rbp|QWORD] = LABEL alignment: 0 numbPhis: 0 label: ? <|@ <|@
      nr    2  <|@ instruction NOP <|@ <|@
      nr    4  <|@ instruction NOP <|@ <|@
      nr    6  <|@ instruction NOP <|@ <|@
      nr    8  <|@ instruction NOP <|@ <|@
      nr   10  <|@ instruction NOP <|@ <|@
      nr   12  <|@ instruction NOP <|@ <|@
      nr   14  <|@ instruction NOP <|@ <|@
      nr   16  <|@ instruction NOP <|@ <|@
      nr   18  <|@ instruction NOP <|@ <|@
      nr   22  <|@ instruction [] = HOTSPOTLOCKSTACK frameMapBuilder: jdk.graal.compiler.hotspot.amd64.AMD64HotSpotFrameMapBuilder@e58d03c slotKind: QWORD <|@ <|@
      nr   24  <|@ instruction RETURN (savedRbp: rbp|QWORD, value: -) isStub: false requiresReservedStackAccessCheck: false thread: r15 scratchForSafepointOnReturn: rcx config: jdk.graal.compiler.hotspot.GraalHotSpotVMConfig@4817c460 <|@ <|@
    end_IR
  end_block
end_cfg
begin_bytecodes
     0: getstatic     #2          // ADDRESS_SIZE:int
     3: iconst_4      
     4: if_icmpne     27
     7: lload_1       
     8: bipush        32
    10: lshr          
    11: lconst_1      
    12: ladd          
    13: ldc2_w        #96         // -2
    16: land          
    17: lconst_0      
    18: lcmp          
    19: ifeq          27
    22: aload_0       
    23: invokevirtual #22         // invalidInput:()java.lang.RuntimeException
    26: athrow        
    27: return        
   <|@
end_bytecodes
begin_cfg
  name "After NullCheckOptimizer"
  begin_block
    name "B0"
    from_bci -1
    to_bci -1
    predecessors 
    successors 
    xhandlers
    flags 
    probability 4607182418800017408
    begin_IR
      LIR
      nr    0  <|@ instruction [rsi|QWORD[.], rdx|QWORD, rbp|QWORD] = LABEL alignment: 0 numbPhis: 0 label: ? <|@ <|@
      nr    2  <|@ instruction NOP <|@ <|@
      nr    4  <|@ instruction NOP <|@ <|@
      nr    6  <|@ instruction NOP <|@ <|@
      nr    8  <|@ instruction NOP <|@ <|@
      nr   10  <|@ instruction NOP <|@ <|@
      nr   12  <|@ instruction NOP <|@ <|@
      nr   14  <|@ instruction NOP <|@ <|@
      nr   16  <|@ instruction NOP <|@ <|@
      nr   18  <|@ instruction NOP <|@ <|@
      nr   22  <|@ instruction [] = HOTSPOTLOCKSTACK frameMapBuilder: jdk.graal.compiler.hotspot.amd64.AMD64HotSpotFrameMapBuilder@e58d03c slotKind: QWORD <|@ <|@
      nr   24  <|@ instruction RETURN (savedRbp: rbp|QWORD, value: -) isStub: false requiresReservedStackAccessCheck: false thread: r15 scratchForSafepointOnReturn: rcx config: jdk.graal.compiler.hotspot.GraalHotSpotVMConfig@4817c460 <|@ <|@
    end_IR
  end_block
end_cfg
begin_bytecodes
     0: getstatic     #2          // ADDRESS_SIZE:int
     3: iconst_4      
     4: if_icmpne     27
     7: lload_1       
     8: bipush        32
    10: lshr          
    11: lconst_1      
    12: ladd          
    13: ldc2_w        #96         // -2
    16: land          
    17: lconst_0      
    18: lcmp          
    19: ifeq          27
    22: aload_0       
    23: invokevirtual #22         // invalidInput:()java.lang.RuntimeException
    26: athrow        
    27: return        
   <|@
end_bytecodes
begin_cfg
  name "After ControlFlowOptimizer"
  begin_block
    name "B0"
    from_bci -1
    to_bci -1
    predecessors 
    successors 
    xhandlers
    flags 
    probability 4607182418800017408
    begin_IR
      LIR
      nr    0  <|@ instruction [rsi|QWORD[.], rdx|QWORD, rbp|QWORD] = LABEL alignment: 0 numbPhis: 0 label: ? <|@ <|@
      nr    2  <|@ instruction NOP <|@ <|@
      nr    4  <|@ instruction NOP <|@ <|@
      nr    6  <|@ instruction NOP <|@ <|@
      nr    8  <|@ instruction NOP <|@ <|@
      nr   10  <|@ instruction NOP <|@ <|@
      nr   12  <|@ instruction NOP <|@ <|@
      nr   14  <|@ instruction NOP <|@ <|@
      nr   16  <|@ instruction NOP <|@ <|@
      nr   18  <|@ instruction NOP <|@ <|@
      nr   22  <|@ instruction [] = HOTSPOTLOCKSTACK frameMapBuilder: jdk.graal.compiler.hotspot.amd64.AMD64HotSpotFrameMapBuilder@e58d03c slotKind: QWORD <|@ <|@
      nr   24  <|@ instruction RETURN (savedRbp: rbp|QWORD, value: -) isStub: false requiresReservedStackAccessCheck: false thread: r15 scratchForSafepointOnReturn: rcx config: jdk.graal.compiler.hotspot.GraalHotSpotVMConfig@4817c460 <|@ <|@
    end_IR
  end_block
end_cfg
begin_bytecodes
     0: getstatic     #2          // ADDRESS_SIZE:int
     3: iconst_4      
     4: if_icmpne     27
     7: lload_1       
     8: bipush        32
    10: lshr          
    11: lconst_1      
    12: ladd          
    13: ldc2_w        #96         // -2
    16: land          
    17: lconst_0      
    18: lcmp          
    19: ifeq          27
    22: aload_0       
    23: invokevirtual #22         // invalidInput:()java.lang.RuntimeException
    26: athrow        
    27: return        
   <|@
end_bytecodes
begin_cfg
  name "After ComputeCodeEmissionOrder"
  begin_block
    name "B0"
    from_bci -1
    to_bci -1
    predecessors 
    successors 
    xhandlers
    flags 
    probability 4607182418800017408
    begin_IR
      LIR
      nr    0  <|@ instruction [rsi|QWORD[.], rdx|QWORD, rbp|QWORD] = LABEL alignment: 0 numbPhis: 0 label: ? <|@ <|@
      nr    2  <|@ instruction NOP <|@ <|@
      nr    4  <|@ instruction NOP <|@ <|@
      nr    6  <|@ instruction NOP <|@ <|@
      nr    8  <|@ instruction NOP <|@ <|@
      nr   10  <|@ instruction NOP <|@ <|@
      nr   12  <|@ instruction NOP <|@ <|@
      nr   14  <|@ instruction NOP <|@ <|@
      nr   16  <|@ instruction NOP <|@ <|@
      nr   18  <|@ instruction NOP <|@ <|@
      nr   22  <|@ instruction [] = HOTSPOTLOCKSTACK frameMapBuilder: jdk.graal.compiler.hotspot.amd64.AMD64HotSpotFrameMapBuilder@e58d03c slotKind: QWORD <|@ <|@
      nr   24  <|@ instruction RETURN (savedRbp: rbp|QWORD, value: -) isStub: false requiresReservedStackAccessCheck: false thread: r15 scratchForSafepointOnReturn: rcx config: jdk.graal.compiler.hotspot.GraalHotSpotVMConfig@4817c460 <|@ <|@
    end_IR
  end_block
end_cfg
begin_bytecodes
     0: getstatic     #2          // ADDRESS_SIZE:int
     3: iconst_4      
     4: if_icmpne     27
     7: lload_1       
     8: bipush        32
    10: lshr          
    11: lconst_1      
    12: ladd          
    13: ldc2_w        #96         // -2
    16: land          
    17: lconst_0      
    18: lcmp          
    19: ifeq          27
    22: aload_0       
    23: invokevirtual #22         // invalidInput:()java.lang.RuntimeException
    26: athrow        
    27: return        
   <|@
end_bytecodes
begin_cfg
  name "After StackMoveOptimization"
  begin_block
    name "B0"
    from_bci -1
    to_bci -1
    predecessors 
    successors 
    xhandlers
    flags 
    probability 4607182418800017408
    begin_IR
      LIR
      nr    0  <|@ instruction [rsi|QWORD[.], rdx|QWORD, rbp|QWORD] = LABEL alignment: 0 numbPhis: 0 label: ? <|@ <|@
      nr    2  <|@ instruction NOP <|@ <|@
      nr    4  <|@ instruction NOP <|@ <|@
      nr    6  <|@ instruction NOP <|@ <|@
      nr    8  <|@ instruction NOP <|@ <|@
      nr   10  <|@ instruction NOP <|@ <|@
      nr   12  <|@ instruction NOP <|@ <|@
      nr   14  <|@ instruction NOP <|@ <|@
      nr   16  <|@ instruction NOP <|@ <|@
      nr   18  <|@ instruction NOP <|@ <|@
      nr   22  <|@ instruction [] = HOTSPOTLOCKSTACK frameMapBuilder: jdk.graal.compiler.hotspot.amd64.AMD64HotSpotFrameMapBuilder@e58d03c slotKind: QWORD <|@ <|@
      nr   24  <|@ instruction RETURN (savedRbp: rbp|QWORD, value: -) isStub: false requiresReservedStackAccessCheck: false thread: r15 scratchForSafepointOnReturn: rcx config: jdk.graal.compiler.hotspot.GraalHotSpotVMConfig@4817c460 <|@ <|@
    end_IR
  end_block
end_cfg
begin_bytecodes
     0: getstatic     #2          // ADDRESS_SIZE:int
     3: iconst_4      
     4: if_icmpne     27
     7: lload_1       
     8: bipush        32
    10: lshr          
    11: lconst_1      
    12: ladd          
    13: ldc2_w        #96         // -2
    16: land          
    17: lconst_0      
    18: lcmp          
    19: ifeq          27
    22: aload_0       
    23: invokevirtual #22         // invalidInput:()java.lang.RuntimeException
    26: athrow        
    27: return        
   <|@
end_bytecodes
begin_cfg
  name "After PostAllocationOptimizationStage"
  begin_block
    name "B0"
    from_bci -1
    to_bci -1
    predecessors 
    successors 
    xhandlers
    flags 
    probability 4607182418800017408
    begin_IR
      LIR
      nr    0  <|@ instruction [rsi|QWORD[.], rdx|QWORD, rbp|QWORD] = LABEL alignment: 0 numbPhis: 0 label: ? <|@ <|@
      nr    2  <|@ instruction NOP <|@ <|@
      nr    4  <|@ instruction NOP <|@ <|@
      nr    6  <|@ instruction NOP <|@ <|@
      nr    8  <|@ instruction NOP <|@ <|@
      nr   10  <|@ instruction NOP <|@ <|@
      nr   12  <|@ instruction NOP <|@ <|@
      nr   14  <|@ instruction NOP <|@ <|@
      nr   16  <|@ instruction NOP <|@ <|@
      nr   18  <|@ instruction NOP <|@ <|@
      nr   22  <|@ instruction [] = HOTSPOTLOCKSTACK frameMapBuilder: jdk.graal.compiler.hotspot.amd64.AMD64HotSpotFrameMapBuilder@e58d03c slotKind: QWORD <|@ <|@
      nr   24  <|@ instruction RETURN (savedRbp: rbp|QWORD, value: -) isStub: false requiresReservedStackAccessCheck: false thread: r15 scratchForSafepointOnReturn: rcx config: jdk.graal.compiler.hotspot.GraalHotSpotVMConfig@4817c460 <|@ <|@
    end_IR
  end_block
end_cfg
begin_bytecodes
     0: getstatic     #2          // ADDRESS_SIZE:int
     3: iconst_4      
     4: if_icmpne     27
     7: lload_1       
     8: bipush        32
    10: lshr          
    11: lconst_1      
    12: ladd          
    13: ldc2_w        #96         // -2
    16: land          
    17: lconst_0      
    18: lcmp          
    19: ifeq          27
    22: aload_0       
    23: invokevirtual #22         // invalidInput:()java.lang.RuntimeException
    26: athrow        
    27: return        
   <|@
end_bytecodes
begin_cfg
  name "After LocationMarker"
  begin_block
    name "B0"
    from_bci -1
    to_bci -1
    predecessors 
    successors 
    xhandlers
    flags 
    probability 4607182418800017408
    begin_IR
      LIR
      nr    0  <|@ instruction [rsi|QWORD[.], rdx|QWORD, rbp|QWORD] = LABEL alignment: 0 numbPhis: 0 label: ? <|@ <|@
      nr    2  <|@ instruction NOP <|@ <|@
      nr    4  <|@ instruction NOP <|@ <|@
      nr    6  <|@ instruction NOP <|@ <|@
      nr    8  <|@ instruction NOP <|@ <|@
      nr   10  <|@ instruction NOP <|@ <|@
      nr   12  <|@ instruction NOP <|@ <|@
      nr   14  <|@ instruction NOP <|@ <|@
      nr   16  <|@ instruction NOP <|@ <|@
      nr   18  <|@ instruction NOP <|@ <|@
      nr   22  <|@ instruction [] = HOTSPOTLOCKSTACK frameMapBuilder: jdk.graal.compiler.hotspot.amd64.AMD64HotSpotFrameMapBuilder@e58d03c slotKind: QWORD <|@ <|@
      nr   24  <|@ instruction RETURN (savedRbp: rbp|QWORD, value: -) isStub: false requiresReservedStackAccessCheck: false thread: r15 scratchForSafepointOnReturn: rcx config: jdk.graal.compiler.hotspot.GraalHotSpotVMConfig@4817c460 <|@ <|@
    end_IR
  end_block
end_cfg
begin_bytecodes
     0: getstatic     #2          // ADDRESS_SIZE:int
     3: iconst_4      
     4: if_icmpne     27
     7: lload_1       
     8: bipush        32
    10: lshr          
    11: lconst_1      
    12: ladd          
    13: ldc2_w        #96         // -2
    16: land          
    17: lconst_0      
    18: lcmp          
    19: ifeq          27
    22: aload_0       
    23: invokevirtual #22         // invalidInput:()java.lang.RuntimeException
    26: athrow        
    27: return        
   <|@
end_bytecodes
begin_cfg
  name "After FinalCodeAnalysisStage"
  begin_block
    name "B0"
    from_bci -1
    to_bci -1
    predecessors 
    successors 
    xhandlers
    flags 
    probability 4607182418800017408
    begin_IR
      LIR
      nr    0  <|@ instruction [rsi|QWORD[.], rdx|QWORD, rbp|QWORD] = LABEL alignment: 0 numbPhis: 0 label: ? <|@ <|@
      nr    2  <|@ instruction NOP <|@ <|@
      nr    4  <|@ instruction NOP <|@ <|@
      nr    6  <|@ instruction NOP <|@ <|@
      nr    8  <|@ instruction NOP <|@ <|@
      nr   10  <|@ instruction NOP <|@ <|@
      nr   12  <|@ instruction NOP <|@ <|@
      nr   14  <|@ instruction NOP <|@ <|@
      nr   16  <|@ instruction NOP <|@ <|@
      nr   18  <|@ instruction NOP <|@ <|@
      nr   22  <|@ instruction [] = HOTSPOTLOCKSTACK frameMapBuilder: jdk.graal.compiler.hotspot.amd64.AMD64HotSpotFrameMapBuilder@e58d03c slotKind: QWORD <|@ <|@
      nr   24  <|@ instruction RETURN (savedRbp: rbp|QWORD, value: -) isStub: false requiresReservedStackAccessCheck: false thread: r15 scratchForSafepointOnReturn: rcx config: jdk.graal.compiler.hotspot.GraalHotSpotVMConfig@4817c460 <|@ <|@
    end_IR
  end_block
end_cfg
begin_bytecodes
     0: getstatic     #2          // ADDRESS_SIZE:int
     3: iconst_4      
     4: if_icmpne     27
     7: lload_1       
     8: bipush        32
    10: lshr          
    11: lconst_1      
    12: ladd          
    13: ldc2_w        #96         // -2
    16: land          
    17: lconst_0      
    18: lcmp          
    19: ifeq          27
    22: aload_0       
    23: invokevirtual #22         // invalidInput:()java.lang.RuntimeException
    26: athrow        
    27: return        
   <|@
end_bytecodes
begin_cfg
  name "After code generation"
end_cfg
begin_nmethod
  <<<HexCodeFile
  Platform AMD64 64  <||@
  HexCode 0 448b560849bc0000002b787f00004d03d44d33e4493bc20f85e3ffffff66669089842400c0feff4883ec189041817f20000000000f851b0000009090909090909090904883c418493ba7500400000f870e000000c348896c2410e800000000ebd9f4488d0ddeffffff49898f68040000e98bfffffff4e800000000f4e800000000f4  <||@
  Comment 0 UNVERIFIED_ENTRY  <||@
  Comment 23 {Field[name=CompilerToVM::Data::SharedRuntime_ic_miss_stub, type=address, offset=0, address=0x7f78b20335c8, value=140155947602048]:0x7f7899785080}  <||@
  Comment 32 [stack overflow check]  <||@
  Comment 32 VERIFIED_ENTRY  <||@
  Comment 44 FRAME_COMPLETE  <||@
  Comment 44 ENTRY_BARRIER_PATCH  <||@
  Comment 58 block B0 null  <||@
  Comment 58 0 [rsi|QWORD[.], rdx|QWORD, rbp|QWORD] = LABEL alignment: 0 numbPhis: 0 label: ?  <||@
  Comment 58 2 NOP  <||@
  Comment 59 4 NOP  <||@
  Comment 60 6 NOP  <||@
  Comment 61 8 NOP  <||@
  Comment 62 10 NOP  <||@
  Comment 63 12 NOP  <||@
  Comment 64 14 NOP  <||@
  Comment 65 16 NOP  <||@
  Comment 66 18 NOP  <||@
  Comment 67 22 [] = HOTSPOTLOCKSTACK frameMapBuilder: jdk.graal.compiler.hotspot.amd64.AMD64HotSpotFrameMapBuilder@e58d03c slotKind: QWORD  <||@
  Comment 67 24 RETURN (savedRbp: rbp|QWORD, value: -) isStub: false requiresReservedStackAccessCheck: false thread: r15 scratchForSafepointOnReturn: rcx config: jdk.graal.compiler.hotspot.GraalHotSpotVMConfig@4817c460  <||@
  Comment 71 POLL_RETURN_FAR  <||@
  Comment 90 {Field[name=CompilerToVM::Data::nmethod_entry_barrier, type=address, offset=0, address=0x7f78b2033598, value=140155947495968]:0x7f789976b220}  <||@
  Comment 112 {Field[name=CompilerToVM::Data::SharedRuntime_polling_page_return_handler, type=address, offset=0, address=0x7f78b20335a0, value=140155947630592]:0x7f789978c000}  <||@
  Comment 118 {Stub<ExceptionHandlerStub.exceptionHandler>@0x7f78998c5300:CallingConvention[rax|QWORD[.], rdx|QWORD]:CallingConvention[rax|QWORD[.], rdx|QWORD]; temps=rdi|ILLEGAL,xmm14|ILLEGAL,xmm15|ILLEGAL,xmm12|ILLEGAL,xmm13|ILLEGAL,xmm10|ILLEGAL,xmm11|ILLEGAL,xmm7|ILLEGAL,xmm8|ILLEGAL,xmm9|ILLEGAL,xmm0|ILLEGAL,xmm1|ILLEGAL,xmm2|ILLEGAL,xmm3|ILLEGAL,xmm4|ILLEGAL,xmm5|ILLEGAL,xmm6|ILLEGAL,rax|ILLEGAL,rcx|ILLEGAL,rdx|ILLEGAL,rsi|ILLEGAL,r8|ILLEGAL,r9|ILLEGAL,r10|ILLEGAL,r11|ILLEGAL}  <||@
  Comment 118 EXCEPTION_HANDLER_ENTRY  <||@
  Comment 124 {Field[name=CompilerToVM::Data::SharedRuntime_deopt_blob_unpack, type=address, offset=0, address=0x7f78b20335b8, value=140155947626272]:0x7f789978af20}  <||@
  Comment 124 DEOPT_HANDLER_ENTRY  <||@
  HexCodeFile>>> <|@
end_nmethod
begin_compilation
  name " HotSpotCompilation-9202[jdk.internal.misc.Unsafe.checkNativeAddress(long)]"
  method "HotSpotCompilation-9202[jdk.internal.misc.Unsafe.checkNativeAddress(long)]"
  date 1724269765444
end_compilation
begin_cfg
  name "After code installation"
end_cfg
begin_nmethod
  <<<HexCodeFile
  Platform AMD64 64  <||@
  HexCode 7f789af7da00 448b560849bc0000002b787f00004d03d44d33e4493bc20f85637680fe66669089842400c0feff4883ec189041817f20030000000f851b0000009090909090909090904883c418493ba7500400000f870e000000c348896c2410e8c1d77efeebd9f4488d0ddeffffff49898f68040000e98be580fef4e8857894fef4e89fd480fef4f4f4f4f4f4f4  <||@
  Comment 0 UNVERIFIED_ENTRY  <||@
  Comment 23 {Field[name=CompilerToVM::Data::SharedRuntime_ic_miss_stub, type=address, offset=0, address=0x7f78b20335c8, value=140155947602048]:0x7f7899785080}  <||@
  Comment 32 [stack overflow check]  <||@
  Comment 32 VERIFIED_ENTRY  <||@
  Comment 44 FRAME_COMPLETE  <||@
  Comment 44 ENTRY_BARRIER_PATCH  <||@
  Comment 58 block B0 null  <||@
  Comment 58 0 [rsi|QWORD[.], rdx|QWORD, rbp|QWORD] = LABEL alignment: 0 numbPhis: 0 label: ?  <||@
  Comment 58 2 NOP  <||@
  Comment 59 4 NOP  <||@
  Comment 60 6 NOP  <||@
  Comment 61 8 NOP  <||@
  Comment 62 10 NOP  <||@
  Comment 63 12 NOP  <||@
  Comment 64 14 NOP  <||@
  Comment 65 16 NOP  <||@
  Comment 66 18 NOP  <||@
  Comment 67 22 [] = HOTSPOTLOCKSTACK frameMapBuilder: jdk.graal.compiler.hotspot.amd64.AMD64HotSpotFrameMapBuilder@e58d03c slotKind: QWORD  <||@
  Comment 67 24 RETURN (savedRbp: rbp|QWORD, value: -) isStub: false requiresReservedStackAccessCheck: false thread: r15 scratchForSafepointOnReturn: rcx config: jdk.graal.compiler.hotspot.GraalHotSpotVMConfig@4817c460  <||@
  Comment 71 POLL_RETURN_FAR  <||@
  Comment 90 {Field[name=CompilerToVM::Data::nmethod_entry_barrier, type=address, offset=0, address=0x7f78b2033598, value=140155947495968]:0x7f789976b220}  <||@
  Comment 112 {Field[name=CompilerToVM::Data::SharedRuntime_polling_page_return_handler, type=address, offset=0, address=0x7f78b20335a0, value=140155947630592]:0x7f789978c000}  <||@
  Comment 118 {Stub<ExceptionHandlerStub.exceptionHandler>@0x7f78998c5300:CallingConvention[rax|QWORD[.], rdx|QWORD]:CallingConvention[rax|QWORD[.], rdx|QWORD]; temps=rdi|ILLEGAL,xmm14|ILLEGAL,xmm15|ILLEGAL,xmm12|ILLEGAL,xmm13|ILLEGAL,xmm10|ILLEGAL,xmm11|ILLEGAL,xmm7|ILLEGAL,xmm8|ILLEGAL,xmm9|ILLEGAL,xmm0|ILLEGAL,xmm1|ILLEGAL,xmm2|ILLEGAL,xmm3|ILLEGAL,xmm4|ILLEGAL,xmm5|ILLEGAL,xmm6|ILLEGAL,rax|ILLEGAL,rcx|ILLEGAL,rdx|ILLEGAL,rsi|ILLEGAL,r8|ILLEGAL,r9|ILLEGAL,r10|ILLEGAL,r11|ILLEGAL}  <||@
  Comment 118 EXCEPTION_HANDLER_ENTRY  <||@
  Comment 124 {Field[name=CompilerToVM::Data::SharedRuntime_deopt_blob_unpack, type=address, offset=0, address=0x7f78b20335b8, value=140155947626272]:0x7f789978af20}  <||@
  Comment 124 DEOPT_HANDLER_ENTRY  <||@
  HexCodeFile>>> <|@
end_nmethod
