begin_compilation
  name " HotSpotCompilation-5326[jdk.internal.misc.Blocker.end(long)]"
  method "HotSpotCompilation-5326[jdk.internal.misc.Blocker.end(long)]"
  date 1724269741062
end_compilation
begin_cfg
  name "Final HIR schedule"
  begin_block
    name "B0"
    from_bci -1
    to_bci -1
    predecessors 
    successors "B1" "B2" 
    xhandlers
    flags 
    probability 4607182418800017408
    begin_IR
      HIR
f <@#|@fixed with next>@ <|@
tid v0 <|@
d <@d|@=== Debug Properties ===
hasSpeculationFence: false
stamp: void
=== Inputs ===
stateAfter: - 
=== Succesors ===
next: v12 
=== Usages ===
=== Predecessor ===
- >@ <|@
instruction <@StartNode|@jdk.graal.compiler.nodes.StartNode>@ stateAfter: - #next: v12  <|@  <|@
f <@~|@floating>@ <|@
tid j1 <|@
d <@d|@=== Debug Properties ===
index: 0
stamp: i64
uncheckedStamp: [null]
=== Inputs ===
=== Succesors ===
=== Usages ===
?2 v6 
=== Predecessor ===
- >@ <|@
instruction <@Parameter|@jdk.graal.compiler.nodes.ParameterNode>@  <|@  <|@
f <@~|@floating>@ <|@
tid j3 <|@
d <@d|@=== Debug Properties ===
isDefaultStable: false
nodeSourcePosition: at jdk.internal.misc.Blocker.end(Blocker.java:102) [bci: 1]
rawvalue: 0
stableDimension: 0
stamp: i64 [0]
stampKind: i64
value: long[0|0x0]
=== Inputs ===
=== Succesors ===
=== Usages ===
v6 
=== Predecessor ===
- >@ <|@
instruction <@Constant|@jdk.graal.compiler.nodes.ConstantNode>@  <|@  <|@
f <@~|@floating>@ <|@
tid v6 <|@
d <@d|@=== Debug Properties ===
condition: LT
nodeSourcePosition: at jdk.internal.misc.Blocker.end(Blocker.java:102) [bci: 3]
op: jdk.graal.compiler.nodes.calc.IntegerLessThanNode$LessThanOp@406e677e
stamp: void
unorderedIsTrue: false
=== Inputs ===
x: j1 
y: j3 
=== Succesors ===
=== Usages ===
v12 
=== Predecessor ===
- >@ <|@
instruction <@<|@jdk.graal.compiler.nodes.calc.IntegerLessThanNode>@ x: j1 y: j3  <|@  <|@
f <@*|@fixed>@ <|@
tid v12 <|@
d <@d|@=== Debug Properties ===
nodeSourcePosition: at jdk.internal.misc.Blocker.end(Blocker.java:102) [bci: 3]
profileData: INJECTED designatedSuccessorProbability: 1.0
stamp: void
=== Inputs ===
condition: v6 
=== Succesors ===
trueSuccessor: v10 
falseSuccessor: v11 
=== Usages ===
=== Predecessor ===
v0 >@ <|@
instruction <@If|@jdk.graal.compiler.nodes.IfNode>@ condition: v6 #trueSuccessor: v10 #falseSuccessor: v11  <|@  <|@
    end_IR
  end_block
  begin_block
    name "B1"
    from_bci -1
    to_bci -1
    predecessors "B0" 
    successors 
    xhandlers
    flags 
    probability 4607182418800017408
    begin_IR
      HIR
f <@#|@fixed with next>@ <|@
tid v10 <|@
d <@d|@=== Debug Properties ===
hasSpeculationFence: false
nodeSourcePosition: at jdk.internal.misc.Blocker.end(Blocker.java:108) [bci: 70]
stamp: void
=== Inputs ===
=== Succesors ===
next: v8 
=== Usages ===
=== Predecessor ===
v12 >@ <|@
instruction <@Begin|@jdk.graal.compiler.nodes.BeginNode>@ #next: v8  <|@  <|@
f <@*|@fixed>@ <|@
tid v8 <|@
d <@d|@=== Debug Properties ===
nodeSourcePosition: at jdk.internal.misc.Blocker.end(Blocker.java:108) [bci: 70]
stamp: void
=== Inputs ===
memoryMap: - 
result: - 
=== Succesors ===
=== Usages ===
=== Predecessor ===
v10 >@ <|@
instruction <@Return|@jdk.graal.compiler.nodes.ReturnNode>@ memoryMap: - result: -  <|@  <|@
    end_IR
  end_block
  begin_block
    name "B2"
    from_bci -1
    to_bci -1
    predecessors "B0" 
    successors 
    xhandlers
    flags 
    probability 2355382605114769408
    begin_IR
      HIR
f <@#|@fixed with next>@ <|@
tid v11 <|@
d <@d|@=== Debug Properties ===
hasSpeculationFence: false
nodeSourcePosition: at jdk.internal.misc.Blocker.end(Blocker.java:102) [bci: 3]
stamp: void
=== Inputs ===
=== Succesors ===
next: v9 
=== Usages ===
=== Predecessor ===
v12 >@ <|@
instruction <@Begin|@jdk.graal.compiler.nodes.BeginNode>@ #next: v9  <|@  <|@
tid ?2 <|@
d <@d|@=== Debug Properties ===
bci: 0
bytecode: lload_0
code: ResolvedJavaMethodBytecode<Blocker.end(long)>
localsSize: 4
locksSize: 0
sourceFile: Blocker.java
sourceLine: 102
stackSize: 0
stackState: BeforePop
validForDeoptimization: true
=== Inputs ===
outerFrameState: - 
values: j1 
=== Succesors ===
=== Usages ===
v9 
=== Predecessor ===
- >@ <|@
instruction <@FrameState|@jdk.graal.compiler.nodes.FrameState>@ outerFrameState: - values: j1  <|@  <|@
f <@*|@fixed>@ <|@
tid v9 <|@
d <@d|@=== Debug Properties ===
action: InvalidateReprofile
debugId: 0
mayConvertToGuard: true
nodeSourcePosition: at jdk.internal.misc.Blocker.end(Blocker.java:102) [bci: 3]
reason: UnreachedCode
speculation: {0x0000000000000014[index: 0, len: 20, hash: 0x8ecaff6a]: UnreachedCode@6[HotSpotMethod<Blocker.end(long)>, 6]}
stamp: void
=== Inputs ===
stateBefore: ?2 
=== Succesors ===
=== Usages ===
=== Predecessor ===
v11 >@ <|@
instruction <@Deopt|@jdk.graal.compiler.nodes.DeoptimizeNode>@ stateBefore: ?2  <|@  <|@
    end_IR
  end_block
end_cfg
begin_cfg
  name "After LIRGeneration"
  begin_block
    name "B0"
    from_bci -1
    to_bci -1
    predecessors 
    successors "B1" "B2" 
    xhandlers
    flags 
    probability 4607182418800017408
    begin_IR
      LIR
      nr   -1  <|@ instruction [rsi|QWORD, rbp|QWORD] = LABEL alignment: 0 numbPhis: 0 label: ? <|@ <|@
      nr   -1  <|@ instruction stack:16|QWORD = MOVE input: rbp|QWORD moveKind: QWORD <|@ <|@
      nr   -1  <|@ instruction [] = HOTSPOTLOCKSTACK frameMapBuilder: jdk.graal.compiler.hotspot.amd64.AMD64HotSpotFrameMapBuilder@abb5079 slotKind: QWORD <|@ <|@
      nr   -1  <|@ instruction v0|QWORD = MOVE input: rsi|QWORD moveKind: QWORD <|@ <|@
      nr   -1  <|@ instruction TESTBRANCH (x: v0|QWORD, y: v0|QWORD) trueDestinationProbability: 1.0 condition: < trueDestination: B0 -> B1 falseDestination: B0 -> B2 size: QWORD <|@ <|@
    end_IR
  end_block
  begin_block
    name "B1"
    from_bci -1
    to_bci -1
    predecessors "B0" 
    successors 
    xhandlers
    flags 
    probability 4607182418800017408
    begin_IR
      LIR
      nr   -1  <|@ instruction [] = LABEL alignment: 0 numbPhis: 0 label: ? <|@ <|@
      nr   -1  <|@ instruction RETURN (savedRbp: stack:16|QWORD, value: -) isStub: false requiresReservedStackAccessCheck: false thread: r15 scratchForSafepointOnReturn: rcx config: jdk.graal.compiler.hotspot.GraalHotSpotVMConfig@4817c460 <|@ <|@
    end_IR
  end_block
  begin_block
    name "B2"
    from_bci -1
    to_bci -1
    predecessors "B0" 
    successors 
    xhandlers
    flags 
    probability 2355382605114769408
    begin_IR
      LIR
      nr   -1  <|@ instruction [] = LABEL alignment: 0 numbPhis: 0 label: ? <|@ <|@
      nr   -1  <|@ instruction MOV x: [r15|QWORD + 1156] y: -2323 size: DWORD <|@ <|@
      nr   -1  <|@ instruction MOV x: [r15|QWORD + 1168] y: 20 size: QWORD <|@ <|@
      nr   -1  <|@ st <@st|@jdk.internal.misc.Blocker.end(Blocker.java:102) [bci: 0]
locals: v0|QWORD - - - 
>@ <|@ instruction DEOPT info [bci:0] <|@ <|@
    end_IR
  end_block
end_cfg
begin_bytecodes
     0: lload_0       
     1: lconst_0      
     2: lcmp          
     3: iflt          70
     6: getstatic     #9          // $assertionsDisabled:boolean
     9: ifne          51
    12: invokestatic  #4          // currentCarrierThread:()java.lang.Thread
    15: astore_3      
    16: aload_3       
    17: instanceof    #26         // jdk.internal.misc.CarrierThread
    20: ifeq          39
    23: aload_3       
    24: checkcast     #26         // jdk.internal.misc.CarrierThread
    27: astore_2      
    28: aload_2       
    29: invokevirtual #5          // jdk.internal.misc.CarrierThread.inBlocking:()boolean
    32: ifeq          39
    35: iconst_1      
    36: goto          40
    39: iconst_0      
    40: ifne          51
    43: new           #48         // java.lang.AssertionError
    46: dup           
    47: invokespecial #10         // java.lang.AssertionError.<init>:()void
    50: athrow        
    51: invokestatic  #4          // currentCarrierThread:()java.lang.Thread
    54: checkcast     #26         // jdk.internal.misc.CarrierThread
    57: astore_2      
    58: aload_2       
    59: invokevirtual #7          // java.util.concurrent.ForkJoinWorkerThread.getPool:()java.util.concurrent.ForkJoinPool
    62: lload_0       
    63: invokestatic  #13         // jdk.internal.misc.Blocker$ForkJoinPools.endCompensatedBlock:(java.util.concurrent.ForkJoinPool, long)void
    66: aload_2       
    67: invokevirtual #11         // jdk.internal.misc.CarrierThread.endBlocking:()void
    70: return        
   <|@
end_bytecodes
begin_cfg
  name "After LIR generation"
  begin_block
    name "B0"
    from_bci -1
    to_bci -1
    predecessors 
    successors "B1" "B2" 
    xhandlers
    flags 
    probability 4607182418800017408
    begin_IR
      HIR
f <@#|@fixed with next>@ <|@
tid v0 <|@
d <@d|@=== Debug Properties ===
hasSpeculationFence: false
stamp: void
=== Inputs ===
stateAfter: - 
=== Succesors ===
next: v12 
=== Usages ===
=== Predecessor ===
- >@ <|@
instruction <@StartNode|@jdk.graal.compiler.nodes.StartNode>@ stateAfter: - #next: v12  <|@  <|@
f <@~|@floating>@ <|@
tid j1 <|@
result v0|QWORD <|@
d <@d|@=== Debug Properties ===
index: 0
stamp: i64
uncheckedStamp: [null]
=== Inputs ===
=== Succesors ===
=== Usages ===
?2 v6 
=== Predecessor ===
- >@ <|@
instruction <@Parameter|@jdk.graal.compiler.nodes.ParameterNode>@  <|@  <|@
f <@~|@floating>@ <|@
tid j3 <|@
result long[0|0x0] <|@
d <@d|@=== Debug Properties ===
isDefaultStable: false
nodeSourcePosition: at jdk.internal.misc.Blocker.end(Blocker.java:102) [bci: 1]
rawvalue: 0
stableDimension: 0
stamp: i64 [0]
stampKind: i64
value: long[0|0x0]
=== Inputs ===
=== Succesors ===
=== Usages ===
v6 
=== Predecessor ===
- >@ <|@
instruction <@Constant|@jdk.graal.compiler.nodes.ConstantNode>@  <|@  <|@
f <@~|@floating>@ <|@
tid v6 <|@
d <@d|@=== Debug Properties ===
condition: LT
nodeSourcePosition: at jdk.internal.misc.Blocker.end(Blocker.java:102) [bci: 3]
op: jdk.graal.compiler.nodes.calc.IntegerLessThanNode$LessThanOp@406e677e
stamp: void
unorderedIsTrue: false
=== Inputs ===
x: j1 
y: j3 
=== Succesors ===
=== Usages ===
v12 
=== Predecessor ===
- >@ <|@
instruction <@<|@jdk.graal.compiler.nodes.calc.IntegerLessThanNode>@ x: j1 y: j3  <|@  <|@
f <@*|@fixed>@ <|@
tid v12 <|@
d <@d|@=== Debug Properties ===
nodeSourcePosition: at jdk.internal.misc.Blocker.end(Blocker.java:102) [bci: 3]
profileData: INJECTED designatedSuccessorProbability: 1.0
stamp: void
=== Inputs ===
condition: v6 
=== Succesors ===
trueSuccessor: v10 
falseSuccessor: v11 
=== Usages ===
=== Predecessor ===
v0 >@ <|@
instruction <@If|@jdk.graal.compiler.nodes.IfNode>@ condition: v6 #trueSuccessor: v10 #falseSuccessor: v11  <|@  <|@
    end_IR
    begin_IR
      LIR
      nr   -1  <|@ instruction [rsi|QWORD, rbp|QWORD] = LABEL alignment: 0 numbPhis: 0 label: ? <|@ <|@
      nr   -1  <|@ instruction stack:16|QWORD = MOVE input: rbp|QWORD moveKind: QWORD <|@ <|@
      nr   -1  <|@ instruction [] = HOTSPOTLOCKSTACK frameMapBuilder: jdk.graal.compiler.hotspot.amd64.AMD64HotSpotFrameMapBuilder@abb5079 slotKind: QWORD <|@ <|@
      nr   -1  <|@ instruction v0|QWORD = MOVE input: rsi|QWORD moveKind: QWORD <|@ <|@
      nr   -1  <|@ instruction TESTBRANCH (x: v0|QWORD, y: v0|QWORD) trueDestinationProbability: 1.0 condition: < trueDestination: B0 -> B1 falseDestination: B0 -> B2 size: QWORD <|@ <|@
    end_IR
  end_block
  begin_block
    name "B1"
    from_bci -1
    to_bci -1
    predecessors "B0" 
    successors 
    xhandlers
    flags 
    probability 4607182418800017408
    begin_IR
      HIR
f <@#|@fixed with next>@ <|@
tid v10 <|@
d <@d|@=== Debug Properties ===
hasSpeculationFence: false
nodeSourcePosition: at jdk.internal.misc.Blocker.end(Blocker.java:108) [bci: 70]
stamp: void
=== Inputs ===
=== Succesors ===
next: v8 
=== Usages ===
=== Predecessor ===
v12 >@ <|@
instruction <@Begin|@jdk.graal.compiler.nodes.BeginNode>@ #next: v8  <|@  <|@
f <@*|@fixed>@ <|@
tid v8 <|@
d <@d|@=== Debug Properties ===
nodeSourcePosition: at jdk.internal.misc.Blocker.end(Blocker.java:108) [bci: 70]
stamp: void
=== Inputs ===
memoryMap: - 
result: - 
=== Succesors ===
=== Usages ===
=== Predecessor ===
v10 >@ <|@
instruction <@Return|@jdk.graal.compiler.nodes.ReturnNode>@ memoryMap: - result: -  <|@  <|@
    end_IR
    begin_IR
      LIR
      nr   -1  <|@ instruction [] = LABEL alignment: 0 numbPhis: 0 label: ? <|@ <|@
      nr   -1  <|@ instruction RETURN (savedRbp: stack:16|QWORD, value: -) isStub: false requiresReservedStackAccessCheck: false thread: r15 scratchForSafepointOnReturn: rcx config: jdk.graal.compiler.hotspot.GraalHotSpotVMConfig@4817c460 <|@ <|@
    end_IR
  end_block
  begin_block
    name "B2"
    from_bci -1
    to_bci -1
    predecessors "B0" 
    successors 
    xhandlers
    flags 
    probability 2355382605114769408
    begin_IR
      HIR
f <@#|@fixed with next>@ <|@
tid v11 <|@
d <@d|@=== Debug Properties ===
hasSpeculationFence: false
nodeSourcePosition: at jdk.internal.misc.Blocker.end(Blocker.java:102) [bci: 3]
stamp: void
=== Inputs ===
=== Succesors ===
next: v9 
=== Usages ===
=== Predecessor ===
v12 >@ <|@
instruction <@Begin|@jdk.graal.compiler.nodes.BeginNode>@ #next: v9  <|@  <|@
tid ?2 <|@
d <@d|@=== Debug Properties ===
bci: 0
bytecode: lload_0
code: ResolvedJavaMethodBytecode<Blocker.end(long)>
localsSize: 4
locksSize: 0
sourceFile: Blocker.java
sourceLine: 102
stackSize: 0
stackState: BeforePop
validForDeoptimization: true
=== Inputs ===
outerFrameState: - 
values: j1 
=== Succesors ===
=== Usages ===
v9 
=== Predecessor ===
- >@ <|@
instruction <@FrameState|@jdk.graal.compiler.nodes.FrameState>@ outerFrameState: - values: j1  <|@  <|@
f <@*|@fixed>@ <|@
tid v9 <|@
d <@d|@=== Debug Properties ===
action: InvalidateReprofile
debugId: 0
mayConvertToGuard: true
nodeSourcePosition: at jdk.internal.misc.Blocker.end(Blocker.java:102) [bci: 3]
reason: UnreachedCode
speculation: {0x0000000000000014[index: 0, len: 20, hash: 0x8ecaff6a]: UnreachedCode@6[HotSpotMethod<Blocker.end(long)>, 6]}
stamp: void
=== Inputs ===
stateBefore: ?2 
=== Succesors ===
=== Usages ===
=== Predecessor ===
v11 >@ <|@
instruction <@Deopt|@jdk.graal.compiler.nodes.DeoptimizeNode>@ stateBefore: ?2  <|@  <|@
    end_IR
    begin_IR
      LIR
      nr   -1  <|@ instruction [] = LABEL alignment: 0 numbPhis: 0 label: ? <|@ <|@
      nr   -1  <|@ instruction MOV x: [r15|QWORD + 1156] y: -2323 size: DWORD <|@ <|@
      nr   -1  <|@ instruction MOV x: [r15|QWORD + 1168] y: 20 size: QWORD <|@ <|@
      nr   -1  <|@ st <@st|@jdk.internal.misc.Blocker.end(Blocker.java:102) [bci: 0]
locals: v0|QWORD - - - 
>@ <|@ instruction DEOPT info [bci:0] <|@ <|@
    end_IR
  end_block
end_cfg
begin_cfg
  name "After LIRGTSlowdown"
  begin_block
    name "B0"
    from_bci -1
    to_bci -1
    predecessors 
    successors "B1" "B2" 
    xhandlers
    flags 
    probability 4607182418800017408
    begin_IR
      LIR
      nr   -1  <|@ instruction [rsi|QWORD, rbp|QWORD] = LABEL alignment: 0 numbPhis: 0 label: ? <|@ <|@
      nr   -1  <|@ instruction NOP <|@ <|@
      nr   -1  <|@ instruction NOP <|@ <|@
      nr   -1  <|@ instruction NOP <|@ <|@
      nr   -1  <|@ instruction NOP <|@ <|@
      nr   -1  <|@ instruction NOP <|@ <|@
      nr   -1  <|@ instruction NOP <|@ <|@
      nr   -1  <|@ instruction NOP <|@ <|@
      nr   -1  <|@ instruction stack:16|QWORD = MOVE input: rbp|QWORD moveKind: QWORD <|@ <|@
      nr   -1  <|@ instruction [] = HOTSPOTLOCKSTACK frameMapBuilder: jdk.graal.compiler.hotspot.amd64.AMD64HotSpotFrameMapBuilder@abb5079 slotKind: QWORD <|@ <|@
      nr   -1  <|@ instruction v0|QWORD = MOVE input: rsi|QWORD moveKind: QWORD <|@ <|@
      nr   -1  <|@ instruction TESTBRANCH (x: v0|QWORD, y: v0|QWORD) trueDestinationProbability: 1.0 condition: < trueDestination: B0 -> B1 falseDestination: B0 -> B2 size: QWORD <|@ <|@
    end_IR
  end_block
  begin_block
    name "B1"
    from_bci -1
    to_bci -1
    predecessors "B0" 
    successors 
    xhandlers
    flags 
    probability 4607182418800017408
    begin_IR
      LIR
      nr   -1  <|@ instruction [] = LABEL alignment: 0 numbPhis: 0 label: ? <|@ <|@
      nr   -1  <|@ instruction NOP <|@ <|@
      nr   -1  <|@ instruction NOP <|@ <|@
      nr   -1  <|@ instruction NOP <|@ <|@
      nr   -1  <|@ instruction NOP <|@ <|@
      nr   -1  <|@ instruction NOP <|@ <|@
      nr   -1  <|@ instruction NOP <|@ <|@
      nr   -1  <|@ instruction NOP <|@ <|@
      nr   -1  <|@ instruction RETURN (savedRbp: stack:16|QWORD, value: -) isStub: false requiresReservedStackAccessCheck: false thread: r15 scratchForSafepointOnReturn: rcx config: jdk.graal.compiler.hotspot.GraalHotSpotVMConfig@4817c460 <|@ <|@
    end_IR
  end_block
  begin_block
    name "B2"
    from_bci -1
    to_bci -1
    predecessors "B0" 
    successors 
    xhandlers
    flags 
    probability 2355382605114769408
    begin_IR
      LIR
      nr   -1  <|@ instruction [] = LABEL alignment: 0 numbPhis: 0 label: ? <|@ <|@
      nr   -1  <|@ instruction NOP <|@ <|@
      nr   -1  <|@ instruction NOP <|@ <|@
      nr   -1  <|@ instruction NOP <|@ <|@
      nr   -1  <|@ instruction NOP <|@ <|@
      nr   -1  <|@ instruction NOP <|@ <|@
      nr   -1  <|@ instruction NOP <|@ <|@
      nr   -1  <|@ instruction NOP <|@ <|@
      nr   -1  <|@ instruction MOV x: [r15|QWORD + 1156] y: -2323 size: DWORD <|@ <|@
      nr   -1  <|@ instruction MOV x: [r15|QWORD + 1168] y: 20 size: QWORD <|@ <|@
      nr   -1  <|@ st <@st|@jdk.internal.misc.Blocker.end(Blocker.java:102) [bci: 0]
locals: v0|QWORD - - - 
>@ <|@ instruction DEOPT info [bci:0] <|@ <|@
    end_IR
  end_block
end_cfg
begin_bytecodes
     0: lload_0       
     1: lconst_0      
     2: lcmp          
     3: iflt          70
     6: getstatic     #9          // $assertionsDisabled:boolean
     9: ifne          51
    12: invokestatic  #4          // currentCarrierThread:()java.lang.Thread
    15: astore_3      
    16: aload_3       
    17: instanceof    #26         // jdk.internal.misc.CarrierThread
    20: ifeq          39
    23: aload_3       
    24: checkcast     #26         // jdk.internal.misc.CarrierThread
    27: astore_2      
    28: aload_2       
    29: invokevirtual #5          // jdk.internal.misc.CarrierThread.inBlocking:()boolean
    32: ifeq          39
    35: iconst_1      
    36: goto          40
    39: iconst_0      
    40: ifne          51
    43: new           #48         // java.lang.AssertionError
    46: dup           
    47: invokespecial #10         // java.lang.AssertionError.<init>:()void
    50: athrow        
    51: invokestatic  #4          // currentCarrierThread:()java.lang.Thread
    54: checkcast     #26         // jdk.internal.misc.CarrierThread
    57: astore_2      
    58: aload_2       
    59: invokevirtual #7          // java.util.concurrent.ForkJoinWorkerThread.getPool:()java.util.concurrent.ForkJoinPool
    62: lload_0       
    63: invokestatic  #13         // jdk.internal.misc.Blocker$ForkJoinPools.endCompensatedBlock:(java.util.concurrent.ForkJoinPool, long)void
    66: aload_2       
    67: invokevirtual #11         // jdk.internal.misc.CarrierThread.endBlocking:()void
    70: return        
   <|@
end_bytecodes
begin_cfg
  name "After ConstantLoadOptimization"
  begin_block
    name "B0"
    from_bci -1
    to_bci -1
    predecessors 
    successors "B1" "B2" 
    xhandlers
    flags 
    probability 4607182418800017408
    begin_IR
      LIR
      nr   -1  <|@ instruction [rsi|QWORD, rbp|QWORD] = LABEL alignment: 0 numbPhis: 0 label: ? <|@ <|@
      nr   -1  <|@ instruction NOP <|@ <|@
      nr   -1  <|@ instruction NOP <|@ <|@
      nr   -1  <|@ instruction NOP <|@ <|@
      nr   -1  <|@ instruction NOP <|@ <|@
      nr   -1  <|@ instruction NOP <|@ <|@
      nr   -1  <|@ instruction NOP <|@ <|@
      nr   -1  <|@ instruction NOP <|@ <|@
      nr   -1  <|@ instruction stack:16|QWORD = MOVE input: rbp|QWORD moveKind: QWORD <|@ <|@
      nr   -1  <|@ instruction [] = HOTSPOTLOCKSTACK frameMapBuilder: jdk.graal.compiler.hotspot.amd64.AMD64HotSpotFrameMapBuilder@abb5079 slotKind: QWORD <|@ <|@
      nr   -1  <|@ instruction v0|QWORD = MOVE input: rsi|QWORD moveKind: QWORD <|@ <|@
      nr   -1  <|@ instruction TESTBRANCH (x: v0|QWORD, y: v0|QWORD) trueDestinationProbability: 1.0 condition: < trueDestination: B0 -> B1 falseDestination: B0 -> B2 size: QWORD <|@ <|@
    end_IR
  end_block
  begin_block
    name "B1"
    from_bci -1
    to_bci -1
    predecessors "B0" 
    successors 
    xhandlers
    flags 
    probability 4607182418800017408
    begin_IR
      LIR
      nr   -1  <|@ instruction [] = LABEL alignment: 0 numbPhis: 0 label: ? <|@ <|@
      nr   -1  <|@ instruction NOP <|@ <|@
      nr   -1  <|@ instruction NOP <|@ <|@
      nr   -1  <|@ instruction NOP <|@ <|@
      nr   -1  <|@ instruction NOP <|@ <|@
      nr   -1  <|@ instruction NOP <|@ <|@
      nr   -1  <|@ instruction NOP <|@ <|@
      nr   -1  <|@ instruction NOP <|@ <|@
      nr   -1  <|@ instruction RETURN (savedRbp: stack:16|QWORD, value: -) isStub: false requiresReservedStackAccessCheck: false thread: r15 scratchForSafepointOnReturn: rcx config: jdk.graal.compiler.hotspot.GraalHotSpotVMConfig@4817c460 <|@ <|@
    end_IR
  end_block
  begin_block
    name "B2"
    from_bci -1
    to_bci -1
    predecessors "B0" 
    successors 
    xhandlers
    flags 
    probability 2355382605114769408
    begin_IR
      LIR
      nr   -1  <|@ instruction [] = LABEL alignment: 0 numbPhis: 0 label: ? <|@ <|@
      nr   -1  <|@ instruction NOP <|@ <|@
      nr   -1  <|@ instruction NOP <|@ <|@
      nr   -1  <|@ instruction NOP <|@ <|@
      nr   -1  <|@ instruction NOP <|@ <|@
      nr   -1  <|@ instruction NOP <|@ <|@
      nr   -1  <|@ instruction NOP <|@ <|@
      nr   -1  <|@ instruction NOP <|@ <|@
      nr   -1  <|@ instruction MOV x: [r15|QWORD + 1156] y: -2323 size: DWORD <|@ <|@
      nr   -1  <|@ instruction MOV x: [r15|QWORD + 1168] y: 20 size: QWORD <|@ <|@
      nr   -1  <|@ st <@st|@jdk.internal.misc.Blocker.end(Blocker.java:102) [bci: 0]
locals: v0|QWORD - - - 
>@ <|@ instruction DEOPT info [bci:0] <|@ <|@
    end_IR
  end_block
end_cfg
begin_bytecodes
     0: lload_0       
     1: lconst_0      
     2: lcmp          
     3: iflt          70
     6: getstatic     #9          // $assertionsDisabled:boolean
     9: ifne          51
    12: invokestatic  #4          // currentCarrierThread:()java.lang.Thread
    15: astore_3      
    16: aload_3       
    17: instanceof    #26         // jdk.internal.misc.CarrierThread
    20: ifeq          39
    23: aload_3       
    24: checkcast     #26         // jdk.internal.misc.CarrierThread
    27: astore_2      
    28: aload_2       
    29: invokevirtual #5          // jdk.internal.misc.CarrierThread.inBlocking:()boolean
    32: ifeq          39
    35: iconst_1      
    36: goto          40
    39: iconst_0      
    40: ifne          51
    43: new           #48         // java.lang.AssertionError
    46: dup           
    47: invokespecial #10         // java.lang.AssertionError.<init>:()void
    50: athrow        
    51: invokestatic  #4          // currentCarrierThread:()java.lang.Thread
    54: checkcast     #26         // jdk.internal.misc.CarrierThread
    57: astore_2      
    58: aload_2       
    59: invokevirtual #7          // java.util.concurrent.ForkJoinWorkerThread.getPool:()java.util.concurrent.ForkJoinPool
    62: lload_0       
    63: invokestatic  #13         // jdk.internal.misc.Blocker$ForkJoinPools.endCompensatedBlock:(java.util.concurrent.ForkJoinPool, long)void
    66: aload_2       
    67: invokevirtual #11         // jdk.internal.misc.CarrierThread.endBlocking:()void
    70: return        
   <|@
end_bytecodes
begin_cfg
  name "After SaveCalleeSaveRegisters"
  begin_block
    name "B0"
    from_bci -1
    to_bci -1
    predecessors 
    successors "B1" "B2" 
    xhandlers
    flags 
    probability 4607182418800017408
    begin_IR
      LIR
      nr   -1  <|@ instruction [rsi|QWORD, rbp|QWORD] = LABEL alignment: 0 numbPhis: 0 label: ? <|@ <|@
      nr   -1  <|@ instruction NOP <|@ <|@
      nr   -1  <|@ instruction NOP <|@ <|@
      nr   -1  <|@ instruction NOP <|@ <|@
      nr   -1  <|@ instruction NOP <|@ <|@
      nr   -1  <|@ instruction NOP <|@ <|@
      nr   -1  <|@ instruction NOP <|@ <|@
      nr   -1  <|@ instruction NOP <|@ <|@
      nr   -1  <|@ instruction stack:16|QWORD = MOVE input: rbp|QWORD moveKind: QWORD <|@ <|@
      nr   -1  <|@ instruction [] = HOTSPOTLOCKSTACK frameMapBuilder: jdk.graal.compiler.hotspot.amd64.AMD64HotSpotFrameMapBuilder@abb5079 slotKind: QWORD <|@ <|@
      nr   -1  <|@ instruction v0|QWORD = MOVE input: rsi|QWORD moveKind: QWORD <|@ <|@
      nr   -1  <|@ instruction TESTBRANCH (x: v0|QWORD, y: v0|QWORD) trueDestinationProbability: 1.0 condition: < trueDestination: B0 -> B1 falseDestination: B0 -> B2 size: QWORD <|@ <|@
    end_IR
  end_block
  begin_block
    name "B1"
    from_bci -1
    to_bci -1
    predecessors "B0" 
    successors 
    xhandlers
    flags 
    probability 4607182418800017408
    begin_IR
      LIR
      nr   -1  <|@ instruction [] = LABEL alignment: 0 numbPhis: 0 label: ? <|@ <|@
      nr   -1  <|@ instruction NOP <|@ <|@
      nr   -1  <|@ instruction NOP <|@ <|@
      nr   -1  <|@ instruction NOP <|@ <|@
      nr   -1  <|@ instruction NOP <|@ <|@
      nr   -1  <|@ instruction NOP <|@ <|@
      nr   -1  <|@ instruction NOP <|@ <|@
      nr   -1  <|@ instruction NOP <|@ <|@
      nr   -1  <|@ instruction RETURN (savedRbp: stack:16|QWORD, value: -) isStub: false requiresReservedStackAccessCheck: false thread: r15 scratchForSafepointOnReturn: rcx config: jdk.graal.compiler.hotspot.GraalHotSpotVMConfig@4817c460 <|@ <|@
    end_IR
  end_block
  begin_block
    name "B2"
    from_bci -1
    to_bci -1
    predecessors "B0" 
    successors 
    xhandlers
    flags 
    probability 2355382605114769408
    begin_IR
      LIR
      nr   -1  <|@ instruction [] = LABEL alignment: 0 numbPhis: 0 label: ? <|@ <|@
      nr   -1  <|@ instruction NOP <|@ <|@
      nr   -1  <|@ instruction NOP <|@ <|@
      nr   -1  <|@ instruction NOP <|@ <|@
      nr   -1  <|@ instruction NOP <|@ <|@
      nr   -1  <|@ instruction NOP <|@ <|@
      nr   -1  <|@ instruction NOP <|@ <|@
      nr   -1  <|@ instruction NOP <|@ <|@
      nr   -1  <|@ instruction MOV x: [r15|QWORD + 1156] y: -2323 size: DWORD <|@ <|@
      nr   -1  <|@ instruction MOV x: [r15|QWORD + 1168] y: 20 size: QWORD <|@ <|@
      nr   -1  <|@ st <@st|@jdk.internal.misc.Blocker.end(Blocker.java:102) [bci: 0]
locals: v0|QWORD - - - 
>@ <|@ instruction DEOPT info [bci:0] <|@ <|@
    end_IR
  end_block
end_cfg
begin_bytecodes
     0: lload_0       
     1: lconst_0      
     2: lcmp          
     3: iflt          70
     6: getstatic     #9          // $assertionsDisabled:boolean
     9: ifne          51
    12: invokestatic  #4          // currentCarrierThread:()java.lang.Thread
    15: astore_3      
    16: aload_3       
    17: instanceof    #26         // jdk.internal.misc.CarrierThread
    20: ifeq          39
    23: aload_3       
    24: checkcast     #26         // jdk.internal.misc.CarrierThread
    27: astore_2      
    28: aload_2       
    29: invokevirtual #5          // jdk.internal.misc.CarrierThread.inBlocking:()boolean
    32: ifeq          39
    35: iconst_1      
    36: goto          40
    39: iconst_0      
    40: ifne          51
    43: new           #48         // java.lang.AssertionError
    46: dup           
    47: invokespecial #10         // java.lang.AssertionError.<init>:()void
    50: athrow        
    51: invokestatic  #4          // currentCarrierThread:()java.lang.Thread
    54: checkcast     #26         // jdk.internal.misc.CarrierThread
    57: astore_2      
    58: aload_2       
    59: invokevirtual #7          // java.util.concurrent.ForkJoinWorkerThread.getPool:()java.util.concurrent.ForkJoinPool
    62: lload_0       
    63: invokestatic  #13         // jdk.internal.misc.Blocker$ForkJoinPools.endCompensatedBlock:(java.util.concurrent.ForkJoinPool, long)void
    66: aload_2       
    67: invokevirtual #11         // jdk.internal.misc.CarrierThread.endBlocking:()void
    70: return        
   <|@
end_bytecodes
begin_cfg
  name "After PreAllocationOptimizationStage"
  begin_block
    name "B0"
    from_bci -1
    to_bci -1
    predecessors 
    successors "B1" "B2" 
    xhandlers
    flags 
    probability 4607182418800017408
    begin_IR
      LIR
      nr   -1  <|@ instruction [rsi|QWORD, rbp|QWORD] = LABEL alignment: 0 numbPhis: 0 label: ? <|@ <|@
      nr   -1  <|@ instruction NOP <|@ <|@
      nr   -1  <|@ instruction NOP <|@ <|@
      nr   -1  <|@ instruction NOP <|@ <|@
      nr   -1  <|@ instruction NOP <|@ <|@
      nr   -1  <|@ instruction NOP <|@ <|@
      nr   -1  <|@ instruction NOP <|@ <|@
      nr   -1  <|@ instruction NOP <|@ <|@
      nr   -1  <|@ instruction stack:16|QWORD = MOVE input: rbp|QWORD moveKind: QWORD <|@ <|@
      nr   -1  <|@ instruction [] = HOTSPOTLOCKSTACK frameMapBuilder: jdk.graal.compiler.hotspot.amd64.AMD64HotSpotFrameMapBuilder@abb5079 slotKind: QWORD <|@ <|@
      nr   -1  <|@ instruction v0|QWORD = MOVE input: rsi|QWORD moveKind: QWORD <|@ <|@
      nr   -1  <|@ instruction TESTBRANCH (x: v0|QWORD, y: v0|QWORD) trueDestinationProbability: 1.0 condition: < trueDestination: B0 -> B1 falseDestination: B0 -> B2 size: QWORD <|@ <|@
    end_IR
  end_block
  begin_block
    name "B1"
    from_bci -1
    to_bci -1
    predecessors "B0" 
    successors 
    xhandlers
    flags 
    probability 4607182418800017408
    begin_IR
      LIR
      nr   -1  <|@ instruction [] = LABEL alignment: 0 numbPhis: 0 label: ? <|@ <|@
      nr   -1  <|@ instruction NOP <|@ <|@
      nr   -1  <|@ instruction NOP <|@ <|@
      nr   -1  <|@ instruction NOP <|@ <|@
      nr   -1  <|@ instruction NOP <|@ <|@
      nr   -1  <|@ instruction NOP <|@ <|@
      nr   -1  <|@ instruction NOP <|@ <|@
      nr   -1  <|@ instruction NOP <|@ <|@
      nr   -1  <|@ instruction RETURN (savedRbp: stack:16|QWORD, value: -) isStub: false requiresReservedStackAccessCheck: false thread: r15 scratchForSafepointOnReturn: rcx config: jdk.graal.compiler.hotspot.GraalHotSpotVMConfig@4817c460 <|@ <|@
    end_IR
  end_block
  begin_block
    name "B2"
    from_bci -1
    to_bci -1
    predecessors "B0" 
    successors 
    xhandlers
    flags 
    probability 2355382605114769408
    begin_IR
      LIR
      nr   -1  <|@ instruction [] = LABEL alignment: 0 numbPhis: 0 label: ? <|@ <|@
      nr   -1  <|@ instruction NOP <|@ <|@
      nr   -1  <|@ instruction NOP <|@ <|@
      nr   -1  <|@ instruction NOP <|@ <|@
      nr   -1  <|@ instruction NOP <|@ <|@
      nr   -1  <|@ instruction NOP <|@ <|@
      nr   -1  <|@ instruction NOP <|@ <|@
      nr   -1  <|@ instruction NOP <|@ <|@
      nr   -1  <|@ instruction MOV x: [r15|QWORD + 1156] y: -2323 size: DWORD <|@ <|@
      nr   -1  <|@ instruction MOV x: [r15|QWORD + 1168] y: 20 size: QWORD <|@ <|@
      nr   -1  <|@ st <@st|@jdk.internal.misc.Blocker.end(Blocker.java:102) [bci: 0]
locals: v0|QWORD - - - 
>@ <|@ instruction DEOPT info [bci:0] <|@ <|@
    end_IR
  end_block
end_cfg
begin_bytecodes
     0: lload_0       
     1: lconst_0      
     2: lcmp          
     3: iflt          70
     6: getstatic     #9          // $assertionsDisabled:boolean
     9: ifne          51
    12: invokestatic  #4          // currentCarrierThread:()java.lang.Thread
    15: astore_3      
    16: aload_3       
    17: instanceof    #26         // jdk.internal.misc.CarrierThread
    20: ifeq          39
    23: aload_3       
    24: checkcast     #26         // jdk.internal.misc.CarrierThread
    27: astore_2      
    28: aload_2       
    29: invokevirtual #5          // jdk.internal.misc.CarrierThread.inBlocking:()boolean
    32: ifeq          39
    35: iconst_1      
    36: goto          40
    39: iconst_0      
    40: ifne          51
    43: new           #48         // java.lang.AssertionError
    46: dup           
    47: invokespecial #10         // java.lang.AssertionError.<init>:()void
    50: athrow        
    51: invokestatic  #4          // currentCarrierThread:()java.lang.Thread
    54: checkcast     #26         // jdk.internal.misc.CarrierThread
    57: astore_2      
    58: aload_2       
    59: invokevirtual #7          // java.util.concurrent.ForkJoinWorkerThread.getPool:()java.util.concurrent.ForkJoinPool
    62: lload_0       
    63: invokestatic  #13         // jdk.internal.misc.Blocker$ForkJoinPools.endCompensatedBlock:(java.util.concurrent.ForkJoinPool, long)void
    66: aload_2       
    67: invokevirtual #11         // jdk.internal.misc.CarrierThread.endBlocking:()void
    70: return        
   <|@
end_bytecodes
begin_cfg
  name "After MarkBasePointers"
  begin_block
    name "B0"
    from_bci -1
    to_bci -1
    predecessors 
    successors "B1" "B2" 
    xhandlers
    flags 
    probability 4607182418800017408
    begin_IR
      LIR
      nr   -1  <|@ instruction [rsi|QWORD, rbp|QWORD] = LABEL alignment: 0 numbPhis: 0 label: ? <|@ <|@
      nr   -1  <|@ instruction NOP <|@ <|@
      nr   -1  <|@ instruction NOP <|@ <|@
      nr   -1  <|@ instruction NOP <|@ <|@
      nr   -1  <|@ instruction NOP <|@ <|@
      nr   -1  <|@ instruction NOP <|@ <|@
      nr   -1  <|@ instruction NOP <|@ <|@
      nr   -1  <|@ instruction NOP <|@ <|@
      nr   -1  <|@ instruction stack:16|QWORD = MOVE input: rbp|QWORD moveKind: QWORD <|@ <|@
      nr   -1  <|@ instruction [] = HOTSPOTLOCKSTACK frameMapBuilder: jdk.graal.compiler.hotspot.amd64.AMD64HotSpotFrameMapBuilder@abb5079 slotKind: QWORD <|@ <|@
      nr   -1  <|@ instruction v0|QWORD = MOVE input: rsi|QWORD moveKind: QWORD <|@ <|@
      nr   -1  <|@ instruction TESTBRANCH (x: v0|QWORD, y: v0|QWORD) trueDestinationProbability: 1.0 condition: < trueDestination: B0 -> B1 falseDestination: B0 -> B2 size: QWORD <|@ <|@
    end_IR
  end_block
  begin_block
    name "B1"
    from_bci -1
    to_bci -1
    predecessors "B0" 
    successors 
    xhandlers
    flags 
    probability 4607182418800017408
    begin_IR
      LIR
      nr   -1  <|@ instruction [] = LABEL alignment: 0 numbPhis: 0 label: ? <|@ <|@
      nr   -1  <|@ instruction NOP <|@ <|@
      nr   -1  <|@ instruction NOP <|@ <|@
      nr   -1  <|@ instruction NOP <|@ <|@
      nr   -1  <|@ instruction NOP <|@ <|@
      nr   -1  <|@ instruction NOP <|@ <|@
      nr   -1  <|@ instruction NOP <|@ <|@
      nr   -1  <|@ instruction NOP <|@ <|@
      nr   -1  <|@ instruction RETURN (savedRbp: stack:16|QWORD, value: -) isStub: false requiresReservedStackAccessCheck: false thread: r15 scratchForSafepointOnReturn: rcx config: jdk.graal.compiler.hotspot.GraalHotSpotVMConfig@4817c460 <|@ <|@
    end_IR
  end_block
  begin_block
    name "B2"
    from_bci -1
    to_bci -1
    predecessors "B0" 
    successors 
    xhandlers
    flags 
    probability 2355382605114769408
    begin_IR
      LIR
      nr   -1  <|@ instruction [] = LABEL alignment: 0 numbPhis: 0 label: ? <|@ <|@
      nr   -1  <|@ instruction NOP <|@ <|@
      nr   -1  <|@ instruction NOP <|@ <|@
      nr   -1  <|@ instruction NOP <|@ <|@
      nr   -1  <|@ instruction NOP <|@ <|@
      nr   -1  <|@ instruction NOP <|@ <|@
      nr   -1  <|@ instruction NOP <|@ <|@
      nr   -1  <|@ instruction NOP <|@ <|@
      nr   -1  <|@ instruction MOV x: [r15|QWORD + 1156] y: -2323 size: DWORD <|@ <|@
      nr   -1  <|@ instruction MOV x: [r15|QWORD + 1168] y: 20 size: QWORD <|@ <|@
      nr   -1  <|@ st <@st|@live-base-pointers: []
jdk.internal.misc.Blocker.end(Blocker.java:102) [bci: 0]
locals: v0|QWORD - - - 
>@ <|@ instruction DEOPT info [bci:0] <|@ <|@
    end_IR
  end_block
end_cfg
begin_bytecodes
     0: lload_0       
     1: lconst_0      
     2: lcmp          
     3: iflt          70
     6: getstatic     #9          // $assertionsDisabled:boolean
     9: ifne          51
    12: invokestatic  #4          // currentCarrierThread:()java.lang.Thread
    15: astore_3      
    16: aload_3       
    17: instanceof    #26         // jdk.internal.misc.CarrierThread
    20: ifeq          39
    23: aload_3       
    24: checkcast     #26         // jdk.internal.misc.CarrierThread
    27: astore_2      
    28: aload_2       
    29: invokevirtual #5          // jdk.internal.misc.CarrierThread.inBlocking:()boolean
    32: ifeq          39
    35: iconst_1      
    36: goto          40
    39: iconst_0      
    40: ifne          51
    43: new           #48         // java.lang.AssertionError
    46: dup           
    47: invokespecial #10         // java.lang.AssertionError.<init>:()void
    50: athrow        
    51: invokestatic  #4          // currentCarrierThread:()java.lang.Thread
    54: checkcast     #26         // jdk.internal.misc.CarrierThread
    57: astore_2      
    58: aload_2       
    59: invokevirtual #7          // java.util.concurrent.ForkJoinWorkerThread.getPool:()java.util.concurrent.ForkJoinPool
    62: lload_0       
    63: invokestatic  #13         // jdk.internal.misc.Blocker$ForkJoinPools.endCompensatedBlock:(java.util.concurrent.ForkJoinPool, long)void
    66: aload_2       
    67: invokevirtual #11         // jdk.internal.misc.CarrierThread.endBlocking:()void
    70: return        
   <|@
end_bytecodes
begin_cfg
  name "Before register allocation"
  begin_block
    name "B0"
    from_bci -1
    to_bci -1
    predecessors 
    successors "B1" "B2" 
    xhandlers
    flags 
    probability 4607182418800017408
    begin_IR
      LIR
      nr    0  <|@ instruction [rsi|QWORD, rbp|QWORD] = LABEL alignment: 0 numbPhis: 0 label: ? <|@ <|@
      nr    2  <|@ instruction NOP <|@ <|@
      nr    4  <|@ instruction NOP <|@ <|@
      nr    6  <|@ instruction NOP <|@ <|@
      nr    8  <|@ instruction NOP <|@ <|@
      nr   10  <|@ instruction NOP <|@ <|@
      nr   12  <|@ instruction NOP <|@ <|@
      nr   14  <|@ instruction NOP <|@ <|@
      nr   16  <|@ instruction stack:16|QWORD = MOVE input: rbp|QWORD moveKind: QWORD <|@ <|@
      nr   18  <|@ instruction [] = HOTSPOTLOCKSTACK frameMapBuilder: jdk.graal.compiler.hotspot.amd64.AMD64HotSpotFrameMapBuilder@abb5079 slotKind: QWORD <|@ <|@
      nr   20  <|@ instruction v0|QWORD = MOVE input: rsi|QWORD moveKind: QWORD <|@ <|@
      nr   22  <|@ instruction TESTBRANCH (x: v0|QWORD, y: v0|QWORD) trueDestinationProbability: 1.0 condition: < trueDestination: B0 -> B1 falseDestination: B0 -> B2 size: QWORD <|@ <|@
    end_IR
  end_block
  begin_block
    name "B1"
    from_bci -1
    to_bci -1
    predecessors "B0" 
    successors 
    xhandlers
    flags 
    probability 4607182418800017408
    begin_IR
      LIR
      nr   24  <|@ instruction [] = LABEL alignment: 0 numbPhis: 0 label: ? <|@ <|@
      nr   26  <|@ instruction NOP <|@ <|@
      nr   28  <|@ instruction NOP <|@ <|@
      nr   30  <|@ instruction NOP <|@ <|@
      nr   32  <|@ instruction NOP <|@ <|@
      nr   34  <|@ instruction NOP <|@ <|@
      nr   36  <|@ instruction NOP <|@ <|@
      nr   38  <|@ instruction NOP <|@ <|@
      nr   40  <|@ instruction RETURN (savedRbp: stack:16|QWORD, value: -) isStub: false requiresReservedStackAccessCheck: false thread: r15 scratchForSafepointOnReturn: rcx config: jdk.graal.compiler.hotspot.GraalHotSpotVMConfig@4817c460 <|@ <|@
    end_IR
  end_block
  begin_block
    name "B2"
    from_bci -1
    to_bci -1
    predecessors "B0" 
    successors 
    xhandlers
    flags 
    probability 2355382605114769408
    begin_IR
      LIR
      nr   42  <|@ instruction [] = LABEL alignment: 0 numbPhis: 0 label: ? <|@ <|@
      nr   44  <|@ instruction NOP <|@ <|@
      nr   46  <|@ instruction NOP <|@ <|@
      nr   48  <|@ instruction NOP <|@ <|@
      nr   50  <|@ instruction NOP <|@ <|@
      nr   52  <|@ instruction NOP <|@ <|@
      nr   54  <|@ instruction NOP <|@ <|@
      nr   56  <|@ instruction NOP <|@ <|@
      nr   58  <|@ instruction MOV x: [r15|QWORD + 1156] y: -2323 size: DWORD <|@ <|@
      nr   60  <|@ instruction MOV x: [r15|QWORD + 1168] y: 20 size: QWORD <|@ <|@
      nr   62  <|@ st <@st|@live-base-pointers: []
jdk.internal.misc.Blocker.end(Blocker.java:102) [bci: 0]
locals: v0|QWORD - - - 
>@ <|@ instruction DEOPT info [bci:0] <|@ <|@
    end_IR
  end_block
end_cfg
begin_bytecodes
     0: lload_0       
     1: lconst_0      
     2: lcmp          
     3: iflt          70
     6: getstatic     #9          // $assertionsDisabled:boolean
     9: ifne          51
    12: invokestatic  #4          // currentCarrierThread:()java.lang.Thread
    15: astore_3      
    16: aload_3       
    17: instanceof    #26         // jdk.internal.misc.CarrierThread
    20: ifeq          39
    23: aload_3       
    24: checkcast     #26         // jdk.internal.misc.CarrierThread
    27: astore_2      
    28: aload_2       
    29: invokevirtual #5          // jdk.internal.misc.CarrierThread.inBlocking:()boolean
    32: ifeq          39
    35: iconst_1      
    36: goto          40
    39: iconst_0      
    40: ifne          51
    43: new           #48         // java.lang.AssertionError
    46: dup           
    47: invokespecial #10         // java.lang.AssertionError.<init>:()void
    50: athrow        
    51: invokestatic  #4          // currentCarrierThread:()java.lang.Thread
    54: checkcast     #26         // jdk.internal.misc.CarrierThread
    57: astore_2      
    58: aload_2       
    59: invokevirtual #7          // java.util.concurrent.ForkJoinWorkerThread.getPool:()java.util.concurrent.ForkJoinPool
    62: lload_0       
    63: invokestatic  #13         // jdk.internal.misc.Blocker$ForkJoinPools.endCompensatedBlock:(java.util.concurrent.ForkJoinPool, long)void
    66: aload_2       
    67: invokevirtual #11         // jdk.internal.misc.CarrierThread.endBlocking:()void
    70: return        
   <|@
end_bytecodes
begin_cfg
  name "After SSALinearScanLifetimeAnalysis"
  begin_block
    name "B0"
    from_bci -1
    to_bci -1
    predecessors 
    successors "B1" "B2" 
    xhandlers
    flags 
    probability 4607182418800017408
    begin_IR
      LIR
      nr    0  <|@ instruction [rsi|QWORD, rbp|QWORD] = LABEL alignment: 0 numbPhis: 0 label: ? <|@ <|@
      nr    2  <|@ instruction NOP <|@ <|@
      nr    4  <|@ instruction NOP <|@ <|@
      nr    6  <|@ instruction NOP <|@ <|@
      nr    8  <|@ instruction NOP <|@ <|@
      nr   10  <|@ instruction NOP <|@ <|@
      nr   12  <|@ instruction NOP <|@ <|@
      nr   14  <|@ instruction NOP <|@ <|@
      nr   16  <|@ instruction stack:16|QWORD = MOVE input: rbp|QWORD moveKind: QWORD <|@ <|@
      nr   18  <|@ instruction [] = HOTSPOTLOCKSTACK frameMapBuilder: jdk.graal.compiler.hotspot.amd64.AMD64HotSpotFrameMapBuilder@abb5079 slotKind: QWORD <|@ <|@
      nr   20  <|@ instruction v0|QWORD = MOVE input: rsi|QWORD moveKind: QWORD <|@ <|@
      nr   22  <|@ instruction TESTBRANCH (x: v0|QWORD, y: v0|QWORD) trueDestinationProbability: 1.0 condition: < trueDestination: B0 -> B1 falseDestination: B0 -> B2 size: QWORD <|@ <|@
    end_IR
  end_block
  begin_block
    name "B1"
    from_bci -1
    to_bci -1
    predecessors "B0" 
    successors 
    xhandlers
    flags 
    probability 4607182418800017408
    begin_IR
      LIR
      nr   24  <|@ instruction [] = LABEL alignment: 0 numbPhis: 0 label: ? <|@ <|@
      nr   26  <|@ instruction NOP <|@ <|@
      nr   28  <|@ instruction NOP <|@ <|@
      nr   30  <|@ instruction NOP <|@ <|@
      nr   32  <|@ instruction NOP <|@ <|@
      nr   34  <|@ instruction NOP <|@ <|@
      nr   36  <|@ instruction NOP <|@ <|@
      nr   38  <|@ instruction NOP <|@ <|@
      nr   40  <|@ instruction RETURN (savedRbp: stack:16|QWORD, value: -) isStub: false requiresReservedStackAccessCheck: false thread: r15 scratchForSafepointOnReturn: rcx config: jdk.graal.compiler.hotspot.GraalHotSpotVMConfig@4817c460 <|@ <|@
    end_IR
  end_block
  begin_block
    name "B2"
    from_bci -1
    to_bci -1
    predecessors "B0" 
    successors 
    xhandlers
    flags 
    probability 2355382605114769408
    begin_IR
      LIR
      nr   42  <|@ instruction [] = LABEL alignment: 0 numbPhis: 0 label: ? <|@ <|@
      nr   44  <|@ instruction NOP <|@ <|@
      nr   46  <|@ instruction NOP <|@ <|@
      nr   48  <|@ instruction NOP <|@ <|@
      nr   50  <|@ instruction NOP <|@ <|@
      nr   52  <|@ instruction NOP <|@ <|@
      nr   54  <|@ instruction NOP <|@ <|@
      nr   56  <|@ instruction NOP <|@ <|@
      nr   58  <|@ instruction MOV x: [r15|QWORD + 1156] y: -2323 size: DWORD <|@ <|@
      nr   60  <|@ instruction MOV x: [r15|QWORD + 1168] y: 20 size: QWORD <|@ <|@
      nr   62  <|@ st <@st|@live-base-pointers: []
jdk.internal.misc.Blocker.end(Blocker.java:102) [bci: 0]
locals: v0|QWORD - - - 
>@ <|@ instruction DEOPT info [bci:0] <|@ <|@
    end_IR
  end_block
end_cfg
begin_bytecodes
     0: lload_0       
     1: lconst_0      
     2: lcmp          
     3: iflt          70
     6: getstatic     #9          // $assertionsDisabled:boolean
     9: ifne          51
    12: invokestatic  #4          // currentCarrierThread:()java.lang.Thread
    15: astore_3      
    16: aload_3       
    17: instanceof    #26         // jdk.internal.misc.CarrierThread
    20: ifeq          39
    23: aload_3       
    24: checkcast     #26         // jdk.internal.misc.CarrierThread
    27: astore_2      
    28: aload_2       
    29: invokevirtual #5          // jdk.internal.misc.CarrierThread.inBlocking:()boolean
    32: ifeq          39
    35: iconst_1      
    36: goto          40
    39: iconst_0      
    40: ifne          51
    43: new           #48         // java.lang.AssertionError
    46: dup           
    47: invokespecial #10         // java.lang.AssertionError.<init>:()void
    50: athrow        
    51: invokestatic  #4          // currentCarrierThread:()java.lang.Thread
    54: checkcast     #26         // jdk.internal.misc.CarrierThread
    57: astore_2      
    58: aload_2       
    59: invokevirtual #7          // java.util.concurrent.ForkJoinWorkerThread.getPool:()java.util.concurrent.ForkJoinPool
    62: lload_0       
    63: invokestatic  #13         // jdk.internal.misc.Blocker$ForkJoinPools.endCompensatedBlock:(java.util.concurrent.ForkJoinPool, long)void
    66: aload_2       
    67: invokevirtual #11         // jdk.internal.misc.CarrierThread.endBlocking:()void
    70: return        
   <|@
end_bytecodes
begin_intervals
  name "Before register allocation"
  rbp|q fixed "[rbp|q]" rbp|q -1 [0, 16[ "NoSpillStore"
  rsi|q fixed "[rsi|q]" rsi|q -1 [0, 20[ "NoSpillStore"
  v0|q QWORD "[v0|q]" v0|q rsi|q [20, 24[[42, 63[20 MustHaveRegister 22 MustHaveRegister  "NoSpillStore"
end_intervals
begin_intervals
  name "After register allocation"
  rbp|q fixed "[rbp|q]" rbp|q -1 [0, 16[ "NoSpillStore"
  rsi|q fixed "[rsi|q]" rsi|q -1 [0, 20[ "NoSpillStore"
  v0|q QWORD "[rsi|q]" v0|q rsi|q [20, 24[[42, 63[20 MustHaveRegister 22 MustHaveRegister  "NoSpillStore"
end_intervals
begin_cfg
  name "After LinearScanRegisterAllocation"
  begin_block
    name "B0"
    from_bci -1
    to_bci -1
    predecessors 
    successors "B1" "B2" 
    xhandlers
    flags 
    probability 4607182418800017408
    begin_IR
      LIR
      nr    0  <|@ instruction [rsi|QWORD, rbp|QWORD] = LABEL alignment: 0 numbPhis: 0 label: ? <|@ <|@
      nr    2  <|@ instruction NOP <|@ <|@
      nr    4  <|@ instruction NOP <|@ <|@
      nr    6  <|@ instruction NOP <|@ <|@
      nr    8  <|@ instruction NOP <|@ <|@
      nr   10  <|@ instruction NOP <|@ <|@
      nr   12  <|@ instruction NOP <|@ <|@
      nr   14  <|@ instruction NOP <|@ <|@
      nr   16  <|@ instruction stack:16|QWORD = MOVE input: rbp|QWORD moveKind: QWORD <|@ <|@
      nr   18  <|@ instruction [] = HOTSPOTLOCKSTACK frameMapBuilder: jdk.graal.compiler.hotspot.amd64.AMD64HotSpotFrameMapBuilder@abb5079 slotKind: QWORD <|@ <|@
      nr   20  <|@ instruction v0|QWORD = MOVE input: rsi|QWORD moveKind: QWORD <|@ <|@
      nr   22  <|@ instruction TESTBRANCH (x: v0|QWORD, y: v0|QWORD) trueDestinationProbability: 1.0 condition: < trueDestination: B0 -> B1 falseDestination: B0 -> B2 size: QWORD <|@ <|@
    end_IR
  end_block
  begin_block
    name "B1"
    from_bci -1
    to_bci -1
    predecessors "B0" 
    successors 
    xhandlers
    flags 
    probability 4607182418800017408
    begin_IR
      LIR
      nr   24  <|@ instruction [] = LABEL alignment: 0 numbPhis: 0 label: ? <|@ <|@
      nr   26  <|@ instruction NOP <|@ <|@
      nr   28  <|@ instruction NOP <|@ <|@
      nr   30  <|@ instruction NOP <|@ <|@
      nr   32  <|@ instruction NOP <|@ <|@
      nr   34  <|@ instruction NOP <|@ <|@
      nr   36  <|@ instruction NOP <|@ <|@
      nr   38  <|@ instruction NOP <|@ <|@
      nr   40  <|@ instruction RETURN (savedRbp: stack:16|QWORD, value: -) isStub: false requiresReservedStackAccessCheck: false thread: r15 scratchForSafepointOnReturn: rcx config: jdk.graal.compiler.hotspot.GraalHotSpotVMConfig@4817c460 <|@ <|@
    end_IR
  end_block
  begin_block
    name "B2"
    from_bci -1
    to_bci -1
    predecessors "B0" 
    successors 
    xhandlers
    flags 
    probability 2355382605114769408
    begin_IR
      LIR
      nr   42  <|@ instruction [] = LABEL alignment: 0 numbPhis: 0 label: ? <|@ <|@
      nr   44  <|@ instruction NOP <|@ <|@
      nr   46  <|@ instruction NOP <|@ <|@
      nr   48  <|@ instruction NOP <|@ <|@
      nr   50  <|@ instruction NOP <|@ <|@
      nr   52  <|@ instruction NOP <|@ <|@
      nr   54  <|@ instruction NOP <|@ <|@
      nr   56  <|@ instruction NOP <|@ <|@
      nr   58  <|@ instruction MOV x: [r15|QWORD + 1156] y: -2323 size: DWORD <|@ <|@
      nr   60  <|@ instruction MOV x: [r15|QWORD + 1168] y: 20 size: QWORD <|@ <|@
      nr   62  <|@ st <@st|@live-base-pointers: []
jdk.internal.misc.Blocker.end(Blocker.java:102) [bci: 0]
locals: v0|QWORD - - - 
>@ <|@ instruction DEOPT info [bci:0] <|@ <|@
    end_IR
  end_block
end_cfg
begin_bytecodes
     0: lload_0       
     1: lconst_0      
     2: lcmp          
     3: iflt          70
     6: getstatic     #9          // $assertionsDisabled:boolean
     9: ifne          51
    12: invokestatic  #4          // currentCarrierThread:()java.lang.Thread
    15: astore_3      
    16: aload_3       
    17: instanceof    #26         // jdk.internal.misc.CarrierThread
    20: ifeq          39
    23: aload_3       
    24: checkcast     #26         // jdk.internal.misc.CarrierThread
    27: astore_2      
    28: aload_2       
    29: invokevirtual #5          // jdk.internal.misc.CarrierThread.inBlocking:()boolean
    32: ifeq          39
    35: iconst_1      
    36: goto          40
    39: iconst_0      
    40: ifne          51
    43: new           #48         // java.lang.AssertionError
    46: dup           
    47: invokespecial #10         // java.lang.AssertionError.<init>:()void
    50: athrow        
    51: invokestatic  #4          // currentCarrierThread:()java.lang.Thread
    54: checkcast     #26         // jdk.internal.misc.CarrierThread
    57: astore_2      
    58: aload_2       
    59: invokevirtual #7          // java.util.concurrent.ForkJoinWorkerThread.getPool:()java.util.concurrent.ForkJoinPool
    62: lload_0       
    63: invokestatic  #13         // jdk.internal.misc.Blocker$ForkJoinPools.endCompensatedBlock:(java.util.concurrent.ForkJoinPool, long)void
    66: aload_2       
    67: invokevirtual #11         // jdk.internal.misc.CarrierThread.endBlocking:()void
    70: return        
   <|@
end_bytecodes
begin_intervals
  name "After optimize spill position"
  rbp|q fixed "[rbp|q]" rbp|q -1 [0, 16[ "NoSpillStore"
  rsi|q fixed "[rsi|q]" rsi|q -1 [0, 20[ "NoSpillStore"
  v0|q QWORD "[rsi|q]" v0|q rsi|q [20, 24[[42, 63[20 MustHaveRegister 22 MustHaveRegister  "NoSpillStore"
end_intervals
begin_cfg
  name "After LinearScanOptimizeSpillPosition"
  begin_block
    name "B0"
    from_bci -1
    to_bci -1
    predecessors 
    successors "B1" "B2" 
    xhandlers
    flags 
    probability 4607182418800017408
    begin_IR
      LIR
      nr    0  <|@ instruction [rsi|QWORD, rbp|QWORD] = LABEL alignment: 0 numbPhis: 0 label: ? <|@ <|@
      nr    2  <|@ instruction NOP <|@ <|@
      nr    4  <|@ instruction NOP <|@ <|@
      nr    6  <|@ instruction NOP <|@ <|@
      nr    8  <|@ instruction NOP <|@ <|@
      nr   10  <|@ instruction NOP <|@ <|@
      nr   12  <|@ instruction NOP <|@ <|@
      nr   14  <|@ instruction NOP <|@ <|@
      nr   16  <|@ instruction stack:16|QWORD = MOVE input: rbp|QWORD moveKind: QWORD <|@ <|@
      nr   18  <|@ instruction [] = HOTSPOTLOCKSTACK frameMapBuilder: jdk.graal.compiler.hotspot.amd64.AMD64HotSpotFrameMapBuilder@abb5079 slotKind: QWORD <|@ <|@
      nr   20  <|@ instruction v0|QWORD = MOVE input: rsi|QWORD moveKind: QWORD <|@ <|@
      nr   22  <|@ instruction TESTBRANCH (x: v0|QWORD, y: v0|QWORD) trueDestinationProbability: 1.0 condition: < trueDestination: B0 -> B1 falseDestination: B0 -> B2 size: QWORD <|@ <|@
    end_IR
  end_block
  begin_block
    name "B1"
    from_bci -1
    to_bci -1
    predecessors "B0" 
    successors 
    xhandlers
    flags 
    probability 4607182418800017408
    begin_IR
      LIR
      nr   24  <|@ instruction [] = LABEL alignment: 0 numbPhis: 0 label: ? <|@ <|@
      nr   26  <|@ instruction NOP <|@ <|@
      nr   28  <|@ instruction NOP <|@ <|@
      nr   30  <|@ instruction NOP <|@ <|@
      nr   32  <|@ instruction NOP <|@ <|@
      nr   34  <|@ instruction NOP <|@ <|@
      nr   36  <|@ instruction NOP <|@ <|@
      nr   38  <|@ instruction NOP <|@ <|@
      nr   40  <|@ instruction RETURN (savedRbp: stack:16|QWORD, value: -) isStub: false requiresReservedStackAccessCheck: false thread: r15 scratchForSafepointOnReturn: rcx config: jdk.graal.compiler.hotspot.GraalHotSpotVMConfig@4817c460 <|@ <|@
    end_IR
  end_block
  begin_block
    name "B2"
    from_bci -1
    to_bci -1
    predecessors "B0" 
    successors 
    xhandlers
    flags 
    probability 2355382605114769408
    begin_IR
      LIR
      nr   42  <|@ instruction [] = LABEL alignment: 0 numbPhis: 0 label: ? <|@ <|@
      nr   44  <|@ instruction NOP <|@ <|@
      nr   46  <|@ instruction NOP <|@ <|@
      nr   48  <|@ instruction NOP <|@ <|@
      nr   50  <|@ instruction NOP <|@ <|@
      nr   52  <|@ instruction NOP <|@ <|@
      nr   54  <|@ instruction NOP <|@ <|@
      nr   56  <|@ instruction NOP <|@ <|@
      nr   58  <|@ instruction MOV x: [r15|QWORD + 1156] y: -2323 size: DWORD <|@ <|@
      nr   60  <|@ instruction MOV x: [r15|QWORD + 1168] y: 20 size: QWORD <|@ <|@
      nr   62  <|@ st <@st|@live-base-pointers: []
jdk.internal.misc.Blocker.end(Blocker.java:102) [bci: 0]
locals: v0|QWORD - - - 
>@ <|@ instruction DEOPT info [bci:0] <|@ <|@
    end_IR
  end_block
end_cfg
begin_bytecodes
     0: lload_0       
     1: lconst_0      
     2: lcmp          
     3: iflt          70
     6: getstatic     #9          // $assertionsDisabled:boolean
     9: ifne          51
    12: invokestatic  #4          // currentCarrierThread:()java.lang.Thread
    15: astore_3      
    16: aload_3       
    17: instanceof    #26         // jdk.internal.misc.CarrierThread
    20: ifeq          39
    23: aload_3       
    24: checkcast     #26         // jdk.internal.misc.CarrierThread
    27: astore_2      
    28: aload_2       
    29: invokevirtual #5          // jdk.internal.misc.CarrierThread.inBlocking:()boolean
    32: ifeq          39
    35: iconst_1      
    36: goto          40
    39: iconst_0      
    40: ifne          51
    43: new           #48         // java.lang.AssertionError
    46: dup           
    47: invokespecial #10         // java.lang.AssertionError.<init>:()void
    50: athrow        
    51: invokestatic  #4          // currentCarrierThread:()java.lang.Thread
    54: checkcast     #26         // jdk.internal.misc.CarrierThread
    57: astore_2      
    58: aload_2       
    59: invokevirtual #7          // java.util.concurrent.ForkJoinWorkerThread.getPool:()java.util.concurrent.ForkJoinPool
    62: lload_0       
    63: invokestatic  #13         // jdk.internal.misc.Blocker$ForkJoinPools.endCompensatedBlock:(java.util.concurrent.ForkJoinPool, long)void
    66: aload_2       
    67: invokevirtual #11         // jdk.internal.misc.CarrierThread.endBlocking:()void
    70: return        
   <|@
end_bytecodes
begin_intervals
  name "After resolve data flow"
  rbp|q fixed "[rbp|q]" rbp|q -1 [0, 16[ "NoSpillStore"
  rsi|q fixed "[rsi|q]" rsi|q -1 [0, 20[ "NoSpillStore"
  v0|q QWORD "[rsi|q]" v0|q rsi|q [20, 24[[42, 63[20 MustHaveRegister 22 MustHaveRegister  "NoSpillStore"
end_intervals
begin_cfg
  name "After SSALinearScanResolveDataFlow"
  begin_block
    name "B0"
    from_bci -1
    to_bci -1
    predecessors 
    successors "B1" "B2" 
    xhandlers
    flags 
    probability 4607182418800017408
    begin_IR
      LIR
      nr    0  <|@ instruction [rsi|QWORD, rbp|QWORD] = LABEL alignment: 0 numbPhis: 0 label: ? <|@ <|@
      nr    2  <|@ instruction NOP <|@ <|@
      nr    4  <|@ instruction NOP <|@ <|@
      nr    6  <|@ instruction NOP <|@ <|@
      nr    8  <|@ instruction NOP <|@ <|@
      nr   10  <|@ instruction NOP <|@ <|@
      nr   12  <|@ instruction NOP <|@ <|@
      nr   14  <|@ instruction NOP <|@ <|@
      nr   16  <|@ instruction stack:16|QWORD = MOVE input: rbp|QWORD moveKind: QWORD <|@ <|@
      nr   18  <|@ instruction [] = HOTSPOTLOCKSTACK frameMapBuilder: jdk.graal.compiler.hotspot.amd64.AMD64HotSpotFrameMapBuilder@abb5079 slotKind: QWORD <|@ <|@
      nr   20  <|@ instruction v0|QWORD = MOVE input: rsi|QWORD moveKind: QWORD <|@ <|@
      nr   22  <|@ instruction TESTBRANCH (x: v0|QWORD, y: v0|QWORD) trueDestinationProbability: 1.0 condition: < trueDestination: B0 -> B1 falseDestination: B0 -> B2 size: QWORD <|@ <|@
    end_IR
  end_block
  begin_block
    name "B1"
    from_bci -1
    to_bci -1
    predecessors "B0" 
    successors 
    xhandlers
    flags 
    probability 4607182418800017408
    begin_IR
      LIR
      nr   24  <|@ instruction [] = LABEL alignment: 0 numbPhis: 0 label: ? <|@ <|@
      nr   26  <|@ instruction NOP <|@ <|@
      nr   28  <|@ instruction NOP <|@ <|@
      nr   30  <|@ instruction NOP <|@ <|@
      nr   32  <|@ instruction NOP <|@ <|@
      nr   34  <|@ instruction NOP <|@ <|@
      nr   36  <|@ instruction NOP <|@ <|@
      nr   38  <|@ instruction NOP <|@ <|@
      nr   40  <|@ instruction RETURN (savedRbp: stack:16|QWORD, value: -) isStub: false requiresReservedStackAccessCheck: false thread: r15 scratchForSafepointOnReturn: rcx config: jdk.graal.compiler.hotspot.GraalHotSpotVMConfig@4817c460 <|@ <|@
    end_IR
  end_block
  begin_block
    name "B2"
    from_bci -1
    to_bci -1
    predecessors "B0" 
    successors 
    xhandlers
    flags 
    probability 2355382605114769408
    begin_IR
      LIR
      nr   42  <|@ instruction [] = LABEL alignment: 0 numbPhis: 0 label: ? <|@ <|@
      nr   44  <|@ instruction NOP <|@ <|@
      nr   46  <|@ instruction NOP <|@ <|@
      nr   48  <|@ instruction NOP <|@ <|@
      nr   50  <|@ instruction NOP <|@ <|@
      nr   52  <|@ instruction NOP <|@ <|@
      nr   54  <|@ instruction NOP <|@ <|@
      nr   56  <|@ instruction NOP <|@ <|@
      nr   58  <|@ instruction MOV x: [r15|QWORD + 1156] y: -2323 size: DWORD <|@ <|@
      nr   60  <|@ instruction MOV x: [r15|QWORD + 1168] y: 20 size: QWORD <|@ <|@
      nr   62  <|@ st <@st|@live-base-pointers: []
jdk.internal.misc.Blocker.end(Blocker.java:102) [bci: 0]
locals: v0|QWORD - - - 
>@ <|@ instruction DEOPT info [bci:0] <|@ <|@
    end_IR
  end_block
end_cfg
begin_bytecodes
     0: lload_0       
     1: lconst_0      
     2: lcmp          
     3: iflt          70
     6: getstatic     #9          // $assertionsDisabled:boolean
     9: ifne          51
    12: invokestatic  #4          // currentCarrierThread:()java.lang.Thread
    15: astore_3      
    16: aload_3       
    17: instanceof    #26         // jdk.internal.misc.CarrierThread
    20: ifeq          39
    23: aload_3       
    24: checkcast     #26         // jdk.internal.misc.CarrierThread
    27: astore_2      
    28: aload_2       
    29: invokevirtual #5          // jdk.internal.misc.CarrierThread.inBlocking:()boolean
    32: ifeq          39
    35: iconst_1      
    36: goto          40
    39: iconst_0      
    40: ifne          51
    43: new           #48         // java.lang.AssertionError
    46: dup           
    47: invokespecial #10         // java.lang.AssertionError.<init>:()void
    50: athrow        
    51: invokestatic  #4          // currentCarrierThread:()java.lang.Thread
    54: checkcast     #26         // jdk.internal.misc.CarrierThread
    57: astore_2      
    58: aload_2       
    59: invokevirtual #7          // java.util.concurrent.ForkJoinWorkerThread.getPool:()java.util.concurrent.ForkJoinPool
    62: lload_0       
    63: invokestatic  #13         // jdk.internal.misc.Blocker$ForkJoinPools.endCompensatedBlock:(java.util.concurrent.ForkJoinPool, long)void
    66: aload_2       
    67: invokevirtual #11         // jdk.internal.misc.CarrierThread.endBlocking:()void
    70: return        
   <|@
end_bytecodes
begin_cfg
  name "After SSALinearScanEliminateSpillMove"
  begin_block
    name "B0"
    from_bci -1
    to_bci -1
    predecessors 
    successors "B1" "B2" 
    xhandlers
    flags 
    probability 4607182418800017408
    begin_IR
      LIR
      nr    0  <|@ instruction [rsi|QWORD, rbp|QWORD] = LABEL alignment: 0 numbPhis: 0 label: ? <|@ <|@
      nr    2  <|@ instruction NOP <|@ <|@
      nr    4  <|@ instruction NOP <|@ <|@
      nr    6  <|@ instruction NOP <|@ <|@
      nr    8  <|@ instruction NOP <|@ <|@
      nr   10  <|@ instruction NOP <|@ <|@
      nr   12  <|@ instruction NOP <|@ <|@
      nr   14  <|@ instruction NOP <|@ <|@
      nr   16  <|@ instruction stack:16|QWORD = MOVE input: rbp|QWORD moveKind: QWORD <|@ <|@
      nr   18  <|@ instruction [] = HOTSPOTLOCKSTACK frameMapBuilder: jdk.graal.compiler.hotspot.amd64.AMD64HotSpotFrameMapBuilder@abb5079 slotKind: QWORD <|@ <|@
      nr   20  <|@ instruction v0|QWORD = MOVE input: rsi|QWORD moveKind: QWORD <|@ <|@
      nr   22  <|@ instruction TESTBRANCH (x: v0|QWORD, y: v0|QWORD) trueDestinationProbability: 1.0 condition: < trueDestination: B0 -> B1 falseDestination: B0 -> B2 size: QWORD <|@ <|@
    end_IR
  end_block
  begin_block
    name "B1"
    from_bci -1
    to_bci -1
    predecessors "B0" 
    successors 
    xhandlers
    flags 
    probability 4607182418800017408
    begin_IR
      LIR
      nr   24  <|@ instruction [] = LABEL alignment: 0 numbPhis: 0 label: ? <|@ <|@
      nr   26  <|@ instruction NOP <|@ <|@
      nr   28  <|@ instruction NOP <|@ <|@
      nr   30  <|@ instruction NOP <|@ <|@
      nr   32  <|@ instruction NOP <|@ <|@
      nr   34  <|@ instruction NOP <|@ <|@
      nr   36  <|@ instruction NOP <|@ <|@
      nr   38  <|@ instruction NOP <|@ <|@
      nr   40  <|@ instruction RETURN (savedRbp: stack:16|QWORD, value: -) isStub: false requiresReservedStackAccessCheck: false thread: r15 scratchForSafepointOnReturn: rcx config: jdk.graal.compiler.hotspot.GraalHotSpotVMConfig@4817c460 <|@ <|@
    end_IR
  end_block
  begin_block
    name "B2"
    from_bci -1
    to_bci -1
    predecessors "B0" 
    successors 
    xhandlers
    flags 
    probability 2355382605114769408
    begin_IR
      LIR
      nr   42  <|@ instruction [] = LABEL alignment: 0 numbPhis: 0 label: ? <|@ <|@
      nr   44  <|@ instruction NOP <|@ <|@
      nr   46  <|@ instruction NOP <|@ <|@
      nr   48  <|@ instruction NOP <|@ <|@
      nr   50  <|@ instruction NOP <|@ <|@
      nr   52  <|@ instruction NOP <|@ <|@
      nr   54  <|@ instruction NOP <|@ <|@
      nr   56  <|@ instruction NOP <|@ <|@
      nr   58  <|@ instruction MOV x: [r15|QWORD + 1156] y: -2323 size: DWORD <|@ <|@
      nr   60  <|@ instruction MOV x: [r15|QWORD + 1168] y: 20 size: QWORD <|@ <|@
      nr   62  <|@ st <@st|@live-base-pointers: []
jdk.internal.misc.Blocker.end(Blocker.java:102) [bci: 0]
locals: v0|QWORD - - - 
>@ <|@ instruction DEOPT info [bci:0] <|@ <|@
    end_IR
  end_block
end_cfg
begin_bytecodes
     0: lload_0       
     1: lconst_0      
     2: lcmp          
     3: iflt          70
     6: getstatic     #9          // $assertionsDisabled:boolean
     9: ifne          51
    12: invokestatic  #4          // currentCarrierThread:()java.lang.Thread
    15: astore_3      
    16: aload_3       
    17: instanceof    #26         // jdk.internal.misc.CarrierThread
    20: ifeq          39
    23: aload_3       
    24: checkcast     #26         // jdk.internal.misc.CarrierThread
    27: astore_2      
    28: aload_2       
    29: invokevirtual #5          // jdk.internal.misc.CarrierThread.inBlocking:()boolean
    32: ifeq          39
    35: iconst_1      
    36: goto          40
    39: iconst_0      
    40: ifne          51
    43: new           #48         // java.lang.AssertionError
    46: dup           
    47: invokespecial #10         // java.lang.AssertionError.<init>:()void
    50: athrow        
    51: invokestatic  #4          // currentCarrierThread:()java.lang.Thread
    54: checkcast     #26         // jdk.internal.misc.CarrierThread
    57: astore_2      
    58: aload_2       
    59: invokevirtual #7          // java.util.concurrent.ForkJoinWorkerThread.getPool:()java.util.concurrent.ForkJoinPool
    62: lload_0       
    63: invokestatic  #13         // jdk.internal.misc.Blocker$ForkJoinPools.endCompensatedBlock:(java.util.concurrent.ForkJoinPool, long)void
    66: aload_2       
    67: invokevirtual #11         // jdk.internal.misc.CarrierThread.endBlocking:()void
    70: return        
   <|@
end_bytecodes
begin_cfg
  name "After LinearScanAssignLocations"
  begin_block
    name "B0"
    from_bci -1
    to_bci -1
    predecessors 
    successors "B1" "B2" 
    xhandlers
    flags 
    probability 4607182418800017408
    begin_IR
      LIR
      nr    0  <|@ instruction [rsi|QWORD, rbp|QWORD] = LABEL alignment: 0 numbPhis: 0 label: ? <|@ <|@
      nr    2  <|@ instruction NOP <|@ <|@
      nr    4  <|@ instruction NOP <|@ <|@
      nr    6  <|@ instruction NOP <|@ <|@
      nr    8  <|@ instruction NOP <|@ <|@
      nr   10  <|@ instruction NOP <|@ <|@
      nr   12  <|@ instruction NOP <|@ <|@
      nr   14  <|@ instruction NOP <|@ <|@
      nr   16  <|@ instruction stack:16|QWORD = MOVE input: rbp|QWORD moveKind: QWORD <|@ <|@
      nr   18  <|@ instruction [] = HOTSPOTLOCKSTACK frameMapBuilder: jdk.graal.compiler.hotspot.amd64.AMD64HotSpotFrameMapBuilder@abb5079 slotKind: QWORD <|@ <|@
      nr   22  <|@ instruction TESTBRANCH (x: rsi|QWORD, y: rsi|QWORD) trueDestinationProbability: 1.0 condition: < trueDestination: B0 -> B1 falseDestination: B0 -> B2 size: QWORD <|@ <|@
    end_IR
  end_block
  begin_block
    name "B1"
    from_bci -1
    to_bci -1
    predecessors "B0" 
    successors 
    xhandlers
    flags 
    probability 4607182418800017408
    begin_IR
      LIR
      nr   24  <|@ instruction [] = LABEL alignment: 0 numbPhis: 0 label: ? <|@ <|@
      nr   26  <|@ instruction NOP <|@ <|@
      nr   28  <|@ instruction NOP <|@ <|@
      nr   30  <|@ instruction NOP <|@ <|@
      nr   32  <|@ instruction NOP <|@ <|@
      nr   34  <|@ instruction NOP <|@ <|@
      nr   36  <|@ instruction NOP <|@ <|@
      nr   38  <|@ instruction NOP <|@ <|@
      nr   40  <|@ instruction RETURN (savedRbp: stack:16|QWORD, value: -) isStub: false requiresReservedStackAccessCheck: false thread: r15 scratchForSafepointOnReturn: rcx config: jdk.graal.compiler.hotspot.GraalHotSpotVMConfig@4817c460 <|@ <|@
    end_IR
  end_block
  begin_block
    name "B2"
    from_bci -1
    to_bci -1
    predecessors "B0" 
    successors 
    xhandlers
    flags 
    probability 2355382605114769408
    begin_IR
      LIR
      nr   42  <|@ instruction [] = LABEL alignment: 0 numbPhis: 0 label: ? <|@ <|@
      nr   44  <|@ instruction NOP <|@ <|@
      nr   46  <|@ instruction NOP <|@ <|@
      nr   48  <|@ instruction NOP <|@ <|@
      nr   50  <|@ instruction NOP <|@ <|@
      nr   52  <|@ instruction NOP <|@ <|@
      nr   54  <|@ instruction NOP <|@ <|@
      nr   56  <|@ instruction NOP <|@ <|@
      nr   58  <|@ instruction MOV x: [r15|QWORD + 1156] y: -2323 size: DWORD <|@ <|@
      nr   60  <|@ instruction MOV x: [r15|QWORD + 1168] y: 20 size: QWORD <|@ <|@
      nr   62  <|@ st <@st|@live-base-pointers: []
jdk.internal.misc.Blocker.end(Blocker.java:102) [bci: 0]
locals: rsi|QWORD - - - 
>@ <|@ instruction DEOPT info [bci:0] <|@ <|@
    end_IR
  end_block
end_cfg
begin_bytecodes
     0: lload_0       
     1: lconst_0      
     2: lcmp          
     3: iflt          70
     6: getstatic     #9          // $assertionsDisabled:boolean
     9: ifne          51
    12: invokestatic  #4          // currentCarrierThread:()java.lang.Thread
    15: astore_3      
    16: aload_3       
    17: instanceof    #26         // jdk.internal.misc.CarrierThread
    20: ifeq          39
    23: aload_3       
    24: checkcast     #26         // jdk.internal.misc.CarrierThread
    27: astore_2      
    28: aload_2       
    29: invokevirtual #5          // jdk.internal.misc.CarrierThread.inBlocking:()boolean
    32: ifeq          39
    35: iconst_1      
    36: goto          40
    39: iconst_0      
    40: ifne          51
    43: new           #48         // java.lang.AssertionError
    46: dup           
    47: invokespecial #10         // java.lang.AssertionError.<init>:()void
    50: athrow        
    51: invokestatic  #4          // currentCarrierThread:()java.lang.Thread
    54: checkcast     #26         // jdk.internal.misc.CarrierThread
    57: astore_2      
    58: aload_2       
    59: invokevirtual #7          // java.util.concurrent.ForkJoinWorkerThread.getPool:()java.util.concurrent.ForkJoinPool
    62: lload_0       
    63: invokestatic  #13         // jdk.internal.misc.Blocker$ForkJoinPools.endCompensatedBlock:(java.util.concurrent.ForkJoinPool, long)void
    66: aload_2       
    67: invokevirtual #11         // jdk.internal.misc.CarrierThread.endBlocking:()void
    70: return        
   <|@
end_bytecodes
begin_cfg
  name "After LinearScan"
  begin_block
    name "B0"
    from_bci -1
    to_bci -1
    predecessors 
    successors "B1" "B2" 
    xhandlers
    flags 
    probability 4607182418800017408
    begin_IR
      LIR
      nr    0  <|@ instruction [rsi|QWORD, rbp|QWORD] = LABEL alignment: 0 numbPhis: 0 label: ? <|@ <|@
      nr    2  <|@ instruction NOP <|@ <|@
      nr    4  <|@ instruction NOP <|@ <|@
      nr    6  <|@ instruction NOP <|@ <|@
      nr    8  <|@ instruction NOP <|@ <|@
      nr   10  <|@ instruction NOP <|@ <|@
      nr   12  <|@ instruction NOP <|@ <|@
      nr   14  <|@ instruction NOP <|@ <|@
      nr   16  <|@ instruction stack:16|QWORD = MOVE input: rbp|QWORD moveKind: QWORD <|@ <|@
      nr   18  <|@ instruction [] = HOTSPOTLOCKSTACK frameMapBuilder: jdk.graal.compiler.hotspot.amd64.AMD64HotSpotFrameMapBuilder@abb5079 slotKind: QWORD <|@ <|@
      nr   22  <|@ instruction TESTBRANCH (x: rsi|QWORD, y: rsi|QWORD) trueDestinationProbability: 1.0 condition: < trueDestination: B0 -> B1 falseDestination: B0 -> B2 size: QWORD <|@ <|@
    end_IR
  end_block
  begin_block
    name "B1"
    from_bci -1
    to_bci -1
    predecessors "B0" 
    successors 
    xhandlers
    flags 
    probability 4607182418800017408
    begin_IR
      LIR
      nr   24  <|@ instruction [] = LABEL alignment: 0 numbPhis: 0 label: ? <|@ <|@
      nr   26  <|@ instruction NOP <|@ <|@
      nr   28  <|@ instruction NOP <|@ <|@
      nr   30  <|@ instruction NOP <|@ <|@
      nr   32  <|@ instruction NOP <|@ <|@
      nr   34  <|@ instruction NOP <|@ <|@
      nr   36  <|@ instruction NOP <|@ <|@
      nr   38  <|@ instruction NOP <|@ <|@
      nr   40  <|@ instruction RETURN (savedRbp: stack:16|QWORD, value: -) isStub: false requiresReservedStackAccessCheck: false thread: r15 scratchForSafepointOnReturn: rcx config: jdk.graal.compiler.hotspot.GraalHotSpotVMConfig@4817c460 <|@ <|@
    end_IR
  end_block
  begin_block
    name "B2"
    from_bci -1
    to_bci -1
    predecessors "B0" 
    successors 
    xhandlers
    flags 
    probability 2355382605114769408
    begin_IR
      LIR
      nr   42  <|@ instruction [] = LABEL alignment: 0 numbPhis: 0 label: ? <|@ <|@
      nr   44  <|@ instruction NOP <|@ <|@
      nr   46  <|@ instruction NOP <|@ <|@
      nr   48  <|@ instruction NOP <|@ <|@
      nr   50  <|@ instruction NOP <|@ <|@
      nr   52  <|@ instruction NOP <|@ <|@
      nr   54  <|@ instruction NOP <|@ <|@
      nr   56  <|@ instruction NOP <|@ <|@
      nr   58  <|@ instruction MOV x: [r15|QWORD + 1156] y: -2323 size: DWORD <|@ <|@
      nr   60  <|@ instruction MOV x: [r15|QWORD + 1168] y: 20 size: QWORD <|@ <|@
      nr   62  <|@ st <@st|@live-base-pointers: []
jdk.internal.misc.Blocker.end(Blocker.java:102) [bci: 0]
locals: rsi|QWORD - - - 
>@ <|@ instruction DEOPT info [bci:0] <|@ <|@
    end_IR
  end_block
end_cfg
begin_bytecodes
     0: lload_0       
     1: lconst_0      
     2: lcmp          
     3: iflt          70
     6: getstatic     #9          // $assertionsDisabled:boolean
     9: ifne          51
    12: invokestatic  #4          // currentCarrierThread:()java.lang.Thread
    15: astore_3      
    16: aload_3       
    17: instanceof    #26         // jdk.internal.misc.CarrierThread
    20: ifeq          39
    23: aload_3       
    24: checkcast     #26         // jdk.internal.misc.CarrierThread
    27: astore_2      
    28: aload_2       
    29: invokevirtual #5          // jdk.internal.misc.CarrierThread.inBlocking:()boolean
    32: ifeq          39
    35: iconst_1      
    36: goto          40
    39: iconst_0      
    40: ifne          51
    43: new           #48         // java.lang.AssertionError
    46: dup           
    47: invokespecial #10         // java.lang.AssertionError.<init>:()void
    50: athrow        
    51: invokestatic  #4          // currentCarrierThread:()java.lang.Thread
    54: checkcast     #26         // jdk.internal.misc.CarrierThread
    57: astore_2      
    58: aload_2       
    59: invokevirtual #7          // java.util.concurrent.ForkJoinWorkerThread.getPool:()java.util.concurrent.ForkJoinPool
    62: lload_0       
    63: invokestatic  #13         // jdk.internal.misc.Blocker$ForkJoinPools.endCompensatedBlock:(java.util.concurrent.ForkJoinPool, long)void
    66: aload_2       
    67: invokevirtual #11         // jdk.internal.misc.CarrierThread.endBlocking:()void
    70: return        
   <|@
end_bytecodes
begin_cfg
  name "After LSStackSlotAllocator"
  begin_block
    name "B0"
    from_bci -1
    to_bci -1
    predecessors 
    successors "B1" "B2" 
    xhandlers
    flags 
    probability 4607182418800017408
    begin_IR
      LIR
      nr    0  <|@ instruction [rsi|QWORD, rbp|QWORD] = LABEL alignment: 0 numbPhis: 0 label: ? <|@ <|@
      nr    2  <|@ instruction NOP <|@ <|@
      nr    4  <|@ instruction NOP <|@ <|@
      nr    6  <|@ instruction NOP <|@ <|@
      nr    8  <|@ instruction NOP <|@ <|@
      nr   10  <|@ instruction NOP <|@ <|@
      nr   12  <|@ instruction NOP <|@ <|@
      nr   14  <|@ instruction NOP <|@ <|@
      nr   16  <|@ instruction stack:16|QWORD = MOVE input: rbp|QWORD moveKind: QWORD <|@ <|@
      nr   18  <|@ instruction [] = HOTSPOTLOCKSTACK frameMapBuilder: jdk.graal.compiler.hotspot.amd64.AMD64HotSpotFrameMapBuilder@abb5079 slotKind: QWORD <|@ <|@
      nr   22  <|@ instruction TESTBRANCH (x: rsi|QWORD, y: rsi|QWORD) trueDestinationProbability: 1.0 condition: < trueDestination: B0 -> B1 falseDestination: B0 -> B2 size: QWORD <|@ <|@
    end_IR
  end_block
  begin_block
    name "B1"
    from_bci -1
    to_bci -1
    predecessors "B0" 
    successors 
    xhandlers
    flags 
    probability 4607182418800017408
    begin_IR
      LIR
      nr   24  <|@ instruction [] = LABEL alignment: 0 numbPhis: 0 label: ? <|@ <|@
      nr   26  <|@ instruction NOP <|@ <|@
      nr   28  <|@ instruction NOP <|@ <|@
      nr   30  <|@ instruction NOP <|@ <|@
      nr   32  <|@ instruction NOP <|@ <|@
      nr   34  <|@ instruction NOP <|@ <|@
      nr   36  <|@ instruction NOP <|@ <|@
      nr   38  <|@ instruction NOP <|@ <|@
      nr   40  <|@ instruction RETURN (savedRbp: stack:16|QWORD, value: -) isStub: false requiresReservedStackAccessCheck: false thread: r15 scratchForSafepointOnReturn: rcx config: jdk.graal.compiler.hotspot.GraalHotSpotVMConfig@4817c460 <|@ <|@
    end_IR
  end_block
  begin_block
    name "B2"
    from_bci -1
    to_bci -1
    predecessors "B0" 
    successors 
    xhandlers
    flags 
    probability 2355382605114769408
    begin_IR
      LIR
      nr   42  <|@ instruction [] = LABEL alignment: 0 numbPhis: 0 label: ? <|@ <|@
      nr   44  <|@ instruction NOP <|@ <|@
      nr   46  <|@ instruction NOP <|@ <|@
      nr   48  <|@ instruction NOP <|@ <|@
      nr   50  <|@ instruction NOP <|@ <|@
      nr   52  <|@ instruction NOP <|@ <|@
      nr   54  <|@ instruction NOP <|@ <|@
      nr   56  <|@ instruction NOP <|@ <|@
      nr   58  <|@ instruction MOV x: [r15|QWORD + 1156] y: -2323 size: DWORD <|@ <|@
      nr   60  <|@ instruction MOV x: [r15|QWORD + 1168] y: 20 size: QWORD <|@ <|@
      nr   62  <|@ st <@st|@live-base-pointers: []
jdk.internal.misc.Blocker.end(Blocker.java:102) [bci: 0]
locals: rsi|QWORD - - - 
>@ <|@ instruction DEOPT info [bci:0] <|@ <|@
    end_IR
  end_block
end_cfg
begin_bytecodes
     0: lload_0       
     1: lconst_0      
     2: lcmp          
     3: iflt          70
     6: getstatic     #9          // $assertionsDisabled:boolean
     9: ifne          51
    12: invokestatic  #4          // currentCarrierThread:()java.lang.Thread
    15: astore_3      
    16: aload_3       
    17: instanceof    #26         // jdk.internal.misc.CarrierThread
    20: ifeq          39
    23: aload_3       
    24: checkcast     #26         // jdk.internal.misc.CarrierThread
    27: astore_2      
    28: aload_2       
    29: invokevirtual #5          // jdk.internal.misc.CarrierThread.inBlocking:()boolean
    32: ifeq          39
    35: iconst_1      
    36: goto          40
    39: iconst_0      
    40: ifne          51
    43: new           #48         // java.lang.AssertionError
    46: dup           
    47: invokespecial #10         // java.lang.AssertionError.<init>:()void
    50: athrow        
    51: invokestatic  #4          // currentCarrierThread:()java.lang.Thread
    54: checkcast     #26         // jdk.internal.misc.CarrierThread
    57: astore_2      
    58: aload_2       
    59: invokevirtual #7          // java.util.concurrent.ForkJoinWorkerThread.getPool:()java.util.concurrent.ForkJoinPool
    62: lload_0       
    63: invokestatic  #13         // jdk.internal.misc.Blocker$ForkJoinPools.endCompensatedBlock:(java.util.concurrent.ForkJoinPool, long)void
    66: aload_2       
    67: invokevirtual #11         // jdk.internal.misc.CarrierThread.endBlocking:()void
    70: return        
   <|@
end_bytecodes
begin_cfg
  name "After AllocationStage"
  begin_block
    name "B0"
    from_bci -1
    to_bci -1
    predecessors 
    successors "B1" "B2" 
    xhandlers
    flags 
    probability 4607182418800017408
    begin_IR
      LIR
      nr    0  <|@ instruction [rsi|QWORD, rbp|QWORD] = LABEL alignment: 0 numbPhis: 0 label: ? <|@ <|@
      nr    2  <|@ instruction NOP <|@ <|@
      nr    4  <|@ instruction NOP <|@ <|@
      nr    6  <|@ instruction NOP <|@ <|@
      nr    8  <|@ instruction NOP <|@ <|@
      nr   10  <|@ instruction NOP <|@ <|@
      nr   12  <|@ instruction NOP <|@ <|@
      nr   14  <|@ instruction NOP <|@ <|@
      nr   16  <|@ instruction stack:16|QWORD = MOVE input: rbp|QWORD moveKind: QWORD <|@ <|@
      nr   18  <|@ instruction [] = HOTSPOTLOCKSTACK frameMapBuilder: jdk.graal.compiler.hotspot.amd64.AMD64HotSpotFrameMapBuilder@abb5079 slotKind: QWORD <|@ <|@
      nr   22  <|@ instruction TESTBRANCH (x: rsi|QWORD, y: rsi|QWORD) trueDestinationProbability: 1.0 condition: < trueDestination: B0 -> B1 falseDestination: B0 -> B2 size: QWORD <|@ <|@
    end_IR
  end_block
  begin_block
    name "B1"
    from_bci -1
    to_bci -1
    predecessors "B0" 
    successors 
    xhandlers
    flags 
    probability 4607182418800017408
    begin_IR
      LIR
      nr   24  <|@ instruction [] = LABEL alignment: 0 numbPhis: 0 label: ? <|@ <|@
      nr   26  <|@ instruction NOP <|@ <|@
      nr   28  <|@ instruction NOP <|@ <|@
      nr   30  <|@ instruction NOP <|@ <|@
      nr   32  <|@ instruction NOP <|@ <|@
      nr   34  <|@ instruction NOP <|@ <|@
      nr   36  <|@ instruction NOP <|@ <|@
      nr   38  <|@ instruction NOP <|@ <|@
      nr   40  <|@ instruction RETURN (savedRbp: stack:16|QWORD, value: -) isStub: false requiresReservedStackAccessCheck: false thread: r15 scratchForSafepointOnReturn: rcx config: jdk.graal.compiler.hotspot.GraalHotSpotVMConfig@4817c460 <|@ <|@
    end_IR
  end_block
  begin_block
    name "B2"
    from_bci -1
    to_bci -1
    predecessors "B0" 
    successors 
    xhandlers
    flags 
    probability 2355382605114769408
    begin_IR
      LIR
      nr   42  <|@ instruction [] = LABEL alignment: 0 numbPhis: 0 label: ? <|@ <|@
      nr   44  <|@ instruction NOP <|@ <|@
      nr   46  <|@ instruction NOP <|@ <|@
      nr   48  <|@ instruction NOP <|@ <|@
      nr   50  <|@ instruction NOP <|@ <|@
      nr   52  <|@ instruction NOP <|@ <|@
      nr   54  <|@ instruction NOP <|@ <|@
      nr   56  <|@ instruction NOP <|@ <|@
      nr   58  <|@ instruction MOV x: [r15|QWORD + 1156] y: -2323 size: DWORD <|@ <|@
      nr   60  <|@ instruction MOV x: [r15|QWORD + 1168] y: 20 size: QWORD <|@ <|@
      nr   62  <|@ st <@st|@live-base-pointers: []
jdk.internal.misc.Blocker.end(Blocker.java:102) [bci: 0]
locals: rsi|QWORD - - - 
>@ <|@ instruction DEOPT info [bci:0] <|@ <|@
    end_IR
  end_block
end_cfg
begin_bytecodes
     0: lload_0       
     1: lconst_0      
     2: lcmp          
     3: iflt          70
     6: getstatic     #9          // $assertionsDisabled:boolean
     9: ifne          51
    12: invokestatic  #4          // currentCarrierThread:()java.lang.Thread
    15: astore_3      
    16: aload_3       
    17: instanceof    #26         // jdk.internal.misc.CarrierThread
    20: ifeq          39
    23: aload_3       
    24: checkcast     #26         // jdk.internal.misc.CarrierThread
    27: astore_2      
    28: aload_2       
    29: invokevirtual #5          // jdk.internal.misc.CarrierThread.inBlocking:()boolean
    32: ifeq          39
    35: iconst_1      
    36: goto          40
    39: iconst_0      
    40: ifne          51
    43: new           #48         // java.lang.AssertionError
    46: dup           
    47: invokespecial #10         // java.lang.AssertionError.<init>:()void
    50: athrow        
    51: invokestatic  #4          // currentCarrierThread:()java.lang.Thread
    54: checkcast     #26         // jdk.internal.misc.CarrierThread
    57: astore_2      
    58: aload_2       
    59: invokevirtual #7          // java.util.concurrent.ForkJoinWorkerThread.getPool:()java.util.concurrent.ForkJoinPool
    62: lload_0       
    63: invokestatic  #13         // jdk.internal.misc.Blocker$ForkJoinPools.endCompensatedBlock:(java.util.concurrent.ForkJoinPool, long)void
    66: aload_2       
    67: invokevirtual #11         // jdk.internal.misc.CarrierThread.endBlocking:()void
    70: return        
   <|@
end_bytecodes
begin_cfg
  name "After EdgeMoveOptimizer"
  begin_block
    name "B0"
    from_bci -1
    to_bci -1
    predecessors 
    successors "B1" "B2" 
    xhandlers
    flags 
    probability 4607182418800017408
    begin_IR
      LIR
      nr    0  <|@ instruction [rsi|QWORD, rbp|QWORD] = LABEL alignment: 0 numbPhis: 0 label: ? <|@ <|@
      nr    2  <|@ instruction NOP <|@ <|@
      nr    4  <|@ instruction NOP <|@ <|@
      nr    6  <|@ instruction NOP <|@ <|@
      nr    8  <|@ instruction NOP <|@ <|@
      nr   10  <|@ instruction NOP <|@ <|@
      nr   12  <|@ instruction NOP <|@ <|@
      nr   14  <|@ instruction NOP <|@ <|@
      nr   16  <|@ instruction stack:16|QWORD = MOVE input: rbp|QWORD moveKind: QWORD <|@ <|@
      nr   18  <|@ instruction [] = HOTSPOTLOCKSTACK frameMapBuilder: jdk.graal.compiler.hotspot.amd64.AMD64HotSpotFrameMapBuilder@abb5079 slotKind: QWORD <|@ <|@
      nr   22  <|@ instruction TESTBRANCH (x: rsi|QWORD, y: rsi|QWORD) trueDestinationProbability: 1.0 condition: < trueDestination: B0 -> B1 falseDestination: B0 -> B2 size: QWORD <|@ <|@
    end_IR
  end_block
  begin_block
    name "B1"
    from_bci -1
    to_bci -1
    predecessors "B0" 
    successors 
    xhandlers
    flags 
    probability 4607182418800017408
    begin_IR
      LIR
      nr   24  <|@ instruction [] = LABEL alignment: 0 numbPhis: 0 label: ? <|@ <|@
      nr   26  <|@ instruction NOP <|@ <|@
      nr   28  <|@ instruction NOP <|@ <|@
      nr   30  <|@ instruction NOP <|@ <|@
      nr   32  <|@ instruction NOP <|@ <|@
      nr   34  <|@ instruction NOP <|@ <|@
      nr   36  <|@ instruction NOP <|@ <|@
      nr   38  <|@ instruction NOP <|@ <|@
      nr   40  <|@ instruction RETURN (savedRbp: stack:16|QWORD, value: -) isStub: false requiresReservedStackAccessCheck: false thread: r15 scratchForSafepointOnReturn: rcx config: jdk.graal.compiler.hotspot.GraalHotSpotVMConfig@4817c460 <|@ <|@
    end_IR
  end_block
  begin_block
    name "B2"
    from_bci -1
    to_bci -1
    predecessors "B0" 
    successors 
    xhandlers
    flags 
    probability 2355382605114769408
    begin_IR
      LIR
      nr   42  <|@ instruction [] = LABEL alignment: 0 numbPhis: 0 label: ? <|@ <|@
      nr   44  <|@ instruction NOP <|@ <|@
      nr   46  <|@ instruction NOP <|@ <|@
      nr   48  <|@ instruction NOP <|@ <|@
      nr   50  <|@ instruction NOP <|@ <|@
      nr   52  <|@ instruction NOP <|@ <|@
      nr   54  <|@ instruction NOP <|@ <|@
      nr   56  <|@ instruction NOP <|@ <|@
      nr   58  <|@ instruction MOV x: [r15|QWORD + 1156] y: -2323 size: DWORD <|@ <|@
      nr   60  <|@ instruction MOV x: [r15|QWORD + 1168] y: 20 size: QWORD <|@ <|@
      nr   62  <|@ st <@st|@live-base-pointers: []
jdk.internal.misc.Blocker.end(Blocker.java:102) [bci: 0]
locals: rsi|QWORD - - - 
>@ <|@ instruction DEOPT info [bci:0] <|@ <|@
    end_IR
  end_block
end_cfg
begin_bytecodes
     0: lload_0       
     1: lconst_0      
     2: lcmp          
     3: iflt          70
     6: getstatic     #9          // $assertionsDisabled:boolean
     9: ifne          51
    12: invokestatic  #4          // currentCarrierThread:()java.lang.Thread
    15: astore_3      
    16: aload_3       
    17: instanceof    #26         // jdk.internal.misc.CarrierThread
    20: ifeq          39
    23: aload_3       
    24: checkcast     #26         // jdk.internal.misc.CarrierThread
    27: astore_2      
    28: aload_2       
    29: invokevirtual #5          // jdk.internal.misc.CarrierThread.inBlocking:()boolean
    32: ifeq          39
    35: iconst_1      
    36: goto          40
    39: iconst_0      
    40: ifne          51
    43: new           #48         // java.lang.AssertionError
    46: dup           
    47: invokespecial #10         // java.lang.AssertionError.<init>:()void
    50: athrow        
    51: invokestatic  #4          // currentCarrierThread:()java.lang.Thread
    54: checkcast     #26         // jdk.internal.misc.CarrierThread
    57: astore_2      
    58: aload_2       
    59: invokevirtual #7          // java.util.concurrent.ForkJoinWorkerThread.getPool:()java.util.concurrent.ForkJoinPool
    62: lload_0       
    63: invokestatic  #13         // jdk.internal.misc.Blocker$ForkJoinPools.endCompensatedBlock:(java.util.concurrent.ForkJoinPool, long)void
    66: aload_2       
    67: invokevirtual #11         // jdk.internal.misc.CarrierThread.endBlocking:()void
    70: return        
   <|@
end_bytecodes
begin_cfg
  name "After RedundantMoveElimination"
  begin_block
    name "B0"
    from_bci -1
    to_bci -1
    predecessors 
    successors "B1" "B2" 
    xhandlers
    flags 
    probability 4607182418800017408
    begin_IR
      LIR
      nr    0  <|@ instruction [rsi|QWORD, rbp|QWORD] = LABEL alignment: 0 numbPhis: 0 label: ? <|@ <|@
      nr    2  <|@ instruction NOP <|@ <|@
      nr    4  <|@ instruction NOP <|@ <|@
      nr    6  <|@ instruction NOP <|@ <|@
      nr    8  <|@ instruction NOP <|@ <|@
      nr   10  <|@ instruction NOP <|@ <|@
      nr   12  <|@ instruction NOP <|@ <|@
      nr   14  <|@ instruction NOP <|@ <|@
      nr   16  <|@ instruction stack:16|QWORD = MOVE input: rbp|QWORD moveKind: QWORD <|@ <|@
      nr   18  <|@ instruction [] = HOTSPOTLOCKSTACK frameMapBuilder: jdk.graal.compiler.hotspot.amd64.AMD64HotSpotFrameMapBuilder@abb5079 slotKind: QWORD <|@ <|@
      nr   22  <|@ instruction TESTBRANCH (x: rsi|QWORD, y: rsi|QWORD) trueDestinationProbability: 1.0 condition: < trueDestination: B0 -> B1 falseDestination: B0 -> B2 size: QWORD <|@ <|@
    end_IR
  end_block
  begin_block
    name "B1"
    from_bci -1
    to_bci -1
    predecessors "B0" 
    successors 
    xhandlers
    flags 
    probability 4607182418800017408
    begin_IR
      LIR
      nr   24  <|@ instruction [] = LABEL alignment: 0 numbPhis: 0 label: ? <|@ <|@
      nr   26  <|@ instruction NOP <|@ <|@
      nr   28  <|@ instruction NOP <|@ <|@
      nr   30  <|@ instruction NOP <|@ <|@
      nr   32  <|@ instruction NOP <|@ <|@
      nr   34  <|@ instruction NOP <|@ <|@
      nr   36  <|@ instruction NOP <|@ <|@
      nr   38  <|@ instruction NOP <|@ <|@
      nr   40  <|@ instruction RETURN (savedRbp: stack:16|QWORD, value: -) isStub: false requiresReservedStackAccessCheck: false thread: r15 scratchForSafepointOnReturn: rcx config: jdk.graal.compiler.hotspot.GraalHotSpotVMConfig@4817c460 <|@ <|@
    end_IR
  end_block
  begin_block
    name "B2"
    from_bci -1
    to_bci -1
    predecessors "B0" 
    successors 
    xhandlers
    flags 
    probability 2355382605114769408
    begin_IR
      LIR
      nr   42  <|@ instruction [] = LABEL alignment: 0 numbPhis: 0 label: ? <|@ <|@
      nr   44  <|@ instruction NOP <|@ <|@
      nr   46  <|@ instruction NOP <|@ <|@
      nr   48  <|@ instruction NOP <|@ <|@
      nr   50  <|@ instruction NOP <|@ <|@
      nr   52  <|@ instruction NOP <|@ <|@
      nr   54  <|@ instruction NOP <|@ <|@
      nr   56  <|@ instruction NOP <|@ <|@
      nr   58  <|@ instruction MOV x: [r15|QWORD + 1156] y: -2323 size: DWORD <|@ <|@
      nr   60  <|@ instruction MOV x: [r15|QWORD + 1168] y: 20 size: QWORD <|@ <|@
      nr   62  <|@ st <@st|@live-base-pointers: []
jdk.internal.misc.Blocker.end(Blocker.java:102) [bci: 0]
locals: rsi|QWORD - - - 
>@ <|@ instruction DEOPT info [bci:0] <|@ <|@
    end_IR
  end_block
end_cfg
begin_bytecodes
     0: lload_0       
     1: lconst_0      
     2: lcmp          
     3: iflt          70
     6: getstatic     #9          // $assertionsDisabled:boolean
     9: ifne          51
    12: invokestatic  #4          // currentCarrierThread:()java.lang.Thread
    15: astore_3      
    16: aload_3       
    17: instanceof    #26         // jdk.internal.misc.CarrierThread
    20: ifeq          39
    23: aload_3       
    24: checkcast     #26         // jdk.internal.misc.CarrierThread
    27: astore_2      
    28: aload_2       
    29: invokevirtual #5          // jdk.internal.misc.CarrierThread.inBlocking:()boolean
    32: ifeq          39
    35: iconst_1      
    36: goto          40
    39: iconst_0      
    40: ifne          51
    43: new           #48         // java.lang.AssertionError
    46: dup           
    47: invokespecial #10         // java.lang.AssertionError.<init>:()void
    50: athrow        
    51: invokestatic  #4          // currentCarrierThread:()java.lang.Thread
    54: checkcast     #26         // jdk.internal.misc.CarrierThread
    57: astore_2      
    58: aload_2       
    59: invokevirtual #7          // java.util.concurrent.ForkJoinWorkerThread.getPool:()java.util.concurrent.ForkJoinPool
    62: lload_0       
    63: invokestatic  #13         // jdk.internal.misc.Blocker$ForkJoinPools.endCompensatedBlock:(java.util.concurrent.ForkJoinPool, long)void
    66: aload_2       
    67: invokevirtual #11         // jdk.internal.misc.CarrierThread.endBlocking:()void
    70: return        
   <|@
end_bytecodes
begin_cfg
  name "After NullCheckOptimizer"
  begin_block
    name "B0"
    from_bci -1
    to_bci -1
    predecessors 
    successors "B1" "B2" 
    xhandlers
    flags 
    probability 4607182418800017408
    begin_IR
      LIR
      nr    0  <|@ instruction [rsi|QWORD, rbp|QWORD] = LABEL alignment: 0 numbPhis: 0 label: ? <|@ <|@
      nr    2  <|@ instruction NOP <|@ <|@
      nr    4  <|@ instruction NOP <|@ <|@
      nr    6  <|@ instruction NOP <|@ <|@
      nr    8  <|@ instruction NOP <|@ <|@
      nr   10  <|@ instruction NOP <|@ <|@
      nr   12  <|@ instruction NOP <|@ <|@
      nr   14  <|@ instruction NOP <|@ <|@
      nr   16  <|@ instruction stack:16|QWORD = MOVE input: rbp|QWORD moveKind: QWORD <|@ <|@
      nr   18  <|@ instruction [] = HOTSPOTLOCKSTACK frameMapBuilder: jdk.graal.compiler.hotspot.amd64.AMD64HotSpotFrameMapBuilder@abb5079 slotKind: QWORD <|@ <|@
      nr   22  <|@ instruction TESTBRANCH (x: rsi|QWORD, y: rsi|QWORD) trueDestinationProbability: 1.0 condition: < trueDestination: B0 -> B1 falseDestination: B0 -> B2 size: QWORD <|@ <|@
    end_IR
  end_block
  begin_block
    name "B1"
    from_bci -1
    to_bci -1
    predecessors "B0" 
    successors 
    xhandlers
    flags 
    probability 4607182418800017408
    begin_IR
      LIR
      nr   24  <|@ instruction [] = LABEL alignment: 0 numbPhis: 0 label: ? <|@ <|@
      nr   26  <|@ instruction NOP <|@ <|@
      nr   28  <|@ instruction NOP <|@ <|@
      nr   30  <|@ instruction NOP <|@ <|@
      nr   32  <|@ instruction NOP <|@ <|@
      nr   34  <|@ instruction NOP <|@ <|@
      nr   36  <|@ instruction NOP <|@ <|@
      nr   38  <|@ instruction NOP <|@ <|@
      nr   40  <|@ instruction RETURN (savedRbp: stack:16|QWORD, value: -) isStub: false requiresReservedStackAccessCheck: false thread: r15 scratchForSafepointOnReturn: rcx config: jdk.graal.compiler.hotspot.GraalHotSpotVMConfig@4817c460 <|@ <|@
    end_IR
  end_block
  begin_block
    name "B2"
    from_bci -1
    to_bci -1
    predecessors "B0" 
    successors 
    xhandlers
    flags 
    probability 2355382605114769408
    begin_IR
      LIR
      nr   42  <|@ instruction [] = LABEL alignment: 0 numbPhis: 0 label: ? <|@ <|@
      nr   44  <|@ instruction NOP <|@ <|@
      nr   46  <|@ instruction NOP <|@ <|@
      nr   48  <|@ instruction NOP <|@ <|@
      nr   50  <|@ instruction NOP <|@ <|@
      nr   52  <|@ instruction NOP <|@ <|@
      nr   54  <|@ instruction NOP <|@ <|@
      nr   56  <|@ instruction NOP <|@ <|@
      nr   58  <|@ instruction MOV x: [r15|QWORD + 1156] y: -2323 size: DWORD <|@ <|@
      nr   60  <|@ instruction MOV x: [r15|QWORD + 1168] y: 20 size: QWORD <|@ <|@
      nr   62  <|@ st <@st|@live-base-pointers: []
jdk.internal.misc.Blocker.end(Blocker.java:102) [bci: 0]
locals: rsi|QWORD - - - 
>@ <|@ instruction DEOPT info [bci:0] <|@ <|@
    end_IR
  end_block
end_cfg
begin_bytecodes
     0: lload_0       
     1: lconst_0      
     2: lcmp          
     3: iflt          70
     6: getstatic     #9          // $assertionsDisabled:boolean
     9: ifne          51
    12: invokestatic  #4          // currentCarrierThread:()java.lang.Thread
    15: astore_3      
    16: aload_3       
    17: instanceof    #26         // jdk.internal.misc.CarrierThread
    20: ifeq          39
    23: aload_3       
    24: checkcast     #26         // jdk.internal.misc.CarrierThread
    27: astore_2      
    28: aload_2       
    29: invokevirtual #5          // jdk.internal.misc.CarrierThread.inBlocking:()boolean
    32: ifeq          39
    35: iconst_1      
    36: goto          40
    39: iconst_0      
    40: ifne          51
    43: new           #48         // java.lang.AssertionError
    46: dup           
    47: invokespecial #10         // java.lang.AssertionError.<init>:()void
    50: athrow        
    51: invokestatic  #4          // currentCarrierThread:()java.lang.Thread
    54: checkcast     #26         // jdk.internal.misc.CarrierThread
    57: astore_2      
    58: aload_2       
    59: invokevirtual #7          // java.util.concurrent.ForkJoinWorkerThread.getPool:()java.util.concurrent.ForkJoinPool
    62: lload_0       
    63: invokestatic  #13         // jdk.internal.misc.Blocker$ForkJoinPools.endCompensatedBlock:(java.util.concurrent.ForkJoinPool, long)void
    66: aload_2       
    67: invokevirtual #11         // jdk.internal.misc.CarrierThread.endBlocking:()void
    70: return        
   <|@
end_bytecodes
begin_cfg
  name "After ControlFlowOptimizer"
  begin_block
    name "B0"
    from_bci -1
    to_bci -1
    predecessors 
    successors "B1" "B2" 
    xhandlers
    flags 
    probability 4607182418800017408
    begin_IR
      LIR
      nr    0  <|@ instruction [rsi|QWORD, rbp|QWORD] = LABEL alignment: 0 numbPhis: 0 label: ? <|@ <|@
      nr    2  <|@ instruction NOP <|@ <|@
      nr    4  <|@ instruction NOP <|@ <|@
      nr    6  <|@ instruction NOP <|@ <|@
      nr    8  <|@ instruction NOP <|@ <|@
      nr   10  <|@ instruction NOP <|@ <|@
      nr   12  <|@ instruction NOP <|@ <|@
      nr   14  <|@ instruction NOP <|@ <|@
      nr   16  <|@ instruction stack:16|QWORD = MOVE input: rbp|QWORD moveKind: QWORD <|@ <|@
      nr   18  <|@ instruction [] = HOTSPOTLOCKSTACK frameMapBuilder: jdk.graal.compiler.hotspot.amd64.AMD64HotSpotFrameMapBuilder@abb5079 slotKind: QWORD <|@ <|@
      nr   22  <|@ instruction TESTBRANCH (x: rsi|QWORD, y: rsi|QWORD) trueDestinationProbability: 1.0 condition: < trueDestination: B0 -> B1 falseDestination: B0 -> B2 size: QWORD <|@ <|@
    end_IR
  end_block
  begin_block
    name "B1"
    from_bci -1
    to_bci -1
    predecessors "B0" 
    successors 
    xhandlers
    flags 
    probability 4607182418800017408
    begin_IR
      LIR
      nr   24  <|@ instruction [] = LABEL alignment: 0 numbPhis: 0 label: ? <|@ <|@
      nr   26  <|@ instruction NOP <|@ <|@
      nr   28  <|@ instruction NOP <|@ <|@
      nr   30  <|@ instruction NOP <|@ <|@
      nr   32  <|@ instruction NOP <|@ <|@
      nr   34  <|@ instruction NOP <|@ <|@
      nr   36  <|@ instruction NOP <|@ <|@
      nr   38  <|@ instruction NOP <|@ <|@
      nr   40  <|@ instruction RETURN (savedRbp: stack:16|QWORD, value: -) isStub: false requiresReservedStackAccessCheck: false thread: r15 scratchForSafepointOnReturn: rcx config: jdk.graal.compiler.hotspot.GraalHotSpotVMConfig@4817c460 <|@ <|@
    end_IR
  end_block
  begin_block
    name "B2"
    from_bci -1
    to_bci -1
    predecessors "B0" 
    successors 
    xhandlers
    flags 
    probability 2355382605114769408
    begin_IR
      LIR
      nr   42  <|@ instruction [] = LABEL alignment: 0 numbPhis: 0 label: ? <|@ <|@
      nr   44  <|@ instruction NOP <|@ <|@
      nr   46  <|@ instruction NOP <|@ <|@
      nr   48  <|@ instruction NOP <|@ <|@
      nr   50  <|@ instruction NOP <|@ <|@
      nr   52  <|@ instruction NOP <|@ <|@
      nr   54  <|@ instruction NOP <|@ <|@
      nr   56  <|@ instruction NOP <|@ <|@
      nr   58  <|@ instruction MOV x: [r15|QWORD + 1156] y: -2323 size: DWORD <|@ <|@
      nr   60  <|@ instruction MOV x: [r15|QWORD + 1168] y: 20 size: QWORD <|@ <|@
      nr   62  <|@ st <@st|@live-base-pointers: []
jdk.internal.misc.Blocker.end(Blocker.java:102) [bci: 0]
locals: rsi|QWORD - - - 
>@ <|@ instruction DEOPT info [bci:0] <|@ <|@
    end_IR
  end_block
end_cfg
begin_bytecodes
     0: lload_0       
     1: lconst_0      
     2: lcmp          
     3: iflt          70
     6: getstatic     #9          // $assertionsDisabled:boolean
     9: ifne          51
    12: invokestatic  #4          // currentCarrierThread:()java.lang.Thread
    15: astore_3      
    16: aload_3       
    17: instanceof    #26         // jdk.internal.misc.CarrierThread
    20: ifeq          39
    23: aload_3       
    24: checkcast     #26         // jdk.internal.misc.CarrierThread
    27: astore_2      
    28: aload_2       
    29: invokevirtual #5          // jdk.internal.misc.CarrierThread.inBlocking:()boolean
    32: ifeq          39
    35: iconst_1      
    36: goto          40
    39: iconst_0      
    40: ifne          51
    43: new           #48         // java.lang.AssertionError
    46: dup           
    47: invokespecial #10         // java.lang.AssertionError.<init>:()void
    50: athrow        
    51: invokestatic  #4          // currentCarrierThread:()java.lang.Thread
    54: checkcast     #26         // jdk.internal.misc.CarrierThread
    57: astore_2      
    58: aload_2       
    59: invokevirtual #7          // java.util.concurrent.ForkJoinWorkerThread.getPool:()java.util.concurrent.ForkJoinPool
    62: lload_0       
    63: invokestatic  #13         // jdk.internal.misc.Blocker$ForkJoinPools.endCompensatedBlock:(java.util.concurrent.ForkJoinPool, long)void
    66: aload_2       
    67: invokevirtual #11         // jdk.internal.misc.CarrierThread.endBlocking:()void
    70: return        
   <|@
end_bytecodes
begin_cfg
  name "After ComputeCodeEmissionOrder"
  begin_block
    name "B0"
    from_bci -1
    to_bci -1
    predecessors 
    successors "B1" "B2" 
    xhandlers
    flags 
    probability 4607182418800017408
    begin_IR
      LIR
      nr    0  <|@ instruction [rsi|QWORD, rbp|QWORD] = LABEL alignment: 0 numbPhis: 0 label: ? <|@ <|@
      nr    2  <|@ instruction NOP <|@ <|@
      nr    4  <|@ instruction NOP <|@ <|@
      nr    6  <|@ instruction NOP <|@ <|@
      nr    8  <|@ instruction NOP <|@ <|@
      nr   10  <|@ instruction NOP <|@ <|@
      nr   12  <|@ instruction NOP <|@ <|@
      nr   14  <|@ instruction NOP <|@ <|@
      nr   16  <|@ instruction stack:16|QWORD = MOVE input: rbp|QWORD moveKind: QWORD <|@ <|@
      nr   18  <|@ instruction [] = HOTSPOTLOCKSTACK frameMapBuilder: jdk.graal.compiler.hotspot.amd64.AMD64HotSpotFrameMapBuilder@abb5079 slotKind: QWORD <|@ <|@
      nr   22  <|@ instruction TESTBRANCH (x: rsi|QWORD, y: rsi|QWORD) trueDestinationProbability: 1.0 condition: < trueDestination: B0 -> B1 falseDestination: B0 -> B2 size: QWORD <|@ <|@
    end_IR
  end_block
  begin_block
    name "B1"
    from_bci -1
    to_bci -1
    predecessors "B0" 
    successors 
    xhandlers
    flags 
    probability 4607182418800017408
    begin_IR
      LIR
      nr   24  <|@ instruction [] = LABEL alignment: 0 numbPhis: 0 label: ? <|@ <|@
      nr   26  <|@ instruction NOP <|@ <|@
      nr   28  <|@ instruction NOP <|@ <|@
      nr   30  <|@ instruction NOP <|@ <|@
      nr   32  <|@ instruction NOP <|@ <|@
      nr   34  <|@ instruction NOP <|@ <|@
      nr   36  <|@ instruction NOP <|@ <|@
      nr   38  <|@ instruction NOP <|@ <|@
      nr   40  <|@ instruction RETURN (savedRbp: stack:16|QWORD, value: -) isStub: false requiresReservedStackAccessCheck: false thread: r15 scratchForSafepointOnReturn: rcx config: jdk.graal.compiler.hotspot.GraalHotSpotVMConfig@4817c460 <|@ <|@
    end_IR
  end_block
  begin_block
    name "B2"
    from_bci -1
    to_bci -1
    predecessors "B0" 
    successors 
    xhandlers
    flags 
    probability 2355382605114769408
    begin_IR
      LIR
      nr   42  <|@ instruction [] = LABEL alignment: 0 numbPhis: 0 label: ? <|@ <|@
      nr   44  <|@ instruction NOP <|@ <|@
      nr   46  <|@ instruction NOP <|@ <|@
      nr   48  <|@ instruction NOP <|@ <|@
      nr   50  <|@ instruction NOP <|@ <|@
      nr   52  <|@ instruction NOP <|@ <|@
      nr   54  <|@ instruction NOP <|@ <|@
      nr   56  <|@ instruction NOP <|@ <|@
      nr   58  <|@ instruction MOV x: [r15|QWORD + 1156] y: -2323 size: DWORD <|@ <|@
      nr   60  <|@ instruction MOV x: [r15|QWORD + 1168] y: 20 size: QWORD <|@ <|@
      nr   62  <|@ st <@st|@live-base-pointers: []
jdk.internal.misc.Blocker.end(Blocker.java:102) [bci: 0]
locals: rsi|QWORD - - - 
>@ <|@ instruction DEOPT info [bci:0] <|@ <|@
    end_IR
  end_block
end_cfg
begin_bytecodes
     0: lload_0       
     1: lconst_0      
     2: lcmp          
     3: iflt          70
     6: getstatic     #9          // $assertionsDisabled:boolean
     9: ifne          51
    12: invokestatic  #4          // currentCarrierThread:()java.lang.Thread
    15: astore_3      
    16: aload_3       
    17: instanceof    #26         // jdk.internal.misc.CarrierThread
    20: ifeq          39
    23: aload_3       
    24: checkcast     #26         // jdk.internal.misc.CarrierThread
    27: astore_2      
    28: aload_2       
    29: invokevirtual #5          // jdk.internal.misc.CarrierThread.inBlocking:()boolean
    32: ifeq          39
    35: iconst_1      
    36: goto          40
    39: iconst_0      
    40: ifne          51
    43: new           #48         // java.lang.AssertionError
    46: dup           
    47: invokespecial #10         // java.lang.AssertionError.<init>:()void
    50: athrow        
    51: invokestatic  #4          // currentCarrierThread:()java.lang.Thread
    54: checkcast     #26         // jdk.internal.misc.CarrierThread
    57: astore_2      
    58: aload_2       
    59: invokevirtual #7          // java.util.concurrent.ForkJoinWorkerThread.getPool:()java.util.concurrent.ForkJoinPool
    62: lload_0       
    63: invokestatic  #13         // jdk.internal.misc.Blocker$ForkJoinPools.endCompensatedBlock:(java.util.concurrent.ForkJoinPool, long)void
    66: aload_2       
    67: invokevirtual #11         // jdk.internal.misc.CarrierThread.endBlocking:()void
    70: return        
   <|@
end_bytecodes
begin_cfg
  name "After StackMoveOptimization"
  begin_block
    name "B0"
    from_bci -1
    to_bci -1
    predecessors 
    successors "B1" "B2" 
    xhandlers
    flags 
    probability 4607182418800017408
    begin_IR
      LIR
      nr    0  <|@ instruction [rsi|QWORD, rbp|QWORD] = LABEL alignment: 0 numbPhis: 0 label: ? <|@ <|@
      nr    2  <|@ instruction NOP <|@ <|@
      nr    4  <|@ instruction NOP <|@ <|@
      nr    6  <|@ instruction NOP <|@ <|@
      nr    8  <|@ instruction NOP <|@ <|@
      nr   10  <|@ instruction NOP <|@ <|@
      nr   12  <|@ instruction NOP <|@ <|@
      nr   14  <|@ instruction NOP <|@ <|@
      nr   16  <|@ instruction stack:16|QWORD = MOVE input: rbp|QWORD moveKind: QWORD <|@ <|@
      nr   18  <|@ instruction [] = HOTSPOTLOCKSTACK frameMapBuilder: jdk.graal.compiler.hotspot.amd64.AMD64HotSpotFrameMapBuilder@abb5079 slotKind: QWORD <|@ <|@
      nr   22  <|@ instruction TESTBRANCH (x: rsi|QWORD, y: rsi|QWORD) trueDestinationProbability: 1.0 condition: < trueDestination: B0 -> B1 falseDestination: B0 -> B2 size: QWORD <|@ <|@
    end_IR
  end_block
  begin_block
    name "B1"
    from_bci -1
    to_bci -1
    predecessors "B0" 
    successors 
    xhandlers
    flags 
    probability 4607182418800017408
    begin_IR
      LIR
      nr   24  <|@ instruction [] = LABEL alignment: 0 numbPhis: 0 label: ? <|@ <|@
      nr   26  <|@ instruction NOP <|@ <|@
      nr   28  <|@ instruction NOP <|@ <|@
      nr   30  <|@ instruction NOP <|@ <|@
      nr   32  <|@ instruction NOP <|@ <|@
      nr   34  <|@ instruction NOP <|@ <|@
      nr   36  <|@ instruction NOP <|@ <|@
      nr   38  <|@ instruction NOP <|@ <|@
      nr   40  <|@ instruction RETURN (savedRbp: stack:16|QWORD, value: -) isStub: false requiresReservedStackAccessCheck: false thread: r15 scratchForSafepointOnReturn: rcx config: jdk.graal.compiler.hotspot.GraalHotSpotVMConfig@4817c460 <|@ <|@
    end_IR
  end_block
  begin_block
    name "B2"
    from_bci -1
    to_bci -1
    predecessors "B0" 
    successors 
    xhandlers
    flags 
    probability 2355382605114769408
    begin_IR
      LIR
      nr   42  <|@ instruction [] = LABEL alignment: 0 numbPhis: 0 label: ? <|@ <|@
      nr   44  <|@ instruction NOP <|@ <|@
      nr   46  <|@ instruction NOP <|@ <|@
      nr   48  <|@ instruction NOP <|@ <|@
      nr   50  <|@ instruction NOP <|@ <|@
      nr   52  <|@ instruction NOP <|@ <|@
      nr   54  <|@ instruction NOP <|@ <|@
      nr   56  <|@ instruction NOP <|@ <|@
      nr   58  <|@ instruction MOV x: [r15|QWORD + 1156] y: -2323 size: DWORD <|@ <|@
      nr   60  <|@ instruction MOV x: [r15|QWORD + 1168] y: 20 size: QWORD <|@ <|@
      nr   62  <|@ st <@st|@live-base-pointers: []
jdk.internal.misc.Blocker.end(Blocker.java:102) [bci: 0]
locals: rsi|QWORD - - - 
>@ <|@ instruction DEOPT info [bci:0] <|@ <|@
    end_IR
  end_block
end_cfg
begin_bytecodes
     0: lload_0       
     1: lconst_0      
     2: lcmp          
     3: iflt          70
     6: getstatic     #9          // $assertionsDisabled:boolean
     9: ifne          51
    12: invokestatic  #4          // currentCarrierThread:()java.lang.Thread
    15: astore_3      
    16: aload_3       
    17: instanceof    #26         // jdk.internal.misc.CarrierThread
    20: ifeq          39
    23: aload_3       
    24: checkcast     #26         // jdk.internal.misc.CarrierThread
    27: astore_2      
    28: aload_2       
    29: invokevirtual #5          // jdk.internal.misc.CarrierThread.inBlocking:()boolean
    32: ifeq          39
    35: iconst_1      
    36: goto          40
    39: iconst_0      
    40: ifne          51
    43: new           #48         // java.lang.AssertionError
    46: dup           
    47: invokespecial #10         // java.lang.AssertionError.<init>:()void
    50: athrow        
    51: invokestatic  #4          // currentCarrierThread:()java.lang.Thread
    54: checkcast     #26         // jdk.internal.misc.CarrierThread
    57: astore_2      
    58: aload_2       
    59: invokevirtual #7          // java.util.concurrent.ForkJoinWorkerThread.getPool:()java.util.concurrent.ForkJoinPool
    62: lload_0       
    63: invokestatic  #13         // jdk.internal.misc.Blocker$ForkJoinPools.endCompensatedBlock:(java.util.concurrent.ForkJoinPool, long)void
    66: aload_2       
    67: invokevirtual #11         // jdk.internal.misc.CarrierThread.endBlocking:()void
    70: return        
   <|@
end_bytecodes
begin_cfg
  name "After PostAllocationOptimizationStage"
  begin_block
    name "B0"
    from_bci -1
    to_bci -1
    predecessors 
    successors "B1" "B2" 
    xhandlers
    flags 
    probability 4607182418800017408
    begin_IR
      LIR
      nr    0  <|@ instruction [rsi|QWORD, rbp|QWORD] = LABEL alignment: 0 numbPhis: 0 label: ? <|@ <|@
      nr    2  <|@ instruction NOP <|@ <|@
      nr    4  <|@ instruction NOP <|@ <|@
      nr    6  <|@ instruction NOP <|@ <|@
      nr    8  <|@ instruction NOP <|@ <|@
      nr   10  <|@ instruction NOP <|@ <|@
      nr   12  <|@ instruction NOP <|@ <|@
      nr   14  <|@ instruction NOP <|@ <|@
      nr   16  <|@ instruction stack:16|QWORD = MOVE input: rbp|QWORD moveKind: QWORD <|@ <|@
      nr   18  <|@ instruction [] = HOTSPOTLOCKSTACK frameMapBuilder: jdk.graal.compiler.hotspot.amd64.AMD64HotSpotFrameMapBuilder@abb5079 slotKind: QWORD <|@ <|@
      nr   22  <|@ instruction TESTBRANCH (x: rsi|QWORD, y: rsi|QWORD) trueDestinationProbability: 1.0 condition: < trueDestination: B0 -> B1 falseDestination: B0 -> B2 size: QWORD <|@ <|@
    end_IR
  end_block
  begin_block
    name "B1"
    from_bci -1
    to_bci -1
    predecessors "B0" 
    successors 
    xhandlers
    flags 
    probability 4607182418800017408
    begin_IR
      LIR
      nr   24  <|@ instruction [] = LABEL alignment: 0 numbPhis: 0 label: ? <|@ <|@
      nr   26  <|@ instruction NOP <|@ <|@
      nr   28  <|@ instruction NOP <|@ <|@
      nr   30  <|@ instruction NOP <|@ <|@
      nr   32  <|@ instruction NOP <|@ <|@
      nr   34  <|@ instruction NOP <|@ <|@
      nr   36  <|@ instruction NOP <|@ <|@
      nr   38  <|@ instruction NOP <|@ <|@
      nr   40  <|@ instruction RETURN (savedRbp: stack:16|QWORD, value: -) isStub: false requiresReservedStackAccessCheck: false thread: r15 scratchForSafepointOnReturn: rcx config: jdk.graal.compiler.hotspot.GraalHotSpotVMConfig@4817c460 <|@ <|@
    end_IR
  end_block
  begin_block
    name "B2"
    from_bci -1
    to_bci -1
    predecessors "B0" 
    successors 
    xhandlers
    flags 
    probability 2355382605114769408
    begin_IR
      LIR
      nr   42  <|@ instruction [] = LABEL alignment: 0 numbPhis: 0 label: ? <|@ <|@
      nr   44  <|@ instruction NOP <|@ <|@
      nr   46  <|@ instruction NOP <|@ <|@
      nr   48  <|@ instruction NOP <|@ <|@
      nr   50  <|@ instruction NOP <|@ <|@
      nr   52  <|@ instruction NOP <|@ <|@
      nr   54  <|@ instruction NOP <|@ <|@
      nr   56  <|@ instruction NOP <|@ <|@
      nr   58  <|@ instruction MOV x: [r15|QWORD + 1156] y: -2323 size: DWORD <|@ <|@
      nr   60  <|@ instruction MOV x: [r15|QWORD + 1168] y: 20 size: QWORD <|@ <|@
      nr   62  <|@ st <@st|@live-base-pointers: []
jdk.internal.misc.Blocker.end(Blocker.java:102) [bci: 0]
locals: rsi|QWORD - - - 
>@ <|@ instruction DEOPT info [bci:0] <|@ <|@
    end_IR
  end_block
end_cfg
begin_bytecodes
     0: lload_0       
     1: lconst_0      
     2: lcmp          
     3: iflt          70
     6: getstatic     #9          // $assertionsDisabled:boolean
     9: ifne          51
    12: invokestatic  #4          // currentCarrierThread:()java.lang.Thread
    15: astore_3      
    16: aload_3       
    17: instanceof    #26         // jdk.internal.misc.CarrierThread
    20: ifeq          39
    23: aload_3       
    24: checkcast     #26         // jdk.internal.misc.CarrierThread
    27: astore_2      
    28: aload_2       
    29: invokevirtual #5          // jdk.internal.misc.CarrierThread.inBlocking:()boolean
    32: ifeq          39
    35: iconst_1      
    36: goto          40
    39: iconst_0      
    40: ifne          51
    43: new           #48         // java.lang.AssertionError
    46: dup           
    47: invokespecial #10         // java.lang.AssertionError.<init>:()void
    50: athrow        
    51: invokestatic  #4          // currentCarrierThread:()java.lang.Thread
    54: checkcast     #26         // jdk.internal.misc.CarrierThread
    57: astore_2      
    58: aload_2       
    59: invokevirtual #7          // java.util.concurrent.ForkJoinWorkerThread.getPool:()java.util.concurrent.ForkJoinPool
    62: lload_0       
    63: invokestatic  #13         // jdk.internal.misc.Blocker$ForkJoinPools.endCompensatedBlock:(java.util.concurrent.ForkJoinPool, long)void
    66: aload_2       
    67: invokevirtual #11         // jdk.internal.misc.CarrierThread.endBlocking:()void
    70: return        
   <|@
end_bytecodes
begin_cfg
  name "After LocationMarker"
  begin_block
    name "B0"
    from_bci -1
    to_bci -1
    predecessors 
    successors "B1" "B2" 
    xhandlers
    flags 
    probability 4607182418800017408
    begin_IR
      LIR
      nr    0  <|@ instruction [rsi|QWORD, rbp|QWORD] = LABEL alignment: 0 numbPhis: 0 label: ? <|@ <|@
      nr    2  <|@ instruction NOP <|@ <|@
      nr    4  <|@ instruction NOP <|@ <|@
      nr    6  <|@ instruction NOP <|@ <|@
      nr    8  <|@ instruction NOP <|@ <|@
      nr   10  <|@ instruction NOP <|@ <|@
      nr   12  <|@ instruction NOP <|@ <|@
      nr   14  <|@ instruction NOP <|@ <|@
      nr   16  <|@ instruction stack:16|QWORD = MOVE input: rbp|QWORD moveKind: QWORD <|@ <|@
      nr   18  <|@ instruction [] = HOTSPOTLOCKSTACK frameMapBuilder: jdk.graal.compiler.hotspot.amd64.AMD64HotSpotFrameMapBuilder@abb5079 slotKind: QWORD <|@ <|@
      nr   22  <|@ instruction TESTBRANCH (x: rsi|QWORD, y: rsi|QWORD) trueDestinationProbability: 1.0 condition: < trueDestination: B0 -> B1 falseDestination: B0 -> B2 size: QWORD <|@ <|@
    end_IR
  end_block
  begin_block
    name "B1"
    from_bci -1
    to_bci -1
    predecessors "B0" 
    successors 
    xhandlers
    flags 
    probability 4607182418800017408
    begin_IR
      LIR
      nr   24  <|@ instruction [] = LABEL alignment: 0 numbPhis: 0 label: ? <|@ <|@
      nr   26  <|@ instruction NOP <|@ <|@
      nr   28  <|@ instruction NOP <|@ <|@
      nr   30  <|@ instruction NOP <|@ <|@
      nr   32  <|@ instruction NOP <|@ <|@
      nr   34  <|@ instruction NOP <|@ <|@
      nr   36  <|@ instruction NOP <|@ <|@
      nr   38  <|@ instruction NOP <|@ <|@
      nr   40  <|@ instruction RETURN (savedRbp: stack:16|QWORD, value: -) isStub: false requiresReservedStackAccessCheck: false thread: r15 scratchForSafepointOnReturn: rcx config: jdk.graal.compiler.hotspot.GraalHotSpotVMConfig@4817c460 <|@ <|@
    end_IR
  end_block
  begin_block
    name "B2"
    from_bci -1
    to_bci -1
    predecessors "B0" 
    successors 
    xhandlers
    flags 
    probability 2355382605114769408
    begin_IR
      LIR
      nr   42  <|@ instruction [] = LABEL alignment: 0 numbPhis: 0 label: ? <|@ <|@
      nr   44  <|@ instruction NOP <|@ <|@
      nr   46  <|@ instruction NOP <|@ <|@
      nr   48  <|@ instruction NOP <|@ <|@
      nr   50  <|@ instruction NOP <|@ <|@
      nr   52  <|@ instruction NOP <|@ <|@
      nr   54  <|@ instruction NOP <|@ <|@
      nr   56  <|@ instruction NOP <|@ <|@
      nr   58  <|@ instruction MOV x: [r15|QWORD + 1156] y: -2323 size: DWORD <|@ <|@
      nr   60  <|@ instruction MOV x: [r15|QWORD + 1168] y: 20 size: QWORD <|@ <|@
      nr   62  <|@ st <@st|@reference-map: []
live-base-pointers: []
jdk.internal.misc.Blocker.end(Blocker.java:102) [bci: 0]
locals: rsi|QWORD - - - 
>@ <|@ instruction DEOPT info [bci:0] <|@ <|@
    end_IR
  end_block
end_cfg
begin_bytecodes
     0: lload_0       
     1: lconst_0      
     2: lcmp          
     3: iflt          70
     6: getstatic     #9          // $assertionsDisabled:boolean
     9: ifne          51
    12: invokestatic  #4          // currentCarrierThread:()java.lang.Thread
    15: astore_3      
    16: aload_3       
    17: instanceof    #26         // jdk.internal.misc.CarrierThread
    20: ifeq          39
    23: aload_3       
    24: checkcast     #26         // jdk.internal.misc.CarrierThread
    27: astore_2      
    28: aload_2       
    29: invokevirtual #5          // jdk.internal.misc.CarrierThread.inBlocking:()boolean
    32: ifeq          39
    35: iconst_1      
    36: goto          40
    39: iconst_0      
    40: ifne          51
    43: new           #48         // java.lang.AssertionError
    46: dup           
    47: invokespecial #10         // java.lang.AssertionError.<init>:()void
    50: athrow        
    51: invokestatic  #4          // currentCarrierThread:()java.lang.Thread
    54: checkcast     #26         // jdk.internal.misc.CarrierThread
    57: astore_2      
    58: aload_2       
    59: invokevirtual #7          // java.util.concurrent.ForkJoinWorkerThread.getPool:()java.util.concurrent.ForkJoinPool
    62: lload_0       
    63: invokestatic  #13         // jdk.internal.misc.Blocker$ForkJoinPools.endCompensatedBlock:(java.util.concurrent.ForkJoinPool, long)void
    66: aload_2       
    67: invokevirtual #11         // jdk.internal.misc.CarrierThread.endBlocking:()void
    70: return        
   <|@
end_bytecodes
begin_cfg
  name "After FinalCodeAnalysisStage"
  begin_block
    name "B0"
    from_bci -1
    to_bci -1
    predecessors 
    successors "B1" "B2" 
    xhandlers
    flags 
    probability 4607182418800017408
    begin_IR
      LIR
      nr    0  <|@ instruction [rsi|QWORD, rbp|QWORD] = LABEL alignment: 0 numbPhis: 0 label: ? <|@ <|@
      nr    2  <|@ instruction NOP <|@ <|@
      nr    4  <|@ instruction NOP <|@ <|@
      nr    6  <|@ instruction NOP <|@ <|@
      nr    8  <|@ instruction NOP <|@ <|@
      nr   10  <|@ instruction NOP <|@ <|@
      nr   12  <|@ instruction NOP <|@ <|@
      nr   14  <|@ instruction NOP <|@ <|@
      nr   16  <|@ instruction stack:16|QWORD = MOVE input: rbp|QWORD moveKind: QWORD <|@ <|@
      nr   18  <|@ instruction [] = HOTSPOTLOCKSTACK frameMapBuilder: jdk.graal.compiler.hotspot.amd64.AMD64HotSpotFrameMapBuilder@abb5079 slotKind: QWORD <|@ <|@
      nr   22  <|@ instruction TESTBRANCH (x: rsi|QWORD, y: rsi|QWORD) trueDestinationProbability: 1.0 condition: < trueDestination: B0 -> B1 falseDestination: B0 -> B2 size: QWORD <|@ <|@
    end_IR
  end_block
  begin_block
    name "B1"
    from_bci -1
    to_bci -1
    predecessors "B0" 
    successors 
    xhandlers
    flags 
    probability 4607182418800017408
    begin_IR
      LIR
      nr   24  <|@ instruction [] = LABEL alignment: 0 numbPhis: 0 label: ? <|@ <|@
      nr   26  <|@ instruction NOP <|@ <|@
      nr   28  <|@ instruction NOP <|@ <|@
      nr   30  <|@ instruction NOP <|@ <|@
      nr   32  <|@ instruction NOP <|@ <|@
      nr   34  <|@ instruction NOP <|@ <|@
      nr   36  <|@ instruction NOP <|@ <|@
      nr   38  <|@ instruction NOP <|@ <|@
      nr   40  <|@ instruction RETURN (savedRbp: stack:16|QWORD, value: -) isStub: false requiresReservedStackAccessCheck: false thread: r15 scratchForSafepointOnReturn: rcx config: jdk.graal.compiler.hotspot.GraalHotSpotVMConfig@4817c460 <|@ <|@
    end_IR
  end_block
  begin_block
    name "B2"
    from_bci -1
    to_bci -1
    predecessors "B0" 
    successors 
    xhandlers
    flags 
    probability 2355382605114769408
    begin_IR
      LIR
      nr   42  <|@ instruction [] = LABEL alignment: 0 numbPhis: 0 label: ? <|@ <|@
      nr   44  <|@ instruction NOP <|@ <|@
      nr   46  <|@ instruction NOP <|@ <|@
      nr   48  <|@ instruction NOP <|@ <|@
      nr   50  <|@ instruction NOP <|@ <|@
      nr   52  <|@ instruction NOP <|@ <|@
      nr   54  <|@ instruction NOP <|@ <|@
      nr   56  <|@ instruction NOP <|@ <|@
      nr   58  <|@ instruction MOV x: [r15|QWORD + 1156] y: -2323 size: DWORD <|@ <|@
      nr   60  <|@ instruction MOV x: [r15|QWORD + 1168] y: 20 size: QWORD <|@ <|@
      nr   62  <|@ st <@st|@reference-map: []
live-base-pointers: []
jdk.internal.misc.Blocker.end(Blocker.java:102) [bci: 0]
locals: rsi|QWORD - - - 
>@ <|@ instruction DEOPT info [bci:0] <|@ <|@
    end_IR
  end_block
end_cfg
begin_bytecodes
     0: lload_0       
     1: lconst_0      
     2: lcmp          
     3: iflt          70
     6: getstatic     #9          // $assertionsDisabled:boolean
     9: ifne          51
    12: invokestatic  #4          // currentCarrierThread:()java.lang.Thread
    15: astore_3      
    16: aload_3       
    17: instanceof    #26         // jdk.internal.misc.CarrierThread
    20: ifeq          39
    23: aload_3       
    24: checkcast     #26         // jdk.internal.misc.CarrierThread
    27: astore_2      
    28: aload_2       
    29: invokevirtual #5          // jdk.internal.misc.CarrierThread.inBlocking:()boolean
    32: ifeq          39
    35: iconst_1      
    36: goto          40
    39: iconst_0      
    40: ifne          51
    43: new           #48         // java.lang.AssertionError
    46: dup           
    47: invokespecial #10         // java.lang.AssertionError.<init>:()void
    50: athrow        
    51: invokestatic  #4          // currentCarrierThread:()java.lang.Thread
    54: checkcast     #26         // jdk.internal.misc.CarrierThread
    57: astore_2      
    58: aload_2       
    59: invokevirtual #7          // java.util.concurrent.ForkJoinWorkerThread.getPool:()java.util.concurrent.ForkJoinPool
    62: lload_0       
    63: invokestatic  #13         // jdk.internal.misc.Blocker$ForkJoinPools.endCompensatedBlock:(java.util.concurrent.ForkJoinPool, long)void
    66: aload_2       
    67: invokevirtual #11         // jdk.internal.misc.CarrierThread.endBlocking:()void
    70: return        
   <|@
end_bytecodes
begin_cfg
  name "After code generation"
end_cfg
begin_nmethod
  <<<HexCodeFile
  Platform AMD64 64  <||@
  HexCode 0 89842400c0feff4883ec189041817f20000000000f855d0000009090909090909048896c24104885f60f8d1e00000090909090909090488b6c24104883c418493ba7500400000f8738000000c39090909090909041c78784040000edf6ffff49c7879004000014000000e8000000000f1f84000000000048896c2410e800000000eb97f4488d0db4ffffff49898f68040000e969fffffff4e800000000f4e800000000f4  <||@
  Comment 0 [stack overflow check]  <||@
  Comment 0 VERIFIED_ENTRY  <||@
  Comment 12 FRAME_COMPLETE  <||@
  Comment 12 ENTRY_BARRIER_PATCH  <||@
  Comment 26 block B0 null  <||@
  Comment 26 0 [rsi|QWORD, rbp|QWORD] = LABEL alignment: 0 numbPhis: 0 label: ?  <||@
  Comment 26 2 NOP  <||@
  Comment 27 4 NOP  <||@
  Comment 28 6 NOP  <||@
  Comment 29 8 NOP  <||@
  Comment 30 10 NOP  <||@
  Comment 31 12 NOP  <||@
  Comment 32 14 NOP  <||@
  Comment 33 16 stack:16|QWORD = MOVE input: rbp|QWORD moveKind: QWORD  <||@
  Comment 38 18 [] = HOTSPOTLOCKSTACK frameMapBuilder: jdk.graal.compiler.hotspot.amd64.AMD64HotSpotFrameMapBuilder@abb5079 slotKind: QWORD  <||@
  Comment 38 22 TESTBRANCH (x: rsi|QWORD, y: rsi|QWORD) trueDestinationProbability: 1.0 condition: < trueDestination: B0 -> B1 falseDestination: B0 -> B2 size: QWORD  <||@
  Comment 47 block B1 null  <||@
  Comment 47 24 [] = LABEL alignment: 0 numbPhis: 0 label: ?  <||@
  Comment 47 26 NOP  <||@
  Comment 48 28 NOP  <||@
  Comment 49 30 NOP  <||@
  Comment 50 32 NOP  <||@
  Comment 51 34 NOP  <||@
  Comment 52 36 NOP  <||@
  Comment 53 38 NOP  <||@
  Comment 54 40 RETURN (savedRbp: stack:16|QWORD, value: -) isStub: false requiresReservedStackAccessCheck: false thread: r15 scratchForSafepointOnReturn: rcx config: jdk.graal.compiler.hotspot.GraalHotSpotVMConfig@4817c460  <||@
  Comment 63 POLL_RETURN_FAR  <||@
  Comment 77 block B2 null  <||@
  Comment 77 42 [] = LABEL alignment: 0 numbPhis: 0 label: ?  <||@
  Comment 77 44 NOP  <||@
  Comment 78 46 NOP  <||@
  Comment 79 48 NOP  <||@
  Comment 80 50 NOP  <||@
  Comment 81 52 NOP  <||@
  Comment 82 54 NOP  <||@
  Comment 83 56 NOP  <||@
  Comment 84 58 MOV x: [r15|QWORD + 1156] y: -2323 size: DWORD  <||@
  Comment 95 60 MOV x: [r15|QWORD + 1168] y: 20 size: QWORD  <||@
  Comment 106 62 DEOPT info [bci:0]  <||@
  Comment 106 {Field[name=CompilerToVM::Data::SharedRuntime_deopt_blob_uncommon_trap, type=address, offset=0, address=0x7f78b20335a8, value=140155947626874]:0x7f789978b17a}  <||@
  Comment 111 []at jdk.internal.misc.Blocker.end(Blocker.java:102) [bci: 0, duringCall: false, rethrow: false]
              |0          |1  |2  |3 
     locals:  |rsi|QWORD  |-  |-  |-   <||@
  Comment 124 {Field[name=CompilerToVM::Data::nmethod_entry_barrier, type=address, offset=0, address=0x7f78b2033598, value=140155947495968]:0x7f789976b220}  <||@
  Comment 146 {Field[name=CompilerToVM::Data::SharedRuntime_polling_page_return_handler, type=address, offset=0, address=0x7f78b20335a0, value=140155947630592]:0x7f789978c000}  <||@
  Comment 152 {Stub<ExceptionHandlerStub.exceptionHandler>@0x7f78998c5300:CallingConvention[rax|QWORD[.], rdx|QWORD]:CallingConvention[rax|QWORD[.], rdx|QWORD]; temps=rdi|ILLEGAL,xmm14|ILLEGAL,xmm15|ILLEGAL,xmm12|ILLEGAL,xmm13|ILLEGAL,xmm10|ILLEGAL,xmm11|ILLEGAL,xmm7|ILLEGAL,xmm8|ILLEGAL,xmm9|ILLEGAL,xmm0|ILLEGAL,xmm1|ILLEGAL,xmm2|ILLEGAL,xmm3|ILLEGAL,xmm4|ILLEGAL,xmm5|ILLEGAL,xmm6|ILLEGAL,rax|ILLEGAL,rcx|ILLEGAL,rdx|ILLEGAL,rsi|ILLEGAL,r8|ILLEGAL,r9|ILLEGAL,r10|ILLEGAL,r11|ILLEGAL}  <||@
  Comment 152 EXCEPTION_HANDLER_ENTRY  <||@
  Comment 158 {Field[name=CompilerToVM::Data::SharedRuntime_deopt_blob_unpack, type=address, offset=0, address=0x7f78b20335b8, value=140155947626272]:0x7f789978af20}  <||@
  Comment 158 DEOPT_HANDLER_ENTRY  <||@
  HexCodeFile>>> <|@
end_nmethod
begin_compilation
  name " HotSpotCompilation-5326[jdk.internal.misc.Blocker.end(long)]"
  method "HotSpotCompilation-5326[jdk.internal.misc.Blocker.end(long)]"
  date 1724269741094
end_compilation
begin_cfg
  name "After code installation"
end_cfg
begin_nmethod
  <<<HexCodeFile
  Platform AMD64 64  <||@
  HexCode 7f789ae1c380 89842400c0feff4883ec189041817f20000000000f855d0000009090909090909048896c24104885f60f8d1e00000090909090909090488b6c24104883c418493ba7500400000f8738000000c39090909090909041c78784040000edf6ffff49c7879004000014000000e88bed96fe0f1f84000000000048896c2410e81fee94feeb97f4488d0db4ffffff49898f68040000e9e9fb96fef4e8e38eaafef4e8fdea96fef4f4f4f4f4  <||@
  Comment 0 [stack overflow check]  <||@
  Comment 0 VERIFIED_ENTRY  <||@
  Comment 12 FRAME_COMPLETE  <||@
  Comment 12 ENTRY_BARRIER_PATCH  <||@
  Comment 26 block B0 null  <||@
  Comment 26 0 [rsi|QWORD, rbp|QWORD] = LABEL alignment: 0 numbPhis: 0 label: ?  <||@
  Comment 26 2 NOP  <||@
  Comment 27 4 NOP  <||@
  Comment 28 6 NOP  <||@
  Comment 29 8 NOP  <||@
  Comment 30 10 NOP  <||@
  Comment 31 12 NOP  <||@
  Comment 32 14 NOP  <||@
  Comment 33 16 stack:16|QWORD = MOVE input: rbp|QWORD moveKind: QWORD  <||@
  Comment 38 18 [] = HOTSPOTLOCKSTACK frameMapBuilder: jdk.graal.compiler.hotspot.amd64.AMD64HotSpotFrameMapBuilder@abb5079 slotKind: QWORD  <||@
  Comment 38 22 TESTBRANCH (x: rsi|QWORD, y: rsi|QWORD) trueDestinationProbability: 1.0 condition: < trueDestination: B0 -> B1 falseDestination: B0 -> B2 size: QWORD  <||@
  Comment 47 block B1 null  <||@
  Comment 47 24 [] = LABEL alignment: 0 numbPhis: 0 label: ?  <||@
  Comment 47 26 NOP  <||@
  Comment 48 28 NOP  <||@
  Comment 49 30 NOP  <||@
  Comment 50 32 NOP  <||@
  Comment 51 34 NOP  <||@
  Comment 52 36 NOP  <||@
  Comment 53 38 NOP  <||@
  Comment 54 40 RETURN (savedRbp: stack:16|QWORD, value: -) isStub: false requiresReservedStackAccessCheck: false thread: r15 scratchForSafepointOnReturn: rcx config: jdk.graal.compiler.hotspot.GraalHotSpotVMConfig@4817c460  <||@
  Comment 63 POLL_RETURN_FAR  <||@
  Comment 77 block B2 null  <||@
  Comment 77 42 [] = LABEL alignment: 0 numbPhis: 0 label: ?  <||@
  Comment 77 44 NOP  <||@
  Comment 78 46 NOP  <||@
  Comment 79 48 NOP  <||@
  Comment 80 50 NOP  <||@
  Comment 81 52 NOP  <||@
  Comment 82 54 NOP  <||@
  Comment 83 56 NOP  <||@
  Comment 84 58 MOV x: [r15|QWORD + 1156] y: -2323 size: DWORD  <||@
  Comment 95 60 MOV x: [r15|QWORD + 1168] y: 20 size: QWORD  <||@
  Comment 106 62 DEOPT info [bci:0]  <||@
  Comment 106 {Field[name=CompilerToVM::Data::SharedRuntime_deopt_blob_uncommon_trap, type=address, offset=0, address=0x7f78b20335a8, value=140155947626874]:0x7f789978b17a}  <||@
  Comment 111 []at jdk.internal.misc.Blocker.end(Blocker.java:102) [bci: 0, duringCall: false, rethrow: false]
              |0          |1  |2  |3 
     locals:  |rsi|QWORD  |-  |-  |-   <||@
  Comment 124 {Field[name=CompilerToVM::Data::nmethod_entry_barrier, type=address, offset=0, address=0x7f78b2033598, value=140155947495968]:0x7f789976b220}  <||@
  Comment 146 {Field[name=CompilerToVM::Data::SharedRuntime_polling_page_return_handler, type=address, offset=0, address=0x7f78b20335a0, value=140155947630592]:0x7f789978c000}  <||@
  Comment 152 {Stub<ExceptionHandlerStub.exceptionHandler>@0x7f78998c5300:CallingConvention[rax|QWORD[.], rdx|QWORD]:CallingConvention[rax|QWORD[.], rdx|QWORD]; temps=rdi|ILLEGAL,xmm14|ILLEGAL,xmm15|ILLEGAL,xmm12|ILLEGAL,xmm13|ILLEGAL,xmm10|ILLEGAL,xmm11|ILLEGAL,xmm7|ILLEGAL,xmm8|ILLEGAL,xmm9|ILLEGAL,xmm0|ILLEGAL,xmm1|ILLEGAL,xmm2|ILLEGAL,xmm3|ILLEGAL,xmm4|ILLEGAL,xmm5|ILLEGAL,xmm6|ILLEGAL,rax|ILLEGAL,rcx|ILLEGAL,rdx|ILLEGAL,rsi|ILLEGAL,r8|ILLEGAL,r9|ILLEGAL,r10|ILLEGAL,r11|ILLEGAL}  <||@
  Comment 152 EXCEPTION_HANDLER_ENTRY  <||@
  Comment 158 {Field[name=CompilerToVM::Data::SharedRuntime_deopt_blob_unpack, type=address, offset=0, address=0x7f78b20335b8, value=140155947626272]:0x7f789978af20}  <||@
  Comment 158 DEOPT_HANDLER_ENTRY  <||@
  HexCodeFile>>> <|@
end_nmethod
