begin_compilation
  name " HotSpotCompilation-682[java.util.Objects.requireNonNull(Object)]"
  method "HotSpotCompilation-682[java.util.Objects.requireNonNull(Object)]"
  date 1724269729140
end_compilation
begin_cfg
  name "Final HIR schedule"
  begin_block
    name "B0"
    from_bci -1
    to_bci -1
    predecessors 
    successors 
    xhandlers
    flags 
    probability 4607182418800017408
    begin_IR
      HIR
f <@#|@fixed with next>@ <|@
tid v0 <|@
d <@d|@=== Debug Properties ===
hasSpeculationFence: false
stamp: void
=== Inputs ===
stateAfter: - 
=== Succesors ===
next: v14 
=== Usages ===
=== Predecessor ===
- >@ <|@
instruction <@StartNode|@jdk.graal.compiler.nodes.StartNode>@ stateAfter: - #next: v14  <|@  <|@
f <@~|@floating>@ <|@
tid a11 <|@
d <@d|@=== Debug Properties ===
isDefaultStable: false
rawvalue: null
stableDimension: 0
stamp: a java.lang.Object NULL
stampKind: a java.lang.Object
value: Object[null]
=== Inputs ===
=== Succesors ===
=== Usages ===
?2 
=== Predecessor ===
- >@ <|@
instruction <@Constant|@jdk.graal.compiler.nodes.ConstantNode>@  <|@  <|@
tid ?2 <|@
d <@d|@=== Debug Properties ===
bci: 0
bytecode: aload_0
code: ResolvedJavaMethodBytecode<Objects.requireNonNull(Object)>
localsSize: 1
locksSize: 0
sourceFile: Objects.java
sourceLine: 232
stackSize: 0
stackState: BeforePop
validForDeoptimization: true
=== Inputs ===
outerFrameState: - 
values: a11 
=== Succesors ===
=== Usages ===
v14 
=== Predecessor ===
- >@ <|@
instruction <@FrameState|@jdk.graal.compiler.nodes.FrameState>@ outerFrameState: - values: a11  <|@  <|@
f <@~|@floating>@ <|@
tid a1 <|@
d <@d|@=== Debug Properties ===
index: 0
stamp: a java.lang.Object
uncheckedStamp: [null]
=== Inputs ===
=== Succesors ===
=== Usages ===
v6 v14 
=== Predecessor ===
- >@ <|@
instruction <@Parameter|@jdk.graal.compiler.nodes.ParameterNode>@  <|@  <|@
f <@#|@fixed with next>@ <|@
tid v14 <|@
d <@d|@=== Debug Properties ===
deoptReasonAndAction: int[-1811|0xfffffffffffff8ed]
deoptSpeculation: long[20|0x14]
stamp: void
=== Inputs ===
stateBefore: ?2 
object: a1 
=== Succesors ===
next: v6 
=== Usages ===
=== Predecessor ===
v0 >@ <|@
instruction <@NullCheck|@jdk.graal.compiler.nodes.extended.NullCheckNode>@ stateBefore: ?2 object: a1 #next: v6  <|@  <|@
f <@*|@fixed>@ <|@
tid v6 <|@
d <@d|@=== Debug Properties ===
nodeSourcePosition: at java.util.Objects.requireNonNull(Objects.java:234) [bci: 13]
stamp: void
=== Inputs ===
memoryMap: - 
result: a1 
=== Succesors ===
=== Usages ===
=== Predecessor ===
v14 >@ <|@
instruction <@Return|@jdk.graal.compiler.nodes.ReturnNode>@ memoryMap: - result: a1  <|@  <|@
    end_IR
  end_block
end_cfg
begin_cfg
  name "After LIRGeneration"
  begin_block
    name "B0"
    from_bci -1
    to_bci -1
    predecessors 
    successors 
    xhandlers
    flags 
    probability 4607182418800017408
    begin_IR
      LIR
      nr   -1  <|@ instruction [rsi|QWORD[.], rbp|QWORD] = LABEL alignment: 0 numbPhis: 0 label: ? <|@ <|@
      nr   -1  <|@ instruction stack:16|QWORD = MOVE input: rbp|QWORD moveKind: QWORD <|@ <|@
      nr   -1  <|@ instruction [] = HOTSPOTLOCKSTACK frameMapBuilder: jdk.graal.compiler.hotspot.amd64.AMD64HotSpotFrameMapBuilder@77b87d6a slotKind: QWORD <|@ <|@
      nr   -1  <|@ instruction v0|QWORD[.] = MOVE input: rsi|QWORD[.] moveKind: QWORD <|@ <|@
      nr   -1  <|@ st <@st|@java.util.Objects.requireNonNull(Objects.java:232) [bci: 0]
locals: Object[null] 
>@ <|@ instruction NULLCHECK address: [v0|QWORD[.]] state [bci:0] <|@ <|@
      nr   -1  <|@ instruction rax|QWORD[.] = MOVE input: v0|QWORD[.] moveKind: QWORD <|@ <|@
      nr   -1  <|@ instruction RETURN (savedRbp: stack:16|QWORD, value: rax|QWORD[.]) isStub: false requiresReservedStackAccessCheck: false thread: r15 scratchForSafepointOnReturn: rcx config: jdk.graal.compiler.hotspot.GraalHotSpotVMConfig@4817c460 <|@ <|@
    end_IR
  end_block
end_cfg
begin_bytecodes
     0: aload_0       
     1: ifnonnull     12
     4: new           #84         // java.lang.NullPointerException
     7: dup           
     8: invokespecial #17         // java.lang.NullPointerException.<init>:()void
    11: athrow        
    12: aload_0       
    13: areturn       
   <|@
end_bytecodes
begin_cfg
  name "After LIR generation"
  begin_block
    name "B0"
    from_bci -1
    to_bci -1
    predecessors 
    successors 
    xhandlers
    flags 
    probability 4607182418800017408
    begin_IR
      HIR
f <@#|@fixed with next>@ <|@
tid v0 <|@
d <@d|@=== Debug Properties ===
hasSpeculationFence: false
stamp: void
=== Inputs ===
stateAfter: - 
=== Succesors ===
next: v14 
=== Usages ===
=== Predecessor ===
- >@ <|@
instruction <@StartNode|@jdk.graal.compiler.nodes.StartNode>@ stateAfter: - #next: v14  <|@  <|@
f <@~|@floating>@ <|@
tid a11 <|@
result Object[null] <|@
d <@d|@=== Debug Properties ===
isDefaultStable: false
rawvalue: null
stableDimension: 0
stamp: a java.lang.Object NULL
stampKind: a java.lang.Object
value: Object[null]
=== Inputs ===
=== Succesors ===
=== Usages ===
?2 
=== Predecessor ===
- >@ <|@
instruction <@Constant|@jdk.graal.compiler.nodes.ConstantNode>@  <|@  <|@
tid ?2 <|@
d <@d|@=== Debug Properties ===
bci: 0
bytecode: aload_0
code: ResolvedJavaMethodBytecode<Objects.requireNonNull(Object)>
localsSize: 1
locksSize: 0
sourceFile: Objects.java
sourceLine: 232
stackSize: 0
stackState: BeforePop
validForDeoptimization: true
=== Inputs ===
outerFrameState: - 
values: a11 
=== Succesors ===
=== Usages ===
v14 
=== Predecessor ===
- >@ <|@
instruction <@FrameState|@jdk.graal.compiler.nodes.FrameState>@ outerFrameState: - values: a11  <|@  <|@
f <@~|@floating>@ <|@
tid a1 <|@
result v0|QWORD[.] <|@
d <@d|@=== Debug Properties ===
index: 0
stamp: a java.lang.Object
uncheckedStamp: [null]
=== Inputs ===
=== Succesors ===
=== Usages ===
v6 v14 
=== Predecessor ===
- >@ <|@
instruction <@Parameter|@jdk.graal.compiler.nodes.ParameterNode>@  <|@  <|@
f <@#|@fixed with next>@ <|@
tid v14 <|@
d <@d|@=== Debug Properties ===
deoptReasonAndAction: int[-1811|0xfffffffffffff8ed]
deoptSpeculation: long[20|0x14]
stamp: void
=== Inputs ===
stateBefore: ?2 
object: a1 
=== Succesors ===
next: v6 
=== Usages ===
=== Predecessor ===
v0 >@ <|@
instruction <@NullCheck|@jdk.graal.compiler.nodes.extended.NullCheckNode>@ stateBefore: ?2 object: a1 #next: v6  <|@  <|@
f <@*|@fixed>@ <|@
tid v6 <|@
d <@d|@=== Debug Properties ===
nodeSourcePosition: at java.util.Objects.requireNonNull(Objects.java:234) [bci: 13]
stamp: void
=== Inputs ===
memoryMap: - 
result: a1 
=== Succesors ===
=== Usages ===
=== Predecessor ===
v14 >@ <|@
instruction <@Return|@jdk.graal.compiler.nodes.ReturnNode>@ memoryMap: - result: a1  <|@  <|@
    end_IR
    begin_IR
      LIR
      nr   -1  <|@ instruction [rsi|QWORD[.], rbp|QWORD] = LABEL alignment: 0 numbPhis: 0 label: ? <|@ <|@
      nr   -1  <|@ instruction stack:16|QWORD = MOVE input: rbp|QWORD moveKind: QWORD <|@ <|@
      nr   -1  <|@ instruction [] = HOTSPOTLOCKSTACK frameMapBuilder: jdk.graal.compiler.hotspot.amd64.AMD64HotSpotFrameMapBuilder@77b87d6a slotKind: QWORD <|@ <|@
      nr   -1  <|@ instruction v0|QWORD[.] = MOVE input: rsi|QWORD[.] moveKind: QWORD <|@ <|@
      nr   -1  <|@ st <@st|@java.util.Objects.requireNonNull(Objects.java:232) [bci: 0]
locals: Object[null] 
>@ <|@ instruction NULLCHECK address: [v0|QWORD[.]] state [bci:0] <|@ <|@
      nr   -1  <|@ instruction rax|QWORD[.] = MOVE input: v0|QWORD[.] moveKind: QWORD <|@ <|@
      nr   -1  <|@ instruction RETURN (savedRbp: stack:16|QWORD, value: rax|QWORD[.]) isStub: false requiresReservedStackAccessCheck: false thread: r15 scratchForSafepointOnReturn: rcx config: jdk.graal.compiler.hotspot.GraalHotSpotVMConfig@4817c460 <|@ <|@
    end_IR
  end_block
end_cfg
begin_cfg
  name "After LIRGTSlowdown"
  begin_block
    name "B0"
    from_bci -1
    to_bci -1
    predecessors 
    successors 
    xhandlers
    flags 
    probability 4607182418800017408
    begin_IR
      LIR
      nr   -1  <|@ instruction [rsi|QWORD[.], rbp|QWORD] = LABEL alignment: 0 numbPhis: 0 label: ? <|@ <|@
      nr   -1  <|@ instruction NOP <|@ <|@
      nr   -1  <|@ instruction NOP <|@ <|@
      nr   -1  <|@ instruction NOP <|@ <|@
      nr   -1  <|@ instruction NOP <|@ <|@
      nr   -1  <|@ instruction NOP <|@ <|@
      nr   -1  <|@ instruction NOP <|@ <|@
      nr   -1  <|@ instruction NOP <|@ <|@
      nr   -1  <|@ instruction NOP <|@ <|@
      nr   -1  <|@ instruction NOP <|@ <|@
      nr   -1  <|@ instruction NOP <|@ <|@
      nr   -1  <|@ instruction NOP <|@ <|@
      nr   -1  <|@ instruction NOP <|@ <|@
      nr   -1  <|@ instruction stack:16|QWORD = MOVE input: rbp|QWORD moveKind: QWORD <|@ <|@
      nr   -1  <|@ instruction [] = HOTSPOTLOCKSTACK frameMapBuilder: jdk.graal.compiler.hotspot.amd64.AMD64HotSpotFrameMapBuilder@77b87d6a slotKind: QWORD <|@ <|@
      nr   -1  <|@ instruction v0|QWORD[.] = MOVE input: rsi|QWORD[.] moveKind: QWORD <|@ <|@
      nr   -1  <|@ st <@st|@java.util.Objects.requireNonNull(Objects.java:232) [bci: 0]
locals: Object[null] 
>@ <|@ instruction NULLCHECK address: [v0|QWORD[.]] state [bci:0] <|@ <|@
      nr   -1  <|@ instruction rax|QWORD[.] = MOVE input: v0|QWORD[.] moveKind: QWORD <|@ <|@
      nr   -1  <|@ instruction RETURN (savedRbp: stack:16|QWORD, value: rax|QWORD[.]) isStub: false requiresReservedStackAccessCheck: false thread: r15 scratchForSafepointOnReturn: rcx config: jdk.graal.compiler.hotspot.GraalHotSpotVMConfig@4817c460 <|@ <|@
    end_IR
  end_block
end_cfg
begin_bytecodes
     0: aload_0       
     1: ifnonnull     12
     4: new           #84         // java.lang.NullPointerException
     7: dup           
     8: invokespecial #17         // java.lang.NullPointerException.<init>:()void
    11: athrow        
    12: aload_0       
    13: areturn       
   <|@
end_bytecodes
begin_cfg
  name "After ConstantLoadOptimization"
  begin_block
    name "B0"
    from_bci -1
    to_bci -1
    predecessors 
    successors 
    xhandlers
    flags 
    probability 4607182418800017408
    begin_IR
      LIR
      nr   -1  <|@ instruction [rsi|QWORD[.], rbp|QWORD] = LABEL alignment: 0 numbPhis: 0 label: ? <|@ <|@
      nr   -1  <|@ instruction NOP <|@ <|@
      nr   -1  <|@ instruction NOP <|@ <|@
      nr   -1  <|@ instruction NOP <|@ <|@
      nr   -1  <|@ instruction NOP <|@ <|@
      nr   -1  <|@ instruction NOP <|@ <|@
      nr   -1  <|@ instruction NOP <|@ <|@
      nr   -1  <|@ instruction NOP <|@ <|@
      nr   -1  <|@ instruction NOP <|@ <|@
      nr   -1  <|@ instruction NOP <|@ <|@
      nr   -1  <|@ instruction NOP <|@ <|@
      nr   -1  <|@ instruction NOP <|@ <|@
      nr   -1  <|@ instruction NOP <|@ <|@
      nr   -1  <|@ instruction stack:16|QWORD = MOVE input: rbp|QWORD moveKind: QWORD <|@ <|@
      nr   -1  <|@ instruction [] = HOTSPOTLOCKSTACK frameMapBuilder: jdk.graal.compiler.hotspot.amd64.AMD64HotSpotFrameMapBuilder@77b87d6a slotKind: QWORD <|@ <|@
      nr   -1  <|@ instruction v0|QWORD[.] = MOVE input: rsi|QWORD[.] moveKind: QWORD <|@ <|@
      nr   -1  <|@ st <@st|@java.util.Objects.requireNonNull(Objects.java:232) [bci: 0]
locals: Object[null] 
>@ <|@ instruction NULLCHECK address: [v0|QWORD[.]] state [bci:0] <|@ <|@
      nr   -1  <|@ instruction rax|QWORD[.] = MOVE input: v0|QWORD[.] moveKind: QWORD <|@ <|@
      nr   -1  <|@ instruction RETURN (savedRbp: stack:16|QWORD, value: rax|QWORD[.]) isStub: false requiresReservedStackAccessCheck: false thread: r15 scratchForSafepointOnReturn: rcx config: jdk.graal.compiler.hotspot.GraalHotSpotVMConfig@4817c460 <|@ <|@
    end_IR
  end_block
end_cfg
begin_bytecodes
     0: aload_0       
     1: ifnonnull     12
     4: new           #84         // java.lang.NullPointerException
     7: dup           
     8: invokespecial #17         // java.lang.NullPointerException.<init>:()void
    11: athrow        
    12: aload_0       
    13: areturn       
   <|@
end_bytecodes
begin_cfg
  name "After SaveCalleeSaveRegisters"
  begin_block
    name "B0"
    from_bci -1
    to_bci -1
    predecessors 
    successors 
    xhandlers
    flags 
    probability 4607182418800017408
    begin_IR
      LIR
      nr   -1  <|@ instruction [rsi|QWORD[.], rbp|QWORD] = LABEL alignment: 0 numbPhis: 0 label: ? <|@ <|@
      nr   -1  <|@ instruction NOP <|@ <|@
      nr   -1  <|@ instruction NOP <|@ <|@
      nr   -1  <|@ instruction NOP <|@ <|@
      nr   -1  <|@ instruction NOP <|@ <|@
      nr   -1  <|@ instruction NOP <|@ <|@
      nr   -1  <|@ instruction NOP <|@ <|@
      nr   -1  <|@ instruction NOP <|@ <|@
      nr   -1  <|@ instruction NOP <|@ <|@
      nr   -1  <|@ instruction NOP <|@ <|@
      nr   -1  <|@ instruction NOP <|@ <|@
      nr   -1  <|@ instruction NOP <|@ <|@
      nr   -1  <|@ instruction NOP <|@ <|@
      nr   -1  <|@ instruction stack:16|QWORD = MOVE input: rbp|QWORD moveKind: QWORD <|@ <|@
      nr   -1  <|@ instruction [] = HOTSPOTLOCKSTACK frameMapBuilder: jdk.graal.compiler.hotspot.amd64.AMD64HotSpotFrameMapBuilder@77b87d6a slotKind: QWORD <|@ <|@
      nr   -1  <|@ instruction v0|QWORD[.] = MOVE input: rsi|QWORD[.] moveKind: QWORD <|@ <|@
      nr   -1  <|@ st <@st|@java.util.Objects.requireNonNull(Objects.java:232) [bci: 0]
locals: Object[null] 
>@ <|@ instruction NULLCHECK address: [v0|QWORD[.]] state [bci:0] <|@ <|@
      nr   -1  <|@ instruction rax|QWORD[.] = MOVE input: v0|QWORD[.] moveKind: QWORD <|@ <|@
      nr   -1  <|@ instruction RETURN (savedRbp: stack:16|QWORD, value: rax|QWORD[.]) isStub: false requiresReservedStackAccessCheck: false thread: r15 scratchForSafepointOnReturn: rcx config: jdk.graal.compiler.hotspot.GraalHotSpotVMConfig@4817c460 <|@ <|@
    end_IR
  end_block
end_cfg
begin_bytecodes
     0: aload_0       
     1: ifnonnull     12
     4: new           #84         // java.lang.NullPointerException
     7: dup           
     8: invokespecial #17         // java.lang.NullPointerException.<init>:()void
    11: athrow        
    12: aload_0       
    13: areturn       
   <|@
end_bytecodes
begin_cfg
  name "After PreAllocationOptimizationStage"
  begin_block
    name "B0"
    from_bci -1
    to_bci -1
    predecessors 
    successors 
    xhandlers
    flags 
    probability 4607182418800017408
    begin_IR
      LIR
      nr   -1  <|@ instruction [rsi|QWORD[.], rbp|QWORD] = LABEL alignment: 0 numbPhis: 0 label: ? <|@ <|@
      nr   -1  <|@ instruction NOP <|@ <|@
      nr   -1  <|@ instruction NOP <|@ <|@
      nr   -1  <|@ instruction NOP <|@ <|@
      nr   -1  <|@ instruction NOP <|@ <|@
      nr   -1  <|@ instruction NOP <|@ <|@
      nr   -1  <|@ instruction NOP <|@ <|@
      nr   -1  <|@ instruction NOP <|@ <|@
      nr   -1  <|@ instruction NOP <|@ <|@
      nr   -1  <|@ instruction NOP <|@ <|@
      nr   -1  <|@ instruction NOP <|@ <|@
      nr   -1  <|@ instruction NOP <|@ <|@
      nr   -1  <|@ instruction NOP <|@ <|@
      nr   -1  <|@ instruction stack:16|QWORD = MOVE input: rbp|QWORD moveKind: QWORD <|@ <|@
      nr   -1  <|@ instruction [] = HOTSPOTLOCKSTACK frameMapBuilder: jdk.graal.compiler.hotspot.amd64.AMD64HotSpotFrameMapBuilder@77b87d6a slotKind: QWORD <|@ <|@
      nr   -1  <|@ instruction v0|QWORD[.] = MOVE input: rsi|QWORD[.] moveKind: QWORD <|@ <|@
      nr   -1  <|@ st <@st|@java.util.Objects.requireNonNull(Objects.java:232) [bci: 0]
locals: Object[null] 
>@ <|@ instruction NULLCHECK address: [v0|QWORD[.]] state [bci:0] <|@ <|@
      nr   -1  <|@ instruction rax|QWORD[.] = MOVE input: v0|QWORD[.] moveKind: QWORD <|@ <|@
      nr   -1  <|@ instruction RETURN (savedRbp: stack:16|QWORD, value: rax|QWORD[.]) isStub: false requiresReservedStackAccessCheck: false thread: r15 scratchForSafepointOnReturn: rcx config: jdk.graal.compiler.hotspot.GraalHotSpotVMConfig@4817c460 <|@ <|@
    end_IR
  end_block
end_cfg
begin_bytecodes
     0: aload_0       
     1: ifnonnull     12
     4: new           #84         // java.lang.NullPointerException
     7: dup           
     8: invokespecial #17         // java.lang.NullPointerException.<init>:()void
    11: athrow        
    12: aload_0       
    13: areturn       
   <|@
end_bytecodes
begin_cfg
  name "After MarkBasePointers"
  begin_block
    name "B0"
    from_bci -1
    to_bci -1
    predecessors 
    successors 
    xhandlers
    flags 
    probability 4607182418800017408
    begin_IR
      LIR
      nr   -1  <|@ instruction [rsi|QWORD[.], rbp|QWORD] = LABEL alignment: 0 numbPhis: 0 label: ? <|@ <|@
      nr   -1  <|@ instruction NOP <|@ <|@
      nr   -1  <|@ instruction NOP <|@ <|@
      nr   -1  <|@ instruction NOP <|@ <|@
      nr   -1  <|@ instruction NOP <|@ <|@
      nr   -1  <|@ instruction NOP <|@ <|@
      nr   -1  <|@ instruction NOP <|@ <|@
      nr   -1  <|@ instruction NOP <|@ <|@
      nr   -1  <|@ instruction NOP <|@ <|@
      nr   -1  <|@ instruction NOP <|@ <|@
      nr   -1  <|@ instruction NOP <|@ <|@
      nr   -1  <|@ instruction NOP <|@ <|@
      nr   -1  <|@ instruction NOP <|@ <|@
      nr   -1  <|@ instruction stack:16|QWORD = MOVE input: rbp|QWORD moveKind: QWORD <|@ <|@
      nr   -1  <|@ instruction [] = HOTSPOTLOCKSTACK frameMapBuilder: jdk.graal.compiler.hotspot.amd64.AMD64HotSpotFrameMapBuilder@77b87d6a slotKind: QWORD <|@ <|@
      nr   -1  <|@ instruction v0|QWORD[.] = MOVE input: rsi|QWORD[.] moveKind: QWORD <|@ <|@
      nr   -1  <|@ st <@st|@live-base-pointers: []
java.util.Objects.requireNonNull(Objects.java:232) [bci: 0]
locals: Object[null] 
>@ <|@ instruction NULLCHECK address: [v0|QWORD[.]] state [bci:0] <|@ <|@
      nr   -1  <|@ instruction rax|QWORD[.] = MOVE input: v0|QWORD[.] moveKind: QWORD <|@ <|@
      nr   -1  <|@ instruction RETURN (savedRbp: stack:16|QWORD, value: rax|QWORD[.]) isStub: false requiresReservedStackAccessCheck: false thread: r15 scratchForSafepointOnReturn: rcx config: jdk.graal.compiler.hotspot.GraalHotSpotVMConfig@4817c460 <|@ <|@
    end_IR
  end_block
end_cfg
begin_bytecodes
     0: aload_0       
     1: ifnonnull     12
     4: new           #84         // java.lang.NullPointerException
     7: dup           
     8: invokespecial #17         // java.lang.NullPointerException.<init>:()void
    11: athrow        
    12: aload_0       
    13: areturn       
   <|@
end_bytecodes
begin_cfg
  name "Before register allocation"
  begin_block
    name "B0"
    from_bci -1
    to_bci -1
    predecessors 
    successors 
    xhandlers
    flags 
    probability 4607182418800017408
    begin_IR
      LIR
      nr    0  <|@ instruction [rsi|QWORD[.], rbp|QWORD] = LABEL alignment: 0 numbPhis: 0 label: ? <|@ <|@
      nr    2  <|@ instruction NOP <|@ <|@
      nr    4  <|@ instruction NOP <|@ <|@
      nr    6  <|@ instruction NOP <|@ <|@
      nr    8  <|@ instruction NOP <|@ <|@
      nr   10  <|@ instruction NOP <|@ <|@
      nr   12  <|@ instruction NOP <|@ <|@
      nr   14  <|@ instruction NOP <|@ <|@
      nr   16  <|@ instruction NOP <|@ <|@
      nr   18  <|@ instruction NOP <|@ <|@
      nr   20  <|@ instruction NOP <|@ <|@
      nr   22  <|@ instruction NOP <|@ <|@
      nr   24  <|@ instruction NOP <|@ <|@
      nr   26  <|@ instruction stack:16|QWORD = MOVE input: rbp|QWORD moveKind: QWORD <|@ <|@
      nr   28  <|@ instruction [] = HOTSPOTLOCKSTACK frameMapBuilder: jdk.graal.compiler.hotspot.amd64.AMD64HotSpotFrameMapBuilder@77b87d6a slotKind: QWORD <|@ <|@
      nr   30  <|@ instruction v0|QWORD[.] = MOVE input: rsi|QWORD[.] moveKind: QWORD <|@ <|@
      nr   32  <|@ st <@st|@live-base-pointers: []
java.util.Objects.requireNonNull(Objects.java:232) [bci: 0]
locals: Object[null] 
>@ <|@ instruction NULLCHECK address: [v0|QWORD[.]] state [bci:0] <|@ <|@
      nr   34  <|@ instruction rax|QWORD[.] = MOVE input: v0|QWORD[.] moveKind: QWORD <|@ <|@
      nr   36  <|@ instruction RETURN (savedRbp: stack:16|QWORD, value: rax|QWORD[.]) isStub: false requiresReservedStackAccessCheck: false thread: r15 scratchForSafepointOnReturn: rcx config: jdk.graal.compiler.hotspot.GraalHotSpotVMConfig@4817c460 <|@ <|@
    end_IR
  end_block
end_cfg
begin_bytecodes
     0: aload_0       
     1: ifnonnull     12
     4: new           #84         // java.lang.NullPointerException
     7: dup           
     8: invokespecial #17         // java.lang.NullPointerException.<init>:()void
    11: athrow        
    12: aload_0       
    13: areturn       
   <|@
end_bytecodes
begin_cfg
  name "After SSALinearScanLifetimeAnalysis"
  begin_block
    name "B0"
    from_bci -1
    to_bci -1
    predecessors 
    successors 
    xhandlers
    flags 
    probability 4607182418800017408
    begin_IR
      LIR
      nr    0  <|@ instruction [rsi|QWORD[.], rbp|QWORD] = LABEL alignment: 0 numbPhis: 0 label: ? <|@ <|@
      nr    2  <|@ instruction NOP <|@ <|@
      nr    4  <|@ instruction NOP <|@ <|@
      nr    6  <|@ instruction NOP <|@ <|@
      nr    8  <|@ instruction NOP <|@ <|@
      nr   10  <|@ instruction NOP <|@ <|@
      nr   12  <|@ instruction NOP <|@ <|@
      nr   14  <|@ instruction NOP <|@ <|@
      nr   16  <|@ instruction NOP <|@ <|@
      nr   18  <|@ instruction NOP <|@ <|@
      nr   20  <|@ instruction NOP <|@ <|@
      nr   22  <|@ instruction NOP <|@ <|@
      nr   24  <|@ instruction NOP <|@ <|@
      nr   26  <|@ instruction stack:16|QWORD = MOVE input: rbp|QWORD moveKind: QWORD <|@ <|@
      nr   28  <|@ instruction [] = HOTSPOTLOCKSTACK frameMapBuilder: jdk.graal.compiler.hotspot.amd64.AMD64HotSpotFrameMapBuilder@77b87d6a slotKind: QWORD <|@ <|@
      nr   30  <|@ instruction v0|QWORD[.] = MOVE input: rsi|QWORD[.] moveKind: QWORD <|@ <|@
      nr   32  <|@ st <@st|@live-base-pointers: []
java.util.Objects.requireNonNull(Objects.java:232) [bci: 0]
locals: Object[null] 
>@ <|@ instruction NULLCHECK address: [v0|QWORD[.]] state [bci:0] <|@ <|@
      nr   34  <|@ instruction rax|QWORD[.] = MOVE input: v0|QWORD[.] moveKind: QWORD <|@ <|@
      nr   36  <|@ instruction RETURN (savedRbp: stack:16|QWORD, value: rax|QWORD[.]) isStub: false requiresReservedStackAccessCheck: false thread: r15 scratchForSafepointOnReturn: rcx config: jdk.graal.compiler.hotspot.GraalHotSpotVMConfig@4817c460 <|@ <|@
    end_IR
  end_block
end_cfg
begin_bytecodes
     0: aload_0       
     1: ifnonnull     12
     4: new           #84         // java.lang.NullPointerException
     7: dup           
     8: invokespecial #17         // java.lang.NullPointerException.<init>:()void
    11: athrow        
    12: aload_0       
    13: areturn       
   <|@
end_bytecodes
begin_intervals
  name "Before register allocation"
  rax|q fixed "[rax|q]" rax|q v0|q [0, 1[[34, 36[ "NoSpillStore"
  rbp|q fixed "[rbp|q]" rbp|q -1 [0, 26[ "NoSpillStore"
  rsi|q fixed "[rsi|q]" rsi|q -1 [0, 30[ "NoSpillStore"
  v0|q QWORD "[v0|q]" v0|q rsi|q [30, 34[30 MustHaveRegister 32 MustHaveRegister 34 ShouldHaveRegister  "NoSpillStore"
end_intervals
begin_intervals
  name "After register allocation"
  rax|q fixed "[rax|q]" rax|q v0|q [0, 1[[34, 36[ "NoSpillStore"
  rbp|q fixed "[rbp|q]" rbp|q -1 [0, 26[ "NoSpillStore"
  rsi|q fixed "[rsi|q]" rsi|q -1 [0, 30[ "NoSpillStore"
  v0|q QWORD "[rsi|q]" v0|q rsi|q [30, 34[30 MustHaveRegister 32 MustHaveRegister 34 ShouldHaveRegister  "NoSpillStore"
end_intervals
begin_cfg
  name "After LinearScanRegisterAllocation"
  begin_block
    name "B0"
    from_bci -1
    to_bci -1
    predecessors 
    successors 
    xhandlers
    flags 
    probability 4607182418800017408
    begin_IR
      LIR
      nr    0  <|@ instruction [rsi|QWORD[.], rbp|QWORD] = LABEL alignment: 0 numbPhis: 0 label: ? <|@ <|@
      nr    2  <|@ instruction NOP <|@ <|@
      nr    4  <|@ instruction NOP <|@ <|@
      nr    6  <|@ instruction NOP <|@ <|@
      nr    8  <|@ instruction NOP <|@ <|@
      nr   10  <|@ instruction NOP <|@ <|@
      nr   12  <|@ instruction NOP <|@ <|@
      nr   14  <|@ instruction NOP <|@ <|@
      nr   16  <|@ instruction NOP <|@ <|@
      nr   18  <|@ instruction NOP <|@ <|@
      nr   20  <|@ instruction NOP <|@ <|@
      nr   22  <|@ instruction NOP <|@ <|@
      nr   24  <|@ instruction NOP <|@ <|@
      nr   26  <|@ instruction stack:16|QWORD = MOVE input: rbp|QWORD moveKind: QWORD <|@ <|@
      nr   28  <|@ instruction [] = HOTSPOTLOCKSTACK frameMapBuilder: jdk.graal.compiler.hotspot.amd64.AMD64HotSpotFrameMapBuilder@77b87d6a slotKind: QWORD <|@ <|@
      nr   30  <|@ instruction v0|QWORD[.] = MOVE input: rsi|QWORD[.] moveKind: QWORD <|@ <|@
      nr   32  <|@ st <@st|@live-base-pointers: []
java.util.Objects.requireNonNull(Objects.java:232) [bci: 0]
locals: Object[null] 
>@ <|@ instruction NULLCHECK address: [v0|QWORD[.]] state [bci:0] <|@ <|@
      nr   34  <|@ instruction rax|QWORD[.] = MOVE input: v0|QWORD[.] moveKind: QWORD <|@ <|@
      nr   36  <|@ instruction RETURN (savedRbp: stack:16|QWORD, value: rax|QWORD[.]) isStub: false requiresReservedStackAccessCheck: false thread: r15 scratchForSafepointOnReturn: rcx config: jdk.graal.compiler.hotspot.GraalHotSpotVMConfig@4817c460 <|@ <|@
    end_IR
  end_block
end_cfg
begin_bytecodes
     0: aload_0       
     1: ifnonnull     12
     4: new           #84         // java.lang.NullPointerException
     7: dup           
     8: invokespecial #17         // java.lang.NullPointerException.<init>:()void
    11: athrow        
    12: aload_0       
    13: areturn       
   <|@
end_bytecodes
begin_intervals
  name "After optimize spill position"
  rax|q fixed "[rax|q]" rax|q v0|q [0, 1[[34, 36[ "NoSpillStore"
  rbp|q fixed "[rbp|q]" rbp|q -1 [0, 26[ "NoSpillStore"
  rsi|q fixed "[rsi|q]" rsi|q -1 [0, 30[ "NoSpillStore"
  v0|q QWORD "[rsi|q]" v0|q rsi|q [30, 34[30 MustHaveRegister 32 MustHaveRegister 34 ShouldHaveRegister  "NoSpillStore"
end_intervals
begin_cfg
  name "After LinearScanOptimizeSpillPosition"
  begin_block
    name "B0"
    from_bci -1
    to_bci -1
    predecessors 
    successors 
    xhandlers
    flags 
    probability 4607182418800017408
    begin_IR
      LIR
      nr    0  <|@ instruction [rsi|QWORD[.], rbp|QWORD] = LABEL alignment: 0 numbPhis: 0 label: ? <|@ <|@
      nr    2  <|@ instruction NOP <|@ <|@
      nr    4  <|@ instruction NOP <|@ <|@
      nr    6  <|@ instruction NOP <|@ <|@
      nr    8  <|@ instruction NOP <|@ <|@
      nr   10  <|@ instruction NOP <|@ <|@
      nr   12  <|@ instruction NOP <|@ <|@
      nr   14  <|@ instruction NOP <|@ <|@
      nr   16  <|@ instruction NOP <|@ <|@
      nr   18  <|@ instruction NOP <|@ <|@
      nr   20  <|@ instruction NOP <|@ <|@
      nr   22  <|@ instruction NOP <|@ <|@
      nr   24  <|@ instruction NOP <|@ <|@
      nr   26  <|@ instruction stack:16|QWORD = MOVE input: rbp|QWORD moveKind: QWORD <|@ <|@
      nr   28  <|@ instruction [] = HOTSPOTLOCKSTACK frameMapBuilder: jdk.graal.compiler.hotspot.amd64.AMD64HotSpotFrameMapBuilder@77b87d6a slotKind: QWORD <|@ <|@
      nr   30  <|@ instruction v0|QWORD[.] = MOVE input: rsi|QWORD[.] moveKind: QWORD <|@ <|@
      nr   32  <|@ st <@st|@live-base-pointers: []
java.util.Objects.requireNonNull(Objects.java:232) [bci: 0]
locals: Object[null] 
>@ <|@ instruction NULLCHECK address: [v0|QWORD[.]] state [bci:0] <|@ <|@
      nr   34  <|@ instruction rax|QWORD[.] = MOVE input: v0|QWORD[.] moveKind: QWORD <|@ <|@
      nr   36  <|@ instruction RETURN (savedRbp: stack:16|QWORD, value: rax|QWORD[.]) isStub: false requiresReservedStackAccessCheck: false thread: r15 scratchForSafepointOnReturn: rcx config: jdk.graal.compiler.hotspot.GraalHotSpotVMConfig@4817c460 <|@ <|@
    end_IR
  end_block
end_cfg
begin_bytecodes
     0: aload_0       
     1: ifnonnull     12
     4: new           #84         // java.lang.NullPointerException
     7: dup           
     8: invokespecial #17         // java.lang.NullPointerException.<init>:()void
    11: athrow        
    12: aload_0       
    13: areturn       
   <|@
end_bytecodes
begin_intervals
  name "After resolve data flow"
  rax|q fixed "[rax|q]" rax|q v0|q [0, 1[[34, 36[ "NoSpillStore"
  rbp|q fixed "[rbp|q]" rbp|q -1 [0, 26[ "NoSpillStore"
  rsi|q fixed "[rsi|q]" rsi|q -1 [0, 30[ "NoSpillStore"
  v0|q QWORD "[rsi|q]" v0|q rsi|q [30, 34[30 MustHaveRegister 32 MustHaveRegister 34 ShouldHaveRegister  "NoSpillStore"
end_intervals
begin_cfg
  name "After SSALinearScanResolveDataFlow"
  begin_block
    name "B0"
    from_bci -1
    to_bci -1
    predecessors 
    successors 
    xhandlers
    flags 
    probability 4607182418800017408
    begin_IR
      LIR
      nr    0  <|@ instruction [rsi|QWORD[.], rbp|QWORD] = LABEL alignment: 0 numbPhis: 0 label: ? <|@ <|@
      nr    2  <|@ instruction NOP <|@ <|@
      nr    4  <|@ instruction NOP <|@ <|@
      nr    6  <|@ instruction NOP <|@ <|@
      nr    8  <|@ instruction NOP <|@ <|@
      nr   10  <|@ instruction NOP <|@ <|@
      nr   12  <|@ instruction NOP <|@ <|@
      nr   14  <|@ instruction NOP <|@ <|@
      nr   16  <|@ instruction NOP <|@ <|@
      nr   18  <|@ instruction NOP <|@ <|@
      nr   20  <|@ instruction NOP <|@ <|@
      nr   22  <|@ instruction NOP <|@ <|@
      nr   24  <|@ instruction NOP <|@ <|@
      nr   26  <|@ instruction stack:16|QWORD = MOVE input: rbp|QWORD moveKind: QWORD <|@ <|@
      nr   28  <|@ instruction [] = HOTSPOTLOCKSTACK frameMapBuilder: jdk.graal.compiler.hotspot.amd64.AMD64HotSpotFrameMapBuilder@77b87d6a slotKind: QWORD <|@ <|@
      nr   30  <|@ instruction v0|QWORD[.] = MOVE input: rsi|QWORD[.] moveKind: QWORD <|@ <|@
      nr   32  <|@ st <@st|@live-base-pointers: []
java.util.Objects.requireNonNull(Objects.java:232) [bci: 0]
locals: Object[null] 
>@ <|@ instruction NULLCHECK address: [v0|QWORD[.]] state [bci:0] <|@ <|@
      nr   34  <|@ instruction rax|QWORD[.] = MOVE input: v0|QWORD[.] moveKind: QWORD <|@ <|@
      nr   36  <|@ instruction RETURN (savedRbp: stack:16|QWORD, value: rax|QWORD[.]) isStub: false requiresReservedStackAccessCheck: false thread: r15 scratchForSafepointOnReturn: rcx config: jdk.graal.compiler.hotspot.GraalHotSpotVMConfig@4817c460 <|@ <|@
    end_IR
  end_block
end_cfg
begin_bytecodes
     0: aload_0       
     1: ifnonnull     12
     4: new           #84         // java.lang.NullPointerException
     7: dup           
     8: invokespecial #17         // java.lang.NullPointerException.<init>:()void
    11: athrow        
    12: aload_0       
    13: areturn       
   <|@
end_bytecodes
begin_cfg
  name "After SSALinearScanEliminateSpillMove"
  begin_block
    name "B0"
    from_bci -1
    to_bci -1
    predecessors 
    successors 
    xhandlers
    flags 
    probability 4607182418800017408
    begin_IR
      LIR
      nr    0  <|@ instruction [rsi|QWORD[.], rbp|QWORD] = LABEL alignment: 0 numbPhis: 0 label: ? <|@ <|@
      nr    2  <|@ instruction NOP <|@ <|@
      nr    4  <|@ instruction NOP <|@ <|@
      nr    6  <|@ instruction NOP <|@ <|@
      nr    8  <|@ instruction NOP <|@ <|@
      nr   10  <|@ instruction NOP <|@ <|@
      nr   12  <|@ instruction NOP <|@ <|@
      nr   14  <|@ instruction NOP <|@ <|@
      nr   16  <|@ instruction NOP <|@ <|@
      nr   18  <|@ instruction NOP <|@ <|@
      nr   20  <|@ instruction NOP <|@ <|@
      nr   22  <|@ instruction NOP <|@ <|@
      nr   24  <|@ instruction NOP <|@ <|@
      nr   26  <|@ instruction stack:16|QWORD = MOVE input: rbp|QWORD moveKind: QWORD <|@ <|@
      nr   28  <|@ instruction [] = HOTSPOTLOCKSTACK frameMapBuilder: jdk.graal.compiler.hotspot.amd64.AMD64HotSpotFrameMapBuilder@77b87d6a slotKind: QWORD <|@ <|@
      nr   30  <|@ instruction v0|QWORD[.] = MOVE input: rsi|QWORD[.] moveKind: QWORD <|@ <|@
      nr   32  <|@ st <@st|@live-base-pointers: []
java.util.Objects.requireNonNull(Objects.java:232) [bci: 0]
locals: Object[null] 
>@ <|@ instruction NULLCHECK address: [v0|QWORD[.]] state [bci:0] <|@ <|@
      nr   34  <|@ instruction rax|QWORD[.] = MOVE input: v0|QWORD[.] moveKind: QWORD <|@ <|@
      nr   36  <|@ instruction RETURN (savedRbp: stack:16|QWORD, value: rax|QWORD[.]) isStub: false requiresReservedStackAccessCheck: false thread: r15 scratchForSafepointOnReturn: rcx config: jdk.graal.compiler.hotspot.GraalHotSpotVMConfig@4817c460 <|@ <|@
    end_IR
  end_block
end_cfg
begin_bytecodes
     0: aload_0       
     1: ifnonnull     12
     4: new           #84         // java.lang.NullPointerException
     7: dup           
     8: invokespecial #17         // java.lang.NullPointerException.<init>:()void
    11: athrow        
    12: aload_0       
    13: areturn       
   <|@
end_bytecodes
begin_cfg
  name "After LinearScanAssignLocations"
  begin_block
    name "B0"
    from_bci -1
    to_bci -1
    predecessors 
    successors 
    xhandlers
    flags 
    probability 4607182418800017408
    begin_IR
      LIR
      nr    0  <|@ instruction [rsi|QWORD[.], rbp|QWORD] = LABEL alignment: 0 numbPhis: 0 label: ? <|@ <|@
      nr    2  <|@ instruction NOP <|@ <|@
      nr    4  <|@ instruction NOP <|@ <|@
      nr    6  <|@ instruction NOP <|@ <|@
      nr    8  <|@ instruction NOP <|@ <|@
      nr   10  <|@ instruction NOP <|@ <|@
      nr   12  <|@ instruction NOP <|@ <|@
      nr   14  <|@ instruction NOP <|@ <|@
      nr   16  <|@ instruction NOP <|@ <|@
      nr   18  <|@ instruction NOP <|@ <|@
      nr   20  <|@ instruction NOP <|@ <|@
      nr   22  <|@ instruction NOP <|@ <|@
      nr   24  <|@ instruction NOP <|@ <|@
      nr   26  <|@ instruction stack:16|QWORD = MOVE input: rbp|QWORD moveKind: QWORD <|@ <|@
      nr   28  <|@ instruction [] = HOTSPOTLOCKSTACK frameMapBuilder: jdk.graal.compiler.hotspot.amd64.AMD64HotSpotFrameMapBuilder@77b87d6a slotKind: QWORD <|@ <|@
      nr   32  <|@ st <@st|@live-base-pointers: []
java.util.Objects.requireNonNull(Objects.java:232) [bci: 0]
locals: Object[null] 
>@ <|@ instruction NULLCHECK address: [rsi|QWORD[.]] state [bci:0] <|@ <|@
      nr   34  <|@ instruction rax|QWORD[.] = MOVE input: rsi|QWORD[.] moveKind: QWORD <|@ <|@
      nr   36  <|@ instruction RETURN (savedRbp: stack:16|QWORD, value: rax|QWORD[.]) isStub: false requiresReservedStackAccessCheck: false thread: r15 scratchForSafepointOnReturn: rcx config: jdk.graal.compiler.hotspot.GraalHotSpotVMConfig@4817c460 <|@ <|@
    end_IR
  end_block
end_cfg
begin_bytecodes
     0: aload_0       
     1: ifnonnull     12
     4: new           #84         // java.lang.NullPointerException
     7: dup           
     8: invokespecial #17         // java.lang.NullPointerException.<init>:()void
    11: athrow        
    12: aload_0       
    13: areturn       
   <|@
end_bytecodes
begin_cfg
  name "After LinearScan"
  begin_block
    name "B0"
    from_bci -1
    to_bci -1
    predecessors 
    successors 
    xhandlers
    flags 
    probability 4607182418800017408
    begin_IR
      LIR
      nr    0  <|@ instruction [rsi|QWORD[.], rbp|QWORD] = LABEL alignment: 0 numbPhis: 0 label: ? <|@ <|@
      nr    2  <|@ instruction NOP <|@ <|@
      nr    4  <|@ instruction NOP <|@ <|@
      nr    6  <|@ instruction NOP <|@ <|@
      nr    8  <|@ instruction NOP <|@ <|@
      nr   10  <|@ instruction NOP <|@ <|@
      nr   12  <|@ instruction NOP <|@ <|@
      nr   14  <|@ instruction NOP <|@ <|@
      nr   16  <|@ instruction NOP <|@ <|@
      nr   18  <|@ instruction NOP <|@ <|@
      nr   20  <|@ instruction NOP <|@ <|@
      nr   22  <|@ instruction NOP <|@ <|@
      nr   24  <|@ instruction NOP <|@ <|@
      nr   26  <|@ instruction stack:16|QWORD = MOVE input: rbp|QWORD moveKind: QWORD <|@ <|@
      nr   28  <|@ instruction [] = HOTSPOTLOCKSTACK frameMapBuilder: jdk.graal.compiler.hotspot.amd64.AMD64HotSpotFrameMapBuilder@77b87d6a slotKind: QWORD <|@ <|@
      nr   32  <|@ st <@st|@live-base-pointers: []
java.util.Objects.requireNonNull(Objects.java:232) [bci: 0]
locals: Object[null] 
>@ <|@ instruction NULLCHECK address: [rsi|QWORD[.]] state [bci:0] <|@ <|@
      nr   34  <|@ instruction rax|QWORD[.] = MOVE input: rsi|QWORD[.] moveKind: QWORD <|@ <|@
      nr   36  <|@ instruction RETURN (savedRbp: stack:16|QWORD, value: rax|QWORD[.]) isStub: false requiresReservedStackAccessCheck: false thread: r15 scratchForSafepointOnReturn: rcx config: jdk.graal.compiler.hotspot.GraalHotSpotVMConfig@4817c460 <|@ <|@
    end_IR
  end_block
end_cfg
begin_bytecodes
     0: aload_0       
     1: ifnonnull     12
     4: new           #84         // java.lang.NullPointerException
     7: dup           
     8: invokespecial #17         // java.lang.NullPointerException.<init>:()void
    11: athrow        
    12: aload_0       
    13: areturn       
   <|@
end_bytecodes
begin_cfg
  name "After LSStackSlotAllocator"
  begin_block
    name "B0"
    from_bci -1
    to_bci -1
    predecessors 
    successors 
    xhandlers
    flags 
    probability 4607182418800017408
    begin_IR
      LIR
      nr    0  <|@ instruction [rsi|QWORD[.], rbp|QWORD] = LABEL alignment: 0 numbPhis: 0 label: ? <|@ <|@
      nr    2  <|@ instruction NOP <|@ <|@
      nr    4  <|@ instruction NOP <|@ <|@
      nr    6  <|@ instruction NOP <|@ <|@
      nr    8  <|@ instruction NOP <|@ <|@
      nr   10  <|@ instruction NOP <|@ <|@
      nr   12  <|@ instruction NOP <|@ <|@
      nr   14  <|@ instruction NOP <|@ <|@
      nr   16  <|@ instruction NOP <|@ <|@
      nr   18  <|@ instruction NOP <|@ <|@
      nr   20  <|@ instruction NOP <|@ <|@
      nr   22  <|@ instruction NOP <|@ <|@
      nr   24  <|@ instruction NOP <|@ <|@
      nr   26  <|@ instruction stack:16|QWORD = MOVE input: rbp|QWORD moveKind: QWORD <|@ <|@
      nr   28  <|@ instruction [] = HOTSPOTLOCKSTACK frameMapBuilder: jdk.graal.compiler.hotspot.amd64.AMD64HotSpotFrameMapBuilder@77b87d6a slotKind: QWORD <|@ <|@
      nr   32  <|@ st <@st|@live-base-pointers: []
java.util.Objects.requireNonNull(Objects.java:232) [bci: 0]
locals: Object[null] 
>@ <|@ instruction NULLCHECK address: [rsi|QWORD[.]] state [bci:0] <|@ <|@
      nr   34  <|@ instruction rax|QWORD[.] = MOVE input: rsi|QWORD[.] moveKind: QWORD <|@ <|@
      nr   36  <|@ instruction RETURN (savedRbp: stack:16|QWORD, value: rax|QWORD[.]) isStub: false requiresReservedStackAccessCheck: false thread: r15 scratchForSafepointOnReturn: rcx config: jdk.graal.compiler.hotspot.GraalHotSpotVMConfig@4817c460 <|@ <|@
    end_IR
  end_block
end_cfg
begin_bytecodes
     0: aload_0       
     1: ifnonnull     12
     4: new           #84         // java.lang.NullPointerException
     7: dup           
     8: invokespecial #17         // java.lang.NullPointerException.<init>:()void
    11: athrow        
    12: aload_0       
    13: areturn       
   <|@
end_bytecodes
begin_cfg
  name "After AllocationStage"
  begin_block
    name "B0"
    from_bci -1
    to_bci -1
    predecessors 
    successors 
    xhandlers
    flags 
    probability 4607182418800017408
    begin_IR
      LIR
      nr    0  <|@ instruction [rsi|QWORD[.], rbp|QWORD] = LABEL alignment: 0 numbPhis: 0 label: ? <|@ <|@
      nr    2  <|@ instruction NOP <|@ <|@
      nr    4  <|@ instruction NOP <|@ <|@
      nr    6  <|@ instruction NOP <|@ <|@
      nr    8  <|@ instruction NOP <|@ <|@
      nr   10  <|@ instruction NOP <|@ <|@
      nr   12  <|@ instruction NOP <|@ <|@
      nr   14  <|@ instruction NOP <|@ <|@
      nr   16  <|@ instruction NOP <|@ <|@
      nr   18  <|@ instruction NOP <|@ <|@
      nr   20  <|@ instruction NOP <|@ <|@
      nr   22  <|@ instruction NOP <|@ <|@
      nr   24  <|@ instruction NOP <|@ <|@
      nr   26  <|@ instruction stack:16|QWORD = MOVE input: rbp|QWORD moveKind: QWORD <|@ <|@
      nr   28  <|@ instruction [] = HOTSPOTLOCKSTACK frameMapBuilder: jdk.graal.compiler.hotspot.amd64.AMD64HotSpotFrameMapBuilder@77b87d6a slotKind: QWORD <|@ <|@
      nr   32  <|@ st <@st|@live-base-pointers: []
java.util.Objects.requireNonNull(Objects.java:232) [bci: 0]
locals: Object[null] 
>@ <|@ instruction NULLCHECK address: [rsi|QWORD[.]] state [bci:0] <|@ <|@
      nr   34  <|@ instruction rax|QWORD[.] = MOVE input: rsi|QWORD[.] moveKind: QWORD <|@ <|@
      nr   36  <|@ instruction RETURN (savedRbp: stack:16|QWORD, value: rax|QWORD[.]) isStub: false requiresReservedStackAccessCheck: false thread: r15 scratchForSafepointOnReturn: rcx config: jdk.graal.compiler.hotspot.GraalHotSpotVMConfig@4817c460 <|@ <|@
    end_IR
  end_block
end_cfg
begin_bytecodes
     0: aload_0       
     1: ifnonnull     12
     4: new           #84         // java.lang.NullPointerException
     7: dup           
     8: invokespecial #17         // java.lang.NullPointerException.<init>:()void
    11: athrow        
    12: aload_0       
    13: areturn       
   <|@
end_bytecodes
begin_cfg
  name "After EdgeMoveOptimizer"
  begin_block
    name "B0"
    from_bci -1
    to_bci -1
    predecessors 
    successors 
    xhandlers
    flags 
    probability 4607182418800017408
    begin_IR
      LIR
      nr    0  <|@ instruction [rsi|QWORD[.], rbp|QWORD] = LABEL alignment: 0 numbPhis: 0 label: ? <|@ <|@
      nr    2  <|@ instruction NOP <|@ <|@
      nr    4  <|@ instruction NOP <|@ <|@
      nr    6  <|@ instruction NOP <|@ <|@
      nr    8  <|@ instruction NOP <|@ <|@
      nr   10  <|@ instruction NOP <|@ <|@
      nr   12  <|@ instruction NOP <|@ <|@
      nr   14  <|@ instruction NOP <|@ <|@
      nr   16  <|@ instruction NOP <|@ <|@
      nr   18  <|@ instruction NOP <|@ <|@
      nr   20  <|@ instruction NOP <|@ <|@
      nr   22  <|@ instruction NOP <|@ <|@
      nr   24  <|@ instruction NOP <|@ <|@
      nr   26  <|@ instruction stack:16|QWORD = MOVE input: rbp|QWORD moveKind: QWORD <|@ <|@
      nr   28  <|@ instruction [] = HOTSPOTLOCKSTACK frameMapBuilder: jdk.graal.compiler.hotspot.amd64.AMD64HotSpotFrameMapBuilder@77b87d6a slotKind: QWORD <|@ <|@
      nr   32  <|@ st <@st|@live-base-pointers: []
java.util.Objects.requireNonNull(Objects.java:232) [bci: 0]
locals: Object[null] 
>@ <|@ instruction NULLCHECK address: [rsi|QWORD[.]] state [bci:0] <|@ <|@
      nr   34  <|@ instruction rax|QWORD[.] = MOVE input: rsi|QWORD[.] moveKind: QWORD <|@ <|@
      nr   36  <|@ instruction RETURN (savedRbp: stack:16|QWORD, value: rax|QWORD[.]) isStub: false requiresReservedStackAccessCheck: false thread: r15 scratchForSafepointOnReturn: rcx config: jdk.graal.compiler.hotspot.GraalHotSpotVMConfig@4817c460 <|@ <|@
    end_IR
  end_block
end_cfg
begin_bytecodes
     0: aload_0       
     1: ifnonnull     12
     4: new           #84         // java.lang.NullPointerException
     7: dup           
     8: invokespecial #17         // java.lang.NullPointerException.<init>:()void
    11: athrow        
    12: aload_0       
    13: areturn       
   <|@
end_bytecodes
begin_cfg
  name "After RedundantMoveElimination"
  begin_block
    name "B0"
    from_bci -1
    to_bci -1
    predecessors 
    successors 
    xhandlers
    flags 
    probability 4607182418800017408
    begin_IR
      LIR
      nr    0  <|@ instruction [rsi|QWORD[.], rbp|QWORD] = LABEL alignment: 0 numbPhis: 0 label: ? <|@ <|@
      nr    2  <|@ instruction NOP <|@ <|@
      nr    4  <|@ instruction NOP <|@ <|@
      nr    6  <|@ instruction NOP <|@ <|@
      nr    8  <|@ instruction NOP <|@ <|@
      nr   10  <|@ instruction NOP <|@ <|@
      nr   12  <|@ instruction NOP <|@ <|@
      nr   14  <|@ instruction NOP <|@ <|@
      nr   16  <|@ instruction NOP <|@ <|@
      nr   18  <|@ instruction NOP <|@ <|@
      nr   20  <|@ instruction NOP <|@ <|@
      nr   22  <|@ instruction NOP <|@ <|@
      nr   24  <|@ instruction NOP <|@ <|@
      nr   26  <|@ instruction stack:16|QWORD = MOVE input: rbp|QWORD moveKind: QWORD <|@ <|@
      nr   28  <|@ instruction [] = HOTSPOTLOCKSTACK frameMapBuilder: jdk.graal.compiler.hotspot.amd64.AMD64HotSpotFrameMapBuilder@77b87d6a slotKind: QWORD <|@ <|@
      nr   32  <|@ st <@st|@live-base-pointers: []
java.util.Objects.requireNonNull(Objects.java:232) [bci: 0]
locals: Object[null] 
>@ <|@ instruction NULLCHECK address: [rsi|QWORD[.]] state [bci:0] <|@ <|@
      nr   34  <|@ instruction rax|QWORD[.] = MOVE input: rsi|QWORD[.] moveKind: QWORD <|@ <|@
      nr   36  <|@ instruction RETURN (savedRbp: stack:16|QWORD, value: rax|QWORD[.]) isStub: false requiresReservedStackAccessCheck: false thread: r15 scratchForSafepointOnReturn: rcx config: jdk.graal.compiler.hotspot.GraalHotSpotVMConfig@4817c460 <|@ <|@
    end_IR
  end_block
end_cfg
begin_bytecodes
     0: aload_0       
     1: ifnonnull     12
     4: new           #84         // java.lang.NullPointerException
     7: dup           
     8: invokespecial #17         // java.lang.NullPointerException.<init>:()void
    11: athrow        
    12: aload_0       
    13: areturn       
   <|@
end_bytecodes
begin_cfg
  name "After NullCheckOptimizer"
  begin_block
    name "B0"
    from_bci -1
    to_bci -1
    predecessors 
    successors 
    xhandlers
    flags 
    probability 4607182418800017408
    begin_IR
      LIR
      nr    0  <|@ instruction [rsi|QWORD[.], rbp|QWORD] = LABEL alignment: 0 numbPhis: 0 label: ? <|@ <|@
      nr    2  <|@ instruction NOP <|@ <|@
      nr    4  <|@ instruction NOP <|@ <|@
      nr    6  <|@ instruction NOP <|@ <|@
      nr    8  <|@ instruction NOP <|@ <|@
      nr   10  <|@ instruction NOP <|@ <|@
      nr   12  <|@ instruction NOP <|@ <|@
      nr   14  <|@ instruction NOP <|@ <|@
      nr   16  <|@ instruction NOP <|@ <|@
      nr   18  <|@ instruction NOP <|@ <|@
      nr   20  <|@ instruction NOP <|@ <|@
      nr   22  <|@ instruction NOP <|@ <|@
      nr   24  <|@ instruction NOP <|@ <|@
      nr   26  <|@ instruction stack:16|QWORD = MOVE input: rbp|QWORD moveKind: QWORD <|@ <|@
      nr   28  <|@ instruction [] = HOTSPOTLOCKSTACK frameMapBuilder: jdk.graal.compiler.hotspot.amd64.AMD64HotSpotFrameMapBuilder@77b87d6a slotKind: QWORD <|@ <|@
      nr   32  <|@ st <@st|@live-base-pointers: []
java.util.Objects.requireNonNull(Objects.java:232) [bci: 0]
locals: Object[null] 
>@ <|@ instruction NULLCHECK address: [rsi|QWORD[.]] state [bci:0] <|@ <|@
      nr   34  <|@ instruction rax|QWORD[.] = MOVE input: rsi|QWORD[.] moveKind: QWORD <|@ <|@
      nr   36  <|@ instruction RETURN (savedRbp: stack:16|QWORD, value: rax|QWORD[.]) isStub: false requiresReservedStackAccessCheck: false thread: r15 scratchForSafepointOnReturn: rcx config: jdk.graal.compiler.hotspot.GraalHotSpotVMConfig@4817c460 <|@ <|@
    end_IR
  end_block
end_cfg
begin_bytecodes
     0: aload_0       
     1: ifnonnull     12
     4: new           #84         // java.lang.NullPointerException
     7: dup           
     8: invokespecial #17         // java.lang.NullPointerException.<init>:()void
    11: athrow        
    12: aload_0       
    13: areturn       
   <|@
end_bytecodes
begin_cfg
  name "After ControlFlowOptimizer"
  begin_block
    name "B0"
    from_bci -1
    to_bci -1
    predecessors 
    successors 
    xhandlers
    flags 
    probability 4607182418800017408
    begin_IR
      LIR
      nr    0  <|@ instruction [rsi|QWORD[.], rbp|QWORD] = LABEL alignment: 0 numbPhis: 0 label: ? <|@ <|@
      nr    2  <|@ instruction NOP <|@ <|@
      nr    4  <|@ instruction NOP <|@ <|@
      nr    6  <|@ instruction NOP <|@ <|@
      nr    8  <|@ instruction NOP <|@ <|@
      nr   10  <|@ instruction NOP <|@ <|@
      nr   12  <|@ instruction NOP <|@ <|@
      nr   14  <|@ instruction NOP <|@ <|@
      nr   16  <|@ instruction NOP <|@ <|@
      nr   18  <|@ instruction NOP <|@ <|@
      nr   20  <|@ instruction NOP <|@ <|@
      nr   22  <|@ instruction NOP <|@ <|@
      nr   24  <|@ instruction NOP <|@ <|@
      nr   26  <|@ instruction stack:16|QWORD = MOVE input: rbp|QWORD moveKind: QWORD <|@ <|@
      nr   28  <|@ instruction [] = HOTSPOTLOCKSTACK frameMapBuilder: jdk.graal.compiler.hotspot.amd64.AMD64HotSpotFrameMapBuilder@77b87d6a slotKind: QWORD <|@ <|@
      nr   32  <|@ st <@st|@live-base-pointers: []
java.util.Objects.requireNonNull(Objects.java:232) [bci: 0]
locals: Object[null] 
>@ <|@ instruction NULLCHECK address: [rsi|QWORD[.]] state [bci:0] <|@ <|@
      nr   34  <|@ instruction rax|QWORD[.] = MOVE input: rsi|QWORD[.] moveKind: QWORD <|@ <|@
      nr   36  <|@ instruction RETURN (savedRbp: stack:16|QWORD, value: rax|QWORD[.]) isStub: false requiresReservedStackAccessCheck: false thread: r15 scratchForSafepointOnReturn: rcx config: jdk.graal.compiler.hotspot.GraalHotSpotVMConfig@4817c460 <|@ <|@
    end_IR
  end_block
end_cfg
begin_bytecodes
     0: aload_0       
     1: ifnonnull     12
     4: new           #84         // java.lang.NullPointerException
     7: dup           
     8: invokespecial #17         // java.lang.NullPointerException.<init>:()void
    11: athrow        
    12: aload_0       
    13: areturn       
   <|@
end_bytecodes
begin_cfg
  name "After ComputeCodeEmissionOrder"
  begin_block
    name "B0"
    from_bci -1
    to_bci -1
    predecessors 
    successors 
    xhandlers
    flags 
    probability 4607182418800017408
    begin_IR
      LIR
      nr    0  <|@ instruction [rsi|QWORD[.], rbp|QWORD] = LABEL alignment: 0 numbPhis: 0 label: ? <|@ <|@
      nr    2  <|@ instruction NOP <|@ <|@
      nr    4  <|@ instruction NOP <|@ <|@
      nr    6  <|@ instruction NOP <|@ <|@
      nr    8  <|@ instruction NOP <|@ <|@
      nr   10  <|@ instruction NOP <|@ <|@
      nr   12  <|@ instruction NOP <|@ <|@
      nr   14  <|@ instruction NOP <|@ <|@
      nr   16  <|@ instruction NOP <|@ <|@
      nr   18  <|@ instruction NOP <|@ <|@
      nr   20  <|@ instruction NOP <|@ <|@
      nr   22  <|@ instruction NOP <|@ <|@
      nr   24  <|@ instruction NOP <|@ <|@
      nr   26  <|@ instruction stack:16|QWORD = MOVE input: rbp|QWORD moveKind: QWORD <|@ <|@
      nr   28  <|@ instruction [] = HOTSPOTLOCKSTACK frameMapBuilder: jdk.graal.compiler.hotspot.amd64.AMD64HotSpotFrameMapBuilder@77b87d6a slotKind: QWORD <|@ <|@
      nr   32  <|@ st <@st|@live-base-pointers: []
java.util.Objects.requireNonNull(Objects.java:232) [bci: 0]
locals: Object[null] 
>@ <|@ instruction NULLCHECK address: [rsi|QWORD[.]] state [bci:0] <|@ <|@
      nr   34  <|@ instruction rax|QWORD[.] = MOVE input: rsi|QWORD[.] moveKind: QWORD <|@ <|@
      nr   36  <|@ instruction RETURN (savedRbp: stack:16|QWORD, value: rax|QWORD[.]) isStub: false requiresReservedStackAccessCheck: false thread: r15 scratchForSafepointOnReturn: rcx config: jdk.graal.compiler.hotspot.GraalHotSpotVMConfig@4817c460 <|@ <|@
    end_IR
  end_block
end_cfg
begin_bytecodes
     0: aload_0       
     1: ifnonnull     12
     4: new           #84         // java.lang.NullPointerException
     7: dup           
     8: invokespecial #17         // java.lang.NullPointerException.<init>:()void
    11: athrow        
    12: aload_0       
    13: areturn       
   <|@
end_bytecodes
begin_cfg
  name "After StackMoveOptimization"
  begin_block
    name "B0"
    from_bci -1
    to_bci -1
    predecessors 
    successors 
    xhandlers
    flags 
    probability 4607182418800017408
    begin_IR
      LIR
      nr    0  <|@ instruction [rsi|QWORD[.], rbp|QWORD] = LABEL alignment: 0 numbPhis: 0 label: ? <|@ <|@
      nr    2  <|@ instruction NOP <|@ <|@
      nr    4  <|@ instruction NOP <|@ <|@
      nr    6  <|@ instruction NOP <|@ <|@
      nr    8  <|@ instruction NOP <|@ <|@
      nr   10  <|@ instruction NOP <|@ <|@
      nr   12  <|@ instruction NOP <|@ <|@
      nr   14  <|@ instruction NOP <|@ <|@
      nr   16  <|@ instruction NOP <|@ <|@
      nr   18  <|@ instruction NOP <|@ <|@
      nr   20  <|@ instruction NOP <|@ <|@
      nr   22  <|@ instruction NOP <|@ <|@
      nr   24  <|@ instruction NOP <|@ <|@
      nr   26  <|@ instruction stack:16|QWORD = MOVE input: rbp|QWORD moveKind: QWORD <|@ <|@
      nr   28  <|@ instruction [] = HOTSPOTLOCKSTACK frameMapBuilder: jdk.graal.compiler.hotspot.amd64.AMD64HotSpotFrameMapBuilder@77b87d6a slotKind: QWORD <|@ <|@
      nr   32  <|@ st <@st|@live-base-pointers: []
java.util.Objects.requireNonNull(Objects.java:232) [bci: 0]
locals: Object[null] 
>@ <|@ instruction NULLCHECK address: [rsi|QWORD[.]] state [bci:0] <|@ <|@
      nr   34  <|@ instruction rax|QWORD[.] = MOVE input: rsi|QWORD[.] moveKind: QWORD <|@ <|@
      nr   36  <|@ instruction RETURN (savedRbp: stack:16|QWORD, value: rax|QWORD[.]) isStub: false requiresReservedStackAccessCheck: false thread: r15 scratchForSafepointOnReturn: rcx config: jdk.graal.compiler.hotspot.GraalHotSpotVMConfig@4817c460 <|@ <|@
    end_IR
  end_block
end_cfg
begin_bytecodes
     0: aload_0       
     1: ifnonnull     12
     4: new           #84         // java.lang.NullPointerException
     7: dup           
     8: invokespecial #17         // java.lang.NullPointerException.<init>:()void
    11: athrow        
    12: aload_0       
    13: areturn       
   <|@
end_bytecodes
begin_cfg
  name "After PostAllocationOptimizationStage"
  begin_block
    name "B0"
    from_bci -1
    to_bci -1
    predecessors 
    successors 
    xhandlers
    flags 
    probability 4607182418800017408
    begin_IR
      LIR
      nr    0  <|@ instruction [rsi|QWORD[.], rbp|QWORD] = LABEL alignment: 0 numbPhis: 0 label: ? <|@ <|@
      nr    2  <|@ instruction NOP <|@ <|@
      nr    4  <|@ instruction NOP <|@ <|@
      nr    6  <|@ instruction NOP <|@ <|@
      nr    8  <|@ instruction NOP <|@ <|@
      nr   10  <|@ instruction NOP <|@ <|@
      nr   12  <|@ instruction NOP <|@ <|@
      nr   14  <|@ instruction NOP <|@ <|@
      nr   16  <|@ instruction NOP <|@ <|@
      nr   18  <|@ instruction NOP <|@ <|@
      nr   20  <|@ instruction NOP <|@ <|@
      nr   22  <|@ instruction NOP <|@ <|@
      nr   24  <|@ instruction NOP <|@ <|@
      nr   26  <|@ instruction stack:16|QWORD = MOVE input: rbp|QWORD moveKind: QWORD <|@ <|@
      nr   28  <|@ instruction [] = HOTSPOTLOCKSTACK frameMapBuilder: jdk.graal.compiler.hotspot.amd64.AMD64HotSpotFrameMapBuilder@77b87d6a slotKind: QWORD <|@ <|@
      nr   32  <|@ st <@st|@live-base-pointers: []
java.util.Objects.requireNonNull(Objects.java:232) [bci: 0]
locals: Object[null] 
>@ <|@ instruction NULLCHECK address: [rsi|QWORD[.]] state [bci:0] <|@ <|@
      nr   34  <|@ instruction rax|QWORD[.] = MOVE input: rsi|QWORD[.] moveKind: QWORD <|@ <|@
      nr   36  <|@ instruction RETURN (savedRbp: stack:16|QWORD, value: rax|QWORD[.]) isStub: false requiresReservedStackAccessCheck: false thread: r15 scratchForSafepointOnReturn: rcx config: jdk.graal.compiler.hotspot.GraalHotSpotVMConfig@4817c460 <|@ <|@
    end_IR
  end_block
end_cfg
begin_bytecodes
     0: aload_0       
     1: ifnonnull     12
     4: new           #84         // java.lang.NullPointerException
     7: dup           
     8: invokespecial #17         // java.lang.NullPointerException.<init>:()void
    11: athrow        
    12: aload_0       
    13: areturn       
   <|@
end_bytecodes
begin_cfg
  name "After LocationMarker"
  begin_block
    name "B0"
    from_bci -1
    to_bci -1
    predecessors 
    successors 
    xhandlers
    flags 
    probability 4607182418800017408
    begin_IR
      LIR
      nr    0  <|@ instruction [rsi|QWORD[.], rbp|QWORD] = LABEL alignment: 0 numbPhis: 0 label: ? <|@ <|@
      nr    2  <|@ instruction NOP <|@ <|@
      nr    4  <|@ instruction NOP <|@ <|@
      nr    6  <|@ instruction NOP <|@ <|@
      nr    8  <|@ instruction NOP <|@ <|@
      nr   10  <|@ instruction NOP <|@ <|@
      nr   12  <|@ instruction NOP <|@ <|@
      nr   14  <|@ instruction NOP <|@ <|@
      nr   16  <|@ instruction NOP <|@ <|@
      nr   18  <|@ instruction NOP <|@ <|@
      nr   20  <|@ instruction NOP <|@ <|@
      nr   22  <|@ instruction NOP <|@ <|@
      nr   24  <|@ instruction NOP <|@ <|@
      nr   26  <|@ instruction stack:16|QWORD = MOVE input: rbp|QWORD moveKind: QWORD <|@ <|@
      nr   28  <|@ instruction [] = HOTSPOTLOCKSTACK frameMapBuilder: jdk.graal.compiler.hotspot.amd64.AMD64HotSpotFrameMapBuilder@77b87d6a slotKind: QWORD <|@ <|@
      nr   32  <|@ st <@st|@reference-map: [rsi:0]
live-base-pointers: []
java.util.Objects.requireNonNull(Objects.java:232) [bci: 0]
locals: Object[null] 
>@ <|@ instruction NULLCHECK address: [rsi|QWORD[.]] state [bci:0] <|@ <|@
      nr   34  <|@ instruction rax|QWORD[.] = MOVE input: rsi|QWORD[.] moveKind: QWORD <|@ <|@
      nr   36  <|@ instruction RETURN (savedRbp: stack:16|QWORD, value: rax|QWORD[.]) isStub: false requiresReservedStackAccessCheck: false thread: r15 scratchForSafepointOnReturn: rcx config: jdk.graal.compiler.hotspot.GraalHotSpotVMConfig@4817c460 <|@ <|@
    end_IR
  end_block
end_cfg
begin_bytecodes
     0: aload_0       
     1: ifnonnull     12
     4: new           #84         // java.lang.NullPointerException
     7: dup           
     8: invokespecial #17         // java.lang.NullPointerException.<init>:()void
    11: athrow        
    12: aload_0       
    13: areturn       
   <|@
end_bytecodes
begin_cfg
  name "After FinalCodeAnalysisStage"
  begin_block
    name "B0"
    from_bci -1
    to_bci -1
    predecessors 
    successors 
    xhandlers
    flags 
    probability 4607182418800017408
    begin_IR
      LIR
      nr    0  <|@ instruction [rsi|QWORD[.], rbp|QWORD] = LABEL alignment: 0 numbPhis: 0 label: ? <|@ <|@
      nr    2  <|@ instruction NOP <|@ <|@
      nr    4  <|@ instruction NOP <|@ <|@
      nr    6  <|@ instruction NOP <|@ <|@
      nr    8  <|@ instruction NOP <|@ <|@
      nr   10  <|@ instruction NOP <|@ <|@
      nr   12  <|@ instruction NOP <|@ <|@
      nr   14  <|@ instruction NOP <|@ <|@
      nr   16  <|@ instruction NOP <|@ <|@
      nr   18  <|@ instruction NOP <|@ <|@
      nr   20  <|@ instruction NOP <|@ <|@
      nr   22  <|@ instruction NOP <|@ <|@
      nr   24  <|@ instruction NOP <|@ <|@
      nr   26  <|@ instruction stack:16|QWORD = MOVE input: rbp|QWORD moveKind: QWORD <|@ <|@
      nr   28  <|@ instruction [] = HOTSPOTLOCKSTACK frameMapBuilder: jdk.graal.compiler.hotspot.amd64.AMD64HotSpotFrameMapBuilder@77b87d6a slotKind: QWORD <|@ <|@
      nr   32  <|@ st <@st|@reference-map: [rsi:0]
live-base-pointers: []
java.util.Objects.requireNonNull(Objects.java:232) [bci: 0]
locals: Object[null] 
>@ <|@ instruction NULLCHECK address: [rsi|QWORD[.]] state [bci:0] <|@ <|@
      nr   34  <|@ instruction rax|QWORD[.] = MOVE input: rsi|QWORD[.] moveKind: QWORD <|@ <|@
      nr   36  <|@ instruction RETURN (savedRbp: stack:16|QWORD, value: rax|QWORD[.]) isStub: false requiresReservedStackAccessCheck: false thread: r15 scratchForSafepointOnReturn: rcx config: jdk.graal.compiler.hotspot.GraalHotSpotVMConfig@4817c460 <|@ <|@
    end_IR
  end_block
end_cfg
begin_bytecodes
     0: aload_0       
     1: ifnonnull     12
     4: new           #84         // java.lang.NullPointerException
     7: dup           
     8: invokespecial #17         // java.lang.NullPointerException.<init>:()void
    11: athrow        
    12: aload_0       
    13: areturn       
   <|@
end_bytecodes
begin_cfg
  name "After code generation"
end_cfg
begin_nmethod
  <<<HexCodeFile
  Platform AMD64 64  <||@
  HexCode 0 89842400c0feff4883ec189041817f20000000000f852d00000090909090909090909090909048896c24108506488bc6488b6c24104883c418493ba7500400000f870e000000c348896c2410e800000000ebc7f4488d0ddeffffff49898f68040000e999fffffff441c78784040000edf8ffff49c7879004000014000000e8000000000f1f840000000000e800000000f4e800000000f4  <||@
  Comment 0 [stack overflow check]  <||@
  Comment 0 VERIFIED_ENTRY  <||@
  Comment 12 FRAME_COMPLETE  <||@
  Comment 12 ENTRY_BARRIER_PATCH  <||@
  Comment 26 block B0 null  <||@
  Comment 26 0 [rsi|QWORD[.], rbp|QWORD] = LABEL alignment: 0 numbPhis: 0 label: ?  <||@
  Comment 26 2 NOP  <||@
  Comment 27 4 NOP  <||@
  Comment 28 6 NOP  <||@
  Comment 29 8 NOP  <||@
  Comment 30 10 NOP  <||@
  Comment 31 12 NOP  <||@
  Comment 32 14 NOP  <||@
  Comment 33 16 NOP  <||@
  Comment 34 18 NOP  <||@
  Comment 35 20 NOP  <||@
  Comment 36 22 NOP  <||@
  Comment 37 24 NOP  <||@
  Comment 38 26 stack:16|QWORD = MOVE input: rbp|QWORD moveKind: QWORD  <||@
  Comment 43 28 [] = HOTSPOTLOCKSTACK frameMapBuilder: jdk.graal.compiler.hotspot.amd64.AMD64HotSpotFrameMapBuilder@77b87d6a slotKind: QWORD  <||@
  Comment 43 32 NULLCHECK address: [rsi|QWORD[.]] state [bci:0]  <||@
  Comment 43 [rsi:0]at java.util.Objects.requireNonNull(Objects.java:232) [bci: 0, duringCall: false, rethrow: false]
              |0            
     locals:  |Object[null]   <||@
  Comment 43 {infopoint: IMPLICIT_EXCEPTION}  <||@
  Comment 45 34 rax|QWORD[.] = MOVE input: rsi|QWORD[.] moveKind: QWORD  <||@
  Comment 48 36 RETURN (savedRbp: stack:16|QWORD, value: rax|QWORD[.]) isStub: false requiresReservedStackAccessCheck: false thread: r15 scratchForSafepointOnReturn: rcx config: jdk.graal.compiler.hotspot.GraalHotSpotVMConfig@4817c460  <||@
  Comment 57 POLL_RETURN_FAR  <||@
  Comment 76 {Field[name=CompilerToVM::Data::nmethod_entry_barrier, type=address, offset=0, address=0x7f78b2033598, value=140155947495968]:0x7f789976b220}  <||@
  Comment 98 {Field[name=CompilerToVM::Data::SharedRuntime_polling_page_return_handler, type=address, offset=0, address=0x7f78b20335a0, value=140155947630592]:0x7f789978c000}  <||@
  Comment 126 {Field[name=CompilerToVM::Data::SharedRuntime_deopt_blob_uncommon_trap, type=address, offset=0, address=0x7f78b20335a8, value=140155947626874]:0x7f789978b17a}  <||@
  Comment 131 [rsi:0]at java.util.Objects.requireNonNull(Objects.java:232) [bci: 0, duringCall: false, rethrow: false]
              |0            
     locals:  |Object[null]   <||@
  Comment 139 {Stub<ExceptionHandlerStub.exceptionHandler>@0x7f78998c5300:CallingConvention[rax|QWORD[.], rdx|QWORD]:CallingConvention[rax|QWORD[.], rdx|QWORD]; temps=rdi|ILLEGAL,xmm14|ILLEGAL,xmm15|ILLEGAL,xmm12|ILLEGAL,xmm13|ILLEGAL,xmm10|ILLEGAL,xmm11|ILLEGAL,xmm7|ILLEGAL,xmm8|ILLEGAL,xmm9|ILLEGAL,xmm0|ILLEGAL,xmm1|ILLEGAL,xmm2|ILLEGAL,xmm3|ILLEGAL,xmm4|ILLEGAL,xmm5|ILLEGAL,xmm6|ILLEGAL,rax|ILLEGAL,rcx|ILLEGAL,rdx|ILLEGAL,rsi|ILLEGAL,r8|ILLEGAL,r9|ILLEGAL,r10|ILLEGAL,r11|ILLEGAL}  <||@
  Comment 139 EXCEPTION_HANDLER_ENTRY  <||@
  Comment 145 {Field[name=CompilerToVM::Data::SharedRuntime_deopt_blob_unpack, type=address, offset=0, address=0x7f78b20335b8, value=140155947626272]:0x7f789978af20}  <||@
  Comment 145 DEOPT_HANDLER_ENTRY  <||@
  HexCodeFile>>> <|@
end_nmethod
begin_compilation
  name " HotSpotCompilation-682[java.util.Objects.requireNonNull(Object)]"
  method "HotSpotCompilation-682[java.util.Objects.requireNonNull(Object)]"
  date 1724269729169
end_compilation
begin_cfg
  name "After code installation"
end_cfg
begin_nmethod
  <<<HexCodeFile
  Platform AMD64 64  <||@
  HexCode 7f789ad7ee80 89842400c0feff4883ec189041817f20030000000f852d00000090909090909090909090909048896c24108506488bc6488b6c24104883c418493ba7500400000f870e000000c348896c2410e84fc39efeebc7f4488d0ddeffffff49898f68040000e919d1a0fef441c78784040000edf8ffff49c7879004000014000000e877c2a0fe0f1f840000000000e8f063b4fef4e80ac0a0fef4f4  <||@
  Comment 0 [stack overflow check]  <||@
  Comment 0 VERIFIED_ENTRY  <||@
  Comment 12 FRAME_COMPLETE  <||@
  Comment 12 ENTRY_BARRIER_PATCH  <||@
  Comment 26 block B0 null  <||@
  Comment 26 0 [rsi|QWORD[.], rbp|QWORD] = LABEL alignment: 0 numbPhis: 0 label: ?  <||@
  Comment 26 2 NOP  <||@
  Comment 27 4 NOP  <||@
  Comment 28 6 NOP  <||@
  Comment 29 8 NOP  <||@
  Comment 30 10 NOP  <||@
  Comment 31 12 NOP  <||@
  Comment 32 14 NOP  <||@
  Comment 33 16 NOP  <||@
  Comment 34 18 NOP  <||@
  Comment 35 20 NOP  <||@
  Comment 36 22 NOP  <||@
  Comment 37 24 NOP  <||@
  Comment 38 26 stack:16|QWORD = MOVE input: rbp|QWORD moveKind: QWORD  <||@
  Comment 43 28 [] = HOTSPOTLOCKSTACK frameMapBuilder: jdk.graal.compiler.hotspot.amd64.AMD64HotSpotFrameMapBuilder@77b87d6a slotKind: QWORD  <||@
  Comment 43 32 NULLCHECK address: [rsi|QWORD[.]] state [bci:0]  <||@
  Comment 43 [rsi:0]at java.util.Objects.requireNonNull(Objects.java:232) [bci: 0, duringCall: false, rethrow: false]
              |0            
     locals:  |Object[null]   <||@
  Comment 43 {infopoint: IMPLICIT_EXCEPTION}  <||@
  Comment 45 34 rax|QWORD[.] = MOVE input: rsi|QWORD[.] moveKind: QWORD  <||@
  Comment 48 36 RETURN (savedRbp: stack:16|QWORD, value: rax|QWORD[.]) isStub: false requiresReservedStackAccessCheck: false thread: r15 scratchForSafepointOnReturn: rcx config: jdk.graal.compiler.hotspot.GraalHotSpotVMConfig@4817c460  <||@
  Comment 57 POLL_RETURN_FAR  <||@
  Comment 76 {Field[name=CompilerToVM::Data::nmethod_entry_barrier, type=address, offset=0, address=0x7f78b2033598, value=140155947495968]:0x7f789976b220}  <||@
  Comment 98 {Field[name=CompilerToVM::Data::SharedRuntime_polling_page_return_handler, type=address, offset=0, address=0x7f78b20335a0, value=140155947630592]:0x7f789978c000}  <||@
  Comment 126 {Field[name=CompilerToVM::Data::SharedRuntime_deopt_blob_uncommon_trap, type=address, offset=0, address=0x7f78b20335a8, value=140155947626874]:0x7f789978b17a}  <||@
  Comment 131 [rsi:0]at java.util.Objects.requireNonNull(Objects.java:232) [bci: 0, duringCall: false, rethrow: false]
              |0            
     locals:  |Object[null]   <||@
  Comment 139 {Stub<ExceptionHandlerStub.exceptionHandler>@0x7f78998c5300:CallingConvention[rax|QWORD[.], rdx|QWORD]:CallingConvention[rax|QWORD[.], rdx|QWORD]; temps=rdi|ILLEGAL,xmm14|ILLEGAL,xmm15|ILLEGAL,xmm12|ILLEGAL,xmm13|ILLEGAL,xmm10|ILLEGAL,xmm11|ILLEGAL,xmm7|ILLEGAL,xmm8|ILLEGAL,xmm9|ILLEGAL,xmm0|ILLEGAL,xmm1|ILLEGAL,xmm2|ILLEGAL,xmm3|ILLEGAL,xmm4|ILLEGAL,xmm5|ILLEGAL,xmm6|ILLEGAL,rax|ILLEGAL,rcx|ILLEGAL,rdx|ILLEGAL,rsi|ILLEGAL,r8|ILLEGAL,r9|ILLEGAL,r10|ILLEGAL,r11|ILLEGAL}  <||@
  Comment 139 EXCEPTION_HANDLER_ENTRY  <||@
  Comment 145 {Field[name=CompilerToVM::Data::SharedRuntime_deopt_blob_unpack, type=address, offset=0, address=0x7f78b20335b8, value=140155947626272]:0x7f789978af20}  <||@
  Comment 145 DEOPT_HANDLER_ENTRY  <||@
  HexCodeFile>>> <|@
end_nmethod
