begin_compilation
  name " HotSpotCompilation-3682[java.lang.Math.clamp(long, int, int)]"
  method "HotSpotCompilation-3682[java.lang.Math.clamp(long, int, int)]"
  date 1724269726848
end_compilation
begin_cfg
  name "Final HIR schedule"
  begin_block
    name "B0"
    from_bci -1
    to_bci -1
    predecessors 
    successors "B1" "B2" 
    xhandlers
    flags 
    probability 4607182418800017408
    begin_IR
      HIR
f <@#|@fixed with next>@ <|@
tid v0 <|@
d <@d|@=== Debug Properties ===
hasSpeculationFence: false
stamp: void
=== Inputs ===
stateAfter: - 
=== Succesors ===
next: v26 
=== Usages ===
=== Predecessor ===
- >@ <|@
instruction <@StartNode|@jdk.graal.compiler.nodes.StartNode>@ stateAfter: - #next: v26  <|@  <|@
f <@~|@floating>@ <|@
tid j1 <|@
d <@d|@=== Debug Properties ===
index: 0
stamp: i64
uncheckedStamp: [null]
=== Inputs ===
=== Succesors ===
=== Usages ===
?4 j19 v17 
=== Predecessor ===
- >@ <|@
instruction <@Parameter|@jdk.graal.compiler.nodes.ParameterNode>@  <|@  <|@
f <@~|@floating>@ <|@
tid i3 <|@
d <@d|@=== Debug Properties ===
index: 2
stamp: i32
uncheckedStamp: [null]
=== Inputs ===
=== Succesors ===
=== Usages ===
?4 v5 j7 
=== Predecessor ===
- >@ <|@
instruction <@Parameter|@jdk.graal.compiler.nodes.ParameterNode>@  <|@  <|@
f <@~|@floating>@ <|@
tid i2 <|@
d <@d|@=== Debug Properties ===
index: 1
stamp: i32
uncheckedStamp: [null]
=== Inputs ===
=== Succesors ===
=== Usages ===
?4 v5 j8 
=== Predecessor ===
- >@ <|@
instruction <@Parameter|@jdk.graal.compiler.nodes.ParameterNode>@  <|@  <|@
f <@~|@floating>@ <|@
tid v5 <|@
d <@d|@=== Debug Properties ===
condition: LT
nodeSourcePosition: at java.lang.Math.clamp(Math.java:2214) [bci: 2]
op: jdk.graal.compiler.nodes.calc.IntegerLessThanNode$LessThanOp@406e677e
stamp: void
unorderedIsTrue: false
=== Inputs ===
x: i3 
y: i2 
=== Succesors ===
=== Usages ===
v26 
=== Predecessor ===
- >@ <|@
instruction <@<|@jdk.graal.compiler.nodes.calc.IntegerLessThanNode>@ x: i3 y: i2  <|@  <|@
f <@*|@fixed>@ <|@
tid v26 <|@
d <@d|@=== Debug Properties ===
nodeSourcePosition: at java.lang.Math.clamp(Math.java:2214) [bci: 2]
profileData: INJECTED designatedSuccessorProbability: 0.0
stamp: void
=== Inputs ===
condition: v5 
=== Succesors ===
trueSuccessor: v24 
falseSuccessor: v25 
=== Usages ===
=== Predecessor ===
v0 >@ <|@
instruction <@If|@jdk.graal.compiler.nodes.IfNode>@ condition: v5 #trueSuccessor: v24 #falseSuccessor: v25  <|@  <|@
    end_IR
  end_block
  begin_block
    name "B1"
    from_bci -1
    to_bci -1
    predecessors "B0" 
    successors 
    xhandlers
    flags 
    probability 2355382605114769408
    begin_IR
      HIR
f <@#|@fixed with next>@ <|@
tid v24 <|@
d <@d|@=== Debug Properties ===
hasSpeculationFence: false
nodeSourcePosition: at java.lang.Math.clamp(Math.java:2214) [bci: 2]
stamp: void
=== Inputs ===
=== Succesors ===
next: v23 
=== Usages ===
=== Predecessor ===
v26 >@ <|@
instruction <@Begin|@jdk.graal.compiler.nodes.BeginNode>@ #next: v23  <|@  <|@
tid ?4 <|@
d <@d|@=== Debug Properties ===
bci: 0
bytecode: iload_2
code: ResolvedJavaMethodBytecode<Math.clamp(long, int, int)>
localsSize: 4
locksSize: 0
sourceFile: Math.java
sourceLine: 2214
stackSize: 0
stackState: BeforePop
validForDeoptimization: true
=== Inputs ===
outerFrameState: - 
values: j1 - i2 i3 
=== Succesors ===
=== Usages ===
v23 
=== Predecessor ===
- >@ <|@
instruction <@FrameState|@jdk.graal.compiler.nodes.FrameState>@ outerFrameState: - values: j1 - i2 i3  <|@  <|@
f <@*|@fixed>@ <|@
tid v23 <|@
d <@d|@=== Debug Properties ===
action: InvalidateReprofile
debugId: 0
mayConvertToGuard: true
nodeSourcePosition: at java.lang.Math.clamp(Math.java:2214) [bci: 2]
reason: UnreachedCode
speculation: {0x0000000000000014[index: 0, len: 20, hash: 0xddb97d58]: UnreachedCode@6[HotSpotMethod<Math.clamp(long, int, int)>, 5]}
stamp: void
=== Inputs ===
stateBefore: ?4 
=== Succesors ===
=== Usages ===
=== Predecessor ===
v24 >@ <|@
instruction <@Deopt|@jdk.graal.compiler.nodes.DeoptimizeNode>@ stateBefore: ?4  <|@  <|@
    end_IR
  end_block
  begin_block
    name "B2"
    from_bci -1
    to_bci -1
    predecessors "B0" 
    successors 
    xhandlers
    flags 
    probability 4607182418800017408
    begin_IR
      HIR
f <@#|@fixed with next>@ <|@
tid v25 <|@
d <@d|@=== Debug Properties ===
hasSpeculationFence: false
nodeSourcePosition: at java.lang.Math.clamp(Math.java:2217) [bci: 36]
stamp: void
=== Inputs ===
=== Succesors ===
next: v16 
=== Usages ===
=== Predecessor ===
v26 >@ <|@
instruction <@Begin|@jdk.graal.compiler.nodes.BeginNode>@ #next: v16  <|@  <|@
f <@~|@floating>@ <|@
tid j8 <|@
d <@d|@=== Debug Properties ===
inputBits: 32
nodeSourcePosition: at java.lang.Math.clamp(Math.java:2217) [bci: 40]
resultBits: 64
stamp: i64 [-2147483648 - 2147483647]
=== Inputs ===
value: i2 
=== Succesors ===
=== Usages ===
j19 v17 
=== Predecessor ===
- >@ <|@
instruction <@SignExtend|@jdk.graal.compiler.nodes.calc.SignExtendNode>@ value: i2  <|@  <|@
f <@~|@floating>@ <|@
tid v17 <|@
d <@d|@=== Debug Properties ===
condition: LT
nodeSourcePosition: at java.lang.Math.max(Math.java:2034) [bci: 3]
at java.lang.Math.clamp(Math.java:2217) [bci: 41]
op: jdk.graal.compiler.nodes.calc.IntegerLessThanNode$LessThanOp@406e677e
stamp: void
unorderedIsTrue: false
=== Inputs ===
x: j1 
y: j8 
=== Succesors ===
=== Usages ===
j19 
=== Predecessor ===
- >@ <|@
instruction <@<|@jdk.graal.compiler.nodes.calc.IntegerLessThanNode>@ x: j1 y: j8  <|@  <|@
f <@~|@floating>@ <|@
tid j19 <|@
d <@d|@=== Debug Properties ===
nodeSourcePosition: at java.lang.Math.max(Math.java:2034) [bci: 3]
at java.lang.Math.clamp(Math.java:2217) [bci: 41]
stamp: i64 [-2147483648 - 9223372036854775807]
=== Inputs ===
condition: v17 
trueValue: j8 
falseValue: j1 
=== Succesors ===
=== Usages ===
j22 v20 
=== Predecessor ===
- >@ <|@
instruction <@Conditional|@jdk.graal.compiler.nodes.calc.ConditionalNode>@ condition: v17 trueValue: j8 falseValue: j1  <|@  <|@
f <@~|@floating>@ <|@
tid j7 <|@
d <@d|@=== Debug Properties ===
inputBits: 32
nodeSourcePosition: at java.lang.Math.clamp(Math.java:2217) [bci: 37]
resultBits: 64
stamp: i64 [-2147483648 - 2147483647]
=== Inputs ===
value: i3 
=== Succesors ===
=== Usages ===
j22 v20 
=== Predecessor ===
- >@ <|@
instruction <@SignExtend|@jdk.graal.compiler.nodes.calc.SignExtendNode>@ value: i3  <|@  <|@
f <@~|@floating>@ <|@
tid v20 <|@
d <@d|@=== Debug Properties ===
condition: LT
nodeSourcePosition: at java.lang.Math.min(Math.java:2129) [bci: 3]
at java.lang.Math.clamp(Math.java:2217) [bci: 44]
op: jdk.graal.compiler.nodes.calc.IntegerLessThanNode$LessThanOp@406e677e
stamp: void
unorderedIsTrue: false
=== Inputs ===
x: j19 
y: j7 
=== Succesors ===
=== Usages ===
j22 
=== Predecessor ===
- >@ <|@
instruction <@<|@jdk.graal.compiler.nodes.calc.IntegerLessThanNode>@ x: j19 y: j7  <|@  <|@
f <@~|@floating>@ <|@
tid j22 <|@
d <@d|@=== Debug Properties ===
nodeSourcePosition: at java.lang.Math.min(Math.java:2129) [bci: 3]
at java.lang.Math.clamp(Math.java:2217) [bci: 44]
stamp: i64 [-2147483648 - 2147483647]
=== Inputs ===
condition: v20 
trueValue: j19 
falseValue: j7 
=== Succesors ===
=== Usages ===
i15 
=== Predecessor ===
- >@ <|@
instruction <@Conditional|@jdk.graal.compiler.nodes.calc.ConditionalNode>@ condition: v20 trueValue: j19 falseValue: j7  <|@  <|@
f <@~|@floating>@ <|@
tid i15 <|@
d <@d|@=== Debug Properties ===
inputBits: 64
nodeSourcePosition: at java.lang.Math.clamp(Math.java:2217) [bci: 47]
resultBits: 32
stamp: i32
=== Inputs ===
value: j22 
=== Succesors ===
=== Usages ===
v16 
=== Predecessor ===
- >@ <|@
instruction <@Narrow|@jdk.graal.compiler.nodes.calc.NarrowNode>@ value: j22  <|@  <|@
f <@*|@fixed>@ <|@
tid v16 <|@
d <@d|@=== Debug Properties ===
nodeSourcePosition: at java.lang.Math.clamp(Math.java:2217) [bci: 48]
stamp: void
=== Inputs ===
memoryMap: - 
result: i15 
=== Succesors ===
=== Usages ===
=== Predecessor ===
v25 >@ <|@
instruction <@Return|@jdk.graal.compiler.nodes.ReturnNode>@ memoryMap: - result: i15  <|@  <|@
    end_IR
  end_block
end_cfg
begin_cfg
  name "After LIRGeneration"
  begin_block
    name "B0"
    from_bci -1
    to_bci -1
    predecessors 
    successors "B1" "B2" 
    xhandlers
    flags 
    probability 4607182418800017408
    begin_IR
      LIR
      nr   -1  <|@ instruction [rsi|QWORD, rdx|DWORD, rcx|DWORD, rbp|QWORD] = LABEL alignment: 0 numbPhis: 0 label: ? <|@ <|@
      nr   -1  <|@ instruction stack:16|QWORD = MOVE input: rbp|QWORD moveKind: QWORD <|@ <|@
      nr   -1  <|@ instruction [] = HOTSPOTLOCKSTACK frameMapBuilder: jdk.graal.compiler.hotspot.amd64.AMD64HotSpotFrameMapBuilder@8113c20 slotKind: QWORD <|@ <|@
      nr   -1  <|@ instruction v0|QWORD = MOVE input: rsi|QWORD moveKind: QWORD <|@ <|@
      nr   -1  <|@ instruction v1|DWORD = MOVE input: rdx|DWORD moveKind: DWORD <|@ <|@
      nr   -1  <|@ instruction v2|DWORD = MOVE input: rcx|DWORD moveKind: DWORD <|@ <|@
      nr   -1  <|@ instruction CMPBRANCH (x: v1|DWORD, y: v2|DWORD) trueDestinationProbability: 0.0 condition: > trueDestination: B0 -> B1 falseDestination: B0 -> B2 size: DWORD <|@ <|@
    end_IR
  end_block
  begin_block
    name "B2"
    from_bci -1
    to_bci -1
    predecessors "B0" 
    successors 
    xhandlers
    flags 
    probability 4607182418800017408
    begin_IR
      LIR
      nr   -1  <|@ instruction [] = LABEL alignment: 0 numbPhis: 0 label: ? <|@ <|@
      nr   -1  <|@ instruction v3|QWORD = MOVSXD value: v1|DWORD size: QWORD <|@ <|@
      nr   -1  <|@ instruction CMP (x: v3|QWORD, y: v0|QWORD) size: QWORD <|@ <|@
      nr   -1  <|@ instruction v4|QWORD = CMOVE (falseValue: v0|QWORD, ~trueValue: v3|QWORD) condition: > <|@ <|@
      nr   -1  <|@ instruction v5|QWORD = MOVSXD value: v2|DWORD size: QWORD <|@ <|@
      nr   -1  <|@ instruction CMP (x: v5|QWORD, y: v4|QWORD) size: QWORD <|@ <|@
      nr   -1  <|@ instruction v6|QWORD = CMOVE (falseValue: v5|QWORD, ~trueValue: v4|QWORD) condition: > <|@ <|@
      nr   -1  <|@ instruction v7|DWORD = MOV value: v6|QWORD size: DWORD <|@ <|@
      nr   -1  <|@ instruction rax|DWORD = MOVE input: v7|DWORD moveKind: DWORD <|@ <|@
      nr   -1  <|@ instruction RETURN (savedRbp: stack:16|QWORD, value: rax|DWORD) isStub: false requiresReservedStackAccessCheck: false thread: r15 scratchForSafepointOnReturn: rcx config: jdk.graal.compiler.hotspot.GraalHotSpotVMConfig@4817c460 <|@ <|@
    end_IR
  end_block
  begin_block
    name "B1"
    from_bci -1
    to_bci -1
    predecessors "B0" 
    successors 
    xhandlers
    flags 
    probability 2355382605114769408
    begin_IR
      LIR
      nr   -1  <|@ instruction [] = LABEL alignment: 0 numbPhis: 0 label: ? <|@ <|@
      nr   -1  <|@ instruction MOV x: [r15|QWORD + 1156] y: -5907 size: DWORD <|@ <|@
      nr   -1  <|@ instruction MOV x: [r15|QWORD + 1168] y: 20 size: QWORD <|@ <|@
      nr   -1  <|@ st <@st|@java.lang.Math.clamp(Math.java:2214) [bci: 0]
locals: v0|QWORD - v1|DWORD v2|DWORD 
>@ <|@ instruction DEOPT info [bci:0] <|@ <|@
    end_IR
  end_block
end_cfg
begin_bytecodes
     0: iload_2       
     1: iload_3       
     2: if_icmple     36
     5: new           #177        // java.lang.IllegalArgumentException
     8: dup           
     9: new           #179        // java.lang.StringBuilder
    12: dup           
    13: invokespecial #35         // java.lang.StringBuilder.<init>:()void
    16: iload_2       
    17: invokevirtual #36         // java.lang.StringBuilder.append:(int)java.lang.StringBuilder
    20: ldc           #186        // " > "
    22: invokevirtual #37         // java.lang.StringBuilder.append:(java.lang.String)java.lang.StringBuilder
    25: iload_3       
    26: invokevirtual #36         // java.lang.StringBuilder.append:(int)java.lang.StringBuilder
    29: invokevirtual #38         // java.lang.StringBuilder.toString:()java.lang.String
    32: invokespecial #39         // java.lang.IllegalArgumentException.<init>:(java.lang.String)void
    35: athrow        
    36: iload_3       
    37: i2l           
    38: lload_0       
    39: iload_2       
    40: i2l           
    41: invokestatic  #40         // max:(long, long)long
    44: invokestatic  #41         // min:(long, long)long
    47: l2i           
    48: ireturn       
   <|@
end_bytecodes
begin_cfg
  name "After LIR generation"
  begin_block
    name "B0"
    from_bci -1
    to_bci -1
    predecessors 
    successors "B1" "B2" 
    xhandlers
    flags 
    probability 4607182418800017408
    begin_IR
      HIR
f <@#|@fixed with next>@ <|@
tid v0 <|@
d <@d|@=== Debug Properties ===
hasSpeculationFence: false
stamp: void
=== Inputs ===
stateAfter: - 
=== Succesors ===
next: v26 
=== Usages ===
=== Predecessor ===
- >@ <|@
instruction <@StartNode|@jdk.graal.compiler.nodes.StartNode>@ stateAfter: - #next: v26  <|@  <|@
f <@~|@floating>@ <|@
tid j1 <|@
result v0|QWORD <|@
d <@d|@=== Debug Properties ===
index: 0
stamp: i64
uncheckedStamp: [null]
=== Inputs ===
=== Succesors ===
=== Usages ===
?4 j19 v17 
=== Predecessor ===
- >@ <|@
instruction <@Parameter|@jdk.graal.compiler.nodes.ParameterNode>@  <|@  <|@
f <@~|@floating>@ <|@
tid i3 <|@
result v2|DWORD <|@
d <@d|@=== Debug Properties ===
index: 2
stamp: i32
uncheckedStamp: [null]
=== Inputs ===
=== Succesors ===
=== Usages ===
?4 v5 j7 
=== Predecessor ===
- >@ <|@
instruction <@Parameter|@jdk.graal.compiler.nodes.ParameterNode>@  <|@  <|@
f <@~|@floating>@ <|@
tid i2 <|@
result v1|DWORD <|@
d <@d|@=== Debug Properties ===
index: 1
stamp: i32
uncheckedStamp: [null]
=== Inputs ===
=== Succesors ===
=== Usages ===
?4 v5 j8 
=== Predecessor ===
- >@ <|@
instruction <@Parameter|@jdk.graal.compiler.nodes.ParameterNode>@  <|@  <|@
f <@~|@floating>@ <|@
tid v5 <|@
d <@d|@=== Debug Properties ===
condition: LT
nodeSourcePosition: at java.lang.Math.clamp(Math.java:2214) [bci: 2]
op: jdk.graal.compiler.nodes.calc.IntegerLessThanNode$LessThanOp@406e677e
stamp: void
unorderedIsTrue: false
=== Inputs ===
x: i3 
y: i2 
=== Succesors ===
=== Usages ===
v26 
=== Predecessor ===
- >@ <|@
instruction <@<|@jdk.graal.compiler.nodes.calc.IntegerLessThanNode>@ x: i3 y: i2  <|@  <|@
f <@*|@fixed>@ <|@
tid v26 <|@
d <@d|@=== Debug Properties ===
nodeSourcePosition: at java.lang.Math.clamp(Math.java:2214) [bci: 2]
profileData: INJECTED designatedSuccessorProbability: 0.0
stamp: void
=== Inputs ===
condition: v5 
=== Succesors ===
trueSuccessor: v24 
falseSuccessor: v25 
=== Usages ===
=== Predecessor ===
v0 >@ <|@
instruction <@If|@jdk.graal.compiler.nodes.IfNode>@ condition: v5 #trueSuccessor: v24 #falseSuccessor: v25  <|@  <|@
    end_IR
    begin_IR
      LIR
      nr   -1  <|@ instruction [rsi|QWORD, rdx|DWORD, rcx|DWORD, rbp|QWORD] = LABEL alignment: 0 numbPhis: 0 label: ? <|@ <|@
      nr   -1  <|@ instruction stack:16|QWORD = MOVE input: rbp|QWORD moveKind: QWORD <|@ <|@
      nr   -1  <|@ instruction [] = HOTSPOTLOCKSTACK frameMapBuilder: jdk.graal.compiler.hotspot.amd64.AMD64HotSpotFrameMapBuilder@8113c20 slotKind: QWORD <|@ <|@
      nr   -1  <|@ instruction v0|QWORD = MOVE input: rsi|QWORD moveKind: QWORD <|@ <|@
      nr   -1  <|@ instruction v1|DWORD = MOVE input: rdx|DWORD moveKind: DWORD <|@ <|@
      nr   -1  <|@ instruction v2|DWORD = MOVE input: rcx|DWORD moveKind: DWORD <|@ <|@
      nr   -1  <|@ instruction CMPBRANCH (x: v1|DWORD, y: v2|DWORD) trueDestinationProbability: 0.0 condition: > trueDestination: B0 -> B1 falseDestination: B0 -> B2 size: DWORD <|@ <|@
    end_IR
  end_block
  begin_block
    name "B1"
    from_bci -1
    to_bci -1
    predecessors "B0" 
    successors 
    xhandlers
    flags 
    probability 2355382605114769408
    begin_IR
      HIR
f <@#|@fixed with next>@ <|@
tid v24 <|@
d <@d|@=== Debug Properties ===
hasSpeculationFence: false
nodeSourcePosition: at java.lang.Math.clamp(Math.java:2214) [bci: 2]
stamp: void
=== Inputs ===
=== Succesors ===
next: v23 
=== Usages ===
=== Predecessor ===
v26 >@ <|@
instruction <@Begin|@jdk.graal.compiler.nodes.BeginNode>@ #next: v23  <|@  <|@
tid ?4 <|@
d <@d|@=== Debug Properties ===
bci: 0
bytecode: iload_2
code: ResolvedJavaMethodBytecode<Math.clamp(long, int, int)>
localsSize: 4
locksSize: 0
sourceFile: Math.java
sourceLine: 2214
stackSize: 0
stackState: BeforePop
validForDeoptimization: true
=== Inputs ===
outerFrameState: - 
values: j1 - i2 i3 
=== Succesors ===
=== Usages ===
v23 
=== Predecessor ===
- >@ <|@
instruction <@FrameState|@jdk.graal.compiler.nodes.FrameState>@ outerFrameState: - values: j1 - i2 i3  <|@  <|@
f <@*|@fixed>@ <|@
tid v23 <|@
d <@d|@=== Debug Properties ===
action: InvalidateReprofile
debugId: 0
mayConvertToGuard: true
nodeSourcePosition: at java.lang.Math.clamp(Math.java:2214) [bci: 2]
reason: UnreachedCode
speculation: {0x0000000000000014[index: 0, len: 20, hash: 0xddb97d58]: UnreachedCode@6[HotSpotMethod<Math.clamp(long, int, int)>, 5]}
stamp: void
=== Inputs ===
stateBefore: ?4 
=== Succesors ===
=== Usages ===
=== Predecessor ===
v24 >@ <|@
instruction <@Deopt|@jdk.graal.compiler.nodes.DeoptimizeNode>@ stateBefore: ?4  <|@  <|@
    end_IR
    begin_IR
      LIR
      nr   -1  <|@ instruction [] = LABEL alignment: 0 numbPhis: 0 label: ? <|@ <|@
      nr   -1  <|@ instruction MOV x: [r15|QWORD + 1156] y: -5907 size: DWORD <|@ <|@
      nr   -1  <|@ instruction MOV x: [r15|QWORD + 1168] y: 20 size: QWORD <|@ <|@
      nr   -1  <|@ st <@st|@java.lang.Math.clamp(Math.java:2214) [bci: 0]
locals: v0|QWORD - v1|DWORD v2|DWORD 
>@ <|@ instruction DEOPT info [bci:0] <|@ <|@
    end_IR
  end_block
  begin_block
    name "B2"
    from_bci -1
    to_bci -1
    predecessors "B0" 
    successors 
    xhandlers
    flags 
    probability 4607182418800017408
    begin_IR
      HIR
f <@#|@fixed with next>@ <|@
tid v25 <|@
d <@d|@=== Debug Properties ===
hasSpeculationFence: false
nodeSourcePosition: at java.lang.Math.clamp(Math.java:2217) [bci: 36]
stamp: void
=== Inputs ===
=== Succesors ===
next: v16 
=== Usages ===
=== Predecessor ===
v26 >@ <|@
instruction <@Begin|@jdk.graal.compiler.nodes.BeginNode>@ #next: v16  <|@  <|@
f <@~|@floating>@ <|@
tid j8 <|@
result v3|QWORD <|@
d <@d|@=== Debug Properties ===
inputBits: 32
nodeSourcePosition: at java.lang.Math.clamp(Math.java:2217) [bci: 40]
resultBits: 64
stamp: i64 [-2147483648 - 2147483647]
=== Inputs ===
value: i2 
=== Succesors ===
=== Usages ===
j19 v17 
=== Predecessor ===
- >@ <|@
instruction <@SignExtend|@jdk.graal.compiler.nodes.calc.SignExtendNode>@ value: i2  <|@  <|@
f <@~|@floating>@ <|@
tid v17 <|@
d <@d|@=== Debug Properties ===
condition: LT
nodeSourcePosition: at java.lang.Math.max(Math.java:2034) [bci: 3]
at java.lang.Math.clamp(Math.java:2217) [bci: 41]
op: jdk.graal.compiler.nodes.calc.IntegerLessThanNode$LessThanOp@406e677e
stamp: void
unorderedIsTrue: false
=== Inputs ===
x: j1 
y: j8 
=== Succesors ===
=== Usages ===
j19 
=== Predecessor ===
- >@ <|@
instruction <@<|@jdk.graal.compiler.nodes.calc.IntegerLessThanNode>@ x: j1 y: j8  <|@  <|@
f <@~|@floating>@ <|@
tid j19 <|@
result v4|QWORD <|@
d <@d|@=== Debug Properties ===
nodeSourcePosition: at java.lang.Math.max(Math.java:2034) [bci: 3]
at java.lang.Math.clamp(Math.java:2217) [bci: 41]
stamp: i64 [-2147483648 - 9223372036854775807]
=== Inputs ===
condition: v17 
trueValue: j8 
falseValue: j1 
=== Succesors ===
=== Usages ===
j22 v20 
=== Predecessor ===
- >@ <|@
instruction <@Conditional|@jdk.graal.compiler.nodes.calc.ConditionalNode>@ condition: v17 trueValue: j8 falseValue: j1  <|@  <|@
f <@~|@floating>@ <|@
tid j7 <|@
result v5|QWORD <|@
d <@d|@=== Debug Properties ===
inputBits: 32
nodeSourcePosition: at java.lang.Math.clamp(Math.java:2217) [bci: 37]
resultBits: 64
stamp: i64 [-2147483648 - 2147483647]
=== Inputs ===
value: i3 
=== Succesors ===
=== Usages ===
j22 v20 
=== Predecessor ===
- >@ <|@
instruction <@SignExtend|@jdk.graal.compiler.nodes.calc.SignExtendNode>@ value: i3  <|@  <|@
f <@~|@floating>@ <|@
tid v20 <|@
d <@d|@=== Debug Properties ===
condition: LT
nodeSourcePosition: at java.lang.Math.min(Math.java:2129) [bci: 3]
at java.lang.Math.clamp(Math.java:2217) [bci: 44]
op: jdk.graal.compiler.nodes.calc.IntegerLessThanNode$LessThanOp@406e677e
stamp: void
unorderedIsTrue: false
=== Inputs ===
x: j19 
y: j7 
=== Succesors ===
=== Usages ===
j22 
=== Predecessor ===
- >@ <|@
instruction <@<|@jdk.graal.compiler.nodes.calc.IntegerLessThanNode>@ x: j19 y: j7  <|@  <|@
f <@~|@floating>@ <|@
tid j22 <|@
result v6|QWORD <|@
d <@d|@=== Debug Properties ===
nodeSourcePosition: at java.lang.Math.min(Math.java:2129) [bci: 3]
at java.lang.Math.clamp(Math.java:2217) [bci: 44]
stamp: i64 [-2147483648 - 2147483647]
=== Inputs ===
condition: v20 
trueValue: j19 
falseValue: j7 
=== Succesors ===
=== Usages ===
i15 
=== Predecessor ===
- >@ <|@
instruction <@Conditional|@jdk.graal.compiler.nodes.calc.ConditionalNode>@ condition: v20 trueValue: j19 falseValue: j7  <|@  <|@
f <@~|@floating>@ <|@
tid i15 <|@
result v7|DWORD <|@
d <@d|@=== Debug Properties ===
inputBits: 64
nodeSourcePosition: at java.lang.Math.clamp(Math.java:2217) [bci: 47]
resultBits: 32
stamp: i32
=== Inputs ===
value: j22 
=== Succesors ===
=== Usages ===
v16 
=== Predecessor ===
- >@ <|@
instruction <@Narrow|@jdk.graal.compiler.nodes.calc.NarrowNode>@ value: j22  <|@  <|@
f <@*|@fixed>@ <|@
tid v16 <|@
d <@d|@=== Debug Properties ===
nodeSourcePosition: at java.lang.Math.clamp(Math.java:2217) [bci: 48]
stamp: void
=== Inputs ===
memoryMap: - 
result: i15 
=== Succesors ===
=== Usages ===
=== Predecessor ===
v25 >@ <|@
instruction <@Return|@jdk.graal.compiler.nodes.ReturnNode>@ memoryMap: - result: i15  <|@  <|@
    end_IR
    begin_IR
      LIR
      nr   -1  <|@ instruction [] = LABEL alignment: 0 numbPhis: 0 label: ? <|@ <|@
      nr   -1  <|@ instruction v3|QWORD = MOVSXD value: v1|DWORD size: QWORD <|@ <|@
      nr   -1  <|@ instruction CMP (x: v3|QWORD, y: v0|QWORD) size: QWORD <|@ <|@
      nr   -1  <|@ instruction v4|QWORD = CMOVE (falseValue: v0|QWORD, ~trueValue: v3|QWORD) condition: > <|@ <|@
      nr   -1  <|@ instruction v5|QWORD = MOVSXD value: v2|DWORD size: QWORD <|@ <|@
      nr   -1  <|@ instruction CMP (x: v5|QWORD, y: v4|QWORD) size: QWORD <|@ <|@
      nr   -1  <|@ instruction v6|QWORD = CMOVE (falseValue: v5|QWORD, ~trueValue: v4|QWORD) condition: > <|@ <|@
      nr   -1  <|@ instruction v7|DWORD = MOV value: v6|QWORD size: DWORD <|@ <|@
      nr   -1  <|@ instruction rax|DWORD = MOVE input: v7|DWORD moveKind: DWORD <|@ <|@
      nr   -1  <|@ instruction RETURN (savedRbp: stack:16|QWORD, value: rax|DWORD) isStub: false requiresReservedStackAccessCheck: false thread: r15 scratchForSafepointOnReturn: rcx config: jdk.graal.compiler.hotspot.GraalHotSpotVMConfig@4817c460 <|@ <|@
    end_IR
  end_block
end_cfg
begin_cfg
  name "After LIRGTSlowdown"
  begin_block
    name "B0"
    from_bci -1
    to_bci -1
    predecessors 
    successors "B1" "B2" 
    xhandlers
    flags 
    probability 4607182418800017408
    begin_IR
      LIR
      nr   -1  <|@ instruction [rsi|QWORD, rdx|DWORD, rcx|DWORD, rbp|QWORD] = LABEL alignment: 0 numbPhis: 0 label: ? <|@ <|@
      nr   -1  <|@ instruction NOP <|@ <|@
      nr   -1  <|@ instruction NOP <|@ <|@
      nr   -1  <|@ instruction NOP <|@ <|@
      nr   -1  <|@ instruction NOP <|@ <|@
      nr   -1  <|@ instruction NOP <|@ <|@
      nr   -1  <|@ instruction NOP <|@ <|@
      nr   -1  <|@ instruction NOP <|@ <|@
      nr   -1  <|@ instruction NOP <|@ <|@
      nr   -1  <|@ instruction NOP <|@ <|@
      nr   -1  <|@ instruction stack:16|QWORD = MOVE input: rbp|QWORD moveKind: QWORD <|@ <|@
      nr   -1  <|@ instruction [] = HOTSPOTLOCKSTACK frameMapBuilder: jdk.graal.compiler.hotspot.amd64.AMD64HotSpotFrameMapBuilder@8113c20 slotKind: QWORD <|@ <|@
      nr   -1  <|@ instruction v0|QWORD = MOVE input: rsi|QWORD moveKind: QWORD <|@ <|@
      nr   -1  <|@ instruction v1|DWORD = MOVE input: rdx|DWORD moveKind: DWORD <|@ <|@
      nr   -1  <|@ instruction v2|DWORD = MOVE input: rcx|DWORD moveKind: DWORD <|@ <|@
      nr   -1  <|@ instruction CMPBRANCH (x: v1|DWORD, y: v2|DWORD) trueDestinationProbability: 0.0 condition: > trueDestination: B0 -> B1 falseDestination: B0 -> B2 size: DWORD <|@ <|@
    end_IR
  end_block
  begin_block
    name "B2"
    from_bci -1
    to_bci -1
    predecessors "B0" 
    successors 
    xhandlers
    flags 
    probability 4607182418800017408
    begin_IR
      LIR
      nr   -1  <|@ instruction [] = LABEL alignment: 0 numbPhis: 0 label: ? <|@ <|@
      nr   -1  <|@ instruction NOP <|@ <|@
      nr   -1  <|@ instruction NOP <|@ <|@
      nr   -1  <|@ instruction NOP <|@ <|@
      nr   -1  <|@ instruction NOP <|@ <|@
      nr   -1  <|@ instruction NOP <|@ <|@
      nr   -1  <|@ instruction NOP <|@ <|@
      nr   -1  <|@ instruction NOP <|@ <|@
      nr   -1  <|@ instruction NOP <|@ <|@
      nr   -1  <|@ instruction NOP <|@ <|@
      nr   -1  <|@ instruction NOP <|@ <|@
      nr   -1  <|@ instruction NOP <|@ <|@
      nr   -1  <|@ instruction NOP <|@ <|@
      nr   -1  <|@ instruction NOP <|@ <|@
      nr   -1  <|@ instruction NOP <|@ <|@
      nr   -1  <|@ instruction NOP <|@ <|@
      nr   -1  <|@ instruction v3|QWORD = MOVSXD value: v1|DWORD size: QWORD <|@ <|@
      nr   -1  <|@ instruction CMP (x: v3|QWORD, y: v0|QWORD) size: QWORD <|@ <|@
      nr   -1  <|@ instruction v4|QWORD = CMOVE (falseValue: v0|QWORD, ~trueValue: v3|QWORD) condition: > <|@ <|@
      nr   -1  <|@ instruction v5|QWORD = MOVSXD value: v2|DWORD size: QWORD <|@ <|@
      nr   -1  <|@ instruction CMP (x: v5|QWORD, y: v4|QWORD) size: QWORD <|@ <|@
      nr   -1  <|@ instruction v6|QWORD = CMOVE (falseValue: v5|QWORD, ~trueValue: v4|QWORD) condition: > <|@ <|@
      nr   -1  <|@ instruction v7|DWORD = MOV value: v6|QWORD size: DWORD <|@ <|@
      nr   -1  <|@ instruction rax|DWORD = MOVE input: v7|DWORD moveKind: DWORD <|@ <|@
      nr   -1  <|@ instruction RETURN (savedRbp: stack:16|QWORD, value: rax|DWORD) isStub: false requiresReservedStackAccessCheck: false thread: r15 scratchForSafepointOnReturn: rcx config: jdk.graal.compiler.hotspot.GraalHotSpotVMConfig@4817c460 <|@ <|@
    end_IR
  end_block
  begin_block
    name "B1"
    from_bci -1
    to_bci -1
    predecessors "B0" 
    successors 
    xhandlers
    flags 
    probability 2355382605114769408
    begin_IR
      LIR
      nr   -1  <|@ instruction [] = LABEL alignment: 0 numbPhis: 0 label: ? <|@ <|@
      nr   -1  <|@ instruction NOP <|@ <|@
      nr   -1  <|@ instruction NOP <|@ <|@
      nr   -1  <|@ instruction NOP <|@ <|@
      nr   -1  <|@ instruction NOP <|@ <|@
      nr   -1  <|@ instruction NOP <|@ <|@
      nr   -1  <|@ instruction NOP <|@ <|@
      nr   -1  <|@ instruction NOP <|@ <|@
      nr   -1  <|@ instruction MOV x: [r15|QWORD + 1156] y: -5907 size: DWORD <|@ <|@
      nr   -1  <|@ instruction MOV x: [r15|QWORD + 1168] y: 20 size: QWORD <|@ <|@
      nr   -1  <|@ st <@st|@java.lang.Math.clamp(Math.java:2214) [bci: 0]
locals: v0|QWORD - v1|DWORD v2|DWORD 
>@ <|@ instruction DEOPT info [bci:0] <|@ <|@
    end_IR
  end_block
end_cfg
begin_bytecodes
     0: iload_2       
     1: iload_3       
     2: if_icmple     36
     5: new           #177        // java.lang.IllegalArgumentException
     8: dup           
     9: new           #179        // java.lang.StringBuilder
    12: dup           
    13: invokespecial #35         // java.lang.StringBuilder.<init>:()void
    16: iload_2       
    17: invokevirtual #36         // java.lang.StringBuilder.append:(int)java.lang.StringBuilder
    20: ldc           #186        // " > "
    22: invokevirtual #37         // java.lang.StringBuilder.append:(java.lang.String)java.lang.StringBuilder
    25: iload_3       
    26: invokevirtual #36         // java.lang.StringBuilder.append:(int)java.lang.StringBuilder
    29: invokevirtual #38         // java.lang.StringBuilder.toString:()java.lang.String
    32: invokespecial #39         // java.lang.IllegalArgumentException.<init>:(java.lang.String)void
    35: athrow        
    36: iload_3       
    37: i2l           
    38: lload_0       
    39: iload_2       
    40: i2l           
    41: invokestatic  #40         // max:(long, long)long
    44: invokestatic  #41         // min:(long, long)long
    47: l2i           
    48: ireturn       
   <|@
end_bytecodes
begin_cfg
  name "After ConstantLoadOptimization"
  begin_block
    name "B0"
    from_bci -1
    to_bci -1
    predecessors 
    successors "B1" "B2" 
    xhandlers
    flags 
    probability 4607182418800017408
    begin_IR
      LIR
      nr   -1  <|@ instruction [rsi|QWORD, rdx|DWORD, rcx|DWORD, rbp|QWORD] = LABEL alignment: 0 numbPhis: 0 label: ? <|@ <|@
      nr   -1  <|@ instruction NOP <|@ <|@
      nr   -1  <|@ instruction NOP <|@ <|@
      nr   -1  <|@ instruction NOP <|@ <|@
      nr   -1  <|@ instruction NOP <|@ <|@
      nr   -1  <|@ instruction NOP <|@ <|@
      nr   -1  <|@ instruction NOP <|@ <|@
      nr   -1  <|@ instruction NOP <|@ <|@
      nr   -1  <|@ instruction NOP <|@ <|@
      nr   -1  <|@ instruction NOP <|@ <|@
      nr   -1  <|@ instruction stack:16|QWORD = MOVE input: rbp|QWORD moveKind: QWORD <|@ <|@
      nr   -1  <|@ instruction [] = HOTSPOTLOCKSTACK frameMapBuilder: jdk.graal.compiler.hotspot.amd64.AMD64HotSpotFrameMapBuilder@8113c20 slotKind: QWORD <|@ <|@
      nr   -1  <|@ instruction v0|QWORD = MOVE input: rsi|QWORD moveKind: QWORD <|@ <|@
      nr   -1  <|@ instruction v1|DWORD = MOVE input: rdx|DWORD moveKind: DWORD <|@ <|@
      nr   -1  <|@ instruction v2|DWORD = MOVE input: rcx|DWORD moveKind: DWORD <|@ <|@
      nr   -1  <|@ instruction CMPBRANCH (x: v1|DWORD, y: v2|DWORD) trueDestinationProbability: 0.0 condition: > trueDestination: B0 -> B1 falseDestination: B0 -> B2 size: DWORD <|@ <|@
    end_IR
  end_block
  begin_block
    name "B2"
    from_bci -1
    to_bci -1
    predecessors "B0" 
    successors 
    xhandlers
    flags 
    probability 4607182418800017408
    begin_IR
      LIR
      nr   -1  <|@ instruction [] = LABEL alignment: 0 numbPhis: 0 label: ? <|@ <|@
      nr   -1  <|@ instruction NOP <|@ <|@
      nr   -1  <|@ instruction NOP <|@ <|@
      nr   -1  <|@ instruction NOP <|@ <|@
      nr   -1  <|@ instruction NOP <|@ <|@
      nr   -1  <|@ instruction NOP <|@ <|@
      nr   -1  <|@ instruction NOP <|@ <|@
      nr   -1  <|@ instruction NOP <|@ <|@
      nr   -1  <|@ instruction NOP <|@ <|@
      nr   -1  <|@ instruction NOP <|@ <|@
      nr   -1  <|@ instruction NOP <|@ <|@
      nr   -1  <|@ instruction NOP <|@ <|@
      nr   -1  <|@ instruction NOP <|@ <|@
      nr   -1  <|@ instruction NOP <|@ <|@
      nr   -1  <|@ instruction NOP <|@ <|@
      nr   -1  <|@ instruction NOP <|@ <|@
      nr   -1  <|@ instruction v3|QWORD = MOVSXD value: v1|DWORD size: QWORD <|@ <|@
      nr   -1  <|@ instruction CMP (x: v3|QWORD, y: v0|QWORD) size: QWORD <|@ <|@
      nr   -1  <|@ instruction v4|QWORD = CMOVE (falseValue: v0|QWORD, ~trueValue: v3|QWORD) condition: > <|@ <|@
      nr   -1  <|@ instruction v5|QWORD = MOVSXD value: v2|DWORD size: QWORD <|@ <|@
      nr   -1  <|@ instruction CMP (x: v5|QWORD, y: v4|QWORD) size: QWORD <|@ <|@
      nr   -1  <|@ instruction v6|QWORD = CMOVE (falseValue: v5|QWORD, ~trueValue: v4|QWORD) condition: > <|@ <|@
      nr   -1  <|@ instruction v7|DWORD = MOV value: v6|QWORD size: DWORD <|@ <|@
      nr   -1  <|@ instruction rax|DWORD = MOVE input: v7|DWORD moveKind: DWORD <|@ <|@
      nr   -1  <|@ instruction RETURN (savedRbp: stack:16|QWORD, value: rax|DWORD) isStub: false requiresReservedStackAccessCheck: false thread: r15 scratchForSafepointOnReturn: rcx config: jdk.graal.compiler.hotspot.GraalHotSpotVMConfig@4817c460 <|@ <|@
    end_IR
  end_block
  begin_block
    name "B1"
    from_bci -1
    to_bci -1
    predecessors "B0" 
    successors 
    xhandlers
    flags 
    probability 2355382605114769408
    begin_IR
      LIR
      nr   -1  <|@ instruction [] = LABEL alignment: 0 numbPhis: 0 label: ? <|@ <|@
      nr   -1  <|@ instruction NOP <|@ <|@
      nr   -1  <|@ instruction NOP <|@ <|@
      nr   -1  <|@ instruction NOP <|@ <|@
      nr   -1  <|@ instruction NOP <|@ <|@
      nr   -1  <|@ instruction NOP <|@ <|@
      nr   -1  <|@ instruction NOP <|@ <|@
      nr   -1  <|@ instruction NOP <|@ <|@
      nr   -1  <|@ instruction MOV x: [r15|QWORD + 1156] y: -5907 size: DWORD <|@ <|@
      nr   -1  <|@ instruction MOV x: [r15|QWORD + 1168] y: 20 size: QWORD <|@ <|@
      nr   -1  <|@ st <@st|@java.lang.Math.clamp(Math.java:2214) [bci: 0]
locals: v0|QWORD - v1|DWORD v2|DWORD 
>@ <|@ instruction DEOPT info [bci:0] <|@ <|@
    end_IR
  end_block
end_cfg
begin_bytecodes
     0: iload_2       
     1: iload_3       
     2: if_icmple     36
     5: new           #177        // java.lang.IllegalArgumentException
     8: dup           
     9: new           #179        // java.lang.StringBuilder
    12: dup           
    13: invokespecial #35         // java.lang.StringBuilder.<init>:()void
    16: iload_2       
    17: invokevirtual #36         // java.lang.StringBuilder.append:(int)java.lang.StringBuilder
    20: ldc           #186        // " > "
    22: invokevirtual #37         // java.lang.StringBuilder.append:(java.lang.String)java.lang.StringBuilder
    25: iload_3       
    26: invokevirtual #36         // java.lang.StringBuilder.append:(int)java.lang.StringBuilder
    29: invokevirtual #38         // java.lang.StringBuilder.toString:()java.lang.String
    32: invokespecial #39         // java.lang.IllegalArgumentException.<init>:(java.lang.String)void
    35: athrow        
    36: iload_3       
    37: i2l           
    38: lload_0       
    39: iload_2       
    40: i2l           
    41: invokestatic  #40         // max:(long, long)long
    44: invokestatic  #41         // min:(long, long)long
    47: l2i           
    48: ireturn       
   <|@
end_bytecodes
begin_cfg
  name "After SaveCalleeSaveRegisters"
  begin_block
    name "B0"
    from_bci -1
    to_bci -1
    predecessors 
    successors "B1" "B2" 
    xhandlers
    flags 
    probability 4607182418800017408
    begin_IR
      LIR
      nr   -1  <|@ instruction [rsi|QWORD, rdx|DWORD, rcx|DWORD, rbp|QWORD] = LABEL alignment: 0 numbPhis: 0 label: ? <|@ <|@
      nr   -1  <|@ instruction NOP <|@ <|@
      nr   -1  <|@ instruction NOP <|@ <|@
      nr   -1  <|@ instruction NOP <|@ <|@
      nr   -1  <|@ instruction NOP <|@ <|@
      nr   -1  <|@ instruction NOP <|@ <|@
      nr   -1  <|@ instruction NOP <|@ <|@
      nr   -1  <|@ instruction NOP <|@ <|@
      nr   -1  <|@ instruction NOP <|@ <|@
      nr   -1  <|@ instruction NOP <|@ <|@
      nr   -1  <|@ instruction stack:16|QWORD = MOVE input: rbp|QWORD moveKind: QWORD <|@ <|@
      nr   -1  <|@ instruction [] = HOTSPOTLOCKSTACK frameMapBuilder: jdk.graal.compiler.hotspot.amd64.AMD64HotSpotFrameMapBuilder@8113c20 slotKind: QWORD <|@ <|@
      nr   -1  <|@ instruction v0|QWORD = MOVE input: rsi|QWORD moveKind: QWORD <|@ <|@
      nr   -1  <|@ instruction v1|DWORD = MOVE input: rdx|DWORD moveKind: DWORD <|@ <|@
      nr   -1  <|@ instruction v2|DWORD = MOVE input: rcx|DWORD moveKind: DWORD <|@ <|@
      nr   -1  <|@ instruction CMPBRANCH (x: v1|DWORD, y: v2|DWORD) trueDestinationProbability: 0.0 condition: > trueDestination: B0 -> B1 falseDestination: B0 -> B2 size: DWORD <|@ <|@
    end_IR
  end_block
  begin_block
    name "B2"
    from_bci -1
    to_bci -1
    predecessors "B0" 
    successors 
    xhandlers
    flags 
    probability 4607182418800017408
    begin_IR
      LIR
      nr   -1  <|@ instruction [] = LABEL alignment: 0 numbPhis: 0 label: ? <|@ <|@
      nr   -1  <|@ instruction NOP <|@ <|@
      nr   -1  <|@ instruction NOP <|@ <|@
      nr   -1  <|@ instruction NOP <|@ <|@
      nr   -1  <|@ instruction NOP <|@ <|@
      nr   -1  <|@ instruction NOP <|@ <|@
      nr   -1  <|@ instruction NOP <|@ <|@
      nr   -1  <|@ instruction NOP <|@ <|@
      nr   -1  <|@ instruction NOP <|@ <|@
      nr   -1  <|@ instruction NOP <|@ <|@
      nr   -1  <|@ instruction NOP <|@ <|@
      nr   -1  <|@ instruction NOP <|@ <|@
      nr   -1  <|@ instruction NOP <|@ <|@
      nr   -1  <|@ instruction NOP <|@ <|@
      nr   -1  <|@ instruction NOP <|@ <|@
      nr   -1  <|@ instruction NOP <|@ <|@
      nr   -1  <|@ instruction v3|QWORD = MOVSXD value: v1|DWORD size: QWORD <|@ <|@
      nr   -1  <|@ instruction CMP (x: v3|QWORD, y: v0|QWORD) size: QWORD <|@ <|@
      nr   -1  <|@ instruction v4|QWORD = CMOVE (falseValue: v0|QWORD, ~trueValue: v3|QWORD) condition: > <|@ <|@
      nr   -1  <|@ instruction v5|QWORD = MOVSXD value: v2|DWORD size: QWORD <|@ <|@
      nr   -1  <|@ instruction CMP (x: v5|QWORD, y: v4|QWORD) size: QWORD <|@ <|@
      nr   -1  <|@ instruction v6|QWORD = CMOVE (falseValue: v5|QWORD, ~trueValue: v4|QWORD) condition: > <|@ <|@
      nr   -1  <|@ instruction v7|DWORD = MOV value: v6|QWORD size: DWORD <|@ <|@
      nr   -1  <|@ instruction rax|DWORD = MOVE input: v7|DWORD moveKind: DWORD <|@ <|@
      nr   -1  <|@ instruction RETURN (savedRbp: stack:16|QWORD, value: rax|DWORD) isStub: false requiresReservedStackAccessCheck: false thread: r15 scratchForSafepointOnReturn: rcx config: jdk.graal.compiler.hotspot.GraalHotSpotVMConfig@4817c460 <|@ <|@
    end_IR
  end_block
  begin_block
    name "B1"
    from_bci -1
    to_bci -1
    predecessors "B0" 
    successors 
    xhandlers
    flags 
    probability 2355382605114769408
    begin_IR
      LIR
      nr   -1  <|@ instruction [] = LABEL alignment: 0 numbPhis: 0 label: ? <|@ <|@
      nr   -1  <|@ instruction NOP <|@ <|@
      nr   -1  <|@ instruction NOP <|@ <|@
      nr   -1  <|@ instruction NOP <|@ <|@
      nr   -1  <|@ instruction NOP <|@ <|@
      nr   -1  <|@ instruction NOP <|@ <|@
      nr   -1  <|@ instruction NOP <|@ <|@
      nr   -1  <|@ instruction NOP <|@ <|@
      nr   -1  <|@ instruction MOV x: [r15|QWORD + 1156] y: -5907 size: DWORD <|@ <|@
      nr   -1  <|@ instruction MOV x: [r15|QWORD + 1168] y: 20 size: QWORD <|@ <|@
      nr   -1  <|@ st <@st|@java.lang.Math.clamp(Math.java:2214) [bci: 0]
locals: v0|QWORD - v1|DWORD v2|DWORD 
>@ <|@ instruction DEOPT info [bci:0] <|@ <|@
    end_IR
  end_block
end_cfg
begin_bytecodes
     0: iload_2       
     1: iload_3       
     2: if_icmple     36
     5: new           #177        // java.lang.IllegalArgumentException
     8: dup           
     9: new           #179        // java.lang.StringBuilder
    12: dup           
    13: invokespecial #35         // java.lang.StringBuilder.<init>:()void
    16: iload_2       
    17: invokevirtual #36         // java.lang.StringBuilder.append:(int)java.lang.StringBuilder
    20: ldc           #186        // " > "
    22: invokevirtual #37         // java.lang.StringBuilder.append:(java.lang.String)java.lang.StringBuilder
    25: iload_3       
    26: invokevirtual #36         // java.lang.StringBuilder.append:(int)java.lang.StringBuilder
    29: invokevirtual #38         // java.lang.StringBuilder.toString:()java.lang.String
    32: invokespecial #39         // java.lang.IllegalArgumentException.<init>:(java.lang.String)void
    35: athrow        
    36: iload_3       
    37: i2l           
    38: lload_0       
    39: iload_2       
    40: i2l           
    41: invokestatic  #40         // max:(long, long)long
    44: invokestatic  #41         // min:(long, long)long
    47: l2i           
    48: ireturn       
   <|@
end_bytecodes
begin_cfg
  name "After PreAllocationOptimizationStage"
  begin_block
    name "B0"
    from_bci -1
    to_bci -1
    predecessors 
    successors "B1" "B2" 
    xhandlers
    flags 
    probability 4607182418800017408
    begin_IR
      LIR
      nr   -1  <|@ instruction [rsi|QWORD, rdx|DWORD, rcx|DWORD, rbp|QWORD] = LABEL alignment: 0 numbPhis: 0 label: ? <|@ <|@
      nr   -1  <|@ instruction NOP <|@ <|@
      nr   -1  <|@ instruction NOP <|@ <|@
      nr   -1  <|@ instruction NOP <|@ <|@
      nr   -1  <|@ instruction NOP <|@ <|@
      nr   -1  <|@ instruction NOP <|@ <|@
      nr   -1  <|@ instruction NOP <|@ <|@
      nr   -1  <|@ instruction NOP <|@ <|@
      nr   -1  <|@ instruction NOP <|@ <|@
      nr   -1  <|@ instruction NOP <|@ <|@
      nr   -1  <|@ instruction stack:16|QWORD = MOVE input: rbp|QWORD moveKind: QWORD <|@ <|@
      nr   -1  <|@ instruction [] = HOTSPOTLOCKSTACK frameMapBuilder: jdk.graal.compiler.hotspot.amd64.AMD64HotSpotFrameMapBuilder@8113c20 slotKind: QWORD <|@ <|@
      nr   -1  <|@ instruction v0|QWORD = MOVE input: rsi|QWORD moveKind: QWORD <|@ <|@
      nr   -1  <|@ instruction v1|DWORD = MOVE input: rdx|DWORD moveKind: DWORD <|@ <|@
      nr   -1  <|@ instruction v2|DWORD = MOVE input: rcx|DWORD moveKind: DWORD <|@ <|@
      nr   -1  <|@ instruction CMPBRANCH (x: v1|DWORD, y: v2|DWORD) trueDestinationProbability: 0.0 condition: > trueDestination: B0 -> B1 falseDestination: B0 -> B2 size: DWORD <|@ <|@
    end_IR
  end_block
  begin_block
    name "B2"
    from_bci -1
    to_bci -1
    predecessors "B0" 
    successors 
    xhandlers
    flags 
    probability 4607182418800017408
    begin_IR
      LIR
      nr   -1  <|@ instruction [] = LABEL alignment: 0 numbPhis: 0 label: ? <|@ <|@
      nr   -1  <|@ instruction NOP <|@ <|@
      nr   -1  <|@ instruction NOP <|@ <|@
      nr   -1  <|@ instruction NOP <|@ <|@
      nr   -1  <|@ instruction NOP <|@ <|@
      nr   -1  <|@ instruction NOP <|@ <|@
      nr   -1  <|@ instruction NOP <|@ <|@
      nr   -1  <|@ instruction NOP <|@ <|@
      nr   -1  <|@ instruction NOP <|@ <|@
      nr   -1  <|@ instruction NOP <|@ <|@
      nr   -1  <|@ instruction NOP <|@ <|@
      nr   -1  <|@ instruction NOP <|@ <|@
      nr   -1  <|@ instruction NOP <|@ <|@
      nr   -1  <|@ instruction NOP <|@ <|@
      nr   -1  <|@ instruction NOP <|@ <|@
      nr   -1  <|@ instruction NOP <|@ <|@
      nr   -1  <|@ instruction v3|QWORD = MOVSXD value: v1|DWORD size: QWORD <|@ <|@
      nr   -1  <|@ instruction CMP (x: v3|QWORD, y: v0|QWORD) size: QWORD <|@ <|@
      nr   -1  <|@ instruction v4|QWORD = CMOVE (falseValue: v0|QWORD, ~trueValue: v3|QWORD) condition: > <|@ <|@
      nr   -1  <|@ instruction v5|QWORD = MOVSXD value: v2|DWORD size: QWORD <|@ <|@
      nr   -1  <|@ instruction CMP (x: v5|QWORD, y: v4|QWORD) size: QWORD <|@ <|@
      nr   -1  <|@ instruction v6|QWORD = CMOVE (falseValue: v5|QWORD, ~trueValue: v4|QWORD) condition: > <|@ <|@
      nr   -1  <|@ instruction v7|DWORD = MOV value: v6|QWORD size: DWORD <|@ <|@
      nr   -1  <|@ instruction rax|DWORD = MOVE input: v7|DWORD moveKind: DWORD <|@ <|@
      nr   -1  <|@ instruction RETURN (savedRbp: stack:16|QWORD, value: rax|DWORD) isStub: false requiresReservedStackAccessCheck: false thread: r15 scratchForSafepointOnReturn: rcx config: jdk.graal.compiler.hotspot.GraalHotSpotVMConfig@4817c460 <|@ <|@
    end_IR
  end_block
  begin_block
    name "B1"
    from_bci -1
    to_bci -1
    predecessors "B0" 
    successors 
    xhandlers
    flags 
    probability 2355382605114769408
    begin_IR
      LIR
      nr   -1  <|@ instruction [] = LABEL alignment: 0 numbPhis: 0 label: ? <|@ <|@
      nr   -1  <|@ instruction NOP <|@ <|@
      nr   -1  <|@ instruction NOP <|@ <|@
      nr   -1  <|@ instruction NOP <|@ <|@
      nr   -1  <|@ instruction NOP <|@ <|@
      nr   -1  <|@ instruction NOP <|@ <|@
      nr   -1  <|@ instruction NOP <|@ <|@
      nr   -1  <|@ instruction NOP <|@ <|@
      nr   -1  <|@ instruction MOV x: [r15|QWORD + 1156] y: -5907 size: DWORD <|@ <|@
      nr   -1  <|@ instruction MOV x: [r15|QWORD + 1168] y: 20 size: QWORD <|@ <|@
      nr   -1  <|@ st <@st|@java.lang.Math.clamp(Math.java:2214) [bci: 0]
locals: v0|QWORD - v1|DWORD v2|DWORD 
>@ <|@ instruction DEOPT info [bci:0] <|@ <|@
    end_IR
  end_block
end_cfg
begin_bytecodes
     0: iload_2       
     1: iload_3       
     2: if_icmple     36
     5: new           #177        // java.lang.IllegalArgumentException
     8: dup           
     9: new           #179        // java.lang.StringBuilder
    12: dup           
    13: invokespecial #35         // java.lang.StringBuilder.<init>:()void
    16: iload_2       
    17: invokevirtual #36         // java.lang.StringBuilder.append:(int)java.lang.StringBuilder
    20: ldc           #186        // " > "
    22: invokevirtual #37         // java.lang.StringBuilder.append:(java.lang.String)java.lang.StringBuilder
    25: iload_3       
    26: invokevirtual #36         // java.lang.StringBuilder.append:(int)java.lang.StringBuilder
    29: invokevirtual #38         // java.lang.StringBuilder.toString:()java.lang.String
    32: invokespecial #39         // java.lang.IllegalArgumentException.<init>:(java.lang.String)void
    35: athrow        
    36: iload_3       
    37: i2l           
    38: lload_0       
    39: iload_2       
    40: i2l           
    41: invokestatic  #40         // max:(long, long)long
    44: invokestatic  #41         // min:(long, long)long
    47: l2i           
    48: ireturn       
   <|@
end_bytecodes
begin_cfg
  name "After MarkBasePointers"
  begin_block
    name "B0"
    from_bci -1
    to_bci -1
    predecessors 
    successors "B1" "B2" 
    xhandlers
    flags 
    probability 4607182418800017408
    begin_IR
      LIR
      nr   -1  <|@ instruction [rsi|QWORD, rdx|DWORD, rcx|DWORD, rbp|QWORD] = LABEL alignment: 0 numbPhis: 0 label: ? <|@ <|@
      nr   -1  <|@ instruction NOP <|@ <|@
      nr   -1  <|@ instruction NOP <|@ <|@
      nr   -1  <|@ instruction NOP <|@ <|@
      nr   -1  <|@ instruction NOP <|@ <|@
      nr   -1  <|@ instruction NOP <|@ <|@
      nr   -1  <|@ instruction NOP <|@ <|@
      nr   -1  <|@ instruction NOP <|@ <|@
      nr   -1  <|@ instruction NOP <|@ <|@
      nr   -1  <|@ instruction NOP <|@ <|@
      nr   -1  <|@ instruction stack:16|QWORD = MOVE input: rbp|QWORD moveKind: QWORD <|@ <|@
      nr   -1  <|@ instruction [] = HOTSPOTLOCKSTACK frameMapBuilder: jdk.graal.compiler.hotspot.amd64.AMD64HotSpotFrameMapBuilder@8113c20 slotKind: QWORD <|@ <|@
      nr   -1  <|@ instruction v0|QWORD = MOVE input: rsi|QWORD moveKind: QWORD <|@ <|@
      nr   -1  <|@ instruction v1|DWORD = MOVE input: rdx|DWORD moveKind: DWORD <|@ <|@
      nr   -1  <|@ instruction v2|DWORD = MOVE input: rcx|DWORD moveKind: DWORD <|@ <|@
      nr   -1  <|@ instruction CMPBRANCH (x: v1|DWORD, y: v2|DWORD) trueDestinationProbability: 0.0 condition: > trueDestination: B0 -> B1 falseDestination: B0 -> B2 size: DWORD <|@ <|@
    end_IR
  end_block
  begin_block
    name "B2"
    from_bci -1
    to_bci -1
    predecessors "B0" 
    successors 
    xhandlers
    flags 
    probability 4607182418800017408
    begin_IR
      LIR
      nr   -1  <|@ instruction [] = LABEL alignment: 0 numbPhis: 0 label: ? <|@ <|@
      nr   -1  <|@ instruction NOP <|@ <|@
      nr   -1  <|@ instruction NOP <|@ <|@
      nr   -1  <|@ instruction NOP <|@ <|@
      nr   -1  <|@ instruction NOP <|@ <|@
      nr   -1  <|@ instruction NOP <|@ <|@
      nr   -1  <|@ instruction NOP <|@ <|@
      nr   -1  <|@ instruction NOP <|@ <|@
      nr   -1  <|@ instruction NOP <|@ <|@
      nr   -1  <|@ instruction NOP <|@ <|@
      nr   -1  <|@ instruction NOP <|@ <|@
      nr   -1  <|@ instruction NOP <|@ <|@
      nr   -1  <|@ instruction NOP <|@ <|@
      nr   -1  <|@ instruction NOP <|@ <|@
      nr   -1  <|@ instruction NOP <|@ <|@
      nr   -1  <|@ instruction NOP <|@ <|@
      nr   -1  <|@ instruction v3|QWORD = MOVSXD value: v1|DWORD size: QWORD <|@ <|@
      nr   -1  <|@ instruction CMP (x: v3|QWORD, y: v0|QWORD) size: QWORD <|@ <|@
      nr   -1  <|@ instruction v4|QWORD = CMOVE (falseValue: v0|QWORD, ~trueValue: v3|QWORD) condition: > <|@ <|@
      nr   -1  <|@ instruction v5|QWORD = MOVSXD value: v2|DWORD size: QWORD <|@ <|@
      nr   -1  <|@ instruction CMP (x: v5|QWORD, y: v4|QWORD) size: QWORD <|@ <|@
      nr   -1  <|@ instruction v6|QWORD = CMOVE (falseValue: v5|QWORD, ~trueValue: v4|QWORD) condition: > <|@ <|@
      nr   -1  <|@ instruction v7|DWORD = MOV value: v6|QWORD size: DWORD <|@ <|@
      nr   -1  <|@ instruction rax|DWORD = MOVE input: v7|DWORD moveKind: DWORD <|@ <|@
      nr   -1  <|@ instruction RETURN (savedRbp: stack:16|QWORD, value: rax|DWORD) isStub: false requiresReservedStackAccessCheck: false thread: r15 scratchForSafepointOnReturn: rcx config: jdk.graal.compiler.hotspot.GraalHotSpotVMConfig@4817c460 <|@ <|@
    end_IR
  end_block
  begin_block
    name "B1"
    from_bci -1
    to_bci -1
    predecessors "B0" 
    successors 
    xhandlers
    flags 
    probability 2355382605114769408
    begin_IR
      LIR
      nr   -1  <|@ instruction [] = LABEL alignment: 0 numbPhis: 0 label: ? <|@ <|@
      nr   -1  <|@ instruction NOP <|@ <|@
      nr   -1  <|@ instruction NOP <|@ <|@
      nr   -1  <|@ instruction NOP <|@ <|@
      nr   -1  <|@ instruction NOP <|@ <|@
      nr   -1  <|@ instruction NOP <|@ <|@
      nr   -1  <|@ instruction NOP <|@ <|@
      nr   -1  <|@ instruction NOP <|@ <|@
      nr   -1  <|@ instruction MOV x: [r15|QWORD + 1156] y: -5907 size: DWORD <|@ <|@
      nr   -1  <|@ instruction MOV x: [r15|QWORD + 1168] y: 20 size: QWORD <|@ <|@
      nr   -1  <|@ st <@st|@live-base-pointers: []
java.lang.Math.clamp(Math.java:2214) [bci: 0]
locals: v0|QWORD - v1|DWORD v2|DWORD 
>@ <|@ instruction DEOPT info [bci:0] <|@ <|@
    end_IR
  end_block
end_cfg
begin_bytecodes
     0: iload_2       
     1: iload_3       
     2: if_icmple     36
     5: new           #177        // java.lang.IllegalArgumentException
     8: dup           
     9: new           #179        // java.lang.StringBuilder
    12: dup           
    13: invokespecial #35         // java.lang.StringBuilder.<init>:()void
    16: iload_2       
    17: invokevirtual #36         // java.lang.StringBuilder.append:(int)java.lang.StringBuilder
    20: ldc           #186        // " > "
    22: invokevirtual #37         // java.lang.StringBuilder.append:(java.lang.String)java.lang.StringBuilder
    25: iload_3       
    26: invokevirtual #36         // java.lang.StringBuilder.append:(int)java.lang.StringBuilder
    29: invokevirtual #38         // java.lang.StringBuilder.toString:()java.lang.String
    32: invokespecial #39         // java.lang.IllegalArgumentException.<init>:(java.lang.String)void
    35: athrow        
    36: iload_3       
    37: i2l           
    38: lload_0       
    39: iload_2       
    40: i2l           
    41: invokestatic  #40         // max:(long, long)long
    44: invokestatic  #41         // min:(long, long)long
    47: l2i           
    48: ireturn       
   <|@
end_bytecodes
begin_cfg
  name "Before register allocation"
  begin_block
    name "B0"
    from_bci -1
    to_bci -1
    predecessors 
    successors "B1" "B2" 
    xhandlers
    flags 
    probability 4607182418800017408
    begin_IR
      LIR
      nr    0  <|@ instruction [rsi|QWORD, rdx|DWORD, rcx|DWORD, rbp|QWORD] = LABEL alignment: 0 numbPhis: 0 label: ? <|@ <|@
      nr    2  <|@ instruction NOP <|@ <|@
      nr    4  <|@ instruction NOP <|@ <|@
      nr    6  <|@ instruction NOP <|@ <|@
      nr    8  <|@ instruction NOP <|@ <|@
      nr   10  <|@ instruction NOP <|@ <|@
      nr   12  <|@ instruction NOP <|@ <|@
      nr   14  <|@ instruction NOP <|@ <|@
      nr   16  <|@ instruction NOP <|@ <|@
      nr   18  <|@ instruction NOP <|@ <|@
      nr   20  <|@ instruction stack:16|QWORD = MOVE input: rbp|QWORD moveKind: QWORD <|@ <|@
      nr   22  <|@ instruction [] = HOTSPOTLOCKSTACK frameMapBuilder: jdk.graal.compiler.hotspot.amd64.AMD64HotSpotFrameMapBuilder@8113c20 slotKind: QWORD <|@ <|@
      nr   24  <|@ instruction v0|QWORD = MOVE input: rsi|QWORD moveKind: QWORD <|@ <|@
      nr   26  <|@ instruction v1|DWORD = MOVE input: rdx|DWORD moveKind: DWORD <|@ <|@
      nr   28  <|@ instruction v2|DWORD = MOVE input: rcx|DWORD moveKind: DWORD <|@ <|@
      nr   30  <|@ instruction CMPBRANCH (x: v1|DWORD, y: v2|DWORD) trueDestinationProbability: 0.0 condition: > trueDestination: B0 -> B1 falseDestination: B0 -> B2 size: DWORD <|@ <|@
    end_IR
  end_block
  begin_block
    name "B2"
    from_bci -1
    to_bci -1
    predecessors "B0" 
    successors 
    xhandlers
    flags 
    probability 4607182418800017408
    begin_IR
      LIR
      nr   32  <|@ instruction [] = LABEL alignment: 0 numbPhis: 0 label: ? <|@ <|@
      nr   34  <|@ instruction NOP <|@ <|@
      nr   36  <|@ instruction NOP <|@ <|@
      nr   38  <|@ instruction NOP <|@ <|@
      nr   40  <|@ instruction NOP <|@ <|@
      nr   42  <|@ instruction NOP <|@ <|@
      nr   44  <|@ instruction NOP <|@ <|@
      nr   46  <|@ instruction NOP <|@ <|@
      nr   48  <|@ instruction NOP <|@ <|@
      nr   50  <|@ instruction NOP <|@ <|@
      nr   52  <|@ instruction NOP <|@ <|@
      nr   54  <|@ instruction NOP <|@ <|@
      nr   56  <|@ instruction NOP <|@ <|@
      nr   58  <|@ instruction NOP <|@ <|@
      nr   60  <|@ instruction NOP <|@ <|@
      nr   62  <|@ instruction NOP <|@ <|@
      nr   64  <|@ instruction v3|QWORD = MOVSXD value: v1|DWORD size: QWORD <|@ <|@
      nr   66  <|@ instruction CMP (x: v3|QWORD, y: v0|QWORD) size: QWORD <|@ <|@
      nr   68  <|@ instruction v4|QWORD = CMOVE (falseValue: v0|QWORD, ~trueValue: v3|QWORD) condition: > <|@ <|@
      nr   70  <|@ instruction v5|QWORD = MOVSXD value: v2|DWORD size: QWORD <|@ <|@
      nr   72  <|@ instruction CMP (x: v5|QWORD, y: v4|QWORD) size: QWORD <|@ <|@
      nr   74  <|@ instruction v6|QWORD = CMOVE (falseValue: v5|QWORD, ~trueValue: v4|QWORD) condition: > <|@ <|@
      nr   76  <|@ instruction v7|DWORD = MOV value: v6|QWORD size: DWORD <|@ <|@
      nr   78  <|@ instruction rax|DWORD = MOVE input: v7|DWORD moveKind: DWORD <|@ <|@
      nr   80  <|@ instruction RETURN (savedRbp: stack:16|QWORD, value: rax|DWORD) isStub: false requiresReservedStackAccessCheck: false thread: r15 scratchForSafepointOnReturn: rcx config: jdk.graal.compiler.hotspot.GraalHotSpotVMConfig@4817c460 <|@ <|@
    end_IR
  end_block
  begin_block
    name "B1"
    from_bci -1
    to_bci -1
    predecessors "B0" 
    successors 
    xhandlers
    flags 
    probability 2355382605114769408
    begin_IR
      LIR
      nr   82  <|@ instruction [] = LABEL alignment: 0 numbPhis: 0 label: ? <|@ <|@
      nr   84  <|@ instruction NOP <|@ <|@
      nr   86  <|@ instruction NOP <|@ <|@
      nr   88  <|@ instruction NOP <|@ <|@
      nr   90  <|@ instruction NOP <|@ <|@
      nr   92  <|@ instruction NOP <|@ <|@
      nr   94  <|@ instruction NOP <|@ <|@
      nr   96  <|@ instruction NOP <|@ <|@
      nr   98  <|@ instruction MOV x: [r15|QWORD + 1156] y: -5907 size: DWORD <|@ <|@
      nr  100  <|@ instruction MOV x: [r15|QWORD + 1168] y: 20 size: QWORD <|@ <|@
      nr  102  <|@ st <@st|@live-base-pointers: []
java.lang.Math.clamp(Math.java:2214) [bci: 0]
locals: v0|QWORD - v1|DWORD v2|DWORD 
>@ <|@ instruction DEOPT info [bci:0] <|@ <|@
    end_IR
  end_block
end_cfg
begin_bytecodes
     0: iload_2       
     1: iload_3       
     2: if_icmple     36
     5: new           #177        // java.lang.IllegalArgumentException
     8: dup           
     9: new           #179        // java.lang.StringBuilder
    12: dup           
    13: invokespecial #35         // java.lang.StringBuilder.<init>:()void
    16: iload_2       
    17: invokevirtual #36         // java.lang.StringBuilder.append:(int)java.lang.StringBuilder
    20: ldc           #186        // " > "
    22: invokevirtual #37         // java.lang.StringBuilder.append:(java.lang.String)java.lang.StringBuilder
    25: iload_3       
    26: invokevirtual #36         // java.lang.StringBuilder.append:(int)java.lang.StringBuilder
    29: invokevirtual #38         // java.lang.StringBuilder.toString:()java.lang.String
    32: invokespecial #39         // java.lang.IllegalArgumentException.<init>:(java.lang.String)void
    35: athrow        
    36: iload_3       
    37: i2l           
    38: lload_0       
    39: iload_2       
    40: i2l           
    41: invokestatic  #40         // max:(long, long)long
    44: invokestatic  #41         // min:(long, long)long
    47: l2i           
    48: ireturn       
   <|@
end_bytecodes
begin_cfg
  name "After SSALinearScanLifetimeAnalysis"
  begin_block
    name "B0"
    from_bci -1
    to_bci -1
    predecessors 
    successors "B1" "B2" 
    xhandlers
    flags 
    probability 4607182418800017408
    begin_IR
      LIR
      nr    0  <|@ instruction [rsi|QWORD, rdx|DWORD, rcx|DWORD, rbp|QWORD] = LABEL alignment: 0 numbPhis: 0 label: ? <|@ <|@
      nr    2  <|@ instruction NOP <|@ <|@
      nr    4  <|@ instruction NOP <|@ <|@
      nr    6  <|@ instruction NOP <|@ <|@
      nr    8  <|@ instruction NOP <|@ <|@
      nr   10  <|@ instruction NOP <|@ <|@
      nr   12  <|@ instruction NOP <|@ <|@
      nr   14  <|@ instruction NOP <|@ <|@
      nr   16  <|@ instruction NOP <|@ <|@
      nr   18  <|@ instruction NOP <|@ <|@
      nr   20  <|@ instruction stack:16|QWORD = MOVE input: rbp|QWORD moveKind: QWORD <|@ <|@
      nr   22  <|@ instruction [] = HOTSPOTLOCKSTACK frameMapBuilder: jdk.graal.compiler.hotspot.amd64.AMD64HotSpotFrameMapBuilder@8113c20 slotKind: QWORD <|@ <|@
      nr   24  <|@ instruction v0|QWORD = MOVE input: rsi|QWORD moveKind: QWORD <|@ <|@
      nr   26  <|@ instruction v1|DWORD = MOVE input: rdx|DWORD moveKind: DWORD <|@ <|@
      nr   28  <|@ instruction v2|DWORD = MOVE input: rcx|DWORD moveKind: DWORD <|@ <|@
      nr   30  <|@ instruction CMPBRANCH (x: v1|DWORD, y: v2|DWORD) trueDestinationProbability: 0.0 condition: > trueDestination: B0 -> B1 falseDestination: B0 -> B2 size: DWORD <|@ <|@
    end_IR
  end_block
  begin_block
    name "B2"
    from_bci -1
    to_bci -1
    predecessors "B0" 
    successors 
    xhandlers
    flags 
    probability 4607182418800017408
    begin_IR
      LIR
      nr   32  <|@ instruction [] = LABEL alignment: 0 numbPhis: 0 label: ? <|@ <|@
      nr   34  <|@ instruction NOP <|@ <|@
      nr   36  <|@ instruction NOP <|@ <|@
      nr   38  <|@ instruction NOP <|@ <|@
      nr   40  <|@ instruction NOP <|@ <|@
      nr   42  <|@ instruction NOP <|@ <|@
      nr   44  <|@ instruction NOP <|@ <|@
      nr   46  <|@ instruction NOP <|@ <|@
      nr   48  <|@ instruction NOP <|@ <|@
      nr   50  <|@ instruction NOP <|@ <|@
      nr   52  <|@ instruction NOP <|@ <|@
      nr   54  <|@ instruction NOP <|@ <|@
      nr   56  <|@ instruction NOP <|@ <|@
      nr   58  <|@ instruction NOP <|@ <|@
      nr   60  <|@ instruction NOP <|@ <|@
      nr   62  <|@ instruction NOP <|@ <|@
      nr   64  <|@ instruction v3|QWORD = MOVSXD value: v1|DWORD size: QWORD <|@ <|@
      nr   66  <|@ instruction CMP (x: v3|QWORD, y: v0|QWORD) size: QWORD <|@ <|@
      nr   68  <|@ instruction v4|QWORD = CMOVE (falseValue: v0|QWORD, ~trueValue: v3|QWORD) condition: > <|@ <|@
      nr   70  <|@ instruction v5|QWORD = MOVSXD value: v2|DWORD size: QWORD <|@ <|@
      nr   72  <|@ instruction CMP (x: v5|QWORD, y: v4|QWORD) size: QWORD <|@ <|@
      nr   74  <|@ instruction v6|QWORD = CMOVE (falseValue: v5|QWORD, ~trueValue: v4|QWORD) condition: > <|@ <|@
      nr   76  <|@ instruction v7|DWORD = MOV value: v6|QWORD size: DWORD <|@ <|@
      nr   78  <|@ instruction rax|DWORD = MOVE input: v7|DWORD moveKind: DWORD <|@ <|@
      nr   80  <|@ instruction RETURN (savedRbp: stack:16|QWORD, value: rax|DWORD) isStub: false requiresReservedStackAccessCheck: false thread: r15 scratchForSafepointOnReturn: rcx config: jdk.graal.compiler.hotspot.GraalHotSpotVMConfig@4817c460 <|@ <|@
    end_IR
  end_block
  begin_block
    name "B1"
    from_bci -1
    to_bci -1
    predecessors "B0" 
    successors 
    xhandlers
    flags 
    probability 2355382605114769408
    begin_IR
      LIR
      nr   82  <|@ instruction [] = LABEL alignment: 0 numbPhis: 0 label: ? <|@ <|@
      nr   84  <|@ instruction NOP <|@ <|@
      nr   86  <|@ instruction NOP <|@ <|@
      nr   88  <|@ instruction NOP <|@ <|@
      nr   90  <|@ instruction NOP <|@ <|@
      nr   92  <|@ instruction NOP <|@ <|@
      nr   94  <|@ instruction NOP <|@ <|@
      nr   96  <|@ instruction NOP <|@ <|@
      nr   98  <|@ instruction MOV x: [r15|QWORD + 1156] y: -5907 size: DWORD <|@ <|@
      nr  100  <|@ instruction MOV x: [r15|QWORD + 1168] y: 20 size: QWORD <|@ <|@
      nr  102  <|@ st <@st|@live-base-pointers: []
java.lang.Math.clamp(Math.java:2214) [bci: 0]
locals: v0|QWORD - v1|DWORD v2|DWORD 
>@ <|@ instruction DEOPT info [bci:0] <|@ <|@
    end_IR
  end_block
end_cfg
begin_bytecodes
     0: iload_2       
     1: iload_3       
     2: if_icmple     36
     5: new           #177        // java.lang.IllegalArgumentException
     8: dup           
     9: new           #179        // java.lang.StringBuilder
    12: dup           
    13: invokespecial #35         // java.lang.StringBuilder.<init>:()void
    16: iload_2       
    17: invokevirtual #36         // java.lang.StringBuilder.append:(int)java.lang.StringBuilder
    20: ldc           #186        // " > "
    22: invokevirtual #37         // java.lang.StringBuilder.append:(java.lang.String)java.lang.StringBuilder
    25: iload_3       
    26: invokevirtual #36         // java.lang.StringBuilder.append:(int)java.lang.StringBuilder
    29: invokevirtual #38         // java.lang.StringBuilder.toString:()java.lang.String
    32: invokespecial #39         // java.lang.IllegalArgumentException.<init>:(java.lang.String)void
    35: athrow        
    36: iload_3       
    37: i2l           
    38: lload_0       
    39: iload_2       
    40: i2l           
    41: invokestatic  #40         // max:(long, long)long
    44: invokestatic  #41         // min:(long, long)long
    47: l2i           
    48: ireturn       
   <|@
end_bytecodes
begin_intervals
  name "Before register allocation"
  rax|d fixed "[rax|d]" rax|d v7|d [0, 1[[78, 80[ "NoSpillStore"
  rcx|d fixed "[rcx|d]" rcx|d -1 [0, 28[ "NoSpillStore"
  rdx|d fixed "[rdx|d]" rdx|d -1 [0, 26[ "NoSpillStore"
  rbp|q fixed "[rbp|q]" rbp|q -1 [0, 20[ "NoSpillStore"
  rsi|q fixed "[rsi|q]" rsi|q -1 [0, 24[ "NoSpillStore"
  v0|q QWORD "[v0|q]" v0|q rsi|q [24, 68[[82, 103[24 MustHaveRegister 66 ShouldHaveRegister 68 ShouldHaveRegister  "NoSpillStore"
  v1|d DWORD "[v1|d]" v1|d rdx|d [26, 64[[82, 103[26 MustHaveRegister 30 MustHaveRegister 64 ShouldHaveRegister  "NoSpillStore"
  v2|d DWORD "[v2|d]" v2|d rcx|d [28, 70[[82, 103[28 MustHaveRegister 30 ShouldHaveRegister 70 ShouldHaveRegister  "NoSpillStore"
  v3|q QWORD "[v3|q]" v3|q -1 [64, 69[64 MustHaveRegister 66 MustHaveRegister 68 MustHaveRegister  "NoSpillStore"
  v4|q QWORD "[v4|q]" v4|q v0|q [68, 75[68 MustHaveRegister 72 ShouldHaveRegister 74 MustHaveRegister  "NoSpillStore"
  v5|q QWORD "[v5|q]" v5|q -1 [70, 74[70 MustHaveRegister 72 MustHaveRegister 74 ShouldHaveRegister  "NoSpillStore"
  v6|q QWORD "[v6|q]" v6|q v5|q [74, 76[74 MustHaveRegister 76 ShouldHaveRegister  "NoSpillStore"
  v7|d DWORD "[v7|d]" v7|d -1 [76, 78[76 MustHaveRegister 78 ShouldHaveRegister  "NoSpillStore"
end_intervals
begin_intervals
  name "After register allocation"
  rax|d fixed "[rax|d]" rax|d v7|d [0, 1[[78, 80[ "NoSpillStore"
  rcx|d fixed "[rcx|d]" rcx|d -1 [0, 28[ "NoSpillStore"
  rdx|d fixed "[rdx|d]" rdx|d -1 [0, 26[ "NoSpillStore"
  rbp|q fixed "[rbp|q]" rbp|q -1 [0, 20[ "NoSpillStore"
  rsi|q fixed "[rsi|q]" rsi|q -1 [0, 24[ "NoSpillStore"
  v0|q QWORD "[rsi|q]" v0|q rsi|q [24, 68[[82, 103[24 MustHaveRegister 66 ShouldHaveRegister 68 ShouldHaveRegister  "NoSpillStore"
  v1|d DWORD "[rdx|d]" v1|d rdx|d [26, 64[[82, 103[26 MustHaveRegister 30 MustHaveRegister 64 ShouldHaveRegister  "NoSpillStore"
  v2|d DWORD "[rcx|d]" v2|d rcx|d [28, 70[[82, 103[28 MustHaveRegister 30 ShouldHaveRegister 70 ShouldHaveRegister  "NoSpillStore"
  v3|q QWORD "[rax|q]" v3|q -1 [64, 69[64 MustHaveRegister 66 MustHaveRegister 68 MustHaveRegister  "NoSpillStore"
  v4|q QWORD "[rsi|q]" v4|q v0|q [68, 75[68 MustHaveRegister 72 ShouldHaveRegister 74 MustHaveRegister  "NoSpillStore"
  v5|q QWORD "[rax|q]" v5|q -1 [70, 74[70 MustHaveRegister 72 MustHaveRegister 74 ShouldHaveRegister  "NoSpillStore"
  v6|q QWORD "[rax|q]" v6|q v5|q [74, 76[74 MustHaveRegister 76 ShouldHaveRegister  "NoSpillStore"
  v7|d DWORD "[rax|d]" v7|d -1 [76, 78[76 MustHaveRegister 78 ShouldHaveRegister  "NoSpillStore"
end_intervals
begin_cfg
  name "After LinearScanRegisterAllocation"
  begin_block
    name "B0"
    from_bci -1
    to_bci -1
    predecessors 
    successors "B1" "B2" 
    xhandlers
    flags 
    probability 4607182418800017408
    begin_IR
      LIR
      nr    0  <|@ instruction [rsi|QWORD, rdx|DWORD, rcx|DWORD, rbp|QWORD] = LABEL alignment: 0 numbPhis: 0 label: ? <|@ <|@
      nr    2  <|@ instruction NOP <|@ <|@
      nr    4  <|@ instruction NOP <|@ <|@
      nr    6  <|@ instruction NOP <|@ <|@
      nr    8  <|@ instruction NOP <|@ <|@
      nr   10  <|@ instruction NOP <|@ <|@
      nr   12  <|@ instruction NOP <|@ <|@
      nr   14  <|@ instruction NOP <|@ <|@
      nr   16  <|@ instruction NOP <|@ <|@
      nr   18  <|@ instruction NOP <|@ <|@
      nr   20  <|@ instruction stack:16|QWORD = MOVE input: rbp|QWORD moveKind: QWORD <|@ <|@
      nr   22  <|@ instruction [] = HOTSPOTLOCKSTACK frameMapBuilder: jdk.graal.compiler.hotspot.amd64.AMD64HotSpotFrameMapBuilder@8113c20 slotKind: QWORD <|@ <|@
      nr   24  <|@ instruction v0|QWORD = MOVE input: rsi|QWORD moveKind: QWORD <|@ <|@
      nr   26  <|@ instruction v1|DWORD = MOVE input: rdx|DWORD moveKind: DWORD <|@ <|@
      nr   28  <|@ instruction v2|DWORD = MOVE input: rcx|DWORD moveKind: DWORD <|@ <|@
      nr   30  <|@ instruction CMPBRANCH (x: v1|DWORD, y: v2|DWORD) trueDestinationProbability: 0.0 condition: > trueDestination: B0 -> B1 falseDestination: B0 -> B2 size: DWORD <|@ <|@
    end_IR
  end_block
  begin_block
    name "B2"
    from_bci -1
    to_bci -1
    predecessors "B0" 
    successors 
    xhandlers
    flags 
    probability 4607182418800017408
    begin_IR
      LIR
      nr   32  <|@ instruction [] = LABEL alignment: 0 numbPhis: 0 label: ? <|@ <|@
      nr   34  <|@ instruction NOP <|@ <|@
      nr   36  <|@ instruction NOP <|@ <|@
      nr   38  <|@ instruction NOP <|@ <|@
      nr   40  <|@ instruction NOP <|@ <|@
      nr   42  <|@ instruction NOP <|@ <|@
      nr   44  <|@ instruction NOP <|@ <|@
      nr   46  <|@ instruction NOP <|@ <|@
      nr   48  <|@ instruction NOP <|@ <|@
      nr   50  <|@ instruction NOP <|@ <|@
      nr   52  <|@ instruction NOP <|@ <|@
      nr   54  <|@ instruction NOP <|@ <|@
      nr   56  <|@ instruction NOP <|@ <|@
      nr   58  <|@ instruction NOP <|@ <|@
      nr   60  <|@ instruction NOP <|@ <|@
      nr   62  <|@ instruction NOP <|@ <|@
      nr   64  <|@ instruction v3|QWORD = MOVSXD value: v1|DWORD size: QWORD <|@ <|@
      nr   66  <|@ instruction CMP (x: v3|QWORD, y: v0|QWORD) size: QWORD <|@ <|@
      nr   68  <|@ instruction v4|QWORD = CMOVE (falseValue: v0|QWORD, ~trueValue: v3|QWORD) condition: > <|@ <|@
      nr   70  <|@ instruction v5|QWORD = MOVSXD value: v2|DWORD size: QWORD <|@ <|@
      nr   72  <|@ instruction CMP (x: v5|QWORD, y: v4|QWORD) size: QWORD <|@ <|@
      nr   74  <|@ instruction v6|QWORD = CMOVE (falseValue: v5|QWORD, ~trueValue: v4|QWORD) condition: > <|@ <|@
      nr   76  <|@ instruction v7|DWORD = MOV value: v6|QWORD size: DWORD <|@ <|@
      nr   78  <|@ instruction rax|DWORD = MOVE input: v7|DWORD moveKind: DWORD <|@ <|@
      nr   80  <|@ instruction RETURN (savedRbp: stack:16|QWORD, value: rax|DWORD) isStub: false requiresReservedStackAccessCheck: false thread: r15 scratchForSafepointOnReturn: rcx config: jdk.graal.compiler.hotspot.GraalHotSpotVMConfig@4817c460 <|@ <|@
    end_IR
  end_block
  begin_block
    name "B1"
    from_bci -1
    to_bci -1
    predecessors "B0" 
    successors 
    xhandlers
    flags 
    probability 2355382605114769408
    begin_IR
      LIR
      nr   82  <|@ instruction [] = LABEL alignment: 0 numbPhis: 0 label: ? <|@ <|@
      nr   84  <|@ instruction NOP <|@ <|@
      nr   86  <|@ instruction NOP <|@ <|@
      nr   88  <|@ instruction NOP <|@ <|@
      nr   90  <|@ instruction NOP <|@ <|@
      nr   92  <|@ instruction NOP <|@ <|@
      nr   94  <|@ instruction NOP <|@ <|@
      nr   96  <|@ instruction NOP <|@ <|@
      nr   98  <|@ instruction MOV x: [r15|QWORD + 1156] y: -5907 size: DWORD <|@ <|@
      nr  100  <|@ instruction MOV x: [r15|QWORD + 1168] y: 20 size: QWORD <|@ <|@
      nr  102  <|@ st <@st|@live-base-pointers: []
java.lang.Math.clamp(Math.java:2214) [bci: 0]
locals: v0|QWORD - v1|DWORD v2|DWORD 
>@ <|@ instruction DEOPT info [bci:0] <|@ <|@
    end_IR
  end_block
end_cfg
begin_bytecodes
     0: iload_2       
     1: iload_3       
     2: if_icmple     36
     5: new           #177        // java.lang.IllegalArgumentException
     8: dup           
     9: new           #179        // java.lang.StringBuilder
    12: dup           
    13: invokespecial #35         // java.lang.StringBuilder.<init>:()void
    16: iload_2       
    17: invokevirtual #36         // java.lang.StringBuilder.append:(int)java.lang.StringBuilder
    20: ldc           #186        // " > "
    22: invokevirtual #37         // java.lang.StringBuilder.append:(java.lang.String)java.lang.StringBuilder
    25: iload_3       
    26: invokevirtual #36         // java.lang.StringBuilder.append:(int)java.lang.StringBuilder
    29: invokevirtual #38         // java.lang.StringBuilder.toString:()java.lang.String
    32: invokespecial #39         // java.lang.IllegalArgumentException.<init>:(java.lang.String)void
    35: athrow        
    36: iload_3       
    37: i2l           
    38: lload_0       
    39: iload_2       
    40: i2l           
    41: invokestatic  #40         // max:(long, long)long
    44: invokestatic  #41         // min:(long, long)long
    47: l2i           
    48: ireturn       
   <|@
end_bytecodes
begin_intervals
  name "After optimize spill position"
  rax|d fixed "[rax|d]" rax|d v7|d [0, 1[[78, 80[ "NoSpillStore"
  rcx|d fixed "[rcx|d]" rcx|d -1 [0, 28[ "NoSpillStore"
  rdx|d fixed "[rdx|d]" rdx|d -1 [0, 26[ "NoSpillStore"
  rbp|q fixed "[rbp|q]" rbp|q -1 [0, 20[ "NoSpillStore"
  rsi|q fixed "[rsi|q]" rsi|q -1 [0, 24[ "NoSpillStore"
  v0|q QWORD "[rsi|q]" v0|q rsi|q [24, 68[[82, 103[24 MustHaveRegister 66 ShouldHaveRegister 68 ShouldHaveRegister  "NoSpillStore"
  v1|d DWORD "[rdx|d]" v1|d rdx|d [26, 64[[82, 103[26 MustHaveRegister 30 MustHaveRegister 64 ShouldHaveRegister  "NoSpillStore"
  v2|d DWORD "[rcx|d]" v2|d rcx|d [28, 70[[82, 103[28 MustHaveRegister 30 ShouldHaveRegister 70 ShouldHaveRegister  "NoSpillStore"
  v3|q QWORD "[rax|q]" v3|q -1 [64, 69[64 MustHaveRegister 66 MustHaveRegister 68 MustHaveRegister  "NoSpillStore"
  v4|q QWORD "[rsi|q]" v4|q v0|q [68, 75[68 MustHaveRegister 72 ShouldHaveRegister 74 MustHaveRegister  "NoSpillStore"
  v5|q QWORD "[rax|q]" v5|q -1 [70, 74[70 MustHaveRegister 72 MustHaveRegister 74 ShouldHaveRegister  "NoSpillStore"
  v6|q QWORD "[rax|q]" v6|q v5|q [74, 76[74 MustHaveRegister 76 ShouldHaveRegister  "NoSpillStore"
  v7|d DWORD "[rax|d]" v7|d -1 [76, 78[76 MustHaveRegister 78 ShouldHaveRegister  "NoSpillStore"
end_intervals
begin_cfg
  name "After LinearScanOptimizeSpillPosition"
  begin_block
    name "B0"
    from_bci -1
    to_bci -1
    predecessors 
    successors "B1" "B2" 
    xhandlers
    flags 
    probability 4607182418800017408
    begin_IR
      LIR
      nr    0  <|@ instruction [rsi|QWORD, rdx|DWORD, rcx|DWORD, rbp|QWORD] = LABEL alignment: 0 numbPhis: 0 label: ? <|@ <|@
      nr    2  <|@ instruction NOP <|@ <|@
      nr    4  <|@ instruction NOP <|@ <|@
      nr    6  <|@ instruction NOP <|@ <|@
      nr    8  <|@ instruction NOP <|@ <|@
      nr   10  <|@ instruction NOP <|@ <|@
      nr   12  <|@ instruction NOP <|@ <|@
      nr   14  <|@ instruction NOP <|@ <|@
      nr   16  <|@ instruction NOP <|@ <|@
      nr   18  <|@ instruction NOP <|@ <|@
      nr   20  <|@ instruction stack:16|QWORD = MOVE input: rbp|QWORD moveKind: QWORD <|@ <|@
      nr   22  <|@ instruction [] = HOTSPOTLOCKSTACK frameMapBuilder: jdk.graal.compiler.hotspot.amd64.AMD64HotSpotFrameMapBuilder@8113c20 slotKind: QWORD <|@ <|@
      nr   24  <|@ instruction v0|QWORD = MOVE input: rsi|QWORD moveKind: QWORD <|@ <|@
      nr   26  <|@ instruction v1|DWORD = MOVE input: rdx|DWORD moveKind: DWORD <|@ <|@
      nr   28  <|@ instruction v2|DWORD = MOVE input: rcx|DWORD moveKind: DWORD <|@ <|@
      nr   30  <|@ instruction CMPBRANCH (x: v1|DWORD, y: v2|DWORD) trueDestinationProbability: 0.0 condition: > trueDestination: B0 -> B1 falseDestination: B0 -> B2 size: DWORD <|@ <|@
    end_IR
  end_block
  begin_block
    name "B2"
    from_bci -1
    to_bci -1
    predecessors "B0" 
    successors 
    xhandlers
    flags 
    probability 4607182418800017408
    begin_IR
      LIR
      nr   32  <|@ instruction [] = LABEL alignment: 0 numbPhis: 0 label: ? <|@ <|@
      nr   34  <|@ instruction NOP <|@ <|@
      nr   36  <|@ instruction NOP <|@ <|@
      nr   38  <|@ instruction NOP <|@ <|@
      nr   40  <|@ instruction NOP <|@ <|@
      nr   42  <|@ instruction NOP <|@ <|@
      nr   44  <|@ instruction NOP <|@ <|@
      nr   46  <|@ instruction NOP <|@ <|@
      nr   48  <|@ instruction NOP <|@ <|@
      nr   50  <|@ instruction NOP <|@ <|@
      nr   52  <|@ instruction NOP <|@ <|@
      nr   54  <|@ instruction NOP <|@ <|@
      nr   56  <|@ instruction NOP <|@ <|@
      nr   58  <|@ instruction NOP <|@ <|@
      nr   60  <|@ instruction NOP <|@ <|@
      nr   62  <|@ instruction NOP <|@ <|@
      nr   64  <|@ instruction v3|QWORD = MOVSXD value: v1|DWORD size: QWORD <|@ <|@
      nr   66  <|@ instruction CMP (x: v3|QWORD, y: v0|QWORD) size: QWORD <|@ <|@
      nr   68  <|@ instruction v4|QWORD = CMOVE (falseValue: v0|QWORD, ~trueValue: v3|QWORD) condition: > <|@ <|@
      nr   70  <|@ instruction v5|QWORD = MOVSXD value: v2|DWORD size: QWORD <|@ <|@
      nr   72  <|@ instruction CMP (x: v5|QWORD, y: v4|QWORD) size: QWORD <|@ <|@
      nr   74  <|@ instruction v6|QWORD = CMOVE (falseValue: v5|QWORD, ~trueValue: v4|QWORD) condition: > <|@ <|@
      nr   76  <|@ instruction v7|DWORD = MOV value: v6|QWORD size: DWORD <|@ <|@
      nr   78  <|@ instruction rax|DWORD = MOVE input: v7|DWORD moveKind: DWORD <|@ <|@
      nr   80  <|@ instruction RETURN (savedRbp: stack:16|QWORD, value: rax|DWORD) isStub: false requiresReservedStackAccessCheck: false thread: r15 scratchForSafepointOnReturn: rcx config: jdk.graal.compiler.hotspot.GraalHotSpotVMConfig@4817c460 <|@ <|@
    end_IR
  end_block
  begin_block
    name "B1"
    from_bci -1
    to_bci -1
    predecessors "B0" 
    successors 
    xhandlers
    flags 
    probability 2355382605114769408
    begin_IR
      LIR
      nr   82  <|@ instruction [] = LABEL alignment: 0 numbPhis: 0 label: ? <|@ <|@
      nr   84  <|@ instruction NOP <|@ <|@
      nr   86  <|@ instruction NOP <|@ <|@
      nr   88  <|@ instruction NOP <|@ <|@
      nr   90  <|@ instruction NOP <|@ <|@
      nr   92  <|@ instruction NOP <|@ <|@
      nr   94  <|@ instruction NOP <|@ <|@
      nr   96  <|@ instruction NOP <|@ <|@
      nr   98  <|@ instruction MOV x: [r15|QWORD + 1156] y: -5907 size: DWORD <|@ <|@
      nr  100  <|@ instruction MOV x: [r15|QWORD + 1168] y: 20 size: QWORD <|@ <|@
      nr  102  <|@ st <@st|@live-base-pointers: []
java.lang.Math.clamp(Math.java:2214) [bci: 0]
locals: v0|QWORD - v1|DWORD v2|DWORD 
>@ <|@ instruction DEOPT info [bci:0] <|@ <|@
    end_IR
  end_block
end_cfg
begin_bytecodes
     0: iload_2       
     1: iload_3       
     2: if_icmple     36
     5: new           #177        // java.lang.IllegalArgumentException
     8: dup           
     9: new           #179        // java.lang.StringBuilder
    12: dup           
    13: invokespecial #35         // java.lang.StringBuilder.<init>:()void
    16: iload_2       
    17: invokevirtual #36         // java.lang.StringBuilder.append:(int)java.lang.StringBuilder
    20: ldc           #186        // " > "
    22: invokevirtual #37         // java.lang.StringBuilder.append:(java.lang.String)java.lang.StringBuilder
    25: iload_3       
    26: invokevirtual #36         // java.lang.StringBuilder.append:(int)java.lang.StringBuilder
    29: invokevirtual #38         // java.lang.StringBuilder.toString:()java.lang.String
    32: invokespecial #39         // java.lang.IllegalArgumentException.<init>:(java.lang.String)void
    35: athrow        
    36: iload_3       
    37: i2l           
    38: lload_0       
    39: iload_2       
    40: i2l           
    41: invokestatic  #40         // max:(long, long)long
    44: invokestatic  #41         // min:(long, long)long
    47: l2i           
    48: ireturn       
   <|@
end_bytecodes
begin_intervals
  name "After resolve data flow"
  rax|d fixed "[rax|d]" rax|d v7|d [0, 1[[78, 80[ "NoSpillStore"
  rcx|d fixed "[rcx|d]" rcx|d -1 [0, 28[ "NoSpillStore"
  rdx|d fixed "[rdx|d]" rdx|d -1 [0, 26[ "NoSpillStore"
  rbp|q fixed "[rbp|q]" rbp|q -1 [0, 20[ "NoSpillStore"
  rsi|q fixed "[rsi|q]" rsi|q -1 [0, 24[ "NoSpillStore"
  v0|q QWORD "[rsi|q]" v0|q rsi|q [24, 68[[82, 103[24 MustHaveRegister 66 ShouldHaveRegister 68 ShouldHaveRegister  "NoSpillStore"
  v1|d DWORD "[rdx|d]" v1|d rdx|d [26, 64[[82, 103[26 MustHaveRegister 30 MustHaveRegister 64 ShouldHaveRegister  "NoSpillStore"
  v2|d DWORD "[rcx|d]" v2|d rcx|d [28, 70[[82, 103[28 MustHaveRegister 30 ShouldHaveRegister 70 ShouldHaveRegister  "NoSpillStore"
  v3|q QWORD "[rax|q]" v3|q -1 [64, 69[64 MustHaveRegister 66 MustHaveRegister 68 MustHaveRegister  "NoSpillStore"
  v4|q QWORD "[rsi|q]" v4|q v0|q [68, 75[68 MustHaveRegister 72 ShouldHaveRegister 74 MustHaveRegister  "NoSpillStore"
  v5|q QWORD "[rax|q]" v5|q -1 [70, 74[70 MustHaveRegister 72 MustHaveRegister 74 ShouldHaveRegister  "NoSpillStore"
  v6|q QWORD "[rax|q]" v6|q v5|q [74, 76[74 MustHaveRegister 76 ShouldHaveRegister  "NoSpillStore"
  v7|d DWORD "[rax|d]" v7|d -1 [76, 78[76 MustHaveRegister 78 ShouldHaveRegister  "NoSpillStore"
end_intervals
begin_cfg
  name "After SSALinearScanResolveDataFlow"
  begin_block
    name "B0"
    from_bci -1
    to_bci -1
    predecessors 
    successors "B1" "B2" 
    xhandlers
    flags 
    probability 4607182418800017408
    begin_IR
      LIR
      nr    0  <|@ instruction [rsi|QWORD, rdx|DWORD, rcx|DWORD, rbp|QWORD] = LABEL alignment: 0 numbPhis: 0 label: ? <|@ <|@
      nr    2  <|@ instruction NOP <|@ <|@
      nr    4  <|@ instruction NOP <|@ <|@
      nr    6  <|@ instruction NOP <|@ <|@
      nr    8  <|@ instruction NOP <|@ <|@
      nr   10  <|@ instruction NOP <|@ <|@
      nr   12  <|@ instruction NOP <|@ <|@
      nr   14  <|@ instruction NOP <|@ <|@
      nr   16  <|@ instruction NOP <|@ <|@
      nr   18  <|@ instruction NOP <|@ <|@
      nr   20  <|@ instruction stack:16|QWORD = MOVE input: rbp|QWORD moveKind: QWORD <|@ <|@
      nr   22  <|@ instruction [] = HOTSPOTLOCKSTACK frameMapBuilder: jdk.graal.compiler.hotspot.amd64.AMD64HotSpotFrameMapBuilder@8113c20 slotKind: QWORD <|@ <|@
      nr   24  <|@ instruction v0|QWORD = MOVE input: rsi|QWORD moveKind: QWORD <|@ <|@
      nr   26  <|@ instruction v1|DWORD = MOVE input: rdx|DWORD moveKind: DWORD <|@ <|@
      nr   28  <|@ instruction v2|DWORD = MOVE input: rcx|DWORD moveKind: DWORD <|@ <|@
      nr   30  <|@ instruction CMPBRANCH (x: v1|DWORD, y: v2|DWORD) trueDestinationProbability: 0.0 condition: > trueDestination: B0 -> B1 falseDestination: B0 -> B2 size: DWORD <|@ <|@
    end_IR
  end_block
  begin_block
    name "B2"
    from_bci -1
    to_bci -1
    predecessors "B0" 
    successors 
    xhandlers
    flags 
    probability 4607182418800017408
    begin_IR
      LIR
      nr   32  <|@ instruction [] = LABEL alignment: 0 numbPhis: 0 label: ? <|@ <|@
      nr   34  <|@ instruction NOP <|@ <|@
      nr   36  <|@ instruction NOP <|@ <|@
      nr   38  <|@ instruction NOP <|@ <|@
      nr   40  <|@ instruction NOP <|@ <|@
      nr   42  <|@ instruction NOP <|@ <|@
      nr   44  <|@ instruction NOP <|@ <|@
      nr   46  <|@ instruction NOP <|@ <|@
      nr   48  <|@ instruction NOP <|@ <|@
      nr   50  <|@ instruction NOP <|@ <|@
      nr   52  <|@ instruction NOP <|@ <|@
      nr   54  <|@ instruction NOP <|@ <|@
      nr   56  <|@ instruction NOP <|@ <|@
      nr   58  <|@ instruction NOP <|@ <|@
      nr   60  <|@ instruction NOP <|@ <|@
      nr   62  <|@ instruction NOP <|@ <|@
      nr   64  <|@ instruction v3|QWORD = MOVSXD value: v1|DWORD size: QWORD <|@ <|@
      nr   66  <|@ instruction CMP (x: v3|QWORD, y: v0|QWORD) size: QWORD <|@ <|@
      nr   68  <|@ instruction v4|QWORD = CMOVE (falseValue: v0|QWORD, ~trueValue: v3|QWORD) condition: > <|@ <|@
      nr   70  <|@ instruction v5|QWORD = MOVSXD value: v2|DWORD size: QWORD <|@ <|@
      nr   72  <|@ instruction CMP (x: v5|QWORD, y: v4|QWORD) size: QWORD <|@ <|@
      nr   74  <|@ instruction v6|QWORD = CMOVE (falseValue: v5|QWORD, ~trueValue: v4|QWORD) condition: > <|@ <|@
      nr   76  <|@ instruction v7|DWORD = MOV value: v6|QWORD size: DWORD <|@ <|@
      nr   78  <|@ instruction rax|DWORD = MOVE input: v7|DWORD moveKind: DWORD <|@ <|@
      nr   80  <|@ instruction RETURN (savedRbp: stack:16|QWORD, value: rax|DWORD) isStub: false requiresReservedStackAccessCheck: false thread: r15 scratchForSafepointOnReturn: rcx config: jdk.graal.compiler.hotspot.GraalHotSpotVMConfig@4817c460 <|@ <|@
    end_IR
  end_block
  begin_block
    name "B1"
    from_bci -1
    to_bci -1
    predecessors "B0" 
    successors 
    xhandlers
    flags 
    probability 2355382605114769408
    begin_IR
      LIR
      nr   82  <|@ instruction [] = LABEL alignment: 0 numbPhis: 0 label: ? <|@ <|@
      nr   84  <|@ instruction NOP <|@ <|@
      nr   86  <|@ instruction NOP <|@ <|@
      nr   88  <|@ instruction NOP <|@ <|@
      nr   90  <|@ instruction NOP <|@ <|@
      nr   92  <|@ instruction NOP <|@ <|@
      nr   94  <|@ instruction NOP <|@ <|@
      nr   96  <|@ instruction NOP <|@ <|@
      nr   98  <|@ instruction MOV x: [r15|QWORD + 1156] y: -5907 size: DWORD <|@ <|@
      nr  100  <|@ instruction MOV x: [r15|QWORD + 1168] y: 20 size: QWORD <|@ <|@
      nr  102  <|@ st <@st|@live-base-pointers: []
java.lang.Math.clamp(Math.java:2214) [bci: 0]
locals: v0|QWORD - v1|DWORD v2|DWORD 
>@ <|@ instruction DEOPT info [bci:0] <|@ <|@
    end_IR
  end_block
end_cfg
begin_bytecodes
     0: iload_2       
     1: iload_3       
     2: if_icmple     36
     5: new           #177        // java.lang.IllegalArgumentException
     8: dup           
     9: new           #179        // java.lang.StringBuilder
    12: dup           
    13: invokespecial #35         // java.lang.StringBuilder.<init>:()void
    16: iload_2       
    17: invokevirtual #36         // java.lang.StringBuilder.append:(int)java.lang.StringBuilder
    20: ldc           #186        // " > "
    22: invokevirtual #37         // java.lang.StringBuilder.append:(java.lang.String)java.lang.StringBuilder
    25: iload_3       
    26: invokevirtual #36         // java.lang.StringBuilder.append:(int)java.lang.StringBuilder
    29: invokevirtual #38         // java.lang.StringBuilder.toString:()java.lang.String
    32: invokespecial #39         // java.lang.IllegalArgumentException.<init>:(java.lang.String)void
    35: athrow        
    36: iload_3       
    37: i2l           
    38: lload_0       
    39: iload_2       
    40: i2l           
    41: invokestatic  #40         // max:(long, long)long
    44: invokestatic  #41         // min:(long, long)long
    47: l2i           
    48: ireturn       
   <|@
end_bytecodes
begin_cfg
  name "After SSALinearScanEliminateSpillMove"
  begin_block
    name "B0"
    from_bci -1
    to_bci -1
    predecessors 
    successors "B1" "B2" 
    xhandlers
    flags 
    probability 4607182418800017408
    begin_IR
      LIR
      nr    0  <|@ instruction [rsi|QWORD, rdx|DWORD, rcx|DWORD, rbp|QWORD] = LABEL alignment: 0 numbPhis: 0 label: ? <|@ <|@
      nr    2  <|@ instruction NOP <|@ <|@
      nr    4  <|@ instruction NOP <|@ <|@
      nr    6  <|@ instruction NOP <|@ <|@
      nr    8  <|@ instruction NOP <|@ <|@
      nr   10  <|@ instruction NOP <|@ <|@
      nr   12  <|@ instruction NOP <|@ <|@
      nr   14  <|@ instruction NOP <|@ <|@
      nr   16  <|@ instruction NOP <|@ <|@
      nr   18  <|@ instruction NOP <|@ <|@
      nr   20  <|@ instruction stack:16|QWORD = MOVE input: rbp|QWORD moveKind: QWORD <|@ <|@
      nr   22  <|@ instruction [] = HOTSPOTLOCKSTACK frameMapBuilder: jdk.graal.compiler.hotspot.amd64.AMD64HotSpotFrameMapBuilder@8113c20 slotKind: QWORD <|@ <|@
      nr   24  <|@ instruction v0|QWORD = MOVE input: rsi|QWORD moveKind: QWORD <|@ <|@
      nr   26  <|@ instruction v1|DWORD = MOVE input: rdx|DWORD moveKind: DWORD <|@ <|@
      nr   28  <|@ instruction v2|DWORD = MOVE input: rcx|DWORD moveKind: DWORD <|@ <|@
      nr   30  <|@ instruction CMPBRANCH (x: v1|DWORD, y: v2|DWORD) trueDestinationProbability: 0.0 condition: > trueDestination: B0 -> B1 falseDestination: B0 -> B2 size: DWORD <|@ <|@
    end_IR
  end_block
  begin_block
    name "B2"
    from_bci -1
    to_bci -1
    predecessors "B0" 
    successors 
    xhandlers
    flags 
    probability 4607182418800017408
    begin_IR
      LIR
      nr   32  <|@ instruction [] = LABEL alignment: 0 numbPhis: 0 label: ? <|@ <|@
      nr   34  <|@ instruction NOP <|@ <|@
      nr   36  <|@ instruction NOP <|@ <|@
      nr   38  <|@ instruction NOP <|@ <|@
      nr   40  <|@ instruction NOP <|@ <|@
      nr   42  <|@ instruction NOP <|@ <|@
      nr   44  <|@ instruction NOP <|@ <|@
      nr   46  <|@ instruction NOP <|@ <|@
      nr   48  <|@ instruction NOP <|@ <|@
      nr   50  <|@ instruction NOP <|@ <|@
      nr   52  <|@ instruction NOP <|@ <|@
      nr   54  <|@ instruction NOP <|@ <|@
      nr   56  <|@ instruction NOP <|@ <|@
      nr   58  <|@ instruction NOP <|@ <|@
      nr   60  <|@ instruction NOP <|@ <|@
      nr   62  <|@ instruction NOP <|@ <|@
      nr   64  <|@ instruction v3|QWORD = MOVSXD value: v1|DWORD size: QWORD <|@ <|@
      nr   66  <|@ instruction CMP (x: v3|QWORD, y: v0|QWORD) size: QWORD <|@ <|@
      nr   68  <|@ instruction v4|QWORD = CMOVE (falseValue: v0|QWORD, ~trueValue: v3|QWORD) condition: > <|@ <|@
      nr   70  <|@ instruction v5|QWORD = MOVSXD value: v2|DWORD size: QWORD <|@ <|@
      nr   72  <|@ instruction CMP (x: v5|QWORD, y: v4|QWORD) size: QWORD <|@ <|@
      nr   74  <|@ instruction v6|QWORD = CMOVE (falseValue: v5|QWORD, ~trueValue: v4|QWORD) condition: > <|@ <|@
      nr   76  <|@ instruction v7|DWORD = MOV value: v6|QWORD size: DWORD <|@ <|@
      nr   78  <|@ instruction rax|DWORD = MOVE input: v7|DWORD moveKind: DWORD <|@ <|@
      nr   80  <|@ instruction RETURN (savedRbp: stack:16|QWORD, value: rax|DWORD) isStub: false requiresReservedStackAccessCheck: false thread: r15 scratchForSafepointOnReturn: rcx config: jdk.graal.compiler.hotspot.GraalHotSpotVMConfig@4817c460 <|@ <|@
    end_IR
  end_block
  begin_block
    name "B1"
    from_bci -1
    to_bci -1
    predecessors "B0" 
    successors 
    xhandlers
    flags 
    probability 2355382605114769408
    begin_IR
      LIR
      nr   82  <|@ instruction [] = LABEL alignment: 0 numbPhis: 0 label: ? <|@ <|@
      nr   84  <|@ instruction NOP <|@ <|@
      nr   86  <|@ instruction NOP <|@ <|@
      nr   88  <|@ instruction NOP <|@ <|@
      nr   90  <|@ instruction NOP <|@ <|@
      nr   92  <|@ instruction NOP <|@ <|@
      nr   94  <|@ instruction NOP <|@ <|@
      nr   96  <|@ instruction NOP <|@ <|@
      nr   98  <|@ instruction MOV x: [r15|QWORD + 1156] y: -5907 size: DWORD <|@ <|@
      nr  100  <|@ instruction MOV x: [r15|QWORD + 1168] y: 20 size: QWORD <|@ <|@
      nr  102  <|@ st <@st|@live-base-pointers: []
java.lang.Math.clamp(Math.java:2214) [bci: 0]
locals: v0|QWORD - v1|DWORD v2|DWORD 
>@ <|@ instruction DEOPT info [bci:0] <|@ <|@
    end_IR
  end_block
end_cfg
begin_bytecodes
     0: iload_2       
     1: iload_3       
     2: if_icmple     36
     5: new           #177        // java.lang.IllegalArgumentException
     8: dup           
     9: new           #179        // java.lang.StringBuilder
    12: dup           
    13: invokespecial #35         // java.lang.StringBuilder.<init>:()void
    16: iload_2       
    17: invokevirtual #36         // java.lang.StringBuilder.append:(int)java.lang.StringBuilder
    20: ldc           #186        // " > "
    22: invokevirtual #37         // java.lang.StringBuilder.append:(java.lang.String)java.lang.StringBuilder
    25: iload_3       
    26: invokevirtual #36         // java.lang.StringBuilder.append:(int)java.lang.StringBuilder
    29: invokevirtual #38         // java.lang.StringBuilder.toString:()java.lang.String
    32: invokespecial #39         // java.lang.IllegalArgumentException.<init>:(java.lang.String)void
    35: athrow        
    36: iload_3       
    37: i2l           
    38: lload_0       
    39: iload_2       
    40: i2l           
    41: invokestatic  #40         // max:(long, long)long
    44: invokestatic  #41         // min:(long, long)long
    47: l2i           
    48: ireturn       
   <|@
end_bytecodes
begin_cfg
  name "After LinearScanAssignLocations"
  begin_block
    name "B0"
    from_bci -1
    to_bci -1
    predecessors 
    successors "B1" "B2" 
    xhandlers
    flags 
    probability 4607182418800017408
    begin_IR
      LIR
      nr    0  <|@ instruction [rsi|QWORD, rdx|DWORD, rcx|DWORD, rbp|QWORD] = LABEL alignment: 0 numbPhis: 0 label: ? <|@ <|@
      nr    2  <|@ instruction NOP <|@ <|@
      nr    4  <|@ instruction NOP <|@ <|@
      nr    6  <|@ instruction NOP <|@ <|@
      nr    8  <|@ instruction NOP <|@ <|@
      nr   10  <|@ instruction NOP <|@ <|@
      nr   12  <|@ instruction NOP <|@ <|@
      nr   14  <|@ instruction NOP <|@ <|@
      nr   16  <|@ instruction NOP <|@ <|@
      nr   18  <|@ instruction NOP <|@ <|@
      nr   20  <|@ instruction stack:16|QWORD = MOVE input: rbp|QWORD moveKind: QWORD <|@ <|@
      nr   22  <|@ instruction [] = HOTSPOTLOCKSTACK frameMapBuilder: jdk.graal.compiler.hotspot.amd64.AMD64HotSpotFrameMapBuilder@8113c20 slotKind: QWORD <|@ <|@
      nr   30  <|@ instruction CMPBRANCH (x: rdx|DWORD, y: rcx|DWORD) trueDestinationProbability: 0.0 condition: > trueDestination: B0 -> B1 falseDestination: B0 -> B2 size: DWORD <|@ <|@
    end_IR
  end_block
  begin_block
    name "B2"
    from_bci -1
    to_bci -1
    predecessors "B0" 
    successors 
    xhandlers
    flags 
    probability 4607182418800017408
    begin_IR
      LIR
      nr   32  <|@ instruction [] = LABEL alignment: 0 numbPhis: 0 label: ? <|@ <|@
      nr   34  <|@ instruction NOP <|@ <|@
      nr   36  <|@ instruction NOP <|@ <|@
      nr   38  <|@ instruction NOP <|@ <|@
      nr   40  <|@ instruction NOP <|@ <|@
      nr   42  <|@ instruction NOP <|@ <|@
      nr   44  <|@ instruction NOP <|@ <|@
      nr   46  <|@ instruction NOP <|@ <|@
      nr   48  <|@ instruction NOP <|@ <|@
      nr   50  <|@ instruction NOP <|@ <|@
      nr   52  <|@ instruction NOP <|@ <|@
      nr   54  <|@ instruction NOP <|@ <|@
      nr   56  <|@ instruction NOP <|@ <|@
      nr   58  <|@ instruction NOP <|@ <|@
      nr   60  <|@ instruction NOP <|@ <|@
      nr   62  <|@ instruction NOP <|@ <|@
      nr   64  <|@ instruction rax|QWORD = MOVSXD value: rdx|DWORD size: QWORD <|@ <|@
      nr   66  <|@ instruction CMP (x: rax|QWORD, y: rsi|QWORD) size: QWORD <|@ <|@
      nr   68  <|@ instruction rsi|QWORD = CMOVE (falseValue: rsi|QWORD, ~trueValue: rax|QWORD) condition: > <|@ <|@
      nr   70  <|@ instruction rax|QWORD = MOVSXD value: rcx|DWORD size: QWORD <|@ <|@
      nr   72  <|@ instruction CMP (x: rax|QWORD, y: rsi|QWORD) size: QWORD <|@ <|@
      nr   74  <|@ instruction rax|QWORD = CMOVE (falseValue: rax|QWORD, ~trueValue: rsi|QWORD) condition: > <|@ <|@
      nr   76  <|@ instruction rax|DWORD = MOV value: rax|QWORD size: DWORD <|@ <|@
      nr   80  <|@ instruction RETURN (savedRbp: stack:16|QWORD, value: rax|DWORD) isStub: false requiresReservedStackAccessCheck: false thread: r15 scratchForSafepointOnReturn: rcx config: jdk.graal.compiler.hotspot.GraalHotSpotVMConfig@4817c460 <|@ <|@
    end_IR
  end_block
  begin_block
    name "B1"
    from_bci -1
    to_bci -1
    predecessors "B0" 
    successors 
    xhandlers
    flags 
    probability 2355382605114769408
    begin_IR
      LIR
      nr   82  <|@ instruction [] = LABEL alignment: 0 numbPhis: 0 label: ? <|@ <|@
      nr   84  <|@ instruction NOP <|@ <|@
      nr   86  <|@ instruction NOP <|@ <|@
      nr   88  <|@ instruction NOP <|@ <|@
      nr   90  <|@ instruction NOP <|@ <|@
      nr   92  <|@ instruction NOP <|@ <|@
      nr   94  <|@ instruction NOP <|@ <|@
      nr   96  <|@ instruction NOP <|@ <|@
      nr   98  <|@ instruction MOV x: [r15|QWORD + 1156] y: -5907 size: DWORD <|@ <|@
      nr  100  <|@ instruction MOV x: [r15|QWORD + 1168] y: 20 size: QWORD <|@ <|@
      nr  102  <|@ st <@st|@live-base-pointers: []
java.lang.Math.clamp(Math.java:2214) [bci: 0]
locals: rsi|QWORD - rdx|DWORD rcx|DWORD 
>@ <|@ instruction DEOPT info [bci:0] <|@ <|@
    end_IR
  end_block
end_cfg
begin_bytecodes
     0: iload_2       
     1: iload_3       
     2: if_icmple     36
     5: new           #177        // java.lang.IllegalArgumentException
     8: dup           
     9: new           #179        // java.lang.StringBuilder
    12: dup           
    13: invokespecial #35         // java.lang.StringBuilder.<init>:()void
    16: iload_2       
    17: invokevirtual #36         // java.lang.StringBuilder.append:(int)java.lang.StringBuilder
    20: ldc           #186        // " > "
    22: invokevirtual #37         // java.lang.StringBuilder.append:(java.lang.String)java.lang.StringBuilder
    25: iload_3       
    26: invokevirtual #36         // java.lang.StringBuilder.append:(int)java.lang.StringBuilder
    29: invokevirtual #38         // java.lang.StringBuilder.toString:()java.lang.String
    32: invokespecial #39         // java.lang.IllegalArgumentException.<init>:(java.lang.String)void
    35: athrow        
    36: iload_3       
    37: i2l           
    38: lload_0       
    39: iload_2       
    40: i2l           
    41: invokestatic  #40         // max:(long, long)long
    44: invokestatic  #41         // min:(long, long)long
    47: l2i           
    48: ireturn       
   <|@
end_bytecodes
begin_cfg
  name "After LinearScan"
  begin_block
    name "B0"
    from_bci -1
    to_bci -1
    predecessors 
    successors "B1" "B2" 
    xhandlers
    flags 
    probability 4607182418800017408
    begin_IR
      LIR
      nr    0  <|@ instruction [rsi|QWORD, rdx|DWORD, rcx|DWORD, rbp|QWORD] = LABEL alignment: 0 numbPhis: 0 label: ? <|@ <|@
      nr    2  <|@ instruction NOP <|@ <|@
      nr    4  <|@ instruction NOP <|@ <|@
      nr    6  <|@ instruction NOP <|@ <|@
      nr    8  <|@ instruction NOP <|@ <|@
      nr   10  <|@ instruction NOP <|@ <|@
      nr   12  <|@ instruction NOP <|@ <|@
      nr   14  <|@ instruction NOP <|@ <|@
      nr   16  <|@ instruction NOP <|@ <|@
      nr   18  <|@ instruction NOP <|@ <|@
      nr   20  <|@ instruction stack:16|QWORD = MOVE input: rbp|QWORD moveKind: QWORD <|@ <|@
      nr   22  <|@ instruction [] = HOTSPOTLOCKSTACK frameMapBuilder: jdk.graal.compiler.hotspot.amd64.AMD64HotSpotFrameMapBuilder@8113c20 slotKind: QWORD <|@ <|@
      nr   30  <|@ instruction CMPBRANCH (x: rdx|DWORD, y: rcx|DWORD) trueDestinationProbability: 0.0 condition: > trueDestination: B0 -> B1 falseDestination: B0 -> B2 size: DWORD <|@ <|@
    end_IR
  end_block
  begin_block
    name "B2"
    from_bci -1
    to_bci -1
    predecessors "B0" 
    successors 
    xhandlers
    flags 
    probability 4607182418800017408
    begin_IR
      LIR
      nr   32  <|@ instruction [] = LABEL alignment: 0 numbPhis: 0 label: ? <|@ <|@
      nr   34  <|@ instruction NOP <|@ <|@
      nr   36  <|@ instruction NOP <|@ <|@
      nr   38  <|@ instruction NOP <|@ <|@
      nr   40  <|@ instruction NOP <|@ <|@
      nr   42  <|@ instruction NOP <|@ <|@
      nr   44  <|@ instruction NOP <|@ <|@
      nr   46  <|@ instruction NOP <|@ <|@
      nr   48  <|@ instruction NOP <|@ <|@
      nr   50  <|@ instruction NOP <|@ <|@
      nr   52  <|@ instruction NOP <|@ <|@
      nr   54  <|@ instruction NOP <|@ <|@
      nr   56  <|@ instruction NOP <|@ <|@
      nr   58  <|@ instruction NOP <|@ <|@
      nr   60  <|@ instruction NOP <|@ <|@
      nr   62  <|@ instruction NOP <|@ <|@
      nr   64  <|@ instruction rax|QWORD = MOVSXD value: rdx|DWORD size: QWORD <|@ <|@
      nr   66  <|@ instruction CMP (x: rax|QWORD, y: rsi|QWORD) size: QWORD <|@ <|@
      nr   68  <|@ instruction rsi|QWORD = CMOVE (falseValue: rsi|QWORD, ~trueValue: rax|QWORD) condition: > <|@ <|@
      nr   70  <|@ instruction rax|QWORD = MOVSXD value: rcx|DWORD size: QWORD <|@ <|@
      nr   72  <|@ instruction CMP (x: rax|QWORD, y: rsi|QWORD) size: QWORD <|@ <|@
      nr   74  <|@ instruction rax|QWORD = CMOVE (falseValue: rax|QWORD, ~trueValue: rsi|QWORD) condition: > <|@ <|@
      nr   76  <|@ instruction rax|DWORD = MOV value: rax|QWORD size: DWORD <|@ <|@
      nr   80  <|@ instruction RETURN (savedRbp: stack:16|QWORD, value: rax|DWORD) isStub: false requiresReservedStackAccessCheck: false thread: r15 scratchForSafepointOnReturn: rcx config: jdk.graal.compiler.hotspot.GraalHotSpotVMConfig@4817c460 <|@ <|@
    end_IR
  end_block
  begin_block
    name "B1"
    from_bci -1
    to_bci -1
    predecessors "B0" 
    successors 
    xhandlers
    flags 
    probability 2355382605114769408
    begin_IR
      LIR
      nr   82  <|@ instruction [] = LABEL alignment: 0 numbPhis: 0 label: ? <|@ <|@
      nr   84  <|@ instruction NOP <|@ <|@
      nr   86  <|@ instruction NOP <|@ <|@
      nr   88  <|@ instruction NOP <|@ <|@
      nr   90  <|@ instruction NOP <|@ <|@
      nr   92  <|@ instruction NOP <|@ <|@
      nr   94  <|@ instruction NOP <|@ <|@
      nr   96  <|@ instruction NOP <|@ <|@
      nr   98  <|@ instruction MOV x: [r15|QWORD + 1156] y: -5907 size: DWORD <|@ <|@
      nr  100  <|@ instruction MOV x: [r15|QWORD + 1168] y: 20 size: QWORD <|@ <|@
      nr  102  <|@ st <@st|@live-base-pointers: []
java.lang.Math.clamp(Math.java:2214) [bci: 0]
locals: rsi|QWORD - rdx|DWORD rcx|DWORD 
>@ <|@ instruction DEOPT info [bci:0] <|@ <|@
    end_IR
  end_block
end_cfg
begin_bytecodes
     0: iload_2       
     1: iload_3       
     2: if_icmple     36
     5: new           #177        // java.lang.IllegalArgumentException
     8: dup           
     9: new           #179        // java.lang.StringBuilder
    12: dup           
    13: invokespecial #35         // java.lang.StringBuilder.<init>:()void
    16: iload_2       
    17: invokevirtual #36         // java.lang.StringBuilder.append:(int)java.lang.StringBuilder
    20: ldc           #186        // " > "
    22: invokevirtual #37         // java.lang.StringBuilder.append:(java.lang.String)java.lang.StringBuilder
    25: iload_3       
    26: invokevirtual #36         // java.lang.StringBuilder.append:(int)java.lang.StringBuilder
    29: invokevirtual #38         // java.lang.StringBuilder.toString:()java.lang.String
    32: invokespecial #39         // java.lang.IllegalArgumentException.<init>:(java.lang.String)void
    35: athrow        
    36: iload_3       
    37: i2l           
    38: lload_0       
    39: iload_2       
    40: i2l           
    41: invokestatic  #40         // max:(long, long)long
    44: invokestatic  #41         // min:(long, long)long
    47: l2i           
    48: ireturn       
   <|@
end_bytecodes
begin_cfg
  name "After LSStackSlotAllocator"
  begin_block
    name "B0"
    from_bci -1
    to_bci -1
    predecessors 
    successors "B1" "B2" 
    xhandlers
    flags 
    probability 4607182418800017408
    begin_IR
      LIR
      nr    0  <|@ instruction [rsi|QWORD, rdx|DWORD, rcx|DWORD, rbp|QWORD] = LABEL alignment: 0 numbPhis: 0 label: ? <|@ <|@
      nr    2  <|@ instruction NOP <|@ <|@
      nr    4  <|@ instruction NOP <|@ <|@
      nr    6  <|@ instruction NOP <|@ <|@
      nr    8  <|@ instruction NOP <|@ <|@
      nr   10  <|@ instruction NOP <|@ <|@
      nr   12  <|@ instruction NOP <|@ <|@
      nr   14  <|@ instruction NOP <|@ <|@
      nr   16  <|@ instruction NOP <|@ <|@
      nr   18  <|@ instruction NOP <|@ <|@
      nr   20  <|@ instruction stack:16|QWORD = MOVE input: rbp|QWORD moveKind: QWORD <|@ <|@
      nr   22  <|@ instruction [] = HOTSPOTLOCKSTACK frameMapBuilder: jdk.graal.compiler.hotspot.amd64.AMD64HotSpotFrameMapBuilder@8113c20 slotKind: QWORD <|@ <|@
      nr   30  <|@ instruction CMPBRANCH (x: rdx|DWORD, y: rcx|DWORD) trueDestinationProbability: 0.0 condition: > trueDestination: B0 -> B1 falseDestination: B0 -> B2 size: DWORD <|@ <|@
    end_IR
  end_block
  begin_block
    name "B2"
    from_bci -1
    to_bci -1
    predecessors "B0" 
    successors 
    xhandlers
    flags 
    probability 4607182418800017408
    begin_IR
      LIR
      nr   32  <|@ instruction [] = LABEL alignment: 0 numbPhis: 0 label: ? <|@ <|@
      nr   34  <|@ instruction NOP <|@ <|@
      nr   36  <|@ instruction NOP <|@ <|@
      nr   38  <|@ instruction NOP <|@ <|@
      nr   40  <|@ instruction NOP <|@ <|@
      nr   42  <|@ instruction NOP <|@ <|@
      nr   44  <|@ instruction NOP <|@ <|@
      nr   46  <|@ instruction NOP <|@ <|@
      nr   48  <|@ instruction NOP <|@ <|@
      nr   50  <|@ instruction NOP <|@ <|@
      nr   52  <|@ instruction NOP <|@ <|@
      nr   54  <|@ instruction NOP <|@ <|@
      nr   56  <|@ instruction NOP <|@ <|@
      nr   58  <|@ instruction NOP <|@ <|@
      nr   60  <|@ instruction NOP <|@ <|@
      nr   62  <|@ instruction NOP <|@ <|@
      nr   64  <|@ instruction rax|QWORD = MOVSXD value: rdx|DWORD size: QWORD <|@ <|@
      nr   66  <|@ instruction CMP (x: rax|QWORD, y: rsi|QWORD) size: QWORD <|@ <|@
      nr   68  <|@ instruction rsi|QWORD = CMOVE (falseValue: rsi|QWORD, ~trueValue: rax|QWORD) condition: > <|@ <|@
      nr   70  <|@ instruction rax|QWORD = MOVSXD value: rcx|DWORD size: QWORD <|@ <|@
      nr   72  <|@ instruction CMP (x: rax|QWORD, y: rsi|QWORD) size: QWORD <|@ <|@
      nr   74  <|@ instruction rax|QWORD = CMOVE (falseValue: rax|QWORD, ~trueValue: rsi|QWORD) condition: > <|@ <|@
      nr   76  <|@ instruction rax|DWORD = MOV value: rax|QWORD size: DWORD <|@ <|@
      nr   80  <|@ instruction RETURN (savedRbp: stack:16|QWORD, value: rax|DWORD) isStub: false requiresReservedStackAccessCheck: false thread: r15 scratchForSafepointOnReturn: rcx config: jdk.graal.compiler.hotspot.GraalHotSpotVMConfig@4817c460 <|@ <|@
    end_IR
  end_block
  begin_block
    name "B1"
    from_bci -1
    to_bci -1
    predecessors "B0" 
    successors 
    xhandlers
    flags 
    probability 2355382605114769408
    begin_IR
      LIR
      nr   82  <|@ instruction [] = LABEL alignment: 0 numbPhis: 0 label: ? <|@ <|@
      nr   84  <|@ instruction NOP <|@ <|@
      nr   86  <|@ instruction NOP <|@ <|@
      nr   88  <|@ instruction NOP <|@ <|@
      nr   90  <|@ instruction NOP <|@ <|@
      nr   92  <|@ instruction NOP <|@ <|@
      nr   94  <|@ instruction NOP <|@ <|@
      nr   96  <|@ instruction NOP <|@ <|@
      nr   98  <|@ instruction MOV x: [r15|QWORD + 1156] y: -5907 size: DWORD <|@ <|@
      nr  100  <|@ instruction MOV x: [r15|QWORD + 1168] y: 20 size: QWORD <|@ <|@
      nr  102  <|@ st <@st|@live-base-pointers: []
java.lang.Math.clamp(Math.java:2214) [bci: 0]
locals: rsi|QWORD - rdx|DWORD rcx|DWORD 
>@ <|@ instruction DEOPT info [bci:0] <|@ <|@
    end_IR
  end_block
end_cfg
begin_bytecodes
     0: iload_2       
     1: iload_3       
     2: if_icmple     36
     5: new           #177        // java.lang.IllegalArgumentException
     8: dup           
     9: new           #179        // java.lang.StringBuilder
    12: dup           
    13: invokespecial #35         // java.lang.StringBuilder.<init>:()void
    16: iload_2       
    17: invokevirtual #36         // java.lang.StringBuilder.append:(int)java.lang.StringBuilder
    20: ldc           #186        // " > "
    22: invokevirtual #37         // java.lang.StringBuilder.append:(java.lang.String)java.lang.StringBuilder
    25: iload_3       
    26: invokevirtual #36         // java.lang.StringBuilder.append:(int)java.lang.StringBuilder
    29: invokevirtual #38         // java.lang.StringBuilder.toString:()java.lang.String
    32: invokespecial #39         // java.lang.IllegalArgumentException.<init>:(java.lang.String)void
    35: athrow        
    36: iload_3       
    37: i2l           
    38: lload_0       
    39: iload_2       
    40: i2l           
    41: invokestatic  #40         // max:(long, long)long
    44: invokestatic  #41         // min:(long, long)long
    47: l2i           
    48: ireturn       
   <|@
end_bytecodes
begin_cfg
  name "After AllocationStage"
  begin_block
    name "B0"
    from_bci -1
    to_bci -1
    predecessors 
    successors "B1" "B2" 
    xhandlers
    flags 
    probability 4607182418800017408
    begin_IR
      LIR
      nr    0  <|@ instruction [rsi|QWORD, rdx|DWORD, rcx|DWORD, rbp|QWORD] = LABEL alignment: 0 numbPhis: 0 label: ? <|@ <|@
      nr    2  <|@ instruction NOP <|@ <|@
      nr    4  <|@ instruction NOP <|@ <|@
      nr    6  <|@ instruction NOP <|@ <|@
      nr    8  <|@ instruction NOP <|@ <|@
      nr   10  <|@ instruction NOP <|@ <|@
      nr   12  <|@ instruction NOP <|@ <|@
      nr   14  <|@ instruction NOP <|@ <|@
      nr   16  <|@ instruction NOP <|@ <|@
      nr   18  <|@ instruction NOP <|@ <|@
      nr   20  <|@ instruction stack:16|QWORD = MOVE input: rbp|QWORD moveKind: QWORD <|@ <|@
      nr   22  <|@ instruction [] = HOTSPOTLOCKSTACK frameMapBuilder: jdk.graal.compiler.hotspot.amd64.AMD64HotSpotFrameMapBuilder@8113c20 slotKind: QWORD <|@ <|@
      nr   30  <|@ instruction CMPBRANCH (x: rdx|DWORD, y: rcx|DWORD) trueDestinationProbability: 0.0 condition: > trueDestination: B0 -> B1 falseDestination: B0 -> B2 size: DWORD <|@ <|@
    end_IR
  end_block
  begin_block
    name "B2"
    from_bci -1
    to_bci -1
    predecessors "B0" 
    successors 
    xhandlers
    flags 
    probability 4607182418800017408
    begin_IR
      LIR
      nr   32  <|@ instruction [] = LABEL alignment: 0 numbPhis: 0 label: ? <|@ <|@
      nr   34  <|@ instruction NOP <|@ <|@
      nr   36  <|@ instruction NOP <|@ <|@
      nr   38  <|@ instruction NOP <|@ <|@
      nr   40  <|@ instruction NOP <|@ <|@
      nr   42  <|@ instruction NOP <|@ <|@
      nr   44  <|@ instruction NOP <|@ <|@
      nr   46  <|@ instruction NOP <|@ <|@
      nr   48  <|@ instruction NOP <|@ <|@
      nr   50  <|@ instruction NOP <|@ <|@
      nr   52  <|@ instruction NOP <|@ <|@
      nr   54  <|@ instruction NOP <|@ <|@
      nr   56  <|@ instruction NOP <|@ <|@
      nr   58  <|@ instruction NOP <|@ <|@
      nr   60  <|@ instruction NOP <|@ <|@
      nr   62  <|@ instruction NOP <|@ <|@
      nr   64  <|@ instruction rax|QWORD = MOVSXD value: rdx|DWORD size: QWORD <|@ <|@
      nr   66  <|@ instruction CMP (x: rax|QWORD, y: rsi|QWORD) size: QWORD <|@ <|@
      nr   68  <|@ instruction rsi|QWORD = CMOVE (falseValue: rsi|QWORD, ~trueValue: rax|QWORD) condition: > <|@ <|@
      nr   70  <|@ instruction rax|QWORD = MOVSXD value: rcx|DWORD size: QWORD <|@ <|@
      nr   72  <|@ instruction CMP (x: rax|QWORD, y: rsi|QWORD) size: QWORD <|@ <|@
      nr   74  <|@ instruction rax|QWORD = CMOVE (falseValue: rax|QWORD, ~trueValue: rsi|QWORD) condition: > <|@ <|@
      nr   76  <|@ instruction rax|DWORD = MOV value: rax|QWORD size: DWORD <|@ <|@
      nr   80  <|@ instruction RETURN (savedRbp: stack:16|QWORD, value: rax|DWORD) isStub: false requiresReservedStackAccessCheck: false thread: r15 scratchForSafepointOnReturn: rcx config: jdk.graal.compiler.hotspot.GraalHotSpotVMConfig@4817c460 <|@ <|@
    end_IR
  end_block
  begin_block
    name "B1"
    from_bci -1
    to_bci -1
    predecessors "B0" 
    successors 
    xhandlers
    flags 
    probability 2355382605114769408
    begin_IR
      LIR
      nr   82  <|@ instruction [] = LABEL alignment: 0 numbPhis: 0 label: ? <|@ <|@
      nr   84  <|@ instruction NOP <|@ <|@
      nr   86  <|@ instruction NOP <|@ <|@
      nr   88  <|@ instruction NOP <|@ <|@
      nr   90  <|@ instruction NOP <|@ <|@
      nr   92  <|@ instruction NOP <|@ <|@
      nr   94  <|@ instruction NOP <|@ <|@
      nr   96  <|@ instruction NOP <|@ <|@
      nr   98  <|@ instruction MOV x: [r15|QWORD + 1156] y: -5907 size: DWORD <|@ <|@
      nr  100  <|@ instruction MOV x: [r15|QWORD + 1168] y: 20 size: QWORD <|@ <|@
      nr  102  <|@ st <@st|@live-base-pointers: []
java.lang.Math.clamp(Math.java:2214) [bci: 0]
locals: rsi|QWORD - rdx|DWORD rcx|DWORD 
>@ <|@ instruction DEOPT info [bci:0] <|@ <|@
    end_IR
  end_block
end_cfg
begin_bytecodes
     0: iload_2       
     1: iload_3       
     2: if_icmple     36
     5: new           #177        // java.lang.IllegalArgumentException
     8: dup           
     9: new           #179        // java.lang.StringBuilder
    12: dup           
    13: invokespecial #35         // java.lang.StringBuilder.<init>:()void
    16: iload_2       
    17: invokevirtual #36         // java.lang.StringBuilder.append:(int)java.lang.StringBuilder
    20: ldc           #186        // " > "
    22: invokevirtual #37         // java.lang.StringBuilder.append:(java.lang.String)java.lang.StringBuilder
    25: iload_3       
    26: invokevirtual #36         // java.lang.StringBuilder.append:(int)java.lang.StringBuilder
    29: invokevirtual #38         // java.lang.StringBuilder.toString:()java.lang.String
    32: invokespecial #39         // java.lang.IllegalArgumentException.<init>:(java.lang.String)void
    35: athrow        
    36: iload_3       
    37: i2l           
    38: lload_0       
    39: iload_2       
    40: i2l           
    41: invokestatic  #40         // max:(long, long)long
    44: invokestatic  #41         // min:(long, long)long
    47: l2i           
    48: ireturn       
   <|@
end_bytecodes
begin_cfg
  name "After EdgeMoveOptimizer"
  begin_block
    name "B0"
    from_bci -1
    to_bci -1
    predecessors 
    successors "B1" "B2" 
    xhandlers
    flags 
    probability 4607182418800017408
    begin_IR
      LIR
      nr    0  <|@ instruction [rsi|QWORD, rdx|DWORD, rcx|DWORD, rbp|QWORD] = LABEL alignment: 0 numbPhis: 0 label: ? <|@ <|@
      nr    2  <|@ instruction NOP <|@ <|@
      nr    4  <|@ instruction NOP <|@ <|@
      nr    6  <|@ instruction NOP <|@ <|@
      nr    8  <|@ instruction NOP <|@ <|@
      nr   10  <|@ instruction NOP <|@ <|@
      nr   12  <|@ instruction NOP <|@ <|@
      nr   14  <|@ instruction NOP <|@ <|@
      nr   16  <|@ instruction NOP <|@ <|@
      nr   18  <|@ instruction NOP <|@ <|@
      nr   20  <|@ instruction stack:16|QWORD = MOVE input: rbp|QWORD moveKind: QWORD <|@ <|@
      nr   22  <|@ instruction [] = HOTSPOTLOCKSTACK frameMapBuilder: jdk.graal.compiler.hotspot.amd64.AMD64HotSpotFrameMapBuilder@8113c20 slotKind: QWORD <|@ <|@
      nr   30  <|@ instruction CMPBRANCH (x: rdx|DWORD, y: rcx|DWORD) trueDestinationProbability: 0.0 condition: > trueDestination: B0 -> B1 falseDestination: B0 -> B2 size: DWORD <|@ <|@
    end_IR
  end_block
  begin_block
    name "B2"
    from_bci -1
    to_bci -1
    predecessors "B0" 
    successors 
    xhandlers
    flags 
    probability 4607182418800017408
    begin_IR
      LIR
      nr   32  <|@ instruction [] = LABEL alignment: 0 numbPhis: 0 label: ? <|@ <|@
      nr   34  <|@ instruction NOP <|@ <|@
      nr   36  <|@ instruction NOP <|@ <|@
      nr   38  <|@ instruction NOP <|@ <|@
      nr   40  <|@ instruction NOP <|@ <|@
      nr   42  <|@ instruction NOP <|@ <|@
      nr   44  <|@ instruction NOP <|@ <|@
      nr   46  <|@ instruction NOP <|@ <|@
      nr   48  <|@ instruction NOP <|@ <|@
      nr   50  <|@ instruction NOP <|@ <|@
      nr   52  <|@ instruction NOP <|@ <|@
      nr   54  <|@ instruction NOP <|@ <|@
      nr   56  <|@ instruction NOP <|@ <|@
      nr   58  <|@ instruction NOP <|@ <|@
      nr   60  <|@ instruction NOP <|@ <|@
      nr   62  <|@ instruction NOP <|@ <|@
      nr   64  <|@ instruction rax|QWORD = MOVSXD value: rdx|DWORD size: QWORD <|@ <|@
      nr   66  <|@ instruction CMP (x: rax|QWORD, y: rsi|QWORD) size: QWORD <|@ <|@
      nr   68  <|@ instruction rsi|QWORD = CMOVE (falseValue: rsi|QWORD, ~trueValue: rax|QWORD) condition: > <|@ <|@
      nr   70  <|@ instruction rax|QWORD = MOVSXD value: rcx|DWORD size: QWORD <|@ <|@
      nr   72  <|@ instruction CMP (x: rax|QWORD, y: rsi|QWORD) size: QWORD <|@ <|@
      nr   74  <|@ instruction rax|QWORD = CMOVE (falseValue: rax|QWORD, ~trueValue: rsi|QWORD) condition: > <|@ <|@
      nr   76  <|@ instruction rax|DWORD = MOV value: rax|QWORD size: DWORD <|@ <|@
      nr   80  <|@ instruction RETURN (savedRbp: stack:16|QWORD, value: rax|DWORD) isStub: false requiresReservedStackAccessCheck: false thread: r15 scratchForSafepointOnReturn: rcx config: jdk.graal.compiler.hotspot.GraalHotSpotVMConfig@4817c460 <|@ <|@
    end_IR
  end_block
  begin_block
    name "B1"
    from_bci -1
    to_bci -1
    predecessors "B0" 
    successors 
    xhandlers
    flags 
    probability 2355382605114769408
    begin_IR
      LIR
      nr   82  <|@ instruction [] = LABEL alignment: 0 numbPhis: 0 label: ? <|@ <|@
      nr   84  <|@ instruction NOP <|@ <|@
      nr   86  <|@ instruction NOP <|@ <|@
      nr   88  <|@ instruction NOP <|@ <|@
      nr   90  <|@ instruction NOP <|@ <|@
      nr   92  <|@ instruction NOP <|@ <|@
      nr   94  <|@ instruction NOP <|@ <|@
      nr   96  <|@ instruction NOP <|@ <|@
      nr   98  <|@ instruction MOV x: [r15|QWORD + 1156] y: -5907 size: DWORD <|@ <|@
      nr  100  <|@ instruction MOV x: [r15|QWORD + 1168] y: 20 size: QWORD <|@ <|@
      nr  102  <|@ st <@st|@live-base-pointers: []
java.lang.Math.clamp(Math.java:2214) [bci: 0]
locals: rsi|QWORD - rdx|DWORD rcx|DWORD 
>@ <|@ instruction DEOPT info [bci:0] <|@ <|@
    end_IR
  end_block
end_cfg
begin_bytecodes
     0: iload_2       
     1: iload_3       
     2: if_icmple     36
     5: new           #177        // java.lang.IllegalArgumentException
     8: dup           
     9: new           #179        // java.lang.StringBuilder
    12: dup           
    13: invokespecial #35         // java.lang.StringBuilder.<init>:()void
    16: iload_2       
    17: invokevirtual #36         // java.lang.StringBuilder.append:(int)java.lang.StringBuilder
    20: ldc           #186        // " > "
    22: invokevirtual #37         // java.lang.StringBuilder.append:(java.lang.String)java.lang.StringBuilder
    25: iload_3       
    26: invokevirtual #36         // java.lang.StringBuilder.append:(int)java.lang.StringBuilder
    29: invokevirtual #38         // java.lang.StringBuilder.toString:()java.lang.String
    32: invokespecial #39         // java.lang.IllegalArgumentException.<init>:(java.lang.String)void
    35: athrow        
    36: iload_3       
    37: i2l           
    38: lload_0       
    39: iload_2       
    40: i2l           
    41: invokestatic  #40         // max:(long, long)long
    44: invokestatic  #41         // min:(long, long)long
    47: l2i           
    48: ireturn       
   <|@
end_bytecodes
begin_cfg
  name "After RedundantMoveElimination"
  begin_block
    name "B0"
    from_bci -1
    to_bci -1
    predecessors 
    successors "B1" "B2" 
    xhandlers
    flags 
    probability 4607182418800017408
    begin_IR
      LIR
      nr    0  <|@ instruction [rsi|QWORD, rdx|DWORD, rcx|DWORD, rbp|QWORD] = LABEL alignment: 0 numbPhis: 0 label: ? <|@ <|@
      nr    2  <|@ instruction NOP <|@ <|@
      nr    4  <|@ instruction NOP <|@ <|@
      nr    6  <|@ instruction NOP <|@ <|@
      nr    8  <|@ instruction NOP <|@ <|@
      nr   10  <|@ instruction NOP <|@ <|@
      nr   12  <|@ instruction NOP <|@ <|@
      nr   14  <|@ instruction NOP <|@ <|@
      nr   16  <|@ instruction NOP <|@ <|@
      nr   18  <|@ instruction NOP <|@ <|@
      nr   20  <|@ instruction stack:16|QWORD = MOVE input: rbp|QWORD moveKind: QWORD <|@ <|@
      nr   22  <|@ instruction [] = HOTSPOTLOCKSTACK frameMapBuilder: jdk.graal.compiler.hotspot.amd64.AMD64HotSpotFrameMapBuilder@8113c20 slotKind: QWORD <|@ <|@
      nr   30  <|@ instruction CMPBRANCH (x: rdx|DWORD, y: rcx|DWORD) trueDestinationProbability: 0.0 condition: > trueDestination: B0 -> B1 falseDestination: B0 -> B2 size: DWORD <|@ <|@
    end_IR
  end_block
  begin_block
    name "B2"
    from_bci -1
    to_bci -1
    predecessors "B0" 
    successors 
    xhandlers
    flags 
    probability 4607182418800017408
    begin_IR
      LIR
      nr   32  <|@ instruction [] = LABEL alignment: 0 numbPhis: 0 label: ? <|@ <|@
      nr   34  <|@ instruction NOP <|@ <|@
      nr   36  <|@ instruction NOP <|@ <|@
      nr   38  <|@ instruction NOP <|@ <|@
      nr   40  <|@ instruction NOP <|@ <|@
      nr   42  <|@ instruction NOP <|@ <|@
      nr   44  <|@ instruction NOP <|@ <|@
      nr   46  <|@ instruction NOP <|@ <|@
      nr   48  <|@ instruction NOP <|@ <|@
      nr   50  <|@ instruction NOP <|@ <|@
      nr   52  <|@ instruction NOP <|@ <|@
      nr   54  <|@ instruction NOP <|@ <|@
      nr   56  <|@ instruction NOP <|@ <|@
      nr   58  <|@ instruction NOP <|@ <|@
      nr   60  <|@ instruction NOP <|@ <|@
      nr   62  <|@ instruction NOP <|@ <|@
      nr   64  <|@ instruction rax|QWORD = MOVSXD value: rdx|DWORD size: QWORD <|@ <|@
      nr   66  <|@ instruction CMP (x: rax|QWORD, y: rsi|QWORD) size: QWORD <|@ <|@
      nr   68  <|@ instruction rsi|QWORD = CMOVE (falseValue: rsi|QWORD, ~trueValue: rax|QWORD) condition: > <|@ <|@
      nr   70  <|@ instruction rax|QWORD = MOVSXD value: rcx|DWORD size: QWORD <|@ <|@
      nr   72  <|@ instruction CMP (x: rax|QWORD, y: rsi|QWORD) size: QWORD <|@ <|@
      nr   74  <|@ instruction rax|QWORD = CMOVE (falseValue: rax|QWORD, ~trueValue: rsi|QWORD) condition: > <|@ <|@
      nr   76  <|@ instruction rax|DWORD = MOV value: rax|QWORD size: DWORD <|@ <|@
      nr   80  <|@ instruction RETURN (savedRbp: stack:16|QWORD, value: rax|DWORD) isStub: false requiresReservedStackAccessCheck: false thread: r15 scratchForSafepointOnReturn: rcx config: jdk.graal.compiler.hotspot.GraalHotSpotVMConfig@4817c460 <|@ <|@
    end_IR
  end_block
  begin_block
    name "B1"
    from_bci -1
    to_bci -1
    predecessors "B0" 
    successors 
    xhandlers
    flags 
    probability 2355382605114769408
    begin_IR
      LIR
      nr   82  <|@ instruction [] = LABEL alignment: 0 numbPhis: 0 label: ? <|@ <|@
      nr   84  <|@ instruction NOP <|@ <|@
      nr   86  <|@ instruction NOP <|@ <|@
      nr   88  <|@ instruction NOP <|@ <|@
      nr   90  <|@ instruction NOP <|@ <|@
      nr   92  <|@ instruction NOP <|@ <|@
      nr   94  <|@ instruction NOP <|@ <|@
      nr   96  <|@ instruction NOP <|@ <|@
      nr   98  <|@ instruction MOV x: [r15|QWORD + 1156] y: -5907 size: DWORD <|@ <|@
      nr  100  <|@ instruction MOV x: [r15|QWORD + 1168] y: 20 size: QWORD <|@ <|@
      nr  102  <|@ st <@st|@live-base-pointers: []
java.lang.Math.clamp(Math.java:2214) [bci: 0]
locals: rsi|QWORD - rdx|DWORD rcx|DWORD 
>@ <|@ instruction DEOPT info [bci:0] <|@ <|@
    end_IR
  end_block
end_cfg
begin_bytecodes
     0: iload_2       
     1: iload_3       
     2: if_icmple     36
     5: new           #177        // java.lang.IllegalArgumentException
     8: dup           
     9: new           #179        // java.lang.StringBuilder
    12: dup           
    13: invokespecial #35         // java.lang.StringBuilder.<init>:()void
    16: iload_2       
    17: invokevirtual #36         // java.lang.StringBuilder.append:(int)java.lang.StringBuilder
    20: ldc           #186        // " > "
    22: invokevirtual #37         // java.lang.StringBuilder.append:(java.lang.String)java.lang.StringBuilder
    25: iload_3       
    26: invokevirtual #36         // java.lang.StringBuilder.append:(int)java.lang.StringBuilder
    29: invokevirtual #38         // java.lang.StringBuilder.toString:()java.lang.String
    32: invokespecial #39         // java.lang.IllegalArgumentException.<init>:(java.lang.String)void
    35: athrow        
    36: iload_3       
    37: i2l           
    38: lload_0       
    39: iload_2       
    40: i2l           
    41: invokestatic  #40         // max:(long, long)long
    44: invokestatic  #41         // min:(long, long)long
    47: l2i           
    48: ireturn       
   <|@
end_bytecodes
begin_cfg
  name "After NullCheckOptimizer"
  begin_block
    name "B0"
    from_bci -1
    to_bci -1
    predecessors 
    successors "B1" "B2" 
    xhandlers
    flags 
    probability 4607182418800017408
    begin_IR
      LIR
      nr    0  <|@ instruction [rsi|QWORD, rdx|DWORD, rcx|DWORD, rbp|QWORD] = LABEL alignment: 0 numbPhis: 0 label: ? <|@ <|@
      nr    2  <|@ instruction NOP <|@ <|@
      nr    4  <|@ instruction NOP <|@ <|@
      nr    6  <|@ instruction NOP <|@ <|@
      nr    8  <|@ instruction NOP <|@ <|@
      nr   10  <|@ instruction NOP <|@ <|@
      nr   12  <|@ instruction NOP <|@ <|@
      nr   14  <|@ instruction NOP <|@ <|@
      nr   16  <|@ instruction NOP <|@ <|@
      nr   18  <|@ instruction NOP <|@ <|@
      nr   20  <|@ instruction stack:16|QWORD = MOVE input: rbp|QWORD moveKind: QWORD <|@ <|@
      nr   22  <|@ instruction [] = HOTSPOTLOCKSTACK frameMapBuilder: jdk.graal.compiler.hotspot.amd64.AMD64HotSpotFrameMapBuilder@8113c20 slotKind: QWORD <|@ <|@
      nr   30  <|@ instruction CMPBRANCH (x: rdx|DWORD, y: rcx|DWORD) trueDestinationProbability: 0.0 condition: > trueDestination: B0 -> B1 falseDestination: B0 -> B2 size: DWORD <|@ <|@
    end_IR
  end_block
  begin_block
    name "B2"
    from_bci -1
    to_bci -1
    predecessors "B0" 
    successors 
    xhandlers
    flags 
    probability 4607182418800017408
    begin_IR
      LIR
      nr   32  <|@ instruction [] = LABEL alignment: 0 numbPhis: 0 label: ? <|@ <|@
      nr   34  <|@ instruction NOP <|@ <|@
      nr   36  <|@ instruction NOP <|@ <|@
      nr   38  <|@ instruction NOP <|@ <|@
      nr   40  <|@ instruction NOP <|@ <|@
      nr   42  <|@ instruction NOP <|@ <|@
      nr   44  <|@ instruction NOP <|@ <|@
      nr   46  <|@ instruction NOP <|@ <|@
      nr   48  <|@ instruction NOP <|@ <|@
      nr   50  <|@ instruction NOP <|@ <|@
      nr   52  <|@ instruction NOP <|@ <|@
      nr   54  <|@ instruction NOP <|@ <|@
      nr   56  <|@ instruction NOP <|@ <|@
      nr   58  <|@ instruction NOP <|@ <|@
      nr   60  <|@ instruction NOP <|@ <|@
      nr   62  <|@ instruction NOP <|@ <|@
      nr   64  <|@ instruction rax|QWORD = MOVSXD value: rdx|DWORD size: QWORD <|@ <|@
      nr   66  <|@ instruction CMP (x: rax|QWORD, y: rsi|QWORD) size: QWORD <|@ <|@
      nr   68  <|@ instruction rsi|QWORD = CMOVE (falseValue: rsi|QWORD, ~trueValue: rax|QWORD) condition: > <|@ <|@
      nr   70  <|@ instruction rax|QWORD = MOVSXD value: rcx|DWORD size: QWORD <|@ <|@
      nr   72  <|@ instruction CMP (x: rax|QWORD, y: rsi|QWORD) size: QWORD <|@ <|@
      nr   74  <|@ instruction rax|QWORD = CMOVE (falseValue: rax|QWORD, ~trueValue: rsi|QWORD) condition: > <|@ <|@
      nr   76  <|@ instruction rax|DWORD = MOV value: rax|QWORD size: DWORD <|@ <|@
      nr   80  <|@ instruction RETURN (savedRbp: stack:16|QWORD, value: rax|DWORD) isStub: false requiresReservedStackAccessCheck: false thread: r15 scratchForSafepointOnReturn: rcx config: jdk.graal.compiler.hotspot.GraalHotSpotVMConfig@4817c460 <|@ <|@
    end_IR
  end_block
  begin_block
    name "B1"
    from_bci -1
    to_bci -1
    predecessors "B0" 
    successors 
    xhandlers
    flags 
    probability 2355382605114769408
    begin_IR
      LIR
      nr   82  <|@ instruction [] = LABEL alignment: 0 numbPhis: 0 label: ? <|@ <|@
      nr   84  <|@ instruction NOP <|@ <|@
      nr   86  <|@ instruction NOP <|@ <|@
      nr   88  <|@ instruction NOP <|@ <|@
      nr   90  <|@ instruction NOP <|@ <|@
      nr   92  <|@ instruction NOP <|@ <|@
      nr   94  <|@ instruction NOP <|@ <|@
      nr   96  <|@ instruction NOP <|@ <|@
      nr   98  <|@ instruction MOV x: [r15|QWORD + 1156] y: -5907 size: DWORD <|@ <|@
      nr  100  <|@ instruction MOV x: [r15|QWORD + 1168] y: 20 size: QWORD <|@ <|@
      nr  102  <|@ st <@st|@live-base-pointers: []
java.lang.Math.clamp(Math.java:2214) [bci: 0]
locals: rsi|QWORD - rdx|DWORD rcx|DWORD 
>@ <|@ instruction DEOPT info [bci:0] <|@ <|@
    end_IR
  end_block
end_cfg
begin_bytecodes
     0: iload_2       
     1: iload_3       
     2: if_icmple     36
     5: new           #177        // java.lang.IllegalArgumentException
     8: dup           
     9: new           #179        // java.lang.StringBuilder
    12: dup           
    13: invokespecial #35         // java.lang.StringBuilder.<init>:()void
    16: iload_2       
    17: invokevirtual #36         // java.lang.StringBuilder.append:(int)java.lang.StringBuilder
    20: ldc           #186        // " > "
    22: invokevirtual #37         // java.lang.StringBuilder.append:(java.lang.String)java.lang.StringBuilder
    25: iload_3       
    26: invokevirtual #36         // java.lang.StringBuilder.append:(int)java.lang.StringBuilder
    29: invokevirtual #38         // java.lang.StringBuilder.toString:()java.lang.String
    32: invokespecial #39         // java.lang.IllegalArgumentException.<init>:(java.lang.String)void
    35: athrow        
    36: iload_3       
    37: i2l           
    38: lload_0       
    39: iload_2       
    40: i2l           
    41: invokestatic  #40         // max:(long, long)long
    44: invokestatic  #41         // min:(long, long)long
    47: l2i           
    48: ireturn       
   <|@
end_bytecodes
begin_cfg
  name "After ControlFlowOptimizer"
  begin_block
    name "B0"
    from_bci -1
    to_bci -1
    predecessors 
    successors "B1" "B2" 
    xhandlers
    flags 
    probability 4607182418800017408
    begin_IR
      LIR
      nr    0  <|@ instruction [rsi|QWORD, rdx|DWORD, rcx|DWORD, rbp|QWORD] = LABEL alignment: 0 numbPhis: 0 label: ? <|@ <|@
      nr    2  <|@ instruction NOP <|@ <|@
      nr    4  <|@ instruction NOP <|@ <|@
      nr    6  <|@ instruction NOP <|@ <|@
      nr    8  <|@ instruction NOP <|@ <|@
      nr   10  <|@ instruction NOP <|@ <|@
      nr   12  <|@ instruction NOP <|@ <|@
      nr   14  <|@ instruction NOP <|@ <|@
      nr   16  <|@ instruction NOP <|@ <|@
      nr   18  <|@ instruction NOP <|@ <|@
      nr   20  <|@ instruction stack:16|QWORD = MOVE input: rbp|QWORD moveKind: QWORD <|@ <|@
      nr   22  <|@ instruction [] = HOTSPOTLOCKSTACK frameMapBuilder: jdk.graal.compiler.hotspot.amd64.AMD64HotSpotFrameMapBuilder@8113c20 slotKind: QWORD <|@ <|@
      nr   30  <|@ instruction CMPBRANCH (x: rdx|DWORD, y: rcx|DWORD) trueDestinationProbability: 0.0 condition: > trueDestination: B0 -> B1 falseDestination: B0 -> B2 size: DWORD <|@ <|@
    end_IR
  end_block
  begin_block
    name "B2"
    from_bci -1
    to_bci -1
    predecessors "B0" 
    successors 
    xhandlers
    flags 
    probability 4607182418800017408
    begin_IR
      LIR
      nr   32  <|@ instruction [] = LABEL alignment: 0 numbPhis: 0 label: ? <|@ <|@
      nr   34  <|@ instruction NOP <|@ <|@
      nr   36  <|@ instruction NOP <|@ <|@
      nr   38  <|@ instruction NOP <|@ <|@
      nr   40  <|@ instruction NOP <|@ <|@
      nr   42  <|@ instruction NOP <|@ <|@
      nr   44  <|@ instruction NOP <|@ <|@
      nr   46  <|@ instruction NOP <|@ <|@
      nr   48  <|@ instruction NOP <|@ <|@
      nr   50  <|@ instruction NOP <|@ <|@
      nr   52  <|@ instruction NOP <|@ <|@
      nr   54  <|@ instruction NOP <|@ <|@
      nr   56  <|@ instruction NOP <|@ <|@
      nr   58  <|@ instruction NOP <|@ <|@
      nr   60  <|@ instruction NOP <|@ <|@
      nr   62  <|@ instruction NOP <|@ <|@
      nr   64  <|@ instruction rax|QWORD = MOVSXD value: rdx|DWORD size: QWORD <|@ <|@
      nr   66  <|@ instruction CMP (x: rax|QWORD, y: rsi|QWORD) size: QWORD <|@ <|@
      nr   68  <|@ instruction rsi|QWORD = CMOVE (falseValue: rsi|QWORD, ~trueValue: rax|QWORD) condition: > <|@ <|@
      nr   70  <|@ instruction rax|QWORD = MOVSXD value: rcx|DWORD size: QWORD <|@ <|@
      nr   72  <|@ instruction CMP (x: rax|QWORD, y: rsi|QWORD) size: QWORD <|@ <|@
      nr   74  <|@ instruction rax|QWORD = CMOVE (falseValue: rax|QWORD, ~trueValue: rsi|QWORD) condition: > <|@ <|@
      nr   76  <|@ instruction rax|DWORD = MOV value: rax|QWORD size: DWORD <|@ <|@
      nr   80  <|@ instruction RETURN (savedRbp: stack:16|QWORD, value: rax|DWORD) isStub: false requiresReservedStackAccessCheck: false thread: r15 scratchForSafepointOnReturn: rcx config: jdk.graal.compiler.hotspot.GraalHotSpotVMConfig@4817c460 <|@ <|@
    end_IR
  end_block
  begin_block
    name "B1"
    from_bci -1
    to_bci -1
    predecessors "B0" 
    successors 
    xhandlers
    flags 
    probability 2355382605114769408
    begin_IR
      LIR
      nr   82  <|@ instruction [] = LABEL alignment: 0 numbPhis: 0 label: ? <|@ <|@
      nr   84  <|@ instruction NOP <|@ <|@
      nr   86  <|@ instruction NOP <|@ <|@
      nr   88  <|@ instruction NOP <|@ <|@
      nr   90  <|@ instruction NOP <|@ <|@
      nr   92  <|@ instruction NOP <|@ <|@
      nr   94  <|@ instruction NOP <|@ <|@
      nr   96  <|@ instruction NOP <|@ <|@
      nr   98  <|@ instruction MOV x: [r15|QWORD + 1156] y: -5907 size: DWORD <|@ <|@
      nr  100  <|@ instruction MOV x: [r15|QWORD + 1168] y: 20 size: QWORD <|@ <|@
      nr  102  <|@ st <@st|@live-base-pointers: []
java.lang.Math.clamp(Math.java:2214) [bci: 0]
locals: rsi|QWORD - rdx|DWORD rcx|DWORD 
>@ <|@ instruction DEOPT info [bci:0] <|@ <|@
    end_IR
  end_block
end_cfg
begin_bytecodes
     0: iload_2       
     1: iload_3       
     2: if_icmple     36
     5: new           #177        // java.lang.IllegalArgumentException
     8: dup           
     9: new           #179        // java.lang.StringBuilder
    12: dup           
    13: invokespecial #35         // java.lang.StringBuilder.<init>:()void
    16: iload_2       
    17: invokevirtual #36         // java.lang.StringBuilder.append:(int)java.lang.StringBuilder
    20: ldc           #186        // " > "
    22: invokevirtual #37         // java.lang.StringBuilder.append:(java.lang.String)java.lang.StringBuilder
    25: iload_3       
    26: invokevirtual #36         // java.lang.StringBuilder.append:(int)java.lang.StringBuilder
    29: invokevirtual #38         // java.lang.StringBuilder.toString:()java.lang.String
    32: invokespecial #39         // java.lang.IllegalArgumentException.<init>:(java.lang.String)void
    35: athrow        
    36: iload_3       
    37: i2l           
    38: lload_0       
    39: iload_2       
    40: i2l           
    41: invokestatic  #40         // max:(long, long)long
    44: invokestatic  #41         // min:(long, long)long
    47: l2i           
    48: ireturn       
   <|@
end_bytecodes
begin_cfg
  name "After ComputeCodeEmissionOrder"
  begin_block
    name "B0"
    from_bci -1
    to_bci -1
    predecessors 
    successors "B1" "B2" 
    xhandlers
    flags 
    probability 4607182418800017408
    begin_IR
      LIR
      nr    0  <|@ instruction [rsi|QWORD, rdx|DWORD, rcx|DWORD, rbp|QWORD] = LABEL alignment: 0 numbPhis: 0 label: ? <|@ <|@
      nr    2  <|@ instruction NOP <|@ <|@
      nr    4  <|@ instruction NOP <|@ <|@
      nr    6  <|@ instruction NOP <|@ <|@
      nr    8  <|@ instruction NOP <|@ <|@
      nr   10  <|@ instruction NOP <|@ <|@
      nr   12  <|@ instruction NOP <|@ <|@
      nr   14  <|@ instruction NOP <|@ <|@
      nr   16  <|@ instruction NOP <|@ <|@
      nr   18  <|@ instruction NOP <|@ <|@
      nr   20  <|@ instruction stack:16|QWORD = MOVE input: rbp|QWORD moveKind: QWORD <|@ <|@
      nr   22  <|@ instruction [] = HOTSPOTLOCKSTACK frameMapBuilder: jdk.graal.compiler.hotspot.amd64.AMD64HotSpotFrameMapBuilder@8113c20 slotKind: QWORD <|@ <|@
      nr   30  <|@ instruction CMPBRANCH (x: rdx|DWORD, y: rcx|DWORD) trueDestinationProbability: 0.0 condition: > trueDestination: B0 -> B1 falseDestination: B0 -> B2 size: DWORD <|@ <|@
    end_IR
  end_block
  begin_block
    name "B2"
    from_bci -1
    to_bci -1
    predecessors "B0" 
    successors 
    xhandlers
    flags 
    probability 4607182418800017408
    begin_IR
      LIR
      nr   32  <|@ instruction [] = LABEL alignment: 0 numbPhis: 0 label: ? <|@ <|@
      nr   34  <|@ instruction NOP <|@ <|@
      nr   36  <|@ instruction NOP <|@ <|@
      nr   38  <|@ instruction NOP <|@ <|@
      nr   40  <|@ instruction NOP <|@ <|@
      nr   42  <|@ instruction NOP <|@ <|@
      nr   44  <|@ instruction NOP <|@ <|@
      nr   46  <|@ instruction NOP <|@ <|@
      nr   48  <|@ instruction NOP <|@ <|@
      nr   50  <|@ instruction NOP <|@ <|@
      nr   52  <|@ instruction NOP <|@ <|@
      nr   54  <|@ instruction NOP <|@ <|@
      nr   56  <|@ instruction NOP <|@ <|@
      nr   58  <|@ instruction NOP <|@ <|@
      nr   60  <|@ instruction NOP <|@ <|@
      nr   62  <|@ instruction NOP <|@ <|@
      nr   64  <|@ instruction rax|QWORD = MOVSXD value: rdx|DWORD size: QWORD <|@ <|@
      nr   66  <|@ instruction CMP (x: rax|QWORD, y: rsi|QWORD) size: QWORD <|@ <|@
      nr   68  <|@ instruction rsi|QWORD = CMOVE (falseValue: rsi|QWORD, ~trueValue: rax|QWORD) condition: > <|@ <|@
      nr   70  <|@ instruction rax|QWORD = MOVSXD value: rcx|DWORD size: QWORD <|@ <|@
      nr   72  <|@ instruction CMP (x: rax|QWORD, y: rsi|QWORD) size: QWORD <|@ <|@
      nr   74  <|@ instruction rax|QWORD = CMOVE (falseValue: rax|QWORD, ~trueValue: rsi|QWORD) condition: > <|@ <|@
      nr   76  <|@ instruction rax|DWORD = MOV value: rax|QWORD size: DWORD <|@ <|@
      nr   80  <|@ instruction RETURN (savedRbp: stack:16|QWORD, value: rax|DWORD) isStub: false requiresReservedStackAccessCheck: false thread: r15 scratchForSafepointOnReturn: rcx config: jdk.graal.compiler.hotspot.GraalHotSpotVMConfig@4817c460 <|@ <|@
    end_IR
  end_block
  begin_block
    name "B1"
    from_bci -1
    to_bci -1
    predecessors "B0" 
    successors 
    xhandlers
    flags 
    probability 2355382605114769408
    begin_IR
      LIR
      nr   82  <|@ instruction [] = LABEL alignment: 0 numbPhis: 0 label: ? <|@ <|@
      nr   84  <|@ instruction NOP <|@ <|@
      nr   86  <|@ instruction NOP <|@ <|@
      nr   88  <|@ instruction NOP <|@ <|@
      nr   90  <|@ instruction NOP <|@ <|@
      nr   92  <|@ instruction NOP <|@ <|@
      nr   94  <|@ instruction NOP <|@ <|@
      nr   96  <|@ instruction NOP <|@ <|@
      nr   98  <|@ instruction MOV x: [r15|QWORD + 1156] y: -5907 size: DWORD <|@ <|@
      nr  100  <|@ instruction MOV x: [r15|QWORD + 1168] y: 20 size: QWORD <|@ <|@
      nr  102  <|@ st <@st|@live-base-pointers: []
java.lang.Math.clamp(Math.java:2214) [bci: 0]
locals: rsi|QWORD - rdx|DWORD rcx|DWORD 
>@ <|@ instruction DEOPT info [bci:0] <|@ <|@
    end_IR
  end_block
end_cfg
begin_bytecodes
     0: iload_2       
     1: iload_3       
     2: if_icmple     36
     5: new           #177        // java.lang.IllegalArgumentException
     8: dup           
     9: new           #179        // java.lang.StringBuilder
    12: dup           
    13: invokespecial #35         // java.lang.StringBuilder.<init>:()void
    16: iload_2       
    17: invokevirtual #36         // java.lang.StringBuilder.append:(int)java.lang.StringBuilder
    20: ldc           #186        // " > "
    22: invokevirtual #37         // java.lang.StringBuilder.append:(java.lang.String)java.lang.StringBuilder
    25: iload_3       
    26: invokevirtual #36         // java.lang.StringBuilder.append:(int)java.lang.StringBuilder
    29: invokevirtual #38         // java.lang.StringBuilder.toString:()java.lang.String
    32: invokespecial #39         // java.lang.IllegalArgumentException.<init>:(java.lang.String)void
    35: athrow        
    36: iload_3       
    37: i2l           
    38: lload_0       
    39: iload_2       
    40: i2l           
    41: invokestatic  #40         // max:(long, long)long
    44: invokestatic  #41         // min:(long, long)long
    47: l2i           
    48: ireturn       
   <|@
end_bytecodes
begin_cfg
  name "After StackMoveOptimization"
  begin_block
    name "B0"
    from_bci -1
    to_bci -1
    predecessors 
    successors "B1" "B2" 
    xhandlers
    flags 
    probability 4607182418800017408
    begin_IR
      LIR
      nr    0  <|@ instruction [rsi|QWORD, rdx|DWORD, rcx|DWORD, rbp|QWORD] = LABEL alignment: 0 numbPhis: 0 label: ? <|@ <|@
      nr    2  <|@ instruction NOP <|@ <|@
      nr    4  <|@ instruction NOP <|@ <|@
      nr    6  <|@ instruction NOP <|@ <|@
      nr    8  <|@ instruction NOP <|@ <|@
      nr   10  <|@ instruction NOP <|@ <|@
      nr   12  <|@ instruction NOP <|@ <|@
      nr   14  <|@ instruction NOP <|@ <|@
      nr   16  <|@ instruction NOP <|@ <|@
      nr   18  <|@ instruction NOP <|@ <|@
      nr   20  <|@ instruction stack:16|QWORD = MOVE input: rbp|QWORD moveKind: QWORD <|@ <|@
      nr   22  <|@ instruction [] = HOTSPOTLOCKSTACK frameMapBuilder: jdk.graal.compiler.hotspot.amd64.AMD64HotSpotFrameMapBuilder@8113c20 slotKind: QWORD <|@ <|@
      nr   30  <|@ instruction CMPBRANCH (x: rdx|DWORD, y: rcx|DWORD) trueDestinationProbability: 0.0 condition: > trueDestination: B0 -> B1 falseDestination: B0 -> B2 size: DWORD <|@ <|@
    end_IR
  end_block
  begin_block
    name "B2"
    from_bci -1
    to_bci -1
    predecessors "B0" 
    successors 
    xhandlers
    flags 
    probability 4607182418800017408
    begin_IR
      LIR
      nr   32  <|@ instruction [] = LABEL alignment: 0 numbPhis: 0 label: ? <|@ <|@
      nr   34  <|@ instruction NOP <|@ <|@
      nr   36  <|@ instruction NOP <|@ <|@
      nr   38  <|@ instruction NOP <|@ <|@
      nr   40  <|@ instruction NOP <|@ <|@
      nr   42  <|@ instruction NOP <|@ <|@
      nr   44  <|@ instruction NOP <|@ <|@
      nr   46  <|@ instruction NOP <|@ <|@
      nr   48  <|@ instruction NOP <|@ <|@
      nr   50  <|@ instruction NOP <|@ <|@
      nr   52  <|@ instruction NOP <|@ <|@
      nr   54  <|@ instruction NOP <|@ <|@
      nr   56  <|@ instruction NOP <|@ <|@
      nr   58  <|@ instruction NOP <|@ <|@
      nr   60  <|@ instruction NOP <|@ <|@
      nr   62  <|@ instruction NOP <|@ <|@
      nr   64  <|@ instruction rax|QWORD = MOVSXD value: rdx|DWORD size: QWORD <|@ <|@
      nr   66  <|@ instruction CMP (x: rax|QWORD, y: rsi|QWORD) size: QWORD <|@ <|@
      nr   68  <|@ instruction rsi|QWORD = CMOVE (falseValue: rsi|QWORD, ~trueValue: rax|QWORD) condition: > <|@ <|@
      nr   70  <|@ instruction rax|QWORD = MOVSXD value: rcx|DWORD size: QWORD <|@ <|@
      nr   72  <|@ instruction CMP (x: rax|QWORD, y: rsi|QWORD) size: QWORD <|@ <|@
      nr   74  <|@ instruction rax|QWORD = CMOVE (falseValue: rax|QWORD, ~trueValue: rsi|QWORD) condition: > <|@ <|@
      nr   76  <|@ instruction rax|DWORD = MOV value: rax|QWORD size: DWORD <|@ <|@
      nr   80  <|@ instruction RETURN (savedRbp: stack:16|QWORD, value: rax|DWORD) isStub: false requiresReservedStackAccessCheck: false thread: r15 scratchForSafepointOnReturn: rcx config: jdk.graal.compiler.hotspot.GraalHotSpotVMConfig@4817c460 <|@ <|@
    end_IR
  end_block
  begin_block
    name "B1"
    from_bci -1
    to_bci -1
    predecessors "B0" 
    successors 
    xhandlers
    flags 
    probability 2355382605114769408
    begin_IR
      LIR
      nr   82  <|@ instruction [] = LABEL alignment: 0 numbPhis: 0 label: ? <|@ <|@
      nr   84  <|@ instruction NOP <|@ <|@
      nr   86  <|@ instruction NOP <|@ <|@
      nr   88  <|@ instruction NOP <|@ <|@
      nr   90  <|@ instruction NOP <|@ <|@
      nr   92  <|@ instruction NOP <|@ <|@
      nr   94  <|@ instruction NOP <|@ <|@
      nr   96  <|@ instruction NOP <|@ <|@
      nr   98  <|@ instruction MOV x: [r15|QWORD + 1156] y: -5907 size: DWORD <|@ <|@
      nr  100  <|@ instruction MOV x: [r15|QWORD + 1168] y: 20 size: QWORD <|@ <|@
      nr  102  <|@ st <@st|@live-base-pointers: []
java.lang.Math.clamp(Math.java:2214) [bci: 0]
locals: rsi|QWORD - rdx|DWORD rcx|DWORD 
>@ <|@ instruction DEOPT info [bci:0] <|@ <|@
    end_IR
  end_block
end_cfg
begin_bytecodes
     0: iload_2       
     1: iload_3       
     2: if_icmple     36
     5: new           #177        // java.lang.IllegalArgumentException
     8: dup           
     9: new           #179        // java.lang.StringBuilder
    12: dup           
    13: invokespecial #35         // java.lang.StringBuilder.<init>:()void
    16: iload_2       
    17: invokevirtual #36         // java.lang.StringBuilder.append:(int)java.lang.StringBuilder
    20: ldc           #186        // " > "
    22: invokevirtual #37         // java.lang.StringBuilder.append:(java.lang.String)java.lang.StringBuilder
    25: iload_3       
    26: invokevirtual #36         // java.lang.StringBuilder.append:(int)java.lang.StringBuilder
    29: invokevirtual #38         // java.lang.StringBuilder.toString:()java.lang.String
    32: invokespecial #39         // java.lang.IllegalArgumentException.<init>:(java.lang.String)void
    35: athrow        
    36: iload_3       
    37: i2l           
    38: lload_0       
    39: iload_2       
    40: i2l           
    41: invokestatic  #40         // max:(long, long)long
    44: invokestatic  #41         // min:(long, long)long
    47: l2i           
    48: ireturn       
   <|@
end_bytecodes
begin_cfg
  name "After PostAllocationOptimizationStage"
  begin_block
    name "B0"
    from_bci -1
    to_bci -1
    predecessors 
    successors "B1" "B2" 
    xhandlers
    flags 
    probability 4607182418800017408
    begin_IR
      LIR
      nr    0  <|@ instruction [rsi|QWORD, rdx|DWORD, rcx|DWORD, rbp|QWORD] = LABEL alignment: 0 numbPhis: 0 label: ? <|@ <|@
      nr    2  <|@ instruction NOP <|@ <|@
      nr    4  <|@ instruction NOP <|@ <|@
      nr    6  <|@ instruction NOP <|@ <|@
      nr    8  <|@ instruction NOP <|@ <|@
      nr   10  <|@ instruction NOP <|@ <|@
      nr   12  <|@ instruction NOP <|@ <|@
      nr   14  <|@ instruction NOP <|@ <|@
      nr   16  <|@ instruction NOP <|@ <|@
      nr   18  <|@ instruction NOP <|@ <|@
      nr   20  <|@ instruction stack:16|QWORD = MOVE input: rbp|QWORD moveKind: QWORD <|@ <|@
      nr   22  <|@ instruction [] = HOTSPOTLOCKSTACK frameMapBuilder: jdk.graal.compiler.hotspot.amd64.AMD64HotSpotFrameMapBuilder@8113c20 slotKind: QWORD <|@ <|@
      nr   30  <|@ instruction CMPBRANCH (x: rdx|DWORD, y: rcx|DWORD) trueDestinationProbability: 0.0 condition: > trueDestination: B0 -> B1 falseDestination: B0 -> B2 size: DWORD <|@ <|@
    end_IR
  end_block
  begin_block
    name "B2"
    from_bci -1
    to_bci -1
    predecessors "B0" 
    successors 
    xhandlers
    flags 
    probability 4607182418800017408
    begin_IR
      LIR
      nr   32  <|@ instruction [] = LABEL alignment: 0 numbPhis: 0 label: ? <|@ <|@
      nr   34  <|@ instruction NOP <|@ <|@
      nr   36  <|@ instruction NOP <|@ <|@
      nr   38  <|@ instruction NOP <|@ <|@
      nr   40  <|@ instruction NOP <|@ <|@
      nr   42  <|@ instruction NOP <|@ <|@
      nr   44  <|@ instruction NOP <|@ <|@
      nr   46  <|@ instruction NOP <|@ <|@
      nr   48  <|@ instruction NOP <|@ <|@
      nr   50  <|@ instruction NOP <|@ <|@
      nr   52  <|@ instruction NOP <|@ <|@
      nr   54  <|@ instruction NOP <|@ <|@
      nr   56  <|@ instruction NOP <|@ <|@
      nr   58  <|@ instruction NOP <|@ <|@
      nr   60  <|@ instruction NOP <|@ <|@
      nr   62  <|@ instruction NOP <|@ <|@
      nr   64  <|@ instruction rax|QWORD = MOVSXD value: rdx|DWORD size: QWORD <|@ <|@
      nr   66  <|@ instruction CMP (x: rax|QWORD, y: rsi|QWORD) size: QWORD <|@ <|@
      nr   68  <|@ instruction rsi|QWORD = CMOVE (falseValue: rsi|QWORD, ~trueValue: rax|QWORD) condition: > <|@ <|@
      nr   70  <|@ instruction rax|QWORD = MOVSXD value: rcx|DWORD size: QWORD <|@ <|@
      nr   72  <|@ instruction CMP (x: rax|QWORD, y: rsi|QWORD) size: QWORD <|@ <|@
      nr   74  <|@ instruction rax|QWORD = CMOVE (falseValue: rax|QWORD, ~trueValue: rsi|QWORD) condition: > <|@ <|@
      nr   76  <|@ instruction rax|DWORD = MOV value: rax|QWORD size: DWORD <|@ <|@
      nr   80  <|@ instruction RETURN (savedRbp: stack:16|QWORD, value: rax|DWORD) isStub: false requiresReservedStackAccessCheck: false thread: r15 scratchForSafepointOnReturn: rcx config: jdk.graal.compiler.hotspot.GraalHotSpotVMConfig@4817c460 <|@ <|@
    end_IR
  end_block
  begin_block
    name "B1"
    from_bci -1
    to_bci -1
    predecessors "B0" 
    successors 
    xhandlers
    flags 
    probability 2355382605114769408
    begin_IR
      LIR
      nr   82  <|@ instruction [] = LABEL alignment: 0 numbPhis: 0 label: ? <|@ <|@
      nr   84  <|@ instruction NOP <|@ <|@
      nr   86  <|@ instruction NOP <|@ <|@
      nr   88  <|@ instruction NOP <|@ <|@
      nr   90  <|@ instruction NOP <|@ <|@
      nr   92  <|@ instruction NOP <|@ <|@
      nr   94  <|@ instruction NOP <|@ <|@
      nr   96  <|@ instruction NOP <|@ <|@
      nr   98  <|@ instruction MOV x: [r15|QWORD + 1156] y: -5907 size: DWORD <|@ <|@
      nr  100  <|@ instruction MOV x: [r15|QWORD + 1168] y: 20 size: QWORD <|@ <|@
      nr  102  <|@ st <@st|@live-base-pointers: []
java.lang.Math.clamp(Math.java:2214) [bci: 0]
locals: rsi|QWORD - rdx|DWORD rcx|DWORD 
>@ <|@ instruction DEOPT info [bci:0] <|@ <|@
    end_IR
  end_block
end_cfg
begin_bytecodes
     0: iload_2       
     1: iload_3       
     2: if_icmple     36
     5: new           #177        // java.lang.IllegalArgumentException
     8: dup           
     9: new           #179        // java.lang.StringBuilder
    12: dup           
    13: invokespecial #35         // java.lang.StringBuilder.<init>:()void
    16: iload_2       
    17: invokevirtual #36         // java.lang.StringBuilder.append:(int)java.lang.StringBuilder
    20: ldc           #186        // " > "
    22: invokevirtual #37         // java.lang.StringBuilder.append:(java.lang.String)java.lang.StringBuilder
    25: iload_3       
    26: invokevirtual #36         // java.lang.StringBuilder.append:(int)java.lang.StringBuilder
    29: invokevirtual #38         // java.lang.StringBuilder.toString:()java.lang.String
    32: invokespecial #39         // java.lang.IllegalArgumentException.<init>:(java.lang.String)void
    35: athrow        
    36: iload_3       
    37: i2l           
    38: lload_0       
    39: iload_2       
    40: i2l           
    41: invokestatic  #40         // max:(long, long)long
    44: invokestatic  #41         // min:(long, long)long
    47: l2i           
    48: ireturn       
   <|@
end_bytecodes
begin_cfg
  name "After LocationMarker"
  begin_block
    name "B0"
    from_bci -1
    to_bci -1
    predecessors 
    successors "B1" "B2" 
    xhandlers
    flags 
    probability 4607182418800017408
    begin_IR
      LIR
      nr    0  <|@ instruction [rsi|QWORD, rdx|DWORD, rcx|DWORD, rbp|QWORD] = LABEL alignment: 0 numbPhis: 0 label: ? <|@ <|@
      nr    2  <|@ instruction NOP <|@ <|@
      nr    4  <|@ instruction NOP <|@ <|@
      nr    6  <|@ instruction NOP <|@ <|@
      nr    8  <|@ instruction NOP <|@ <|@
      nr   10  <|@ instruction NOP <|@ <|@
      nr   12  <|@ instruction NOP <|@ <|@
      nr   14  <|@ instruction NOP <|@ <|@
      nr   16  <|@ instruction NOP <|@ <|@
      nr   18  <|@ instruction NOP <|@ <|@
      nr   20  <|@ instruction stack:16|QWORD = MOVE input: rbp|QWORD moveKind: QWORD <|@ <|@
      nr   22  <|@ instruction [] = HOTSPOTLOCKSTACK frameMapBuilder: jdk.graal.compiler.hotspot.amd64.AMD64HotSpotFrameMapBuilder@8113c20 slotKind: QWORD <|@ <|@
      nr   30  <|@ instruction CMPBRANCH (x: rdx|DWORD, y: rcx|DWORD) trueDestinationProbability: 0.0 condition: > trueDestination: B0 -> B1 falseDestination: B0 -> B2 size: DWORD <|@ <|@
    end_IR
  end_block
  begin_block
    name "B2"
    from_bci -1
    to_bci -1
    predecessors "B0" 
    successors 
    xhandlers
    flags 
    probability 4607182418800017408
    begin_IR
      LIR
      nr   32  <|@ instruction [] = LABEL alignment: 0 numbPhis: 0 label: ? <|@ <|@
      nr   34  <|@ instruction NOP <|@ <|@
      nr   36  <|@ instruction NOP <|@ <|@
      nr   38  <|@ instruction NOP <|@ <|@
      nr   40  <|@ instruction NOP <|@ <|@
      nr   42  <|@ instruction NOP <|@ <|@
      nr   44  <|@ instruction NOP <|@ <|@
      nr   46  <|@ instruction NOP <|@ <|@
      nr   48  <|@ instruction NOP <|@ <|@
      nr   50  <|@ instruction NOP <|@ <|@
      nr   52  <|@ instruction NOP <|@ <|@
      nr   54  <|@ instruction NOP <|@ <|@
      nr   56  <|@ instruction NOP <|@ <|@
      nr   58  <|@ instruction NOP <|@ <|@
      nr   60  <|@ instruction NOP <|@ <|@
      nr   62  <|@ instruction NOP <|@ <|@
      nr   64  <|@ instruction rax|QWORD = MOVSXD value: rdx|DWORD size: QWORD <|@ <|@
      nr   66  <|@ instruction CMP (x: rax|QWORD, y: rsi|QWORD) size: QWORD <|@ <|@
      nr   68  <|@ instruction rsi|QWORD = CMOVE (falseValue: rsi|QWORD, ~trueValue: rax|QWORD) condition: > <|@ <|@
      nr   70  <|@ instruction rax|QWORD = MOVSXD value: rcx|DWORD size: QWORD <|@ <|@
      nr   72  <|@ instruction CMP (x: rax|QWORD, y: rsi|QWORD) size: QWORD <|@ <|@
      nr   74  <|@ instruction rax|QWORD = CMOVE (falseValue: rax|QWORD, ~trueValue: rsi|QWORD) condition: > <|@ <|@
      nr   76  <|@ instruction rax|DWORD = MOV value: rax|QWORD size: DWORD <|@ <|@
      nr   80  <|@ instruction RETURN (savedRbp: stack:16|QWORD, value: rax|DWORD) isStub: false requiresReservedStackAccessCheck: false thread: r15 scratchForSafepointOnReturn: rcx config: jdk.graal.compiler.hotspot.GraalHotSpotVMConfig@4817c460 <|@ <|@
    end_IR
  end_block
  begin_block
    name "B1"
    from_bci -1
    to_bci -1
    predecessors "B0" 
    successors 
    xhandlers
    flags 
    probability 2355382605114769408
    begin_IR
      LIR
      nr   82  <|@ instruction [] = LABEL alignment: 0 numbPhis: 0 label: ? <|@ <|@
      nr   84  <|@ instruction NOP <|@ <|@
      nr   86  <|@ instruction NOP <|@ <|@
      nr   88  <|@ instruction NOP <|@ <|@
      nr   90  <|@ instruction NOP <|@ <|@
      nr   92  <|@ instruction NOP <|@ <|@
      nr   94  <|@ instruction NOP <|@ <|@
      nr   96  <|@ instruction NOP <|@ <|@
      nr   98  <|@ instruction MOV x: [r15|QWORD + 1156] y: -5907 size: DWORD <|@ <|@
      nr  100  <|@ instruction MOV x: [r15|QWORD + 1168] y: 20 size: QWORD <|@ <|@
      nr  102  <|@ st <@st|@reference-map: []
live-base-pointers: []
java.lang.Math.clamp(Math.java:2214) [bci: 0]
locals: rsi|QWORD - rdx|DWORD rcx|DWORD 
>@ <|@ instruction DEOPT info [bci:0] <|@ <|@
    end_IR
  end_block
end_cfg
begin_bytecodes
     0: iload_2       
     1: iload_3       
     2: if_icmple     36
     5: new           #177        // java.lang.IllegalArgumentException
     8: dup           
     9: new           #179        // java.lang.StringBuilder
    12: dup           
    13: invokespecial #35         // java.lang.StringBuilder.<init>:()void
    16: iload_2       
    17: invokevirtual #36         // java.lang.StringBuilder.append:(int)java.lang.StringBuilder
    20: ldc           #186        // " > "
    22: invokevirtual #37         // java.lang.StringBuilder.append:(java.lang.String)java.lang.StringBuilder
    25: iload_3       
    26: invokevirtual #36         // java.lang.StringBuilder.append:(int)java.lang.StringBuilder
    29: invokevirtual #38         // java.lang.StringBuilder.toString:()java.lang.String
    32: invokespecial #39         // java.lang.IllegalArgumentException.<init>:(java.lang.String)void
    35: athrow        
    36: iload_3       
    37: i2l           
    38: lload_0       
    39: iload_2       
    40: i2l           
    41: invokestatic  #40         // max:(long, long)long
    44: invokestatic  #41         // min:(long, long)long
    47: l2i           
    48: ireturn       
   <|@
end_bytecodes
begin_cfg
  name "After FinalCodeAnalysisStage"
  begin_block
    name "B0"
    from_bci -1
    to_bci -1
    predecessors 
    successors "B1" "B2" 
    xhandlers
    flags 
    probability 4607182418800017408
    begin_IR
      LIR
      nr    0  <|@ instruction [rsi|QWORD, rdx|DWORD, rcx|DWORD, rbp|QWORD] = LABEL alignment: 0 numbPhis: 0 label: ? <|@ <|@
      nr    2  <|@ instruction NOP <|@ <|@
      nr    4  <|@ instruction NOP <|@ <|@
      nr    6  <|@ instruction NOP <|@ <|@
      nr    8  <|@ instruction NOP <|@ <|@
      nr   10  <|@ instruction NOP <|@ <|@
      nr   12  <|@ instruction NOP <|@ <|@
      nr   14  <|@ instruction NOP <|@ <|@
      nr   16  <|@ instruction NOP <|@ <|@
      nr   18  <|@ instruction NOP <|@ <|@
      nr   20  <|@ instruction stack:16|QWORD = MOVE input: rbp|QWORD moveKind: QWORD <|@ <|@
      nr   22  <|@ instruction [] = HOTSPOTLOCKSTACK frameMapBuilder: jdk.graal.compiler.hotspot.amd64.AMD64HotSpotFrameMapBuilder@8113c20 slotKind: QWORD <|@ <|@
      nr   30  <|@ instruction CMPBRANCH (x: rdx|DWORD, y: rcx|DWORD) trueDestinationProbability: 0.0 condition: > trueDestination: B0 -> B1 falseDestination: B0 -> B2 size: DWORD <|@ <|@
    end_IR
  end_block
  begin_block
    name "B2"
    from_bci -1
    to_bci -1
    predecessors "B0" 
    successors 
    xhandlers
    flags 
    probability 4607182418800017408
    begin_IR
      LIR
      nr   32  <|@ instruction [] = LABEL alignment: 0 numbPhis: 0 label: ? <|@ <|@
      nr   34  <|@ instruction NOP <|@ <|@
      nr   36  <|@ instruction NOP <|@ <|@
      nr   38  <|@ instruction NOP <|@ <|@
      nr   40  <|@ instruction NOP <|@ <|@
      nr   42  <|@ instruction NOP <|@ <|@
      nr   44  <|@ instruction NOP <|@ <|@
      nr   46  <|@ instruction NOP <|@ <|@
      nr   48  <|@ instruction NOP <|@ <|@
      nr   50  <|@ instruction NOP <|@ <|@
      nr   52  <|@ instruction NOP <|@ <|@
      nr   54  <|@ instruction NOP <|@ <|@
      nr   56  <|@ instruction NOP <|@ <|@
      nr   58  <|@ instruction NOP <|@ <|@
      nr   60  <|@ instruction NOP <|@ <|@
      nr   62  <|@ instruction NOP <|@ <|@
      nr   64  <|@ instruction rax|QWORD = MOVSXD value: rdx|DWORD size: QWORD <|@ <|@
      nr   66  <|@ instruction CMP (x: rax|QWORD, y: rsi|QWORD) size: QWORD <|@ <|@
      nr   68  <|@ instruction rsi|QWORD = CMOVE (falseValue: rsi|QWORD, ~trueValue: rax|QWORD) condition: > <|@ <|@
      nr   70  <|@ instruction rax|QWORD = MOVSXD value: rcx|DWORD size: QWORD <|@ <|@
      nr   72  <|@ instruction CMP (x: rax|QWORD, y: rsi|QWORD) size: QWORD <|@ <|@
      nr   74  <|@ instruction rax|QWORD = CMOVE (falseValue: rax|QWORD, ~trueValue: rsi|QWORD) condition: > <|@ <|@
      nr   76  <|@ instruction rax|DWORD = MOV value: rax|QWORD size: DWORD <|@ <|@
      nr   80  <|@ instruction RETURN (savedRbp: stack:16|QWORD, value: rax|DWORD) isStub: false requiresReservedStackAccessCheck: false thread: r15 scratchForSafepointOnReturn: rcx config: jdk.graal.compiler.hotspot.GraalHotSpotVMConfig@4817c460 <|@ <|@
    end_IR
  end_block
  begin_block
    name "B1"
    from_bci -1
    to_bci -1
    predecessors "B0" 
    successors 
    xhandlers
    flags 
    probability 2355382605114769408
    begin_IR
      LIR
      nr   82  <|@ instruction [] = LABEL alignment: 0 numbPhis: 0 label: ? <|@ <|@
      nr   84  <|@ instruction NOP <|@ <|@
      nr   86  <|@ instruction NOP <|@ <|@
      nr   88  <|@ instruction NOP <|@ <|@
      nr   90  <|@ instruction NOP <|@ <|@
      nr   92  <|@ instruction NOP <|@ <|@
      nr   94  <|@ instruction NOP <|@ <|@
      nr   96  <|@ instruction NOP <|@ <|@
      nr   98  <|@ instruction MOV x: [r15|QWORD + 1156] y: -5907 size: DWORD <|@ <|@
      nr  100  <|@ instruction MOV x: [r15|QWORD + 1168] y: 20 size: QWORD <|@ <|@
      nr  102  <|@ st <@st|@reference-map: []
live-base-pointers: []
java.lang.Math.clamp(Math.java:2214) [bci: 0]
locals: rsi|QWORD - rdx|DWORD rcx|DWORD 
>@ <|@ instruction DEOPT info [bci:0] <|@ <|@
    end_IR
  end_block
end_cfg
begin_bytecodes
     0: iload_2       
     1: iload_3       
     2: if_icmple     36
     5: new           #177        // java.lang.IllegalArgumentException
     8: dup           
     9: new           #179        // java.lang.StringBuilder
    12: dup           
    13: invokespecial #35         // java.lang.StringBuilder.<init>:()void
    16: iload_2       
    17: invokevirtual #36         // java.lang.StringBuilder.append:(int)java.lang.StringBuilder
    20: ldc           #186        // " > "
    22: invokevirtual #37         // java.lang.StringBuilder.append:(java.lang.String)java.lang.StringBuilder
    25: iload_3       
    26: invokevirtual #36         // java.lang.StringBuilder.append:(int)java.lang.StringBuilder
    29: invokevirtual #38         // java.lang.StringBuilder.toString:()java.lang.String
    32: invokespecial #39         // java.lang.IllegalArgumentException.<init>:(java.lang.String)void
    35: athrow        
    36: iload_3       
    37: i2l           
    38: lload_0       
    39: iload_2       
    40: i2l           
    41: invokestatic  #40         // max:(long, long)long
    44: invokestatic  #41         // min:(long, long)long
    47: l2i           
    48: ireturn       
   <|@
end_bytecodes
begin_cfg
  name "After code generation"
end_cfg
begin_nmethod
  <<<HexCodeFile
  Platform AMD64 64  <||@
  HexCode 0 89842400c0feff4883ec189041817f20000000000f857c00000090909090909090909048896c24103bd10f8f3c0000009090909090909090909090909090904863c2483bc6480f4ff04863c1483bc6480f4fc68bc0488b6c24104883c418493ba7500400000f873b000000c39090909090909041c78784040000ede8ffff49c7879004000014000000e8000000000f1f84000000000048896c2410e800000000e975fffffff4488d0db1ffffff49898f68040000e947fffffff4e800000000f4e800000000f4  <||@
  Comment 0 [stack overflow check]  <||@
  Comment 0 VERIFIED_ENTRY  <||@
  Comment 12 FRAME_COMPLETE  <||@
  Comment 12 ENTRY_BARRIER_PATCH  <||@
  Comment 26 block B0 null  <||@
  Comment 26 0 [rsi|QWORD, rdx|DWORD, rcx|DWORD, rbp|QWORD] = LABEL alignment: 0 numbPhis: 0 label: ?  <||@
  Comment 26 2 NOP  <||@
  Comment 27 4 NOP  <||@
  Comment 28 6 NOP  <||@
  Comment 29 8 NOP  <||@
  Comment 30 10 NOP  <||@
  Comment 31 12 NOP  <||@
  Comment 32 14 NOP  <||@
  Comment 33 16 NOP  <||@
  Comment 34 18 NOP  <||@
  Comment 35 20 stack:16|QWORD = MOVE input: rbp|QWORD moveKind: QWORD  <||@
  Comment 40 22 [] = HOTSPOTLOCKSTACK frameMapBuilder: jdk.graal.compiler.hotspot.amd64.AMD64HotSpotFrameMapBuilder@8113c20 slotKind: QWORD  <||@
  Comment 40 30 CMPBRANCH (x: rdx|DWORD, y: rcx|DWORD) trueDestinationProbability: 0.0 condition: > trueDestination: B0 -> B1 falseDestination: B0 -> B2 size: DWORD  <||@
  Comment 48 block B2 null  <||@
  Comment 48 32 [] = LABEL alignment: 0 numbPhis: 0 label: ?  <||@
  Comment 48 34 NOP  <||@
  Comment 49 36 NOP  <||@
  Comment 50 38 NOP  <||@
  Comment 51 40 NOP  <||@
  Comment 52 42 NOP  <||@
  Comment 53 44 NOP  <||@
  Comment 54 46 NOP  <||@
  Comment 55 48 NOP  <||@
  Comment 56 50 NOP  <||@
  Comment 57 52 NOP  <||@
  Comment 58 54 NOP  <||@
  Comment 59 56 NOP  <||@
  Comment 60 58 NOP  <||@
  Comment 61 60 NOP  <||@
  Comment 62 62 NOP  <||@
  Comment 63 64 rax|QWORD = MOVSXD value: rdx|DWORD size: QWORD  <||@
  Comment 66 66 CMP (x: rax|QWORD, y: rsi|QWORD) size: QWORD  <||@
  Comment 69 68 rsi|QWORD = CMOVE (falseValue: rsi|QWORD, ~trueValue: rax|QWORD) condition: >  <||@
  Comment 73 70 rax|QWORD = MOVSXD value: rcx|DWORD size: QWORD  <||@
  Comment 76 72 CMP (x: rax|QWORD, y: rsi|QWORD) size: QWORD  <||@
  Comment 79 74 rax|QWORD = CMOVE (falseValue: rax|QWORD, ~trueValue: rsi|QWORD) condition: >  <||@
  Comment 83 76 rax|DWORD = MOV value: rax|QWORD size: DWORD  <||@
  Comment 85 80 RETURN (savedRbp: stack:16|QWORD, value: rax|DWORD) isStub: false requiresReservedStackAccessCheck: false thread: r15 scratchForSafepointOnReturn: rcx config: jdk.graal.compiler.hotspot.GraalHotSpotVMConfig@4817c460  <||@
  Comment 94 POLL_RETURN_FAR  <||@
  Comment 108 block B1 null  <||@
  Comment 108 82 [] = LABEL alignment: 0 numbPhis: 0 label: ?  <||@
  Comment 108 84 NOP  <||@
  Comment 109 86 NOP  <||@
  Comment 110 88 NOP  <||@
  Comment 111 90 NOP  <||@
  Comment 112 92 NOP  <||@
  Comment 113 94 NOP  <||@
  Comment 114 96 NOP  <||@
  Comment 115 98 MOV x: [r15|QWORD + 1156] y: -5907 size: DWORD  <||@
  Comment 126 100 MOV x: [r15|QWORD + 1168] y: 20 size: QWORD  <||@
  Comment 137 102 DEOPT info [bci:0]  <||@
  Comment 137 {Field[name=CompilerToVM::Data::SharedRuntime_deopt_blob_uncommon_trap, type=address, offset=0, address=0x7f78b20335a8, value=140155947626874]:0x7f789978b17a}  <||@
  Comment 142 []at java.lang.Math.clamp(Math.java:2214) [bci: 0, duringCall: false, rethrow: false]
              |0          |1  |2          |3         
     locals:  |rsi|QWORD  |-  |rdx|DWORD  |rcx|DWORD   <||@
  Comment 155 {Field[name=CompilerToVM::Data::nmethod_entry_barrier, type=address, offset=0, address=0x7f78b2033598, value=140155947495968]:0x7f789976b220}  <||@
  Comment 180 {Field[name=CompilerToVM::Data::SharedRuntime_polling_page_return_handler, type=address, offset=0, address=0x7f78b20335a0, value=140155947630592]:0x7f789978c000}  <||@
  Comment 186 {Stub<ExceptionHandlerStub.exceptionHandler>@0x7f78998c5300:CallingConvention[rax|QWORD[.], rdx|QWORD]:CallingConvention[rax|QWORD[.], rdx|QWORD]; temps=rdi|ILLEGAL,xmm14|ILLEGAL,xmm15|ILLEGAL,xmm12|ILLEGAL,xmm13|ILLEGAL,xmm10|ILLEGAL,xmm11|ILLEGAL,xmm7|ILLEGAL,xmm8|ILLEGAL,xmm9|ILLEGAL,xmm0|ILLEGAL,xmm1|ILLEGAL,xmm2|ILLEGAL,xmm3|ILLEGAL,xmm4|ILLEGAL,xmm5|ILLEGAL,xmm6|ILLEGAL,rax|ILLEGAL,rcx|ILLEGAL,rdx|ILLEGAL,rsi|ILLEGAL,r8|ILLEGAL,r9|ILLEGAL,r10|ILLEGAL,r11|ILLEGAL}  <||@
  Comment 186 EXCEPTION_HANDLER_ENTRY  <||@
  Comment 192 {Field[name=CompilerToVM::Data::SharedRuntime_deopt_blob_unpack, type=address, offset=0, address=0x7f78b20335b8, value=140155947626272]:0x7f789978af20}  <||@
  Comment 192 DEOPT_HANDLER_ENTRY  <||@
  HexCodeFile>>> <|@
end_nmethod
begin_compilation
  name " HotSpotCompilation-3682[java.lang.Math.clamp(long, int, int)]"
  method "HotSpotCompilation-3682[java.lang.Math.clamp(long, int, int)]"
  date 1724269726916
end_compilation
begin_cfg
  name "After code installation"
end_cfg
begin_nmethod
  <<<HexCodeFile
  Platform AMD64 64  <||@
  HexCode 7f789ad3ee00 89842400c0feff4883ec189041817f20000000000f857c00000090909090909090909048896c24103bd10f8f3c0000009090909090909090909090909090904863c2483bc6480f4ff04863c1483bc6480f4fc68bc0488b6c24104883c418493ba7500400000f873b000000c39090909090909041c78784040000ede8ffff49c7879004000014000000e8ecc2a4fe0f1f84000000000048896c2410e880c3a2fee975fffffff4488d0db1ffffff49898f68040000e947d1a4fef4e84164b8fef4e85bc0a4fef4f4f4  <||@
  Comment 0 [stack overflow check]  <||@
  Comment 0 VERIFIED_ENTRY  <||@
  Comment 12 FRAME_COMPLETE  <||@
  Comment 12 ENTRY_BARRIER_PATCH  <||@
  Comment 26 block B0 null  <||@
  Comment 26 0 [rsi|QWORD, rdx|DWORD, rcx|DWORD, rbp|QWORD] = LABEL alignment: 0 numbPhis: 0 label: ?  <||@
  Comment 26 2 NOP  <||@
  Comment 27 4 NOP  <||@
  Comment 28 6 NOP  <||@
  Comment 29 8 NOP  <||@
  Comment 30 10 NOP  <||@
  Comment 31 12 NOP  <||@
  Comment 32 14 NOP  <||@
  Comment 33 16 NOP  <||@
  Comment 34 18 NOP  <||@
  Comment 35 20 stack:16|QWORD = MOVE input: rbp|QWORD moveKind: QWORD  <||@
  Comment 40 22 [] = HOTSPOTLOCKSTACK frameMapBuilder: jdk.graal.compiler.hotspot.amd64.AMD64HotSpotFrameMapBuilder@8113c20 slotKind: QWORD  <||@
  Comment 40 30 CMPBRANCH (x: rdx|DWORD, y: rcx|DWORD) trueDestinationProbability: 0.0 condition: > trueDestination: B0 -> B1 falseDestination: B0 -> B2 size: DWORD  <||@
  Comment 48 block B2 null  <||@
  Comment 48 32 [] = LABEL alignment: 0 numbPhis: 0 label: ?  <||@
  Comment 48 34 NOP  <||@
  Comment 49 36 NOP  <||@
  Comment 50 38 NOP  <||@
  Comment 51 40 NOP  <||@
  Comment 52 42 NOP  <||@
  Comment 53 44 NOP  <||@
  Comment 54 46 NOP  <||@
  Comment 55 48 NOP  <||@
  Comment 56 50 NOP  <||@
  Comment 57 52 NOP  <||@
  Comment 58 54 NOP  <||@
  Comment 59 56 NOP  <||@
  Comment 60 58 NOP  <||@
  Comment 61 60 NOP  <||@
  Comment 62 62 NOP  <||@
  Comment 63 64 rax|QWORD = MOVSXD value: rdx|DWORD size: QWORD  <||@
  Comment 66 66 CMP (x: rax|QWORD, y: rsi|QWORD) size: QWORD  <||@
  Comment 69 68 rsi|QWORD = CMOVE (falseValue: rsi|QWORD, ~trueValue: rax|QWORD) condition: >  <||@
  Comment 73 70 rax|QWORD = MOVSXD value: rcx|DWORD size: QWORD  <||@
  Comment 76 72 CMP (x: rax|QWORD, y: rsi|QWORD) size: QWORD  <||@
  Comment 79 74 rax|QWORD = CMOVE (falseValue: rax|QWORD, ~trueValue: rsi|QWORD) condition: >  <||@
  Comment 83 76 rax|DWORD = MOV value: rax|QWORD size: DWORD  <||@
  Comment 85 80 RETURN (savedRbp: stack:16|QWORD, value: rax|DWORD) isStub: false requiresReservedStackAccessCheck: false thread: r15 scratchForSafepointOnReturn: rcx config: jdk.graal.compiler.hotspot.GraalHotSpotVMConfig@4817c460  <||@
  Comment 94 POLL_RETURN_FAR  <||@
  Comment 108 block B1 null  <||@
  Comment 108 82 [] = LABEL alignment: 0 numbPhis: 0 label: ?  <||@
  Comment 108 84 NOP  <||@
  Comment 109 86 NOP  <||@
  Comment 110 88 NOP  <||@
  Comment 111 90 NOP  <||@
  Comment 112 92 NOP  <||@
  Comment 113 94 NOP  <||@
  Comment 114 96 NOP  <||@
  Comment 115 98 MOV x: [r15|QWORD + 1156] y: -5907 size: DWORD  <||@
  Comment 126 100 MOV x: [r15|QWORD + 1168] y: 20 size: QWORD  <||@
  Comment 137 102 DEOPT info [bci:0]  <||@
  Comment 137 {Field[name=CompilerToVM::Data::SharedRuntime_deopt_blob_uncommon_trap, type=address, offset=0, address=0x7f78b20335a8, value=140155947626874]:0x7f789978b17a}  <||@
  Comment 142 []at java.lang.Math.clamp(Math.java:2214) [bci: 0, duringCall: false, rethrow: false]
              |0          |1  |2          |3         
     locals:  |rsi|QWORD  |-  |rdx|DWORD  |rcx|DWORD   <||@
  Comment 155 {Field[name=CompilerToVM::Data::nmethod_entry_barrier, type=address, offset=0, address=0x7f78b2033598, value=140155947495968]:0x7f789976b220}  <||@
  Comment 180 {Field[name=CompilerToVM::Data::SharedRuntime_polling_page_return_handler, type=address, offset=0, address=0x7f78b20335a0, value=140155947630592]:0x7f789978c000}  <||@
  Comment 186 {Stub<ExceptionHandlerStub.exceptionHandler>@0x7f78998c5300:CallingConvention[rax|QWORD[.], rdx|QWORD]:CallingConvention[rax|QWORD[.], rdx|QWORD]; temps=rdi|ILLEGAL,xmm14|ILLEGAL,xmm15|ILLEGAL,xmm12|ILLEGAL,xmm13|ILLEGAL,xmm10|ILLEGAL,xmm11|ILLEGAL,xmm7|ILLEGAL,xmm8|ILLEGAL,xmm9|ILLEGAL,xmm0|ILLEGAL,xmm1|ILLEGAL,xmm2|ILLEGAL,xmm3|ILLEGAL,xmm4|ILLEGAL,xmm5|ILLEGAL,xmm6|ILLEGAL,rax|ILLEGAL,rcx|ILLEGAL,rdx|ILLEGAL,rsi|ILLEGAL,r8|ILLEGAL,r9|ILLEGAL,r10|ILLEGAL,r11|ILLEGAL}  <||@
  Comment 186 EXCEPTION_HANDLER_ENTRY  <||@
  Comment 192 {Field[name=CompilerToVM::Data::SharedRuntime_deopt_blob_unpack, type=address, offset=0, address=0x7f78b20335b8, value=140155947626272]:0x7f789978af20}  <||@
  Comment 192 DEOPT_HANDLER_ENTRY  <||@
  HexCodeFile>>> <|@
end_nmethod
