begin_compilation
  name " HotSpotCompilation-7250[java.lang.String.valueOf(Object)]"
  method "HotSpotCompilation-7250[java.lang.String.valueOf(Object)]"
  date 1724269739223
end_compilation
begin_cfg
  name "Final HIR schedule"
  begin_block
    name "B0"
    from_bci -1
    to_bci -1
    predecessors 
    successors "B1" "B2" 
    xhandlers
    flags 
    probability 4607182418800017408
    begin_IR
      HIR
f <@#|@fixed with next>@ <|@
tid v0 <|@
d <@d|@=== Debug Properties ===
hasSpeculationFence: false
stamp: void
=== Inputs ===
stateAfter: - 
=== Succesors ===
next: v7 
=== Usages ===
=== Predecessor ===
- >@ <|@
instruction <@StartNode|@jdk.graal.compiler.nodes.StartNode>@ stateAfter: - #next: v7  <|@  <|@
f <@~|@floating>@ <|@
tid a1 <|@
d <@d|@=== Debug Properties ===
index: 0
stamp: a java.lang.Object
uncheckedStamp: [null]
=== Inputs ===
=== Succesors ===
=== Usages ===
a16 v4 v46 v58 
=== Predecessor ===
- >@ <|@
instruction <@Parameter|@jdk.graal.compiler.nodes.ParameterNode>@  <|@  <|@
f <@~|@floating>@ <|@
tid v4 <|@
d <@d|@=== Debug Properties ===
nodeSourcePosition: at java.lang.String.valueOf(String.java:4465) [bci: 1]
nullConstant: Object[null]
stamp: void
=== Inputs ===
value: a1 
=== Succesors ===
=== Usages ===
v7 
=== Predecessor ===
- >@ <|@
instruction <@IsNull|@jdk.graal.compiler.nodes.calc.IsNullNode>@ value: a1  <|@  <|@
f <@*|@fixed>@ <|@
tid v7 <|@
d <@d|@=== Debug Properties ===
nodeSourcePosition: at java.lang.String.valueOf(String.java:4465) [bci: 1]
profileData: PROFILED designatedSuccessorProbability: 9.91958358897982E-7
stamp: void
=== Inputs ===
condition: v4 
=== Succesors ===
trueSuccessor: v6 
falseSuccessor: v5 
=== Usages ===
=== Predecessor ===
v0 >@ <|@
instruction <@If|@jdk.graal.compiler.nodes.IfNode>@ condition: v4 #trueSuccessor: v6 #falseSuccessor: v5  <|@  <|@
    end_IR
  end_block
  begin_block
    name "B1"
    from_bci -1
    to_bci -1
    predecessors "B0" 
    successors "B5" 
    xhandlers
    flags 
    probability 4517291217531699200
    begin_IR
      HIR
f <@#|@fixed with next>@ <|@
tid v6 <|@
d <@d|@=== Debug Properties ===
hasSpeculationFence: false
nodeSourcePosition: at java.lang.String.valueOf(String.java:4465) [bci: 4]
stamp: void
=== Inputs ===
=== Succesors ===
next: v13 
=== Usages ===
=== Predecessor ===
v7 >@ <|@
instruction <@Begin|@jdk.graal.compiler.nodes.BeginNode>@ #next: v13  <|@  <|@
f <@~|@floating>@ <|@
tid a8 <|@
d <@d|@=== Debug Properties ===
isDefaultStable: false
nodeSourcePosition: at java.lang.String.valueOf(String.java:4465) [bci: 4]
rawvalue: "null"
stableDimension: 0
stamp: a!# java.lang.String
stampKind: a java.lang.Object
value: Object[String:"null"]
=== Inputs ===
=== Succesors ===
=== Usages ===
a16 
=== Predecessor ===
- >@ <|@
instruction <@Constant|@jdk.graal.compiler.nodes.ConstantNode>@  <|@  <|@
f <@*|@fixed>@ <|@
tid v13 <|@
d <@d|@=== Debug Properties ===
nodeSourcePosition: at java.lang.String.valueOf(String.java:4465) [bci: 14]
stamp: void
=== Inputs ===
=== Succesors ===
=== Usages ===
v14 
=== Predecessor ===
v6 >@ <|@
instruction <@EndNode|@jdk.graal.compiler.nodes.EndNode>@  <|@  <|@
    end_IR
  end_block
  begin_block
    name "B2"
    from_bci -1
    to_bci -1
    predecessors "B0" 
    successors "B3" "B4" 
    xhandlers
    flags 
    probability 4607182409865250817
    begin_IR
      HIR
f <@#|@fixed with next>@ <|@
tid v5 <|@
d <@d|@=== Debug Properties ===
hasSpeculationFence: false
nodeSourcePosition: at java.lang.String.valueOf(String.java:4465) [bci: 10]
stamp: void
=== Inputs ===
=== Succesors ===
next: v55 
=== Usages ===
=== Predecessor ===
v7 >@ <|@
instruction <@Begin|@jdk.graal.compiler.nodes.BeginNode>@ #next: v55  <|@  <|@
f <@~|@floating>@ <|@
tid v58 <|@
d <@d|@=== Debug Properties ===
displacement: 8
stamp: void*
stride: S1
=== Inputs ===
base: a1 
index: - 
=== Succesors ===
=== Usages ===
v55 
=== Predecessor ===
- >@ <|@
instruction <@AMD64Address|@jdk.graal.compiler.core.amd64.AMD64AddressNode>@ base: a1 index: -  <|@  <|@
f <@#|@fixed with next>@ <|@
tid v55 <|@
d <@d|@=== Debug Properties ===
accessStamp: Klass*!(compressed base: 140154094223360 shift: 0)
barrierType: NONE
deoptReasonAndAction: [null]
deoptSpeculation: [null]
extendKind: DEFAULT zero? false sign? false extendSize 0
forceFixed: false
location: CompressedHub:final
memoryOrder: PLAIN
stamp: Klass*!(compressed base: 140154094223360 shift: 0)
usedAsNullCheck: false
=== Inputs ===
stateBefore: - 
guard: - 
address: v58 
lastLocationAccess: - 
=== Succesors ===
next: v34 
=== Usages ===
v54 
=== Predecessor ===
v5 >@ <|@
instruction <@Read|@jdk.graal.compiler.nodes.memory.ReadNode>@ stateBefore: - guard: - address: v58 lastLocationAccess: - #next: v34  <|@  <|@
f <@~|@floating>@ <|@
tid v54 <|@
d <@d|@=== Debug Properties ===
encoding: base: 140154094223360 shift: 0
op: Uncompress
stamp: Klass*!
=== Inputs ===
value: v55 
=== Succesors ===
=== Usages ===
v34 v56 
=== Predecessor ===
- >@ <|@
instruction <@HotSpotCompression|@jdk.graal.compiler.hotspot.nodes.HotSpotCompressionNode>@ value: v55  <|@  <|@
f <@*|@fixed>@ <|@
tid v34 <|@
d <@d|@=== Debug Properties ===
hubs: [meta{HotSpotType<Ljava/lang/String;, resolved>}]
keySuccessors: [I@48c3d9b
keys: [HotSpotType<Ljava/lang/String;, resolved>]
profileData: PROFILED keyProbabilities: [0.43400564574488104, 0.565994354255119]
stamp: void
=== Inputs ===
value: v54 
=== Succesors ===
successors: v24 v29 
=== Usages ===
=== Predecessor ===
v55 >@ <|@
instruction <@TypeSwitch|@jdk.graal.compiler.nodes.java.TypeSwitchNode>@ value: v54 #successors: v24 v29  <|@  <|@
    end_IR
  end_block
  begin_block
    name "B3"
    from_bci -1
    to_bci -1
    predecessors "B2" 
    successors "B5" 
    xhandlers
    flags 
    probability 4601489962820240983
    begin_IR
      HIR
f <@#|@fixed with next>@ <|@
tid v24 <|@
d <@d|@=== Debug Properties ===
hasSpeculationFence: false
stamp: void
=== Inputs ===
=== Succesors ===
next: v15 
=== Usages ===
=== Predecessor ===
v34 >@ <|@
instruction <@Begin|@jdk.graal.compiler.nodes.BeginNode>@ #next: v15  <|@  <|@
f <@*|@fixed>@ <|@
tid v15 <|@
d <@d|@=== Debug Properties ===
nodeSourcePosition: at java.lang.String.valueOf(String.java:4465) [bci: 14]
stamp: void
=== Inputs ===
=== Succesors ===
=== Usages ===
v14 
=== Predecessor ===
v24 >@ <|@
instruction <@EndNode|@jdk.graal.compiler.nodes.EndNode>@  <|@  <|@
    end_IR
  end_block
  begin_block
    name "B4"
    from_bci -1
    to_bci -1
    predecessors "B2" 
    successors "B5" 
    xhandlers
    flags 
    probability 4603273238414083286
    begin_IR
      HIR
f <@#|@fixed with next>@ <|@
tid v29 <|@
d <@d|@=== Debug Properties ===
hasSpeculationFence: false
stamp: void
=== Inputs ===
=== Succesors ===
next: v42 
=== Usages ===
=== Predecessor ===
v34 >@ <|@
instruction <@Begin|@jdk.graal.compiler.nodes.BeginNode>@ #next: v42  <|@  <|@
f <@~|@floating>@ <|@
tid v56 <|@
d <@d|@=== Debug Properties ===
displacement: 472
stamp: void*
stride: S1
=== Inputs ===
base: v54 
index: - 
=== Succesors ===
=== Usages ===
v42 
=== Predecessor ===
- >@ <|@
instruction <@AMD64Address|@jdk.graal.compiler.core.amd64.AMD64AddressNode>@ base: v54 index: -  <|@  <|@
f <@#|@fixed with next>@ <|@
tid v42 <|@
d <@d|@=== Debug Properties ===
accessStamp: Method*!
barrierType: NONE
deoptReasonAndAction: [null]
deoptSpeculation: [null]
extendKind: DEFAULT zero? false sign? false extendSize 0
forceFixed: false
location: ANY_LOCATION
memoryOrder: PLAIN
nodeSourcePosition: at java.lang.String.valueOf(String.java:4465) [bci: 11]
stamp: Method*!
usedAsNullCheck: false
=== Inputs ===
stateBefore: - 
guard: - 
address: v56 
lastLocationAccess: - 
=== Succesors ===
next: j45 
=== Usages ===
v57 v46 
=== Predecessor ===
v29 >@ <|@
instruction <@Read|@jdk.graal.compiler.nodes.memory.ReadNode>@ stateBefore: - guard: - address: v56 lastLocationAccess: - #next: j45  <|@  <|@
f <@~|@floating>@ <|@
tid v57 <|@
d <@d|@=== Debug Properties ===
displacement: 64
stamp: void*
stride: S1
=== Inputs ===
base: v42 
index: - 
=== Succesors ===
=== Usages ===
j45 
=== Predecessor ===
- >@ <|@
instruction <@AMD64Address|@jdk.graal.compiler.core.amd64.AMD64AddressNode>@ base: v42 index: -  <|@  <|@
f <@#|@fixed with next>@ <|@
tid j45 <|@
d <@d|@=== Debug Properties ===
accessStamp: i64
barrierType: NONE
deoptReasonAndAction: [null]
deoptSpeculation: [null]
extendKind: DEFAULT zero? false sign? false extendSize 0
forceFixed: false
location: ANY_LOCATION
memoryOrder: PLAIN
nodeSourcePosition: at java.lang.String.valueOf(String.java:4465) [bci: 11]
stamp: i64
usedAsNullCheck: false
=== Inputs ===
stateBefore: - 
guard: - 
address: v57 
lastLocationAccess: - 
=== Succesors ===
next: a26 
=== Usages ===
v46 
=== Predecessor ===
v42 >@ <|@
instruction <@Read|@jdk.graal.compiler.nodes.memory.ReadNode>@ stateBefore: - guard: - address: v57 lastLocationAccess: - #next: a26  <|@  <|@
tid v46 <|@
d <@d|@=== Debug Properties ===
callType: JavaCall
invokeKind: Virtual
nodeSourcePosition: at java.lang.String.valueOf(String.java:4465) [bci: 11]
referencedType: [null]
returnStamp: a# java.lang.String
signature: [HotSpotType<Ljava/lang/Object;, resolved>]
stamp: void
targetMethod: HotSpotMethod<Object.toString()>
=== Inputs ===
computedAddress: j45 
metaspaceMethod: v42 
arguments: a1 
=== Succesors ===
=== Usages ===
a26 
=== Predecessor ===
- >@ <|@
instruction <@HotSpotIndirectCallTarget|@jdk.graal.compiler.hotspot.nodes.HotSpotIndirectCallTargetNode>@ computedAddress: j45 metaspaceMethod: v42 arguments: a1  <|@  <|@
tid ?49 <|@
d <@d|@=== Debug Properties ===
bci: 11
bytecode: invokevirtual
code: ResolvedJavaMethodBytecode<String.valueOf(Object)>
localsSize: 1
locksSize: 0
sourceFile: String.java
sourceLine: 4465
stackSize: 0
stackState: AfterPop
validForDeoptimization: true
=== Inputs ===
outerFrameState: - 
=== Succesors ===
=== Usages ===
a26 
=== Predecessor ===
- >@ <|@
instruction <@FrameState|@jdk.graal.compiler.nodes.FrameState>@ outerFrameState: -  <|@  <|@
f <@#|@fixed with next>@ <|@
tid a26 <|@
d <@d|@=== Debug Properties ===
bci: 11
identity: ANY_LOCATION
inlineControl: Never
isInOOMETry: false
nodeSourcePosition: at java.lang.String.valueOf(String.java:4465) [bci: 11]
polymorphic: true
stamp: a# java.lang.String
targetMethod: Indirect#Object.toString
=== Inputs ===
stateAfter: - 
classInit: - 
callTarget: v46 
stateDuring: ?49 
=== Succesors ===
next: v50 
=== Usages ===
a16 
=== Predecessor ===
j45 >@ <|@
instruction <@Invoke|@jdk.graal.compiler.nodes.InvokeNode>@ stateAfter: - classInit: - callTarget: v46 stateDuring: ?49 #next: v50  <|@  <|@
f <@*|@fixed>@ <|@
tid v50 <|@
d <@d|@=== Debug Properties ===
stamp: void
=== Inputs ===
=== Succesors ===
=== Usages ===
v14 
=== Predecessor ===
a26 >@ <|@
instruction <@EndNode|@jdk.graal.compiler.nodes.EndNode>@  <|@  <|@
    end_IR
  end_block
  begin_block
    name "B5"
    from_bci -1
    to_bci -1
    predecessors "B1" "B3" "B4" 
    successors 
    xhandlers
    flags 
    probability 4607182418800017408
    begin_IR
      HIR
f <@~|@floating>@ <|@
tid a16 <|@
d <@d|@=== Debug Properties ===
nodeSourcePosition: at java.lang.String.valueOf(String.java:4465) [bci: 14]
stamp: a# java.lang.String
valueDescription: a java.lang.Object
=== Inputs ===
merge: v14 
values: a8 a1 a26 
=== Succesors ===
=== Usages ===
v18 
=== Predecessor ===
- >@ <|@
instruction <@ValuePhi|@jdk.graal.compiler.nodes.ValuePhiNode>@ merge: v14 values: a8 a1 a26  <|@  <|@
f <@#|@fixed with next>@ <|@
tid v14 <|@
d <@d|@=== Debug Properties ===
hasSpeculationFence: false
nodeSourcePosition: at java.lang.String.valueOf(String.java:4465) [bci: 14]
stamp: void
=== Inputs ===
stateAfter: - 
ends: v13 v15 v50 
=== Succesors ===
next: v18 
=== Usages ===
a16 
=== Predecessor ===
- >@ <|@
instruction <@Merge|@jdk.graal.compiler.nodes.MergeNode>@ stateAfter: - ends: v13 v15 v50 #next: v18  <|@  <|@
f <@*|@fixed>@ <|@
tid v18 <|@
d <@d|@=== Debug Properties ===
nodeSourcePosition: at java.lang.String.valueOf(String.java:4465) [bci: 14]
stamp: void
=== Inputs ===
memoryMap: - 
result: a16 
=== Succesors ===
=== Usages ===
=== Predecessor ===
v14 >@ <|@
instruction <@Return|@jdk.graal.compiler.nodes.ReturnNode>@ memoryMap: - result: a16  <|@  <|@
    end_IR
  end_block
end_cfg
begin_cfg
  name "After LIRGeneration"
  begin_block
    name "B0"
    from_bci -1
    to_bci -1
    predecessors 
    successors "B1" "B2" 
    xhandlers
    flags 
    probability 4607182418800017408
    begin_IR
      LIR
      nr   -1  <|@ instruction [rsi|QWORD[.], rbp|QWORD] = LABEL alignment: 0 numbPhis: 0 label: ? <|@ <|@
      nr   -1  <|@ instruction stack:16|QWORD = MOVE input: rbp|QWORD moveKind: QWORD <|@ <|@
      nr   -1  <|@ instruction [] = HOTSPOTLOCKSTACK frameMapBuilder: jdk.graal.compiler.hotspot.amd64.AMD64HotSpotFrameMapBuilder@64144869 slotKind: QWORD <|@ <|@
      nr   -1  <|@ instruction v0|QWORD[.] = MOVE input: rsi|QWORD[.] moveKind: QWORD <|@ <|@
      nr   -1  <|@ instruction TESTBRANCH (x: v0|QWORD[.], y: v0|QWORD[.]) trueDestinationProbability: 9.91958358897982E-7 condition: = trueDestination: B0 -> B1 falseDestination: B0 -> B2 size: QWORD <|@ <|@
    end_IR
  end_block
  begin_block
    name "B2"
    from_bci -1
    to_bci -1
    predecessors "B0" 
    successors "B3" "B4" 
    xhandlers
    flags 
    probability 4607182409865250817
    begin_IR
      LIR
      nr   -1  <|@ instruction [] = LABEL alignment: 0 numbPhis: 0 label: ? <|@ <|@
      nr   -1  <|@ instruction v3|DWORD = MOV input: [v0|QWORD[.] + 8] size: DWORD <|@ <|@
      nr   -1  <|@ instruction v5|QWORD = MOVE input: long[140154094223360|0x7f782b000000] <|@ <|@
      nr   -1  <|@ instruction v4|QWORD = UNCOMPRESSPOINTER (input: v3|DWORD, ~baseRegister: v5|QWORD) nonNull: true lirKindTool: jdk.graal.compiler.hotspot.amd64.AMD64HotSpotLIRKindTool@d0246bd encoding: base: 140154094223360 shift: 0 <|@ <|@
      nr   -1  <|@ instruction v6|QWORD = HOTSPOTLOADMETASPACECONSTANT input: meta{HotSpotType<Ljava/lang/String;, resolved>} <|@ <|@
      nr   -1  <|@ instruction CMPBRANCH (x: v6|QWORD, y: v4|QWORD) trueDestinationProbability: 0.43400564574488104 condition: = trueDestination: B2 -> B3 falseDestination: B2 -> B4 size: QWORD <|@ <|@
    end_IR
  end_block
  begin_block
    name "B4"
    from_bci -1
    to_bci -1
    predecessors "B2" 
    successors "B5" 
    xhandlers
    flags 
    probability 4603273238414083286
    begin_IR
      LIR
      nr   -1  <|@ instruction [] = LABEL alignment: 0 numbPhis: 0 label: ? <|@ <|@
      nr   -1  <|@ instruction v7|QWORD = MOV input: [v4|QWORD + 472] size: QWORD <|@ <|@
      nr   -1  <|@ instruction v8|QWORD = MOV input: [v7|QWORD + 64] size: QWORD <|@ <|@
      nr   -1  <|@ instruction rsi|QWORD[.] = MOVE input: v0|QWORD[.] moveKind: QWORD <|@ <|@
      nr   -1  <|@ instruction rbx|QWORD = MOVE input: v7|QWORD moveKind: QWORD <|@ <|@
      nr   -1  <|@ instruction rax|QWORD = MOVE input: v8|QWORD moveKind: QWORD <|@ <|@
      nr   -1  <|@ st <@st|@java.lang.String.valueOf(String.java:4465) [bci: 11]
locals: - 
>@ <|@ instruction rax|QWORD[.] = CALL_INDIRECT (targetAddress: rax|QWORD, metaspaceMethod: rbx|QWORD, parameters: [rsi|QWORD[.]]) temps: [] callTarget: HotSpotMethod<Object.toString()> state [bci:11] <|@ <|@
      nr   -1  <|@ instruction v9|QWORD[.] = MOVE input: rax|QWORD[.] moveKind: QWORD <|@ <|@
      nr   -1  <|@ instruction JUMP ~outgoingValues: [v9|QWORD[.]] destination: B4 -> B5 <|@ <|@
    end_IR
  end_block
  begin_block
    name "B3"
    from_bci -1
    to_bci -1
    predecessors "B2" 
    successors "B5" 
    xhandlers
    flags 
    probability 4601489962820240983
    begin_IR
      LIR
      nr   -1  <|@ instruction [] = LABEL alignment: 0 numbPhis: 0 label: ? <|@ <|@
      nr   -1  <|@ instruction JUMP ~outgoingValues: [v0|QWORD[.]] destination: B3 -> B5 <|@ <|@
    end_IR
  end_block
  begin_block
    name "B5"
    from_bci -1
    to_bci -1
    predecessors "B1" "B3" "B4" 
    successors 
    xhandlers
    flags 
    probability 4607182418800017408
    begin_IR
      LIR
      nr   -1  <|@ instruction [v10|QWORD[.]] = LABEL alignment: 0 numbPhis: 1 label: ? <|@ <|@
      nr   -1  <|@ instruction rax|QWORD[.] = MOVE input: v10|QWORD[.] moveKind: QWORD <|@ <|@
      nr   -1  <|@ instruction RETURN (savedRbp: stack:16|QWORD, value: rax|QWORD[.]) isStub: false requiresReservedStackAccessCheck: false thread: r15 scratchForSafepointOnReturn: rcx config: jdk.graal.compiler.hotspot.GraalHotSpotVMConfig@4817c460 <|@ <|@
    end_IR
  end_block
  begin_block
    name "B1"
    from_bci -1
    to_bci -1
    predecessors "B0" 
    successors "B5" 
    xhandlers
    flags 
    probability 4517291217531699200
    begin_IR
      LIR
      nr   -1  <|@ instruction [] = LABEL alignment: 0 numbPhis: 0 label: ? <|@ <|@
      nr   -1  <|@ instruction v1|QWORD[.] = HOTSPOTLOADOBJECTCONSTANT input: Object[String:"null"] <|@ <|@
      nr   -1  <|@ instruction v2|QWORD[.] = MOVE input: v1|QWORD[.] moveKind: QWORD <|@ <|@
      nr   -1  <|@ instruction JUMP ~outgoingValues: [v2|QWORD[.]] destination: B1 -> B5 <|@ <|@
    end_IR
  end_block
end_cfg
begin_bytecodes
     0: aload_0       
     1: ifnonnull     10
     4: ldc_w         #1000       // "null"
     7: goto          14
    10: aload_0       
    11: invokevirtual #281        // java.lang.Object.toString:()java.lang.String
    14: areturn       
   <|@
end_bytecodes
begin_cfg
  name "After LIR generation"
  begin_block
    name "B0"
    from_bci -1
    to_bci -1
    predecessors 
    successors "B1" "B2" 
    xhandlers
    flags 
    probability 4607182418800017408
    begin_IR
      HIR
f <@#|@fixed with next>@ <|@
tid v0 <|@
d <@d|@=== Debug Properties ===
hasSpeculationFence: false
stamp: void
=== Inputs ===
stateAfter: - 
=== Succesors ===
next: v7 
=== Usages ===
=== Predecessor ===
- >@ <|@
instruction <@StartNode|@jdk.graal.compiler.nodes.StartNode>@ stateAfter: - #next: v7  <|@  <|@
f <@~|@floating>@ <|@
tid a1 <|@
result v0|QWORD[.] <|@
d <@d|@=== Debug Properties ===
index: 0
stamp: a java.lang.Object
uncheckedStamp: [null]
=== Inputs ===
=== Succesors ===
=== Usages ===
a16 v4 v46 v58 
=== Predecessor ===
- >@ <|@
instruction <@Parameter|@jdk.graal.compiler.nodes.ParameterNode>@  <|@  <|@
f <@~|@floating>@ <|@
tid v4 <|@
d <@d|@=== Debug Properties ===
nodeSourcePosition: at java.lang.String.valueOf(String.java:4465) [bci: 1]
nullConstant: Object[null]
stamp: void
=== Inputs ===
value: a1 
=== Succesors ===
=== Usages ===
v7 
=== Predecessor ===
- >@ <|@
instruction <@IsNull|@jdk.graal.compiler.nodes.calc.IsNullNode>@ value: a1  <|@  <|@
f <@*|@fixed>@ <|@
tid v7 <|@
d <@d|@=== Debug Properties ===
nodeSourcePosition: at java.lang.String.valueOf(String.java:4465) [bci: 1]
profileData: PROFILED designatedSuccessorProbability: 9.91958358897982E-7
stamp: void
=== Inputs ===
condition: v4 
=== Succesors ===
trueSuccessor: v6 
falseSuccessor: v5 
=== Usages ===
=== Predecessor ===
v0 >@ <|@
instruction <@If|@jdk.graal.compiler.nodes.IfNode>@ condition: v4 #trueSuccessor: v6 #falseSuccessor: v5  <|@  <|@
    end_IR
    begin_IR
      LIR
      nr   -1  <|@ instruction [rsi|QWORD[.], rbp|QWORD] = LABEL alignment: 0 numbPhis: 0 label: ? <|@ <|@
      nr   -1  <|@ instruction stack:16|QWORD = MOVE input: rbp|QWORD moveKind: QWORD <|@ <|@
      nr   -1  <|@ instruction [] = HOTSPOTLOCKSTACK frameMapBuilder: jdk.graal.compiler.hotspot.amd64.AMD64HotSpotFrameMapBuilder@64144869 slotKind: QWORD <|@ <|@
      nr   -1  <|@ instruction v0|QWORD[.] = MOVE input: rsi|QWORD[.] moveKind: QWORD <|@ <|@
      nr   -1  <|@ instruction TESTBRANCH (x: v0|QWORD[.], y: v0|QWORD[.]) trueDestinationProbability: 9.91958358897982E-7 condition: = trueDestination: B0 -> B1 falseDestination: B0 -> B2 size: QWORD <|@ <|@
    end_IR
  end_block
  begin_block
    name "B1"
    from_bci -1
    to_bci -1
    predecessors "B0" 
    successors "B5" 
    xhandlers
    flags 
    probability 4517291217531699200
    begin_IR
      HIR
f <@#|@fixed with next>@ <|@
tid v6 <|@
d <@d|@=== Debug Properties ===
hasSpeculationFence: false
nodeSourcePosition: at java.lang.String.valueOf(String.java:4465) [bci: 4]
stamp: void
=== Inputs ===
=== Succesors ===
next: v13 
=== Usages ===
=== Predecessor ===
v7 >@ <|@
instruction <@Begin|@jdk.graal.compiler.nodes.BeginNode>@ #next: v13  <|@  <|@
f <@~|@floating>@ <|@
tid a8 <|@
result v1|QWORD[.] <|@
d <@d|@=== Debug Properties ===
isDefaultStable: false
nodeSourcePosition: at java.lang.String.valueOf(String.java:4465) [bci: 4]
rawvalue: "null"
stableDimension: 0
stamp: a!# java.lang.String
stampKind: a java.lang.Object
value: Object[String:"null"]
=== Inputs ===
=== Succesors ===
=== Usages ===
a16 
=== Predecessor ===
- >@ <|@
instruction <@Constant|@jdk.graal.compiler.nodes.ConstantNode>@  <|@  <|@
f <@*|@fixed>@ <|@
tid v13 <|@
d <@d|@=== Debug Properties ===
nodeSourcePosition: at java.lang.String.valueOf(String.java:4465) [bci: 14]
stamp: void
=== Inputs ===
=== Succesors ===
=== Usages ===
v14 
=== Predecessor ===
v6 >@ <|@
instruction <@EndNode|@jdk.graal.compiler.nodes.EndNode>@  <|@  <|@
    end_IR
    begin_IR
      LIR
      nr   -1  <|@ instruction [] = LABEL alignment: 0 numbPhis: 0 label: ? <|@ <|@
      nr   -1  <|@ instruction v1|QWORD[.] = HOTSPOTLOADOBJECTCONSTANT input: Object[String:"null"] <|@ <|@
      nr   -1  <|@ instruction v2|QWORD[.] = MOVE input: v1|QWORD[.] moveKind: QWORD <|@ <|@
      nr   -1  <|@ instruction JUMP ~outgoingValues: [v2|QWORD[.]] destination: B1 -> B5 <|@ <|@
    end_IR
  end_block
  begin_block
    name "B2"
    from_bci -1
    to_bci -1
    predecessors "B0" 
    successors "B3" "B4" 
    xhandlers
    flags 
    probability 4607182409865250817
    begin_IR
      HIR
f <@#|@fixed with next>@ <|@
tid v5 <|@
d <@d|@=== Debug Properties ===
hasSpeculationFence: false
nodeSourcePosition: at java.lang.String.valueOf(String.java:4465) [bci: 10]
stamp: void
=== Inputs ===
=== Succesors ===
next: v55 
=== Usages ===
=== Predecessor ===
v7 >@ <|@
instruction <@Begin|@jdk.graal.compiler.nodes.BeginNode>@ #next: v55  <|@  <|@
f <@~|@floating>@ <|@
tid v58 <|@
result [v0|QWORD[.] + 8] <|@
d <@d|@=== Debug Properties ===
displacement: 8
stamp: void*
stride: S1
=== Inputs ===
base: a1 
index: - 
=== Succesors ===
=== Usages ===
v55 
=== Predecessor ===
- >@ <|@
instruction <@AMD64Address|@jdk.graal.compiler.core.amd64.AMD64AddressNode>@ base: a1 index: -  <|@  <|@
f <@#|@fixed with next>@ <|@
tid v55 <|@
result v3|DWORD <|@
d <@d|@=== Debug Properties ===
accessStamp: Klass*!(compressed base: 140154094223360 shift: 0)
barrierType: NONE
deoptReasonAndAction: [null]
deoptSpeculation: [null]
extendKind: DEFAULT zero? false sign? false extendSize 0
forceFixed: false
location: CompressedHub:final
memoryOrder: PLAIN
stamp: Klass*!(compressed base: 140154094223360 shift: 0)
usedAsNullCheck: false
=== Inputs ===
stateBefore: - 
guard: - 
address: v58 
lastLocationAccess: - 
=== Succesors ===
next: v34 
=== Usages ===
v54 
=== Predecessor ===
v5 >@ <|@
instruction <@Read|@jdk.graal.compiler.nodes.memory.ReadNode>@ stateBefore: - guard: - address: v58 lastLocationAccess: - #next: v34  <|@  <|@
f <@~|@floating>@ <|@
tid v54 <|@
result v4|QWORD <|@
d <@d|@=== Debug Properties ===
encoding: base: 140154094223360 shift: 0
op: Uncompress
stamp: Klass*!
=== Inputs ===
value: v55 
=== Succesors ===
=== Usages ===
v34 v56 
=== Predecessor ===
- >@ <|@
instruction <@HotSpotCompression|@jdk.graal.compiler.hotspot.nodes.HotSpotCompressionNode>@ value: v55  <|@  <|@
f <@*|@fixed>@ <|@
tid v34 <|@
d <@d|@=== Debug Properties ===
hubs: [meta{HotSpotType<Ljava/lang/String;, resolved>}]
keySuccessors: [I@48c3d9b
keys: [HotSpotType<Ljava/lang/String;, resolved>]
profileData: PROFILED keyProbabilities: [0.43400564574488104, 0.565994354255119]
stamp: void
=== Inputs ===
value: v54 
=== Succesors ===
successors: v24 v29 
=== Usages ===
=== Predecessor ===
v55 >@ <|@
instruction <@TypeSwitch|@jdk.graal.compiler.nodes.java.TypeSwitchNode>@ value: v54 #successors: v24 v29  <|@  <|@
    end_IR
    begin_IR
      LIR
      nr   -1  <|@ instruction [] = LABEL alignment: 0 numbPhis: 0 label: ? <|@ <|@
      nr   -1  <|@ instruction v3|DWORD = MOV input: [v0|QWORD[.] + 8] size: DWORD <|@ <|@
      nr   -1  <|@ instruction v5|QWORD = MOVE input: long[140154094223360|0x7f782b000000] <|@ <|@
      nr   -1  <|@ instruction v4|QWORD = UNCOMPRESSPOINTER (input: v3|DWORD, ~baseRegister: v5|QWORD) nonNull: true lirKindTool: jdk.graal.compiler.hotspot.amd64.AMD64HotSpotLIRKindTool@d0246bd encoding: base: 140154094223360 shift: 0 <|@ <|@
      nr   -1  <|@ instruction v6|QWORD = HOTSPOTLOADMETASPACECONSTANT input: meta{HotSpotType<Ljava/lang/String;, resolved>} <|@ <|@
      nr   -1  <|@ instruction CMPBRANCH (x: v6|QWORD, y: v4|QWORD) trueDestinationProbability: 0.43400564574488104 condition: = trueDestination: B2 -> B3 falseDestination: B2 -> B4 size: QWORD <|@ <|@
    end_IR
  end_block
  begin_block
    name "B3"
    from_bci -1
    to_bci -1
    predecessors "B2" 
    successors "B5" 
    xhandlers
    flags 
    probability 4601489962820240983
    begin_IR
      HIR
f <@#|@fixed with next>@ <|@
tid v24 <|@
d <@d|@=== Debug Properties ===
hasSpeculationFence: false
stamp: void
=== Inputs ===
=== Succesors ===
next: v15 
=== Usages ===
=== Predecessor ===
v34 >@ <|@
instruction <@Begin|@jdk.graal.compiler.nodes.BeginNode>@ #next: v15  <|@  <|@
f <@*|@fixed>@ <|@
tid v15 <|@
d <@d|@=== Debug Properties ===
nodeSourcePosition: at java.lang.String.valueOf(String.java:4465) [bci: 14]
stamp: void
=== Inputs ===
=== Succesors ===
=== Usages ===
v14 
=== Predecessor ===
v24 >@ <|@
instruction <@EndNode|@jdk.graal.compiler.nodes.EndNode>@  <|@  <|@
    end_IR
    begin_IR
      LIR
      nr   -1  <|@ instruction [] = LABEL alignment: 0 numbPhis: 0 label: ? <|@ <|@
      nr   -1  <|@ instruction JUMP ~outgoingValues: [v0|QWORD[.]] destination: B3 -> B5 <|@ <|@
    end_IR
  end_block
  begin_block
    name "B4"
    from_bci -1
    to_bci -1
    predecessors "B2" 
    successors "B5" 
    xhandlers
    flags 
    probability 4603273238414083286
    begin_IR
      HIR
f <@#|@fixed with next>@ <|@
tid v29 <|@
d <@d|@=== Debug Properties ===
hasSpeculationFence: false
stamp: void
=== Inputs ===
=== Succesors ===
next: v42 
=== Usages ===
=== Predecessor ===
v34 >@ <|@
instruction <@Begin|@jdk.graal.compiler.nodes.BeginNode>@ #next: v42  <|@  <|@
f <@~|@floating>@ <|@
tid v56 <|@
result [v4|QWORD + 472] <|@
d <@d|@=== Debug Properties ===
displacement: 472
stamp: void*
stride: S1
=== Inputs ===
base: v54 
index: - 
=== Succesors ===
=== Usages ===
v42 
=== Predecessor ===
- >@ <|@
instruction <@AMD64Address|@jdk.graal.compiler.core.amd64.AMD64AddressNode>@ base: v54 index: -  <|@  <|@
f <@#|@fixed with next>@ <|@
tid v42 <|@
result v7|QWORD <|@
d <@d|@=== Debug Properties ===
accessStamp: Method*!
barrierType: NONE
deoptReasonAndAction: [null]
deoptSpeculation: [null]
extendKind: DEFAULT zero? false sign? false extendSize 0
forceFixed: false
location: ANY_LOCATION
memoryOrder: PLAIN
nodeSourcePosition: at java.lang.String.valueOf(String.java:4465) [bci: 11]
stamp: Method*!
usedAsNullCheck: false
=== Inputs ===
stateBefore: - 
guard: - 
address: v56 
lastLocationAccess: - 
=== Succesors ===
next: j45 
=== Usages ===
v57 v46 
=== Predecessor ===
v29 >@ <|@
instruction <@Read|@jdk.graal.compiler.nodes.memory.ReadNode>@ stateBefore: - guard: - address: v56 lastLocationAccess: - #next: j45  <|@  <|@
f <@~|@floating>@ <|@
tid v57 <|@
result [v7|QWORD + 64] <|@
d <@d|@=== Debug Properties ===
displacement: 64
stamp: void*
stride: S1
=== Inputs ===
base: v42 
index: - 
=== Succesors ===
=== Usages ===
j45 
=== Predecessor ===
- >@ <|@
instruction <@AMD64Address|@jdk.graal.compiler.core.amd64.AMD64AddressNode>@ base: v42 index: -  <|@  <|@
f <@#|@fixed with next>@ <|@
tid j45 <|@
result v8|QWORD <|@
d <@d|@=== Debug Properties ===
accessStamp: i64
barrierType: NONE
deoptReasonAndAction: [null]
deoptSpeculation: [null]
extendKind: DEFAULT zero? false sign? false extendSize 0
forceFixed: false
location: ANY_LOCATION
memoryOrder: PLAIN
nodeSourcePosition: at java.lang.String.valueOf(String.java:4465) [bci: 11]
stamp: i64
usedAsNullCheck: false
=== Inputs ===
stateBefore: - 
guard: - 
address: v57 
lastLocationAccess: - 
=== Succesors ===
next: a26 
=== Usages ===
v46 
=== Predecessor ===
v42 >@ <|@
instruction <@Read|@jdk.graal.compiler.nodes.memory.ReadNode>@ stateBefore: - guard: - address: v57 lastLocationAccess: - #next: a26  <|@  <|@
tid v46 <|@
d <@d|@=== Debug Properties ===
callType: JavaCall
invokeKind: Virtual
nodeSourcePosition: at java.lang.String.valueOf(String.java:4465) [bci: 11]
referencedType: [null]
returnStamp: a# java.lang.String
signature: [HotSpotType<Ljava/lang/Object;, resolved>]
stamp: void
targetMethod: HotSpotMethod<Object.toString()>
=== Inputs ===
computedAddress: j45 
metaspaceMethod: v42 
arguments: a1 
=== Succesors ===
=== Usages ===
a26 
=== Predecessor ===
- >@ <|@
instruction <@HotSpotIndirectCallTarget|@jdk.graal.compiler.hotspot.nodes.HotSpotIndirectCallTargetNode>@ computedAddress: j45 metaspaceMethod: v42 arguments: a1  <|@  <|@
tid ?49 <|@
d <@d|@=== Debug Properties ===
bci: 11
bytecode: invokevirtual
code: ResolvedJavaMethodBytecode<String.valueOf(Object)>
localsSize: 1
locksSize: 0
sourceFile: String.java
sourceLine: 4465
stackSize: 0
stackState: AfterPop
validForDeoptimization: true
=== Inputs ===
outerFrameState: - 
=== Succesors ===
=== Usages ===
a26 
=== Predecessor ===
- >@ <|@
instruction <@FrameState|@jdk.graal.compiler.nodes.FrameState>@ outerFrameState: -  <|@  <|@
f <@#|@fixed with next>@ <|@
tid a26 <|@
result v9|QWORD[.] <|@
d <@d|@=== Debug Properties ===
bci: 11
identity: ANY_LOCATION
inlineControl: Never
isInOOMETry: false
nodeSourcePosition: at java.lang.String.valueOf(String.java:4465) [bci: 11]
polymorphic: true
stamp: a# java.lang.String
targetMethod: Indirect#Object.toString
=== Inputs ===
stateAfter: - 
classInit: - 
callTarget: v46 
stateDuring: ?49 
=== Succesors ===
next: v50 
=== Usages ===
a16 
=== Predecessor ===
j45 >@ <|@
instruction <@Invoke|@jdk.graal.compiler.nodes.InvokeNode>@ stateAfter: - classInit: - callTarget: v46 stateDuring: ?49 #next: v50  <|@  <|@
f <@*|@fixed>@ <|@
tid v50 <|@
d <@d|@=== Debug Properties ===
stamp: void
=== Inputs ===
=== Succesors ===
=== Usages ===
v14 
=== Predecessor ===
a26 >@ <|@
instruction <@EndNode|@jdk.graal.compiler.nodes.EndNode>@  <|@  <|@
    end_IR
    begin_IR
      LIR
      nr   -1  <|@ instruction [] = LABEL alignment: 0 numbPhis: 0 label: ? <|@ <|@
      nr   -1  <|@ instruction v7|QWORD = MOV input: [v4|QWORD + 472] size: QWORD <|@ <|@
      nr   -1  <|@ instruction v8|QWORD = MOV input: [v7|QWORD + 64] size: QWORD <|@ <|@
      nr   -1  <|@ instruction rsi|QWORD[.] = MOVE input: v0|QWORD[.] moveKind: QWORD <|@ <|@
      nr   -1  <|@ instruction rbx|QWORD = MOVE input: v7|QWORD moveKind: QWORD <|@ <|@
      nr   -1  <|@ instruction rax|QWORD = MOVE input: v8|QWORD moveKind: QWORD <|@ <|@
      nr   -1  <|@ st <@st|@java.lang.String.valueOf(String.java:4465) [bci: 11]
locals: - 
>@ <|@ instruction rax|QWORD[.] = CALL_INDIRECT (targetAddress: rax|QWORD, metaspaceMethod: rbx|QWORD, parameters: [rsi|QWORD[.]]) temps: [] callTarget: HotSpotMethod<Object.toString()> state [bci:11] <|@ <|@
      nr   -1  <|@ instruction v9|QWORD[.] = MOVE input: rax|QWORD[.] moveKind: QWORD <|@ <|@
      nr   -1  <|@ instruction JUMP ~outgoingValues: [v9|QWORD[.]] destination: B4 -> B5 <|@ <|@
    end_IR
  end_block
  begin_block
    name "B5"
    from_bci -1
    to_bci -1
    predecessors "B1" "B3" "B4" 
    successors 
    xhandlers
    flags 
    probability 4607182418800017408
    begin_IR
      HIR
f <@~|@floating>@ <|@
tid a16 <|@
result v10|QWORD[.] <|@
d <@d|@=== Debug Properties ===
nodeSourcePosition: at java.lang.String.valueOf(String.java:4465) [bci: 14]
stamp: a# java.lang.String
valueDescription: a java.lang.Object
=== Inputs ===
merge: v14 
values: a8 a1 a26 
=== Succesors ===
=== Usages ===
v18 
=== Predecessor ===
- >@ <|@
instruction <@ValuePhi|@jdk.graal.compiler.nodes.ValuePhiNode>@ merge: v14 values: a8 a1 a26  <|@  <|@
f <@#|@fixed with next>@ <|@
tid v14 <|@
d <@d|@=== Debug Properties ===
hasSpeculationFence: false
nodeSourcePosition: at java.lang.String.valueOf(String.java:4465) [bci: 14]
stamp: void
=== Inputs ===
stateAfter: - 
ends: v13 v15 v50 
=== Succesors ===
next: v18 
=== Usages ===
a16 
=== Predecessor ===
- >@ <|@
instruction <@Merge|@jdk.graal.compiler.nodes.MergeNode>@ stateAfter: - ends: v13 v15 v50 #next: v18  <|@  <|@
f <@*|@fixed>@ <|@
tid v18 <|@
d <@d|@=== Debug Properties ===
nodeSourcePosition: at java.lang.String.valueOf(String.java:4465) [bci: 14]
stamp: void
=== Inputs ===
memoryMap: - 
result: a16 
=== Succesors ===
=== Usages ===
=== Predecessor ===
v14 >@ <|@
instruction <@Return|@jdk.graal.compiler.nodes.ReturnNode>@ memoryMap: - result: a16  <|@  <|@
    end_IR
    begin_IR
      LIR
      nr   -1  <|@ instruction [v10|QWORD[.]] = LABEL alignment: 0 numbPhis: 1 label: ? <|@ <|@
      nr   -1  <|@ instruction rax|QWORD[.] = MOVE input: v10|QWORD[.] moveKind: QWORD <|@ <|@
      nr   -1  <|@ instruction RETURN (savedRbp: stack:16|QWORD, value: rax|QWORD[.]) isStub: false requiresReservedStackAccessCheck: false thread: r15 scratchForSafepointOnReturn: rcx config: jdk.graal.compiler.hotspot.GraalHotSpotVMConfig@4817c460 <|@ <|@
    end_IR
  end_block
end_cfg
begin_cfg
  name "After LIRGTSlowdown"
  begin_block
    name "B0"
    from_bci -1
    to_bci -1
    predecessors 
    successors "B1" "B2" 
    xhandlers
    flags 
    probability 4607182418800017408
    begin_IR
      LIR
      nr   -1  <|@ instruction [rsi|QWORD[.], rbp|QWORD] = LABEL alignment: 0 numbPhis: 0 label: ? <|@ <|@
      nr   -1  <|@ instruction NOP <|@ <|@
      nr   -1  <|@ instruction NOP <|@ <|@
      nr   -1  <|@ instruction NOP <|@ <|@
      nr   -1  <|@ instruction NOP <|@ <|@
      nr   -1  <|@ instruction NOP <|@ <|@
      nr   -1  <|@ instruction NOP <|@ <|@
      nr   -1  <|@ instruction NOP <|@ <|@
      nr   -1  <|@ instruction stack:16|QWORD = MOVE input: rbp|QWORD moveKind: QWORD <|@ <|@
      nr   -1  <|@ instruction [] = HOTSPOTLOCKSTACK frameMapBuilder: jdk.graal.compiler.hotspot.amd64.AMD64HotSpotFrameMapBuilder@64144869 slotKind: QWORD <|@ <|@
      nr   -1  <|@ instruction v0|QWORD[.] = MOVE input: rsi|QWORD[.] moveKind: QWORD <|@ <|@
      nr   -1  <|@ instruction TESTBRANCH (x: v0|QWORD[.], y: v0|QWORD[.]) trueDestinationProbability: 9.91958358897982E-7 condition: = trueDestination: B0 -> B1 falseDestination: B0 -> B2 size: QWORD <|@ <|@
    end_IR
  end_block
  begin_block
    name "B2"
    from_bci -1
    to_bci -1
    predecessors "B0" 
    successors "B3" "B4" 
    xhandlers
    flags 
    probability 4607182409865250817
    begin_IR
      LIR
      nr   -1  <|@ instruction [] = LABEL alignment: 0 numbPhis: 0 label: ? <|@ <|@
      nr   -1  <|@ instruction NOP <|@ <|@
      nr   -1  <|@ instruction NOP <|@ <|@
      nr   -1  <|@ instruction NOP <|@ <|@
      nr   -1  <|@ instruction NOP <|@ <|@
      nr   -1  <|@ instruction NOP <|@ <|@
      nr   -1  <|@ instruction NOP <|@ <|@
      nr   -1  <|@ instruction NOP <|@ <|@
      nr   -1  <|@ instruction NOP <|@ <|@
      nr   -1  <|@ instruction NOP <|@ <|@
      nr   -1  <|@ instruction v3|DWORD = MOV input: [v0|QWORD[.] + 8] size: DWORD <|@ <|@
      nr   -1  <|@ instruction v5|QWORD = MOVE input: long[140154094223360|0x7f782b000000] <|@ <|@
      nr   -1  <|@ instruction v4|QWORD = UNCOMPRESSPOINTER (input: v3|DWORD, ~baseRegister: v5|QWORD) nonNull: true lirKindTool: jdk.graal.compiler.hotspot.amd64.AMD64HotSpotLIRKindTool@d0246bd encoding: base: 140154094223360 shift: 0 <|@ <|@
      nr   -1  <|@ instruction v6|QWORD = HOTSPOTLOADMETASPACECONSTANT input: meta{HotSpotType<Ljava/lang/String;, resolved>} <|@ <|@
      nr   -1  <|@ instruction CMPBRANCH (x: v6|QWORD, y: v4|QWORD) trueDestinationProbability: 0.43400564574488104 condition: = trueDestination: B2 -> B3 falseDestination: B2 -> B4 size: QWORD <|@ <|@
    end_IR
  end_block
  begin_block
    name "B4"
    from_bci -1
    to_bci -1
    predecessors "B2" 
    successors "B5" 
    xhandlers
    flags 
    probability 4603273238414083286
    begin_IR
      LIR
      nr   -1  <|@ instruction [] = LABEL alignment: 0 numbPhis: 0 label: ? <|@ <|@
      nr   -1  <|@ instruction NOP <|@ <|@
      nr   -1  <|@ instruction NOP <|@ <|@
      nr   -1  <|@ instruction NOP <|@ <|@
      nr   -1  <|@ instruction NOP <|@ <|@
      nr   -1  <|@ instruction NOP <|@ <|@
      nr   -1  <|@ instruction NOP <|@ <|@
      nr   -1  <|@ instruction NOP <|@ <|@
      nr   -1  <|@ instruction NOP <|@ <|@
      nr   -1  <|@ instruction NOP <|@ <|@
      nr   -1  <|@ instruction NOP <|@ <|@
      nr   -1  <|@ instruction NOP <|@ <|@
      nr   -1  <|@ instruction NOP <|@ <|@
      nr   -1  <|@ instruction v7|QWORD = MOV input: [v4|QWORD + 472] size: QWORD <|@ <|@
      nr   -1  <|@ instruction v8|QWORD = MOV input: [v7|QWORD + 64] size: QWORD <|@ <|@
      nr   -1  <|@ instruction rsi|QWORD[.] = MOVE input: v0|QWORD[.] moveKind: QWORD <|@ <|@
      nr   -1  <|@ instruction rbx|QWORD = MOVE input: v7|QWORD moveKind: QWORD <|@ <|@
      nr   -1  <|@ instruction rax|QWORD = MOVE input: v8|QWORD moveKind: QWORD <|@ <|@
      nr   -1  <|@ st <@st|@java.lang.String.valueOf(String.java:4465) [bci: 11]
locals: - 
>@ <|@ instruction rax|QWORD[.] = CALL_INDIRECT (targetAddress: rax|QWORD, metaspaceMethod: rbx|QWORD, parameters: [rsi|QWORD[.]]) temps: [] callTarget: HotSpotMethod<Object.toString()> state [bci:11] <|@ <|@
      nr   -1  <|@ instruction v9|QWORD[.] = MOVE input: rax|QWORD[.] moveKind: QWORD <|@ <|@
      nr   -1  <|@ instruction JUMP ~outgoingValues: [v9|QWORD[.]] destination: B4 -> B5 <|@ <|@
    end_IR
  end_block
  begin_block
    name "B3"
    from_bci -1
    to_bci -1
    predecessors "B2" 
    successors "B5" 
    xhandlers
    flags 
    probability 4601489962820240983
    begin_IR
      LIR
      nr   -1  <|@ instruction [] = LABEL alignment: 0 numbPhis: 0 label: ? <|@ <|@
      nr   -1  <|@ instruction NOP <|@ <|@
      nr   -1  <|@ instruction NOP <|@ <|@
      nr   -1  <|@ instruction NOP <|@ <|@
      nr   -1  <|@ instruction JUMP ~outgoingValues: [v0|QWORD[.]] destination: B3 -> B5 <|@ <|@
    end_IR
  end_block
  begin_block
    name "B5"
    from_bci -1
    to_bci -1
    predecessors "B1" "B3" "B4" 
    successors 
    xhandlers
    flags 
    probability 4607182418800017408
    begin_IR
      LIR
      nr   -1  <|@ instruction [v10|QWORD[.]] = LABEL alignment: 0 numbPhis: 1 label: ? <|@ <|@
      nr   -1  <|@ instruction NOP <|@ <|@
      nr   -1  <|@ instruction NOP <|@ <|@
      nr   -1  <|@ instruction NOP <|@ <|@
      nr   -1  <|@ instruction NOP <|@ <|@
      nr   -1  <|@ instruction NOP <|@ <|@
      nr   -1  <|@ instruction NOP <|@ <|@
      nr   -1  <|@ instruction NOP <|@ <|@
      nr   -1  <|@ instruction NOP <|@ <|@
      nr   -1  <|@ instruction rax|QWORD[.] = MOVE input: v10|QWORD[.] moveKind: QWORD <|@ <|@
      nr   -1  <|@ instruction RETURN (savedRbp: stack:16|QWORD, value: rax|QWORD[.]) isStub: false requiresReservedStackAccessCheck: false thread: r15 scratchForSafepointOnReturn: rcx config: jdk.graal.compiler.hotspot.GraalHotSpotVMConfig@4817c460 <|@ <|@
    end_IR
  end_block
  begin_block
    name "B1"
    from_bci -1
    to_bci -1
    predecessors "B0" 
    successors "B5" 
    xhandlers
    flags 
    probability 4517291217531699200
    begin_IR
      LIR
      nr   -1  <|@ instruction [] = LABEL alignment: 0 numbPhis: 0 label: ? <|@ <|@
      nr   -1  <|@ instruction NOP <|@ <|@
      nr   -1  <|@ instruction NOP <|@ <|@
      nr   -1  <|@ instruction NOP <|@ <|@
      nr   -1  <|@ instruction NOP <|@ <|@
      nr   -1  <|@ instruction NOP <|@ <|@
      nr   -1  <|@ instruction v1|QWORD[.] = HOTSPOTLOADOBJECTCONSTANT input: Object[String:"null"] <|@ <|@
      nr   -1  <|@ instruction v2|QWORD[.] = MOVE input: v1|QWORD[.] moveKind: QWORD <|@ <|@
      nr   -1  <|@ instruction JUMP ~outgoingValues: [v2|QWORD[.]] destination: B1 -> B5 <|@ <|@
    end_IR
  end_block
end_cfg
begin_bytecodes
     0: aload_0       
     1: ifnonnull     10
     4: ldc_w         #1000       // "null"
     7: goto          14
    10: aload_0       
    11: invokevirtual #281        // java.lang.Object.toString:()java.lang.String
    14: areturn       
   <|@
end_bytecodes
begin_cfg
  name "After ConstantLoadOptimization"
  begin_block
    name "B0"
    from_bci -1
    to_bci -1
    predecessors 
    successors "B1" "B2" 
    xhandlers
    flags 
    probability 4607182418800017408
    begin_IR
      LIR
      nr   -1  <|@ instruction [rsi|QWORD[.], rbp|QWORD] = LABEL alignment: 0 numbPhis: 0 label: ? <|@ <|@
      nr   -1  <|@ instruction NOP <|@ <|@
      nr   -1  <|@ instruction NOP <|@ <|@
      nr   -1  <|@ instruction NOP <|@ <|@
      nr   -1  <|@ instruction NOP <|@ <|@
      nr   -1  <|@ instruction NOP <|@ <|@
      nr   -1  <|@ instruction NOP <|@ <|@
      nr   -1  <|@ instruction NOP <|@ <|@
      nr   -1  <|@ instruction stack:16|QWORD = MOVE input: rbp|QWORD moveKind: QWORD <|@ <|@
      nr   -1  <|@ instruction [] = HOTSPOTLOCKSTACK frameMapBuilder: jdk.graal.compiler.hotspot.amd64.AMD64HotSpotFrameMapBuilder@64144869 slotKind: QWORD <|@ <|@
      nr   -1  <|@ instruction v0|QWORD[.] = MOVE input: rsi|QWORD[.] moveKind: QWORD <|@ <|@
      nr   -1  <|@ instruction TESTBRANCH (x: v0|QWORD[.], y: v0|QWORD[.]) trueDestinationProbability: 9.91958358897982E-7 condition: = trueDestination: B0 -> B1 falseDestination: B0 -> B2 size: QWORD <|@ <|@
    end_IR
  end_block
  begin_block
    name "B2"
    from_bci -1
    to_bci -1
    predecessors "B0" 
    successors "B3" "B4" 
    xhandlers
    flags 
    probability 4607182409865250817
    begin_IR
      LIR
      nr   -1  <|@ instruction [] = LABEL alignment: 0 numbPhis: 0 label: ? <|@ <|@
      nr   -1  <|@ instruction NOP <|@ <|@
      nr   -1  <|@ instruction NOP <|@ <|@
      nr   -1  <|@ instruction NOP <|@ <|@
      nr   -1  <|@ instruction NOP <|@ <|@
      nr   -1  <|@ instruction NOP <|@ <|@
      nr   -1  <|@ instruction NOP <|@ <|@
      nr   -1  <|@ instruction NOP <|@ <|@
      nr   -1  <|@ instruction NOP <|@ <|@
      nr   -1  <|@ instruction NOP <|@ <|@
      nr   -1  <|@ instruction v3|DWORD = MOV input: [v0|QWORD[.] + 8] size: DWORD <|@ <|@
      nr   -1  <|@ instruction v5|QWORD = MOVE input: long[140154094223360|0x7f782b000000] <|@ <|@
      nr   -1  <|@ instruction v4|QWORD = UNCOMPRESSPOINTER (input: v3|DWORD, ~baseRegister: v5|QWORD) nonNull: true lirKindTool: jdk.graal.compiler.hotspot.amd64.AMD64HotSpotLIRKindTool@d0246bd encoding: base: 140154094223360 shift: 0 <|@ <|@
      nr   -1  <|@ instruction v6|QWORD = HOTSPOTLOADMETASPACECONSTANT input: meta{HotSpotType<Ljava/lang/String;, resolved>} <|@ <|@
      nr   -1  <|@ instruction CMPBRANCH (x: v6|QWORD, y: v4|QWORD) trueDestinationProbability: 0.43400564574488104 condition: = trueDestination: B2 -> B3 falseDestination: B2 -> B4 size: QWORD <|@ <|@
    end_IR
  end_block
  begin_block
    name "B4"
    from_bci -1
    to_bci -1
    predecessors "B2" 
    successors "B5" 
    xhandlers
    flags 
    probability 4603273238414083286
    begin_IR
      LIR
      nr   -1  <|@ instruction [] = LABEL alignment: 0 numbPhis: 0 label: ? <|@ <|@
      nr   -1  <|@ instruction NOP <|@ <|@
      nr   -1  <|@ instruction NOP <|@ <|@
      nr   -1  <|@ instruction NOP <|@ <|@
      nr   -1  <|@ instruction NOP <|@ <|@
      nr   -1  <|@ instruction NOP <|@ <|@
      nr   -1  <|@ instruction NOP <|@ <|@
      nr   -1  <|@ instruction NOP <|@ <|@
      nr   -1  <|@ instruction NOP <|@ <|@
      nr   -1  <|@ instruction NOP <|@ <|@
      nr   -1  <|@ instruction NOP <|@ <|@
      nr   -1  <|@ instruction NOP <|@ <|@
      nr   -1  <|@ instruction NOP <|@ <|@
      nr   -1  <|@ instruction v7|QWORD = MOV input: [v4|QWORD + 472] size: QWORD <|@ <|@
      nr   -1  <|@ instruction v8|QWORD = MOV input: [v7|QWORD + 64] size: QWORD <|@ <|@
      nr   -1  <|@ instruction rsi|QWORD[.] = MOVE input: v0|QWORD[.] moveKind: QWORD <|@ <|@
      nr   -1  <|@ instruction rbx|QWORD = MOVE input: v7|QWORD moveKind: QWORD <|@ <|@
      nr   -1  <|@ instruction rax|QWORD = MOVE input: v8|QWORD moveKind: QWORD <|@ <|@
      nr   -1  <|@ st <@st|@java.lang.String.valueOf(String.java:4465) [bci: 11]
locals: - 
>@ <|@ instruction rax|QWORD[.] = CALL_INDIRECT (targetAddress: rax|QWORD, metaspaceMethod: rbx|QWORD, parameters: [rsi|QWORD[.]]) temps: [] callTarget: HotSpotMethod<Object.toString()> state [bci:11] <|@ <|@
      nr   -1  <|@ instruction v9|QWORD[.] = MOVE input: rax|QWORD[.] moveKind: QWORD <|@ <|@
      nr   -1  <|@ instruction JUMP ~outgoingValues: [v9|QWORD[.]] destination: B4 -> B5 <|@ <|@
    end_IR
  end_block
  begin_block
    name "B3"
    from_bci -1
    to_bci -1
    predecessors "B2" 
    successors "B5" 
    xhandlers
    flags 
    probability 4601489962820240983
    begin_IR
      LIR
      nr   -1  <|@ instruction [] = LABEL alignment: 0 numbPhis: 0 label: ? <|@ <|@
      nr   -1  <|@ instruction NOP <|@ <|@
      nr   -1  <|@ instruction NOP <|@ <|@
      nr   -1  <|@ instruction NOP <|@ <|@
      nr   -1  <|@ instruction JUMP ~outgoingValues: [v0|QWORD[.]] destination: B3 -> B5 <|@ <|@
    end_IR
  end_block
  begin_block
    name "B5"
    from_bci -1
    to_bci -1
    predecessors "B1" "B3" "B4" 
    successors 
    xhandlers
    flags 
    probability 4607182418800017408
    begin_IR
      LIR
      nr   -1  <|@ instruction [v10|QWORD[.]] = LABEL alignment: 0 numbPhis: 1 label: ? <|@ <|@
      nr   -1  <|@ instruction NOP <|@ <|@
      nr   -1  <|@ instruction NOP <|@ <|@
      nr   -1  <|@ instruction NOP <|@ <|@
      nr   -1  <|@ instruction NOP <|@ <|@
      nr   -1  <|@ instruction NOP <|@ <|@
      nr   -1  <|@ instruction NOP <|@ <|@
      nr   -1  <|@ instruction NOP <|@ <|@
      nr   -1  <|@ instruction NOP <|@ <|@
      nr   -1  <|@ instruction rax|QWORD[.] = MOVE input: v10|QWORD[.] moveKind: QWORD <|@ <|@
      nr   -1  <|@ instruction RETURN (savedRbp: stack:16|QWORD, value: rax|QWORD[.]) isStub: false requiresReservedStackAccessCheck: false thread: r15 scratchForSafepointOnReturn: rcx config: jdk.graal.compiler.hotspot.GraalHotSpotVMConfig@4817c460 <|@ <|@
    end_IR
  end_block
  begin_block
    name "B1"
    from_bci -1
    to_bci -1
    predecessors "B0" 
    successors "B5" 
    xhandlers
    flags 
    probability 4517291217531699200
    begin_IR
      LIR
      nr   -1  <|@ instruction [] = LABEL alignment: 0 numbPhis: 0 label: ? <|@ <|@
      nr   -1  <|@ instruction NOP <|@ <|@
      nr   -1  <|@ instruction NOP <|@ <|@
      nr   -1  <|@ instruction NOP <|@ <|@
      nr   -1  <|@ instruction NOP <|@ <|@
      nr   -1  <|@ instruction NOP <|@ <|@
      nr   -1  <|@ instruction v1|QWORD[.] = HOTSPOTLOADOBJECTCONSTANT input: Object[String:"null"] <|@ <|@
      nr   -1  <|@ instruction v2|QWORD[.] = MOVE input: v1|QWORD[.] moveKind: QWORD <|@ <|@
      nr   -1  <|@ instruction JUMP ~outgoingValues: [v2|QWORD[.]] destination: B1 -> B5 <|@ <|@
    end_IR
  end_block
end_cfg
begin_bytecodes
     0: aload_0       
     1: ifnonnull     10
     4: ldc_w         #1000       // "null"
     7: goto          14
    10: aload_0       
    11: invokevirtual #281        // java.lang.Object.toString:()java.lang.String
    14: areturn       
   <|@
end_bytecodes
begin_cfg
  name "After SaveCalleeSaveRegisters"
  begin_block
    name "B0"
    from_bci -1
    to_bci -1
    predecessors 
    successors "B1" "B2" 
    xhandlers
    flags 
    probability 4607182418800017408
    begin_IR
      LIR
      nr   -1  <|@ instruction [rsi|QWORD[.], rbp|QWORD] = LABEL alignment: 0 numbPhis: 0 label: ? <|@ <|@
      nr   -1  <|@ instruction NOP <|@ <|@
      nr   -1  <|@ instruction NOP <|@ <|@
      nr   -1  <|@ instruction NOP <|@ <|@
      nr   -1  <|@ instruction NOP <|@ <|@
      nr   -1  <|@ instruction NOP <|@ <|@
      nr   -1  <|@ instruction NOP <|@ <|@
      nr   -1  <|@ instruction NOP <|@ <|@
      nr   -1  <|@ instruction stack:16|QWORD = MOVE input: rbp|QWORD moveKind: QWORD <|@ <|@
      nr   -1  <|@ instruction [] = HOTSPOTLOCKSTACK frameMapBuilder: jdk.graal.compiler.hotspot.amd64.AMD64HotSpotFrameMapBuilder@64144869 slotKind: QWORD <|@ <|@
      nr   -1  <|@ instruction v0|QWORD[.] = MOVE input: rsi|QWORD[.] moveKind: QWORD <|@ <|@
      nr   -1  <|@ instruction TESTBRANCH (x: v0|QWORD[.], y: v0|QWORD[.]) trueDestinationProbability: 9.91958358897982E-7 condition: = trueDestination: B0 -> B1 falseDestination: B0 -> B2 size: QWORD <|@ <|@
    end_IR
  end_block
  begin_block
    name "B2"
    from_bci -1
    to_bci -1
    predecessors "B0" 
    successors "B3" "B4" 
    xhandlers
    flags 
    probability 4607182409865250817
    begin_IR
      LIR
      nr   -1  <|@ instruction [] = LABEL alignment: 0 numbPhis: 0 label: ? <|@ <|@
      nr   -1  <|@ instruction NOP <|@ <|@
      nr   -1  <|@ instruction NOP <|@ <|@
      nr   -1  <|@ instruction NOP <|@ <|@
      nr   -1  <|@ instruction NOP <|@ <|@
      nr   -1  <|@ instruction NOP <|@ <|@
      nr   -1  <|@ instruction NOP <|@ <|@
      nr   -1  <|@ instruction NOP <|@ <|@
      nr   -1  <|@ instruction NOP <|@ <|@
      nr   -1  <|@ instruction NOP <|@ <|@
      nr   -1  <|@ instruction v3|DWORD = MOV input: [v0|QWORD[.] + 8] size: DWORD <|@ <|@
      nr   -1  <|@ instruction v5|QWORD = MOVE input: long[140154094223360|0x7f782b000000] <|@ <|@
      nr   -1  <|@ instruction v4|QWORD = UNCOMPRESSPOINTER (input: v3|DWORD, ~baseRegister: v5|QWORD) nonNull: true lirKindTool: jdk.graal.compiler.hotspot.amd64.AMD64HotSpotLIRKindTool@d0246bd encoding: base: 140154094223360 shift: 0 <|@ <|@
      nr   -1  <|@ instruction v6|QWORD = HOTSPOTLOADMETASPACECONSTANT input: meta{HotSpotType<Ljava/lang/String;, resolved>} <|@ <|@
      nr   -1  <|@ instruction CMPBRANCH (x: v6|QWORD, y: v4|QWORD) trueDestinationProbability: 0.43400564574488104 condition: = trueDestination: B2 -> B3 falseDestination: B2 -> B4 size: QWORD <|@ <|@
    end_IR
  end_block
  begin_block
    name "B4"
    from_bci -1
    to_bci -1
    predecessors "B2" 
    successors "B5" 
    xhandlers
    flags 
    probability 4603273238414083286
    begin_IR
      LIR
      nr   -1  <|@ instruction [] = LABEL alignment: 0 numbPhis: 0 label: ? <|@ <|@
      nr   -1  <|@ instruction NOP <|@ <|@
      nr   -1  <|@ instruction NOP <|@ <|@
      nr   -1  <|@ instruction NOP <|@ <|@
      nr   -1  <|@ instruction NOP <|@ <|@
      nr   -1  <|@ instruction NOP <|@ <|@
      nr   -1  <|@ instruction NOP <|@ <|@
      nr   -1  <|@ instruction NOP <|@ <|@
      nr   -1  <|@ instruction NOP <|@ <|@
      nr   -1  <|@ instruction NOP <|@ <|@
      nr   -1  <|@ instruction NOP <|@ <|@
      nr   -1  <|@ instruction NOP <|@ <|@
      nr   -1  <|@ instruction NOP <|@ <|@
      nr   -1  <|@ instruction v7|QWORD = MOV input: [v4|QWORD + 472] size: QWORD <|@ <|@
      nr   -1  <|@ instruction v8|QWORD = MOV input: [v7|QWORD + 64] size: QWORD <|@ <|@
      nr   -1  <|@ instruction rsi|QWORD[.] = MOVE input: v0|QWORD[.] moveKind: QWORD <|@ <|@
      nr   -1  <|@ instruction rbx|QWORD = MOVE input: v7|QWORD moveKind: QWORD <|@ <|@
      nr   -1  <|@ instruction rax|QWORD = MOVE input: v8|QWORD moveKind: QWORD <|@ <|@
      nr   -1  <|@ st <@st|@java.lang.String.valueOf(String.java:4465) [bci: 11]
locals: - 
>@ <|@ instruction rax|QWORD[.] = CALL_INDIRECT (targetAddress: rax|QWORD, metaspaceMethod: rbx|QWORD, parameters: [rsi|QWORD[.]]) temps: [] callTarget: HotSpotMethod<Object.toString()> state [bci:11] <|@ <|@
      nr   -1  <|@ instruction v9|QWORD[.] = MOVE input: rax|QWORD[.] moveKind: QWORD <|@ <|@
      nr   -1  <|@ instruction JUMP ~outgoingValues: [v9|QWORD[.]] destination: B4 -> B5 <|@ <|@
    end_IR
  end_block
  begin_block
    name "B3"
    from_bci -1
    to_bci -1
    predecessors "B2" 
    successors "B5" 
    xhandlers
    flags 
    probability 4601489962820240983
    begin_IR
      LIR
      nr   -1  <|@ instruction [] = LABEL alignment: 0 numbPhis: 0 label: ? <|@ <|@
      nr   -1  <|@ instruction NOP <|@ <|@
      nr   -1  <|@ instruction NOP <|@ <|@
      nr   -1  <|@ instruction NOP <|@ <|@
      nr   -1  <|@ instruction JUMP ~outgoingValues: [v0|QWORD[.]] destination: B3 -> B5 <|@ <|@
    end_IR
  end_block
  begin_block
    name "B5"
    from_bci -1
    to_bci -1
    predecessors "B1" "B3" "B4" 
    successors 
    xhandlers
    flags 
    probability 4607182418800017408
    begin_IR
      LIR
      nr   -1  <|@ instruction [v10|QWORD[.]] = LABEL alignment: 0 numbPhis: 1 label: ? <|@ <|@
      nr   -1  <|@ instruction NOP <|@ <|@
      nr   -1  <|@ instruction NOP <|@ <|@
      nr   -1  <|@ instruction NOP <|@ <|@
      nr   -1  <|@ instruction NOP <|@ <|@
      nr   -1  <|@ instruction NOP <|@ <|@
      nr   -1  <|@ instruction NOP <|@ <|@
      nr   -1  <|@ instruction NOP <|@ <|@
      nr   -1  <|@ instruction NOP <|@ <|@
      nr   -1  <|@ instruction rax|QWORD[.] = MOVE input: v10|QWORD[.] moveKind: QWORD <|@ <|@
      nr   -1  <|@ instruction RETURN (savedRbp: stack:16|QWORD, value: rax|QWORD[.]) isStub: false requiresReservedStackAccessCheck: false thread: r15 scratchForSafepointOnReturn: rcx config: jdk.graal.compiler.hotspot.GraalHotSpotVMConfig@4817c460 <|@ <|@
    end_IR
  end_block
  begin_block
    name "B1"
    from_bci -1
    to_bci -1
    predecessors "B0" 
    successors "B5" 
    xhandlers
    flags 
    probability 4517291217531699200
    begin_IR
      LIR
      nr   -1  <|@ instruction [] = LABEL alignment: 0 numbPhis: 0 label: ? <|@ <|@
      nr   -1  <|@ instruction NOP <|@ <|@
      nr   -1  <|@ instruction NOP <|@ <|@
      nr   -1  <|@ instruction NOP <|@ <|@
      nr   -1  <|@ instruction NOP <|@ <|@
      nr   -1  <|@ instruction NOP <|@ <|@
      nr   -1  <|@ instruction v1|QWORD[.] = HOTSPOTLOADOBJECTCONSTANT input: Object[String:"null"] <|@ <|@
      nr   -1  <|@ instruction v2|QWORD[.] = MOVE input: v1|QWORD[.] moveKind: QWORD <|@ <|@
      nr   -1  <|@ instruction JUMP ~outgoingValues: [v2|QWORD[.]] destination: B1 -> B5 <|@ <|@
    end_IR
  end_block
end_cfg
begin_bytecodes
     0: aload_0       
     1: ifnonnull     10
     4: ldc_w         #1000       // "null"
     7: goto          14
    10: aload_0       
    11: invokevirtual #281        // java.lang.Object.toString:()java.lang.String
    14: areturn       
   <|@
end_bytecodes
begin_cfg
  name "After PreAllocationOptimizationStage"
  begin_block
    name "B0"
    from_bci -1
    to_bci -1
    predecessors 
    successors "B1" "B2" 
    xhandlers
    flags 
    probability 4607182418800017408
    begin_IR
      LIR
      nr   -1  <|@ instruction [rsi|QWORD[.], rbp|QWORD] = LABEL alignment: 0 numbPhis: 0 label: ? <|@ <|@
      nr   -1  <|@ instruction NOP <|@ <|@
      nr   -1  <|@ instruction NOP <|@ <|@
      nr   -1  <|@ instruction NOP <|@ <|@
      nr   -1  <|@ instruction NOP <|@ <|@
      nr   -1  <|@ instruction NOP <|@ <|@
      nr   -1  <|@ instruction NOP <|@ <|@
      nr   -1  <|@ instruction NOP <|@ <|@
      nr   -1  <|@ instruction stack:16|QWORD = MOVE input: rbp|QWORD moveKind: QWORD <|@ <|@
      nr   -1  <|@ instruction [] = HOTSPOTLOCKSTACK frameMapBuilder: jdk.graal.compiler.hotspot.amd64.AMD64HotSpotFrameMapBuilder@64144869 slotKind: QWORD <|@ <|@
      nr   -1  <|@ instruction v0|QWORD[.] = MOVE input: rsi|QWORD[.] moveKind: QWORD <|@ <|@
      nr   -1  <|@ instruction TESTBRANCH (x: v0|QWORD[.], y: v0|QWORD[.]) trueDestinationProbability: 9.91958358897982E-7 condition: = trueDestination: B0 -> B1 falseDestination: B0 -> B2 size: QWORD <|@ <|@
    end_IR
  end_block
  begin_block
    name "B2"
    from_bci -1
    to_bci -1
    predecessors "B0" 
    successors "B3" "B4" 
    xhandlers
    flags 
    probability 4607182409865250817
    begin_IR
      LIR
      nr   -1  <|@ instruction [] = LABEL alignment: 0 numbPhis: 0 label: ? <|@ <|@
      nr   -1  <|@ instruction NOP <|@ <|@
      nr   -1  <|@ instruction NOP <|@ <|@
      nr   -1  <|@ instruction NOP <|@ <|@
      nr   -1  <|@ instruction NOP <|@ <|@
      nr   -1  <|@ instruction NOP <|@ <|@
      nr   -1  <|@ instruction NOP <|@ <|@
      nr   -1  <|@ instruction NOP <|@ <|@
      nr   -1  <|@ instruction NOP <|@ <|@
      nr   -1  <|@ instruction NOP <|@ <|@
      nr   -1  <|@ instruction v3|DWORD = MOV input: [v0|QWORD[.] + 8] size: DWORD <|@ <|@
      nr   -1  <|@ instruction v5|QWORD = MOVE input: long[140154094223360|0x7f782b000000] <|@ <|@
      nr   -1  <|@ instruction v4|QWORD = UNCOMPRESSPOINTER (input: v3|DWORD, ~baseRegister: v5|QWORD) nonNull: true lirKindTool: jdk.graal.compiler.hotspot.amd64.AMD64HotSpotLIRKindTool@d0246bd encoding: base: 140154094223360 shift: 0 <|@ <|@
      nr   -1  <|@ instruction v6|QWORD = HOTSPOTLOADMETASPACECONSTANT input: meta{HotSpotType<Ljava/lang/String;, resolved>} <|@ <|@
      nr   -1  <|@ instruction CMPBRANCH (x: v6|QWORD, y: v4|QWORD) trueDestinationProbability: 0.43400564574488104 condition: = trueDestination: B2 -> B3 falseDestination: B2 -> B4 size: QWORD <|@ <|@
    end_IR
  end_block
  begin_block
    name "B4"
    from_bci -1
    to_bci -1
    predecessors "B2" 
    successors "B5" 
    xhandlers
    flags 
    probability 4603273238414083286
    begin_IR
      LIR
      nr   -1  <|@ instruction [] = LABEL alignment: 0 numbPhis: 0 label: ? <|@ <|@
      nr   -1  <|@ instruction NOP <|@ <|@
      nr   -1  <|@ instruction NOP <|@ <|@
      nr   -1  <|@ instruction NOP <|@ <|@
      nr   -1  <|@ instruction NOP <|@ <|@
      nr   -1  <|@ instruction NOP <|@ <|@
      nr   -1  <|@ instruction NOP <|@ <|@
      nr   -1  <|@ instruction NOP <|@ <|@
      nr   -1  <|@ instruction NOP <|@ <|@
      nr   -1  <|@ instruction NOP <|@ <|@
      nr   -1  <|@ instruction NOP <|@ <|@
      nr   -1  <|@ instruction NOP <|@ <|@
      nr   -1  <|@ instruction NOP <|@ <|@
      nr   -1  <|@ instruction v7|QWORD = MOV input: [v4|QWORD + 472] size: QWORD <|@ <|@
      nr   -1  <|@ instruction v8|QWORD = MOV input: [v7|QWORD + 64] size: QWORD <|@ <|@
      nr   -1  <|@ instruction rsi|QWORD[.] = MOVE input: v0|QWORD[.] moveKind: QWORD <|@ <|@
      nr   -1  <|@ instruction rbx|QWORD = MOVE input: v7|QWORD moveKind: QWORD <|@ <|@
      nr   -1  <|@ instruction rax|QWORD = MOVE input: v8|QWORD moveKind: QWORD <|@ <|@
      nr   -1  <|@ st <@st|@java.lang.String.valueOf(String.java:4465) [bci: 11]
locals: - 
>@ <|@ instruction rax|QWORD[.] = CALL_INDIRECT (targetAddress: rax|QWORD, metaspaceMethod: rbx|QWORD, parameters: [rsi|QWORD[.]]) temps: [] callTarget: HotSpotMethod<Object.toString()> state [bci:11] <|@ <|@
      nr   -1  <|@ instruction v9|QWORD[.] = MOVE input: rax|QWORD[.] moveKind: QWORD <|@ <|@
      nr   -1  <|@ instruction JUMP ~outgoingValues: [v9|QWORD[.]] destination: B4 -> B5 <|@ <|@
    end_IR
  end_block
  begin_block
    name "B3"
    from_bci -1
    to_bci -1
    predecessors "B2" 
    successors "B5" 
    xhandlers
    flags 
    probability 4601489962820240983
    begin_IR
      LIR
      nr   -1  <|@ instruction [] = LABEL alignment: 0 numbPhis: 0 label: ? <|@ <|@
      nr   -1  <|@ instruction NOP <|@ <|@
      nr   -1  <|@ instruction NOP <|@ <|@
      nr   -1  <|@ instruction NOP <|@ <|@
      nr   -1  <|@ instruction JUMP ~outgoingValues: [v0|QWORD[.]] destination: B3 -> B5 <|@ <|@
    end_IR
  end_block
  begin_block
    name "B5"
    from_bci -1
    to_bci -1
    predecessors "B1" "B3" "B4" 
    successors 
    xhandlers
    flags 
    probability 4607182418800017408
    begin_IR
      LIR
      nr   -1  <|@ instruction [v10|QWORD[.]] = LABEL alignment: 0 numbPhis: 1 label: ? <|@ <|@
      nr   -1  <|@ instruction NOP <|@ <|@
      nr   -1  <|@ instruction NOP <|@ <|@
      nr   -1  <|@ instruction NOP <|@ <|@
      nr   -1  <|@ instruction NOP <|@ <|@
      nr   -1  <|@ instruction NOP <|@ <|@
      nr   -1  <|@ instruction NOP <|@ <|@
      nr   -1  <|@ instruction NOP <|@ <|@
      nr   -1  <|@ instruction NOP <|@ <|@
      nr   -1  <|@ instruction rax|QWORD[.] = MOVE input: v10|QWORD[.] moveKind: QWORD <|@ <|@
      nr   -1  <|@ instruction RETURN (savedRbp: stack:16|QWORD, value: rax|QWORD[.]) isStub: false requiresReservedStackAccessCheck: false thread: r15 scratchForSafepointOnReturn: rcx config: jdk.graal.compiler.hotspot.GraalHotSpotVMConfig@4817c460 <|@ <|@
    end_IR
  end_block
  begin_block
    name "B1"
    from_bci -1
    to_bci -1
    predecessors "B0" 
    successors "B5" 
    xhandlers
    flags 
    probability 4517291217531699200
    begin_IR
      LIR
      nr   -1  <|@ instruction [] = LABEL alignment: 0 numbPhis: 0 label: ? <|@ <|@
      nr   -1  <|@ instruction NOP <|@ <|@
      nr   -1  <|@ instruction NOP <|@ <|@
      nr   -1  <|@ instruction NOP <|@ <|@
      nr   -1  <|@ instruction NOP <|@ <|@
      nr   -1  <|@ instruction NOP <|@ <|@
      nr   -1  <|@ instruction v1|QWORD[.] = HOTSPOTLOADOBJECTCONSTANT input: Object[String:"null"] <|@ <|@
      nr   -1  <|@ instruction v2|QWORD[.] = MOVE input: v1|QWORD[.] moveKind: QWORD <|@ <|@
      nr   -1  <|@ instruction JUMP ~outgoingValues: [v2|QWORD[.]] destination: B1 -> B5 <|@ <|@
    end_IR
  end_block
end_cfg
begin_bytecodes
     0: aload_0       
     1: ifnonnull     10
     4: ldc_w         #1000       // "null"
     7: goto          14
    10: aload_0       
    11: invokevirtual #281        // java.lang.Object.toString:()java.lang.String
    14: areturn       
   <|@
end_bytecodes
begin_cfg
  name "After MarkBasePointers"
  begin_block
    name "B0"
    from_bci -1
    to_bci -1
    predecessors 
    successors "B1" "B2" 
    xhandlers
    flags 
    probability 4607182418800017408
    begin_IR
      LIR
      nr   -1  <|@ instruction [rsi|QWORD[.], rbp|QWORD] = LABEL alignment: 0 numbPhis: 0 label: ? <|@ <|@
      nr   -1  <|@ instruction NOP <|@ <|@
      nr   -1  <|@ instruction NOP <|@ <|@
      nr   -1  <|@ instruction NOP <|@ <|@
      nr   -1  <|@ instruction NOP <|@ <|@
      nr   -1  <|@ instruction NOP <|@ <|@
      nr   -1  <|@ instruction NOP <|@ <|@
      nr   -1  <|@ instruction NOP <|@ <|@
      nr   -1  <|@ instruction stack:16|QWORD = MOVE input: rbp|QWORD moveKind: QWORD <|@ <|@
      nr   -1  <|@ instruction [] = HOTSPOTLOCKSTACK frameMapBuilder: jdk.graal.compiler.hotspot.amd64.AMD64HotSpotFrameMapBuilder@64144869 slotKind: QWORD <|@ <|@
      nr   -1  <|@ instruction v0|QWORD[.] = MOVE input: rsi|QWORD[.] moveKind: QWORD <|@ <|@
      nr   -1  <|@ instruction TESTBRANCH (x: v0|QWORD[.], y: v0|QWORD[.]) trueDestinationProbability: 9.91958358897982E-7 condition: = trueDestination: B0 -> B1 falseDestination: B0 -> B2 size: QWORD <|@ <|@
    end_IR
  end_block
  begin_block
    name "B2"
    from_bci -1
    to_bci -1
    predecessors "B0" 
    successors "B3" "B4" 
    xhandlers
    flags 
    probability 4607182409865250817
    begin_IR
      LIR
      nr   -1  <|@ instruction [] = LABEL alignment: 0 numbPhis: 0 label: ? <|@ <|@
      nr   -1  <|@ instruction NOP <|@ <|@
      nr   -1  <|@ instruction NOP <|@ <|@
      nr   -1  <|@ instruction NOP <|@ <|@
      nr   -1  <|@ instruction NOP <|@ <|@
      nr   -1  <|@ instruction NOP <|@ <|@
      nr   -1  <|@ instruction NOP <|@ <|@
      nr   -1  <|@ instruction NOP <|@ <|@
      nr   -1  <|@ instruction NOP <|@ <|@
      nr   -1  <|@ instruction NOP <|@ <|@
      nr   -1  <|@ instruction v3|DWORD = MOV input: [v0|QWORD[.] + 8] size: DWORD <|@ <|@
      nr   -1  <|@ instruction v5|QWORD = MOVE input: long[140154094223360|0x7f782b000000] <|@ <|@
      nr   -1  <|@ instruction v4|QWORD = UNCOMPRESSPOINTER (input: v3|DWORD, ~baseRegister: v5|QWORD) nonNull: true lirKindTool: jdk.graal.compiler.hotspot.amd64.AMD64HotSpotLIRKindTool@d0246bd encoding: base: 140154094223360 shift: 0 <|@ <|@
      nr   -1  <|@ instruction v6|QWORD = HOTSPOTLOADMETASPACECONSTANT input: meta{HotSpotType<Ljava/lang/String;, resolved>} <|@ <|@
      nr   -1  <|@ instruction CMPBRANCH (x: v6|QWORD, y: v4|QWORD) trueDestinationProbability: 0.43400564574488104 condition: = trueDestination: B2 -> B3 falseDestination: B2 -> B4 size: QWORD <|@ <|@
    end_IR
  end_block
  begin_block
    name "B4"
    from_bci -1
    to_bci -1
    predecessors "B2" 
    successors "B5" 
    xhandlers
    flags 
    probability 4603273238414083286
    begin_IR
      LIR
      nr   -1  <|@ instruction [] = LABEL alignment: 0 numbPhis: 0 label: ? <|@ <|@
      nr   -1  <|@ instruction NOP <|@ <|@
      nr   -1  <|@ instruction NOP <|@ <|@
      nr   -1  <|@ instruction NOP <|@ <|@
      nr   -1  <|@ instruction NOP <|@ <|@
      nr   -1  <|@ instruction NOP <|@ <|@
      nr   -1  <|@ instruction NOP <|@ <|@
      nr   -1  <|@ instruction NOP <|@ <|@
      nr   -1  <|@ instruction NOP <|@ <|@
      nr   -1  <|@ instruction NOP <|@ <|@
      nr   -1  <|@ instruction NOP <|@ <|@
      nr   -1  <|@ instruction NOP <|@ <|@
      nr   -1  <|@ instruction NOP <|@ <|@
      nr   -1  <|@ instruction v7|QWORD = MOV input: [v4|QWORD + 472] size: QWORD <|@ <|@
      nr   -1  <|@ instruction v8|QWORD = MOV input: [v7|QWORD + 64] size: QWORD <|@ <|@
      nr   -1  <|@ instruction rsi|QWORD[.] = MOVE input: v0|QWORD[.] moveKind: QWORD <|@ <|@
      nr   -1  <|@ instruction rbx|QWORD = MOVE input: v7|QWORD moveKind: QWORD <|@ <|@
      nr   -1  <|@ instruction rax|QWORD = MOVE input: v8|QWORD moveKind: QWORD <|@ <|@
      nr   -1  <|@ st <@st|@live-base-pointers: []
java.lang.String.valueOf(String.java:4465) [bci: 11]
locals: - 
>@ <|@ instruction rax|QWORD[.] = CALL_INDIRECT (targetAddress: rax|QWORD, metaspaceMethod: rbx|QWORD, parameters: [rsi|QWORD[.]]) temps: [] callTarget: HotSpotMethod<Object.toString()> state [bci:11] <|@ <|@
      nr   -1  <|@ instruction v9|QWORD[.] = MOVE input: rax|QWORD[.] moveKind: QWORD <|@ <|@
      nr   -1  <|@ instruction JUMP ~outgoingValues: [v9|QWORD[.]] destination: B4 -> B5 <|@ <|@
    end_IR
  end_block
  begin_block
    name "B3"
    from_bci -1
    to_bci -1
    predecessors "B2" 
    successors "B5" 
    xhandlers
    flags 
    probability 4601489962820240983
    begin_IR
      LIR
      nr   -1  <|@ instruction [] = LABEL alignment: 0 numbPhis: 0 label: ? <|@ <|@
      nr   -1  <|@ instruction NOP <|@ <|@
      nr   -1  <|@ instruction NOP <|@ <|@
      nr   -1  <|@ instruction NOP <|@ <|@
      nr   -1  <|@ instruction JUMP ~outgoingValues: [v0|QWORD[.]] destination: B3 -> B5 <|@ <|@
    end_IR
  end_block
  begin_block
    name "B5"
    from_bci -1
    to_bci -1
    predecessors "B1" "B3" "B4" 
    successors 
    xhandlers
    flags 
    probability 4607182418800017408
    begin_IR
      LIR
      nr   -1  <|@ instruction [v10|QWORD[.]] = LABEL alignment: 0 numbPhis: 1 label: ? <|@ <|@
      nr   -1  <|@ instruction NOP <|@ <|@
      nr   -1  <|@ instruction NOP <|@ <|@
      nr   -1  <|@ instruction NOP <|@ <|@
      nr   -1  <|@ instruction NOP <|@ <|@
      nr   -1  <|@ instruction NOP <|@ <|@
      nr   -1  <|@ instruction NOP <|@ <|@
      nr   -1  <|@ instruction NOP <|@ <|@
      nr   -1  <|@ instruction NOP <|@ <|@
      nr   -1  <|@ instruction rax|QWORD[.] = MOVE input: v10|QWORD[.] moveKind: QWORD <|@ <|@
      nr   -1  <|@ instruction RETURN (savedRbp: stack:16|QWORD, value: rax|QWORD[.]) isStub: false requiresReservedStackAccessCheck: false thread: r15 scratchForSafepointOnReturn: rcx config: jdk.graal.compiler.hotspot.GraalHotSpotVMConfig@4817c460 <|@ <|@
    end_IR
  end_block
  begin_block
    name "B1"
    from_bci -1
    to_bci -1
    predecessors "B0" 
    successors "B5" 
    xhandlers
    flags 
    probability 4517291217531699200
    begin_IR
      LIR
      nr   -1  <|@ instruction [] = LABEL alignment: 0 numbPhis: 0 label: ? <|@ <|@
      nr   -1  <|@ instruction NOP <|@ <|@
      nr   -1  <|@ instruction NOP <|@ <|@
      nr   -1  <|@ instruction NOP <|@ <|@
      nr   -1  <|@ instruction NOP <|@ <|@
      nr   -1  <|@ instruction NOP <|@ <|@
      nr   -1  <|@ instruction v1|QWORD[.] = HOTSPOTLOADOBJECTCONSTANT input: Object[String:"null"] <|@ <|@
      nr   -1  <|@ instruction v2|QWORD[.] = MOVE input: v1|QWORD[.] moveKind: QWORD <|@ <|@
      nr   -1  <|@ instruction JUMP ~outgoingValues: [v2|QWORD[.]] destination: B1 -> B5 <|@ <|@
    end_IR
  end_block
end_cfg
begin_bytecodes
     0: aload_0       
     1: ifnonnull     10
     4: ldc_w         #1000       // "null"
     7: goto          14
    10: aload_0       
    11: invokevirtual #281        // java.lang.Object.toString:()java.lang.String
    14: areturn       
   <|@
end_bytecodes
begin_cfg
  name "Before register allocation"
  begin_block
    name "B0"
    from_bci -1
    to_bci -1
    predecessors 
    successors "B1" "B2" 
    xhandlers
    flags 
    probability 4607182418800017408
    begin_IR
      LIR
      nr    0  <|@ instruction [rsi|QWORD[.], rbp|QWORD] = LABEL alignment: 0 numbPhis: 0 label: ? <|@ <|@
      nr    2  <|@ instruction NOP <|@ <|@
      nr    4  <|@ instruction NOP <|@ <|@
      nr    6  <|@ instruction NOP <|@ <|@
      nr    8  <|@ instruction NOP <|@ <|@
      nr   10  <|@ instruction NOP <|@ <|@
      nr   12  <|@ instruction NOP <|@ <|@
      nr   14  <|@ instruction NOP <|@ <|@
      nr   16  <|@ instruction stack:16|QWORD = MOVE input: rbp|QWORD moveKind: QWORD <|@ <|@
      nr   18  <|@ instruction [] = HOTSPOTLOCKSTACK frameMapBuilder: jdk.graal.compiler.hotspot.amd64.AMD64HotSpotFrameMapBuilder@64144869 slotKind: QWORD <|@ <|@
      nr   20  <|@ instruction v0|QWORD[.] = MOVE input: rsi|QWORD[.] moveKind: QWORD <|@ <|@
      nr   22  <|@ instruction TESTBRANCH (x: v0|QWORD[.], y: v0|QWORD[.]) trueDestinationProbability: 9.91958358897982E-7 condition: = trueDestination: B0 -> B1 falseDestination: B0 -> B2 size: QWORD <|@ <|@
    end_IR
  end_block
  begin_block
    name "B2"
    from_bci -1
    to_bci -1
    predecessors "B0" 
    successors "B3" "B4" 
    xhandlers
    flags 
    probability 4607182409865250817
    begin_IR
      LIR
      nr   24  <|@ instruction [] = LABEL alignment: 0 numbPhis: 0 label: ? <|@ <|@
      nr   26  <|@ instruction NOP <|@ <|@
      nr   28  <|@ instruction NOP <|@ <|@
      nr   30  <|@ instruction NOP <|@ <|@
      nr   32  <|@ instruction NOP <|@ <|@
      nr   34  <|@ instruction NOP <|@ <|@
      nr   36  <|@ instruction NOP <|@ <|@
      nr   38  <|@ instruction NOP <|@ <|@
      nr   40  <|@ instruction NOP <|@ <|@
      nr   42  <|@ instruction NOP <|@ <|@
      nr   44  <|@ instruction v3|DWORD = MOV input: [v0|QWORD[.] + 8] size: DWORD <|@ <|@
      nr   46  <|@ instruction v5|QWORD = MOVE input: long[140154094223360|0x7f782b000000] <|@ <|@
      nr   48  <|@ instruction v4|QWORD = UNCOMPRESSPOINTER (input: v3|DWORD, ~baseRegister: v5|QWORD) nonNull: true lirKindTool: jdk.graal.compiler.hotspot.amd64.AMD64HotSpotLIRKindTool@d0246bd encoding: base: 140154094223360 shift: 0 <|@ <|@
      nr   50  <|@ instruction v6|QWORD = HOTSPOTLOADMETASPACECONSTANT input: meta{HotSpotType<Ljava/lang/String;, resolved>} <|@ <|@
      nr   52  <|@ instruction CMPBRANCH (x: v6|QWORD, y: v4|QWORD) trueDestinationProbability: 0.43400564574488104 condition: = trueDestination: B2 -> B3 falseDestination: B2 -> B4 size: QWORD <|@ <|@
    end_IR
  end_block
  begin_block
    name "B4"
    from_bci -1
    to_bci -1
    predecessors "B2" 
    successors "B5" 
    xhandlers
    flags 
    probability 4603273238414083286
    begin_IR
      LIR
      nr   54  <|@ instruction [] = LABEL alignment: 0 numbPhis: 0 label: ? <|@ <|@
      nr   56  <|@ instruction NOP <|@ <|@
      nr   58  <|@ instruction NOP <|@ <|@
      nr   60  <|@ instruction NOP <|@ <|@
      nr   62  <|@ instruction NOP <|@ <|@
      nr   64  <|@ instruction NOP <|@ <|@
      nr   66  <|@ instruction NOP <|@ <|@
      nr   68  <|@ instruction NOP <|@ <|@
      nr   70  <|@ instruction NOP <|@ <|@
      nr   72  <|@ instruction NOP <|@ <|@
      nr   74  <|@ instruction NOP <|@ <|@
      nr   76  <|@ instruction NOP <|@ <|@
      nr   78  <|@ instruction NOP <|@ <|@
      nr   80  <|@ instruction v7|QWORD = MOV input: [v4|QWORD + 472] size: QWORD <|@ <|@
      nr   82  <|@ instruction v8|QWORD = MOV input: [v7|QWORD + 64] size: QWORD <|@ <|@
      nr   84  <|@ instruction rsi|QWORD[.] = MOVE input: v0|QWORD[.] moveKind: QWORD <|@ <|@
      nr   86  <|@ instruction rbx|QWORD = MOVE input: v7|QWORD moveKind: QWORD <|@ <|@
      nr   88  <|@ instruction rax|QWORD = MOVE input: v8|QWORD moveKind: QWORD <|@ <|@
      nr   90  <|@ st <@st|@live-base-pointers: []
java.lang.String.valueOf(String.java:4465) [bci: 11]
locals: - 
>@ <|@ instruction rax|QWORD[.] = CALL_INDIRECT (targetAddress: rax|QWORD, metaspaceMethod: rbx|QWORD, parameters: [rsi|QWORD[.]]) temps: [] callTarget: HotSpotMethod<Object.toString()> state [bci:11] <|@ <|@
      nr   92  <|@ instruction v9|QWORD[.] = MOVE input: rax|QWORD[.] moveKind: QWORD <|@ <|@
      nr   94  <|@ instruction JUMP ~outgoingValues: [v9|QWORD[.]] destination: B4 -> B5 <|@ <|@
    end_IR
  end_block
  begin_block
    name "B3"
    from_bci -1
    to_bci -1
    predecessors "B2" 
    successors "B5" 
    xhandlers
    flags 
    probability 4601489962820240983
    begin_IR
      LIR
      nr   96  <|@ instruction [] = LABEL alignment: 0 numbPhis: 0 label: ? <|@ <|@
      nr   98  <|@ instruction NOP <|@ <|@
      nr  100  <|@ instruction NOP <|@ <|@
      nr  102  <|@ instruction NOP <|@ <|@
      nr  104  <|@ instruction JUMP ~outgoingValues: [v0|QWORD[.]] destination: B3 -> B5 <|@ <|@
    end_IR
  end_block
  begin_block
    name "B5"
    from_bci -1
    to_bci -1
    predecessors "B1" "B3" "B4" 
    successors 
    xhandlers
    flags 
    probability 4607182418800017408
    begin_IR
      LIR
      nr  106  <|@ instruction [v10|QWORD[.]] = LABEL alignment: 0 numbPhis: 1 label: ? <|@ <|@
      nr  108  <|@ instruction NOP <|@ <|@
      nr  110  <|@ instruction NOP <|@ <|@
      nr  112  <|@ instruction NOP <|@ <|@
      nr  114  <|@ instruction NOP <|@ <|@
      nr  116  <|@ instruction NOP <|@ <|@
      nr  118  <|@ instruction NOP <|@ <|@
      nr  120  <|@ instruction NOP <|@ <|@
      nr  122  <|@ instruction NOP <|@ <|@
      nr  124  <|@ instruction rax|QWORD[.] = MOVE input: v10|QWORD[.] moveKind: QWORD <|@ <|@
      nr  126  <|@ instruction RETURN (savedRbp: stack:16|QWORD, value: rax|QWORD[.]) isStub: false requiresReservedStackAccessCheck: false thread: r15 scratchForSafepointOnReturn: rcx config: jdk.graal.compiler.hotspot.GraalHotSpotVMConfig@4817c460 <|@ <|@
    end_IR
  end_block
  begin_block
    name "B1"
    from_bci -1
    to_bci -1
    predecessors "B0" 
    successors "B5" 
    xhandlers
    flags 
    probability 4517291217531699200
    begin_IR
      LIR
      nr  128  <|@ instruction [] = LABEL alignment: 0 numbPhis: 0 label: ? <|@ <|@
      nr  130  <|@ instruction NOP <|@ <|@
      nr  132  <|@ instruction NOP <|@ <|@
      nr  134  <|@ instruction NOP <|@ <|@
      nr  136  <|@ instruction NOP <|@ <|@
      nr  138  <|@ instruction NOP <|@ <|@
      nr  140  <|@ instruction v1|QWORD[.] = HOTSPOTLOADOBJECTCONSTANT input: Object[String:"null"] <|@ <|@
      nr  142  <|@ instruction v2|QWORD[.] = MOVE input: v1|QWORD[.] moveKind: QWORD <|@ <|@
      nr  144  <|@ instruction JUMP ~outgoingValues: [v2|QWORD[.]] destination: B1 -> B5 <|@ <|@
    end_IR
  end_block
end_cfg
begin_bytecodes
     0: aload_0       
     1: ifnonnull     10
     4: ldc_w         #1000       // "null"
     7: goto          14
    10: aload_0       
    11: invokevirtual #281        // java.lang.Object.toString:()java.lang.String
    14: areturn       
   <|@
end_bytecodes
begin_cfg
  name "After SSALinearScanLifetimeAnalysis"
  begin_block
    name "B0"
    from_bci -1
    to_bci -1
    predecessors 
    successors "B1" "B2" 
    xhandlers
    flags 
    probability 4607182418800017408
    begin_IR
      LIR
      nr    0  <|@ instruction [rsi|QWORD[.], rbp|QWORD] = LABEL alignment: 0 numbPhis: 0 label: ? <|@ <|@
      nr    2  <|@ instruction NOP <|@ <|@
      nr    4  <|@ instruction NOP <|@ <|@
      nr    6  <|@ instruction NOP <|@ <|@
      nr    8  <|@ instruction NOP <|@ <|@
      nr   10  <|@ instruction NOP <|@ <|@
      nr   12  <|@ instruction NOP <|@ <|@
      nr   14  <|@ instruction NOP <|@ <|@
      nr   16  <|@ instruction stack:16|QWORD = MOVE input: rbp|QWORD moveKind: QWORD <|@ <|@
      nr   18  <|@ instruction [] = HOTSPOTLOCKSTACK frameMapBuilder: jdk.graal.compiler.hotspot.amd64.AMD64HotSpotFrameMapBuilder@64144869 slotKind: QWORD <|@ <|@
      nr   20  <|@ instruction v0|QWORD[.] = MOVE input: rsi|QWORD[.] moveKind: QWORD <|@ <|@
      nr   22  <|@ instruction TESTBRANCH (x: v0|QWORD[.], y: v0|QWORD[.]) trueDestinationProbability: 9.91958358897982E-7 condition: = trueDestination: B0 -> B1 falseDestination: B0 -> B2 size: QWORD <|@ <|@
    end_IR
  end_block
  begin_block
    name "B2"
    from_bci -1
    to_bci -1
    predecessors "B0" 
    successors "B3" "B4" 
    xhandlers
    flags 
    probability 4607182409865250817
    begin_IR
      LIR
      nr   24  <|@ instruction [] = LABEL alignment: 0 numbPhis: 0 label: ? <|@ <|@
      nr   26  <|@ instruction NOP <|@ <|@
      nr   28  <|@ instruction NOP <|@ <|@
      nr   30  <|@ instruction NOP <|@ <|@
      nr   32  <|@ instruction NOP <|@ <|@
      nr   34  <|@ instruction NOP <|@ <|@
      nr   36  <|@ instruction NOP <|@ <|@
      nr   38  <|@ instruction NOP <|@ <|@
      nr   40  <|@ instruction NOP <|@ <|@
      nr   42  <|@ instruction NOP <|@ <|@
      nr   44  <|@ instruction v3|DWORD = MOV input: [v0|QWORD[.] + 8] size: DWORD <|@ <|@
      nr   46  <|@ instruction v5|QWORD = MOVE input: long[140154094223360|0x7f782b000000] <|@ <|@
      nr   48  <|@ instruction v4|QWORD = UNCOMPRESSPOINTER (input: v3|DWORD, ~baseRegister: v5|QWORD) nonNull: true lirKindTool: jdk.graal.compiler.hotspot.amd64.AMD64HotSpotLIRKindTool@d0246bd encoding: base: 140154094223360 shift: 0 <|@ <|@
      nr   50  <|@ instruction v6|QWORD = HOTSPOTLOADMETASPACECONSTANT input: meta{HotSpotType<Ljava/lang/String;, resolved>} <|@ <|@
      nr   52  <|@ instruction CMPBRANCH (x: v6|QWORD, y: v4|QWORD) trueDestinationProbability: 0.43400564574488104 condition: = trueDestination: B2 -> B3 falseDestination: B2 -> B4 size: QWORD <|@ <|@
    end_IR
  end_block
  begin_block
    name "B4"
    from_bci -1
    to_bci -1
    predecessors "B2" 
    successors "B5" 
    xhandlers
    flags 
    probability 4603273238414083286
    begin_IR
      LIR
      nr   54  <|@ instruction [] = LABEL alignment: 0 numbPhis: 0 label: ? <|@ <|@
      nr   56  <|@ instruction NOP <|@ <|@
      nr   58  <|@ instruction NOP <|@ <|@
      nr   60  <|@ instruction NOP <|@ <|@
      nr   62  <|@ instruction NOP <|@ <|@
      nr   64  <|@ instruction NOP <|@ <|@
      nr   66  <|@ instruction NOP <|@ <|@
      nr   68  <|@ instruction NOP <|@ <|@
      nr   70  <|@ instruction NOP <|@ <|@
      nr   72  <|@ instruction NOP <|@ <|@
      nr   74  <|@ instruction NOP <|@ <|@
      nr   76  <|@ instruction NOP <|@ <|@
      nr   78  <|@ instruction NOP <|@ <|@
      nr   80  <|@ instruction v7|QWORD = MOV input: [v4|QWORD + 472] size: QWORD <|@ <|@
      nr   82  <|@ instruction v8|QWORD = MOV input: [v7|QWORD + 64] size: QWORD <|@ <|@
      nr   84  <|@ instruction rsi|QWORD[.] = MOVE input: v0|QWORD[.] moveKind: QWORD <|@ <|@
      nr   86  <|@ instruction rbx|QWORD = MOVE input: v7|QWORD moveKind: QWORD <|@ <|@
      nr   88  <|@ instruction rax|QWORD = MOVE input: v8|QWORD moveKind: QWORD <|@ <|@
      nr   90  <|@ st <@st|@live-base-pointers: []
java.lang.String.valueOf(String.java:4465) [bci: 11]
locals: - 
>@ <|@ instruction rax|QWORD[.] = CALL_INDIRECT (targetAddress: rax|QWORD, metaspaceMethod: rbx|QWORD, parameters: [rsi|QWORD[.]]) temps: [] callTarget: HotSpotMethod<Object.toString()> state [bci:11] <|@ <|@
      nr   92  <|@ instruction v9|QWORD[.] = MOVE input: rax|QWORD[.] moveKind: QWORD <|@ <|@
      nr   94  <|@ instruction JUMP ~outgoingValues: [v9|QWORD[.]] destination: B4 -> B5 <|@ <|@
    end_IR
  end_block
  begin_block
    name "B3"
    from_bci -1
    to_bci -1
    predecessors "B2" 
    successors "B5" 
    xhandlers
    flags 
    probability 4601489962820240983
    begin_IR
      LIR
      nr   96  <|@ instruction [] = LABEL alignment: 0 numbPhis: 0 label: ? <|@ <|@
      nr   98  <|@ instruction NOP <|@ <|@
      nr  100  <|@ instruction NOP <|@ <|@
      nr  102  <|@ instruction NOP <|@ <|@
      nr  104  <|@ instruction JUMP ~outgoingValues: [v0|QWORD[.]] destination: B3 -> B5 <|@ <|@
    end_IR
  end_block
  begin_block
    name "B5"
    from_bci -1
    to_bci -1
    predecessors "B1" "B3" "B4" 
    successors 
    xhandlers
    flags 
    probability 4607182418800017408
    begin_IR
      LIR
      nr  106  <|@ instruction [v10|QWORD[.]] = LABEL alignment: 0 numbPhis: 1 label: ? <|@ <|@
      nr  108  <|@ instruction NOP <|@ <|@
      nr  110  <|@ instruction NOP <|@ <|@
      nr  112  <|@ instruction NOP <|@ <|@
      nr  114  <|@ instruction NOP <|@ <|@
      nr  116  <|@ instruction NOP <|@ <|@
      nr  118  <|@ instruction NOP <|@ <|@
      nr  120  <|@ instruction NOP <|@ <|@
      nr  122  <|@ instruction NOP <|@ <|@
      nr  124  <|@ instruction rax|QWORD[.] = MOVE input: v10|QWORD[.] moveKind: QWORD <|@ <|@
      nr  126  <|@ instruction RETURN (savedRbp: stack:16|QWORD, value: rax|QWORD[.]) isStub: false requiresReservedStackAccessCheck: false thread: r15 scratchForSafepointOnReturn: rcx config: jdk.graal.compiler.hotspot.GraalHotSpotVMConfig@4817c460 <|@ <|@
    end_IR
  end_block
  begin_block
    name "B1"
    from_bci -1
    to_bci -1
    predecessors "B0" 
    successors "B5" 
    xhandlers
    flags 
    probability 4517291217531699200
    begin_IR
      LIR
      nr  128  <|@ instruction [] = LABEL alignment: 0 numbPhis: 0 label: ? <|@ <|@
      nr  130  <|@ instruction NOP <|@ <|@
      nr  132  <|@ instruction NOP <|@ <|@
      nr  134  <|@ instruction NOP <|@ <|@
      nr  136  <|@ instruction NOP <|@ <|@
      nr  138  <|@ instruction NOP <|@ <|@
      nr  140  <|@ instruction v1|QWORD[.] = HOTSPOTLOADOBJECTCONSTANT input: Object[String:"null"] <|@ <|@
      nr  142  <|@ instruction v2|QWORD[.] = MOVE input: v1|QWORD[.] moveKind: QWORD <|@ <|@
      nr  144  <|@ instruction JUMP ~outgoingValues: [v2|QWORD[.]] destination: B1 -> B5 <|@ <|@
    end_IR
  end_block
end_cfg
begin_bytecodes
     0: aload_0       
     1: ifnonnull     10
     4: ldc_w         #1000       // "null"
     7: goto          14
    10: aload_0       
    11: invokevirtual #281        // java.lang.Object.toString:()java.lang.String
    14: areturn       
   <|@
end_bytecodes
begin_intervals
  name "Before register allocation"
  rax|q fixed "[rax|q]" rax|q v8|q [0, 1[[88, 92[[124, 126[ "NoOptimization"
  rcx|- fixed "[rcx|-]" rcx|- -1 [0, 1[[90, 91[ "NoDefinitionFound"
  rdx|- fixed "[rdx|-]" rdx|- -1 [0, 1[[90, 91[ "NoDefinitionFound"
  rbx|- fixed "[rbx|-]" rbx|- v7|q [0, 1[[86, 91[ "NoSpillStore"
  rbp|- fixed "[rbp|-]" rbp|- -1 [0, 16[[90, 91[ "NoSpillStore"
  rsi|- fixed "[rsi|-]" rsi|- v0|q [0, 20[[84, 91[ "NoOptimization"
  rdi|- fixed "[rdi|-]" rdi|- -1 [0, 1[[90, 91[ "NoDefinitionFound"
  r8|- fixed "[r8|-]" r8|- -1 [0, 1[[90, 91[ "NoDefinitionFound"
  r9|- fixed "[r9|-]" r9|- -1 [0, 1[[90, 91[ "NoDefinitionFound"
  r10|- fixed "[r10|-]" r10|- -1 [0, 1[[90, 91[ "NoDefinitionFound"
  r11|- fixed "[r11|-]" r11|- -1 [0, 1[[90, 91[ "NoDefinitionFound"
  r13|- fixed "[r13|-]" r13|- -1 [0, 1[[90, 91[ "NoDefinitionFound"
  r14|- fixed "[r14|-]" r14|- -1 [0, 1[[90, 91[ "NoDefinitionFound"
  xmm0|- fixed "[xmm0|-]" xmm0|- -1 [0, 1[[90, 91[ "NoDefinitionFound"
  xmm1|- fixed "[xmm1|-]" xmm1|- -1 [0, 1[[90, 91[ "NoDefinitionFound"
  xmm2|- fixed "[xmm2|-]" xmm2|- -1 [0, 1[[90, 91[ "NoDefinitionFound"
  xmm3|- fixed "[xmm3|-]" xmm3|- -1 [0, 1[[90, 91[ "NoDefinitionFound"
  xmm4|- fixed "[xmm4|-]" xmm4|- -1 [0, 1[[90, 91[ "NoDefinitionFound"
  xmm5|- fixed "[xmm5|-]" xmm5|- -1 [0, 1[[90, 91[ "NoDefinitionFound"
  xmm6|- fixed "[xmm6|-]" xmm6|- -1 [0, 1[[90, 91[ "NoDefinitionFound"
  xmm7|- fixed "[xmm7|-]" xmm7|- -1 [0, 1[[90, 91[ "NoDefinitionFound"
  xmm8|- fixed "[xmm8|-]" xmm8|- -1 [0, 1[[90, 91[ "NoDefinitionFound"
  xmm9|- fixed "[xmm9|-]" xmm9|- -1 [0, 1[[90, 91[ "NoDefinitionFound"
  xmm10|- fixed "[xmm10|-]" xmm10|- -1 [0, 1[[90, 91[ "NoDefinitionFound"
  xmm11|- fixed "[xmm11|-]" xmm11|- -1 [0, 1[[90, 91[ "NoDefinitionFound"
  xmm12|- fixed "[xmm12|-]" xmm12|- -1 [0, 1[[90, 91[ "NoDefinitionFound"
  xmm13|- fixed "[xmm13|-]" xmm13|- -1 [0, 1[[90, 91[ "NoDefinitionFound"
  xmm14|- fixed "[xmm14|-]" xmm14|- -1 [0, 1[[90, 91[ "NoDefinitionFound"
  xmm15|- fixed "[xmm15|-]" xmm15|- -1 [0, 1[[90, 91[ "NoDefinitionFound"
  v0|q QWORD "[v0|q]" v0|q rsi|- [20, 84[[96, 105[20 MustHaveRegister 22 MustHaveRegister 44 MustHaveRegister 84 ShouldHaveRegister 104 ShouldHaveRegister  "NoSpillStore"
  v1|q QWORD "[v1|q]" v1|q -1 [140, 142[140 MustHaveRegister 142 ShouldHaveRegister  "NoSpillStore"
  v2|q QWORD "[v2|q]" v2|q v1|q [142, 145[142 MustHaveRegister 144 ShouldHaveRegister  "NoSpillStore"
  v3|d DWORD "[v3|d]" v3|d -1 [44, 48[44 MustHaveRegister 48 MustHaveRegister  "NoSpillStore"
  v4|q QWORD "[v4|q]" v4|q v3|d [48, 80[48 MustHaveRegister 52 ShouldHaveRegister 80 MustHaveRegister  "NoSpillStore"
  v5|q QWORD "[v5|q]" v5|q -1 [46, 49[46 MustHaveRegister 48 MustHaveRegister  "NoSpillStore"
  v6|q QWORD "[v6|q]" v6|q -1 [50, 52[50 MustHaveRegister 52 MustHaveRegister  "NoSpillStore"
  v7|q QWORD "[v7|q]" v7|q -1 [80, 86[80 MustHaveRegister 82 MustHaveRegister 86 ShouldHaveRegister  "NoSpillStore"
  v8|q QWORD "[v8|q]" v8|q -1 [82, 88[82 MustHaveRegister 88 ShouldHaveRegister  "NoSpillStore"
  v9|q QWORD "[v9|q]" v9|q rax|q [92, 95[92 MustHaveRegister 94 ShouldHaveRegister  "NoSpillStore"
  v10|q QWORD "[v10|q]" v10|q v9|q [106, 124[124 ShouldHaveRegister  "NoSpillStore"
end_intervals
begin_intervals
  name "After register allocation"
  rax|q fixed "[rax|q]" rax|q v8|q [0, 1[[88, 92[[124, 126[ "NoOptimization"
  rcx|- fixed "[rcx|-]" rcx|- -1 [0, 1[[90, 91[ "NoDefinitionFound"
  rdx|- fixed "[rdx|-]" rdx|- -1 [0, 1[[90, 91[ "NoDefinitionFound"
  rbx|- fixed "[rbx|-]" rbx|- v7|q [0, 1[[86, 91[ "NoSpillStore"
  rbp|- fixed "[rbp|-]" rbp|- -1 [0, 16[[90, 91[ "NoSpillStore"
  rsi|- fixed "[rsi|-]" rsi|- v0|q [0, 20[[84, 91[ "NoOptimization"
  rdi|- fixed "[rdi|-]" rdi|- -1 [0, 1[[90, 91[ "NoDefinitionFound"
  r8|- fixed "[r8|-]" r8|- -1 [0, 1[[90, 91[ "NoDefinitionFound"
  r9|- fixed "[r9|-]" r9|- -1 [0, 1[[90, 91[ "NoDefinitionFound"
  r10|- fixed "[r10|-]" r10|- -1 [0, 1[[90, 91[ "NoDefinitionFound"
  r11|- fixed "[r11|-]" r11|- -1 [0, 1[[90, 91[ "NoDefinitionFound"
  r13|- fixed "[r13|-]" r13|- -1 [0, 1[[90, 91[ "NoDefinitionFound"
  r14|- fixed "[r14|-]" r14|- -1 [0, 1[[90, 91[ "NoDefinitionFound"
  xmm0|- fixed "[xmm0|-]" xmm0|- -1 [0, 1[[90, 91[ "NoDefinitionFound"
  xmm1|- fixed "[xmm1|-]" xmm1|- -1 [0, 1[[90, 91[ "NoDefinitionFound"
  xmm2|- fixed "[xmm2|-]" xmm2|- -1 [0, 1[[90, 91[ "NoDefinitionFound"
  xmm3|- fixed "[xmm3|-]" xmm3|- -1 [0, 1[[90, 91[ "NoDefinitionFound"
  xmm4|- fixed "[xmm4|-]" xmm4|- -1 [0, 1[[90, 91[ "NoDefinitionFound"
  xmm5|- fixed "[xmm5|-]" xmm5|- -1 [0, 1[[90, 91[ "NoDefinitionFound"
  xmm6|- fixed "[xmm6|-]" xmm6|- -1 [0, 1[[90, 91[ "NoDefinitionFound"
  xmm7|- fixed "[xmm7|-]" xmm7|- -1 [0, 1[[90, 91[ "NoDefinitionFound"
  xmm8|- fixed "[xmm8|-]" xmm8|- -1 [0, 1[[90, 91[ "NoDefinitionFound"
  xmm9|- fixed "[xmm9|-]" xmm9|- -1 [0, 1[[90, 91[ "NoDefinitionFound"
  xmm10|- fixed "[xmm10|-]" xmm10|- -1 [0, 1[[90, 91[ "NoDefinitionFound"
  xmm11|- fixed "[xmm11|-]" xmm11|- -1 [0, 1[[90, 91[ "NoDefinitionFound"
  xmm12|- fixed "[xmm12|-]" xmm12|- -1 [0, 1[[90, 91[ "NoDefinitionFound"
  xmm13|- fixed "[xmm13|-]" xmm13|- -1 [0, 1[[90, 91[ "NoDefinitionFound"
  xmm14|- fixed "[xmm14|-]" xmm14|- -1 [0, 1[[90, 91[ "NoDefinitionFound"
  xmm15|- fixed "[xmm15|-]" xmm15|- -1 [0, 1[[90, 91[ "NoDefinitionFound"
  v0|q QWORD "[rsi|q]" v0|q rsi|- [20, 84[[96, 105[20 MustHaveRegister 22 MustHaveRegister 44 MustHaveRegister 84 ShouldHaveRegister 104 ShouldHaveRegister  "NoSpillStore"
  v1|q QWORD "[r10|q]" v1|q -1 [140, 142[140 MustHaveRegister 142 ShouldHaveRegister  "NoSpillStore"
  v2|q QWORD "[r10|q]" v2|q v1|q [142, 145[142 MustHaveRegister 144 ShouldHaveRegister  "NoSpillStore"
  v3|d DWORD "[rbx|d]" v3|d -1 [44, 48[44 MustHaveRegister 48 MustHaveRegister  "NoSpillStore"
  v4|q QWORD "[rbx|q]" v4|q v3|d [48, 80[48 MustHaveRegister 52 ShouldHaveRegister 80 MustHaveRegister  "NoSpillStore"
  v5|q QWORD "[rax|q]" v5|q -1 [46, 49[46 MustHaveRegister 48 MustHaveRegister  "NoSpillStore"
  v6|q QWORD "[rax|q]" v6|q -1 [50, 52[50 MustHaveRegister 52 MustHaveRegister  "NoSpillStore"
  v7|q QWORD "[rbx|q]" v7|q -1 [80, 86[80 MustHaveRegister 82 MustHaveRegister 86 ShouldHaveRegister  "NoSpillStore"
  v8|q QWORD "[rax|q]" v8|q -1 [82, 88[82 MustHaveRegister 88 ShouldHaveRegister  "NoSpillStore"
  v9|q QWORD "[rax|q]" v9|q rax|q [92, 95[92 MustHaveRegister 94 ShouldHaveRegister  "NoSpillStore"
  v10|q QWORD "[rax|q]" v10|q v9|q [106, 124[124 ShouldHaveRegister  "NoSpillStore"
end_intervals
begin_cfg
  name "After LinearScanRegisterAllocation"
  begin_block
    name "B0"
    from_bci -1
    to_bci -1
    predecessors 
    successors "B1" "B2" 
    xhandlers
    flags 
    probability 4607182418800017408
    begin_IR
      LIR
      nr    0  <|@ instruction [rsi|QWORD[.], rbp|QWORD] = LABEL alignment: 0 numbPhis: 0 label: ? <|@ <|@
      nr    2  <|@ instruction NOP <|@ <|@
      nr    4  <|@ instruction NOP <|@ <|@
      nr    6  <|@ instruction NOP <|@ <|@
      nr    8  <|@ instruction NOP <|@ <|@
      nr   10  <|@ instruction NOP <|@ <|@
      nr   12  <|@ instruction NOP <|@ <|@
      nr   14  <|@ instruction NOP <|@ <|@
      nr   16  <|@ instruction stack:16|QWORD = MOVE input: rbp|QWORD moveKind: QWORD <|@ <|@
      nr   18  <|@ instruction [] = HOTSPOTLOCKSTACK frameMapBuilder: jdk.graal.compiler.hotspot.amd64.AMD64HotSpotFrameMapBuilder@64144869 slotKind: QWORD <|@ <|@
      nr   20  <|@ instruction v0|QWORD[.] = MOVE input: rsi|QWORD[.] moveKind: QWORD <|@ <|@
      nr   22  <|@ instruction TESTBRANCH (x: v0|QWORD[.], y: v0|QWORD[.]) trueDestinationProbability: 9.91958358897982E-7 condition: = trueDestination: B0 -> B1 falseDestination: B0 -> B2 size: QWORD <|@ <|@
    end_IR
  end_block
  begin_block
    name "B2"
    from_bci -1
    to_bci -1
    predecessors "B0" 
    successors "B3" "B4" 
    xhandlers
    flags 
    probability 4607182409865250817
    begin_IR
      LIR
      nr   24  <|@ instruction [] = LABEL alignment: 0 numbPhis: 0 label: ? <|@ <|@
      nr   26  <|@ instruction NOP <|@ <|@
      nr   28  <|@ instruction NOP <|@ <|@
      nr   30  <|@ instruction NOP <|@ <|@
      nr   32  <|@ instruction NOP <|@ <|@
      nr   34  <|@ instruction NOP <|@ <|@
      nr   36  <|@ instruction NOP <|@ <|@
      nr   38  <|@ instruction NOP <|@ <|@
      nr   40  <|@ instruction NOP <|@ <|@
      nr   42  <|@ instruction NOP <|@ <|@
      nr   44  <|@ instruction v3|DWORD = MOV input: [v0|QWORD[.] + 8] size: DWORD <|@ <|@
      nr   46  <|@ instruction v5|QWORD = MOVE input: long[140154094223360|0x7f782b000000] <|@ <|@
      nr   48  <|@ instruction v4|QWORD = UNCOMPRESSPOINTER (input: v3|DWORD, ~baseRegister: v5|QWORD) nonNull: true lirKindTool: jdk.graal.compiler.hotspot.amd64.AMD64HotSpotLIRKindTool@d0246bd encoding: base: 140154094223360 shift: 0 <|@ <|@
      nr   50  <|@ instruction v6|QWORD = HOTSPOTLOADMETASPACECONSTANT input: meta{HotSpotType<Ljava/lang/String;, resolved>} <|@ <|@
      nr   52  <|@ instruction CMPBRANCH (x: v6|QWORD, y: v4|QWORD) trueDestinationProbability: 0.43400564574488104 condition: = trueDestination: B2 -> B3 falseDestination: B2 -> B4 size: QWORD <|@ <|@
    end_IR
  end_block
  begin_block
    name "B4"
    from_bci -1
    to_bci -1
    predecessors "B2" 
    successors "B5" 
    xhandlers
    flags 
    probability 4603273238414083286
    begin_IR
      LIR
      nr   54  <|@ instruction [] = LABEL alignment: 0 numbPhis: 0 label: ? <|@ <|@
      nr   56  <|@ instruction NOP <|@ <|@
      nr   58  <|@ instruction NOP <|@ <|@
      nr   60  <|@ instruction NOP <|@ <|@
      nr   62  <|@ instruction NOP <|@ <|@
      nr   64  <|@ instruction NOP <|@ <|@
      nr   66  <|@ instruction NOP <|@ <|@
      nr   68  <|@ instruction NOP <|@ <|@
      nr   70  <|@ instruction NOP <|@ <|@
      nr   72  <|@ instruction NOP <|@ <|@
      nr   74  <|@ instruction NOP <|@ <|@
      nr   76  <|@ instruction NOP <|@ <|@
      nr   78  <|@ instruction NOP <|@ <|@
      nr   80  <|@ instruction v7|QWORD = MOV input: [v4|QWORD + 472] size: QWORD <|@ <|@
      nr   82  <|@ instruction v8|QWORD = MOV input: [v7|QWORD + 64] size: QWORD <|@ <|@
      nr   84  <|@ instruction rsi|QWORD[.] = MOVE input: v0|QWORD[.] moveKind: QWORD <|@ <|@
      nr   86  <|@ instruction rbx|QWORD = MOVE input: v7|QWORD moveKind: QWORD <|@ <|@
      nr   88  <|@ instruction rax|QWORD = MOVE input: v8|QWORD moveKind: QWORD <|@ <|@
      nr   90  <|@ st <@st|@live-base-pointers: []
java.lang.String.valueOf(String.java:4465) [bci: 11]
locals: - 
>@ <|@ instruction rax|QWORD[.] = CALL_INDIRECT (targetAddress: rax|QWORD, metaspaceMethod: rbx|QWORD, parameters: [rsi|QWORD[.]]) temps: [] callTarget: HotSpotMethod<Object.toString()> state [bci:11] <|@ <|@
      nr   92  <|@ instruction v9|QWORD[.] = MOVE input: rax|QWORD[.] moveKind: QWORD <|@ <|@
      nr   94  <|@ instruction JUMP ~outgoingValues: [v9|QWORD[.]] destination: B4 -> B5 <|@ <|@
    end_IR
  end_block
  begin_block
    name "B3"
    from_bci -1
    to_bci -1
    predecessors "B2" 
    successors "B5" 
    xhandlers
    flags 
    probability 4601489962820240983
    begin_IR
      LIR
      nr   96  <|@ instruction [] = LABEL alignment: 0 numbPhis: 0 label: ? <|@ <|@
      nr   98  <|@ instruction NOP <|@ <|@
      nr  100  <|@ instruction NOP <|@ <|@
      nr  102  <|@ instruction NOP <|@ <|@
      nr  104  <|@ instruction JUMP ~outgoingValues: [v0|QWORD[.]] destination: B3 -> B5 <|@ <|@
    end_IR
  end_block
  begin_block
    name "B5"
    from_bci -1
    to_bci -1
    predecessors "B1" "B3" "B4" 
    successors 
    xhandlers
    flags 
    probability 4607182418800017408
    begin_IR
      LIR
      nr  106  <|@ instruction [v10|QWORD[.]] = LABEL alignment: 0 numbPhis: 1 label: ? <|@ <|@
      nr  108  <|@ instruction NOP <|@ <|@
      nr  110  <|@ instruction NOP <|@ <|@
      nr  112  <|@ instruction NOP <|@ <|@
      nr  114  <|@ instruction NOP <|@ <|@
      nr  116  <|@ instruction NOP <|@ <|@
      nr  118  <|@ instruction NOP <|@ <|@
      nr  120  <|@ instruction NOP <|@ <|@
      nr  122  <|@ instruction NOP <|@ <|@
      nr  124  <|@ instruction rax|QWORD[.] = MOVE input: v10|QWORD[.] moveKind: QWORD <|@ <|@
      nr  126  <|@ instruction RETURN (savedRbp: stack:16|QWORD, value: rax|QWORD[.]) isStub: false requiresReservedStackAccessCheck: false thread: r15 scratchForSafepointOnReturn: rcx config: jdk.graal.compiler.hotspot.GraalHotSpotVMConfig@4817c460 <|@ <|@
    end_IR
  end_block
  begin_block
    name "B1"
    from_bci -1
    to_bci -1
    predecessors "B0" 
    successors "B5" 
    xhandlers
    flags 
    probability 4517291217531699200
    begin_IR
      LIR
      nr  128  <|@ instruction [] = LABEL alignment: 0 numbPhis: 0 label: ? <|@ <|@
      nr  130  <|@ instruction NOP <|@ <|@
      nr  132  <|@ instruction NOP <|@ <|@
      nr  134  <|@ instruction NOP <|@ <|@
      nr  136  <|@ instruction NOP <|@ <|@
      nr  138  <|@ instruction NOP <|@ <|@
      nr  140  <|@ instruction v1|QWORD[.] = HOTSPOTLOADOBJECTCONSTANT input: Object[String:"null"] <|@ <|@
      nr  142  <|@ instruction v2|QWORD[.] = MOVE input: v1|QWORD[.] moveKind: QWORD <|@ <|@
      nr  144  <|@ instruction JUMP ~outgoingValues: [v2|QWORD[.]] destination: B1 -> B5 <|@ <|@
    end_IR
  end_block
end_cfg
begin_bytecodes
     0: aload_0       
     1: ifnonnull     10
     4: ldc_w         #1000       // "null"
     7: goto          14
    10: aload_0       
    11: invokevirtual #281        // java.lang.Object.toString:()java.lang.String
    14: areturn       
   <|@
end_bytecodes
begin_intervals
  name "After optimize spill position"
  rax|q fixed "[rax|q]" rax|q v8|q [0, 1[[88, 92[[124, 126[ "NoOptimization"
  rcx|- fixed "[rcx|-]" rcx|- -1 [0, 1[[90, 91[ "NoDefinitionFound"
  rdx|- fixed "[rdx|-]" rdx|- -1 [0, 1[[90, 91[ "NoDefinitionFound"
  rbx|- fixed "[rbx|-]" rbx|- v7|q [0, 1[[86, 91[ "NoSpillStore"
  rbp|- fixed "[rbp|-]" rbp|- -1 [0, 16[[90, 91[ "NoSpillStore"
  rsi|- fixed "[rsi|-]" rsi|- v0|q [0, 20[[84, 91[ "NoOptimization"
  rdi|- fixed "[rdi|-]" rdi|- -1 [0, 1[[90, 91[ "NoDefinitionFound"
  r8|- fixed "[r8|-]" r8|- -1 [0, 1[[90, 91[ "NoDefinitionFound"
  r9|- fixed "[r9|-]" r9|- -1 [0, 1[[90, 91[ "NoDefinitionFound"
  r10|- fixed "[r10|-]" r10|- -1 [0, 1[[90, 91[ "NoDefinitionFound"
  r11|- fixed "[r11|-]" r11|- -1 [0, 1[[90, 91[ "NoDefinitionFound"
  r13|- fixed "[r13|-]" r13|- -1 [0, 1[[90, 91[ "NoDefinitionFound"
  r14|- fixed "[r14|-]" r14|- -1 [0, 1[[90, 91[ "NoDefinitionFound"
  xmm0|- fixed "[xmm0|-]" xmm0|- -1 [0, 1[[90, 91[ "NoDefinitionFound"
  xmm1|- fixed "[xmm1|-]" xmm1|- -1 [0, 1[[90, 91[ "NoDefinitionFound"
  xmm2|- fixed "[xmm2|-]" xmm2|- -1 [0, 1[[90, 91[ "NoDefinitionFound"
  xmm3|- fixed "[xmm3|-]" xmm3|- -1 [0, 1[[90, 91[ "NoDefinitionFound"
  xmm4|- fixed "[xmm4|-]" xmm4|- -1 [0, 1[[90, 91[ "NoDefinitionFound"
  xmm5|- fixed "[xmm5|-]" xmm5|- -1 [0, 1[[90, 91[ "NoDefinitionFound"
  xmm6|- fixed "[xmm6|-]" xmm6|- -1 [0, 1[[90, 91[ "NoDefinitionFound"
  xmm7|- fixed "[xmm7|-]" xmm7|- -1 [0, 1[[90, 91[ "NoDefinitionFound"
  xmm8|- fixed "[xmm8|-]" xmm8|- -1 [0, 1[[90, 91[ "NoDefinitionFound"
  xmm9|- fixed "[xmm9|-]" xmm9|- -1 [0, 1[[90, 91[ "NoDefinitionFound"
  xmm10|- fixed "[xmm10|-]" xmm10|- -1 [0, 1[[90, 91[ "NoDefinitionFound"
  xmm11|- fixed "[xmm11|-]" xmm11|- -1 [0, 1[[90, 91[ "NoDefinitionFound"
  xmm12|- fixed "[xmm12|-]" xmm12|- -1 [0, 1[[90, 91[ "NoDefinitionFound"
  xmm13|- fixed "[xmm13|-]" xmm13|- -1 [0, 1[[90, 91[ "NoDefinitionFound"
  xmm14|- fixed "[xmm14|-]" xmm14|- -1 [0, 1[[90, 91[ "NoDefinitionFound"
  xmm15|- fixed "[xmm15|-]" xmm15|- -1 [0, 1[[90, 91[ "NoDefinitionFound"
  v0|q QWORD "[rsi|q]" v0|q rsi|- [20, 84[[96, 105[20 MustHaveRegister 22 MustHaveRegister 44 MustHaveRegister 84 ShouldHaveRegister 104 ShouldHaveRegister  "NoSpillStore"
  v1|q QWORD "[r10|q]" v1|q -1 [140, 142[140 MustHaveRegister 142 ShouldHaveRegister  "NoSpillStore"
  v2|q QWORD "[r10|q]" v2|q v1|q [142, 145[142 MustHaveRegister 144 ShouldHaveRegister  "NoSpillStore"
  v3|d DWORD "[rbx|d]" v3|d -1 [44, 48[44 MustHaveRegister 48 MustHaveRegister  "NoSpillStore"
  v4|q QWORD "[rbx|q]" v4|q v3|d [48, 80[48 MustHaveRegister 52 ShouldHaveRegister 80 MustHaveRegister  "NoSpillStore"
  v5|q QWORD "[rax|q]" v5|q -1 [46, 49[46 MustHaveRegister 48 MustHaveRegister  "NoSpillStore"
  v6|q QWORD "[rax|q]" v6|q -1 [50, 52[50 MustHaveRegister 52 MustHaveRegister  "NoSpillStore"
  v7|q QWORD "[rbx|q]" v7|q -1 [80, 86[80 MustHaveRegister 82 MustHaveRegister 86 ShouldHaveRegister  "NoSpillStore"
  v8|q QWORD "[rax|q]" v8|q -1 [82, 88[82 MustHaveRegister 88 ShouldHaveRegister  "NoSpillStore"
  v9|q QWORD "[rax|q]" v9|q rax|q [92, 95[92 MustHaveRegister 94 ShouldHaveRegister  "NoSpillStore"
  v10|q QWORD "[rax|q]" v10|q v9|q [106, 124[124 ShouldHaveRegister  "NoSpillStore"
end_intervals
begin_cfg
  name "After LinearScanOptimizeSpillPosition"
  begin_block
    name "B0"
    from_bci -1
    to_bci -1
    predecessors 
    successors "B1" "B2" 
    xhandlers
    flags 
    probability 4607182418800017408
    begin_IR
      LIR
      nr    0  <|@ instruction [rsi|QWORD[.], rbp|QWORD] = LABEL alignment: 0 numbPhis: 0 label: ? <|@ <|@
      nr    2  <|@ instruction NOP <|@ <|@
      nr    4  <|@ instruction NOP <|@ <|@
      nr    6  <|@ instruction NOP <|@ <|@
      nr    8  <|@ instruction NOP <|@ <|@
      nr   10  <|@ instruction NOP <|@ <|@
      nr   12  <|@ instruction NOP <|@ <|@
      nr   14  <|@ instruction NOP <|@ <|@
      nr   16  <|@ instruction stack:16|QWORD = MOVE input: rbp|QWORD moveKind: QWORD <|@ <|@
      nr   18  <|@ instruction [] = HOTSPOTLOCKSTACK frameMapBuilder: jdk.graal.compiler.hotspot.amd64.AMD64HotSpotFrameMapBuilder@64144869 slotKind: QWORD <|@ <|@
      nr   20  <|@ instruction v0|QWORD[.] = MOVE input: rsi|QWORD[.] moveKind: QWORD <|@ <|@
      nr   22  <|@ instruction TESTBRANCH (x: v0|QWORD[.], y: v0|QWORD[.]) trueDestinationProbability: 9.91958358897982E-7 condition: = trueDestination: B0 -> B1 falseDestination: B0 -> B2 size: QWORD <|@ <|@
    end_IR
  end_block
  begin_block
    name "B2"
    from_bci -1
    to_bci -1
    predecessors "B0" 
    successors "B3" "B4" 
    xhandlers
    flags 
    probability 4607182409865250817
    begin_IR
      LIR
      nr   24  <|@ instruction [] = LABEL alignment: 0 numbPhis: 0 label: ? <|@ <|@
      nr   26  <|@ instruction NOP <|@ <|@
      nr   28  <|@ instruction NOP <|@ <|@
      nr   30  <|@ instruction NOP <|@ <|@
      nr   32  <|@ instruction NOP <|@ <|@
      nr   34  <|@ instruction NOP <|@ <|@
      nr   36  <|@ instruction NOP <|@ <|@
      nr   38  <|@ instruction NOP <|@ <|@
      nr   40  <|@ instruction NOP <|@ <|@
      nr   42  <|@ instruction NOP <|@ <|@
      nr   44  <|@ instruction v3|DWORD = MOV input: [v0|QWORD[.] + 8] size: DWORD <|@ <|@
      nr   46  <|@ instruction v5|QWORD = MOVE input: long[140154094223360|0x7f782b000000] <|@ <|@
      nr   48  <|@ instruction v4|QWORD = UNCOMPRESSPOINTER (input: v3|DWORD, ~baseRegister: v5|QWORD) nonNull: true lirKindTool: jdk.graal.compiler.hotspot.amd64.AMD64HotSpotLIRKindTool@d0246bd encoding: base: 140154094223360 shift: 0 <|@ <|@
      nr   50  <|@ instruction v6|QWORD = HOTSPOTLOADMETASPACECONSTANT input: meta{HotSpotType<Ljava/lang/String;, resolved>} <|@ <|@
      nr   52  <|@ instruction CMPBRANCH (x: v6|QWORD, y: v4|QWORD) trueDestinationProbability: 0.43400564574488104 condition: = trueDestination: B2 -> B3 falseDestination: B2 -> B4 size: QWORD <|@ <|@
    end_IR
  end_block
  begin_block
    name "B4"
    from_bci -1
    to_bci -1
    predecessors "B2" 
    successors "B5" 
    xhandlers
    flags 
    probability 4603273238414083286
    begin_IR
      LIR
      nr   54  <|@ instruction [] = LABEL alignment: 0 numbPhis: 0 label: ? <|@ <|@
      nr   56  <|@ instruction NOP <|@ <|@
      nr   58  <|@ instruction NOP <|@ <|@
      nr   60  <|@ instruction NOP <|@ <|@
      nr   62  <|@ instruction NOP <|@ <|@
      nr   64  <|@ instruction NOP <|@ <|@
      nr   66  <|@ instruction NOP <|@ <|@
      nr   68  <|@ instruction NOP <|@ <|@
      nr   70  <|@ instruction NOP <|@ <|@
      nr   72  <|@ instruction NOP <|@ <|@
      nr   74  <|@ instruction NOP <|@ <|@
      nr   76  <|@ instruction NOP <|@ <|@
      nr   78  <|@ instruction NOP <|@ <|@
      nr   80  <|@ instruction v7|QWORD = MOV input: [v4|QWORD + 472] size: QWORD <|@ <|@
      nr   82  <|@ instruction v8|QWORD = MOV input: [v7|QWORD + 64] size: QWORD <|@ <|@
      nr   84  <|@ instruction rsi|QWORD[.] = MOVE input: v0|QWORD[.] moveKind: QWORD <|@ <|@
      nr   86  <|@ instruction rbx|QWORD = MOVE input: v7|QWORD moveKind: QWORD <|@ <|@
      nr   88  <|@ instruction rax|QWORD = MOVE input: v8|QWORD moveKind: QWORD <|@ <|@
      nr   90  <|@ st <@st|@live-base-pointers: []
java.lang.String.valueOf(String.java:4465) [bci: 11]
locals: - 
>@ <|@ instruction rax|QWORD[.] = CALL_INDIRECT (targetAddress: rax|QWORD, metaspaceMethod: rbx|QWORD, parameters: [rsi|QWORD[.]]) temps: [] callTarget: HotSpotMethod<Object.toString()> state [bci:11] <|@ <|@
      nr   92  <|@ instruction v9|QWORD[.] = MOVE input: rax|QWORD[.] moveKind: QWORD <|@ <|@
      nr   94  <|@ instruction JUMP ~outgoingValues: [v9|QWORD[.]] destination: B4 -> B5 <|@ <|@
    end_IR
  end_block
  begin_block
    name "B3"
    from_bci -1
    to_bci -1
    predecessors "B2" 
    successors "B5" 
    xhandlers
    flags 
    probability 4601489962820240983
    begin_IR
      LIR
      nr   96  <|@ instruction [] = LABEL alignment: 0 numbPhis: 0 label: ? <|@ <|@
      nr   98  <|@ instruction NOP <|@ <|@
      nr  100  <|@ instruction NOP <|@ <|@
      nr  102  <|@ instruction NOP <|@ <|@
      nr  104  <|@ instruction JUMP ~outgoingValues: [v0|QWORD[.]] destination: B3 -> B5 <|@ <|@
    end_IR
  end_block
  begin_block
    name "B5"
    from_bci -1
    to_bci -1
    predecessors "B1" "B3" "B4" 
    successors 
    xhandlers
    flags 
    probability 4607182418800017408
    begin_IR
      LIR
      nr  106  <|@ instruction [v10|QWORD[.]] = LABEL alignment: 0 numbPhis: 1 label: ? <|@ <|@
      nr  108  <|@ instruction NOP <|@ <|@
      nr  110  <|@ instruction NOP <|@ <|@
      nr  112  <|@ instruction NOP <|@ <|@
      nr  114  <|@ instruction NOP <|@ <|@
      nr  116  <|@ instruction NOP <|@ <|@
      nr  118  <|@ instruction NOP <|@ <|@
      nr  120  <|@ instruction NOP <|@ <|@
      nr  122  <|@ instruction NOP <|@ <|@
      nr  124  <|@ instruction rax|QWORD[.] = MOVE input: v10|QWORD[.] moveKind: QWORD <|@ <|@
      nr  126  <|@ instruction RETURN (savedRbp: stack:16|QWORD, value: rax|QWORD[.]) isStub: false requiresReservedStackAccessCheck: false thread: r15 scratchForSafepointOnReturn: rcx config: jdk.graal.compiler.hotspot.GraalHotSpotVMConfig@4817c460 <|@ <|@
    end_IR
  end_block
  begin_block
    name "B1"
    from_bci -1
    to_bci -1
    predecessors "B0" 
    successors "B5" 
    xhandlers
    flags 
    probability 4517291217531699200
    begin_IR
      LIR
      nr  128  <|@ instruction [] = LABEL alignment: 0 numbPhis: 0 label: ? <|@ <|@
      nr  130  <|@ instruction NOP <|@ <|@
      nr  132  <|@ instruction NOP <|@ <|@
      nr  134  <|@ instruction NOP <|@ <|@
      nr  136  <|@ instruction NOP <|@ <|@
      nr  138  <|@ instruction NOP <|@ <|@
      nr  140  <|@ instruction v1|QWORD[.] = HOTSPOTLOADOBJECTCONSTANT input: Object[String:"null"] <|@ <|@
      nr  142  <|@ instruction v2|QWORD[.] = MOVE input: v1|QWORD[.] moveKind: QWORD <|@ <|@
      nr  144  <|@ instruction JUMP ~outgoingValues: [v2|QWORD[.]] destination: B1 -> B5 <|@ <|@
    end_IR
  end_block
end_cfg
begin_bytecodes
     0: aload_0       
     1: ifnonnull     10
     4: ldc_w         #1000       // "null"
     7: goto          14
    10: aload_0       
    11: invokevirtual #281        // java.lang.Object.toString:()java.lang.String
    14: areturn       
   <|@
end_bytecodes
begin_intervals
  name "After resolve data flow"
  rax|q fixed "[rax|q]" rax|q v8|q [0, 1[[88, 92[[124, 126[ "NoOptimization"
  rcx|- fixed "[rcx|-]" rcx|- -1 [0, 1[[90, 91[ "NoDefinitionFound"
  rdx|- fixed "[rdx|-]" rdx|- -1 [0, 1[[90, 91[ "NoDefinitionFound"
  rbx|- fixed "[rbx|-]" rbx|- v7|q [0, 1[[86, 91[ "NoSpillStore"
  rbp|- fixed "[rbp|-]" rbp|- -1 [0, 16[[90, 91[ "NoSpillStore"
  rsi|- fixed "[rsi|-]" rsi|- v0|q [0, 20[[84, 91[ "NoOptimization"
  rdi|- fixed "[rdi|-]" rdi|- -1 [0, 1[[90, 91[ "NoDefinitionFound"
  r8|- fixed "[r8|-]" r8|- -1 [0, 1[[90, 91[ "NoDefinitionFound"
  r9|- fixed "[r9|-]" r9|- -1 [0, 1[[90, 91[ "NoDefinitionFound"
  r10|- fixed "[r10|-]" r10|- -1 [0, 1[[90, 91[ "NoDefinitionFound"
  r11|- fixed "[r11|-]" r11|- -1 [0, 1[[90, 91[ "NoDefinitionFound"
  r13|- fixed "[r13|-]" r13|- -1 [0, 1[[90, 91[ "NoDefinitionFound"
  r14|- fixed "[r14|-]" r14|- -1 [0, 1[[90, 91[ "NoDefinitionFound"
  xmm0|- fixed "[xmm0|-]" xmm0|- -1 [0, 1[[90, 91[ "NoDefinitionFound"
  xmm1|- fixed "[xmm1|-]" xmm1|- -1 [0, 1[[90, 91[ "NoDefinitionFound"
  xmm2|- fixed "[xmm2|-]" xmm2|- -1 [0, 1[[90, 91[ "NoDefinitionFound"
  xmm3|- fixed "[xmm3|-]" xmm3|- -1 [0, 1[[90, 91[ "NoDefinitionFound"
  xmm4|- fixed "[xmm4|-]" xmm4|- -1 [0, 1[[90, 91[ "NoDefinitionFound"
  xmm5|- fixed "[xmm5|-]" xmm5|- -1 [0, 1[[90, 91[ "NoDefinitionFound"
  xmm6|- fixed "[xmm6|-]" xmm6|- -1 [0, 1[[90, 91[ "NoDefinitionFound"
  xmm7|- fixed "[xmm7|-]" xmm7|- -1 [0, 1[[90, 91[ "NoDefinitionFound"
  xmm8|- fixed "[xmm8|-]" xmm8|- -1 [0, 1[[90, 91[ "NoDefinitionFound"
  xmm9|- fixed "[xmm9|-]" xmm9|- -1 [0, 1[[90, 91[ "NoDefinitionFound"
  xmm10|- fixed "[xmm10|-]" xmm10|- -1 [0, 1[[90, 91[ "NoDefinitionFound"
  xmm11|- fixed "[xmm11|-]" xmm11|- -1 [0, 1[[90, 91[ "NoDefinitionFound"
  xmm12|- fixed "[xmm12|-]" xmm12|- -1 [0, 1[[90, 91[ "NoDefinitionFound"
  xmm13|- fixed "[xmm13|-]" xmm13|- -1 [0, 1[[90, 91[ "NoDefinitionFound"
  xmm14|- fixed "[xmm14|-]" xmm14|- -1 [0, 1[[90, 91[ "NoDefinitionFound"
  xmm15|- fixed "[xmm15|-]" xmm15|- -1 [0, 1[[90, 91[ "NoDefinitionFound"
  v0|q QWORD "[rsi|q]" v0|q rsi|- [20, 84[[96, 105[20 MustHaveRegister 22 MustHaveRegister 44 MustHaveRegister 84 ShouldHaveRegister 104 ShouldHaveRegister  "NoSpillStore"
  v1|q QWORD "[r10|q]" v1|q -1 [140, 142[140 MustHaveRegister 142 ShouldHaveRegister  "NoSpillStore"
  v2|q QWORD "[r10|q]" v2|q v1|q [142, 145[142 MustHaveRegister 144 ShouldHaveRegister  "NoSpillStore"
  v3|d DWORD "[rbx|d]" v3|d -1 [44, 48[44 MustHaveRegister 48 MustHaveRegister  "NoSpillStore"
  v4|q QWORD "[rbx|q]" v4|q v3|d [48, 80[48 MustHaveRegister 52 ShouldHaveRegister 80 MustHaveRegister  "NoSpillStore"
  v5|q QWORD "[rax|q]" v5|q -1 [46, 49[46 MustHaveRegister 48 MustHaveRegister  "NoSpillStore"
  v6|q QWORD "[rax|q]" v6|q -1 [50, 52[50 MustHaveRegister 52 MustHaveRegister  "NoSpillStore"
  v7|q QWORD "[rbx|q]" v7|q -1 [80, 86[80 MustHaveRegister 82 MustHaveRegister 86 ShouldHaveRegister  "NoSpillStore"
  v8|q QWORD "[rax|q]" v8|q -1 [82, 88[82 MustHaveRegister 88 ShouldHaveRegister  "NoSpillStore"
  v9|q QWORD "[rax|q]" v9|q rax|q [92, 95[92 MustHaveRegister 94 ShouldHaveRegister  "NoSpillStore"
  v10|q QWORD "[rax|q]" v10|q v9|q [106, 124[124 ShouldHaveRegister  "NoSpillStore"
end_intervals
begin_cfg
  name "After SSALinearScanResolveDataFlow"
  begin_block
    name "B0"
    from_bci -1
    to_bci -1
    predecessors 
    successors "B1" "B2" 
    xhandlers
    flags 
    probability 4607182418800017408
    begin_IR
      LIR
      nr    0  <|@ instruction [rsi|QWORD[.], rbp|QWORD] = LABEL alignment: 0 numbPhis: 0 label: ? <|@ <|@
      nr    2  <|@ instruction NOP <|@ <|@
      nr    4  <|@ instruction NOP <|@ <|@
      nr    6  <|@ instruction NOP <|@ <|@
      nr    8  <|@ instruction NOP <|@ <|@
      nr   10  <|@ instruction NOP <|@ <|@
      nr   12  <|@ instruction NOP <|@ <|@
      nr   14  <|@ instruction NOP <|@ <|@
      nr   16  <|@ instruction stack:16|QWORD = MOVE input: rbp|QWORD moveKind: QWORD <|@ <|@
      nr   18  <|@ instruction [] = HOTSPOTLOCKSTACK frameMapBuilder: jdk.graal.compiler.hotspot.amd64.AMD64HotSpotFrameMapBuilder@64144869 slotKind: QWORD <|@ <|@
      nr   20  <|@ instruction v0|QWORD[.] = MOVE input: rsi|QWORD[.] moveKind: QWORD <|@ <|@
      nr   22  <|@ instruction TESTBRANCH (x: v0|QWORD[.], y: v0|QWORD[.]) trueDestinationProbability: 9.91958358897982E-7 condition: = trueDestination: B0 -> B1 falseDestination: B0 -> B2 size: QWORD <|@ <|@
    end_IR
  end_block
  begin_block
    name "B2"
    from_bci -1
    to_bci -1
    predecessors "B0" 
    successors "B3" "B4" 
    xhandlers
    flags 
    probability 4607182409865250817
    begin_IR
      LIR
      nr   24  <|@ instruction [] = LABEL alignment: 0 numbPhis: 0 label: ? <|@ <|@
      nr   26  <|@ instruction NOP <|@ <|@
      nr   28  <|@ instruction NOP <|@ <|@
      nr   30  <|@ instruction NOP <|@ <|@
      nr   32  <|@ instruction NOP <|@ <|@
      nr   34  <|@ instruction NOP <|@ <|@
      nr   36  <|@ instruction NOP <|@ <|@
      nr   38  <|@ instruction NOP <|@ <|@
      nr   40  <|@ instruction NOP <|@ <|@
      nr   42  <|@ instruction NOP <|@ <|@
      nr   44  <|@ instruction v3|DWORD = MOV input: [v0|QWORD[.] + 8] size: DWORD <|@ <|@
      nr   46  <|@ instruction v5|QWORD = MOVE input: long[140154094223360|0x7f782b000000] <|@ <|@
      nr   48  <|@ instruction v4|QWORD = UNCOMPRESSPOINTER (input: v3|DWORD, ~baseRegister: v5|QWORD) nonNull: true lirKindTool: jdk.graal.compiler.hotspot.amd64.AMD64HotSpotLIRKindTool@d0246bd encoding: base: 140154094223360 shift: 0 <|@ <|@
      nr   50  <|@ instruction v6|QWORD = HOTSPOTLOADMETASPACECONSTANT input: meta{HotSpotType<Ljava/lang/String;, resolved>} <|@ <|@
      nr   52  <|@ instruction CMPBRANCH (x: v6|QWORD, y: v4|QWORD) trueDestinationProbability: 0.43400564574488104 condition: = trueDestination: B2 -> B3 falseDestination: B2 -> B4 size: QWORD <|@ <|@
    end_IR
  end_block
  begin_block
    name "B4"
    from_bci -1
    to_bci -1
    predecessors "B2" 
    successors "B5" 
    xhandlers
    flags 
    probability 4603273238414083286
    begin_IR
      LIR
      nr   54  <|@ instruction [] = LABEL alignment: 0 numbPhis: 0 label: ? <|@ <|@
      nr   56  <|@ instruction NOP <|@ <|@
      nr   58  <|@ instruction NOP <|@ <|@
      nr   60  <|@ instruction NOP <|@ <|@
      nr   62  <|@ instruction NOP <|@ <|@
      nr   64  <|@ instruction NOP <|@ <|@
      nr   66  <|@ instruction NOP <|@ <|@
      nr   68  <|@ instruction NOP <|@ <|@
      nr   70  <|@ instruction NOP <|@ <|@
      nr   72  <|@ instruction NOP <|@ <|@
      nr   74  <|@ instruction NOP <|@ <|@
      nr   76  <|@ instruction NOP <|@ <|@
      nr   78  <|@ instruction NOP <|@ <|@
      nr   80  <|@ instruction v7|QWORD = MOV input: [v4|QWORD + 472] size: QWORD <|@ <|@
      nr   82  <|@ instruction v8|QWORD = MOV input: [v7|QWORD + 64] size: QWORD <|@ <|@
      nr   84  <|@ instruction rsi|QWORD[.] = MOVE input: v0|QWORD[.] moveKind: QWORD <|@ <|@
      nr   86  <|@ instruction rbx|QWORD = MOVE input: v7|QWORD moveKind: QWORD <|@ <|@
      nr   88  <|@ instruction rax|QWORD = MOVE input: v8|QWORD moveKind: QWORD <|@ <|@
      nr   90  <|@ st <@st|@live-base-pointers: []
java.lang.String.valueOf(String.java:4465) [bci: 11]
locals: - 
>@ <|@ instruction rax|QWORD[.] = CALL_INDIRECT (targetAddress: rax|QWORD, metaspaceMethod: rbx|QWORD, parameters: [rsi|QWORD[.]]) temps: [] callTarget: HotSpotMethod<Object.toString()> state [bci:11] <|@ <|@
      nr   92  <|@ instruction v9|QWORD[.] = MOVE input: rax|QWORD[.] moveKind: QWORD <|@ <|@
      nr   94  <|@ instruction JUMP ~outgoingValues: [] destination: B4 -> B5 <|@ <|@
    end_IR
  end_block
  begin_block
    name "B3"
    from_bci -1
    to_bci -1
    predecessors "B2" 
    successors "B5" 
    xhandlers
    flags 
    probability 4601489962820240983
    begin_IR
      LIR
      nr   96  <|@ instruction [] = LABEL alignment: 0 numbPhis: 0 label: ? <|@ <|@
      nr   98  <|@ instruction NOP <|@ <|@
      nr  100  <|@ instruction NOP <|@ <|@
      nr  102  <|@ instruction NOP <|@ <|@
      nr   -1  <|@ instruction v10|QWORD[.] = MOVE input: v0|QWORD[.] moveKind: QWORD // MoveResolver resolve mapping <|@ <|@
      nr  104  <|@ instruction JUMP ~outgoingValues: [] destination: B3 -> B5 <|@ <|@
    end_IR
  end_block
  begin_block
    name "B5"
    from_bci -1
    to_bci -1
    predecessors "B1" "B3" "B4" 
    successors 
    xhandlers
    flags 
    probability 4607182418800017408
    begin_IR
      LIR
      nr  106  <|@ instruction [v10|QWORD[.]] = LABEL alignment: 0 numbPhis: 1 label: ? <|@ <|@
      nr  108  <|@ instruction NOP <|@ <|@
      nr  110  <|@ instruction NOP <|@ <|@
      nr  112  <|@ instruction NOP <|@ <|@
      nr  114  <|@ instruction NOP <|@ <|@
      nr  116  <|@ instruction NOP <|@ <|@
      nr  118  <|@ instruction NOP <|@ <|@
      nr  120  <|@ instruction NOP <|@ <|@
      nr  122  <|@ instruction NOP <|@ <|@
      nr  124  <|@ instruction rax|QWORD[.] = MOVE input: v10|QWORD[.] moveKind: QWORD <|@ <|@
      nr  126  <|@ instruction RETURN (savedRbp: stack:16|QWORD, value: rax|QWORD[.]) isStub: false requiresReservedStackAccessCheck: false thread: r15 scratchForSafepointOnReturn: rcx config: jdk.graal.compiler.hotspot.GraalHotSpotVMConfig@4817c460 <|@ <|@
    end_IR
  end_block
  begin_block
    name "B1"
    from_bci -1
    to_bci -1
    predecessors "B0" 
    successors "B5" 
    xhandlers
    flags 
    probability 4517291217531699200
    begin_IR
      LIR
      nr  128  <|@ instruction [] = LABEL alignment: 0 numbPhis: 0 label: ? <|@ <|@
      nr  130  <|@ instruction NOP <|@ <|@
      nr  132  <|@ instruction NOP <|@ <|@
      nr  134  <|@ instruction NOP <|@ <|@
      nr  136  <|@ instruction NOP <|@ <|@
      nr  138  <|@ instruction NOP <|@ <|@
      nr  140  <|@ instruction v1|QWORD[.] = HOTSPOTLOADOBJECTCONSTANT input: Object[String:"null"] <|@ <|@
      nr  142  <|@ instruction v2|QWORD[.] = MOVE input: v1|QWORD[.] moveKind: QWORD <|@ <|@
      nr   -1  <|@ instruction v10|QWORD[.] = MOVE input: v2|QWORD[.] moveKind: QWORD // MoveResolver resolve mapping <|@ <|@
      nr  144  <|@ instruction JUMP ~outgoingValues: [] destination: B1 -> B5 <|@ <|@
    end_IR
  end_block
end_cfg
begin_bytecodes
     0: aload_0       
     1: ifnonnull     10
     4: ldc_w         #1000       // "null"
     7: goto          14
    10: aload_0       
    11: invokevirtual #281        // java.lang.Object.toString:()java.lang.String
    14: areturn       
   <|@
end_bytecodes
begin_cfg
  name "After SSALinearScanEliminateSpillMove"
  begin_block
    name "B0"
    from_bci -1
    to_bci -1
    predecessors 
    successors "B1" "B2" 
    xhandlers
    flags 
    probability 4607182418800017408
    begin_IR
      LIR
      nr    0  <|@ instruction [rsi|QWORD[.], rbp|QWORD] = LABEL alignment: 0 numbPhis: 0 label: ? <|@ <|@
      nr    2  <|@ instruction NOP <|@ <|@
      nr    4  <|@ instruction NOP <|@ <|@
      nr    6  <|@ instruction NOP <|@ <|@
      nr    8  <|@ instruction NOP <|@ <|@
      nr   10  <|@ instruction NOP <|@ <|@
      nr   12  <|@ instruction NOP <|@ <|@
      nr   14  <|@ instruction NOP <|@ <|@
      nr   16  <|@ instruction stack:16|QWORD = MOVE input: rbp|QWORD moveKind: QWORD <|@ <|@
      nr   18  <|@ instruction [] = HOTSPOTLOCKSTACK frameMapBuilder: jdk.graal.compiler.hotspot.amd64.AMD64HotSpotFrameMapBuilder@64144869 slotKind: QWORD <|@ <|@
      nr   20  <|@ instruction v0|QWORD[.] = MOVE input: rsi|QWORD[.] moveKind: QWORD <|@ <|@
      nr   22  <|@ instruction TESTBRANCH (x: v0|QWORD[.], y: v0|QWORD[.]) trueDestinationProbability: 9.91958358897982E-7 condition: = trueDestination: B0 -> B1 falseDestination: B0 -> B2 size: QWORD <|@ <|@
    end_IR
  end_block
  begin_block
    name "B2"
    from_bci -1
    to_bci -1
    predecessors "B0" 
    successors "B3" "B4" 
    xhandlers
    flags 
    probability 4607182409865250817
    begin_IR
      LIR
      nr   24  <|@ instruction [] = LABEL alignment: 0 numbPhis: 0 label: ? <|@ <|@
      nr   26  <|@ instruction NOP <|@ <|@
      nr   28  <|@ instruction NOP <|@ <|@
      nr   30  <|@ instruction NOP <|@ <|@
      nr   32  <|@ instruction NOP <|@ <|@
      nr   34  <|@ instruction NOP <|@ <|@
      nr   36  <|@ instruction NOP <|@ <|@
      nr   38  <|@ instruction NOP <|@ <|@
      nr   40  <|@ instruction NOP <|@ <|@
      nr   42  <|@ instruction NOP <|@ <|@
      nr   44  <|@ instruction v3|DWORD = MOV input: [v0|QWORD[.] + 8] size: DWORD <|@ <|@
      nr   46  <|@ instruction v5|QWORD = MOVE input: long[140154094223360|0x7f782b000000] <|@ <|@
      nr   48  <|@ instruction v4|QWORD = UNCOMPRESSPOINTER (input: v3|DWORD, ~baseRegister: v5|QWORD) nonNull: true lirKindTool: jdk.graal.compiler.hotspot.amd64.AMD64HotSpotLIRKindTool@d0246bd encoding: base: 140154094223360 shift: 0 <|@ <|@
      nr   50  <|@ instruction v6|QWORD = HOTSPOTLOADMETASPACECONSTANT input: meta{HotSpotType<Ljava/lang/String;, resolved>} <|@ <|@
      nr   52  <|@ instruction CMPBRANCH (x: v6|QWORD, y: v4|QWORD) trueDestinationProbability: 0.43400564574488104 condition: = trueDestination: B2 -> B3 falseDestination: B2 -> B4 size: QWORD <|@ <|@
    end_IR
  end_block
  begin_block
    name "B4"
    from_bci -1
    to_bci -1
    predecessors "B2" 
    successors "B5" 
    xhandlers
    flags 
    probability 4603273238414083286
    begin_IR
      LIR
      nr   54  <|@ instruction [] = LABEL alignment: 0 numbPhis: 0 label: ? <|@ <|@
      nr   56  <|@ instruction NOP <|@ <|@
      nr   58  <|@ instruction NOP <|@ <|@
      nr   60  <|@ instruction NOP <|@ <|@
      nr   62  <|@ instruction NOP <|@ <|@
      nr   64  <|@ instruction NOP <|@ <|@
      nr   66  <|@ instruction NOP <|@ <|@
      nr   68  <|@ instruction NOP <|@ <|@
      nr   70  <|@ instruction NOP <|@ <|@
      nr   72  <|@ instruction NOP <|@ <|@
      nr   74  <|@ instruction NOP <|@ <|@
      nr   76  <|@ instruction NOP <|@ <|@
      nr   78  <|@ instruction NOP <|@ <|@
      nr   80  <|@ instruction v7|QWORD = MOV input: [v4|QWORD + 472] size: QWORD <|@ <|@
      nr   82  <|@ instruction v8|QWORD = MOV input: [v7|QWORD + 64] size: QWORD <|@ <|@
      nr   84  <|@ instruction rsi|QWORD[.] = MOVE input: v0|QWORD[.] moveKind: QWORD <|@ <|@
      nr   86  <|@ instruction rbx|QWORD = MOVE input: v7|QWORD moveKind: QWORD <|@ <|@
      nr   88  <|@ instruction rax|QWORD = MOVE input: v8|QWORD moveKind: QWORD <|@ <|@
      nr   90  <|@ st <@st|@live-base-pointers: []
java.lang.String.valueOf(String.java:4465) [bci: 11]
locals: - 
>@ <|@ instruction rax|QWORD[.] = CALL_INDIRECT (targetAddress: rax|QWORD, metaspaceMethod: rbx|QWORD, parameters: [rsi|QWORD[.]]) temps: [] callTarget: HotSpotMethod<Object.toString()> state [bci:11] <|@ <|@
      nr   92  <|@ instruction v9|QWORD[.] = MOVE input: rax|QWORD[.] moveKind: QWORD <|@ <|@
      nr   94  <|@ instruction JUMP ~outgoingValues: [] destination: B4 -> B5 <|@ <|@
    end_IR
  end_block
  begin_block
    name "B3"
    from_bci -1
    to_bci -1
    predecessors "B2" 
    successors "B5" 
    xhandlers
    flags 
    probability 4601489962820240983
    begin_IR
      LIR
      nr   96  <|@ instruction [] = LABEL alignment: 0 numbPhis: 0 label: ? <|@ <|@
      nr   98  <|@ instruction NOP <|@ <|@
      nr  100  <|@ instruction NOP <|@ <|@
      nr  102  <|@ instruction NOP <|@ <|@
      nr   -1  <|@ instruction v10|QWORD[.] = MOVE input: v0|QWORD[.] moveKind: QWORD // MoveResolver resolve mapping <|@ <|@
      nr  104  <|@ instruction JUMP ~outgoingValues: [] destination: B3 -> B5 <|@ <|@
    end_IR
  end_block
  begin_block
    name "B5"
    from_bci -1
    to_bci -1
    predecessors "B1" "B3" "B4" 
    successors 
    xhandlers
    flags 
    probability 4607182418800017408
    begin_IR
      LIR
      nr  106  <|@ instruction [] = LABEL alignment: 0 numbPhis: 1 label: ? <|@ <|@
      nr  108  <|@ instruction NOP <|@ <|@
      nr  110  <|@ instruction NOP <|@ <|@
      nr  112  <|@ instruction NOP <|@ <|@
      nr  114  <|@ instruction NOP <|@ <|@
      nr  116  <|@ instruction NOP <|@ <|@
      nr  118  <|@ instruction NOP <|@ <|@
      nr  120  <|@ instruction NOP <|@ <|@
      nr  122  <|@ instruction NOP <|@ <|@
      nr  124  <|@ instruction rax|QWORD[.] = MOVE input: v10|QWORD[.] moveKind: QWORD <|@ <|@
      nr  126  <|@ instruction RETURN (savedRbp: stack:16|QWORD, value: rax|QWORD[.]) isStub: false requiresReservedStackAccessCheck: false thread: r15 scratchForSafepointOnReturn: rcx config: jdk.graal.compiler.hotspot.GraalHotSpotVMConfig@4817c460 <|@ <|@
    end_IR
  end_block
  begin_block
    name "B1"
    from_bci -1
    to_bci -1
    predecessors "B0" 
    successors "B5" 
    xhandlers
    flags 
    probability 4517291217531699200
    begin_IR
      LIR
      nr  128  <|@ instruction [] = LABEL alignment: 0 numbPhis: 0 label: ? <|@ <|@
      nr  130  <|@ instruction NOP <|@ <|@
      nr  132  <|@ instruction NOP <|@ <|@
      nr  134  <|@ instruction NOP <|@ <|@
      nr  136  <|@ instruction NOP <|@ <|@
      nr  138  <|@ instruction NOP <|@ <|@
      nr  140  <|@ instruction v1|QWORD[.] = HOTSPOTLOADOBJECTCONSTANT input: Object[String:"null"] <|@ <|@
      nr  142  <|@ instruction v2|QWORD[.] = MOVE input: v1|QWORD[.] moveKind: QWORD <|@ <|@
      nr   -1  <|@ instruction v10|QWORD[.] = MOVE input: v2|QWORD[.] moveKind: QWORD // MoveResolver resolve mapping <|@ <|@
      nr  144  <|@ instruction JUMP ~outgoingValues: [] destination: B1 -> B5 <|@ <|@
    end_IR
  end_block
end_cfg
begin_bytecodes
     0: aload_0       
     1: ifnonnull     10
     4: ldc_w         #1000       // "null"
     7: goto          14
    10: aload_0       
    11: invokevirtual #281        // java.lang.Object.toString:()java.lang.String
    14: areturn       
   <|@
end_bytecodes
begin_cfg
  name "After LinearScanAssignLocations"
  begin_block
    name "B0"
    from_bci -1
    to_bci -1
    predecessors 
    successors "B1" "B2" 
    xhandlers
    flags 
    probability 4607182418800017408
    begin_IR
      LIR
      nr    0  <|@ instruction [rsi|QWORD[.], rbp|QWORD] = LABEL alignment: 0 numbPhis: 0 label: ? <|@ <|@
      nr    2  <|@ instruction NOP <|@ <|@
      nr    4  <|@ instruction NOP <|@ <|@
      nr    6  <|@ instruction NOP <|@ <|@
      nr    8  <|@ instruction NOP <|@ <|@
      nr   10  <|@ instruction NOP <|@ <|@
      nr   12  <|@ instruction NOP <|@ <|@
      nr   14  <|@ instruction NOP <|@ <|@
      nr   16  <|@ instruction stack:16|QWORD = MOVE input: rbp|QWORD moveKind: QWORD <|@ <|@
      nr   18  <|@ instruction [] = HOTSPOTLOCKSTACK frameMapBuilder: jdk.graal.compiler.hotspot.amd64.AMD64HotSpotFrameMapBuilder@64144869 slotKind: QWORD <|@ <|@
      nr   22  <|@ instruction TESTBRANCH (x: rsi|QWORD[.], y: rsi|QWORD[.]) trueDestinationProbability: 9.91958358897982E-7 condition: = trueDestination: B0 -> B1 falseDestination: B0 -> B2 size: QWORD <|@ <|@
    end_IR
  end_block
  begin_block
    name "B2"
    from_bci -1
    to_bci -1
    predecessors "B0" 
    successors "B3" "B4" 
    xhandlers
    flags 
    probability 4607182409865250817
    begin_IR
      LIR
      nr   24  <|@ instruction [] = LABEL alignment: 0 numbPhis: 0 label: ? <|@ <|@
      nr   26  <|@ instruction NOP <|@ <|@
      nr   28  <|@ instruction NOP <|@ <|@
      nr   30  <|@ instruction NOP <|@ <|@
      nr   32  <|@ instruction NOP <|@ <|@
      nr   34  <|@ instruction NOP <|@ <|@
      nr   36  <|@ instruction NOP <|@ <|@
      nr   38  <|@ instruction NOP <|@ <|@
      nr   40  <|@ instruction NOP <|@ <|@
      nr   42  <|@ instruction NOP <|@ <|@
      nr   44  <|@ instruction rbx|DWORD = MOV input: [rsi|QWORD[.] + 8] size: DWORD <|@ <|@
      nr   46  <|@ instruction rax|QWORD = MOVE input: long[140154094223360|0x7f782b000000] <|@ <|@
      nr   48  <|@ instruction rbx|QWORD = UNCOMPRESSPOINTER (input: rbx|DWORD, ~baseRegister: rax|QWORD) nonNull: true lirKindTool: jdk.graal.compiler.hotspot.amd64.AMD64HotSpotLIRKindTool@d0246bd encoding: base: 140154094223360 shift: 0 <|@ <|@
      nr   50  <|@ instruction rax|QWORD = HOTSPOTLOADMETASPACECONSTANT input: meta{HotSpotType<Ljava/lang/String;, resolved>} <|@ <|@
      nr   52  <|@ instruction CMPBRANCH (x: rax|QWORD, y: rbx|QWORD) trueDestinationProbability: 0.43400564574488104 condition: = trueDestination: B2 -> B3 falseDestination: B2 -> B4 size: QWORD <|@ <|@
    end_IR
  end_block
  begin_block
    name "B4"
    from_bci -1
    to_bci -1
    predecessors "B2" 
    successors "B5" 
    xhandlers
    flags 
    probability 4603273238414083286
    begin_IR
      LIR
      nr   54  <|@ instruction [] = LABEL alignment: 0 numbPhis: 0 label: ? <|@ <|@
      nr   56  <|@ instruction NOP <|@ <|@
      nr   58  <|@ instruction NOP <|@ <|@
      nr   60  <|@ instruction NOP <|@ <|@
      nr   62  <|@ instruction NOP <|@ <|@
      nr   64  <|@ instruction NOP <|@ <|@
      nr   66  <|@ instruction NOP <|@ <|@
      nr   68  <|@ instruction NOP <|@ <|@
      nr   70  <|@ instruction NOP <|@ <|@
      nr   72  <|@ instruction NOP <|@ <|@
      nr   74  <|@ instruction NOP <|@ <|@
      nr   76  <|@ instruction NOP <|@ <|@
      nr   78  <|@ instruction NOP <|@ <|@
      nr   80  <|@ instruction rbx|QWORD = MOV input: [rbx|QWORD + 472] size: QWORD <|@ <|@
      nr   82  <|@ instruction rax|QWORD = MOV input: [rbx|QWORD + 64] size: QWORD <|@ <|@
      nr   90  <|@ st <@st|@live-base-pointers: []
java.lang.String.valueOf(String.java:4465) [bci: 11]
locals: - 
>@ <|@ instruction rax|QWORD[.] = CALL_INDIRECT (targetAddress: rax|QWORD, metaspaceMethod: rbx|QWORD, parameters: [rsi|QWORD[.]]) temps: [] callTarget: HotSpotMethod<Object.toString()> state [bci:11] <|@ <|@
      nr   94  <|@ instruction JUMP ~outgoingValues: [] destination: B4 -> B5 <|@ <|@
    end_IR
  end_block
  begin_block
    name "B3"
    from_bci -1
    to_bci -1
    predecessors "B2" 
    successors "B5" 
    xhandlers
    flags 
    probability 4601489962820240983
    begin_IR
      LIR
      nr   96  <|@ instruction [] = LABEL alignment: 0 numbPhis: 0 label: ? <|@ <|@
      nr   98  <|@ instruction NOP <|@ <|@
      nr  100  <|@ instruction NOP <|@ <|@
      nr  102  <|@ instruction NOP <|@ <|@
      nr   -1  <|@ instruction rax|QWORD[.] = MOVE input: rsi|QWORD[.] moveKind: QWORD // MoveResolver resolve mapping <|@ <|@
      nr  104  <|@ instruction JUMP ~outgoingValues: [] destination: B3 -> B5 <|@ <|@
    end_IR
  end_block
  begin_block
    name "B5"
    from_bci -1
    to_bci -1
    predecessors "B1" "B3" "B4" 
    successors 
    xhandlers
    flags 
    probability 4607182418800017408
    begin_IR
      LIR
      nr  106  <|@ instruction [] = LABEL alignment: 0 numbPhis: 1 label: ? <|@ <|@
      nr  108  <|@ instruction NOP <|@ <|@
      nr  110  <|@ instruction NOP <|@ <|@
      nr  112  <|@ instruction NOP <|@ <|@
      nr  114  <|@ instruction NOP <|@ <|@
      nr  116  <|@ instruction NOP <|@ <|@
      nr  118  <|@ instruction NOP <|@ <|@
      nr  120  <|@ instruction NOP <|@ <|@
      nr  122  <|@ instruction NOP <|@ <|@
      nr  126  <|@ instruction RETURN (savedRbp: stack:16|QWORD, value: rax|QWORD[.]) isStub: false requiresReservedStackAccessCheck: false thread: r15 scratchForSafepointOnReturn: rcx config: jdk.graal.compiler.hotspot.GraalHotSpotVMConfig@4817c460 <|@ <|@
    end_IR
  end_block
  begin_block
    name "B1"
    from_bci -1
    to_bci -1
    predecessors "B0" 
    successors "B5" 
    xhandlers
    flags 
    probability 4517291217531699200
    begin_IR
      LIR
      nr  128  <|@ instruction [] = LABEL alignment: 0 numbPhis: 0 label: ? <|@ <|@
      nr  130  <|@ instruction NOP <|@ <|@
      nr  132  <|@ instruction NOP <|@ <|@
      nr  134  <|@ instruction NOP <|@ <|@
      nr  136  <|@ instruction NOP <|@ <|@
      nr  138  <|@ instruction NOP <|@ <|@
      nr  140  <|@ instruction r10|QWORD[.] = HOTSPOTLOADOBJECTCONSTANT input: Object[String:"null"] <|@ <|@
      nr   -1  <|@ instruction rax|QWORD[.] = MOVE input: r10|QWORD[.] moveKind: QWORD // MoveResolver resolve mapping <|@ <|@
      nr  144  <|@ instruction JUMP ~outgoingValues: [] destination: B1 -> B5 <|@ <|@
    end_IR
  end_block
end_cfg
begin_bytecodes
     0: aload_0       
     1: ifnonnull     10
     4: ldc_w         #1000       // "null"
     7: goto          14
    10: aload_0       
    11: invokevirtual #281        // java.lang.Object.toString:()java.lang.String
    14: areturn       
   <|@
end_bytecodes
begin_cfg
  name "After LinearScan"
  begin_block
    name "B0"
    from_bci -1
    to_bci -1
    predecessors 
    successors "B1" "B2" 
    xhandlers
    flags 
    probability 4607182418800017408
    begin_IR
      LIR
      nr    0  <|@ instruction [rsi|QWORD[.], rbp|QWORD] = LABEL alignment: 0 numbPhis: 0 label: ? <|@ <|@
      nr    2  <|@ instruction NOP <|@ <|@
      nr    4  <|@ instruction NOP <|@ <|@
      nr    6  <|@ instruction NOP <|@ <|@
      nr    8  <|@ instruction NOP <|@ <|@
      nr   10  <|@ instruction NOP <|@ <|@
      nr   12  <|@ instruction NOP <|@ <|@
      nr   14  <|@ instruction NOP <|@ <|@
      nr   16  <|@ instruction stack:16|QWORD = MOVE input: rbp|QWORD moveKind: QWORD <|@ <|@
      nr   18  <|@ instruction [] = HOTSPOTLOCKSTACK frameMapBuilder: jdk.graal.compiler.hotspot.amd64.AMD64HotSpotFrameMapBuilder@64144869 slotKind: QWORD <|@ <|@
      nr   22  <|@ instruction TESTBRANCH (x: rsi|QWORD[.], y: rsi|QWORD[.]) trueDestinationProbability: 9.91958358897982E-7 condition: = trueDestination: B0 -> B1 falseDestination: B0 -> B2 size: QWORD <|@ <|@
    end_IR
  end_block
  begin_block
    name "B2"
    from_bci -1
    to_bci -1
    predecessors "B0" 
    successors "B3" "B4" 
    xhandlers
    flags 
    probability 4607182409865250817
    begin_IR
      LIR
      nr   24  <|@ instruction [] = LABEL alignment: 0 numbPhis: 0 label: ? <|@ <|@
      nr   26  <|@ instruction NOP <|@ <|@
      nr   28  <|@ instruction NOP <|@ <|@
      nr   30  <|@ instruction NOP <|@ <|@
      nr   32  <|@ instruction NOP <|@ <|@
      nr   34  <|@ instruction NOP <|@ <|@
      nr   36  <|@ instruction NOP <|@ <|@
      nr   38  <|@ instruction NOP <|@ <|@
      nr   40  <|@ instruction NOP <|@ <|@
      nr   42  <|@ instruction NOP <|@ <|@
      nr   44  <|@ instruction rbx|DWORD = MOV input: [rsi|QWORD[.] + 8] size: DWORD <|@ <|@
      nr   46  <|@ instruction rax|QWORD = MOVE input: long[140154094223360|0x7f782b000000] <|@ <|@
      nr   48  <|@ instruction rbx|QWORD = UNCOMPRESSPOINTER (input: rbx|DWORD, ~baseRegister: rax|QWORD) nonNull: true lirKindTool: jdk.graal.compiler.hotspot.amd64.AMD64HotSpotLIRKindTool@d0246bd encoding: base: 140154094223360 shift: 0 <|@ <|@
      nr   50  <|@ instruction rax|QWORD = HOTSPOTLOADMETASPACECONSTANT input: meta{HotSpotType<Ljava/lang/String;, resolved>} <|@ <|@
      nr   52  <|@ instruction CMPBRANCH (x: rax|QWORD, y: rbx|QWORD) trueDestinationProbability: 0.43400564574488104 condition: = trueDestination: B2 -> B3 falseDestination: B2 -> B4 size: QWORD <|@ <|@
    end_IR
  end_block
  begin_block
    name "B4"
    from_bci -1
    to_bci -1
    predecessors "B2" 
    successors "B5" 
    xhandlers
    flags 
    probability 4603273238414083286
    begin_IR
      LIR
      nr   54  <|@ instruction [] = LABEL alignment: 0 numbPhis: 0 label: ? <|@ <|@
      nr   56  <|@ instruction NOP <|@ <|@
      nr   58  <|@ instruction NOP <|@ <|@
      nr   60  <|@ instruction NOP <|@ <|@
      nr   62  <|@ instruction NOP <|@ <|@
      nr   64  <|@ instruction NOP <|@ <|@
      nr   66  <|@ instruction NOP <|@ <|@
      nr   68  <|@ instruction NOP <|@ <|@
      nr   70  <|@ instruction NOP <|@ <|@
      nr   72  <|@ instruction NOP <|@ <|@
      nr   74  <|@ instruction NOP <|@ <|@
      nr   76  <|@ instruction NOP <|@ <|@
      nr   78  <|@ instruction NOP <|@ <|@
      nr   80  <|@ instruction rbx|QWORD = MOV input: [rbx|QWORD + 472] size: QWORD <|@ <|@
      nr   82  <|@ instruction rax|QWORD = MOV input: [rbx|QWORD + 64] size: QWORD <|@ <|@
      nr   90  <|@ st <@st|@live-base-pointers: []
java.lang.String.valueOf(String.java:4465) [bci: 11]
locals: - 
>@ <|@ instruction rax|QWORD[.] = CALL_INDIRECT (targetAddress: rax|QWORD, metaspaceMethod: rbx|QWORD, parameters: [rsi|QWORD[.]]) temps: [] callTarget: HotSpotMethod<Object.toString()> state [bci:11] <|@ <|@
      nr   94  <|@ instruction JUMP ~outgoingValues: [] destination: B4 -> B5 <|@ <|@
    end_IR
  end_block
  begin_block
    name "B3"
    from_bci -1
    to_bci -1
    predecessors "B2" 
    successors "B5" 
    xhandlers
    flags 
    probability 4601489962820240983
    begin_IR
      LIR
      nr   96  <|@ instruction [] = LABEL alignment: 0 numbPhis: 0 label: ? <|@ <|@
      nr   98  <|@ instruction NOP <|@ <|@
      nr  100  <|@ instruction NOP <|@ <|@
      nr  102  <|@ instruction NOP <|@ <|@
      nr   -1  <|@ instruction rax|QWORD[.] = MOVE input: rsi|QWORD[.] moveKind: QWORD // MoveResolver resolve mapping <|@ <|@
      nr  104  <|@ instruction JUMP ~outgoingValues: [] destination: B3 -> B5 <|@ <|@
    end_IR
  end_block
  begin_block
    name "B5"
    from_bci -1
    to_bci -1
    predecessors "B1" "B3" "B4" 
    successors 
    xhandlers
    flags 
    probability 4607182418800017408
    begin_IR
      LIR
      nr  106  <|@ instruction [] = LABEL alignment: 0 numbPhis: 1 label: ? <|@ <|@
      nr  108  <|@ instruction NOP <|@ <|@
      nr  110  <|@ instruction NOP <|@ <|@
      nr  112  <|@ instruction NOP <|@ <|@
      nr  114  <|@ instruction NOP <|@ <|@
      nr  116  <|@ instruction NOP <|@ <|@
      nr  118  <|@ instruction NOP <|@ <|@
      nr  120  <|@ instruction NOP <|@ <|@
      nr  122  <|@ instruction NOP <|@ <|@
      nr  126  <|@ instruction RETURN (savedRbp: stack:16|QWORD, value: rax|QWORD[.]) isStub: false requiresReservedStackAccessCheck: false thread: r15 scratchForSafepointOnReturn: rcx config: jdk.graal.compiler.hotspot.GraalHotSpotVMConfig@4817c460 <|@ <|@
    end_IR
  end_block
  begin_block
    name "B1"
    from_bci -1
    to_bci -1
    predecessors "B0" 
    successors "B5" 
    xhandlers
    flags 
    probability 4517291217531699200
    begin_IR
      LIR
      nr  128  <|@ instruction [] = LABEL alignment: 0 numbPhis: 0 label: ? <|@ <|@
      nr  130  <|@ instruction NOP <|@ <|@
      nr  132  <|@ instruction NOP <|@ <|@
      nr  134  <|@ instruction NOP <|@ <|@
      nr  136  <|@ instruction NOP <|@ <|@
      nr  138  <|@ instruction NOP <|@ <|@
      nr  140  <|@ instruction r10|QWORD[.] = HOTSPOTLOADOBJECTCONSTANT input: Object[String:"null"] <|@ <|@
      nr   -1  <|@ instruction rax|QWORD[.] = MOVE input: r10|QWORD[.] moveKind: QWORD // MoveResolver resolve mapping <|@ <|@
      nr  144  <|@ instruction JUMP ~outgoingValues: [] destination: B1 -> B5 <|@ <|@
    end_IR
  end_block
end_cfg
begin_bytecodes
     0: aload_0       
     1: ifnonnull     10
     4: ldc_w         #1000       // "null"
     7: goto          14
    10: aload_0       
    11: invokevirtual #281        // java.lang.Object.toString:()java.lang.String
    14: areturn       
   <|@
end_bytecodes
begin_cfg
  name "After LSStackSlotAllocator"
  begin_block
    name "B0"
    from_bci -1
    to_bci -1
    predecessors 
    successors "B1" "B2" 
    xhandlers
    flags 
    probability 4607182418800017408
    begin_IR
      LIR
      nr    0  <|@ instruction [rsi|QWORD[.], rbp|QWORD] = LABEL alignment: 0 numbPhis: 0 label: ? <|@ <|@
      nr    2  <|@ instruction NOP <|@ <|@
      nr    4  <|@ instruction NOP <|@ <|@
      nr    6  <|@ instruction NOP <|@ <|@
      nr    8  <|@ instruction NOP <|@ <|@
      nr   10  <|@ instruction NOP <|@ <|@
      nr   12  <|@ instruction NOP <|@ <|@
      nr   14  <|@ instruction NOP <|@ <|@
      nr   16  <|@ instruction stack:16|QWORD = MOVE input: rbp|QWORD moveKind: QWORD <|@ <|@
      nr   18  <|@ instruction [] = HOTSPOTLOCKSTACK frameMapBuilder: jdk.graal.compiler.hotspot.amd64.AMD64HotSpotFrameMapBuilder@64144869 slotKind: QWORD <|@ <|@
      nr   22  <|@ instruction TESTBRANCH (x: rsi|QWORD[.], y: rsi|QWORD[.]) trueDestinationProbability: 9.91958358897982E-7 condition: = trueDestination: B0 -> B1 falseDestination: B0 -> B2 size: QWORD <|@ <|@
    end_IR
  end_block
  begin_block
    name "B2"
    from_bci -1
    to_bci -1
    predecessors "B0" 
    successors "B3" "B4" 
    xhandlers
    flags 
    probability 4607182409865250817
    begin_IR
      LIR
      nr   24  <|@ instruction [] = LABEL alignment: 0 numbPhis: 0 label: ? <|@ <|@
      nr   26  <|@ instruction NOP <|@ <|@
      nr   28  <|@ instruction NOP <|@ <|@
      nr   30  <|@ instruction NOP <|@ <|@
      nr   32  <|@ instruction NOP <|@ <|@
      nr   34  <|@ instruction NOP <|@ <|@
      nr   36  <|@ instruction NOP <|@ <|@
      nr   38  <|@ instruction NOP <|@ <|@
      nr   40  <|@ instruction NOP <|@ <|@
      nr   42  <|@ instruction NOP <|@ <|@
      nr   44  <|@ instruction rbx|DWORD = MOV input: [rsi|QWORD[.] + 8] size: DWORD <|@ <|@
      nr   46  <|@ instruction rax|QWORD = MOVE input: long[140154094223360|0x7f782b000000] <|@ <|@
      nr   48  <|@ instruction rbx|QWORD = UNCOMPRESSPOINTER (input: rbx|DWORD, ~baseRegister: rax|QWORD) nonNull: true lirKindTool: jdk.graal.compiler.hotspot.amd64.AMD64HotSpotLIRKindTool@d0246bd encoding: base: 140154094223360 shift: 0 <|@ <|@
      nr   50  <|@ instruction rax|QWORD = HOTSPOTLOADMETASPACECONSTANT input: meta{HotSpotType<Ljava/lang/String;, resolved>} <|@ <|@
      nr   52  <|@ instruction CMPBRANCH (x: rax|QWORD, y: rbx|QWORD) trueDestinationProbability: 0.43400564574488104 condition: = trueDestination: B2 -> B3 falseDestination: B2 -> B4 size: QWORD <|@ <|@
    end_IR
  end_block
  begin_block
    name "B4"
    from_bci -1
    to_bci -1
    predecessors "B2" 
    successors "B5" 
    xhandlers
    flags 
    probability 4603273238414083286
    begin_IR
      LIR
      nr   54  <|@ instruction [] = LABEL alignment: 0 numbPhis: 0 label: ? <|@ <|@
      nr   56  <|@ instruction NOP <|@ <|@
      nr   58  <|@ instruction NOP <|@ <|@
      nr   60  <|@ instruction NOP <|@ <|@
      nr   62  <|@ instruction NOP <|@ <|@
      nr   64  <|@ instruction NOP <|@ <|@
      nr   66  <|@ instruction NOP <|@ <|@
      nr   68  <|@ instruction NOP <|@ <|@
      nr   70  <|@ instruction NOP <|@ <|@
      nr   72  <|@ instruction NOP <|@ <|@
      nr   74  <|@ instruction NOP <|@ <|@
      nr   76  <|@ instruction NOP <|@ <|@
      nr   78  <|@ instruction NOP <|@ <|@
      nr   80  <|@ instruction rbx|QWORD = MOV input: [rbx|QWORD + 472] size: QWORD <|@ <|@
      nr   82  <|@ instruction rax|QWORD = MOV input: [rbx|QWORD + 64] size: QWORD <|@ <|@
      nr   90  <|@ st <@st|@live-base-pointers: []
java.lang.String.valueOf(String.java:4465) [bci: 11]
locals: - 
>@ <|@ instruction rax|QWORD[.] = CALL_INDIRECT (targetAddress: rax|QWORD, metaspaceMethod: rbx|QWORD, parameters: [rsi|QWORD[.]]) temps: [] callTarget: HotSpotMethod<Object.toString()> state [bci:11] <|@ <|@
      nr   94  <|@ instruction JUMP ~outgoingValues: [] destination: B4 -> B5 <|@ <|@
    end_IR
  end_block
  begin_block
    name "B3"
    from_bci -1
    to_bci -1
    predecessors "B2" 
    successors "B5" 
    xhandlers
    flags 
    probability 4601489962820240983
    begin_IR
      LIR
      nr   96  <|@ instruction [] = LABEL alignment: 0 numbPhis: 0 label: ? <|@ <|@
      nr   98  <|@ instruction NOP <|@ <|@
      nr  100  <|@ instruction NOP <|@ <|@
      nr  102  <|@ instruction NOP <|@ <|@
      nr   -1  <|@ instruction rax|QWORD[.] = MOVE input: rsi|QWORD[.] moveKind: QWORD // MoveResolver resolve mapping <|@ <|@
      nr  104  <|@ instruction JUMP ~outgoingValues: [] destination: B3 -> B5 <|@ <|@
    end_IR
  end_block
  begin_block
    name "B5"
    from_bci -1
    to_bci -1
    predecessors "B1" "B3" "B4" 
    successors 
    xhandlers
    flags 
    probability 4607182418800017408
    begin_IR
      LIR
      nr  106  <|@ instruction [] = LABEL alignment: 0 numbPhis: 1 label: ? <|@ <|@
      nr  108  <|@ instruction NOP <|@ <|@
      nr  110  <|@ instruction NOP <|@ <|@
      nr  112  <|@ instruction NOP <|@ <|@
      nr  114  <|@ instruction NOP <|@ <|@
      nr  116  <|@ instruction NOP <|@ <|@
      nr  118  <|@ instruction NOP <|@ <|@
      nr  120  <|@ instruction NOP <|@ <|@
      nr  122  <|@ instruction NOP <|@ <|@
      nr  126  <|@ instruction RETURN (savedRbp: stack:16|QWORD, value: rax|QWORD[.]) isStub: false requiresReservedStackAccessCheck: false thread: r15 scratchForSafepointOnReturn: rcx config: jdk.graal.compiler.hotspot.GraalHotSpotVMConfig@4817c460 <|@ <|@
    end_IR
  end_block
  begin_block
    name "B1"
    from_bci -1
    to_bci -1
    predecessors "B0" 
    successors "B5" 
    xhandlers
    flags 
    probability 4517291217531699200
    begin_IR
      LIR
      nr  128  <|@ instruction [] = LABEL alignment: 0 numbPhis: 0 label: ? <|@ <|@
      nr  130  <|@ instruction NOP <|@ <|@
      nr  132  <|@ instruction NOP <|@ <|@
      nr  134  <|@ instruction NOP <|@ <|@
      nr  136  <|@ instruction NOP <|@ <|@
      nr  138  <|@ instruction NOP <|@ <|@
      nr  140  <|@ instruction r10|QWORD[.] = HOTSPOTLOADOBJECTCONSTANT input: Object[String:"null"] <|@ <|@
      nr   -1  <|@ instruction rax|QWORD[.] = MOVE input: r10|QWORD[.] moveKind: QWORD // MoveResolver resolve mapping <|@ <|@
      nr  144  <|@ instruction JUMP ~outgoingValues: [] destination: B1 -> B5 <|@ <|@
    end_IR
  end_block
end_cfg
begin_bytecodes
     0: aload_0       
     1: ifnonnull     10
     4: ldc_w         #1000       // "null"
     7: goto          14
    10: aload_0       
    11: invokevirtual #281        // java.lang.Object.toString:()java.lang.String
    14: areturn       
   <|@
end_bytecodes
begin_cfg
  name "After AllocationStage"
  begin_block
    name "B0"
    from_bci -1
    to_bci -1
    predecessors 
    successors "B1" "B2" 
    xhandlers
    flags 
    probability 4607182418800017408
    begin_IR
      LIR
      nr    0  <|@ instruction [rsi|QWORD[.], rbp|QWORD] = LABEL alignment: 0 numbPhis: 0 label: ? <|@ <|@
      nr    2  <|@ instruction NOP <|@ <|@
      nr    4  <|@ instruction NOP <|@ <|@
      nr    6  <|@ instruction NOP <|@ <|@
      nr    8  <|@ instruction NOP <|@ <|@
      nr   10  <|@ instruction NOP <|@ <|@
      nr   12  <|@ instruction NOP <|@ <|@
      nr   14  <|@ instruction NOP <|@ <|@
      nr   16  <|@ instruction stack:16|QWORD = MOVE input: rbp|QWORD moveKind: QWORD <|@ <|@
      nr   18  <|@ instruction [] = HOTSPOTLOCKSTACK frameMapBuilder: jdk.graal.compiler.hotspot.amd64.AMD64HotSpotFrameMapBuilder@64144869 slotKind: QWORD <|@ <|@
      nr   22  <|@ instruction TESTBRANCH (x: rsi|QWORD[.], y: rsi|QWORD[.]) trueDestinationProbability: 9.91958358897982E-7 condition: = trueDestination: B0 -> B1 falseDestination: B0 -> B2 size: QWORD <|@ <|@
    end_IR
  end_block
  begin_block
    name "B2"
    from_bci -1
    to_bci -1
    predecessors "B0" 
    successors "B3" "B4" 
    xhandlers
    flags 
    probability 4607182409865250817
    begin_IR
      LIR
      nr   24  <|@ instruction [] = LABEL alignment: 0 numbPhis: 0 label: ? <|@ <|@
      nr   26  <|@ instruction NOP <|@ <|@
      nr   28  <|@ instruction NOP <|@ <|@
      nr   30  <|@ instruction NOP <|@ <|@
      nr   32  <|@ instruction NOP <|@ <|@
      nr   34  <|@ instruction NOP <|@ <|@
      nr   36  <|@ instruction NOP <|@ <|@
      nr   38  <|@ instruction NOP <|@ <|@
      nr   40  <|@ instruction NOP <|@ <|@
      nr   42  <|@ instruction NOP <|@ <|@
      nr   44  <|@ instruction rbx|DWORD = MOV input: [rsi|QWORD[.] + 8] size: DWORD <|@ <|@
      nr   46  <|@ instruction rax|QWORD = MOVE input: long[140154094223360|0x7f782b000000] <|@ <|@
      nr   48  <|@ instruction rbx|QWORD = UNCOMPRESSPOINTER (input: rbx|DWORD, ~baseRegister: rax|QWORD) nonNull: true lirKindTool: jdk.graal.compiler.hotspot.amd64.AMD64HotSpotLIRKindTool@d0246bd encoding: base: 140154094223360 shift: 0 <|@ <|@
      nr   50  <|@ instruction rax|QWORD = HOTSPOTLOADMETASPACECONSTANT input: meta{HotSpotType<Ljava/lang/String;, resolved>} <|@ <|@
      nr   52  <|@ instruction CMPBRANCH (x: rax|QWORD, y: rbx|QWORD) trueDestinationProbability: 0.43400564574488104 condition: = trueDestination: B2 -> B3 falseDestination: B2 -> B4 size: QWORD <|@ <|@
    end_IR
  end_block
  begin_block
    name "B4"
    from_bci -1
    to_bci -1
    predecessors "B2" 
    successors "B5" 
    xhandlers
    flags 
    probability 4603273238414083286
    begin_IR
      LIR
      nr   54  <|@ instruction [] = LABEL alignment: 0 numbPhis: 0 label: ? <|@ <|@
      nr   56  <|@ instruction NOP <|@ <|@
      nr   58  <|@ instruction NOP <|@ <|@
      nr   60  <|@ instruction NOP <|@ <|@
      nr   62  <|@ instruction NOP <|@ <|@
      nr   64  <|@ instruction NOP <|@ <|@
      nr   66  <|@ instruction NOP <|@ <|@
      nr   68  <|@ instruction NOP <|@ <|@
      nr   70  <|@ instruction NOP <|@ <|@
      nr   72  <|@ instruction NOP <|@ <|@
      nr   74  <|@ instruction NOP <|@ <|@
      nr   76  <|@ instruction NOP <|@ <|@
      nr   78  <|@ instruction NOP <|@ <|@
      nr   80  <|@ instruction rbx|QWORD = MOV input: [rbx|QWORD + 472] size: QWORD <|@ <|@
      nr   82  <|@ instruction rax|QWORD = MOV input: [rbx|QWORD + 64] size: QWORD <|@ <|@
      nr   90  <|@ st <@st|@live-base-pointers: []
java.lang.String.valueOf(String.java:4465) [bci: 11]
locals: - 
>@ <|@ instruction rax|QWORD[.] = CALL_INDIRECT (targetAddress: rax|QWORD, metaspaceMethod: rbx|QWORD, parameters: [rsi|QWORD[.]]) temps: [] callTarget: HotSpotMethod<Object.toString()> state [bci:11] <|@ <|@
      nr   94  <|@ instruction JUMP ~outgoingValues: [] destination: B4 -> B5 <|@ <|@
    end_IR
  end_block
  begin_block
    name "B3"
    from_bci -1
    to_bci -1
    predecessors "B2" 
    successors "B5" 
    xhandlers
    flags 
    probability 4601489962820240983
    begin_IR
      LIR
      nr   96  <|@ instruction [] = LABEL alignment: 0 numbPhis: 0 label: ? <|@ <|@
      nr   98  <|@ instruction NOP <|@ <|@
      nr  100  <|@ instruction NOP <|@ <|@
      nr  102  <|@ instruction NOP <|@ <|@
      nr   -1  <|@ instruction rax|QWORD[.] = MOVE input: rsi|QWORD[.] moveKind: QWORD // MoveResolver resolve mapping <|@ <|@
      nr  104  <|@ instruction JUMP ~outgoingValues: [] destination: B3 -> B5 <|@ <|@
    end_IR
  end_block
  begin_block
    name "B5"
    from_bci -1
    to_bci -1
    predecessors "B1" "B3" "B4" 
    successors 
    xhandlers
    flags 
    probability 4607182418800017408
    begin_IR
      LIR
      nr  106  <|@ instruction [] = LABEL alignment: 0 numbPhis: 1 label: ? <|@ <|@
      nr  108  <|@ instruction NOP <|@ <|@
      nr  110  <|@ instruction NOP <|@ <|@
      nr  112  <|@ instruction NOP <|@ <|@
      nr  114  <|@ instruction NOP <|@ <|@
      nr  116  <|@ instruction NOP <|@ <|@
      nr  118  <|@ instruction NOP <|@ <|@
      nr  120  <|@ instruction NOP <|@ <|@
      nr  122  <|@ instruction NOP <|@ <|@
      nr  126  <|@ instruction RETURN (savedRbp: stack:16|QWORD, value: rax|QWORD[.]) isStub: false requiresReservedStackAccessCheck: false thread: r15 scratchForSafepointOnReturn: rcx config: jdk.graal.compiler.hotspot.GraalHotSpotVMConfig@4817c460 <|@ <|@
    end_IR
  end_block
  begin_block
    name "B1"
    from_bci -1
    to_bci -1
    predecessors "B0" 
    successors "B5" 
    xhandlers
    flags 
    probability 4517291217531699200
    begin_IR
      LIR
      nr  128  <|@ instruction [] = LABEL alignment: 0 numbPhis: 0 label: ? <|@ <|@
      nr  130  <|@ instruction NOP <|@ <|@
      nr  132  <|@ instruction NOP <|@ <|@
      nr  134  <|@ instruction NOP <|@ <|@
      nr  136  <|@ instruction NOP <|@ <|@
      nr  138  <|@ instruction NOP <|@ <|@
      nr  140  <|@ instruction r10|QWORD[.] = HOTSPOTLOADOBJECTCONSTANT input: Object[String:"null"] <|@ <|@
      nr   -1  <|@ instruction rax|QWORD[.] = MOVE input: r10|QWORD[.] moveKind: QWORD // MoveResolver resolve mapping <|@ <|@
      nr  144  <|@ instruction JUMP ~outgoingValues: [] destination: B1 -> B5 <|@ <|@
    end_IR
  end_block
end_cfg
begin_bytecodes
     0: aload_0       
     1: ifnonnull     10
     4: ldc_w         #1000       // "null"
     7: goto          14
    10: aload_0       
    11: invokevirtual #281        // java.lang.Object.toString:()java.lang.String
    14: areturn       
   <|@
end_bytecodes
begin_cfg
  name "After EdgeMoveOptimizer"
  begin_block
    name "B0"
    from_bci -1
    to_bci -1
    predecessors 
    successors "B1" "B2" 
    xhandlers
    flags 
    probability 4607182418800017408
    begin_IR
      LIR
      nr    0  <|@ instruction [rsi|QWORD[.], rbp|QWORD] = LABEL alignment: 0 numbPhis: 0 label: ? <|@ <|@
      nr    2  <|@ instruction NOP <|@ <|@
      nr    4  <|@ instruction NOP <|@ <|@
      nr    6  <|@ instruction NOP <|@ <|@
      nr    8  <|@ instruction NOP <|@ <|@
      nr   10  <|@ instruction NOP <|@ <|@
      nr   12  <|@ instruction NOP <|@ <|@
      nr   14  <|@ instruction NOP <|@ <|@
      nr   16  <|@ instruction stack:16|QWORD = MOVE input: rbp|QWORD moveKind: QWORD <|@ <|@
      nr   18  <|@ instruction [] = HOTSPOTLOCKSTACK frameMapBuilder: jdk.graal.compiler.hotspot.amd64.AMD64HotSpotFrameMapBuilder@64144869 slotKind: QWORD <|@ <|@
      nr   22  <|@ instruction TESTBRANCH (x: rsi|QWORD[.], y: rsi|QWORD[.]) trueDestinationProbability: 9.91958358897982E-7 condition: = trueDestination: B0 -> B1 falseDestination: B0 -> B2 size: QWORD <|@ <|@
    end_IR
  end_block
  begin_block
    name "B2"
    from_bci -1
    to_bci -1
    predecessors "B0" 
    successors "B3" "B4" 
    xhandlers
    flags 
    probability 4607182409865250817
    begin_IR
      LIR
      nr   24  <|@ instruction [] = LABEL alignment: 0 numbPhis: 0 label: ? <|@ <|@
      nr   26  <|@ instruction NOP <|@ <|@
      nr   28  <|@ instruction NOP <|@ <|@
      nr   30  <|@ instruction NOP <|@ <|@
      nr   32  <|@ instruction NOP <|@ <|@
      nr   34  <|@ instruction NOP <|@ <|@
      nr   36  <|@ instruction NOP <|@ <|@
      nr   38  <|@ instruction NOP <|@ <|@
      nr   40  <|@ instruction NOP <|@ <|@
      nr   42  <|@ instruction NOP <|@ <|@
      nr   44  <|@ instruction rbx|DWORD = MOV input: [rsi|QWORD[.] + 8] size: DWORD <|@ <|@
      nr   46  <|@ instruction rax|QWORD = MOVE input: long[140154094223360|0x7f782b000000] <|@ <|@
      nr   48  <|@ instruction rbx|QWORD = UNCOMPRESSPOINTER (input: rbx|DWORD, ~baseRegister: rax|QWORD) nonNull: true lirKindTool: jdk.graal.compiler.hotspot.amd64.AMD64HotSpotLIRKindTool@d0246bd encoding: base: 140154094223360 shift: 0 <|@ <|@
      nr   50  <|@ instruction rax|QWORD = HOTSPOTLOADMETASPACECONSTANT input: meta{HotSpotType<Ljava/lang/String;, resolved>} <|@ <|@
      nr   52  <|@ instruction CMPBRANCH (x: rax|QWORD, y: rbx|QWORD) trueDestinationProbability: 0.43400564574488104 condition: = trueDestination: B2 -> B3 falseDestination: B2 -> B4 size: QWORD <|@ <|@
    end_IR
  end_block
  begin_block
    name "B4"
    from_bci -1
    to_bci -1
    predecessors "B2" 
    successors "B5" 
    xhandlers
    flags 
    probability 4603273238414083286
    begin_IR
      LIR
      nr   54  <|@ instruction [] = LABEL alignment: 0 numbPhis: 0 label: ? <|@ <|@
      nr   56  <|@ instruction NOP <|@ <|@
      nr   58  <|@ instruction NOP <|@ <|@
      nr   60  <|@ instruction NOP <|@ <|@
      nr   62  <|@ instruction NOP <|@ <|@
      nr   64  <|@ instruction NOP <|@ <|@
      nr   66  <|@ instruction NOP <|@ <|@
      nr   68  <|@ instruction NOP <|@ <|@
      nr   70  <|@ instruction NOP <|@ <|@
      nr   72  <|@ instruction NOP <|@ <|@
      nr   74  <|@ instruction NOP <|@ <|@
      nr   76  <|@ instruction NOP <|@ <|@
      nr   78  <|@ instruction NOP <|@ <|@
      nr   80  <|@ instruction rbx|QWORD = MOV input: [rbx|QWORD + 472] size: QWORD <|@ <|@
      nr   82  <|@ instruction rax|QWORD = MOV input: [rbx|QWORD + 64] size: QWORD <|@ <|@
      nr   90  <|@ st <@st|@live-base-pointers: []
java.lang.String.valueOf(String.java:4465) [bci: 11]
locals: - 
>@ <|@ instruction rax|QWORD[.] = CALL_INDIRECT (targetAddress: rax|QWORD, metaspaceMethod: rbx|QWORD, parameters: [rsi|QWORD[.]]) temps: [] callTarget: HotSpotMethod<Object.toString()> state [bci:11] <|@ <|@
      nr   94  <|@ instruction JUMP ~outgoingValues: [] destination: B4 -> B5 <|@ <|@
    end_IR
  end_block
  begin_block
    name "B3"
    from_bci -1
    to_bci -1
    predecessors "B2" 
    successors "B5" 
    xhandlers
    flags 
    probability 4601489962820240983
    begin_IR
      LIR
      nr   96  <|@ instruction [] = LABEL alignment: 0 numbPhis: 0 label: ? <|@ <|@
      nr   98  <|@ instruction NOP <|@ <|@
      nr  100  <|@ instruction NOP <|@ <|@
      nr  102  <|@ instruction NOP <|@ <|@
      nr   -1  <|@ instruction rax|QWORD[.] = MOVE input: rsi|QWORD[.] moveKind: QWORD // MoveResolver resolve mapping <|@ <|@
      nr  104  <|@ instruction JUMP ~outgoingValues: [] destination: B3 -> B5 <|@ <|@
    end_IR
  end_block
  begin_block
    name "B5"
    from_bci -1
    to_bci -1
    predecessors "B1" "B3" "B4" 
    successors 
    xhandlers
    flags 
    probability 4607182418800017408
    begin_IR
      LIR
      nr  106  <|@ instruction [] = LABEL alignment: 0 numbPhis: 1 label: ? <|@ <|@
      nr  108  <|@ instruction NOP <|@ <|@
      nr  110  <|@ instruction NOP <|@ <|@
      nr  112  <|@ instruction NOP <|@ <|@
      nr  114  <|@ instruction NOP <|@ <|@
      nr  116  <|@ instruction NOP <|@ <|@
      nr  118  <|@ instruction NOP <|@ <|@
      nr  120  <|@ instruction NOP <|@ <|@
      nr  122  <|@ instruction NOP <|@ <|@
      nr  126  <|@ instruction RETURN (savedRbp: stack:16|QWORD, value: rax|QWORD[.]) isStub: false requiresReservedStackAccessCheck: false thread: r15 scratchForSafepointOnReturn: rcx config: jdk.graal.compiler.hotspot.GraalHotSpotVMConfig@4817c460 <|@ <|@
    end_IR
  end_block
  begin_block
    name "B1"
    from_bci -1
    to_bci -1
    predecessors "B0" 
    successors "B5" 
    xhandlers
    flags 
    probability 4517291217531699200
    begin_IR
      LIR
      nr  128  <|@ instruction [] = LABEL alignment: 0 numbPhis: 0 label: ? <|@ <|@
      nr  130  <|@ instruction NOP <|@ <|@
      nr  132  <|@ instruction NOP <|@ <|@
      nr  134  <|@ instruction NOP <|@ <|@
      nr  136  <|@ instruction NOP <|@ <|@
      nr  138  <|@ instruction NOP <|@ <|@
      nr  140  <|@ instruction r10|QWORD[.] = HOTSPOTLOADOBJECTCONSTANT input: Object[String:"null"] <|@ <|@
      nr   -1  <|@ instruction rax|QWORD[.] = MOVE input: r10|QWORD[.] moveKind: QWORD // MoveResolver resolve mapping <|@ <|@
      nr  144  <|@ instruction JUMP ~outgoingValues: [] destination: B1 -> B5 <|@ <|@
    end_IR
  end_block
end_cfg
begin_bytecodes
     0: aload_0       
     1: ifnonnull     10
     4: ldc_w         #1000       // "null"
     7: goto          14
    10: aload_0       
    11: invokevirtual #281        // java.lang.Object.toString:()java.lang.String
    14: areturn       
   <|@
end_bytecodes
begin_cfg
  name "After RedundantMoveElimination"
  begin_block
    name "B0"
    from_bci -1
    to_bci -1
    predecessors 
    successors "B1" "B2" 
    xhandlers
    flags 
    probability 4607182418800017408
    begin_IR
      LIR
      nr    0  <|@ instruction [rsi|QWORD[.], rbp|QWORD] = LABEL alignment: 0 numbPhis: 0 label: ? <|@ <|@
      nr    2  <|@ instruction NOP <|@ <|@
      nr    4  <|@ instruction NOP <|@ <|@
      nr    6  <|@ instruction NOP <|@ <|@
      nr    8  <|@ instruction NOP <|@ <|@
      nr   10  <|@ instruction NOP <|@ <|@
      nr   12  <|@ instruction NOP <|@ <|@
      nr   14  <|@ instruction NOP <|@ <|@
      nr   16  <|@ instruction stack:16|QWORD = MOVE input: rbp|QWORD moveKind: QWORD <|@ <|@
      nr   18  <|@ instruction [] = HOTSPOTLOCKSTACK frameMapBuilder: jdk.graal.compiler.hotspot.amd64.AMD64HotSpotFrameMapBuilder@64144869 slotKind: QWORD <|@ <|@
      nr   22  <|@ instruction TESTBRANCH (x: rsi|QWORD[.], y: rsi|QWORD[.]) trueDestinationProbability: 9.91958358897982E-7 condition: = trueDestination: B0 -> B1 falseDestination: B0 -> B2 size: QWORD <|@ <|@
    end_IR
  end_block
  begin_block
    name "B2"
    from_bci -1
    to_bci -1
    predecessors "B0" 
    successors "B3" "B4" 
    xhandlers
    flags 
    probability 4607182409865250817
    begin_IR
      LIR
      nr   24  <|@ instruction [] = LABEL alignment: 0 numbPhis: 0 label: ? <|@ <|@
      nr   26  <|@ instruction NOP <|@ <|@
      nr   28  <|@ instruction NOP <|@ <|@
      nr   30  <|@ instruction NOP <|@ <|@
      nr   32  <|@ instruction NOP <|@ <|@
      nr   34  <|@ instruction NOP <|@ <|@
      nr   36  <|@ instruction NOP <|@ <|@
      nr   38  <|@ instruction NOP <|@ <|@
      nr   40  <|@ instruction NOP <|@ <|@
      nr   42  <|@ instruction NOP <|@ <|@
      nr   44  <|@ instruction rbx|DWORD = MOV input: [rsi|QWORD[.] + 8] size: DWORD <|@ <|@
      nr   46  <|@ instruction rax|QWORD = MOVE input: long[140154094223360|0x7f782b000000] <|@ <|@
      nr   48  <|@ instruction rbx|QWORD = UNCOMPRESSPOINTER (input: rbx|DWORD, ~baseRegister: rax|QWORD) nonNull: true lirKindTool: jdk.graal.compiler.hotspot.amd64.AMD64HotSpotLIRKindTool@d0246bd encoding: base: 140154094223360 shift: 0 <|@ <|@
      nr   50  <|@ instruction rax|QWORD = HOTSPOTLOADMETASPACECONSTANT input: meta{HotSpotType<Ljava/lang/String;, resolved>} <|@ <|@
      nr   52  <|@ instruction CMPBRANCH (x: rax|QWORD, y: rbx|QWORD) trueDestinationProbability: 0.43400564574488104 condition: = trueDestination: B2 -> B3 falseDestination: B2 -> B4 size: QWORD <|@ <|@
    end_IR
  end_block
  begin_block
    name "B4"
    from_bci -1
    to_bci -1
    predecessors "B2" 
    successors "B5" 
    xhandlers
    flags 
    probability 4603273238414083286
    begin_IR
      LIR
      nr   54  <|@ instruction [] = LABEL alignment: 0 numbPhis: 0 label: ? <|@ <|@
      nr   56  <|@ instruction NOP <|@ <|@
      nr   58  <|@ instruction NOP <|@ <|@
      nr   60  <|@ instruction NOP <|@ <|@
      nr   62  <|@ instruction NOP <|@ <|@
      nr   64  <|@ instruction NOP <|@ <|@
      nr   66  <|@ instruction NOP <|@ <|@
      nr   68  <|@ instruction NOP <|@ <|@
      nr   70  <|@ instruction NOP <|@ <|@
      nr   72  <|@ instruction NOP <|@ <|@
      nr   74  <|@ instruction NOP <|@ <|@
      nr   76  <|@ instruction NOP <|@ <|@
      nr   78  <|@ instruction NOP <|@ <|@
      nr   80  <|@ instruction rbx|QWORD = MOV input: [rbx|QWORD + 472] size: QWORD <|@ <|@
      nr   82  <|@ instruction rax|QWORD = MOV input: [rbx|QWORD + 64] size: QWORD <|@ <|@
      nr   90  <|@ st <@st|@live-base-pointers: []
java.lang.String.valueOf(String.java:4465) [bci: 11]
locals: - 
>@ <|@ instruction rax|QWORD[.] = CALL_INDIRECT (targetAddress: rax|QWORD, metaspaceMethod: rbx|QWORD, parameters: [rsi|QWORD[.]]) temps: [] callTarget: HotSpotMethod<Object.toString()> state [bci:11] <|@ <|@
      nr   94  <|@ instruction JUMP ~outgoingValues: [] destination: B4 -> B5 <|@ <|@
    end_IR
  end_block
  begin_block
    name "B3"
    from_bci -1
    to_bci -1
    predecessors "B2" 
    successors "B5" 
    xhandlers
    flags 
    probability 4601489962820240983
    begin_IR
      LIR
      nr   96  <|@ instruction [] = LABEL alignment: 0 numbPhis: 0 label: ? <|@ <|@
      nr   98  <|@ instruction NOP <|@ <|@
      nr  100  <|@ instruction NOP <|@ <|@
      nr  102  <|@ instruction NOP <|@ <|@
      nr   -1  <|@ instruction rax|QWORD[.] = MOVE input: rsi|QWORD[.] moveKind: QWORD // MoveResolver resolve mapping <|@ <|@
      nr  104  <|@ instruction JUMP ~outgoingValues: [] destination: B3 -> B5 <|@ <|@
    end_IR
  end_block
  begin_block
    name "B5"
    from_bci -1
    to_bci -1
    predecessors "B1" "B3" "B4" 
    successors 
    xhandlers
    flags 
    probability 4607182418800017408
    begin_IR
      LIR
      nr  106  <|@ instruction [] = LABEL alignment: 0 numbPhis: 1 label: ? <|@ <|@
      nr  108  <|@ instruction NOP <|@ <|@
      nr  110  <|@ instruction NOP <|@ <|@
      nr  112  <|@ instruction NOP <|@ <|@
      nr  114  <|@ instruction NOP <|@ <|@
      nr  116  <|@ instruction NOP <|@ <|@
      nr  118  <|@ instruction NOP <|@ <|@
      nr  120  <|@ instruction NOP <|@ <|@
      nr  122  <|@ instruction NOP <|@ <|@
      nr  126  <|@ instruction RETURN (savedRbp: stack:16|QWORD, value: rax|QWORD[.]) isStub: false requiresReservedStackAccessCheck: false thread: r15 scratchForSafepointOnReturn: rcx config: jdk.graal.compiler.hotspot.GraalHotSpotVMConfig@4817c460 <|@ <|@
    end_IR
  end_block
  begin_block
    name "B1"
    from_bci -1
    to_bci -1
    predecessors "B0" 
    successors "B5" 
    xhandlers
    flags 
    probability 4517291217531699200
    begin_IR
      LIR
      nr  128  <|@ instruction [] = LABEL alignment: 0 numbPhis: 0 label: ? <|@ <|@
      nr  130  <|@ instruction NOP <|@ <|@
      nr  132  <|@ instruction NOP <|@ <|@
      nr  134  <|@ instruction NOP <|@ <|@
      nr  136  <|@ instruction NOP <|@ <|@
      nr  138  <|@ instruction NOP <|@ <|@
      nr  140  <|@ instruction r10|QWORD[.] = HOTSPOTLOADOBJECTCONSTANT input: Object[String:"null"] <|@ <|@
      nr   -1  <|@ instruction rax|QWORD[.] = MOVE input: r10|QWORD[.] moveKind: QWORD // MoveResolver resolve mapping <|@ <|@
      nr  144  <|@ instruction JUMP ~outgoingValues: [] destination: B1 -> B5 <|@ <|@
    end_IR
  end_block
end_cfg
begin_bytecodes
     0: aload_0       
     1: ifnonnull     10
     4: ldc_w         #1000       // "null"
     7: goto          14
    10: aload_0       
    11: invokevirtual #281        // java.lang.Object.toString:()java.lang.String
    14: areturn       
   <|@
end_bytecodes
begin_cfg
  name "After NullCheckOptimizer"
  begin_block
    name "B0"
    from_bci -1
    to_bci -1
    predecessors 
    successors "B1" "B2" 
    xhandlers
    flags 
    probability 4607182418800017408
    begin_IR
      LIR
      nr    0  <|@ instruction [rsi|QWORD[.], rbp|QWORD] = LABEL alignment: 0 numbPhis: 0 label: ? <|@ <|@
      nr    2  <|@ instruction NOP <|@ <|@
      nr    4  <|@ instruction NOP <|@ <|@
      nr    6  <|@ instruction NOP <|@ <|@
      nr    8  <|@ instruction NOP <|@ <|@
      nr   10  <|@ instruction NOP <|@ <|@
      nr   12  <|@ instruction NOP <|@ <|@
      nr   14  <|@ instruction NOP <|@ <|@
      nr   16  <|@ instruction stack:16|QWORD = MOVE input: rbp|QWORD moveKind: QWORD <|@ <|@
      nr   18  <|@ instruction [] = HOTSPOTLOCKSTACK frameMapBuilder: jdk.graal.compiler.hotspot.amd64.AMD64HotSpotFrameMapBuilder@64144869 slotKind: QWORD <|@ <|@
      nr   22  <|@ instruction TESTBRANCH (x: rsi|QWORD[.], y: rsi|QWORD[.]) trueDestinationProbability: 9.91958358897982E-7 condition: = trueDestination: B0 -> B1 falseDestination: B0 -> B2 size: QWORD <|@ <|@
    end_IR
  end_block
  begin_block
    name "B2"
    from_bci -1
    to_bci -1
    predecessors "B0" 
    successors "B3" "B4" 
    xhandlers
    flags 
    probability 4607182409865250817
    begin_IR
      LIR
      nr   24  <|@ instruction [] = LABEL alignment: 0 numbPhis: 0 label: ? <|@ <|@
      nr   26  <|@ instruction NOP <|@ <|@
      nr   28  <|@ instruction NOP <|@ <|@
      nr   30  <|@ instruction NOP <|@ <|@
      nr   32  <|@ instruction NOP <|@ <|@
      nr   34  <|@ instruction NOP <|@ <|@
      nr   36  <|@ instruction NOP <|@ <|@
      nr   38  <|@ instruction NOP <|@ <|@
      nr   40  <|@ instruction NOP <|@ <|@
      nr   42  <|@ instruction NOP <|@ <|@
      nr   44  <|@ instruction rbx|DWORD = MOV input: [rsi|QWORD[.] + 8] size: DWORD <|@ <|@
      nr   46  <|@ instruction rax|QWORD = MOVE input: long[140154094223360|0x7f782b000000] <|@ <|@
      nr   48  <|@ instruction rbx|QWORD = UNCOMPRESSPOINTER (input: rbx|DWORD, ~baseRegister: rax|QWORD) nonNull: true lirKindTool: jdk.graal.compiler.hotspot.amd64.AMD64HotSpotLIRKindTool@d0246bd encoding: base: 140154094223360 shift: 0 <|@ <|@
      nr   50  <|@ instruction rax|QWORD = HOTSPOTLOADMETASPACECONSTANT input: meta{HotSpotType<Ljava/lang/String;, resolved>} <|@ <|@
      nr   52  <|@ instruction CMPBRANCH (x: rax|QWORD, y: rbx|QWORD) trueDestinationProbability: 0.43400564574488104 condition: = trueDestination: B2 -> B3 falseDestination: B2 -> B4 size: QWORD <|@ <|@
    end_IR
  end_block
  begin_block
    name "B4"
    from_bci -1
    to_bci -1
    predecessors "B2" 
    successors "B5" 
    xhandlers
    flags 
    probability 4603273238414083286
    begin_IR
      LIR
      nr   54  <|@ instruction [] = LABEL alignment: 0 numbPhis: 0 label: ? <|@ <|@
      nr   56  <|@ instruction NOP <|@ <|@
      nr   58  <|@ instruction NOP <|@ <|@
      nr   60  <|@ instruction NOP <|@ <|@
      nr   62  <|@ instruction NOP <|@ <|@
      nr   64  <|@ instruction NOP <|@ <|@
      nr   66  <|@ instruction NOP <|@ <|@
      nr   68  <|@ instruction NOP <|@ <|@
      nr   70  <|@ instruction NOP <|@ <|@
      nr   72  <|@ instruction NOP <|@ <|@
      nr   74  <|@ instruction NOP <|@ <|@
      nr   76  <|@ instruction NOP <|@ <|@
      nr   78  <|@ instruction NOP <|@ <|@
      nr   80  <|@ instruction rbx|QWORD = MOV input: [rbx|QWORD + 472] size: QWORD <|@ <|@
      nr   82  <|@ instruction rax|QWORD = MOV input: [rbx|QWORD + 64] size: QWORD <|@ <|@
      nr   90  <|@ st <@st|@live-base-pointers: []
java.lang.String.valueOf(String.java:4465) [bci: 11]
locals: - 
>@ <|@ instruction rax|QWORD[.] = CALL_INDIRECT (targetAddress: rax|QWORD, metaspaceMethod: rbx|QWORD, parameters: [rsi|QWORD[.]]) temps: [] callTarget: HotSpotMethod<Object.toString()> state [bci:11] <|@ <|@
      nr   94  <|@ instruction JUMP ~outgoingValues: [] destination: B4 -> B5 <|@ <|@
    end_IR
  end_block
  begin_block
    name "B3"
    from_bci -1
    to_bci -1
    predecessors "B2" 
    successors "B5" 
    xhandlers
    flags 
    probability 4601489962820240983
    begin_IR
      LIR
      nr   96  <|@ instruction [] = LABEL alignment: 0 numbPhis: 0 label: ? <|@ <|@
      nr   98  <|@ instruction NOP <|@ <|@
      nr  100  <|@ instruction NOP <|@ <|@
      nr  102  <|@ instruction NOP <|@ <|@
      nr   -1  <|@ instruction rax|QWORD[.] = MOVE input: rsi|QWORD[.] moveKind: QWORD // MoveResolver resolve mapping <|@ <|@
      nr  104  <|@ instruction JUMP ~outgoingValues: [] destination: B3 -> B5 <|@ <|@
    end_IR
  end_block
  begin_block
    name "B5"
    from_bci -1
    to_bci -1
    predecessors "B1" "B3" "B4" 
    successors 
    xhandlers
    flags 
    probability 4607182418800017408
    begin_IR
      LIR
      nr  106  <|@ instruction [] = LABEL alignment: 0 numbPhis: 1 label: ? <|@ <|@
      nr  108  <|@ instruction NOP <|@ <|@
      nr  110  <|@ instruction NOP <|@ <|@
      nr  112  <|@ instruction NOP <|@ <|@
      nr  114  <|@ instruction NOP <|@ <|@
      nr  116  <|@ instruction NOP <|@ <|@
      nr  118  <|@ instruction NOP <|@ <|@
      nr  120  <|@ instruction NOP <|@ <|@
      nr  122  <|@ instruction NOP <|@ <|@
      nr  126  <|@ instruction RETURN (savedRbp: stack:16|QWORD, value: rax|QWORD[.]) isStub: false requiresReservedStackAccessCheck: false thread: r15 scratchForSafepointOnReturn: rcx config: jdk.graal.compiler.hotspot.GraalHotSpotVMConfig@4817c460 <|@ <|@
    end_IR
  end_block
  begin_block
    name "B1"
    from_bci -1
    to_bci -1
    predecessors "B0" 
    successors "B5" 
    xhandlers
    flags 
    probability 4517291217531699200
    begin_IR
      LIR
      nr  128  <|@ instruction [] = LABEL alignment: 0 numbPhis: 0 label: ? <|@ <|@
      nr  130  <|@ instruction NOP <|@ <|@
      nr  132  <|@ instruction NOP <|@ <|@
      nr  134  <|@ instruction NOP <|@ <|@
      nr  136  <|@ instruction NOP <|@ <|@
      nr  138  <|@ instruction NOP <|@ <|@
      nr  140  <|@ instruction r10|QWORD[.] = HOTSPOTLOADOBJECTCONSTANT input: Object[String:"null"] <|@ <|@
      nr   -1  <|@ instruction rax|QWORD[.] = MOVE input: r10|QWORD[.] moveKind: QWORD // MoveResolver resolve mapping <|@ <|@
      nr  144  <|@ instruction JUMP ~outgoingValues: [] destination: B1 -> B5 <|@ <|@
    end_IR
  end_block
end_cfg
begin_bytecodes
     0: aload_0       
     1: ifnonnull     10
     4: ldc_w         #1000       // "null"
     7: goto          14
    10: aload_0       
    11: invokevirtual #281        // java.lang.Object.toString:()java.lang.String
    14: areturn       
   <|@
end_bytecodes
begin_cfg
  name "After ControlFlowOptimizer"
  begin_block
    name "B0"
    from_bci -1
    to_bci -1
    predecessors 
    successors "B1" "B2" 
    xhandlers
    flags 
    probability 4607182418800017408
    begin_IR
      LIR
      nr    0  <|@ instruction [rsi|QWORD[.], rbp|QWORD] = LABEL alignment: 0 numbPhis: 0 label: ? <|@ <|@
      nr    2  <|@ instruction NOP <|@ <|@
      nr    4  <|@ instruction NOP <|@ <|@
      nr    6  <|@ instruction NOP <|@ <|@
      nr    8  <|@ instruction NOP <|@ <|@
      nr   10  <|@ instruction NOP <|@ <|@
      nr   12  <|@ instruction NOP <|@ <|@
      nr   14  <|@ instruction NOP <|@ <|@
      nr   16  <|@ instruction stack:16|QWORD = MOVE input: rbp|QWORD moveKind: QWORD <|@ <|@
      nr   18  <|@ instruction [] = HOTSPOTLOCKSTACK frameMapBuilder: jdk.graal.compiler.hotspot.amd64.AMD64HotSpotFrameMapBuilder@64144869 slotKind: QWORD <|@ <|@
      nr   22  <|@ instruction TESTBRANCH (x: rsi|QWORD[.], y: rsi|QWORD[.]) trueDestinationProbability: 9.91958358897982E-7 condition: = trueDestination: B0 -> B1 falseDestination: B0 -> B2 size: QWORD <|@ <|@
    end_IR
  end_block
  begin_block
    name "B2"
    from_bci -1
    to_bci -1
    predecessors "B0" 
    successors "B3" "B4" 
    xhandlers
    flags 
    probability 4607182409865250817
    begin_IR
      LIR
      nr   24  <|@ instruction [] = LABEL alignment: 0 numbPhis: 0 label: ? <|@ <|@
      nr   26  <|@ instruction NOP <|@ <|@
      nr   28  <|@ instruction NOP <|@ <|@
      nr   30  <|@ instruction NOP <|@ <|@
      nr   32  <|@ instruction NOP <|@ <|@
      nr   34  <|@ instruction NOP <|@ <|@
      nr   36  <|@ instruction NOP <|@ <|@
      nr   38  <|@ instruction NOP <|@ <|@
      nr   40  <|@ instruction NOP <|@ <|@
      nr   42  <|@ instruction NOP <|@ <|@
      nr   44  <|@ instruction rbx|DWORD = MOV input: [rsi|QWORD[.] + 8] size: DWORD <|@ <|@
      nr   46  <|@ instruction rax|QWORD = MOVE input: long[140154094223360|0x7f782b000000] <|@ <|@
      nr   48  <|@ instruction rbx|QWORD = UNCOMPRESSPOINTER (input: rbx|DWORD, ~baseRegister: rax|QWORD) nonNull: true lirKindTool: jdk.graal.compiler.hotspot.amd64.AMD64HotSpotLIRKindTool@d0246bd encoding: base: 140154094223360 shift: 0 <|@ <|@
      nr   50  <|@ instruction rax|QWORD = HOTSPOTLOADMETASPACECONSTANT input: meta{HotSpotType<Ljava/lang/String;, resolved>} <|@ <|@
      nr   52  <|@ instruction CMPBRANCH (x: rax|QWORD, y: rbx|QWORD) trueDestinationProbability: 0.43400564574488104 condition: = trueDestination: B2 -> B3 falseDestination: B2 -> B4 size: QWORD <|@ <|@
    end_IR
  end_block
  begin_block
    name "B4"
    from_bci -1
    to_bci -1
    predecessors "B2" 
    successors "B5" 
    xhandlers
    flags 
    probability 4603273238414083286
    begin_IR
      LIR
      nr   54  <|@ instruction [] = LABEL alignment: 0 numbPhis: 0 label: ? <|@ <|@
      nr   56  <|@ instruction NOP <|@ <|@
      nr   58  <|@ instruction NOP <|@ <|@
      nr   60  <|@ instruction NOP <|@ <|@
      nr   62  <|@ instruction NOP <|@ <|@
      nr   64  <|@ instruction NOP <|@ <|@
      nr   66  <|@ instruction NOP <|@ <|@
      nr   68  <|@ instruction NOP <|@ <|@
      nr   70  <|@ instruction NOP <|@ <|@
      nr   72  <|@ instruction NOP <|@ <|@
      nr   74  <|@ instruction NOP <|@ <|@
      nr   76  <|@ instruction NOP <|@ <|@
      nr   78  <|@ instruction NOP <|@ <|@
      nr   80  <|@ instruction rbx|QWORD = MOV input: [rbx|QWORD + 472] size: QWORD <|@ <|@
      nr   82  <|@ instruction rax|QWORD = MOV input: [rbx|QWORD + 64] size: QWORD <|@ <|@
      nr   90  <|@ st <@st|@live-base-pointers: []
java.lang.String.valueOf(String.java:4465) [bci: 11]
locals: - 
>@ <|@ instruction rax|QWORD[.] = CALL_INDIRECT (targetAddress: rax|QWORD, metaspaceMethod: rbx|QWORD, parameters: [rsi|QWORD[.]]) temps: [] callTarget: HotSpotMethod<Object.toString()> state [bci:11] <|@ <|@
      nr   94  <|@ instruction JUMP ~outgoingValues: [] destination: B4 -> B5 <|@ <|@
    end_IR
  end_block
  begin_block
    name "B3"
    from_bci -1
    to_bci -1
    predecessors "B2" 
    successors "B5" 
    xhandlers
    flags 
    probability 4601489962820240983
    begin_IR
      LIR
      nr   96  <|@ instruction [] = LABEL alignment: 0 numbPhis: 0 label: ? <|@ <|@
      nr   98  <|@ instruction NOP <|@ <|@
      nr  100  <|@ instruction NOP <|@ <|@
      nr  102  <|@ instruction NOP <|@ <|@
      nr   -1  <|@ instruction rax|QWORD[.] = MOVE input: rsi|QWORD[.] moveKind: QWORD // MoveResolver resolve mapping <|@ <|@
      nr  104  <|@ instruction JUMP ~outgoingValues: [] destination: B3 -> B5 <|@ <|@
    end_IR
  end_block
  begin_block
    name "B5"
    from_bci -1
    to_bci -1
    predecessors "B1" "B3" "B4" 
    successors 
    xhandlers
    flags 
    probability 4607182418800017408
    begin_IR
      LIR
      nr  106  <|@ instruction [] = LABEL alignment: 0 numbPhis: 1 label: ? <|@ <|@
      nr  108  <|@ instruction NOP <|@ <|@
      nr  110  <|@ instruction NOP <|@ <|@
      nr  112  <|@ instruction NOP <|@ <|@
      nr  114  <|@ instruction NOP <|@ <|@
      nr  116  <|@ instruction NOP <|@ <|@
      nr  118  <|@ instruction NOP <|@ <|@
      nr  120  <|@ instruction NOP <|@ <|@
      nr  122  <|@ instruction NOP <|@ <|@
      nr  126  <|@ instruction RETURN (savedRbp: stack:16|QWORD, value: rax|QWORD[.]) isStub: false requiresReservedStackAccessCheck: false thread: r15 scratchForSafepointOnReturn: rcx config: jdk.graal.compiler.hotspot.GraalHotSpotVMConfig@4817c460 <|@ <|@
    end_IR
  end_block
  begin_block
    name "B1"
    from_bci -1
    to_bci -1
    predecessors "B0" 
    successors "B5" 
    xhandlers
    flags 
    probability 4517291217531699200
    begin_IR
      LIR
      nr  128  <|@ instruction [] = LABEL alignment: 0 numbPhis: 0 label: ? <|@ <|@
      nr  130  <|@ instruction NOP <|@ <|@
      nr  132  <|@ instruction NOP <|@ <|@
      nr  134  <|@ instruction NOP <|@ <|@
      nr  136  <|@ instruction NOP <|@ <|@
      nr  138  <|@ instruction NOP <|@ <|@
      nr  140  <|@ instruction r10|QWORD[.] = HOTSPOTLOADOBJECTCONSTANT input: Object[String:"null"] <|@ <|@
      nr   -1  <|@ instruction rax|QWORD[.] = MOVE input: r10|QWORD[.] moveKind: QWORD // MoveResolver resolve mapping <|@ <|@
      nr  144  <|@ instruction JUMP ~outgoingValues: [] destination: B1 -> B5 <|@ <|@
    end_IR
  end_block
end_cfg
begin_bytecodes
     0: aload_0       
     1: ifnonnull     10
     4: ldc_w         #1000       // "null"
     7: goto          14
    10: aload_0       
    11: invokevirtual #281        // java.lang.Object.toString:()java.lang.String
    14: areturn       
   <|@
end_bytecodes
begin_cfg
  name "After ComputeCodeEmissionOrder"
  begin_block
    name "B0"
    from_bci -1
    to_bci -1
    predecessors 
    successors "B1" "B2" 
    xhandlers
    flags 
    probability 4607182418800017408
    begin_IR
      LIR
      nr    0  <|@ instruction [rsi|QWORD[.], rbp|QWORD] = LABEL alignment: 0 numbPhis: 0 label: ? <|@ <|@
      nr    2  <|@ instruction NOP <|@ <|@
      nr    4  <|@ instruction NOP <|@ <|@
      nr    6  <|@ instruction NOP <|@ <|@
      nr    8  <|@ instruction NOP <|@ <|@
      nr   10  <|@ instruction NOP <|@ <|@
      nr   12  <|@ instruction NOP <|@ <|@
      nr   14  <|@ instruction NOP <|@ <|@
      nr   16  <|@ instruction stack:16|QWORD = MOVE input: rbp|QWORD moveKind: QWORD <|@ <|@
      nr   18  <|@ instruction [] = HOTSPOTLOCKSTACK frameMapBuilder: jdk.graal.compiler.hotspot.amd64.AMD64HotSpotFrameMapBuilder@64144869 slotKind: QWORD <|@ <|@
      nr   22  <|@ instruction TESTBRANCH (x: rsi|QWORD[.], y: rsi|QWORD[.]) trueDestinationProbability: 9.91958358897982E-7 condition: = trueDestination: B0 -> B1 falseDestination: B0 -> B2 size: QWORD <|@ <|@
    end_IR
  end_block
  begin_block
    name "B2"
    from_bci -1
    to_bci -1
    predecessors "B0" 
    successors "B3" "B4" 
    xhandlers
    flags 
    probability 4607182409865250817
    begin_IR
      LIR
      nr   24  <|@ instruction [] = LABEL alignment: 0 numbPhis: 0 label: ? <|@ <|@
      nr   26  <|@ instruction NOP <|@ <|@
      nr   28  <|@ instruction NOP <|@ <|@
      nr   30  <|@ instruction NOP <|@ <|@
      nr   32  <|@ instruction NOP <|@ <|@
      nr   34  <|@ instruction NOP <|@ <|@
      nr   36  <|@ instruction NOP <|@ <|@
      nr   38  <|@ instruction NOP <|@ <|@
      nr   40  <|@ instruction NOP <|@ <|@
      nr   42  <|@ instruction NOP <|@ <|@
      nr   44  <|@ instruction rbx|DWORD = MOV input: [rsi|QWORD[.] + 8] size: DWORD <|@ <|@
      nr   46  <|@ instruction rax|QWORD = MOVE input: long[140154094223360|0x7f782b000000] <|@ <|@
      nr   48  <|@ instruction rbx|QWORD = UNCOMPRESSPOINTER (input: rbx|DWORD, ~baseRegister: rax|QWORD) nonNull: true lirKindTool: jdk.graal.compiler.hotspot.amd64.AMD64HotSpotLIRKindTool@d0246bd encoding: base: 140154094223360 shift: 0 <|@ <|@
      nr   50  <|@ instruction rax|QWORD = HOTSPOTLOADMETASPACECONSTANT input: meta{HotSpotType<Ljava/lang/String;, resolved>} <|@ <|@
      nr   52  <|@ instruction CMPBRANCH (x: rax|QWORD, y: rbx|QWORD) trueDestinationProbability: 0.43400564574488104 condition: = trueDestination: B2 -> B3 falseDestination: B2 -> B4 size: QWORD <|@ <|@
    end_IR
  end_block
  begin_block
    name "B4"
    from_bci -1
    to_bci -1
    predecessors "B2" 
    successors "B5" 
    xhandlers
    flags 
    probability 4603273238414083286
    begin_IR
      LIR
      nr   54  <|@ instruction [] = LABEL alignment: 0 numbPhis: 0 label: ? <|@ <|@
      nr   56  <|@ instruction NOP <|@ <|@
      nr   58  <|@ instruction NOP <|@ <|@
      nr   60  <|@ instruction NOP <|@ <|@
      nr   62  <|@ instruction NOP <|@ <|@
      nr   64  <|@ instruction NOP <|@ <|@
      nr   66  <|@ instruction NOP <|@ <|@
      nr   68  <|@ instruction NOP <|@ <|@
      nr   70  <|@ instruction NOP <|@ <|@
      nr   72  <|@ instruction NOP <|@ <|@
      nr   74  <|@ instruction NOP <|@ <|@
      nr   76  <|@ instruction NOP <|@ <|@
      nr   78  <|@ instruction NOP <|@ <|@
      nr   80  <|@ instruction rbx|QWORD = MOV input: [rbx|QWORD + 472] size: QWORD <|@ <|@
      nr   82  <|@ instruction rax|QWORD = MOV input: [rbx|QWORD + 64] size: QWORD <|@ <|@
      nr   90  <|@ st <@st|@live-base-pointers: []
java.lang.String.valueOf(String.java:4465) [bci: 11]
locals: - 
>@ <|@ instruction rax|QWORD[.] = CALL_INDIRECT (targetAddress: rax|QWORD, metaspaceMethod: rbx|QWORD, parameters: [rsi|QWORD[.]]) temps: [] callTarget: HotSpotMethod<Object.toString()> state [bci:11] <|@ <|@
      nr   94  <|@ instruction JUMP ~outgoingValues: [] destination: B4 -> B5 <|@ <|@
    end_IR
  end_block
  begin_block
    name "B5"
    from_bci -1
    to_bci -1
    predecessors "B1" "B3" "B4" 
    successors 
    xhandlers
    flags 
    probability 4607182418800017408
    begin_IR
      LIR
      nr  106  <|@ instruction [] = LABEL alignment: 0 numbPhis: 1 label: ? <|@ <|@
      nr  108  <|@ instruction NOP <|@ <|@
      nr  110  <|@ instruction NOP <|@ <|@
      nr  112  <|@ instruction NOP <|@ <|@
      nr  114  <|@ instruction NOP <|@ <|@
      nr  116  <|@ instruction NOP <|@ <|@
      nr  118  <|@ instruction NOP <|@ <|@
      nr  120  <|@ instruction NOP <|@ <|@
      nr  122  <|@ instruction NOP <|@ <|@
      nr  126  <|@ instruction RETURN (savedRbp: stack:16|QWORD, value: rax|QWORD[.]) isStub: false requiresReservedStackAccessCheck: false thread: r15 scratchForSafepointOnReturn: rcx config: jdk.graal.compiler.hotspot.GraalHotSpotVMConfig@4817c460 <|@ <|@
    end_IR
  end_block
  begin_block
    name "B3"
    from_bci -1
    to_bci -1
    predecessors "B2" 
    successors "B5" 
    xhandlers
    flags 
    probability 4601489962820240983
    begin_IR
      LIR
      nr   96  <|@ instruction [] = LABEL alignment: 0 numbPhis: 0 label: ? <|@ <|@
      nr   98  <|@ instruction NOP <|@ <|@
      nr  100  <|@ instruction NOP <|@ <|@
      nr  102  <|@ instruction NOP <|@ <|@
      nr   -1  <|@ instruction rax|QWORD[.] = MOVE input: rsi|QWORD[.] moveKind: QWORD // MoveResolver resolve mapping <|@ <|@
      nr  104  <|@ instruction JUMP ~outgoingValues: [] destination: B3 -> B5 <|@ <|@
    end_IR
  end_block
  begin_block
    name "B1"
    from_bci -1
    to_bci -1
    predecessors "B0" 
    successors "B5" 
    xhandlers
    flags 
    probability 4517291217531699200
    begin_IR
      LIR
      nr  128  <|@ instruction [] = LABEL alignment: 0 numbPhis: 0 label: ? <|@ <|@
      nr  130  <|@ instruction NOP <|@ <|@
      nr  132  <|@ instruction NOP <|@ <|@
      nr  134  <|@ instruction NOP <|@ <|@
      nr  136  <|@ instruction NOP <|@ <|@
      nr  138  <|@ instruction NOP <|@ <|@
      nr  140  <|@ instruction r10|QWORD[.] = HOTSPOTLOADOBJECTCONSTANT input: Object[String:"null"] <|@ <|@
      nr   -1  <|@ instruction rax|QWORD[.] = MOVE input: r10|QWORD[.] moveKind: QWORD // MoveResolver resolve mapping <|@ <|@
      nr  144  <|@ instruction JUMP ~outgoingValues: [] destination: B1 -> B5 <|@ <|@
    end_IR
  end_block
end_cfg
begin_bytecodes
     0: aload_0       
     1: ifnonnull     10
     4: ldc_w         #1000       // "null"
     7: goto          14
    10: aload_0       
    11: invokevirtual #281        // java.lang.Object.toString:()java.lang.String
    14: areturn       
   <|@
end_bytecodes
begin_cfg
  name "After StackMoveOptimization"
  begin_block
    name "B0"
    from_bci -1
    to_bci -1
    predecessors 
    successors "B1" "B2" 
    xhandlers
    flags 
    probability 4607182418800017408
    begin_IR
      LIR
      nr    0  <|@ instruction [rsi|QWORD[.], rbp|QWORD] = LABEL alignment: 0 numbPhis: 0 label: ? <|@ <|@
      nr    2  <|@ instruction NOP <|@ <|@
      nr    4  <|@ instruction NOP <|@ <|@
      nr    6  <|@ instruction NOP <|@ <|@
      nr    8  <|@ instruction NOP <|@ <|@
      nr   10  <|@ instruction NOP <|@ <|@
      nr   12  <|@ instruction NOP <|@ <|@
      nr   14  <|@ instruction NOP <|@ <|@
      nr   16  <|@ instruction stack:16|QWORD = MOVE input: rbp|QWORD moveKind: QWORD <|@ <|@
      nr   18  <|@ instruction [] = HOTSPOTLOCKSTACK frameMapBuilder: jdk.graal.compiler.hotspot.amd64.AMD64HotSpotFrameMapBuilder@64144869 slotKind: QWORD <|@ <|@
      nr   22  <|@ instruction TESTBRANCH (x: rsi|QWORD[.], y: rsi|QWORD[.]) trueDestinationProbability: 9.91958358897982E-7 condition: = trueDestination: B0 -> B1 falseDestination: B0 -> B2 size: QWORD <|@ <|@
    end_IR
  end_block
  begin_block
    name "B2"
    from_bci -1
    to_bci -1
    predecessors "B0" 
    successors "B3" "B4" 
    xhandlers
    flags 
    probability 4607182409865250817
    begin_IR
      LIR
      nr   24  <|@ instruction [] = LABEL alignment: 0 numbPhis: 0 label: ? <|@ <|@
      nr   26  <|@ instruction NOP <|@ <|@
      nr   28  <|@ instruction NOP <|@ <|@
      nr   30  <|@ instruction NOP <|@ <|@
      nr   32  <|@ instruction NOP <|@ <|@
      nr   34  <|@ instruction NOP <|@ <|@
      nr   36  <|@ instruction NOP <|@ <|@
      nr   38  <|@ instruction NOP <|@ <|@
      nr   40  <|@ instruction NOP <|@ <|@
      nr   42  <|@ instruction NOP <|@ <|@
      nr   44  <|@ instruction rbx|DWORD = MOV input: [rsi|QWORD[.] + 8] size: DWORD <|@ <|@
      nr   46  <|@ instruction rax|QWORD = MOVE input: long[140154094223360|0x7f782b000000] <|@ <|@
      nr   48  <|@ instruction rbx|QWORD = UNCOMPRESSPOINTER (input: rbx|DWORD, ~baseRegister: rax|QWORD) nonNull: true lirKindTool: jdk.graal.compiler.hotspot.amd64.AMD64HotSpotLIRKindTool@d0246bd encoding: base: 140154094223360 shift: 0 <|@ <|@
      nr   50  <|@ instruction rax|QWORD = HOTSPOTLOADMETASPACECONSTANT input: meta{HotSpotType<Ljava/lang/String;, resolved>} <|@ <|@
      nr   52  <|@ instruction CMPBRANCH (x: rax|QWORD, y: rbx|QWORD) trueDestinationProbability: 0.43400564574488104 condition: = trueDestination: B2 -> B3 falseDestination: B2 -> B4 size: QWORD <|@ <|@
    end_IR
  end_block
  begin_block
    name "B4"
    from_bci -1
    to_bci -1
    predecessors "B2" 
    successors "B5" 
    xhandlers
    flags 
    probability 4603273238414083286
    begin_IR
      LIR
      nr   54  <|@ instruction [] = LABEL alignment: 0 numbPhis: 0 label: ? <|@ <|@
      nr   56  <|@ instruction NOP <|@ <|@
      nr   58  <|@ instruction NOP <|@ <|@
      nr   60  <|@ instruction NOP <|@ <|@
      nr   62  <|@ instruction NOP <|@ <|@
      nr   64  <|@ instruction NOP <|@ <|@
      nr   66  <|@ instruction NOP <|@ <|@
      nr   68  <|@ instruction NOP <|@ <|@
      nr   70  <|@ instruction NOP <|@ <|@
      nr   72  <|@ instruction NOP <|@ <|@
      nr   74  <|@ instruction NOP <|@ <|@
      nr   76  <|@ instruction NOP <|@ <|@
      nr   78  <|@ instruction NOP <|@ <|@
      nr   80  <|@ instruction rbx|QWORD = MOV input: [rbx|QWORD + 472] size: QWORD <|@ <|@
      nr   82  <|@ instruction rax|QWORD = MOV input: [rbx|QWORD + 64] size: QWORD <|@ <|@
      nr   90  <|@ st <@st|@live-base-pointers: []
java.lang.String.valueOf(String.java:4465) [bci: 11]
locals: - 
>@ <|@ instruction rax|QWORD[.] = CALL_INDIRECT (targetAddress: rax|QWORD, metaspaceMethod: rbx|QWORD, parameters: [rsi|QWORD[.]]) temps: [] callTarget: HotSpotMethod<Object.toString()> state [bci:11] <|@ <|@
      nr   94  <|@ instruction JUMP ~outgoingValues: [] destination: B4 -> B5 <|@ <|@
    end_IR
  end_block
  begin_block
    name "B5"
    from_bci -1
    to_bci -1
    predecessors "B1" "B3" "B4" 
    successors 
    xhandlers
    flags 
    probability 4607182418800017408
    begin_IR
      LIR
      nr  106  <|@ instruction [] = LABEL alignment: 0 numbPhis: 1 label: ? <|@ <|@
      nr  108  <|@ instruction NOP <|@ <|@
      nr  110  <|@ instruction NOP <|@ <|@
      nr  112  <|@ instruction NOP <|@ <|@
      nr  114  <|@ instruction NOP <|@ <|@
      nr  116  <|@ instruction NOP <|@ <|@
      nr  118  <|@ instruction NOP <|@ <|@
      nr  120  <|@ instruction NOP <|@ <|@
      nr  122  <|@ instruction NOP <|@ <|@
      nr  126  <|@ instruction RETURN (savedRbp: stack:16|QWORD, value: rax|QWORD[.]) isStub: false requiresReservedStackAccessCheck: false thread: r15 scratchForSafepointOnReturn: rcx config: jdk.graal.compiler.hotspot.GraalHotSpotVMConfig@4817c460 <|@ <|@
    end_IR
  end_block
  begin_block
    name "B3"
    from_bci -1
    to_bci -1
    predecessors "B2" 
    successors "B5" 
    xhandlers
    flags 
    probability 4601489962820240983
    begin_IR
      LIR
      nr   96  <|@ instruction [] = LABEL alignment: 0 numbPhis: 0 label: ? <|@ <|@
      nr   98  <|@ instruction NOP <|@ <|@
      nr  100  <|@ instruction NOP <|@ <|@
      nr  102  <|@ instruction NOP <|@ <|@
      nr   -1  <|@ instruction rax|QWORD[.] = MOVE input: rsi|QWORD[.] moveKind: QWORD // MoveResolver resolve mapping <|@ <|@
      nr  104  <|@ instruction JUMP ~outgoingValues: [] destination: B3 -> B5 <|@ <|@
    end_IR
  end_block
  begin_block
    name "B1"
    from_bci -1
    to_bci -1
    predecessors "B0" 
    successors "B5" 
    xhandlers
    flags 
    probability 4517291217531699200
    begin_IR
      LIR
      nr  128  <|@ instruction [] = LABEL alignment: 0 numbPhis: 0 label: ? <|@ <|@
      nr  130  <|@ instruction NOP <|@ <|@
      nr  132  <|@ instruction NOP <|@ <|@
      nr  134  <|@ instruction NOP <|@ <|@
      nr  136  <|@ instruction NOP <|@ <|@
      nr  138  <|@ instruction NOP <|@ <|@
      nr  140  <|@ instruction r10|QWORD[.] = HOTSPOTLOADOBJECTCONSTANT input: Object[String:"null"] <|@ <|@
      nr   -1  <|@ instruction rax|QWORD[.] = MOVE input: r10|QWORD[.] moveKind: QWORD // MoveResolver resolve mapping <|@ <|@
      nr  144  <|@ instruction JUMP ~outgoingValues: [] destination: B1 -> B5 <|@ <|@
    end_IR
  end_block
end_cfg
begin_bytecodes
     0: aload_0       
     1: ifnonnull     10
     4: ldc_w         #1000       // "null"
     7: goto          14
    10: aload_0       
    11: invokevirtual #281        // java.lang.Object.toString:()java.lang.String
    14: areturn       
   <|@
end_bytecodes
begin_cfg
  name "After PostAllocationOptimizationStage"
  begin_block
    name "B0"
    from_bci -1
    to_bci -1
    predecessors 
    successors "B1" "B2" 
    xhandlers
    flags 
    probability 4607182418800017408
    begin_IR
      LIR
      nr    0  <|@ instruction [rsi|QWORD[.], rbp|QWORD] = LABEL alignment: 0 numbPhis: 0 label: ? <|@ <|@
      nr    2  <|@ instruction NOP <|@ <|@
      nr    4  <|@ instruction NOP <|@ <|@
      nr    6  <|@ instruction NOP <|@ <|@
      nr    8  <|@ instruction NOP <|@ <|@
      nr   10  <|@ instruction NOP <|@ <|@
      nr   12  <|@ instruction NOP <|@ <|@
      nr   14  <|@ instruction NOP <|@ <|@
      nr   16  <|@ instruction stack:16|QWORD = MOVE input: rbp|QWORD moveKind: QWORD <|@ <|@
      nr   18  <|@ instruction [] = HOTSPOTLOCKSTACK frameMapBuilder: jdk.graal.compiler.hotspot.amd64.AMD64HotSpotFrameMapBuilder@64144869 slotKind: QWORD <|@ <|@
      nr   22  <|@ instruction TESTBRANCH (x: rsi|QWORD[.], y: rsi|QWORD[.]) trueDestinationProbability: 9.91958358897982E-7 condition: = trueDestination: B0 -> B1 falseDestination: B0 -> B2 size: QWORD <|@ <|@
    end_IR
  end_block
  begin_block
    name "B2"
    from_bci -1
    to_bci -1
    predecessors "B0" 
    successors "B3" "B4" 
    xhandlers
    flags 
    probability 4607182409865250817
    begin_IR
      LIR
      nr   24  <|@ instruction [] = LABEL alignment: 0 numbPhis: 0 label: ? <|@ <|@
      nr   26  <|@ instruction NOP <|@ <|@
      nr   28  <|@ instruction NOP <|@ <|@
      nr   30  <|@ instruction NOP <|@ <|@
      nr   32  <|@ instruction NOP <|@ <|@
      nr   34  <|@ instruction NOP <|@ <|@
      nr   36  <|@ instruction NOP <|@ <|@
      nr   38  <|@ instruction NOP <|@ <|@
      nr   40  <|@ instruction NOP <|@ <|@
      nr   42  <|@ instruction NOP <|@ <|@
      nr   44  <|@ instruction rbx|DWORD = MOV input: [rsi|QWORD[.] + 8] size: DWORD <|@ <|@
      nr   46  <|@ instruction rax|QWORD = MOVE input: long[140154094223360|0x7f782b000000] <|@ <|@
      nr   48  <|@ instruction rbx|QWORD = UNCOMPRESSPOINTER (input: rbx|DWORD, ~baseRegister: rax|QWORD) nonNull: true lirKindTool: jdk.graal.compiler.hotspot.amd64.AMD64HotSpotLIRKindTool@d0246bd encoding: base: 140154094223360 shift: 0 <|@ <|@
      nr   50  <|@ instruction rax|QWORD = HOTSPOTLOADMETASPACECONSTANT input: meta{HotSpotType<Ljava/lang/String;, resolved>} <|@ <|@
      nr   52  <|@ instruction CMPBRANCH (x: rax|QWORD, y: rbx|QWORD) trueDestinationProbability: 0.43400564574488104 condition: = trueDestination: B2 -> B3 falseDestination: B2 -> B4 size: QWORD <|@ <|@
    end_IR
  end_block
  begin_block
    name "B4"
    from_bci -1
    to_bci -1
    predecessors "B2" 
    successors "B5" 
    xhandlers
    flags 
    probability 4603273238414083286
    begin_IR
      LIR
      nr   54  <|@ instruction [] = LABEL alignment: 0 numbPhis: 0 label: ? <|@ <|@
      nr   56  <|@ instruction NOP <|@ <|@
      nr   58  <|@ instruction NOP <|@ <|@
      nr   60  <|@ instruction NOP <|@ <|@
      nr   62  <|@ instruction NOP <|@ <|@
      nr   64  <|@ instruction NOP <|@ <|@
      nr   66  <|@ instruction NOP <|@ <|@
      nr   68  <|@ instruction NOP <|@ <|@
      nr   70  <|@ instruction NOP <|@ <|@
      nr   72  <|@ instruction NOP <|@ <|@
      nr   74  <|@ instruction NOP <|@ <|@
      nr   76  <|@ instruction NOP <|@ <|@
      nr   78  <|@ instruction NOP <|@ <|@
      nr   80  <|@ instruction rbx|QWORD = MOV input: [rbx|QWORD + 472] size: QWORD <|@ <|@
      nr   82  <|@ instruction rax|QWORD = MOV input: [rbx|QWORD + 64] size: QWORD <|@ <|@
      nr   90  <|@ st <@st|@live-base-pointers: []
java.lang.String.valueOf(String.java:4465) [bci: 11]
locals: - 
>@ <|@ instruction rax|QWORD[.] = CALL_INDIRECT (targetAddress: rax|QWORD, metaspaceMethod: rbx|QWORD, parameters: [rsi|QWORD[.]]) temps: [] callTarget: HotSpotMethod<Object.toString()> state [bci:11] <|@ <|@
      nr   94  <|@ instruction JUMP ~outgoingValues: [] destination: B4 -> B5 <|@ <|@
    end_IR
  end_block
  begin_block
    name "B5"
    from_bci -1
    to_bci -1
    predecessors "B1" "B3" "B4" 
    successors 
    xhandlers
    flags 
    probability 4607182418800017408
    begin_IR
      LIR
      nr  106  <|@ instruction [] = LABEL alignment: 0 numbPhis: 1 label: ? <|@ <|@
      nr  108  <|@ instruction NOP <|@ <|@
      nr  110  <|@ instruction NOP <|@ <|@
      nr  112  <|@ instruction NOP <|@ <|@
      nr  114  <|@ instruction NOP <|@ <|@
      nr  116  <|@ instruction NOP <|@ <|@
      nr  118  <|@ instruction NOP <|@ <|@
      nr  120  <|@ instruction NOP <|@ <|@
      nr  122  <|@ instruction NOP <|@ <|@
      nr  126  <|@ instruction RETURN (savedRbp: stack:16|QWORD, value: rax|QWORD[.]) isStub: false requiresReservedStackAccessCheck: false thread: r15 scratchForSafepointOnReturn: rcx config: jdk.graal.compiler.hotspot.GraalHotSpotVMConfig@4817c460 <|@ <|@
    end_IR
  end_block
  begin_block
    name "B3"
    from_bci -1
    to_bci -1
    predecessors "B2" 
    successors "B5" 
    xhandlers
    flags 
    probability 4601489962820240983
    begin_IR
      LIR
      nr   96  <|@ instruction [] = LABEL alignment: 0 numbPhis: 0 label: ? <|@ <|@
      nr   98  <|@ instruction NOP <|@ <|@
      nr  100  <|@ instruction NOP <|@ <|@
      nr  102  <|@ instruction NOP <|@ <|@
      nr   -1  <|@ instruction rax|QWORD[.] = MOVE input: rsi|QWORD[.] moveKind: QWORD // MoveResolver resolve mapping <|@ <|@
      nr  104  <|@ instruction JUMP ~outgoingValues: [] destination: B3 -> B5 <|@ <|@
    end_IR
  end_block
  begin_block
    name "B1"
    from_bci -1
    to_bci -1
    predecessors "B0" 
    successors "B5" 
    xhandlers
    flags 
    probability 4517291217531699200
    begin_IR
      LIR
      nr  128  <|@ instruction [] = LABEL alignment: 0 numbPhis: 0 label: ? <|@ <|@
      nr  130  <|@ instruction NOP <|@ <|@
      nr  132  <|@ instruction NOP <|@ <|@
      nr  134  <|@ instruction NOP <|@ <|@
      nr  136  <|@ instruction NOP <|@ <|@
      nr  138  <|@ instruction NOP <|@ <|@
      nr  140  <|@ instruction r10|QWORD[.] = HOTSPOTLOADOBJECTCONSTANT input: Object[String:"null"] <|@ <|@
      nr   -1  <|@ instruction rax|QWORD[.] = MOVE input: r10|QWORD[.] moveKind: QWORD // MoveResolver resolve mapping <|@ <|@
      nr  144  <|@ instruction JUMP ~outgoingValues: [] destination: B1 -> B5 <|@ <|@
    end_IR
  end_block
end_cfg
begin_bytecodes
     0: aload_0       
     1: ifnonnull     10
     4: ldc_w         #1000       // "null"
     7: goto          14
    10: aload_0       
    11: invokevirtual #281        // java.lang.Object.toString:()java.lang.String
    14: areturn       
   <|@
end_bytecodes
begin_cfg
  name "After LocationMarker"
  begin_block
    name "B0"
    from_bci -1
    to_bci -1
    predecessors 
    successors "B1" "B2" 
    xhandlers
    flags 
    probability 4607182418800017408
    begin_IR
      LIR
      nr    0  <|@ instruction [rsi|QWORD[.], rbp|QWORD] = LABEL alignment: 0 numbPhis: 0 label: ? <|@ <|@
      nr    2  <|@ instruction NOP <|@ <|@
      nr    4  <|@ instruction NOP <|@ <|@
      nr    6  <|@ instruction NOP <|@ <|@
      nr    8  <|@ instruction NOP <|@ <|@
      nr   10  <|@ instruction NOP <|@ <|@
      nr   12  <|@ instruction NOP <|@ <|@
      nr   14  <|@ instruction NOP <|@ <|@
      nr   16  <|@ instruction stack:16|QWORD = MOVE input: rbp|QWORD moveKind: QWORD <|@ <|@
      nr   18  <|@ instruction [] = HOTSPOTLOCKSTACK frameMapBuilder: jdk.graal.compiler.hotspot.amd64.AMD64HotSpotFrameMapBuilder@64144869 slotKind: QWORD <|@ <|@
      nr   22  <|@ instruction TESTBRANCH (x: rsi|QWORD[.], y: rsi|QWORD[.]) trueDestinationProbability: 9.91958358897982E-7 condition: = trueDestination: B0 -> B1 falseDestination: B0 -> B2 size: QWORD <|@ <|@
    end_IR
  end_block
  begin_block
    name "B2"
    from_bci -1
    to_bci -1
    predecessors "B0" 
    successors "B3" "B4" 
    xhandlers
    flags 
    probability 4607182409865250817
    begin_IR
      LIR
      nr   24  <|@ instruction [] = LABEL alignment: 0 numbPhis: 0 label: ? <|@ <|@
      nr   26  <|@ instruction NOP <|@ <|@
      nr   28  <|@ instruction NOP <|@ <|@
      nr   30  <|@ instruction NOP <|@ <|@
      nr   32  <|@ instruction NOP <|@ <|@
      nr   34  <|@ instruction NOP <|@ <|@
      nr   36  <|@ instruction NOP <|@ <|@
      nr   38  <|@ instruction NOP <|@ <|@
      nr   40  <|@ instruction NOP <|@ <|@
      nr   42  <|@ instruction NOP <|@ <|@
      nr   44  <|@ instruction rbx|DWORD = MOV input: [rsi|QWORD[.] + 8] size: DWORD <|@ <|@
      nr   46  <|@ instruction rax|QWORD = MOVE input: long[140154094223360|0x7f782b000000] <|@ <|@
      nr   48  <|@ instruction rbx|QWORD = UNCOMPRESSPOINTER (input: rbx|DWORD, ~baseRegister: rax|QWORD) nonNull: true lirKindTool: jdk.graal.compiler.hotspot.amd64.AMD64HotSpotLIRKindTool@d0246bd encoding: base: 140154094223360 shift: 0 <|@ <|@
      nr   50  <|@ instruction rax|QWORD = HOTSPOTLOADMETASPACECONSTANT input: meta{HotSpotType<Ljava/lang/String;, resolved>} <|@ <|@
      nr   52  <|@ instruction CMPBRANCH (x: rax|QWORD, y: rbx|QWORD) trueDestinationProbability: 0.43400564574488104 condition: = trueDestination: B2 -> B3 falseDestination: B2 -> B4 size: QWORD <|@ <|@
    end_IR
  end_block
  begin_block
    name "B4"
    from_bci -1
    to_bci -1
    predecessors "B2" 
    successors "B5" 
    xhandlers
    flags 
    probability 4603273238414083286
    begin_IR
      LIR
      nr   54  <|@ instruction [] = LABEL alignment: 0 numbPhis: 0 label: ? <|@ <|@
      nr   56  <|@ instruction NOP <|@ <|@
      nr   58  <|@ instruction NOP <|@ <|@
      nr   60  <|@ instruction NOP <|@ <|@
      nr   62  <|@ instruction NOP <|@ <|@
      nr   64  <|@ instruction NOP <|@ <|@
      nr   66  <|@ instruction NOP <|@ <|@
      nr   68  <|@ instruction NOP <|@ <|@
      nr   70  <|@ instruction NOP <|@ <|@
      nr   72  <|@ instruction NOP <|@ <|@
      nr   74  <|@ instruction NOP <|@ <|@
      nr   76  <|@ instruction NOP <|@ <|@
      nr   78  <|@ instruction NOP <|@ <|@
      nr   80  <|@ instruction rbx|QWORD = MOV input: [rbx|QWORD + 472] size: QWORD <|@ <|@
      nr   82  <|@ instruction rax|QWORD = MOV input: [rbx|QWORD + 64] size: QWORD <|@ <|@
      nr   90  <|@ st <@st|@reference-map: []
live-base-pointers: []
java.lang.String.valueOf(String.java:4465) [bci: 11]
locals: - 
>@ <|@ instruction rax|QWORD[.] = CALL_INDIRECT (targetAddress: rax|QWORD, metaspaceMethod: rbx|QWORD, parameters: [rsi|QWORD[.]]) temps: [] callTarget: HotSpotMethod<Object.toString()> state [bci:11] <|@ <|@
      nr   94  <|@ instruction JUMP ~outgoingValues: [] destination: B4 -> B5 <|@ <|@
    end_IR
  end_block
  begin_block
    name "B5"
    from_bci -1
    to_bci -1
    predecessors "B1" "B3" "B4" 
    successors 
    xhandlers
    flags 
    probability 4607182418800017408
    begin_IR
      LIR
      nr  106  <|@ instruction [] = LABEL alignment: 0 numbPhis: 1 label: ? <|@ <|@
      nr  108  <|@ instruction NOP <|@ <|@
      nr  110  <|@ instruction NOP <|@ <|@
      nr  112  <|@ instruction NOP <|@ <|@
      nr  114  <|@ instruction NOP <|@ <|@
      nr  116  <|@ instruction NOP <|@ <|@
      nr  118  <|@ instruction NOP <|@ <|@
      nr  120  <|@ instruction NOP <|@ <|@
      nr  122  <|@ instruction NOP <|@ <|@
      nr  126  <|@ instruction RETURN (savedRbp: stack:16|QWORD, value: rax|QWORD[.]) isStub: false requiresReservedStackAccessCheck: false thread: r15 scratchForSafepointOnReturn: rcx config: jdk.graal.compiler.hotspot.GraalHotSpotVMConfig@4817c460 <|@ <|@
    end_IR
  end_block
  begin_block
    name "B3"
    from_bci -1
    to_bci -1
    predecessors "B2" 
    successors "B5" 
    xhandlers
    flags 
    probability 4601489962820240983
    begin_IR
      LIR
      nr   96  <|@ instruction [] = LABEL alignment: 0 numbPhis: 0 label: ? <|@ <|@
      nr   98  <|@ instruction NOP <|@ <|@
      nr  100  <|@ instruction NOP <|@ <|@
      nr  102  <|@ instruction NOP <|@ <|@
      nr   -1  <|@ instruction rax|QWORD[.] = MOVE input: rsi|QWORD[.] moveKind: QWORD // MoveResolver resolve mapping <|@ <|@
      nr  104  <|@ instruction JUMP ~outgoingValues: [] destination: B3 -> B5 <|@ <|@
    end_IR
  end_block
  begin_block
    name "B1"
    from_bci -1
    to_bci -1
    predecessors "B0" 
    successors "B5" 
    xhandlers
    flags 
    probability 4517291217531699200
    begin_IR
      LIR
      nr  128  <|@ instruction [] = LABEL alignment: 0 numbPhis: 0 label: ? <|@ <|@
      nr  130  <|@ instruction NOP <|@ <|@
      nr  132  <|@ instruction NOP <|@ <|@
      nr  134  <|@ instruction NOP <|@ <|@
      nr  136  <|@ instruction NOP <|@ <|@
      nr  138  <|@ instruction NOP <|@ <|@
      nr  140  <|@ instruction r10|QWORD[.] = HOTSPOTLOADOBJECTCONSTANT input: Object[String:"null"] <|@ <|@
      nr   -1  <|@ instruction rax|QWORD[.] = MOVE input: r10|QWORD[.] moveKind: QWORD // MoveResolver resolve mapping <|@ <|@
      nr  144  <|@ instruction JUMP ~outgoingValues: [] destination: B1 -> B5 <|@ <|@
    end_IR
  end_block
end_cfg
begin_bytecodes
     0: aload_0       
     1: ifnonnull     10
     4: ldc_w         #1000       // "null"
     7: goto          14
    10: aload_0       
    11: invokevirtual #281        // java.lang.Object.toString:()java.lang.String
    14: areturn       
   <|@
end_bytecodes
begin_cfg
  name "After FinalCodeAnalysisStage"
  begin_block
    name "B0"
    from_bci -1
    to_bci -1
    predecessors 
    successors "B1" "B2" 
    xhandlers
    flags 
    probability 4607182418800017408
    begin_IR
      LIR
      nr    0  <|@ instruction [rsi|QWORD[.], rbp|QWORD] = LABEL alignment: 0 numbPhis: 0 label: ? <|@ <|@
      nr    2  <|@ instruction NOP <|@ <|@
      nr    4  <|@ instruction NOP <|@ <|@
      nr    6  <|@ instruction NOP <|@ <|@
      nr    8  <|@ instruction NOP <|@ <|@
      nr   10  <|@ instruction NOP <|@ <|@
      nr   12  <|@ instruction NOP <|@ <|@
      nr   14  <|@ instruction NOP <|@ <|@
      nr   16  <|@ instruction stack:16|QWORD = MOVE input: rbp|QWORD moveKind: QWORD <|@ <|@
      nr   18  <|@ instruction [] = HOTSPOTLOCKSTACK frameMapBuilder: jdk.graal.compiler.hotspot.amd64.AMD64HotSpotFrameMapBuilder@64144869 slotKind: QWORD <|@ <|@
      nr   22  <|@ instruction TESTBRANCH (x: rsi|QWORD[.], y: rsi|QWORD[.]) trueDestinationProbability: 9.91958358897982E-7 condition: = trueDestination: B0 -> B1 falseDestination: B0 -> B2 size: QWORD <|@ <|@
    end_IR
  end_block
  begin_block
    name "B2"
    from_bci -1
    to_bci -1
    predecessors "B0" 
    successors "B3" "B4" 
    xhandlers
    flags 
    probability 4607182409865250817
    begin_IR
      LIR
      nr   24  <|@ instruction [] = LABEL alignment: 0 numbPhis: 0 label: ? <|@ <|@
      nr   26  <|@ instruction NOP <|@ <|@
      nr   28  <|@ instruction NOP <|@ <|@
      nr   30  <|@ instruction NOP <|@ <|@
      nr   32  <|@ instruction NOP <|@ <|@
      nr   34  <|@ instruction NOP <|@ <|@
      nr   36  <|@ instruction NOP <|@ <|@
      nr   38  <|@ instruction NOP <|@ <|@
      nr   40  <|@ instruction NOP <|@ <|@
      nr   42  <|@ instruction NOP <|@ <|@
      nr   44  <|@ instruction rbx|DWORD = MOV input: [rsi|QWORD[.] + 8] size: DWORD <|@ <|@
      nr   46  <|@ instruction rax|QWORD = MOVE input: long[140154094223360|0x7f782b000000] <|@ <|@
      nr   48  <|@ instruction rbx|QWORD = UNCOMPRESSPOINTER (input: rbx|DWORD, ~baseRegister: rax|QWORD) nonNull: true lirKindTool: jdk.graal.compiler.hotspot.amd64.AMD64HotSpotLIRKindTool@d0246bd encoding: base: 140154094223360 shift: 0 <|@ <|@
      nr   50  <|@ instruction rax|QWORD = HOTSPOTLOADMETASPACECONSTANT input: meta{HotSpotType<Ljava/lang/String;, resolved>} <|@ <|@
      nr   52  <|@ instruction CMPBRANCH (x: rax|QWORD, y: rbx|QWORD) trueDestinationProbability: 0.43400564574488104 condition: = trueDestination: B2 -> B3 falseDestination: B2 -> B4 size: QWORD <|@ <|@
    end_IR
  end_block
  begin_block
    name "B4"
    from_bci -1
    to_bci -1
    predecessors "B2" 
    successors "B5" 
    xhandlers
    flags 
    probability 4603273238414083286
    begin_IR
      LIR
      nr   54  <|@ instruction [] = LABEL alignment: 0 numbPhis: 0 label: ? <|@ <|@
      nr   56  <|@ instruction NOP <|@ <|@
      nr   58  <|@ instruction NOP <|@ <|@
      nr   60  <|@ instruction NOP <|@ <|@
      nr   62  <|@ instruction NOP <|@ <|@
      nr   64  <|@ instruction NOP <|@ <|@
      nr   66  <|@ instruction NOP <|@ <|@
      nr   68  <|@ instruction NOP <|@ <|@
      nr   70  <|@ instruction NOP <|@ <|@
      nr   72  <|@ instruction NOP <|@ <|@
      nr   74  <|@ instruction NOP <|@ <|@
      nr   76  <|@ instruction NOP <|@ <|@
      nr   78  <|@ instruction NOP <|@ <|@
      nr   80  <|@ instruction rbx|QWORD = MOV input: [rbx|QWORD + 472] size: QWORD <|@ <|@
      nr   82  <|@ instruction rax|QWORD = MOV input: [rbx|QWORD + 64] size: QWORD <|@ <|@
      nr   90  <|@ st <@st|@reference-map: []
live-base-pointers: []
java.lang.String.valueOf(String.java:4465) [bci: 11]
locals: - 
>@ <|@ instruction rax|QWORD[.] = CALL_INDIRECT (targetAddress: rax|QWORD, metaspaceMethod: rbx|QWORD, parameters: [rsi|QWORD[.]]) temps: [] callTarget: HotSpotMethod<Object.toString()> state [bci:11] <|@ <|@
      nr   94  <|@ instruction JUMP ~outgoingValues: [] destination: B4 -> B5 <|@ <|@
    end_IR
  end_block
  begin_block
    name "B5"
    from_bci -1
    to_bci -1
    predecessors "B1" "B3" "B4" 
    successors 
    xhandlers
    flags 
    probability 4607182418800017408
    begin_IR
      LIR
      nr  106  <|@ instruction [] = LABEL alignment: 0 numbPhis: 1 label: ? <|@ <|@
      nr  108  <|@ instruction NOP <|@ <|@
      nr  110  <|@ instruction NOP <|@ <|@
      nr  112  <|@ instruction NOP <|@ <|@
      nr  114  <|@ instruction NOP <|@ <|@
      nr  116  <|@ instruction NOP <|@ <|@
      nr  118  <|@ instruction NOP <|@ <|@
      nr  120  <|@ instruction NOP <|@ <|@
      nr  122  <|@ instruction NOP <|@ <|@
      nr  126  <|@ instruction RETURN (savedRbp: stack:16|QWORD, value: rax|QWORD[.]) isStub: false requiresReservedStackAccessCheck: false thread: r15 scratchForSafepointOnReturn: rcx config: jdk.graal.compiler.hotspot.GraalHotSpotVMConfig@4817c460 <|@ <|@
    end_IR
  end_block
  begin_block
    name "B3"
    from_bci -1
    to_bci -1
    predecessors "B2" 
    successors "B5" 
    xhandlers
    flags 
    probability 4601489962820240983
    begin_IR
      LIR
      nr   96  <|@ instruction [] = LABEL alignment: 0 numbPhis: 0 label: ? <|@ <|@
      nr   98  <|@ instruction NOP <|@ <|@
      nr  100  <|@ instruction NOP <|@ <|@
      nr  102  <|@ instruction NOP <|@ <|@
      nr   -1  <|@ instruction rax|QWORD[.] = MOVE input: rsi|QWORD[.] moveKind: QWORD // MoveResolver resolve mapping <|@ <|@
      nr  104  <|@ instruction JUMP ~outgoingValues: [] destination: B3 -> B5 <|@ <|@
    end_IR
  end_block
  begin_block
    name "B1"
    from_bci -1
    to_bci -1
    predecessors "B0" 
    successors "B5" 
    xhandlers
    flags 
    probability 4517291217531699200
    begin_IR
      LIR
      nr  128  <|@ instruction [] = LABEL alignment: 0 numbPhis: 0 label: ? <|@ <|@
      nr  130  <|@ instruction NOP <|@ <|@
      nr  132  <|@ instruction NOP <|@ <|@
      nr  134  <|@ instruction NOP <|@ <|@
      nr  136  <|@ instruction NOP <|@ <|@
      nr  138  <|@ instruction NOP <|@ <|@
      nr  140  <|@ instruction r10|QWORD[.] = HOTSPOTLOADOBJECTCONSTANT input: Object[String:"null"] <|@ <|@
      nr   -1  <|@ instruction rax|QWORD[.] = MOVE input: r10|QWORD[.] moveKind: QWORD // MoveResolver resolve mapping <|@ <|@
      nr  144  <|@ instruction JUMP ~outgoingValues: [] destination: B1 -> B5 <|@ <|@
    end_IR
  end_block
end_cfg
begin_bytecodes
     0: aload_0       
     1: ifnonnull     10
     4: ldc_w         #1000       // "null"
     7: goto          14
    10: aload_0       
    11: invokevirtual #281        // java.lang.Object.toString:()java.lang.String
    14: areturn       
   <|@
end_bytecodes
begin_cfg
  name "After code generation"
end_cfg
begin_nmethod
  <<<HexCodeFile
  Platform AMD64 64  <||@
  HexCode 0 89842400c0feff4883ec189041817f20000000000f859e0000009090909090909048896c24104885f60f84750000009090909090909090908b5e0848b80000002b787f0000488d1c1848b8addeaddeaddeadde483bc30f8440000000909090909090909090909090488b9bd8010000488b4340ffd00f1f8400000000009090909090909090488b6c24104883c418493ba7500400000f872d000000c3909090488bc6ebd9909090909049baaddeaddeaddeadde498bc2ebc548896c2410e800000000e953fffffff4488d0dbfffffff49898f68040000e925fffffff4e800000000f4e800000000f4  <||@
  Comment 0 [stack overflow check]  <||@
  Comment 0 VERIFIED_ENTRY  <||@
  Comment 12 FRAME_COMPLETE  <||@
  Comment 12 ENTRY_BARRIER_PATCH  <||@
  Comment 26 block B0 null  <||@
  Comment 26 0 [rsi|QWORD[.], rbp|QWORD] = LABEL alignment: 0 numbPhis: 0 label: ?  <||@
  Comment 26 2 NOP  <||@
  Comment 27 4 NOP  <||@
  Comment 28 6 NOP  <||@
  Comment 29 8 NOP  <||@
  Comment 30 10 NOP  <||@
  Comment 31 12 NOP  <||@
  Comment 32 14 NOP  <||@
  Comment 33 16 stack:16|QWORD = MOVE input: rbp|QWORD moveKind: QWORD  <||@
  Comment 38 18 [] = HOTSPOTLOCKSTACK frameMapBuilder: jdk.graal.compiler.hotspot.amd64.AMD64HotSpotFrameMapBuilder@64144869 slotKind: QWORD  <||@
  Comment 38 22 TESTBRANCH (x: rsi|QWORD[.], y: rsi|QWORD[.]) trueDestinationProbability: 9.91958358897982E-7 condition: = trueDestination: B0 -> B1 falseDestination: B0 -> B2 size: QWORD  <||@
  Comment 47 block B2 null  <||@
  Comment 47 24 [] = LABEL alignment: 0 numbPhis: 0 label: ?  <||@
  Comment 47 26 NOP  <||@
  Comment 48 28 NOP  <||@
  Comment 49 30 NOP  <||@
  Comment 50 32 NOP  <||@
  Comment 51 34 NOP  <||@
  Comment 52 36 NOP  <||@
  Comment 53 38 NOP  <||@
  Comment 54 40 NOP  <||@
  Comment 55 42 NOP  <||@
  Comment 56 44 rbx|DWORD = MOV input: [rsi|QWORD[.] + 8] size: DWORD  <||@
  Comment 59 46 rax|QWORD = MOVE input: long[140154094223360|0x7f782b000000]  <||@
  Comment 69 48 rbx|QWORD = UNCOMPRESSPOINTER (input: rbx|DWORD, ~baseRegister: rax|QWORD) nonNull: true lirKindTool: jdk.graal.compiler.hotspot.amd64.AMD64HotSpotLIRKindTool@d0246bd encoding: base: 140154094223360 shift: 0  <||@
  Comment 73 50 rax|QWORD = HOTSPOTLOADMETASPACECONSTANT input: meta{HotSpotType<Ljava/lang/String;, resolved>}  <||@
  Comment 73 {meta{HotSpotType<Ljava/lang/String;, resolved>}}  <||@
  Comment 83 52 CMPBRANCH (x: rax|QWORD, y: rbx|QWORD) trueDestinationProbability: 0.43400564574488104 condition: = trueDestination: B2 -> B3 falseDestination: B2 -> B4 size: QWORD  <||@
  Comment 92 block B4 null  <||@
  Comment 92 54 [] = LABEL alignment: 0 numbPhis: 0 label: ?  <||@
  Comment 92 56 NOP  <||@
  Comment 93 58 NOP  <||@
  Comment 94 60 NOP  <||@
  Comment 95 62 NOP  <||@
  Comment 96 64 NOP  <||@
  Comment 97 66 NOP  <||@
  Comment 98 68 NOP  <||@
  Comment 99 70 NOP  <||@
  Comment 100 72 NOP  <||@
  Comment 101 74 NOP  <||@
  Comment 102 76 NOP  <||@
  Comment 103 78 NOP  <||@
  Comment 104 80 rbx|QWORD = MOV input: [rbx|QWORD + 472] size: QWORD  <||@
  Comment 111 82 rax|QWORD = MOV input: [rbx|QWORD + 64] size: QWORD  <||@
  Comment 115 90 rax|QWORD[.] = CALL_INDIRECT (targetAddress: rax|QWORD, metaspaceMethod: rbx|QWORD, parameters: [rsi|QWORD[.]]) temps: [] callTarget: HotSpotMethod<Object.toString()> state [bci:11]  <||@
  Comment 115 {HotSpotMethod<Object.toString()>}  <||@
  Comment 115 INLINE_INVOKE  <||@
  Comment 117 []at java.lang.String.valueOf(String.java:4465) [bci: 11, duringCall: true, rethrow: false]
              |0 
     locals:  |-   <||@
  Comment 125 94 JUMP ~outgoingValues: [] destination: B4 -> B5  <||@
  Comment 125 block B5 null  <||@
  Comment 125 106 [] = LABEL alignment: 0 numbPhis: 1 label: ?  <||@
  Comment 125 108 NOP  <||@
  Comment 126 110 NOP  <||@
  Comment 127 112 NOP  <||@
  Comment 128 114 NOP  <||@
  Comment 129 116 NOP  <||@
  Comment 130 118 NOP  <||@
  Comment 131 120 NOP  <||@
  Comment 132 122 NOP  <||@
  Comment 133 126 RETURN (savedRbp: stack:16|QWORD, value: rax|QWORD[.]) isStub: false requiresReservedStackAccessCheck: false thread: r15 scratchForSafepointOnReturn: rcx config: jdk.graal.compiler.hotspot.GraalHotSpotVMConfig@4817c460  <||@
  Comment 142 POLL_RETURN_FAR  <||@
  Comment 156 block B3 null  <||@
  Comment 156 96 [] = LABEL alignment: 0 numbPhis: 0 label: ?  <||@
  Comment 156 98 NOP  <||@
  Comment 157 100 NOP  <||@
  Comment 158 102 NOP  <||@
  Comment 159 -1 rax|QWORD[.] = MOVE input: rsi|QWORD[.] moveKind: QWORD  <||@
  Comment 162 104 JUMP ~outgoingValues: [] destination: B3 -> B5  <||@
  Comment 164 block B1 null  <||@
  Comment 164 128 [] = LABEL alignment: 0 numbPhis: 0 label: ?  <||@
  Comment 164 130 NOP  <||@
  Comment 165 132 NOP  <||@
  Comment 166 134 NOP  <||@
  Comment 167 136 NOP  <||@
  Comment 168 138 NOP  <||@
  Comment 169 140 r10|QWORD[.] = HOTSPOTLOADOBJECTCONSTANT input: Object[String:"null"]  <||@
  Comment 169 {Object[String:"null"]}  <||@
  Comment 179 -1 rax|QWORD[.] = MOVE input: r10|QWORD[.] moveKind: QWORD  <||@
  Comment 182 144 JUMP ~outgoingValues: [] destination: B1 -> B5  <||@
  Comment 189 {Field[name=CompilerToVM::Data::nmethod_entry_barrier, type=address, offset=0, address=0x7f78b2033598, value=140155947495968]:0x7f789976b220}  <||@
  Comment 214 {Field[name=CompilerToVM::Data::SharedRuntime_polling_page_return_handler, type=address, offset=0, address=0x7f78b20335a0, value=140155947630592]:0x7f789978c000}  <||@
  Comment 220 {Stub<ExceptionHandlerStub.exceptionHandler>@0x7f78998c5300:CallingConvention[rax|QWORD[.], rdx|QWORD]:CallingConvention[rax|QWORD[.], rdx|QWORD]; temps=rdi|ILLEGAL,xmm14|ILLEGAL,xmm15|ILLEGAL,xmm12|ILLEGAL,xmm13|ILLEGAL,xmm10|ILLEGAL,xmm11|ILLEGAL,xmm7|ILLEGAL,xmm8|ILLEGAL,xmm9|ILLEGAL,xmm0|ILLEGAL,xmm1|ILLEGAL,xmm2|ILLEGAL,xmm3|ILLEGAL,xmm4|ILLEGAL,xmm5|ILLEGAL,xmm6|ILLEGAL,rax|ILLEGAL,rcx|ILLEGAL,rdx|ILLEGAL,rsi|ILLEGAL,r8|ILLEGAL,r9|ILLEGAL,r10|ILLEGAL,r11|ILLEGAL}  <||@
  Comment 220 EXCEPTION_HANDLER_ENTRY  <||@
  Comment 226 {Field[name=CompilerToVM::Data::SharedRuntime_deopt_blob_unpack, type=address, offset=0, address=0x7f78b20335b8, value=140155947626272]:0x7f789978af20}  <||@
  Comment 226 DEOPT_HANDLER_ENTRY  <||@
  HexCodeFile>>> <|@
end_nmethod
begin_compilation
  name " HotSpotCompilation-7250[java.lang.String.valueOf(Object)]"
  method "HotSpotCompilation-7250[java.lang.String.valueOf(Object)]"
  date 1724269739286
end_compilation
begin_cfg
  name "After code installation"
end_cfg
begin_nmethod
  <<<HexCodeFile
  Platform AMD64 64  <||@
  HexCode 7f789ae08300 89842400c0feff4883ec189041817f20000000000f859e0000009090909090909048896c24104885f60f84750000009090909090909090908b5e0848b80000002b787f0000488d1c1848b8d8e8002b787f0000483bc30f8440000000909090909090909090909090488b9bd8010000488b4340ffd00f1f8400000000009090909090909090488b6c24104883c418493ba7500400000f872d000000c3909090488bc6ebd9909090909049ba10b9c4ff07000000498bc2ebc548896c2410e85e2e96fee953fffffff4488d0dbfffffff49898f68040000e9253c98fef4e81fcfabfef4e8392b98fef4  <||@
  Comment 0 [stack overflow check]  <||@
  Comment 0 VERIFIED_ENTRY  <||@
  Comment 12 FRAME_COMPLETE  <||@
  Comment 12 ENTRY_BARRIER_PATCH  <||@
  Comment 26 block B0 null  <||@
  Comment 26 0 [rsi|QWORD[.], rbp|QWORD] = LABEL alignment: 0 numbPhis: 0 label: ?  <||@
  Comment 26 2 NOP  <||@
  Comment 27 4 NOP  <||@
  Comment 28 6 NOP  <||@
  Comment 29 8 NOP  <||@
  Comment 30 10 NOP  <||@
  Comment 31 12 NOP  <||@
  Comment 32 14 NOP  <||@
  Comment 33 16 stack:16|QWORD = MOVE input: rbp|QWORD moveKind: QWORD  <||@
  Comment 38 18 [] = HOTSPOTLOCKSTACK frameMapBuilder: jdk.graal.compiler.hotspot.amd64.AMD64HotSpotFrameMapBuilder@64144869 slotKind: QWORD  <||@
  Comment 38 22 TESTBRANCH (x: rsi|QWORD[.], y: rsi|QWORD[.]) trueDestinationProbability: 9.91958358897982E-7 condition: = trueDestination: B0 -> B1 falseDestination: B0 -> B2 size: QWORD  <||@
  Comment 47 block B2 null  <||@
  Comment 47 24 [] = LABEL alignment: 0 numbPhis: 0 label: ?  <||@
  Comment 47 26 NOP  <||@
  Comment 48 28 NOP  <||@
  Comment 49 30 NOP  <||@
  Comment 50 32 NOP  <||@
  Comment 51 34 NOP  <||@
  Comment 52 36 NOP  <||@
  Comment 53 38 NOP  <||@
  Comment 54 40 NOP  <||@
  Comment 55 42 NOP  <||@
  Comment 56 44 rbx|DWORD = MOV input: [rsi|QWORD[.] + 8] size: DWORD  <||@
  Comment 59 46 rax|QWORD = MOVE input: long[140154094223360|0x7f782b000000]  <||@
  Comment 69 48 rbx|QWORD = UNCOMPRESSPOINTER (input: rbx|DWORD, ~baseRegister: rax|QWORD) nonNull: true lirKindTool: jdk.graal.compiler.hotspot.amd64.AMD64HotSpotLIRKindTool@d0246bd encoding: base: 140154094223360 shift: 0  <||@
  Comment 73 50 rax|QWORD = HOTSPOTLOADMETASPACECONSTANT input: meta{HotSpotType<Ljava/lang/String;, resolved>}  <||@
  Comment 73 {meta{HotSpotType<Ljava/lang/String;, resolved>}}  <||@
  Comment 83 52 CMPBRANCH (x: rax|QWORD, y: rbx|QWORD) trueDestinationProbability: 0.43400564574488104 condition: = trueDestination: B2 -> B3 falseDestination: B2 -> B4 size: QWORD  <||@
  Comment 92 block B4 null  <||@
  Comment 92 54 [] = LABEL alignment: 0 numbPhis: 0 label: ?  <||@
  Comment 92 56 NOP  <||@
  Comment 93 58 NOP  <||@
  Comment 94 60 NOP  <||@
  Comment 95 62 NOP  <||@
  Comment 96 64 NOP  <||@
  Comment 97 66 NOP  <||@
  Comment 98 68 NOP  <||@
  Comment 99 70 NOP  <||@
  Comment 100 72 NOP  <||@
  Comment 101 74 NOP  <||@
  Comment 102 76 NOP  <||@
  Comment 103 78 NOP  <||@
  Comment 104 80 rbx|QWORD = MOV input: [rbx|QWORD + 472] size: QWORD  <||@
  Comment 111 82 rax|QWORD = MOV input: [rbx|QWORD + 64] size: QWORD  <||@
  Comment 115 90 rax|QWORD[.] = CALL_INDIRECT (targetAddress: rax|QWORD, metaspaceMethod: rbx|QWORD, parameters: [rsi|QWORD[.]]) temps: [] callTarget: HotSpotMethod<Object.toString()> state [bci:11]  <||@
  Comment 115 {HotSpotMethod<Object.toString()>}  <||@
  Comment 115 INLINE_INVOKE  <||@
  Comment 117 []at java.lang.String.valueOf(String.java:4465) [bci: 11, duringCall: true, rethrow: false]
              |0 
     locals:  |-   <||@
  Comment 125 94 JUMP ~outgoingValues: [] destination: B4 -> B5  <||@
  Comment 125 block B5 null  <||@
  Comment 125 106 [] = LABEL alignment: 0 numbPhis: 1 label: ?  <||@
  Comment 125 108 NOP  <||@
  Comment 126 110 NOP  <||@
  Comment 127 112 NOP  <||@
  Comment 128 114 NOP  <||@
  Comment 129 116 NOP  <||@
  Comment 130 118 NOP  <||@
  Comment 131 120 NOP  <||@
  Comment 132 122 NOP  <||@
  Comment 133 126 RETURN (savedRbp: stack:16|QWORD, value: rax|QWORD[.]) isStub: false requiresReservedStackAccessCheck: false thread: r15 scratchForSafepointOnReturn: rcx config: jdk.graal.compiler.hotspot.GraalHotSpotVMConfig@4817c460  <||@
  Comment 142 POLL_RETURN_FAR  <||@
  Comment 156 block B3 null  <||@
  Comment 156 96 [] = LABEL alignment: 0 numbPhis: 0 label: ?  <||@
  Comment 156 98 NOP  <||@
  Comment 157 100 NOP  <||@
  Comment 158 102 NOP  <||@
  Comment 159 -1 rax|QWORD[.] = MOVE input: rsi|QWORD[.] moveKind: QWORD  <||@
  Comment 162 104 JUMP ~outgoingValues: [] destination: B3 -> B5  <||@
  Comment 164 block B1 null  <||@
  Comment 164 128 [] = LABEL alignment: 0 numbPhis: 0 label: ?  <||@
  Comment 164 130 NOP  <||@
  Comment 165 132 NOP  <||@
  Comment 166 134 NOP  <||@
  Comment 167 136 NOP  <||@
  Comment 168 138 NOP  <||@
  Comment 169 140 r10|QWORD[.] = HOTSPOTLOADOBJECTCONSTANT input: Object[String:"null"]  <||@
  Comment 169 {Object[String:"null"]}  <||@
  Comment 179 -1 rax|QWORD[.] = MOVE input: r10|QWORD[.] moveKind: QWORD  <||@
  Comment 182 144 JUMP ~outgoingValues: [] destination: B1 -> B5  <||@
  Comment 189 {Field[name=CompilerToVM::Data::nmethod_entry_barrier, type=address, offset=0, address=0x7f78b2033598, value=140155947495968]:0x7f789976b220}  <||@
  Comment 214 {Field[name=CompilerToVM::Data::SharedRuntime_polling_page_return_handler, type=address, offset=0, address=0x7f78b20335a0, value=140155947630592]:0x7f789978c000}  <||@
  Comment 220 {Stub<ExceptionHandlerStub.exceptionHandler>@0x7f78998c5300:CallingConvention[rax|QWORD[.], rdx|QWORD]:CallingConvention[rax|QWORD[.], rdx|QWORD]; temps=rdi|ILLEGAL,xmm14|ILLEGAL,xmm15|ILLEGAL,xmm12|ILLEGAL,xmm13|ILLEGAL,xmm10|ILLEGAL,xmm11|ILLEGAL,xmm7|ILLEGAL,xmm8|ILLEGAL,xmm9|ILLEGAL,xmm0|ILLEGAL,xmm1|ILLEGAL,xmm2|ILLEGAL,xmm3|ILLEGAL,xmm4|ILLEGAL,xmm5|ILLEGAL,xmm6|ILLEGAL,rax|ILLEGAL,rcx|ILLEGAL,rdx|ILLEGAL,rsi|ILLEGAL,r8|ILLEGAL,r9|ILLEGAL,r10|ILLEGAL,r11|ILLEGAL}  <||@
  Comment 220 EXCEPTION_HANDLER_ENTRY  <||@
  Comment 226 {Field[name=CompilerToVM::Data::SharedRuntime_deopt_blob_unpack, type=address, offset=0, address=0x7f78b20335b8, value=140155947626272]:0x7f789978af20}  <||@
  Comment 226 DEOPT_HANDLER_ENTRY  <||@
  HexCodeFile>>> <|@
end_nmethod
