begin_compilation
  name " HotSpotCompilation-11145[java.lang.Byte.toString()]"
  method "HotSpotCompilation-11145[java.lang.Byte.toString()]"
  date 1724269765446
end_compilation
begin_cfg
  name "Final HIR schedule"
  begin_block
    name "B0"
    from_bci -1
    to_bci -1
    predecessors 
    successors 
    xhandlers
    flags 
    probability 4607182418800017408
    begin_IR
      HIR
f <@#|@fixed with next>@ <|@
tid v0 <|@
d <@d|@=== Debug Properties ===
hasSpeculationFence: false
stamp: void
=== Inputs ===
stateAfter: - 
=== Succesors ===
next: i15 
=== Usages ===
=== Predecessor ===
- >@ <|@
instruction <@StartNode|@jdk.graal.compiler.nodes.StartNode>@ stateAfter: - #next: i15  <|@  <|@
f <@~|@floating>@ <|@
tid a1 <|@
d <@d|@=== Debug Properties ===
index: 0
stamp: a!# java.lang.Byte
uncheckedStamp: [null]
=== Inputs ===
=== Succesors ===
=== Usages ===
v16 
=== Predecessor ===
- >@ <|@
instruction <@Parameter|@jdk.graal.compiler.nodes.ParameterNode>@  <|@  <|@
f <@~|@floating>@ <|@
tid v16 <|@
d <@d|@=== Debug Properties ===
displacement: 12
stamp: void*
stride: S1
=== Inputs ===
base: a1 
index: - 
=== Succesors ===
=== Usages ===
i15 
=== Predecessor ===
- >@ <|@
instruction <@AMD64Address|@jdk.graal.compiler.core.amd64.AMD64AddressNode>@ base: a1 index: -  <|@  <|@
f <@#|@fixed with next>@ <|@
tid i15 <|@
d <@d|@=== Debug Properties ===
accessStamp: i8
barrierType: NONE
deoptReasonAndAction: [null]
deoptSpeculation: [null]
extendKind: DEFAULT zero? false sign? false extendSize 0
forceFixed: false
location: Byte.value
memoryOrder: PLAIN
nodeSourcePosition: at java.lang.Byte.toString(Byte.java:443) [bci: 1]
stamp: i8
usedAsNullCheck: false
=== Inputs ===
stateBefore: - 
guard: - 
address: v16 
lastLocationAccess: - 
=== Succesors ===
next: a5 
=== Usages ===
i11 
=== Predecessor ===
v0 >@ <|@
instruction <@Read|@jdk.graal.compiler.nodes.memory.ReadNode>@ stateBefore: - guard: - address: v16 lastLocationAccess: - #next: a5  <|@  <|@
f <@~|@floating>@ <|@
tid i11 <|@
d <@d|@=== Debug Properties ===
inputBits: 8
nodeSourcePosition: at java.lang.Byte.toString(Byte.java:443) [bci: 1]
resultBits: 32
stamp: i32 [-128 - 127]
=== Inputs ===
value: i15 
=== Succesors ===
=== Usages ===
v12 
=== Predecessor ===
- >@ <|@
instruction <@SignExtend|@jdk.graal.compiler.nodes.calc.SignExtendNode>@ value: i15  <|@  <|@
tid v12 <|@
d <@d|@=== Debug Properties ===
callType: JavaCall
invokeKind: Static
nodeSourcePosition: at java.lang.Byte.toString(Byte.java:443) [bci: 4]
referencedType: [null]
returnStamp: a# java.lang.String
signature: [HotSpotResolvedPrimitiveType<int>]
stamp: void
targetMethod: HotSpotMethod<Integer.toString(int)>
=== Inputs ===
arguments: i11 
=== Succesors ===
=== Usages ===
a5 
=== Predecessor ===
- >@ <|@
instruction <@HotSpotDirectCallTarget|@jdk.graal.compiler.hotspot.nodes.HotSpotDirectCallTargetNode>@ arguments: i11  <|@  <|@
tid ?14 <|@
d <@d|@=== Debug Properties ===
bci: 4
bytecode: invokestatic
code: ResolvedJavaMethodBytecode<Byte.toString()>
localsSize: 1
locksSize: 0
sourceFile: Byte.java
sourceLine: 443
stackSize: 0
stackState: AfterPop
validForDeoptimization: true
=== Inputs ===
outerFrameState: - 
=== Succesors ===
=== Usages ===
a5 
=== Predecessor ===
- >@ <|@
instruction <@FrameState|@jdk.graal.compiler.nodes.FrameState>@ outerFrameState: -  <|@  <|@
f <@#|@fixed with next>@ <|@
tid a5 <|@
d <@d|@=== Debug Properties ===
bci: 4
identity: ANY_LOCATION
inlineControl: Normal
isInOOMETry: false
nodeSourcePosition: at java.lang.Byte.toString(Byte.java:443) [bci: 4]
polymorphic: false
stamp: a# java.lang.String
targetMethod: Direct#Integer.toString
=== Inputs ===
stateAfter: - 
classInit: - 
callTarget: v12 
stateDuring: ?14 
=== Succesors ===
next: v7 
=== Usages ===
v7 
=== Predecessor ===
i15 >@ <|@
instruction <@Invoke|@jdk.graal.compiler.nodes.InvokeNode>@ stateAfter: - classInit: - callTarget: v12 stateDuring: ?14 #next: v7  <|@  <|@
f <@*|@fixed>@ <|@
tid v7 <|@
d <@d|@=== Debug Properties ===
nodeSourcePosition: at java.lang.Byte.toString(Byte.java:443) [bci: 7]
stamp: void
=== Inputs ===
memoryMap: - 
result: a5 
=== Succesors ===
=== Usages ===
=== Predecessor ===
a5 >@ <|@
instruction <@Return|@jdk.graal.compiler.nodes.ReturnNode>@ memoryMap: - result: a5  <|@  <|@
    end_IR
  end_block
end_cfg
begin_cfg
  name "After LIRGeneration"
  begin_block
    name "B0"
    from_bci -1
    to_bci -1
    predecessors 
    successors 
    xhandlers
    flags 
    probability 4607182418800017408
    begin_IR
      LIR
      nr   -1  <|@ instruction [rsi|QWORD[.], rbp|QWORD] = LABEL alignment: 0 numbPhis: 0 label: ? <|@ <|@
      nr   -1  <|@ instruction stack:16|QWORD = MOVE input: rbp|QWORD moveKind: QWORD <|@ <|@
      nr   -1  <|@ instruction [] = HOTSPOTLOCKSTACK frameMapBuilder: jdk.graal.compiler.hotspot.amd64.AMD64HotSpotFrameMapBuilder@20881f79 slotKind: QWORD <|@ <|@
      nr   -1  <|@ instruction v0|QWORD[.] = MOVE input: rsi|QWORD[.] moveKind: QWORD <|@ <|@
      nr   -1  <|@ instruction v1|DWORD = MOVSXB input: [v0|QWORD[.] + 12] size: DWORD <|@ <|@
      nr   -1  <|@ instruction rsi|DWORD = MOVE input: v1|DWORD moveKind: DWORD <|@ <|@
      nr   -1  <|@ st <@st|@java.lang.Byte.toString(Byte.java:443) [bci: 4]
locals: - 
>@ <|@ instruction rax|QWORD[.] = CALL_DIRECT parameters: [rsi|DWORD] temps: [] callTarget: HotSpotMethod<Integer.toString(int)> invokeKind: Static config: jdk.graal.compiler.hotspot.GraalHotSpotVMConfig@4817c460 state [bci:4] <|@ <|@
      nr   -1  <|@ instruction v2|QWORD[.] = MOVE input: rax|QWORD[.] moveKind: QWORD <|@ <|@
      nr   -1  <|@ instruction rax|QWORD[.] = MOVE input: v2|QWORD[.] moveKind: QWORD <|@ <|@
      nr   -1  <|@ instruction RETURN (savedRbp: stack:16|QWORD, value: rax|QWORD[.]) isStub: false requiresReservedStackAccessCheck: false thread: r15 scratchForSafepointOnReturn: rcx config: jdk.graal.compiler.hotspot.GraalHotSpotVMConfig@4817c460 <|@ <|@
    end_IR
  end_block
end_cfg
begin_bytecodes
     0: aload_0       
     1: getfield      #20         // value:byte
     4: invokestatic  #0          // java.lang.Integer.toString:(int)java.lang.String
     7: areturn       
   <|@
end_bytecodes
begin_cfg
  name "After LIR generation"
  begin_block
    name "B0"
    from_bci -1
    to_bci -1
    predecessors 
    successors 
    xhandlers
    flags 
    probability 4607182418800017408
    begin_IR
      HIR
f <@#|@fixed with next>@ <|@
tid v0 <|@
d <@d|@=== Debug Properties ===
hasSpeculationFence: false
stamp: void
=== Inputs ===
stateAfter: - 
=== Succesors ===
next: i15 
=== Usages ===
=== Predecessor ===
- >@ <|@
instruction <@StartNode|@jdk.graal.compiler.nodes.StartNode>@ stateAfter: - #next: i15  <|@  <|@
f <@~|@floating>@ <|@
tid a1 <|@
result v0|QWORD[.] <|@
d <@d|@=== Debug Properties ===
index: 0
stamp: a!# java.lang.Byte
uncheckedStamp: [null]
=== Inputs ===
=== Succesors ===
=== Usages ===
v16 
=== Predecessor ===
- >@ <|@
instruction <@Parameter|@jdk.graal.compiler.nodes.ParameterNode>@  <|@  <|@
f <@~|@floating>@ <|@
tid v16 <|@
result [v0|QWORD[.] + 12] <|@
d <@d|@=== Debug Properties ===
displacement: 12
stamp: void*
stride: S1
=== Inputs ===
base: a1 
index: - 
=== Succesors ===
=== Usages ===
i15 
=== Predecessor ===
- >@ <|@
instruction <@AMD64Address|@jdk.graal.compiler.core.amd64.AMD64AddressNode>@ base: a1 index: -  <|@  <|@
f <@#|@fixed with next>@ <|@
tid i15 <|@
d <@d|@=== Debug Properties ===
accessStamp: i8
barrierType: NONE
deoptReasonAndAction: [null]
deoptSpeculation: [null]
extendKind: DEFAULT zero? false sign? false extendSize 0
forceFixed: false
location: Byte.value
memoryOrder: PLAIN
nodeSourcePosition: at java.lang.Byte.toString(Byte.java:443) [bci: 1]
stamp: i8
usedAsNullCheck: false
=== Inputs ===
stateBefore: - 
guard: - 
address: v16 
lastLocationAccess: - 
=== Succesors ===
next: a5 
=== Usages ===
i11 
=== Predecessor ===
v0 >@ <|@
instruction <@Read|@jdk.graal.compiler.nodes.memory.ReadNode>@ stateBefore: - guard: - address: v16 lastLocationAccess: - #next: a5  <|@  <|@
f <@~|@floating>@ <|@
tid i11 <|@
result v1|DWORD <|@
d <@d|@=== Debug Properties ===
inputBits: 8
nodeSourcePosition: at java.lang.Byte.toString(Byte.java:443) [bci: 1]
resultBits: 32
stamp: i32 [-128 - 127]
=== Inputs ===
value: i15 
=== Succesors ===
=== Usages ===
v12 
=== Predecessor ===
- >@ <|@
instruction <@SignExtend|@jdk.graal.compiler.nodes.calc.SignExtendNode>@ value: i15  <|@  <|@
tid v12 <|@
d <@d|@=== Debug Properties ===
callType: JavaCall
invokeKind: Static
nodeSourcePosition: at java.lang.Byte.toString(Byte.java:443) [bci: 4]
referencedType: [null]
returnStamp: a# java.lang.String
signature: [HotSpotResolvedPrimitiveType<int>]
stamp: void
targetMethod: HotSpotMethod<Integer.toString(int)>
=== Inputs ===
arguments: i11 
=== Succesors ===
=== Usages ===
a5 
=== Predecessor ===
- >@ <|@
instruction <@HotSpotDirectCallTarget|@jdk.graal.compiler.hotspot.nodes.HotSpotDirectCallTargetNode>@ arguments: i11  <|@  <|@
tid ?14 <|@
d <@d|@=== Debug Properties ===
bci: 4
bytecode: invokestatic
code: ResolvedJavaMethodBytecode<Byte.toString()>
localsSize: 1
locksSize: 0
sourceFile: Byte.java
sourceLine: 443
stackSize: 0
stackState: AfterPop
validForDeoptimization: true
=== Inputs ===
outerFrameState: - 
=== Succesors ===
=== Usages ===
a5 
=== Predecessor ===
- >@ <|@
instruction <@FrameState|@jdk.graal.compiler.nodes.FrameState>@ outerFrameState: -  <|@  <|@
f <@#|@fixed with next>@ <|@
tid a5 <|@
result v2|QWORD[.] <|@
d <@d|@=== Debug Properties ===
bci: 4
identity: ANY_LOCATION
inlineControl: Normal
isInOOMETry: false
nodeSourcePosition: at java.lang.Byte.toString(Byte.java:443) [bci: 4]
polymorphic: false
stamp: a# java.lang.String
targetMethod: Direct#Integer.toString
=== Inputs ===
stateAfter: - 
classInit: - 
callTarget: v12 
stateDuring: ?14 
=== Succesors ===
next: v7 
=== Usages ===
v7 
=== Predecessor ===
i15 >@ <|@
instruction <@Invoke|@jdk.graal.compiler.nodes.InvokeNode>@ stateAfter: - classInit: - callTarget: v12 stateDuring: ?14 #next: v7  <|@  <|@
f <@*|@fixed>@ <|@
tid v7 <|@
d <@d|@=== Debug Properties ===
nodeSourcePosition: at java.lang.Byte.toString(Byte.java:443) [bci: 7]
stamp: void
=== Inputs ===
memoryMap: - 
result: a5 
=== Succesors ===
=== Usages ===
=== Predecessor ===
a5 >@ <|@
instruction <@Return|@jdk.graal.compiler.nodes.ReturnNode>@ memoryMap: - result: a5  <|@  <|@
    end_IR
    begin_IR
      LIR
      nr   -1  <|@ instruction [rsi|QWORD[.], rbp|QWORD] = LABEL alignment: 0 numbPhis: 0 label: ? <|@ <|@
      nr   -1  <|@ instruction stack:16|QWORD = MOVE input: rbp|QWORD moveKind: QWORD <|@ <|@
      nr   -1  <|@ instruction [] = HOTSPOTLOCKSTACK frameMapBuilder: jdk.graal.compiler.hotspot.amd64.AMD64HotSpotFrameMapBuilder@20881f79 slotKind: QWORD <|@ <|@
      nr   -1  <|@ instruction v0|QWORD[.] = MOVE input: rsi|QWORD[.] moveKind: QWORD <|@ <|@
      nr   -1  <|@ instruction v1|DWORD = MOVSXB input: [v0|QWORD[.] + 12] size: DWORD <|@ <|@
      nr   -1  <|@ instruction rsi|DWORD = MOVE input: v1|DWORD moveKind: DWORD <|@ <|@
      nr   -1  <|@ st <@st|@java.lang.Byte.toString(Byte.java:443) [bci: 4]
locals: - 
>@ <|@ instruction rax|QWORD[.] = CALL_DIRECT parameters: [rsi|DWORD] temps: [] callTarget: HotSpotMethod<Integer.toString(int)> invokeKind: Static config: jdk.graal.compiler.hotspot.GraalHotSpotVMConfig@4817c460 state [bci:4] <|@ <|@
      nr   -1  <|@ instruction v2|QWORD[.] = MOVE input: rax|QWORD[.] moveKind: QWORD <|@ <|@
      nr   -1  <|@ instruction rax|QWORD[.] = MOVE input: v2|QWORD[.] moveKind: QWORD <|@ <|@
      nr   -1  <|@ instruction RETURN (savedRbp: stack:16|QWORD, value: rax|QWORD[.]) isStub: false requiresReservedStackAccessCheck: false thread: r15 scratchForSafepointOnReturn: rcx config: jdk.graal.compiler.hotspot.GraalHotSpotVMConfig@4817c460 <|@ <|@
    end_IR
  end_block
end_cfg
begin_cfg
  name "After LIRGTSlowdown"
  begin_block
    name "B0"
    from_bci -1
    to_bci -1
    predecessors 
    successors 
    xhandlers
    flags 
    probability 4607182418800017408
    begin_IR
      LIR
      nr   -1  <|@ instruction [rsi|QWORD[.], rbp|QWORD] = LABEL alignment: 0 numbPhis: 0 label: ? <|@ <|@
      nr   -1  <|@ instruction NOP <|@ <|@
      nr   -1  <|@ instruction NOP <|@ <|@
      nr   -1  <|@ instruction NOP <|@ <|@
      nr   -1  <|@ instruction NOP <|@ <|@
      nr   -1  <|@ instruction NOP <|@ <|@
      nr   -1  <|@ instruction NOP <|@ <|@
      nr   -1  <|@ instruction NOP <|@ <|@
      nr   -1  <|@ instruction NOP <|@ <|@
      nr   -1  <|@ instruction NOP <|@ <|@
      nr   -1  <|@ instruction NOP <|@ <|@
      nr   -1  <|@ instruction NOP <|@ <|@
      nr   -1  <|@ instruction NOP <|@ <|@
      nr   -1  <|@ instruction NOP <|@ <|@
      nr   -1  <|@ instruction NOP <|@ <|@
      nr   -1  <|@ instruction NOP <|@ <|@
      nr   -1  <|@ instruction NOP <|@ <|@
      nr   -1  <|@ instruction NOP <|@ <|@
      nr   -1  <|@ instruction stack:16|QWORD = MOVE input: rbp|QWORD moveKind: QWORD <|@ <|@
      nr   -1  <|@ instruction [] = HOTSPOTLOCKSTACK frameMapBuilder: jdk.graal.compiler.hotspot.amd64.AMD64HotSpotFrameMapBuilder@20881f79 slotKind: QWORD <|@ <|@
      nr   -1  <|@ instruction v0|QWORD[.] = MOVE input: rsi|QWORD[.] moveKind: QWORD <|@ <|@
      nr   -1  <|@ instruction v1|DWORD = MOVSXB input: [v0|QWORD[.] + 12] size: DWORD <|@ <|@
      nr   -1  <|@ instruction rsi|DWORD = MOVE input: v1|DWORD moveKind: DWORD <|@ <|@
      nr   -1  <|@ st <@st|@java.lang.Byte.toString(Byte.java:443) [bci: 4]
locals: - 
>@ <|@ instruction rax|QWORD[.] = CALL_DIRECT parameters: [rsi|DWORD] temps: [] callTarget: HotSpotMethod<Integer.toString(int)> invokeKind: Static config: jdk.graal.compiler.hotspot.GraalHotSpotVMConfig@4817c460 state [bci:4] <|@ <|@
      nr   -1  <|@ instruction v2|QWORD[.] = MOVE input: rax|QWORD[.] moveKind: QWORD <|@ <|@
      nr   -1  <|@ instruction rax|QWORD[.] = MOVE input: v2|QWORD[.] moveKind: QWORD <|@ <|@
      nr   -1  <|@ instruction RETURN (savedRbp: stack:16|QWORD, value: rax|QWORD[.]) isStub: false requiresReservedStackAccessCheck: false thread: r15 scratchForSafepointOnReturn: rcx config: jdk.graal.compiler.hotspot.GraalHotSpotVMConfig@4817c460 <|@ <|@
    end_IR
  end_block
end_cfg
begin_bytecodes
     0: aload_0       
     1: getfield      #20         // value:byte
     4: invokestatic  #0          // java.lang.Integer.toString:(int)java.lang.String
     7: areturn       
   <|@
end_bytecodes
begin_cfg
  name "After ConstantLoadOptimization"
  begin_block
    name "B0"
    from_bci -1
    to_bci -1
    predecessors 
    successors 
    xhandlers
    flags 
    probability 4607182418800017408
    begin_IR
      LIR
      nr   -1  <|@ instruction [rsi|QWORD[.], rbp|QWORD] = LABEL alignment: 0 numbPhis: 0 label: ? <|@ <|@
      nr   -1  <|@ instruction NOP <|@ <|@
      nr   -1  <|@ instruction NOP <|@ <|@
      nr   -1  <|@ instruction NOP <|@ <|@
      nr   -1  <|@ instruction NOP <|@ <|@
      nr   -1  <|@ instruction NOP <|@ <|@
      nr   -1  <|@ instruction NOP <|@ <|@
      nr   -1  <|@ instruction NOP <|@ <|@
      nr   -1  <|@ instruction NOP <|@ <|@
      nr   -1  <|@ instruction NOP <|@ <|@
      nr   -1  <|@ instruction NOP <|@ <|@
      nr   -1  <|@ instruction NOP <|@ <|@
      nr   -1  <|@ instruction NOP <|@ <|@
      nr   -1  <|@ instruction NOP <|@ <|@
      nr   -1  <|@ instruction NOP <|@ <|@
      nr   -1  <|@ instruction NOP <|@ <|@
      nr   -1  <|@ instruction NOP <|@ <|@
      nr   -1  <|@ instruction NOP <|@ <|@
      nr   -1  <|@ instruction stack:16|QWORD = MOVE input: rbp|QWORD moveKind: QWORD <|@ <|@
      nr   -1  <|@ instruction [] = HOTSPOTLOCKSTACK frameMapBuilder: jdk.graal.compiler.hotspot.amd64.AMD64HotSpotFrameMapBuilder@20881f79 slotKind: QWORD <|@ <|@
      nr   -1  <|@ instruction v0|QWORD[.] = MOVE input: rsi|QWORD[.] moveKind: QWORD <|@ <|@
      nr   -1  <|@ instruction v1|DWORD = MOVSXB input: [v0|QWORD[.] + 12] size: DWORD <|@ <|@
      nr   -1  <|@ instruction rsi|DWORD = MOVE input: v1|DWORD moveKind: DWORD <|@ <|@
      nr   -1  <|@ st <@st|@java.lang.Byte.toString(Byte.java:443) [bci: 4]
locals: - 
>@ <|@ instruction rax|QWORD[.] = CALL_DIRECT parameters: [rsi|DWORD] temps: [] callTarget: HotSpotMethod<Integer.toString(int)> invokeKind: Static config: jdk.graal.compiler.hotspot.GraalHotSpotVMConfig@4817c460 state [bci:4] <|@ <|@
      nr   -1  <|@ instruction v2|QWORD[.] = MOVE input: rax|QWORD[.] moveKind: QWORD <|@ <|@
      nr   -1  <|@ instruction rax|QWORD[.] = MOVE input: v2|QWORD[.] moveKind: QWORD <|@ <|@
      nr   -1  <|@ instruction RETURN (savedRbp: stack:16|QWORD, value: rax|QWORD[.]) isStub: false requiresReservedStackAccessCheck: false thread: r15 scratchForSafepointOnReturn: rcx config: jdk.graal.compiler.hotspot.GraalHotSpotVMConfig@4817c460 <|@ <|@
    end_IR
  end_block
end_cfg
begin_bytecodes
     0: aload_0       
     1: getfield      #20         // value:byte
     4: invokestatic  #0          // java.lang.Integer.toString:(int)java.lang.String
     7: areturn       
   <|@
end_bytecodes
begin_cfg
  name "After SaveCalleeSaveRegisters"
  begin_block
    name "B0"
    from_bci -1
    to_bci -1
    predecessors 
    successors 
    xhandlers
    flags 
    probability 4607182418800017408
    begin_IR
      LIR
      nr   -1  <|@ instruction [rsi|QWORD[.], rbp|QWORD] = LABEL alignment: 0 numbPhis: 0 label: ? <|@ <|@
      nr   -1  <|@ instruction NOP <|@ <|@
      nr   -1  <|@ instruction NOP <|@ <|@
      nr   -1  <|@ instruction NOP <|@ <|@
      nr   -1  <|@ instruction NOP <|@ <|@
      nr   -1  <|@ instruction NOP <|@ <|@
      nr   -1  <|@ instruction NOP <|@ <|@
      nr   -1  <|@ instruction NOP <|@ <|@
      nr   -1  <|@ instruction NOP <|@ <|@
      nr   -1  <|@ instruction NOP <|@ <|@
      nr   -1  <|@ instruction NOP <|@ <|@
      nr   -1  <|@ instruction NOP <|@ <|@
      nr   -1  <|@ instruction NOP <|@ <|@
      nr   -1  <|@ instruction NOP <|@ <|@
      nr   -1  <|@ instruction NOP <|@ <|@
      nr   -1  <|@ instruction NOP <|@ <|@
      nr   -1  <|@ instruction NOP <|@ <|@
      nr   -1  <|@ instruction NOP <|@ <|@
      nr   -1  <|@ instruction stack:16|QWORD = MOVE input: rbp|QWORD moveKind: QWORD <|@ <|@
      nr   -1  <|@ instruction [] = HOTSPOTLOCKSTACK frameMapBuilder: jdk.graal.compiler.hotspot.amd64.AMD64HotSpotFrameMapBuilder@20881f79 slotKind: QWORD <|@ <|@
      nr   -1  <|@ instruction v0|QWORD[.] = MOVE input: rsi|QWORD[.] moveKind: QWORD <|@ <|@
      nr   -1  <|@ instruction v1|DWORD = MOVSXB input: [v0|QWORD[.] + 12] size: DWORD <|@ <|@
      nr   -1  <|@ instruction rsi|DWORD = MOVE input: v1|DWORD moveKind: DWORD <|@ <|@
      nr   -1  <|@ st <@st|@java.lang.Byte.toString(Byte.java:443) [bci: 4]
locals: - 
>@ <|@ instruction rax|QWORD[.] = CALL_DIRECT parameters: [rsi|DWORD] temps: [] callTarget: HotSpotMethod<Integer.toString(int)> invokeKind: Static config: jdk.graal.compiler.hotspot.GraalHotSpotVMConfig@4817c460 state [bci:4] <|@ <|@
      nr   -1  <|@ instruction v2|QWORD[.] = MOVE input: rax|QWORD[.] moveKind: QWORD <|@ <|@
      nr   -1  <|@ instruction rax|QWORD[.] = MOVE input: v2|QWORD[.] moveKind: QWORD <|@ <|@
      nr   -1  <|@ instruction RETURN (savedRbp: stack:16|QWORD, value: rax|QWORD[.]) isStub: false requiresReservedStackAccessCheck: false thread: r15 scratchForSafepointOnReturn: rcx config: jdk.graal.compiler.hotspot.GraalHotSpotVMConfig@4817c460 <|@ <|@
    end_IR
  end_block
end_cfg
begin_bytecodes
     0: aload_0       
     1: getfield      #20         // value:byte
     4: invokestatic  #0          // java.lang.Integer.toString:(int)java.lang.String
     7: areturn       
   <|@
end_bytecodes
begin_cfg
  name "After PreAllocationOptimizationStage"
  begin_block
    name "B0"
    from_bci -1
    to_bci -1
    predecessors 
    successors 
    xhandlers
    flags 
    probability 4607182418800017408
    begin_IR
      LIR
      nr   -1  <|@ instruction [rsi|QWORD[.], rbp|QWORD] = LABEL alignment: 0 numbPhis: 0 label: ? <|@ <|@
      nr   -1  <|@ instruction NOP <|@ <|@
      nr   -1  <|@ instruction NOP <|@ <|@
      nr   -1  <|@ instruction NOP <|@ <|@
      nr   -1  <|@ instruction NOP <|@ <|@
      nr   -1  <|@ instruction NOP <|@ <|@
      nr   -1  <|@ instruction NOP <|@ <|@
      nr   -1  <|@ instruction NOP <|@ <|@
      nr   -1  <|@ instruction NOP <|@ <|@
      nr   -1  <|@ instruction NOP <|@ <|@
      nr   -1  <|@ instruction NOP <|@ <|@
      nr   -1  <|@ instruction NOP <|@ <|@
      nr   -1  <|@ instruction NOP <|@ <|@
      nr   -1  <|@ instruction NOP <|@ <|@
      nr   -1  <|@ instruction NOP <|@ <|@
      nr   -1  <|@ instruction NOP <|@ <|@
      nr   -1  <|@ instruction NOP <|@ <|@
      nr   -1  <|@ instruction NOP <|@ <|@
      nr   -1  <|@ instruction stack:16|QWORD = MOVE input: rbp|QWORD moveKind: QWORD <|@ <|@
      nr   -1  <|@ instruction [] = HOTSPOTLOCKSTACK frameMapBuilder: jdk.graal.compiler.hotspot.amd64.AMD64HotSpotFrameMapBuilder@20881f79 slotKind: QWORD <|@ <|@
      nr   -1  <|@ instruction v0|QWORD[.] = MOVE input: rsi|QWORD[.] moveKind: QWORD <|@ <|@
      nr   -1  <|@ instruction v1|DWORD = MOVSXB input: [v0|QWORD[.] + 12] size: DWORD <|@ <|@
      nr   -1  <|@ instruction rsi|DWORD = MOVE input: v1|DWORD moveKind: DWORD <|@ <|@
      nr   -1  <|@ st <@st|@java.lang.Byte.toString(Byte.java:443) [bci: 4]
locals: - 
>@ <|@ instruction rax|QWORD[.] = CALL_DIRECT parameters: [rsi|DWORD] temps: [] callTarget: HotSpotMethod<Integer.toString(int)> invokeKind: Static config: jdk.graal.compiler.hotspot.GraalHotSpotVMConfig@4817c460 state [bci:4] <|@ <|@
      nr   -1  <|@ instruction v2|QWORD[.] = MOVE input: rax|QWORD[.] moveKind: QWORD <|@ <|@
      nr   -1  <|@ instruction rax|QWORD[.] = MOVE input: v2|QWORD[.] moveKind: QWORD <|@ <|@
      nr   -1  <|@ instruction RETURN (savedRbp: stack:16|QWORD, value: rax|QWORD[.]) isStub: false requiresReservedStackAccessCheck: false thread: r15 scratchForSafepointOnReturn: rcx config: jdk.graal.compiler.hotspot.GraalHotSpotVMConfig@4817c460 <|@ <|@
    end_IR
  end_block
end_cfg
begin_bytecodes
     0: aload_0       
     1: getfield      #20         // value:byte
     4: invokestatic  #0          // java.lang.Integer.toString:(int)java.lang.String
     7: areturn       
   <|@
end_bytecodes
begin_cfg
  name "After MarkBasePointers"
  begin_block
    name "B0"
    from_bci -1
    to_bci -1
    predecessors 
    successors 
    xhandlers
    flags 
    probability 4607182418800017408
    begin_IR
      LIR
      nr   -1  <|@ instruction [rsi|QWORD[.], rbp|QWORD] = LABEL alignment: 0 numbPhis: 0 label: ? <|@ <|@
      nr   -1  <|@ instruction NOP <|@ <|@
      nr   -1  <|@ instruction NOP <|@ <|@
      nr   -1  <|@ instruction NOP <|@ <|@
      nr   -1  <|@ instruction NOP <|@ <|@
      nr   -1  <|@ instruction NOP <|@ <|@
      nr   -1  <|@ instruction NOP <|@ <|@
      nr   -1  <|@ instruction NOP <|@ <|@
      nr   -1  <|@ instruction NOP <|@ <|@
      nr   -1  <|@ instruction NOP <|@ <|@
      nr   -1  <|@ instruction NOP <|@ <|@
      nr   -1  <|@ instruction NOP <|@ <|@
      nr   -1  <|@ instruction NOP <|@ <|@
      nr   -1  <|@ instruction NOP <|@ <|@
      nr   -1  <|@ instruction NOP <|@ <|@
      nr   -1  <|@ instruction NOP <|@ <|@
      nr   -1  <|@ instruction NOP <|@ <|@
      nr   -1  <|@ instruction NOP <|@ <|@
      nr   -1  <|@ instruction stack:16|QWORD = MOVE input: rbp|QWORD moveKind: QWORD <|@ <|@
      nr   -1  <|@ instruction [] = HOTSPOTLOCKSTACK frameMapBuilder: jdk.graal.compiler.hotspot.amd64.AMD64HotSpotFrameMapBuilder@20881f79 slotKind: QWORD <|@ <|@
      nr   -1  <|@ instruction v0|QWORD[.] = MOVE input: rsi|QWORD[.] moveKind: QWORD <|@ <|@
      nr   -1  <|@ instruction v1|DWORD = MOVSXB input: [v0|QWORD[.] + 12] size: DWORD <|@ <|@
      nr   -1  <|@ instruction rsi|DWORD = MOVE input: v1|DWORD moveKind: DWORD <|@ <|@
      nr   -1  <|@ st <@st|@live-base-pointers: []
java.lang.Byte.toString(Byte.java:443) [bci: 4]
locals: - 
>@ <|@ instruction rax|QWORD[.] = CALL_DIRECT parameters: [rsi|DWORD] temps: [] callTarget: HotSpotMethod<Integer.toString(int)> invokeKind: Static config: jdk.graal.compiler.hotspot.GraalHotSpotVMConfig@4817c460 state [bci:4] <|@ <|@
      nr   -1  <|@ instruction v2|QWORD[.] = MOVE input: rax|QWORD[.] moveKind: QWORD <|@ <|@
      nr   -1  <|@ instruction rax|QWORD[.] = MOVE input: v2|QWORD[.] moveKind: QWORD <|@ <|@
      nr   -1  <|@ instruction RETURN (savedRbp: stack:16|QWORD, value: rax|QWORD[.]) isStub: false requiresReservedStackAccessCheck: false thread: r15 scratchForSafepointOnReturn: rcx config: jdk.graal.compiler.hotspot.GraalHotSpotVMConfig@4817c460 <|@ <|@
    end_IR
  end_block
end_cfg
begin_bytecodes
     0: aload_0       
     1: getfield      #20         // value:byte
     4: invokestatic  #0          // java.lang.Integer.toString:(int)java.lang.String
     7: areturn       
   <|@
end_bytecodes
begin_cfg
  name "Before register allocation"
  begin_block
    name "B0"
    from_bci -1
    to_bci -1
    predecessors 
    successors 
    xhandlers
    flags 
    probability 4607182418800017408
    begin_IR
      LIR
      nr    0  <|@ instruction [rsi|QWORD[.], rbp|QWORD] = LABEL alignment: 0 numbPhis: 0 label: ? <|@ <|@
      nr    2  <|@ instruction NOP <|@ <|@
      nr    4  <|@ instruction NOP <|@ <|@
      nr    6  <|@ instruction NOP <|@ <|@
      nr    8  <|@ instruction NOP <|@ <|@
      nr   10  <|@ instruction NOP <|@ <|@
      nr   12  <|@ instruction NOP <|@ <|@
      nr   14  <|@ instruction NOP <|@ <|@
      nr   16  <|@ instruction NOP <|@ <|@
      nr   18  <|@ instruction NOP <|@ <|@
      nr   20  <|@ instruction NOP <|@ <|@
      nr   22  <|@ instruction NOP <|@ <|@
      nr   24  <|@ instruction NOP <|@ <|@
      nr   26  <|@ instruction NOP <|@ <|@
      nr   28  <|@ instruction NOP <|@ <|@
      nr   30  <|@ instruction NOP <|@ <|@
      nr   32  <|@ instruction NOP <|@ <|@
      nr   34  <|@ instruction NOP <|@ <|@
      nr   36  <|@ instruction stack:16|QWORD = MOVE input: rbp|QWORD moveKind: QWORD <|@ <|@
      nr   38  <|@ instruction [] = HOTSPOTLOCKSTACK frameMapBuilder: jdk.graal.compiler.hotspot.amd64.AMD64HotSpotFrameMapBuilder@20881f79 slotKind: QWORD <|@ <|@
      nr   40  <|@ instruction v0|QWORD[.] = MOVE input: rsi|QWORD[.] moveKind: QWORD <|@ <|@
      nr   42  <|@ instruction v1|DWORD = MOVSXB input: [v0|QWORD[.] + 12] size: DWORD <|@ <|@
      nr   44  <|@ instruction rsi|DWORD = MOVE input: v1|DWORD moveKind: DWORD <|@ <|@
      nr   46  <|@ st <@st|@live-base-pointers: []
java.lang.Byte.toString(Byte.java:443) [bci: 4]
locals: - 
>@ <|@ instruction rax|QWORD[.] = CALL_DIRECT parameters: [rsi|DWORD] temps: [] callTarget: HotSpotMethod<Integer.toString(int)> invokeKind: Static config: jdk.graal.compiler.hotspot.GraalHotSpotVMConfig@4817c460 state [bci:4] <|@ <|@
      nr   48  <|@ instruction v2|QWORD[.] = MOVE input: rax|QWORD[.] moveKind: QWORD <|@ <|@
      nr   50  <|@ instruction rax|QWORD[.] = MOVE input: v2|QWORD[.] moveKind: QWORD <|@ <|@
      nr   52  <|@ instruction RETURN (savedRbp: stack:16|QWORD, value: rax|QWORD[.]) isStub: false requiresReservedStackAccessCheck: false thread: r15 scratchForSafepointOnReturn: rcx config: jdk.graal.compiler.hotspot.GraalHotSpotVMConfig@4817c460 <|@ <|@
    end_IR
  end_block
end_cfg
begin_bytecodes
     0: aload_0       
     1: getfield      #20         // value:byte
     4: invokestatic  #0          // java.lang.Integer.toString:(int)java.lang.String
     7: areturn       
   <|@
end_bytecodes
begin_cfg
  name "After SSALinearScanLifetimeAnalysis"
  begin_block
    name "B0"
    from_bci -1
    to_bci -1
    predecessors 
    successors 
    xhandlers
    flags 
    probability 4607182418800017408
    begin_IR
      LIR
      nr    0  <|@ instruction [rsi|QWORD[.], rbp|QWORD] = LABEL alignment: 0 numbPhis: 0 label: ? <|@ <|@
      nr    2  <|@ instruction NOP <|@ <|@
      nr    4  <|@ instruction NOP <|@ <|@
      nr    6  <|@ instruction NOP <|@ <|@
      nr    8  <|@ instruction NOP <|@ <|@
      nr   10  <|@ instruction NOP <|@ <|@
      nr   12  <|@ instruction NOP <|@ <|@
      nr   14  <|@ instruction NOP <|@ <|@
      nr   16  <|@ instruction NOP <|@ <|@
      nr   18  <|@ instruction NOP <|@ <|@
      nr   20  <|@ instruction NOP <|@ <|@
      nr   22  <|@ instruction NOP <|@ <|@
      nr   24  <|@ instruction NOP <|@ <|@
      nr   26  <|@ instruction NOP <|@ <|@
      nr   28  <|@ instruction NOP <|@ <|@
      nr   30  <|@ instruction NOP <|@ <|@
      nr   32  <|@ instruction NOP <|@ <|@
      nr   34  <|@ instruction NOP <|@ <|@
      nr   36  <|@ instruction stack:16|QWORD = MOVE input: rbp|QWORD moveKind: QWORD <|@ <|@
      nr   38  <|@ instruction [] = HOTSPOTLOCKSTACK frameMapBuilder: jdk.graal.compiler.hotspot.amd64.AMD64HotSpotFrameMapBuilder@20881f79 slotKind: QWORD <|@ <|@
      nr   40  <|@ instruction v0|QWORD[.] = MOVE input: rsi|QWORD[.] moveKind: QWORD <|@ <|@
      nr   42  <|@ instruction v1|DWORD = MOVSXB input: [v0|QWORD[.] + 12] size: DWORD <|@ <|@
      nr   44  <|@ instruction rsi|DWORD = MOVE input: v1|DWORD moveKind: DWORD <|@ <|@
      nr   46  <|@ st <@st|@live-base-pointers: []
java.lang.Byte.toString(Byte.java:443) [bci: 4]
locals: - 
>@ <|@ instruction rax|QWORD[.] = CALL_DIRECT parameters: [rsi|DWORD] temps: [] callTarget: HotSpotMethod<Integer.toString(int)> invokeKind: Static config: jdk.graal.compiler.hotspot.GraalHotSpotVMConfig@4817c460 state [bci:4] <|@ <|@
      nr   48  <|@ instruction v2|QWORD[.] = MOVE input: rax|QWORD[.] moveKind: QWORD <|@ <|@
      nr   50  <|@ instruction rax|QWORD[.] = MOVE input: v2|QWORD[.] moveKind: QWORD <|@ <|@
      nr   52  <|@ instruction RETURN (savedRbp: stack:16|QWORD, value: rax|QWORD[.]) isStub: false requiresReservedStackAccessCheck: false thread: r15 scratchForSafepointOnReturn: rcx config: jdk.graal.compiler.hotspot.GraalHotSpotVMConfig@4817c460 <|@ <|@
    end_IR
  end_block
end_cfg
begin_bytecodes
     0: aload_0       
     1: getfield      #20         // value:byte
     4: invokestatic  #0          // java.lang.Integer.toString:(int)java.lang.String
     7: areturn       
   <|@
end_bytecodes
begin_intervals
  name "Before register allocation"
  rax|q fixed "[rax|q]" rax|q v2|q [0, 1[[46, 48[[50, 52[ "NoOptimization"
  rcx|- fixed "[rcx|-]" rcx|- -1 [0, 1[[46, 47[ "NoDefinitionFound"
  rdx|- fixed "[rdx|-]" rdx|- -1 [0, 1[[46, 47[ "NoDefinitionFound"
  rbx|- fixed "[rbx|-]" rbx|- -1 [0, 1[[46, 47[ "NoDefinitionFound"
  rbp|- fixed "[rbp|-]" rbp|- -1 [0, 36[[46, 47[ "NoSpillStore"
  rsi|- fixed "[rsi|-]" rsi|- v1|d [0, 40[[44, 47[ "NoOptimization"
  rdi|- fixed "[rdi|-]" rdi|- -1 [0, 1[[46, 47[ "NoDefinitionFound"
  r8|- fixed "[r8|-]" r8|- -1 [0, 1[[46, 47[ "NoDefinitionFound"
  r9|- fixed "[r9|-]" r9|- -1 [0, 1[[46, 47[ "NoDefinitionFound"
  r10|- fixed "[r10|-]" r10|- -1 [0, 1[[46, 47[ "NoDefinitionFound"
  r11|- fixed "[r11|-]" r11|- -1 [0, 1[[46, 47[ "NoDefinitionFound"
  r13|- fixed "[r13|-]" r13|- -1 [0, 1[[46, 47[ "NoDefinitionFound"
  r14|- fixed "[r14|-]" r14|- -1 [0, 1[[46, 47[ "NoDefinitionFound"
  xmm0|- fixed "[xmm0|-]" xmm0|- -1 [0, 1[[46, 47[ "NoDefinitionFound"
  xmm1|- fixed "[xmm1|-]" xmm1|- -1 [0, 1[[46, 47[ "NoDefinitionFound"
  xmm2|- fixed "[xmm2|-]" xmm2|- -1 [0, 1[[46, 47[ "NoDefinitionFound"
  xmm3|- fixed "[xmm3|-]" xmm3|- -1 [0, 1[[46, 47[ "NoDefinitionFound"
  xmm4|- fixed "[xmm4|-]" xmm4|- -1 [0, 1[[46, 47[ "NoDefinitionFound"
  xmm5|- fixed "[xmm5|-]" xmm5|- -1 [0, 1[[46, 47[ "NoDefinitionFound"
  xmm6|- fixed "[xmm6|-]" xmm6|- -1 [0, 1[[46, 47[ "NoDefinitionFound"
  xmm7|- fixed "[xmm7|-]" xmm7|- -1 [0, 1[[46, 47[ "NoDefinitionFound"
  xmm8|- fixed "[xmm8|-]" xmm8|- -1 [0, 1[[46, 47[ "NoDefinitionFound"
  xmm9|- fixed "[xmm9|-]" xmm9|- -1 [0, 1[[46, 47[ "NoDefinitionFound"
  xmm10|- fixed "[xmm10|-]" xmm10|- -1 [0, 1[[46, 47[ "NoDefinitionFound"
  xmm11|- fixed "[xmm11|-]" xmm11|- -1 [0, 1[[46, 47[ "NoDefinitionFound"
  xmm12|- fixed "[xmm12|-]" xmm12|- -1 [0, 1[[46, 47[ "NoDefinitionFound"
  xmm13|- fixed "[xmm13|-]" xmm13|- -1 [0, 1[[46, 47[ "NoDefinitionFound"
  xmm14|- fixed "[xmm14|-]" xmm14|- -1 [0, 1[[46, 47[ "NoDefinitionFound"
  xmm15|- fixed "[xmm15|-]" xmm15|- -1 [0, 1[[46, 47[ "NoDefinitionFound"
  v0|q QWORD "[v0|q]" v0|q rsi|- [40, 42[40 MustHaveRegister 42 MustHaveRegister  "NoSpillStore"
  v1|d DWORD "[v1|d]" v1|d -1 [42, 44[42 MustHaveRegister 44 ShouldHaveRegister  "NoSpillStore"
  v2|q QWORD "[v2|q]" v2|q rax|q [48, 50[48 MustHaveRegister 50 ShouldHaveRegister  "NoSpillStore"
end_intervals
begin_intervals
  name "After register allocation"
  rax|q fixed "[rax|q]" rax|q v2|q [0, 1[[46, 48[[50, 52[ "NoOptimization"
  rcx|- fixed "[rcx|-]" rcx|- -1 [0, 1[[46, 47[ "NoDefinitionFound"
  rdx|- fixed "[rdx|-]" rdx|- -1 [0, 1[[46, 47[ "NoDefinitionFound"
  rbx|- fixed "[rbx|-]" rbx|- -1 [0, 1[[46, 47[ "NoDefinitionFound"
  rbp|- fixed "[rbp|-]" rbp|- -1 [0, 36[[46, 47[ "NoSpillStore"
  rsi|- fixed "[rsi|-]" rsi|- v1|d [0, 40[[44, 47[ "NoOptimization"
  rdi|- fixed "[rdi|-]" rdi|- -1 [0, 1[[46, 47[ "NoDefinitionFound"
  r8|- fixed "[r8|-]" r8|- -1 [0, 1[[46, 47[ "NoDefinitionFound"
  r9|- fixed "[r9|-]" r9|- -1 [0, 1[[46, 47[ "NoDefinitionFound"
  r10|- fixed "[r10|-]" r10|- -1 [0, 1[[46, 47[ "NoDefinitionFound"
  r11|- fixed "[r11|-]" r11|- -1 [0, 1[[46, 47[ "NoDefinitionFound"
  r13|- fixed "[r13|-]" r13|- -1 [0, 1[[46, 47[ "NoDefinitionFound"
  r14|- fixed "[r14|-]" r14|- -1 [0, 1[[46, 47[ "NoDefinitionFound"
  xmm0|- fixed "[xmm0|-]" xmm0|- -1 [0, 1[[46, 47[ "NoDefinitionFound"
  xmm1|- fixed "[xmm1|-]" xmm1|- -1 [0, 1[[46, 47[ "NoDefinitionFound"
  xmm2|- fixed "[xmm2|-]" xmm2|- -1 [0, 1[[46, 47[ "NoDefinitionFound"
  xmm3|- fixed "[xmm3|-]" xmm3|- -1 [0, 1[[46, 47[ "NoDefinitionFound"
  xmm4|- fixed "[xmm4|-]" xmm4|- -1 [0, 1[[46, 47[ "NoDefinitionFound"
  xmm5|- fixed "[xmm5|-]" xmm5|- -1 [0, 1[[46, 47[ "NoDefinitionFound"
  xmm6|- fixed "[xmm6|-]" xmm6|- -1 [0, 1[[46, 47[ "NoDefinitionFound"
  xmm7|- fixed "[xmm7|-]" xmm7|- -1 [0, 1[[46, 47[ "NoDefinitionFound"
  xmm8|- fixed "[xmm8|-]" xmm8|- -1 [0, 1[[46, 47[ "NoDefinitionFound"
  xmm9|- fixed "[xmm9|-]" xmm9|- -1 [0, 1[[46, 47[ "NoDefinitionFound"
  xmm10|- fixed "[xmm10|-]" xmm10|- -1 [0, 1[[46, 47[ "NoDefinitionFound"
  xmm11|- fixed "[xmm11|-]" xmm11|- -1 [0, 1[[46, 47[ "NoDefinitionFound"
  xmm12|- fixed "[xmm12|-]" xmm12|- -1 [0, 1[[46, 47[ "NoDefinitionFound"
  xmm13|- fixed "[xmm13|-]" xmm13|- -1 [0, 1[[46, 47[ "NoDefinitionFound"
  xmm14|- fixed "[xmm14|-]" xmm14|- -1 [0, 1[[46, 47[ "NoDefinitionFound"
  xmm15|- fixed "[xmm15|-]" xmm15|- -1 [0, 1[[46, 47[ "NoDefinitionFound"
  v0|q QWORD "[rsi|q]" v0|q rsi|- [40, 42[40 MustHaveRegister 42 MustHaveRegister  "NoSpillStore"
  v1|d DWORD "[rsi|d]" v1|d -1 [42, 44[42 MustHaveRegister 44 ShouldHaveRegister  "NoSpillStore"
  v2|q QWORD "[rax|q]" v2|q rax|q [48, 50[48 MustHaveRegister 50 ShouldHaveRegister  "NoSpillStore"
end_intervals
begin_cfg
  name "After LinearScanRegisterAllocation"
  begin_block
    name "B0"
    from_bci -1
    to_bci -1
    predecessors 
    successors 
    xhandlers
    flags 
    probability 4607182418800017408
    begin_IR
      LIR
      nr    0  <|@ instruction [rsi|QWORD[.], rbp|QWORD] = LABEL alignment: 0 numbPhis: 0 label: ? <|@ <|@
      nr    2  <|@ instruction NOP <|@ <|@
      nr    4  <|@ instruction NOP <|@ <|@
      nr    6  <|@ instruction NOP <|@ <|@
      nr    8  <|@ instruction NOP <|@ <|@
      nr   10  <|@ instruction NOP <|@ <|@
      nr   12  <|@ instruction NOP <|@ <|@
      nr   14  <|@ instruction NOP <|@ <|@
      nr   16  <|@ instruction NOP <|@ <|@
      nr   18  <|@ instruction NOP <|@ <|@
      nr   20  <|@ instruction NOP <|@ <|@
      nr   22  <|@ instruction NOP <|@ <|@
      nr   24  <|@ instruction NOP <|@ <|@
      nr   26  <|@ instruction NOP <|@ <|@
      nr   28  <|@ instruction NOP <|@ <|@
      nr   30  <|@ instruction NOP <|@ <|@
      nr   32  <|@ instruction NOP <|@ <|@
      nr   34  <|@ instruction NOP <|@ <|@
      nr   36  <|@ instruction stack:16|QWORD = MOVE input: rbp|QWORD moveKind: QWORD <|@ <|@
      nr   38  <|@ instruction [] = HOTSPOTLOCKSTACK frameMapBuilder: jdk.graal.compiler.hotspot.amd64.AMD64HotSpotFrameMapBuilder@20881f79 slotKind: QWORD <|@ <|@
      nr   40  <|@ instruction v0|QWORD[.] = MOVE input: rsi|QWORD[.] moveKind: QWORD <|@ <|@
      nr   42  <|@ instruction v1|DWORD = MOVSXB input: [v0|QWORD[.] + 12] size: DWORD <|@ <|@
      nr   44  <|@ instruction rsi|DWORD = MOVE input: v1|DWORD moveKind: DWORD <|@ <|@
      nr   46  <|@ st <@st|@live-base-pointers: []
java.lang.Byte.toString(Byte.java:443) [bci: 4]
locals: - 
>@ <|@ instruction rax|QWORD[.] = CALL_DIRECT parameters: [rsi|DWORD] temps: [] callTarget: HotSpotMethod<Integer.toString(int)> invokeKind: Static config: jdk.graal.compiler.hotspot.GraalHotSpotVMConfig@4817c460 state [bci:4] <|@ <|@
      nr   48  <|@ instruction v2|QWORD[.] = MOVE input: rax|QWORD[.] moveKind: QWORD <|@ <|@
      nr   50  <|@ instruction rax|QWORD[.] = MOVE input: v2|QWORD[.] moveKind: QWORD <|@ <|@
      nr   52  <|@ instruction RETURN (savedRbp: stack:16|QWORD, value: rax|QWORD[.]) isStub: false requiresReservedStackAccessCheck: false thread: r15 scratchForSafepointOnReturn: rcx config: jdk.graal.compiler.hotspot.GraalHotSpotVMConfig@4817c460 <|@ <|@
    end_IR
  end_block
end_cfg
begin_bytecodes
     0: aload_0       
     1: getfield      #20         // value:byte
     4: invokestatic  #0          // java.lang.Integer.toString:(int)java.lang.String
     7: areturn       
   <|@
end_bytecodes
begin_intervals
  name "After optimize spill position"
  rax|q fixed "[rax|q]" rax|q v2|q [0, 1[[46, 48[[50, 52[ "NoOptimization"
  rcx|- fixed "[rcx|-]" rcx|- -1 [0, 1[[46, 47[ "NoDefinitionFound"
  rdx|- fixed "[rdx|-]" rdx|- -1 [0, 1[[46, 47[ "NoDefinitionFound"
  rbx|- fixed "[rbx|-]" rbx|- -1 [0, 1[[46, 47[ "NoDefinitionFound"
  rbp|- fixed "[rbp|-]" rbp|- -1 [0, 36[[46, 47[ "NoSpillStore"
  rsi|- fixed "[rsi|-]" rsi|- v1|d [0, 40[[44, 47[ "NoOptimization"
  rdi|- fixed "[rdi|-]" rdi|- -1 [0, 1[[46, 47[ "NoDefinitionFound"
  r8|- fixed "[r8|-]" r8|- -1 [0, 1[[46, 47[ "NoDefinitionFound"
  r9|- fixed "[r9|-]" r9|- -1 [0, 1[[46, 47[ "NoDefinitionFound"
  r10|- fixed "[r10|-]" r10|- -1 [0, 1[[46, 47[ "NoDefinitionFound"
  r11|- fixed "[r11|-]" r11|- -1 [0, 1[[46, 47[ "NoDefinitionFound"
  r13|- fixed "[r13|-]" r13|- -1 [0, 1[[46, 47[ "NoDefinitionFound"
  r14|- fixed "[r14|-]" r14|- -1 [0, 1[[46, 47[ "NoDefinitionFound"
  xmm0|- fixed "[xmm0|-]" xmm0|- -1 [0, 1[[46, 47[ "NoDefinitionFound"
  xmm1|- fixed "[xmm1|-]" xmm1|- -1 [0, 1[[46, 47[ "NoDefinitionFound"
  xmm2|- fixed "[xmm2|-]" xmm2|- -1 [0, 1[[46, 47[ "NoDefinitionFound"
  xmm3|- fixed "[xmm3|-]" xmm3|- -1 [0, 1[[46, 47[ "NoDefinitionFound"
  xmm4|- fixed "[xmm4|-]" xmm4|- -1 [0, 1[[46, 47[ "NoDefinitionFound"
  xmm5|- fixed "[xmm5|-]" xmm5|- -1 [0, 1[[46, 47[ "NoDefinitionFound"
  xmm6|- fixed "[xmm6|-]" xmm6|- -1 [0, 1[[46, 47[ "NoDefinitionFound"
  xmm7|- fixed "[xmm7|-]" xmm7|- -1 [0, 1[[46, 47[ "NoDefinitionFound"
  xmm8|- fixed "[xmm8|-]" xmm8|- -1 [0, 1[[46, 47[ "NoDefinitionFound"
  xmm9|- fixed "[xmm9|-]" xmm9|- -1 [0, 1[[46, 47[ "NoDefinitionFound"
  xmm10|- fixed "[xmm10|-]" xmm10|- -1 [0, 1[[46, 47[ "NoDefinitionFound"
  xmm11|- fixed "[xmm11|-]" xmm11|- -1 [0, 1[[46, 47[ "NoDefinitionFound"
  xmm12|- fixed "[xmm12|-]" xmm12|- -1 [0, 1[[46, 47[ "NoDefinitionFound"
  xmm13|- fixed "[xmm13|-]" xmm13|- -1 [0, 1[[46, 47[ "NoDefinitionFound"
  xmm14|- fixed "[xmm14|-]" xmm14|- -1 [0, 1[[46, 47[ "NoDefinitionFound"
  xmm15|- fixed "[xmm15|-]" xmm15|- -1 [0, 1[[46, 47[ "NoDefinitionFound"
  v0|q QWORD "[rsi|q]" v0|q rsi|- [40, 42[40 MustHaveRegister 42 MustHaveRegister  "NoSpillStore"
  v1|d DWORD "[rsi|d]" v1|d -1 [42, 44[42 MustHaveRegister 44 ShouldHaveRegister  "NoSpillStore"
  v2|q QWORD "[rax|q]" v2|q rax|q [48, 50[48 MustHaveRegister 50 ShouldHaveRegister  "NoSpillStore"
end_intervals
begin_cfg
  name "After LinearScanOptimizeSpillPosition"
  begin_block
    name "B0"
    from_bci -1
    to_bci -1
    predecessors 
    successors 
    xhandlers
    flags 
    probability 4607182418800017408
    begin_IR
      LIR
      nr    0  <|@ instruction [rsi|QWORD[.], rbp|QWORD] = LABEL alignment: 0 numbPhis: 0 label: ? <|@ <|@
      nr    2  <|@ instruction NOP <|@ <|@
      nr    4  <|@ instruction NOP <|@ <|@
      nr    6  <|@ instruction NOP <|@ <|@
      nr    8  <|@ instruction NOP <|@ <|@
      nr   10  <|@ instruction NOP <|@ <|@
      nr   12  <|@ instruction NOP <|@ <|@
      nr   14  <|@ instruction NOP <|@ <|@
      nr   16  <|@ instruction NOP <|@ <|@
      nr   18  <|@ instruction NOP <|@ <|@
      nr   20  <|@ instruction NOP <|@ <|@
      nr   22  <|@ instruction NOP <|@ <|@
      nr   24  <|@ instruction NOP <|@ <|@
      nr   26  <|@ instruction NOP <|@ <|@
      nr   28  <|@ instruction NOP <|@ <|@
      nr   30  <|@ instruction NOP <|@ <|@
      nr   32  <|@ instruction NOP <|@ <|@
      nr   34  <|@ instruction NOP <|@ <|@
      nr   36  <|@ instruction stack:16|QWORD = MOVE input: rbp|QWORD moveKind: QWORD <|@ <|@
      nr   38  <|@ instruction [] = HOTSPOTLOCKSTACK frameMapBuilder: jdk.graal.compiler.hotspot.amd64.AMD64HotSpotFrameMapBuilder@20881f79 slotKind: QWORD <|@ <|@
      nr   40  <|@ instruction v0|QWORD[.] = MOVE input: rsi|QWORD[.] moveKind: QWORD <|@ <|@
      nr   42  <|@ instruction v1|DWORD = MOVSXB input: [v0|QWORD[.] + 12] size: DWORD <|@ <|@
      nr   44  <|@ instruction rsi|DWORD = MOVE input: v1|DWORD moveKind: DWORD <|@ <|@
      nr   46  <|@ st <@st|@live-base-pointers: []
java.lang.Byte.toString(Byte.java:443) [bci: 4]
locals: - 
>@ <|@ instruction rax|QWORD[.] = CALL_DIRECT parameters: [rsi|DWORD] temps: [] callTarget: HotSpotMethod<Integer.toString(int)> invokeKind: Static config: jdk.graal.compiler.hotspot.GraalHotSpotVMConfig@4817c460 state [bci:4] <|@ <|@
      nr   48  <|@ instruction v2|QWORD[.] = MOVE input: rax|QWORD[.] moveKind: QWORD <|@ <|@
      nr   50  <|@ instruction rax|QWORD[.] = MOVE input: v2|QWORD[.] moveKind: QWORD <|@ <|@
      nr   52  <|@ instruction RETURN (savedRbp: stack:16|QWORD, value: rax|QWORD[.]) isStub: false requiresReservedStackAccessCheck: false thread: r15 scratchForSafepointOnReturn: rcx config: jdk.graal.compiler.hotspot.GraalHotSpotVMConfig@4817c460 <|@ <|@
    end_IR
  end_block
end_cfg
begin_bytecodes
     0: aload_0       
     1: getfield      #20         // value:byte
     4: invokestatic  #0          // java.lang.Integer.toString:(int)java.lang.String
     7: areturn       
   <|@
end_bytecodes
begin_intervals
  name "After resolve data flow"
  rax|q fixed "[rax|q]" rax|q v2|q [0, 1[[46, 48[[50, 52[ "NoOptimization"
  rcx|- fixed "[rcx|-]" rcx|- -1 [0, 1[[46, 47[ "NoDefinitionFound"
  rdx|- fixed "[rdx|-]" rdx|- -1 [0, 1[[46, 47[ "NoDefinitionFound"
  rbx|- fixed "[rbx|-]" rbx|- -1 [0, 1[[46, 47[ "NoDefinitionFound"
  rbp|- fixed "[rbp|-]" rbp|- -1 [0, 36[[46, 47[ "NoSpillStore"
  rsi|- fixed "[rsi|-]" rsi|- v1|d [0, 40[[44, 47[ "NoOptimization"
  rdi|- fixed "[rdi|-]" rdi|- -1 [0, 1[[46, 47[ "NoDefinitionFound"
  r8|- fixed "[r8|-]" r8|- -1 [0, 1[[46, 47[ "NoDefinitionFound"
  r9|- fixed "[r9|-]" r9|- -1 [0, 1[[46, 47[ "NoDefinitionFound"
  r10|- fixed "[r10|-]" r10|- -1 [0, 1[[46, 47[ "NoDefinitionFound"
  r11|- fixed "[r11|-]" r11|- -1 [0, 1[[46, 47[ "NoDefinitionFound"
  r13|- fixed "[r13|-]" r13|- -1 [0, 1[[46, 47[ "NoDefinitionFound"
  r14|- fixed "[r14|-]" r14|- -1 [0, 1[[46, 47[ "NoDefinitionFound"
  xmm0|- fixed "[xmm0|-]" xmm0|- -1 [0, 1[[46, 47[ "NoDefinitionFound"
  xmm1|- fixed "[xmm1|-]" xmm1|- -1 [0, 1[[46, 47[ "NoDefinitionFound"
  xmm2|- fixed "[xmm2|-]" xmm2|- -1 [0, 1[[46, 47[ "NoDefinitionFound"
  xmm3|- fixed "[xmm3|-]" xmm3|- -1 [0, 1[[46, 47[ "NoDefinitionFound"
  xmm4|- fixed "[xmm4|-]" xmm4|- -1 [0, 1[[46, 47[ "NoDefinitionFound"
  xmm5|- fixed "[xmm5|-]" xmm5|- -1 [0, 1[[46, 47[ "NoDefinitionFound"
  xmm6|- fixed "[xmm6|-]" xmm6|- -1 [0, 1[[46, 47[ "NoDefinitionFound"
  xmm7|- fixed "[xmm7|-]" xmm7|- -1 [0, 1[[46, 47[ "NoDefinitionFound"
  xmm8|- fixed "[xmm8|-]" xmm8|- -1 [0, 1[[46, 47[ "NoDefinitionFound"
  xmm9|- fixed "[xmm9|-]" xmm9|- -1 [0, 1[[46, 47[ "NoDefinitionFound"
  xmm10|- fixed "[xmm10|-]" xmm10|- -1 [0, 1[[46, 47[ "NoDefinitionFound"
  xmm11|- fixed "[xmm11|-]" xmm11|- -1 [0, 1[[46, 47[ "NoDefinitionFound"
  xmm12|- fixed "[xmm12|-]" xmm12|- -1 [0, 1[[46, 47[ "NoDefinitionFound"
  xmm13|- fixed "[xmm13|-]" xmm13|- -1 [0, 1[[46, 47[ "NoDefinitionFound"
  xmm14|- fixed "[xmm14|-]" xmm14|- -1 [0, 1[[46, 47[ "NoDefinitionFound"
  xmm15|- fixed "[xmm15|-]" xmm15|- -1 [0, 1[[46, 47[ "NoDefinitionFound"
  v0|q QWORD "[rsi|q]" v0|q rsi|- [40, 42[40 MustHaveRegister 42 MustHaveRegister  "NoSpillStore"
  v1|d DWORD "[rsi|d]" v1|d -1 [42, 44[42 MustHaveRegister 44 ShouldHaveRegister  "NoSpillStore"
  v2|q QWORD "[rax|q]" v2|q rax|q [48, 50[48 MustHaveRegister 50 ShouldHaveRegister  "NoSpillStore"
end_intervals
begin_cfg
  name "After SSALinearScanResolveDataFlow"
  begin_block
    name "B0"
    from_bci -1
    to_bci -1
    predecessors 
    successors 
    xhandlers
    flags 
    probability 4607182418800017408
    begin_IR
      LIR
      nr    0  <|@ instruction [rsi|QWORD[.], rbp|QWORD] = LABEL alignment: 0 numbPhis: 0 label: ? <|@ <|@
      nr    2  <|@ instruction NOP <|@ <|@
      nr    4  <|@ instruction NOP <|@ <|@
      nr    6  <|@ instruction NOP <|@ <|@
      nr    8  <|@ instruction NOP <|@ <|@
      nr   10  <|@ instruction NOP <|@ <|@
      nr   12  <|@ instruction NOP <|@ <|@
      nr   14  <|@ instruction NOP <|@ <|@
      nr   16  <|@ instruction NOP <|@ <|@
      nr   18  <|@ instruction NOP <|@ <|@
      nr   20  <|@ instruction NOP <|@ <|@
      nr   22  <|@ instruction NOP <|@ <|@
      nr   24  <|@ instruction NOP <|@ <|@
      nr   26  <|@ instruction NOP <|@ <|@
      nr   28  <|@ instruction NOP <|@ <|@
      nr   30  <|@ instruction NOP <|@ <|@
      nr   32  <|@ instruction NOP <|@ <|@
      nr   34  <|@ instruction NOP <|@ <|@
      nr   36  <|@ instruction stack:16|QWORD = MOVE input: rbp|QWORD moveKind: QWORD <|@ <|@
      nr   38  <|@ instruction [] = HOTSPOTLOCKSTACK frameMapBuilder: jdk.graal.compiler.hotspot.amd64.AMD64HotSpotFrameMapBuilder@20881f79 slotKind: QWORD <|@ <|@
      nr   40  <|@ instruction v0|QWORD[.] = MOVE input: rsi|QWORD[.] moveKind: QWORD <|@ <|@
      nr   42  <|@ instruction v1|DWORD = MOVSXB input: [v0|QWORD[.] + 12] size: DWORD <|@ <|@
      nr   44  <|@ instruction rsi|DWORD = MOVE input: v1|DWORD moveKind: DWORD <|@ <|@
      nr   46  <|@ st <@st|@live-base-pointers: []
java.lang.Byte.toString(Byte.java:443) [bci: 4]
locals: - 
>@ <|@ instruction rax|QWORD[.] = CALL_DIRECT parameters: [rsi|DWORD] temps: [] callTarget: HotSpotMethod<Integer.toString(int)> invokeKind: Static config: jdk.graal.compiler.hotspot.GraalHotSpotVMConfig@4817c460 state [bci:4] <|@ <|@
      nr   48  <|@ instruction v2|QWORD[.] = MOVE input: rax|QWORD[.] moveKind: QWORD <|@ <|@
      nr   50  <|@ instruction rax|QWORD[.] = MOVE input: v2|QWORD[.] moveKind: QWORD <|@ <|@
      nr   52  <|@ instruction RETURN (savedRbp: stack:16|QWORD, value: rax|QWORD[.]) isStub: false requiresReservedStackAccessCheck: false thread: r15 scratchForSafepointOnReturn: rcx config: jdk.graal.compiler.hotspot.GraalHotSpotVMConfig@4817c460 <|@ <|@
    end_IR
  end_block
end_cfg
begin_bytecodes
     0: aload_0       
     1: getfield      #20         // value:byte
     4: invokestatic  #0          // java.lang.Integer.toString:(int)java.lang.String
     7: areturn       
   <|@
end_bytecodes
begin_cfg
  name "After SSALinearScanEliminateSpillMove"
  begin_block
    name "B0"
    from_bci -1
    to_bci -1
    predecessors 
    successors 
    xhandlers
    flags 
    probability 4607182418800017408
    begin_IR
      LIR
      nr    0  <|@ instruction [rsi|QWORD[.], rbp|QWORD] = LABEL alignment: 0 numbPhis: 0 label: ? <|@ <|@
      nr    2  <|@ instruction NOP <|@ <|@
      nr    4  <|@ instruction NOP <|@ <|@
      nr    6  <|@ instruction NOP <|@ <|@
      nr    8  <|@ instruction NOP <|@ <|@
      nr   10  <|@ instruction NOP <|@ <|@
      nr   12  <|@ instruction NOP <|@ <|@
      nr   14  <|@ instruction NOP <|@ <|@
      nr   16  <|@ instruction NOP <|@ <|@
      nr   18  <|@ instruction NOP <|@ <|@
      nr   20  <|@ instruction NOP <|@ <|@
      nr   22  <|@ instruction NOP <|@ <|@
      nr   24  <|@ instruction NOP <|@ <|@
      nr   26  <|@ instruction NOP <|@ <|@
      nr   28  <|@ instruction NOP <|@ <|@
      nr   30  <|@ instruction NOP <|@ <|@
      nr   32  <|@ instruction NOP <|@ <|@
      nr   34  <|@ instruction NOP <|@ <|@
      nr   36  <|@ instruction stack:16|QWORD = MOVE input: rbp|QWORD moveKind: QWORD <|@ <|@
      nr   38  <|@ instruction [] = HOTSPOTLOCKSTACK frameMapBuilder: jdk.graal.compiler.hotspot.amd64.AMD64HotSpotFrameMapBuilder@20881f79 slotKind: QWORD <|@ <|@
      nr   40  <|@ instruction v0|QWORD[.] = MOVE input: rsi|QWORD[.] moveKind: QWORD <|@ <|@
      nr   42  <|@ instruction v1|DWORD = MOVSXB input: [v0|QWORD[.] + 12] size: DWORD <|@ <|@
      nr   44  <|@ instruction rsi|DWORD = MOVE input: v1|DWORD moveKind: DWORD <|@ <|@
      nr   46  <|@ st <@st|@live-base-pointers: []
java.lang.Byte.toString(Byte.java:443) [bci: 4]
locals: - 
>@ <|@ instruction rax|QWORD[.] = CALL_DIRECT parameters: [rsi|DWORD] temps: [] callTarget: HotSpotMethod<Integer.toString(int)> invokeKind: Static config: jdk.graal.compiler.hotspot.GraalHotSpotVMConfig@4817c460 state [bci:4] <|@ <|@
      nr   48  <|@ instruction v2|QWORD[.] = MOVE input: rax|QWORD[.] moveKind: QWORD <|@ <|@
      nr   50  <|@ instruction rax|QWORD[.] = MOVE input: v2|QWORD[.] moveKind: QWORD <|@ <|@
      nr   52  <|@ instruction RETURN (savedRbp: stack:16|QWORD, value: rax|QWORD[.]) isStub: false requiresReservedStackAccessCheck: false thread: r15 scratchForSafepointOnReturn: rcx config: jdk.graal.compiler.hotspot.GraalHotSpotVMConfig@4817c460 <|@ <|@
    end_IR
  end_block
end_cfg
begin_bytecodes
     0: aload_0       
     1: getfield      #20         // value:byte
     4: invokestatic  #0          // java.lang.Integer.toString:(int)java.lang.String
     7: areturn       
   <|@
end_bytecodes
begin_cfg
  name "After LinearScanAssignLocations"
  begin_block
    name "B0"
    from_bci -1
    to_bci -1
    predecessors 
    successors 
    xhandlers
    flags 
    probability 4607182418800017408
    begin_IR
      LIR
      nr    0  <|@ instruction [rsi|QWORD[.], rbp|QWORD] = LABEL alignment: 0 numbPhis: 0 label: ? <|@ <|@
      nr    2  <|@ instruction NOP <|@ <|@
      nr    4  <|@ instruction NOP <|@ <|@
      nr    6  <|@ instruction NOP <|@ <|@
      nr    8  <|@ instruction NOP <|@ <|@
      nr   10  <|@ instruction NOP <|@ <|@
      nr   12  <|@ instruction NOP <|@ <|@
      nr   14  <|@ instruction NOP <|@ <|@
      nr   16  <|@ instruction NOP <|@ <|@
      nr   18  <|@ instruction NOP <|@ <|@
      nr   20  <|@ instruction NOP <|@ <|@
      nr   22  <|@ instruction NOP <|@ <|@
      nr   24  <|@ instruction NOP <|@ <|@
      nr   26  <|@ instruction NOP <|@ <|@
      nr   28  <|@ instruction NOP <|@ <|@
      nr   30  <|@ instruction NOP <|@ <|@
      nr   32  <|@ instruction NOP <|@ <|@
      nr   34  <|@ instruction NOP <|@ <|@
      nr   36  <|@ instruction stack:16|QWORD = MOVE input: rbp|QWORD moveKind: QWORD <|@ <|@
      nr   38  <|@ instruction [] = HOTSPOTLOCKSTACK frameMapBuilder: jdk.graal.compiler.hotspot.amd64.AMD64HotSpotFrameMapBuilder@20881f79 slotKind: QWORD <|@ <|@
      nr   42  <|@ instruction rsi|DWORD = MOVSXB input: [rsi|QWORD[.] + 12] size: DWORD <|@ <|@
      nr   46  <|@ st <@st|@live-base-pointers: []
java.lang.Byte.toString(Byte.java:443) [bci: 4]
locals: - 
>@ <|@ instruction rax|QWORD[.] = CALL_DIRECT parameters: [rsi|DWORD] temps: [] callTarget: HotSpotMethod<Integer.toString(int)> invokeKind: Static config: jdk.graal.compiler.hotspot.GraalHotSpotVMConfig@4817c460 state [bci:4] <|@ <|@
      nr   52  <|@ instruction RETURN (savedRbp: stack:16|QWORD, value: rax|QWORD[.]) isStub: false requiresReservedStackAccessCheck: false thread: r15 scratchForSafepointOnReturn: rcx config: jdk.graal.compiler.hotspot.GraalHotSpotVMConfig@4817c460 <|@ <|@
    end_IR
  end_block
end_cfg
begin_bytecodes
     0: aload_0       
     1: getfield      #20         // value:byte
     4: invokestatic  #0          // java.lang.Integer.toString:(int)java.lang.String
     7: areturn       
   <|@
end_bytecodes
begin_cfg
  name "After LinearScan"
  begin_block
    name "B0"
    from_bci -1
    to_bci -1
    predecessors 
    successors 
    xhandlers
    flags 
    probability 4607182418800017408
    begin_IR
      LIR
      nr    0  <|@ instruction [rsi|QWORD[.], rbp|QWORD] = LABEL alignment: 0 numbPhis: 0 label: ? <|@ <|@
      nr    2  <|@ instruction NOP <|@ <|@
      nr    4  <|@ instruction NOP <|@ <|@
      nr    6  <|@ instruction NOP <|@ <|@
      nr    8  <|@ instruction NOP <|@ <|@
      nr   10  <|@ instruction NOP <|@ <|@
      nr   12  <|@ instruction NOP <|@ <|@
      nr   14  <|@ instruction NOP <|@ <|@
      nr   16  <|@ instruction NOP <|@ <|@
      nr   18  <|@ instruction NOP <|@ <|@
      nr   20  <|@ instruction NOP <|@ <|@
      nr   22  <|@ instruction NOP <|@ <|@
      nr   24  <|@ instruction NOP <|@ <|@
      nr   26  <|@ instruction NOP <|@ <|@
      nr   28  <|@ instruction NOP <|@ <|@
      nr   30  <|@ instruction NOP <|@ <|@
      nr   32  <|@ instruction NOP <|@ <|@
      nr   34  <|@ instruction NOP <|@ <|@
      nr   36  <|@ instruction stack:16|QWORD = MOVE input: rbp|QWORD moveKind: QWORD <|@ <|@
      nr   38  <|@ instruction [] = HOTSPOTLOCKSTACK frameMapBuilder: jdk.graal.compiler.hotspot.amd64.AMD64HotSpotFrameMapBuilder@20881f79 slotKind: QWORD <|@ <|@
      nr   42  <|@ instruction rsi|DWORD = MOVSXB input: [rsi|QWORD[.] + 12] size: DWORD <|@ <|@
      nr   46  <|@ st <@st|@live-base-pointers: []
java.lang.Byte.toString(Byte.java:443) [bci: 4]
locals: - 
>@ <|@ instruction rax|QWORD[.] = CALL_DIRECT parameters: [rsi|DWORD] temps: [] callTarget: HotSpotMethod<Integer.toString(int)> invokeKind: Static config: jdk.graal.compiler.hotspot.GraalHotSpotVMConfig@4817c460 state [bci:4] <|@ <|@
      nr   52  <|@ instruction RETURN (savedRbp: stack:16|QWORD, value: rax|QWORD[.]) isStub: false requiresReservedStackAccessCheck: false thread: r15 scratchForSafepointOnReturn: rcx config: jdk.graal.compiler.hotspot.GraalHotSpotVMConfig@4817c460 <|@ <|@
    end_IR
  end_block
end_cfg
begin_bytecodes
     0: aload_0       
     1: getfield      #20         // value:byte
     4: invokestatic  #0          // java.lang.Integer.toString:(int)java.lang.String
     7: areturn       
   <|@
end_bytecodes
begin_cfg
  name "After LSStackSlotAllocator"
  begin_block
    name "B0"
    from_bci -1
    to_bci -1
    predecessors 
    successors 
    xhandlers
    flags 
    probability 4607182418800017408
    begin_IR
      LIR
      nr    0  <|@ instruction [rsi|QWORD[.], rbp|QWORD] = LABEL alignment: 0 numbPhis: 0 label: ? <|@ <|@
      nr    2  <|@ instruction NOP <|@ <|@
      nr    4  <|@ instruction NOP <|@ <|@
      nr    6  <|@ instruction NOP <|@ <|@
      nr    8  <|@ instruction NOP <|@ <|@
      nr   10  <|@ instruction NOP <|@ <|@
      nr   12  <|@ instruction NOP <|@ <|@
      nr   14  <|@ instruction NOP <|@ <|@
      nr   16  <|@ instruction NOP <|@ <|@
      nr   18  <|@ instruction NOP <|@ <|@
      nr   20  <|@ instruction NOP <|@ <|@
      nr   22  <|@ instruction NOP <|@ <|@
      nr   24  <|@ instruction NOP <|@ <|@
      nr   26  <|@ instruction NOP <|@ <|@
      nr   28  <|@ instruction NOP <|@ <|@
      nr   30  <|@ instruction NOP <|@ <|@
      nr   32  <|@ instruction NOP <|@ <|@
      nr   34  <|@ instruction NOP <|@ <|@
      nr   36  <|@ instruction stack:16|QWORD = MOVE input: rbp|QWORD moveKind: QWORD <|@ <|@
      nr   38  <|@ instruction [] = HOTSPOTLOCKSTACK frameMapBuilder: jdk.graal.compiler.hotspot.amd64.AMD64HotSpotFrameMapBuilder@20881f79 slotKind: QWORD <|@ <|@
      nr   42  <|@ instruction rsi|DWORD = MOVSXB input: [rsi|QWORD[.] + 12] size: DWORD <|@ <|@
      nr   46  <|@ st <@st|@live-base-pointers: []
java.lang.Byte.toString(Byte.java:443) [bci: 4]
locals: - 
>@ <|@ instruction rax|QWORD[.] = CALL_DIRECT parameters: [rsi|DWORD] temps: [] callTarget: HotSpotMethod<Integer.toString(int)> invokeKind: Static config: jdk.graal.compiler.hotspot.GraalHotSpotVMConfig@4817c460 state [bci:4] <|@ <|@
      nr   52  <|@ instruction RETURN (savedRbp: stack:16|QWORD, value: rax|QWORD[.]) isStub: false requiresReservedStackAccessCheck: false thread: r15 scratchForSafepointOnReturn: rcx config: jdk.graal.compiler.hotspot.GraalHotSpotVMConfig@4817c460 <|@ <|@
    end_IR
  end_block
end_cfg
begin_bytecodes
     0: aload_0       
     1: getfield      #20         // value:byte
     4: invokestatic  #0          // java.lang.Integer.toString:(int)java.lang.String
     7: areturn       
   <|@
end_bytecodes
begin_cfg
  name "After AllocationStage"
  begin_block
    name "B0"
    from_bci -1
    to_bci -1
    predecessors 
    successors 
    xhandlers
    flags 
    probability 4607182418800017408
    begin_IR
      LIR
      nr    0  <|@ instruction [rsi|QWORD[.], rbp|QWORD] = LABEL alignment: 0 numbPhis: 0 label: ? <|@ <|@
      nr    2  <|@ instruction NOP <|@ <|@
      nr    4  <|@ instruction NOP <|@ <|@
      nr    6  <|@ instruction NOP <|@ <|@
      nr    8  <|@ instruction NOP <|@ <|@
      nr   10  <|@ instruction NOP <|@ <|@
      nr   12  <|@ instruction NOP <|@ <|@
      nr   14  <|@ instruction NOP <|@ <|@
      nr   16  <|@ instruction NOP <|@ <|@
      nr   18  <|@ instruction NOP <|@ <|@
      nr   20  <|@ instruction NOP <|@ <|@
      nr   22  <|@ instruction NOP <|@ <|@
      nr   24  <|@ instruction NOP <|@ <|@
      nr   26  <|@ instruction NOP <|@ <|@
      nr   28  <|@ instruction NOP <|@ <|@
      nr   30  <|@ instruction NOP <|@ <|@
      nr   32  <|@ instruction NOP <|@ <|@
      nr   34  <|@ instruction NOP <|@ <|@
      nr   36  <|@ instruction stack:16|QWORD = MOVE input: rbp|QWORD moveKind: QWORD <|@ <|@
      nr   38  <|@ instruction [] = HOTSPOTLOCKSTACK frameMapBuilder: jdk.graal.compiler.hotspot.amd64.AMD64HotSpotFrameMapBuilder@20881f79 slotKind: QWORD <|@ <|@
      nr   42  <|@ instruction rsi|DWORD = MOVSXB input: [rsi|QWORD[.] + 12] size: DWORD <|@ <|@
      nr   46  <|@ st <@st|@live-base-pointers: []
java.lang.Byte.toString(Byte.java:443) [bci: 4]
locals: - 
>@ <|@ instruction rax|QWORD[.] = CALL_DIRECT parameters: [rsi|DWORD] temps: [] callTarget: HotSpotMethod<Integer.toString(int)> invokeKind: Static config: jdk.graal.compiler.hotspot.GraalHotSpotVMConfig@4817c460 state [bci:4] <|@ <|@
      nr   52  <|@ instruction RETURN (savedRbp: stack:16|QWORD, value: rax|QWORD[.]) isStub: false requiresReservedStackAccessCheck: false thread: r15 scratchForSafepointOnReturn: rcx config: jdk.graal.compiler.hotspot.GraalHotSpotVMConfig@4817c460 <|@ <|@
    end_IR
  end_block
end_cfg
begin_bytecodes
     0: aload_0       
     1: getfield      #20         // value:byte
     4: invokestatic  #0          // java.lang.Integer.toString:(int)java.lang.String
     7: areturn       
   <|@
end_bytecodes
begin_cfg
  name "After EdgeMoveOptimizer"
  begin_block
    name "B0"
    from_bci -1
    to_bci -1
    predecessors 
    successors 
    xhandlers
    flags 
    probability 4607182418800017408
    begin_IR
      LIR
      nr    0  <|@ instruction [rsi|QWORD[.], rbp|QWORD] = LABEL alignment: 0 numbPhis: 0 label: ? <|@ <|@
      nr    2  <|@ instruction NOP <|@ <|@
      nr    4  <|@ instruction NOP <|@ <|@
      nr    6  <|@ instruction NOP <|@ <|@
      nr    8  <|@ instruction NOP <|@ <|@
      nr   10  <|@ instruction NOP <|@ <|@
      nr   12  <|@ instruction NOP <|@ <|@
      nr   14  <|@ instruction NOP <|@ <|@
      nr   16  <|@ instruction NOP <|@ <|@
      nr   18  <|@ instruction NOP <|@ <|@
      nr   20  <|@ instruction NOP <|@ <|@
      nr   22  <|@ instruction NOP <|@ <|@
      nr   24  <|@ instruction NOP <|@ <|@
      nr   26  <|@ instruction NOP <|@ <|@
      nr   28  <|@ instruction NOP <|@ <|@
      nr   30  <|@ instruction NOP <|@ <|@
      nr   32  <|@ instruction NOP <|@ <|@
      nr   34  <|@ instruction NOP <|@ <|@
      nr   36  <|@ instruction stack:16|QWORD = MOVE input: rbp|QWORD moveKind: QWORD <|@ <|@
      nr   38  <|@ instruction [] = HOTSPOTLOCKSTACK frameMapBuilder: jdk.graal.compiler.hotspot.amd64.AMD64HotSpotFrameMapBuilder@20881f79 slotKind: QWORD <|@ <|@
      nr   42  <|@ instruction rsi|DWORD = MOVSXB input: [rsi|QWORD[.] + 12] size: DWORD <|@ <|@
      nr   46  <|@ st <@st|@live-base-pointers: []
java.lang.Byte.toString(Byte.java:443) [bci: 4]
locals: - 
>@ <|@ instruction rax|QWORD[.] = CALL_DIRECT parameters: [rsi|DWORD] temps: [] callTarget: HotSpotMethod<Integer.toString(int)> invokeKind: Static config: jdk.graal.compiler.hotspot.GraalHotSpotVMConfig@4817c460 state [bci:4] <|@ <|@
      nr   52  <|@ instruction RETURN (savedRbp: stack:16|QWORD, value: rax|QWORD[.]) isStub: false requiresReservedStackAccessCheck: false thread: r15 scratchForSafepointOnReturn: rcx config: jdk.graal.compiler.hotspot.GraalHotSpotVMConfig@4817c460 <|@ <|@
    end_IR
  end_block
end_cfg
begin_bytecodes
     0: aload_0       
     1: getfield      #20         // value:byte
     4: invokestatic  #0          // java.lang.Integer.toString:(int)java.lang.String
     7: areturn       
   <|@
end_bytecodes
begin_cfg
  name "After RedundantMoveElimination"
  begin_block
    name "B0"
    from_bci -1
    to_bci -1
    predecessors 
    successors 
    xhandlers
    flags 
    probability 4607182418800017408
    begin_IR
      LIR
      nr    0  <|@ instruction [rsi|QWORD[.], rbp|QWORD] = LABEL alignment: 0 numbPhis: 0 label: ? <|@ <|@
      nr    2  <|@ instruction NOP <|@ <|@
      nr    4  <|@ instruction NOP <|@ <|@
      nr    6  <|@ instruction NOP <|@ <|@
      nr    8  <|@ instruction NOP <|@ <|@
      nr   10  <|@ instruction NOP <|@ <|@
      nr   12  <|@ instruction NOP <|@ <|@
      nr   14  <|@ instruction NOP <|@ <|@
      nr   16  <|@ instruction NOP <|@ <|@
      nr   18  <|@ instruction NOP <|@ <|@
      nr   20  <|@ instruction NOP <|@ <|@
      nr   22  <|@ instruction NOP <|@ <|@
      nr   24  <|@ instruction NOP <|@ <|@
      nr   26  <|@ instruction NOP <|@ <|@
      nr   28  <|@ instruction NOP <|@ <|@
      nr   30  <|@ instruction NOP <|@ <|@
      nr   32  <|@ instruction NOP <|@ <|@
      nr   34  <|@ instruction NOP <|@ <|@
      nr   36  <|@ instruction stack:16|QWORD = MOVE input: rbp|QWORD moveKind: QWORD <|@ <|@
      nr   38  <|@ instruction [] = HOTSPOTLOCKSTACK frameMapBuilder: jdk.graal.compiler.hotspot.amd64.AMD64HotSpotFrameMapBuilder@20881f79 slotKind: QWORD <|@ <|@
      nr   42  <|@ instruction rsi|DWORD = MOVSXB input: [rsi|QWORD[.] + 12] size: DWORD <|@ <|@
      nr   46  <|@ st <@st|@live-base-pointers: []
java.lang.Byte.toString(Byte.java:443) [bci: 4]
locals: - 
>@ <|@ instruction rax|QWORD[.] = CALL_DIRECT parameters: [rsi|DWORD] temps: [] callTarget: HotSpotMethod<Integer.toString(int)> invokeKind: Static config: jdk.graal.compiler.hotspot.GraalHotSpotVMConfig@4817c460 state [bci:4] <|@ <|@
      nr   52  <|@ instruction RETURN (savedRbp: stack:16|QWORD, value: rax|QWORD[.]) isStub: false requiresReservedStackAccessCheck: false thread: r15 scratchForSafepointOnReturn: rcx config: jdk.graal.compiler.hotspot.GraalHotSpotVMConfig@4817c460 <|@ <|@
    end_IR
  end_block
end_cfg
begin_bytecodes
     0: aload_0       
     1: getfield      #20         // value:byte
     4: invokestatic  #0          // java.lang.Integer.toString:(int)java.lang.String
     7: areturn       
   <|@
end_bytecodes
begin_cfg
  name "After NullCheckOptimizer"
  begin_block
    name "B0"
    from_bci -1
    to_bci -1
    predecessors 
    successors 
    xhandlers
    flags 
    probability 4607182418800017408
    begin_IR
      LIR
      nr    0  <|@ instruction [rsi|QWORD[.], rbp|QWORD] = LABEL alignment: 0 numbPhis: 0 label: ? <|@ <|@
      nr    2  <|@ instruction NOP <|@ <|@
      nr    4  <|@ instruction NOP <|@ <|@
      nr    6  <|@ instruction NOP <|@ <|@
      nr    8  <|@ instruction NOP <|@ <|@
      nr   10  <|@ instruction NOP <|@ <|@
      nr   12  <|@ instruction NOP <|@ <|@
      nr   14  <|@ instruction NOP <|@ <|@
      nr   16  <|@ instruction NOP <|@ <|@
      nr   18  <|@ instruction NOP <|@ <|@
      nr   20  <|@ instruction NOP <|@ <|@
      nr   22  <|@ instruction NOP <|@ <|@
      nr   24  <|@ instruction NOP <|@ <|@
      nr   26  <|@ instruction NOP <|@ <|@
      nr   28  <|@ instruction NOP <|@ <|@
      nr   30  <|@ instruction NOP <|@ <|@
      nr   32  <|@ instruction NOP <|@ <|@
      nr   34  <|@ instruction NOP <|@ <|@
      nr   36  <|@ instruction stack:16|QWORD = MOVE input: rbp|QWORD moveKind: QWORD <|@ <|@
      nr   38  <|@ instruction [] = HOTSPOTLOCKSTACK frameMapBuilder: jdk.graal.compiler.hotspot.amd64.AMD64HotSpotFrameMapBuilder@20881f79 slotKind: QWORD <|@ <|@
      nr   42  <|@ instruction rsi|DWORD = MOVSXB input: [rsi|QWORD[.] + 12] size: DWORD <|@ <|@
      nr   46  <|@ st <@st|@live-base-pointers: []
java.lang.Byte.toString(Byte.java:443) [bci: 4]
locals: - 
>@ <|@ instruction rax|QWORD[.] = CALL_DIRECT parameters: [rsi|DWORD] temps: [] callTarget: HotSpotMethod<Integer.toString(int)> invokeKind: Static config: jdk.graal.compiler.hotspot.GraalHotSpotVMConfig@4817c460 state [bci:4] <|@ <|@
      nr   52  <|@ instruction RETURN (savedRbp: stack:16|QWORD, value: rax|QWORD[.]) isStub: false requiresReservedStackAccessCheck: false thread: r15 scratchForSafepointOnReturn: rcx config: jdk.graal.compiler.hotspot.GraalHotSpotVMConfig@4817c460 <|@ <|@
    end_IR
  end_block
end_cfg
begin_bytecodes
     0: aload_0       
     1: getfield      #20         // value:byte
     4: invokestatic  #0          // java.lang.Integer.toString:(int)java.lang.String
     7: areturn       
   <|@
end_bytecodes
begin_cfg
  name "After ControlFlowOptimizer"
  begin_block
    name "B0"
    from_bci -1
    to_bci -1
    predecessors 
    successors 
    xhandlers
    flags 
    probability 4607182418800017408
    begin_IR
      LIR
      nr    0  <|@ instruction [rsi|QWORD[.], rbp|QWORD] = LABEL alignment: 0 numbPhis: 0 label: ? <|@ <|@
      nr    2  <|@ instruction NOP <|@ <|@
      nr    4  <|@ instruction NOP <|@ <|@
      nr    6  <|@ instruction NOP <|@ <|@
      nr    8  <|@ instruction NOP <|@ <|@
      nr   10  <|@ instruction NOP <|@ <|@
      nr   12  <|@ instruction NOP <|@ <|@
      nr   14  <|@ instruction NOP <|@ <|@
      nr   16  <|@ instruction NOP <|@ <|@
      nr   18  <|@ instruction NOP <|@ <|@
      nr   20  <|@ instruction NOP <|@ <|@
      nr   22  <|@ instruction NOP <|@ <|@
      nr   24  <|@ instruction NOP <|@ <|@
      nr   26  <|@ instruction NOP <|@ <|@
      nr   28  <|@ instruction NOP <|@ <|@
      nr   30  <|@ instruction NOP <|@ <|@
      nr   32  <|@ instruction NOP <|@ <|@
      nr   34  <|@ instruction NOP <|@ <|@
      nr   36  <|@ instruction stack:16|QWORD = MOVE input: rbp|QWORD moveKind: QWORD <|@ <|@
      nr   38  <|@ instruction [] = HOTSPOTLOCKSTACK frameMapBuilder: jdk.graal.compiler.hotspot.amd64.AMD64HotSpotFrameMapBuilder@20881f79 slotKind: QWORD <|@ <|@
      nr   42  <|@ instruction rsi|DWORD = MOVSXB input: [rsi|QWORD[.] + 12] size: DWORD <|@ <|@
      nr   46  <|@ st <@st|@live-base-pointers: []
java.lang.Byte.toString(Byte.java:443) [bci: 4]
locals: - 
>@ <|@ instruction rax|QWORD[.] = CALL_DIRECT parameters: [rsi|DWORD] temps: [] callTarget: HotSpotMethod<Integer.toString(int)> invokeKind: Static config: jdk.graal.compiler.hotspot.GraalHotSpotVMConfig@4817c460 state [bci:4] <|@ <|@
      nr   52  <|@ instruction RETURN (savedRbp: stack:16|QWORD, value: rax|QWORD[.]) isStub: false requiresReservedStackAccessCheck: false thread: r15 scratchForSafepointOnReturn: rcx config: jdk.graal.compiler.hotspot.GraalHotSpotVMConfig@4817c460 <|@ <|@
    end_IR
  end_block
end_cfg
begin_bytecodes
     0: aload_0       
     1: getfield      #20         // value:byte
     4: invokestatic  #0          // java.lang.Integer.toString:(int)java.lang.String
     7: areturn       
   <|@
end_bytecodes
begin_cfg
  name "After ComputeCodeEmissionOrder"
  begin_block
    name "B0"
    from_bci -1
    to_bci -1
    predecessors 
    successors 
    xhandlers
    flags 
    probability 4607182418800017408
    begin_IR
      LIR
      nr    0  <|@ instruction [rsi|QWORD[.], rbp|QWORD] = LABEL alignment: 0 numbPhis: 0 label: ? <|@ <|@
      nr    2  <|@ instruction NOP <|@ <|@
      nr    4  <|@ instruction NOP <|@ <|@
      nr    6  <|@ instruction NOP <|@ <|@
      nr    8  <|@ instruction NOP <|@ <|@
      nr   10  <|@ instruction NOP <|@ <|@
      nr   12  <|@ instruction NOP <|@ <|@
      nr   14  <|@ instruction NOP <|@ <|@
      nr   16  <|@ instruction NOP <|@ <|@
      nr   18  <|@ instruction NOP <|@ <|@
      nr   20  <|@ instruction NOP <|@ <|@
      nr   22  <|@ instruction NOP <|@ <|@
      nr   24  <|@ instruction NOP <|@ <|@
      nr   26  <|@ instruction NOP <|@ <|@
      nr   28  <|@ instruction NOP <|@ <|@
      nr   30  <|@ instruction NOP <|@ <|@
      nr   32  <|@ instruction NOP <|@ <|@
      nr   34  <|@ instruction NOP <|@ <|@
      nr   36  <|@ instruction stack:16|QWORD = MOVE input: rbp|QWORD moveKind: QWORD <|@ <|@
      nr   38  <|@ instruction [] = HOTSPOTLOCKSTACK frameMapBuilder: jdk.graal.compiler.hotspot.amd64.AMD64HotSpotFrameMapBuilder@20881f79 slotKind: QWORD <|@ <|@
      nr   42  <|@ instruction rsi|DWORD = MOVSXB input: [rsi|QWORD[.] + 12] size: DWORD <|@ <|@
      nr   46  <|@ st <@st|@live-base-pointers: []
java.lang.Byte.toString(Byte.java:443) [bci: 4]
locals: - 
>@ <|@ instruction rax|QWORD[.] = CALL_DIRECT parameters: [rsi|DWORD] temps: [] callTarget: HotSpotMethod<Integer.toString(int)> invokeKind: Static config: jdk.graal.compiler.hotspot.GraalHotSpotVMConfig@4817c460 state [bci:4] <|@ <|@
      nr   52  <|@ instruction RETURN (savedRbp: stack:16|QWORD, value: rax|QWORD[.]) isStub: false requiresReservedStackAccessCheck: false thread: r15 scratchForSafepointOnReturn: rcx config: jdk.graal.compiler.hotspot.GraalHotSpotVMConfig@4817c460 <|@ <|@
    end_IR
  end_block
end_cfg
begin_bytecodes
     0: aload_0       
     1: getfield      #20         // value:byte
     4: invokestatic  #0          // java.lang.Integer.toString:(int)java.lang.String
     7: areturn       
   <|@
end_bytecodes
begin_cfg
  name "After StackMoveOptimization"
  begin_block
    name "B0"
    from_bci -1
    to_bci -1
    predecessors 
    successors 
    xhandlers
    flags 
    probability 4607182418800017408
    begin_IR
      LIR
      nr    0  <|@ instruction [rsi|QWORD[.], rbp|QWORD] = LABEL alignment: 0 numbPhis: 0 label: ? <|@ <|@
      nr    2  <|@ instruction NOP <|@ <|@
      nr    4  <|@ instruction NOP <|@ <|@
      nr    6  <|@ instruction NOP <|@ <|@
      nr    8  <|@ instruction NOP <|@ <|@
      nr   10  <|@ instruction NOP <|@ <|@
      nr   12  <|@ instruction NOP <|@ <|@
      nr   14  <|@ instruction NOP <|@ <|@
      nr   16  <|@ instruction NOP <|@ <|@
      nr   18  <|@ instruction NOP <|@ <|@
      nr   20  <|@ instruction NOP <|@ <|@
      nr   22  <|@ instruction NOP <|@ <|@
      nr   24  <|@ instruction NOP <|@ <|@
      nr   26  <|@ instruction NOP <|@ <|@
      nr   28  <|@ instruction NOP <|@ <|@
      nr   30  <|@ instruction NOP <|@ <|@
      nr   32  <|@ instruction NOP <|@ <|@
      nr   34  <|@ instruction NOP <|@ <|@
      nr   36  <|@ instruction stack:16|QWORD = MOVE input: rbp|QWORD moveKind: QWORD <|@ <|@
      nr   38  <|@ instruction [] = HOTSPOTLOCKSTACK frameMapBuilder: jdk.graal.compiler.hotspot.amd64.AMD64HotSpotFrameMapBuilder@20881f79 slotKind: QWORD <|@ <|@
      nr   42  <|@ instruction rsi|DWORD = MOVSXB input: [rsi|QWORD[.] + 12] size: DWORD <|@ <|@
      nr   46  <|@ st <@st|@live-base-pointers: []
java.lang.Byte.toString(Byte.java:443) [bci: 4]
locals: - 
>@ <|@ instruction rax|QWORD[.] = CALL_DIRECT parameters: [rsi|DWORD] temps: [] callTarget: HotSpotMethod<Integer.toString(int)> invokeKind: Static config: jdk.graal.compiler.hotspot.GraalHotSpotVMConfig@4817c460 state [bci:4] <|@ <|@
      nr   52  <|@ instruction RETURN (savedRbp: stack:16|QWORD, value: rax|QWORD[.]) isStub: false requiresReservedStackAccessCheck: false thread: r15 scratchForSafepointOnReturn: rcx config: jdk.graal.compiler.hotspot.GraalHotSpotVMConfig@4817c460 <|@ <|@
    end_IR
  end_block
end_cfg
begin_bytecodes
     0: aload_0       
     1: getfield      #20         // value:byte
     4: invokestatic  #0          // java.lang.Integer.toString:(int)java.lang.String
     7: areturn       
   <|@
end_bytecodes
begin_cfg
  name "After PostAllocationOptimizationStage"
  begin_block
    name "B0"
    from_bci -1
    to_bci -1
    predecessors 
    successors 
    xhandlers
    flags 
    probability 4607182418800017408
    begin_IR
      LIR
      nr    0  <|@ instruction [rsi|QWORD[.], rbp|QWORD] = LABEL alignment: 0 numbPhis: 0 label: ? <|@ <|@
      nr    2  <|@ instruction NOP <|@ <|@
      nr    4  <|@ instruction NOP <|@ <|@
      nr    6  <|@ instruction NOP <|@ <|@
      nr    8  <|@ instruction NOP <|@ <|@
      nr   10  <|@ instruction NOP <|@ <|@
      nr   12  <|@ instruction NOP <|@ <|@
      nr   14  <|@ instruction NOP <|@ <|@
      nr   16  <|@ instruction NOP <|@ <|@
      nr   18  <|@ instruction NOP <|@ <|@
      nr   20  <|@ instruction NOP <|@ <|@
      nr   22  <|@ instruction NOP <|@ <|@
      nr   24  <|@ instruction NOP <|@ <|@
      nr   26  <|@ instruction NOP <|@ <|@
      nr   28  <|@ instruction NOP <|@ <|@
      nr   30  <|@ instruction NOP <|@ <|@
      nr   32  <|@ instruction NOP <|@ <|@
      nr   34  <|@ instruction NOP <|@ <|@
      nr   36  <|@ instruction stack:16|QWORD = MOVE input: rbp|QWORD moveKind: QWORD <|@ <|@
      nr   38  <|@ instruction [] = HOTSPOTLOCKSTACK frameMapBuilder: jdk.graal.compiler.hotspot.amd64.AMD64HotSpotFrameMapBuilder@20881f79 slotKind: QWORD <|@ <|@
      nr   42  <|@ instruction rsi|DWORD = MOVSXB input: [rsi|QWORD[.] + 12] size: DWORD <|@ <|@
      nr   46  <|@ st <@st|@live-base-pointers: []
java.lang.Byte.toString(Byte.java:443) [bci: 4]
locals: - 
>@ <|@ instruction rax|QWORD[.] = CALL_DIRECT parameters: [rsi|DWORD] temps: [] callTarget: HotSpotMethod<Integer.toString(int)> invokeKind: Static config: jdk.graal.compiler.hotspot.GraalHotSpotVMConfig@4817c460 state [bci:4] <|@ <|@
      nr   52  <|@ instruction RETURN (savedRbp: stack:16|QWORD, value: rax|QWORD[.]) isStub: false requiresReservedStackAccessCheck: false thread: r15 scratchForSafepointOnReturn: rcx config: jdk.graal.compiler.hotspot.GraalHotSpotVMConfig@4817c460 <|@ <|@
    end_IR
  end_block
end_cfg
begin_bytecodes
     0: aload_0       
     1: getfield      #20         // value:byte
     4: invokestatic  #0          // java.lang.Integer.toString:(int)java.lang.String
     7: areturn       
   <|@
end_bytecodes
begin_cfg
  name "After LocationMarker"
  begin_block
    name "B0"
    from_bci -1
    to_bci -1
    predecessors 
    successors 
    xhandlers
    flags 
    probability 4607182418800017408
    begin_IR
      LIR
      nr    0  <|@ instruction [rsi|QWORD[.], rbp|QWORD] = LABEL alignment: 0 numbPhis: 0 label: ? <|@ <|@
      nr    2  <|@ instruction NOP <|@ <|@
      nr    4  <|@ instruction NOP <|@ <|@
      nr    6  <|@ instruction NOP <|@ <|@
      nr    8  <|@ instruction NOP <|@ <|@
      nr   10  <|@ instruction NOP <|@ <|@
      nr   12  <|@ instruction NOP <|@ <|@
      nr   14  <|@ instruction NOP <|@ <|@
      nr   16  <|@ instruction NOP <|@ <|@
      nr   18  <|@ instruction NOP <|@ <|@
      nr   20  <|@ instruction NOP <|@ <|@
      nr   22  <|@ instruction NOP <|@ <|@
      nr   24  <|@ instruction NOP <|@ <|@
      nr   26  <|@ instruction NOP <|@ <|@
      nr   28  <|@ instruction NOP <|@ <|@
      nr   30  <|@ instruction NOP <|@ <|@
      nr   32  <|@ instruction NOP <|@ <|@
      nr   34  <|@ instruction NOP <|@ <|@
      nr   36  <|@ instruction stack:16|QWORD = MOVE input: rbp|QWORD moveKind: QWORD <|@ <|@
      nr   38  <|@ instruction [] = HOTSPOTLOCKSTACK frameMapBuilder: jdk.graal.compiler.hotspot.amd64.AMD64HotSpotFrameMapBuilder@20881f79 slotKind: QWORD <|@ <|@
      nr   42  <|@ instruction rsi|DWORD = MOVSXB input: [rsi|QWORD[.] + 12] size: DWORD <|@ <|@
      nr   46  <|@ st <@st|@reference-map: []
live-base-pointers: []
java.lang.Byte.toString(Byte.java:443) [bci: 4]
locals: - 
>@ <|@ instruction rax|QWORD[.] = CALL_DIRECT parameters: [rsi|DWORD] temps: [] callTarget: HotSpotMethod<Integer.toString(int)> invokeKind: Static config: jdk.graal.compiler.hotspot.GraalHotSpotVMConfig@4817c460 state [bci:4] <|@ <|@
      nr   52  <|@ instruction RETURN (savedRbp: stack:16|QWORD, value: rax|QWORD[.]) isStub: false requiresReservedStackAccessCheck: false thread: r15 scratchForSafepointOnReturn: rcx config: jdk.graal.compiler.hotspot.GraalHotSpotVMConfig@4817c460 <|@ <|@
    end_IR
  end_block
end_cfg
begin_bytecodes
     0: aload_0       
     1: getfield      #20         // value:byte
     4: invokestatic  #0          // java.lang.Integer.toString:(int)java.lang.String
     7: areturn       
   <|@
end_bytecodes
begin_cfg
  name "After FinalCodeAnalysisStage"
  begin_block
    name "B0"
    from_bci -1
    to_bci -1
    predecessors 
    successors 
    xhandlers
    flags 
    probability 4607182418800017408
    begin_IR
      LIR
      nr    0  <|@ instruction [rsi|QWORD[.], rbp|QWORD] = LABEL alignment: 0 numbPhis: 0 label: ? <|@ <|@
      nr    2  <|@ instruction NOP <|@ <|@
      nr    4  <|@ instruction NOP <|@ <|@
      nr    6  <|@ instruction NOP <|@ <|@
      nr    8  <|@ instruction NOP <|@ <|@
      nr   10  <|@ instruction NOP <|@ <|@
      nr   12  <|@ instruction NOP <|@ <|@
      nr   14  <|@ instruction NOP <|@ <|@
      nr   16  <|@ instruction NOP <|@ <|@
      nr   18  <|@ instruction NOP <|@ <|@
      nr   20  <|@ instruction NOP <|@ <|@
      nr   22  <|@ instruction NOP <|@ <|@
      nr   24  <|@ instruction NOP <|@ <|@
      nr   26  <|@ instruction NOP <|@ <|@
      nr   28  <|@ instruction NOP <|@ <|@
      nr   30  <|@ instruction NOP <|@ <|@
      nr   32  <|@ instruction NOP <|@ <|@
      nr   34  <|@ instruction NOP <|@ <|@
      nr   36  <|@ instruction stack:16|QWORD = MOVE input: rbp|QWORD moveKind: QWORD <|@ <|@
      nr   38  <|@ instruction [] = HOTSPOTLOCKSTACK frameMapBuilder: jdk.graal.compiler.hotspot.amd64.AMD64HotSpotFrameMapBuilder@20881f79 slotKind: QWORD <|@ <|@
      nr   42  <|@ instruction rsi|DWORD = MOVSXB input: [rsi|QWORD[.] + 12] size: DWORD <|@ <|@
      nr   46  <|@ st <@st|@reference-map: []
live-base-pointers: []
java.lang.Byte.toString(Byte.java:443) [bci: 4]
locals: - 
>@ <|@ instruction rax|QWORD[.] = CALL_DIRECT parameters: [rsi|DWORD] temps: [] callTarget: HotSpotMethod<Integer.toString(int)> invokeKind: Static config: jdk.graal.compiler.hotspot.GraalHotSpotVMConfig@4817c460 state [bci:4] <|@ <|@
      nr   52  <|@ instruction RETURN (savedRbp: stack:16|QWORD, value: rax|QWORD[.]) isStub: false requiresReservedStackAccessCheck: false thread: r15 scratchForSafepointOnReturn: rcx config: jdk.graal.compiler.hotspot.GraalHotSpotVMConfig@4817c460 <|@ <|@
    end_IR
  end_block
end_cfg
begin_bytecodes
     0: aload_0       
     1: getfield      #20         // value:byte
     4: invokestatic  #0          // java.lang.Integer.toString:(int)java.lang.String
     7: areturn       
   <|@
end_bytecodes
begin_cfg
  name "After code generation"
end_cfg
begin_nmethod
  <<<HexCodeFile
  Platform AMD64 64  <||@
  HexCode 0 448b560849bc0000002b787f00004d03d44d33e4493bc20f85e3ffffff66669089842400c0feff4883ec189041817f20000000000f8541000000909090909090909090909090909090909048896c24100fbe760c666690e8000000000f1f840000000000488b6c24104883c418493ba7500400000f870e000000c348896c2410e800000000ebb3f4488d0ddeffffff49898f68040000e965fffffff4e800000000f4e800000000f4  <||@
  Comment 0 UNVERIFIED_ENTRY  <||@
  Comment 23 {Field[name=CompilerToVM::Data::SharedRuntime_ic_miss_stub, type=address, offset=0, address=0x7f78b20335c8, value=140155947602048]:0x7f7899785080}  <||@
  Comment 32 [stack overflow check]  <||@
  Comment 32 VERIFIED_ENTRY  <||@
  Comment 44 FRAME_COMPLETE  <||@
  Comment 44 ENTRY_BARRIER_PATCH  <||@
  Comment 58 block B0 null  <||@
  Comment 58 0 [rsi|QWORD[.], rbp|QWORD] = LABEL alignment: 0 numbPhis: 0 label: ?  <||@
  Comment 58 2 NOP  <||@
  Comment 59 4 NOP  <||@
  Comment 60 6 NOP  <||@
  Comment 61 8 NOP  <||@
  Comment 62 10 NOP  <||@
  Comment 63 12 NOP  <||@
  Comment 64 14 NOP  <||@
  Comment 65 16 NOP  <||@
  Comment 66 18 NOP  <||@
  Comment 67 20 NOP  <||@
  Comment 68 22 NOP  <||@
  Comment 69 24 NOP  <||@
  Comment 70 26 NOP  <||@
  Comment 71 28 NOP  <||@
  Comment 72 30 NOP  <||@
  Comment 73 32 NOP  <||@
  Comment 74 34 NOP  <||@
  Comment 75 36 stack:16|QWORD = MOVE input: rbp|QWORD moveKind: QWORD  <||@
  Comment 80 38 [] = HOTSPOTLOCKSTACK frameMapBuilder: jdk.graal.compiler.hotspot.amd64.AMD64HotSpotFrameMapBuilder@20881f79 slotKind: QWORD  <||@
  Comment 80 42 rsi|DWORD = MOVSXB input: [rsi|QWORD[.] + 12] size: DWORD  <||@
  Comment 84 46 rax|QWORD[.] = CALL_DIRECT parameters: [rsi|DWORD] temps: [] callTarget: HotSpotMethod<Integer.toString(int)> invokeKind: Static config: jdk.graal.compiler.hotspot.GraalHotSpotVMConfig@4817c460 state [bci:4]  <||@
  Comment 87 {HotSpotMethod<Integer.toString(int)>}  <||@
  Comment 87 INVOKESTATIC  <||@
  Comment 92 []at java.lang.Byte.toString(Byte.java:443) [bci: 4, duringCall: true, rethrow: false]
              |0 
     locals:  |-   <||@
  Comment 100 52 RETURN (savedRbp: stack:16|QWORD, value: rax|QWORD[.]) isStub: false requiresReservedStackAccessCheck: false thread: r15 scratchForSafepointOnReturn: rcx config: jdk.graal.compiler.hotspot.GraalHotSpotVMConfig@4817c460  <||@
  Comment 109 POLL_RETURN_FAR  <||@
  Comment 128 {Field[name=CompilerToVM::Data::nmethod_entry_barrier, type=address, offset=0, address=0x7f78b2033598, value=140155947495968]:0x7f789976b220}  <||@
  Comment 150 {Field[name=CompilerToVM::Data::SharedRuntime_polling_page_return_handler, type=address, offset=0, address=0x7f78b20335a0, value=140155947630592]:0x7f789978c000}  <||@
  Comment 156 {Stub<ExceptionHandlerStub.exceptionHandler>@0x7f78998c5300:CallingConvention[rax|QWORD[.], rdx|QWORD]:CallingConvention[rax|QWORD[.], rdx|QWORD]; temps=rdi|ILLEGAL,xmm14|ILLEGAL,xmm15|ILLEGAL,xmm12|ILLEGAL,xmm13|ILLEGAL,xmm10|ILLEGAL,xmm11|ILLEGAL,xmm7|ILLEGAL,xmm8|ILLEGAL,xmm9|ILLEGAL,xmm0|ILLEGAL,xmm1|ILLEGAL,xmm2|ILLEGAL,xmm3|ILLEGAL,xmm4|ILLEGAL,xmm5|ILLEGAL,xmm6|ILLEGAL,rax|ILLEGAL,rcx|ILLEGAL,rdx|ILLEGAL,rsi|ILLEGAL,r8|ILLEGAL,r9|ILLEGAL,r10|ILLEGAL,r11|ILLEGAL}  <||@
  Comment 156 EXCEPTION_HANDLER_ENTRY  <||@
  Comment 162 {Field[name=CompilerToVM::Data::SharedRuntime_deopt_blob_unpack, type=address, offset=0, address=0x7f78b20335b8, value=140155947626272]:0x7f789978af20}  <||@
  Comment 162 DEOPT_HANDLER_ENTRY  <||@
  HexCodeFile>>> <|@
end_nmethod
begin_compilation
  name " HotSpotCompilation-11145[java.lang.Byte.toString()]"
  method "HotSpotCompilation-11145[java.lang.Byte.toString()]"
  date 1724269765472
end_compilation
begin_cfg
  name "After code installation"
end_cfg
begin_nmethod
  <<<HexCodeFile
  Platform AMD64 64  <||@
  HexCode 7f789af7dd20 448b560849bc0000002b787f00004d03d44d33e4493bc20f85437380fe66669089842400c0feff4883ec189041817f20000000000f8541000000909090909090909090909090909090909048896c24100fbe760c666690e8047c80fe0f1f8400ec010000488b6c24104883c418493ba7500400000f870e000000c348896c2410e87bd47efeebb3f4488d0ddeffffff49898f68040000e945e280fef4e83f7594fef4e859d180fef448bb0000000000000000e9fbfffffff4  <||@
  Comment 0 UNVERIFIED_ENTRY  <||@
  Comment 23 {Field[name=CompilerToVM::Data::SharedRuntime_ic_miss_stub, type=address, offset=0, address=0x7f78b20335c8, value=140155947602048]:0x7f7899785080}  <||@
  Comment 32 [stack overflow check]  <||@
  Comment 32 VERIFIED_ENTRY  <||@
  Comment 44 FRAME_COMPLETE  <||@
  Comment 44 ENTRY_BARRIER_PATCH  <||@
  Comment 58 block B0 null  <||@
  Comment 58 0 [rsi|QWORD[.], rbp|QWORD] = LABEL alignment: 0 numbPhis: 0 label: ?  <||@
  Comment 58 2 NOP  <||@
  Comment 59 4 NOP  <||@
  Comment 60 6 NOP  <||@
  Comment 61 8 NOP  <||@
  Comment 62 10 NOP  <||@
  Comment 63 12 NOP  <||@
  Comment 64 14 NOP  <||@
  Comment 65 16 NOP  <||@
  Comment 66 18 NOP  <||@
  Comment 67 20 NOP  <||@
  Comment 68 22 NOP  <||@
  Comment 69 24 NOP  <||@
  Comment 70 26 NOP  <||@
  Comment 71 28 NOP  <||@
  Comment 72 30 NOP  <||@
  Comment 73 32 NOP  <||@
  Comment 74 34 NOP  <||@
  Comment 75 36 stack:16|QWORD = MOVE input: rbp|QWORD moveKind: QWORD  <||@
  Comment 80 38 [] = HOTSPOTLOCKSTACK frameMapBuilder: jdk.graal.compiler.hotspot.amd64.AMD64HotSpotFrameMapBuilder@20881f79 slotKind: QWORD  <||@
  Comment 80 42 rsi|DWORD = MOVSXB input: [rsi|QWORD[.] + 12] size: DWORD  <||@
  Comment 84 46 rax|QWORD[.] = CALL_DIRECT parameters: [rsi|DWORD] temps: [] callTarget: HotSpotMethod<Integer.toString(int)> invokeKind: Static config: jdk.graal.compiler.hotspot.GraalHotSpotVMConfig@4817c460 state [bci:4]  <||@
  Comment 87 {HotSpotMethod<Integer.toString(int)>}  <||@
  Comment 87 INVOKESTATIC  <||@
  Comment 92 []at java.lang.Byte.toString(Byte.java:443) [bci: 4, duringCall: true, rethrow: false]
              |0 
     locals:  |-   <||@
  Comment 100 52 RETURN (savedRbp: stack:16|QWORD, value: rax|QWORD[.]) isStub: false requiresReservedStackAccessCheck: false thread: r15 scratchForSafepointOnReturn: rcx config: jdk.graal.compiler.hotspot.GraalHotSpotVMConfig@4817c460  <||@
  Comment 109 POLL_RETURN_FAR  <||@
  Comment 128 {Field[name=CompilerToVM::Data::nmethod_entry_barrier, type=address, offset=0, address=0x7f78b2033598, value=140155947495968]:0x7f789976b220}  <||@
  Comment 150 {Field[name=CompilerToVM::Data::SharedRuntime_polling_page_return_handler, type=address, offset=0, address=0x7f78b20335a0, value=140155947630592]:0x7f789978c000}  <||@
  Comment 156 {Stub<ExceptionHandlerStub.exceptionHandler>@0x7f78998c5300:CallingConvention[rax|QWORD[.], rdx|QWORD]:CallingConvention[rax|QWORD[.], rdx|QWORD]; temps=rdi|ILLEGAL,xmm14|ILLEGAL,xmm15|ILLEGAL,xmm12|ILLEGAL,xmm13|ILLEGAL,xmm10|ILLEGAL,xmm11|ILLEGAL,xmm7|ILLEGAL,xmm8|ILLEGAL,xmm9|ILLEGAL,xmm0|ILLEGAL,xmm1|ILLEGAL,xmm2|ILLEGAL,xmm3|ILLEGAL,xmm4|ILLEGAL,xmm5|ILLEGAL,xmm6|ILLEGAL,rax|ILLEGAL,rcx|ILLEGAL,rdx|ILLEGAL,rsi|ILLEGAL,r8|ILLEGAL,r9|ILLEGAL,r10|ILLEGAL,r11|ILLEGAL}  <||@
  Comment 156 EXCEPTION_HANDLER_ENTRY  <||@
  Comment 162 {Field[name=CompilerToVM::Data::SharedRuntime_deopt_blob_unpack, type=address, offset=0, address=0x7f78b20335b8, value=140155947626272]:0x7f789978af20}  <||@
  Comment 162 DEOPT_HANDLER_ENTRY  <||@
  HexCodeFile>>> <|@
end_nmethod
