begin_compilation
  name " HotSpotCompilation-6956[java.util.ArrayList.<init>()]"
  method "HotSpotCompilation-6956[java.util.ArrayList.<init>()]"
  date 1724269753810
end_compilation
begin_cfg
  name "Final HIR schedule"
  begin_block
    name "B0"
    from_bci -1
    to_bci -1
    predecessors 
    successors 
    xhandlers
    flags 
    probability 4607182418800017408
    begin_IR
      HIR
f <@#|@fixed with next>@ <|@
tid v0 <|@
d <@d|@=== Debug Properties ===
hasSpeculationFence: false
stamp: void
=== Inputs ===
stateAfter: - 
=== Succesors ===
next: v15 
=== Usages ===
=== Predecessor ===
- >@ <|@
instruction <@StartNode|@jdk.graal.compiler.nodes.StartNode>@ stateAfter: - #next: v15  <|@  <|@
f <@~|@floating>@ <|@
tid a1 <|@
d <@d|@=== Debug Properties ===
index: 0
stamp: a!# java.util.ArrayList
uncheckedStamp: [null]
=== Inputs ===
=== Succesors ===
=== Usages ===
v26 v25 v23 
=== Predecessor ===
- >@ <|@
instruction <@Parameter|@jdk.graal.compiler.nodes.ParameterNode>@  <|@  <|@
f <@~|@floating>@ <|@
tid v25 <|@
d <@d|@=== Debug Properties ===
displacement: 12
stamp: void*
stride: S1
=== Inputs ===
base: a1 
index: - 
=== Succesors ===
=== Usages ===
v15 
=== Predecessor ===
- >@ <|@
instruction <@AMD64Address|@jdk.graal.compiler.core.amd64.AMD64AddressNode>@ base: a1 index: -  <|@  <|@
f <@~|@floating>@ <|@
tid i6 <|@
d <@d|@=== Debug Properties ===
isDefaultStable: false
nodeSourcePosition: at java.util.AbstractList.<init>(AbstractList.java:630) [bci: 5]
at java.util.ArrayList.<init>(ArrayList.java:168) [bci: 1]
rawvalue: 0
stableDimension: 0
stamp: i32 [0]
stampKind: i32
value: int[0|0x0]
=== Inputs ===
=== Succesors ===
=== Usages ===
v15 
=== Predecessor ===
- >@ <|@
instruction <@Constant|@jdk.graal.compiler.nodes.ConstantNode>@  <|@  <|@
f <@#|@fixed with next>@ <|@
tid v15 <|@
d <@d|@=== Debug Properties ===
barrierType: NONE
deoptReasonAndAction: [null]
deoptSpeculation: [null]
killedLocationIdentity: AbstractList.modCount
location: AbstractList.modCount
memoryOrder: PLAIN
nodeSourcePosition: at java.util.AbstractList.<init>(AbstractList.java:630) [bci: 6]
at java.util.ArrayList.<init>(ArrayList.java:168) [bci: 1]
stamp: void
usedAsNullCheck: false
=== Inputs ===
stateBefore: - 
guard: - 
address: v25 
lastLocationAccess: - 
value: i6 
stateAfter: - 
=== Succesors ===
next: v21 
=== Usages ===
=== Predecessor ===
v0 >@ <|@
instruction <@Write|@jdk.graal.compiler.nodes.memory.WriteNode>@ stateBefore: - guard: - address: v25 lastLocationAccess: - value: i6 stateAfter: - #next: v21  <|@  <|@
f <@~|@floating>@ <|@
tid v26 <|@
d <@d|@=== Debug Properties ===
displacement: 20
stamp: void*
stride: S1
=== Inputs ===
base: a1 
index: - 
=== Succesors ===
=== Usages ===
v19 v21 v23 
=== Predecessor ===
- >@ <|@
instruction <@AMD64Address|@jdk.graal.compiler.core.amd64.AMD64AddressNode>@ base: a1 index: -  <|@  <|@
f <@#|@fixed with next>@ <|@
tid v21 <|@
d <@d|@=== Debug Properties ===
doLoad: true
nodeSourcePosition: at java.util.ArrayList.<init>(ArrayList.java:169) [bci: 8]
precise: true
stamp: void
=== Inputs ===
address: v26 
value: - 
stateBefore: - 
=== Succesors ===
next: v19 
=== Usages ===
=== Predecessor ===
v15 >@ <|@
instruction <@G1PreWriteBarrier|@jdk.graal.compiler.nodes.gc.G1PreWriteBarrierNode>@ address: v26 value: - stateBefore: - #next: v19  <|@  <|@
f <@~|@floating>@ <|@
tid a20 <|@
d <@d|@=== Debug Properties ===
isDefaultStable: false
nodeSourcePosition: at java.util.ArrayList.<init>(ArrayList.java:169) [bci: 8]
rawvalue: Object[0]{}
stableDimension: 0
stamp: n!# java.lang.Object[]
stampKind: n java.lang.Object
value: NarrowOop[Object[0]{}]
=== Inputs ===
=== Succesors ===
=== Usages ===
v19 
=== Predecessor ===
- >@ <|@
instruction <@Constant|@jdk.graal.compiler.nodes.ConstantNode>@  <|@  <|@
f <@#|@fixed with next>@ <|@
tid v19 <|@
d <@d|@=== Debug Properties ===
barrierType: FIELD
deoptReasonAndAction: [null]
deoptSpeculation: [null]
killedLocationIdentity: ArrayList.elementData
location: ArrayList.elementData
memoryOrder: PLAIN
nodeSourcePosition: at java.util.ArrayList.<init>(ArrayList.java:169) [bci: 8]
stamp: void
usedAsNullCheck: false
=== Inputs ===
stateBefore: - 
guard: - 
address: v26 
lastLocationAccess: - 
value: a20 
stateAfter: - 
=== Succesors ===
next: v23 
=== Usages ===
=== Predecessor ===
v21 >@ <|@
instruction <@Write|@jdk.graal.compiler.nodes.memory.WriteNode>@ stateBefore: - guard: - address: v26 lastLocationAccess: - value: a20 stateAfter: - #next: v23  <|@  <|@
f <@~|@floating>@ <|@
tid a24 <|@
d <@d|@=== Debug Properties ===
isDefaultStable: false
nodeSourcePosition: at java.util.ArrayList.<init>(ArrayList.java:169) [bci: 8]
rawvalue: Object[0]{}
stableDimension: 0
stamp: a!# java.lang.Object[]
stampKind: a java.lang.Object
value: Object[Object[0]{}]
=== Inputs ===
=== Succesors ===
=== Usages ===
v23 
=== Predecessor ===
- >@ <|@
instruction <@Constant|@jdk.graal.compiler.nodes.ConstantNode>@  <|@  <|@
f <@#|@fixed with next>@ <|@
tid v23 <|@
d <@d|@=== Debug Properties ===
alwaysNull: false
nodeSourcePosition: at java.util.ArrayList.<init>(ArrayList.java:169) [bci: 8]
precise: false
stamp: void
=== Inputs ===
address: v26 
value: a24 
object: a1 
=== Succesors ===
next: v12 
=== Usages ===
=== Predecessor ===
v19 >@ <|@
instruction <@G1PostWriteBarrier|@jdk.graal.compiler.nodes.gc.G1PostWriteBarrierNode>@ address: v26 value: a24 object: a1 #next: v12  <|@  <|@
f <@*|@fixed>@ <|@
tid v12 <|@
d <@d|@=== Debug Properties ===
nodeSourcePosition: at java.util.ArrayList.<init>(ArrayList.java:170) [bci: 11]
stamp: void
=== Inputs ===
memoryMap: - 
result: - 
=== Succesors ===
=== Usages ===
=== Predecessor ===
v23 >@ <|@
instruction <@Return|@jdk.graal.compiler.nodes.ReturnNode>@ memoryMap: - result: -  <|@  <|@
    end_IR
  end_block
end_cfg
begin_cfg
  name "After LIRGeneration"
  begin_block
    name "B0"
    from_bci -1
    to_bci -1
    predecessors 
    successors 
    xhandlers
    flags 
    probability 4607182418800017408
    begin_IR
      LIR
      nr   -1  <|@ instruction [rsi|QWORD[.], rbp|QWORD] = LABEL alignment: 0 numbPhis: 0 label: ? <|@ <|@
      nr   -1  <|@ instruction v6|QWORD = MOVE input: rbp|QWORD moveKind: QWORD <|@ <|@
      nr   -1  <|@ instruction [] = HOTSPOTLOCKSTACK frameMapBuilder: jdk.graal.compiler.hotspot.amd64.AMD64HotSpotFrameMapBuilder@59edbf8f slotKind: QWORD <|@ <|@
      nr   -1  <|@ instruction v0|QWORD[.] = MOVE input: rsi|QWORD[.] moveKind: QWORD <|@ <|@
      nr   -1  <|@ instruction MOV x: [v0|QWORD[.] + 12] y: 0 size: DWORD <|@ <|@
      nr   -1  <|@ instruction AMD64G1PREWRITEBARRIER (~address: [v0|QWORD[.] + 20], ~expectedObject: -) {temp: v1|QWORD, temp2: v2|QWORD, temp3: -} nonNull: false callTarget: Stub<write_barrier_pre-stack-only(Object)void>@0x7f78998c8200:CallingConvention[out:0|QWORD[.]]:CallingConvention[in:0|QWORD[.]] tool: jdk.graal.compiler.hotspot.amd64.g1.AMD64HotSpotG1BarrierSetLIRTool@33580fae <|@ <|@
      nr   -1  <|@ instruction MOV x: [v0|QWORD[.] + 20] y: -559030611 size: DWORD c: NarrowOop[Object[0]{}] <|@ <|@
      nr   -1  <|@ instruction v3|QWORD[.] = HOTSPOTLOADOBJECTCONSTANT input: Object[Object[0]{}] <|@ <|@
      nr   -1  <|@ instruction AMD64G1POSTWRITEBARRIER (~address: v0|QWORD[.], ~newValue: v3|QWORD[.]) {temp: v4|QWORD, temp2: v5|QWORD} nonNull: true callTarget: Stub<write_barrier_post-stack-only(Word)void>@0x7f78998ca380:CallingConvention[out:0|QWORD]:CallingConvention[in:0|QWORD] tool: jdk.graal.compiler.hotspot.amd64.g1.AMD64HotSpotG1BarrierSetLIRTool@33580fae <|@ <|@
      nr   -1  <|@ instruction RETURN (savedRbp: v6|QWORD, value: -) isStub: false requiresReservedStackAccessCheck: false thread: r15 scratchForSafepointOnReturn: rcx config: jdk.graal.compiler.hotspot.GraalHotSpotVMConfig@4817c460 <|@ <|@
    end_IR
  end_block
end_cfg
begin_bytecodes
     0: aload_0       
     1: invokespecial #0          // java.util.AbstractList.<init>:()void
     4: aload_0       
     5: getstatic     #8          // DEFAULTCAPACITY_EMPTY_ELEMENTDATA:java.lang.Object[]
     8: putfield      #1          // elementData:java.lang.Object[]
    11: return        
   <|@
end_bytecodes
begin_cfg
  name "After LIR generation"
  begin_block
    name "B0"
    from_bci -1
    to_bci -1
    predecessors 
    successors 
    xhandlers
    flags 
    probability 4607182418800017408
    begin_IR
      HIR
f <@#|@fixed with next>@ <|@
tid v0 <|@
d <@d|@=== Debug Properties ===
hasSpeculationFence: false
stamp: void
=== Inputs ===
stateAfter: - 
=== Succesors ===
next: v15 
=== Usages ===
=== Predecessor ===
- >@ <|@
instruction <@StartNode|@jdk.graal.compiler.nodes.StartNode>@ stateAfter: - #next: v15  <|@  <|@
f <@~|@floating>@ <|@
tid a1 <|@
result v0|QWORD[.] <|@
d <@d|@=== Debug Properties ===
index: 0
stamp: a!# java.util.ArrayList
uncheckedStamp: [null]
=== Inputs ===
=== Succesors ===
=== Usages ===
v26 v25 v23 
=== Predecessor ===
- >@ <|@
instruction <@Parameter|@jdk.graal.compiler.nodes.ParameterNode>@  <|@  <|@
f <@~|@floating>@ <|@
tid v25 <|@
result [v0|QWORD[.] + 12] <|@
d <@d|@=== Debug Properties ===
displacement: 12
stamp: void*
stride: S1
=== Inputs ===
base: a1 
index: - 
=== Succesors ===
=== Usages ===
v15 
=== Predecessor ===
- >@ <|@
instruction <@AMD64Address|@jdk.graal.compiler.core.amd64.AMD64AddressNode>@ base: a1 index: -  <|@  <|@
f <@~|@floating>@ <|@
tid i6 <|@
result int[0|0x0] <|@
d <@d|@=== Debug Properties ===
isDefaultStable: false
nodeSourcePosition: at java.util.AbstractList.<init>(AbstractList.java:630) [bci: 5]
at java.util.ArrayList.<init>(ArrayList.java:168) [bci: 1]
rawvalue: 0
stableDimension: 0
stamp: i32 [0]
stampKind: i32
value: int[0|0x0]
=== Inputs ===
=== Succesors ===
=== Usages ===
v15 
=== Predecessor ===
- >@ <|@
instruction <@Constant|@jdk.graal.compiler.nodes.ConstantNode>@  <|@  <|@
f <@#|@fixed with next>@ <|@
tid v15 <|@
d <@d|@=== Debug Properties ===
barrierType: NONE
deoptReasonAndAction: [null]
deoptSpeculation: [null]
killedLocationIdentity: AbstractList.modCount
location: AbstractList.modCount
memoryOrder: PLAIN
nodeSourcePosition: at java.util.AbstractList.<init>(AbstractList.java:630) [bci: 6]
at java.util.ArrayList.<init>(ArrayList.java:168) [bci: 1]
stamp: void
usedAsNullCheck: false
=== Inputs ===
stateBefore: - 
guard: - 
address: v25 
lastLocationAccess: - 
value: i6 
stateAfter: - 
=== Succesors ===
next: v21 
=== Usages ===
=== Predecessor ===
v0 >@ <|@
instruction <@Write|@jdk.graal.compiler.nodes.memory.WriteNode>@ stateBefore: - guard: - address: v25 lastLocationAccess: - value: i6 stateAfter: - #next: v21  <|@  <|@
f <@~|@floating>@ <|@
tid v26 <|@
result [v0|QWORD[.] + 20] <|@
d <@d|@=== Debug Properties ===
displacement: 20
stamp: void*
stride: S1
=== Inputs ===
base: a1 
index: - 
=== Succesors ===
=== Usages ===
v19 v21 v23 
=== Predecessor ===
- >@ <|@
instruction <@AMD64Address|@jdk.graal.compiler.core.amd64.AMD64AddressNode>@ base: a1 index: -  <|@  <|@
f <@#|@fixed with next>@ <|@
tid v21 <|@
d <@d|@=== Debug Properties ===
doLoad: true
nodeSourcePosition: at java.util.ArrayList.<init>(ArrayList.java:169) [bci: 8]
precise: true
stamp: void
=== Inputs ===
address: v26 
value: - 
stateBefore: - 
=== Succesors ===
next: v19 
=== Usages ===
=== Predecessor ===
v15 >@ <|@
instruction <@G1PreWriteBarrier|@jdk.graal.compiler.nodes.gc.G1PreWriteBarrierNode>@ address: v26 value: - stateBefore: - #next: v19  <|@  <|@
f <@~|@floating>@ <|@
tid a20 <|@
result NarrowOop[Object[0]{}] <|@
d <@d|@=== Debug Properties ===
isDefaultStable: false
nodeSourcePosition: at java.util.ArrayList.<init>(ArrayList.java:169) [bci: 8]
rawvalue: Object[0]{}
stableDimension: 0
stamp: n!# java.lang.Object[]
stampKind: n java.lang.Object
value: NarrowOop[Object[0]{}]
=== Inputs ===
=== Succesors ===
=== Usages ===
v19 
=== Predecessor ===
- >@ <|@
instruction <@Constant|@jdk.graal.compiler.nodes.ConstantNode>@  <|@  <|@
f <@#|@fixed with next>@ <|@
tid v19 <|@
d <@d|@=== Debug Properties ===
barrierType: FIELD
deoptReasonAndAction: [null]
deoptSpeculation: [null]
killedLocationIdentity: ArrayList.elementData
location: ArrayList.elementData
memoryOrder: PLAIN
nodeSourcePosition: at java.util.ArrayList.<init>(ArrayList.java:169) [bci: 8]
stamp: void
usedAsNullCheck: false
=== Inputs ===
stateBefore: - 
guard: - 
address: v26 
lastLocationAccess: - 
value: a20 
stateAfter: - 
=== Succesors ===
next: v23 
=== Usages ===
=== Predecessor ===
v21 >@ <|@
instruction <@Write|@jdk.graal.compiler.nodes.memory.WriteNode>@ stateBefore: - guard: - address: v26 lastLocationAccess: - value: a20 stateAfter: - #next: v23  <|@  <|@
f <@~|@floating>@ <|@
tid a24 <|@
result v3|QWORD[.] <|@
d <@d|@=== Debug Properties ===
isDefaultStable: false
nodeSourcePosition: at java.util.ArrayList.<init>(ArrayList.java:169) [bci: 8]
rawvalue: Object[0]{}
stableDimension: 0
stamp: a!# java.lang.Object[]
stampKind: a java.lang.Object
value: Object[Object[0]{}]
=== Inputs ===
=== Succesors ===
=== Usages ===
v23 
=== Predecessor ===
- >@ <|@
instruction <@Constant|@jdk.graal.compiler.nodes.ConstantNode>@  <|@  <|@
f <@#|@fixed with next>@ <|@
tid v23 <|@
d <@d|@=== Debug Properties ===
alwaysNull: false
nodeSourcePosition: at java.util.ArrayList.<init>(ArrayList.java:169) [bci: 8]
precise: false
stamp: void
=== Inputs ===
address: v26 
value: a24 
object: a1 
=== Succesors ===
next: v12 
=== Usages ===
=== Predecessor ===
v19 >@ <|@
instruction <@G1PostWriteBarrier|@jdk.graal.compiler.nodes.gc.G1PostWriteBarrierNode>@ address: v26 value: a24 object: a1 #next: v12  <|@  <|@
f <@*|@fixed>@ <|@
tid v12 <|@
d <@d|@=== Debug Properties ===
nodeSourcePosition: at java.util.ArrayList.<init>(ArrayList.java:170) [bci: 11]
stamp: void
=== Inputs ===
memoryMap: - 
result: - 
=== Succesors ===
=== Usages ===
=== Predecessor ===
v23 >@ <|@
instruction <@Return|@jdk.graal.compiler.nodes.ReturnNode>@ memoryMap: - result: -  <|@  <|@
    end_IR
    begin_IR
      LIR
      nr   -1  <|@ instruction [rsi|QWORD[.], rbp|QWORD] = LABEL alignment: 0 numbPhis: 0 label: ? <|@ <|@
      nr   -1  <|@ instruction v6|QWORD = MOVE input: rbp|QWORD moveKind: QWORD <|@ <|@
      nr   -1  <|@ instruction [] = HOTSPOTLOCKSTACK frameMapBuilder: jdk.graal.compiler.hotspot.amd64.AMD64HotSpotFrameMapBuilder@59edbf8f slotKind: QWORD <|@ <|@
      nr   -1  <|@ instruction v0|QWORD[.] = MOVE input: rsi|QWORD[.] moveKind: QWORD <|@ <|@
      nr   -1  <|@ instruction MOV x: [v0|QWORD[.] + 12] y: 0 size: DWORD <|@ <|@
      nr   -1  <|@ instruction AMD64G1PREWRITEBARRIER (~address: [v0|QWORD[.] + 20], ~expectedObject: -) {temp: v1|QWORD, temp2: v2|QWORD, temp3: -} nonNull: false callTarget: Stub<write_barrier_pre-stack-only(Object)void>@0x7f78998c8200:CallingConvention[out:0|QWORD[.]]:CallingConvention[in:0|QWORD[.]] tool: jdk.graal.compiler.hotspot.amd64.g1.AMD64HotSpotG1BarrierSetLIRTool@33580fae <|@ <|@
      nr   -1  <|@ instruction MOV x: [v0|QWORD[.] + 20] y: -559030611 size: DWORD c: NarrowOop[Object[0]{}] <|@ <|@
      nr   -1  <|@ instruction v3|QWORD[.] = HOTSPOTLOADOBJECTCONSTANT input: Object[Object[0]{}] <|@ <|@
      nr   -1  <|@ instruction AMD64G1POSTWRITEBARRIER (~address: v0|QWORD[.], ~newValue: v3|QWORD[.]) {temp: v4|QWORD, temp2: v5|QWORD} nonNull: true callTarget: Stub<write_barrier_post-stack-only(Word)void>@0x7f78998ca380:CallingConvention[out:0|QWORD]:CallingConvention[in:0|QWORD] tool: jdk.graal.compiler.hotspot.amd64.g1.AMD64HotSpotG1BarrierSetLIRTool@33580fae <|@ <|@
      nr   -1  <|@ instruction RETURN (savedRbp: v6|QWORD, value: -) isStub: false requiresReservedStackAccessCheck: false thread: r15 scratchForSafepointOnReturn: rcx config: jdk.graal.compiler.hotspot.GraalHotSpotVMConfig@4817c460 <|@ <|@
    end_IR
  end_block
end_cfg
begin_cfg
  name "After LIRGTSlowdown"
  begin_block
    name "B0"
    from_bci -1
    to_bci -1
    predecessors 
    successors 
    xhandlers
    flags 
    probability 4607182418800017408
    begin_IR
      LIR
      nr   -1  <|@ instruction [rsi|QWORD[.], rbp|QWORD] = LABEL alignment: 0 numbPhis: 0 label: ? <|@ <|@
      nr   -1  <|@ instruction NOP <|@ <|@
      nr   -1  <|@ instruction NOP <|@ <|@
      nr   -1  <|@ instruction NOP <|@ <|@
      nr   -1  <|@ instruction NOP <|@ <|@
      nr   -1  <|@ instruction NOP <|@ <|@
      nr   -1  <|@ instruction NOP <|@ <|@
      nr   -1  <|@ instruction NOP <|@ <|@
      nr   -1  <|@ instruction NOP <|@ <|@
      nr   -1  <|@ instruction NOP <|@ <|@
      nr   -1  <|@ instruction NOP <|@ <|@
      nr   -1  <|@ instruction NOP <|@ <|@
      nr   -1  <|@ instruction NOP <|@ <|@
      nr   -1  <|@ instruction NOP <|@ <|@
      nr   -1  <|@ instruction NOP <|@ <|@
      nr   -1  <|@ instruction NOP <|@ <|@
      nr   -1  <|@ instruction NOP <|@ <|@
      nr   -1  <|@ instruction NOP <|@ <|@
      nr   -1  <|@ instruction NOP <|@ <|@
      nr   -1  <|@ instruction NOP <|@ <|@
      nr   -1  <|@ instruction NOP <|@ <|@
      nr   -1  <|@ instruction NOP <|@ <|@
      nr   -1  <|@ instruction NOP <|@ <|@
      nr   -1  <|@ instruction NOP <|@ <|@
      nr   -1  <|@ instruction NOP <|@ <|@
      nr   -1  <|@ instruction NOP <|@ <|@
      nr   -1  <|@ instruction NOP <|@ <|@
      nr   -1  <|@ instruction NOP <|@ <|@
      nr   -1  <|@ instruction NOP <|@ <|@
      nr   -1  <|@ instruction NOP <|@ <|@
      nr   -1  <|@ instruction NOP <|@ <|@
      nr   -1  <|@ instruction NOP <|@ <|@
      nr   -1  <|@ instruction NOP <|@ <|@
      nr   -1  <|@ instruction NOP <|@ <|@
      nr   -1  <|@ instruction NOP <|@ <|@
      nr   -1  <|@ instruction NOP <|@ <|@
      nr   -1  <|@ instruction NOP <|@ <|@
      nr   -1  <|@ instruction NOP <|@ <|@
      nr   -1  <|@ instruction NOP <|@ <|@
      nr   -1  <|@ instruction NOP <|@ <|@
      nr   -1  <|@ instruction NOP <|@ <|@
      nr   -1  <|@ instruction NOP <|@ <|@
      nr   -1  <|@ instruction NOP <|@ <|@
      nr   -1  <|@ instruction NOP <|@ <|@
      nr   -1  <|@ instruction NOP <|@ <|@
      nr   -1  <|@ instruction NOP <|@ <|@
      nr   -1  <|@ instruction NOP <|@ <|@
      nr   -1  <|@ instruction NOP <|@ <|@
      nr   -1  <|@ instruction NOP <|@ <|@
      nr   -1  <|@ instruction NOP <|@ <|@
      nr   -1  <|@ instruction NOP <|@ <|@
      nr   -1  <|@ instruction NOP <|@ <|@
      nr   -1  <|@ instruction NOP <|@ <|@
      nr   -1  <|@ instruction NOP <|@ <|@
      nr   -1  <|@ instruction NOP <|@ <|@
      nr   -1  <|@ instruction NOP <|@ <|@
      nr   -1  <|@ instruction NOP <|@ <|@
      nr   -1  <|@ instruction NOP <|@ <|@
      nr   -1  <|@ instruction NOP <|@ <|@
      nr   -1  <|@ instruction NOP <|@ <|@
      nr   -1  <|@ instruction NOP <|@ <|@
      nr   -1  <|@ instruction NOP <|@ <|@
      nr   -1  <|@ instruction NOP <|@ <|@
      nr   -1  <|@ instruction NOP <|@ <|@
      nr   -1  <|@ instruction NOP <|@ <|@
      nr   -1  <|@ instruction v6|QWORD = MOVE input: rbp|QWORD moveKind: QWORD <|@ <|@
      nr   -1  <|@ instruction [] = HOTSPOTLOCKSTACK frameMapBuilder: jdk.graal.compiler.hotspot.amd64.AMD64HotSpotFrameMapBuilder@59edbf8f slotKind: QWORD <|@ <|@
      nr   -1  <|@ instruction v0|QWORD[.] = MOVE input: rsi|QWORD[.] moveKind: QWORD <|@ <|@
      nr   -1  <|@ instruction MOV x: [v0|QWORD[.] + 12] y: 0 size: DWORD <|@ <|@
      nr   -1  <|@ instruction AMD64G1PREWRITEBARRIER (~address: [v0|QWORD[.] + 20], ~expectedObject: -) {temp: v1|QWORD, temp2: v2|QWORD, temp3: -} nonNull: false callTarget: Stub<write_barrier_pre-stack-only(Object)void>@0x7f78998c8200:CallingConvention[out:0|QWORD[.]]:CallingConvention[in:0|QWORD[.]] tool: jdk.graal.compiler.hotspot.amd64.g1.AMD64HotSpotG1BarrierSetLIRTool@33580fae <|@ <|@
      nr   -1  <|@ instruction MOV x: [v0|QWORD[.] + 20] y: -559030611 size: DWORD c: NarrowOop[Object[0]{}] <|@ <|@
      nr   -1  <|@ instruction v3|QWORD[.] = HOTSPOTLOADOBJECTCONSTANT input: Object[Object[0]{}] <|@ <|@
      nr   -1  <|@ instruction AMD64G1POSTWRITEBARRIER (~address: v0|QWORD[.], ~newValue: v3|QWORD[.]) {temp: v4|QWORD, temp2: v5|QWORD} nonNull: true callTarget: Stub<write_barrier_post-stack-only(Word)void>@0x7f78998ca380:CallingConvention[out:0|QWORD]:CallingConvention[in:0|QWORD] tool: jdk.graal.compiler.hotspot.amd64.g1.AMD64HotSpotG1BarrierSetLIRTool@33580fae <|@ <|@
      nr   -1  <|@ instruction RETURN (savedRbp: v6|QWORD, value: -) isStub: false requiresReservedStackAccessCheck: false thread: r15 scratchForSafepointOnReturn: rcx config: jdk.graal.compiler.hotspot.GraalHotSpotVMConfig@4817c460 <|@ <|@
    end_IR
  end_block
end_cfg
begin_bytecodes
     0: aload_0       
     1: invokespecial #0          // java.util.AbstractList.<init>:()void
     4: aload_0       
     5: getstatic     #8          // DEFAULTCAPACITY_EMPTY_ELEMENTDATA:java.lang.Object[]
     8: putfield      #1          // elementData:java.lang.Object[]
    11: return        
   <|@
end_bytecodes
begin_cfg
  name "After ConstantLoadOptimization"
  begin_block
    name "B0"
    from_bci -1
    to_bci -1
    predecessors 
    successors 
    xhandlers
    flags 
    probability 4607182418800017408
    begin_IR
      LIR
      nr   -1  <|@ instruction [rsi|QWORD[.], rbp|QWORD] = LABEL alignment: 0 numbPhis: 0 label: ? <|@ <|@
      nr   -1  <|@ instruction NOP <|@ <|@
      nr   -1  <|@ instruction NOP <|@ <|@
      nr   -1  <|@ instruction NOP <|@ <|@
      nr   -1  <|@ instruction NOP <|@ <|@
      nr   -1  <|@ instruction NOP <|@ <|@
      nr   -1  <|@ instruction NOP <|@ <|@
      nr   -1  <|@ instruction NOP <|@ <|@
      nr   -1  <|@ instruction NOP <|@ <|@
      nr   -1  <|@ instruction NOP <|@ <|@
      nr   -1  <|@ instruction NOP <|@ <|@
      nr   -1  <|@ instruction NOP <|@ <|@
      nr   -1  <|@ instruction NOP <|@ <|@
      nr   -1  <|@ instruction NOP <|@ <|@
      nr   -1  <|@ instruction NOP <|@ <|@
      nr   -1  <|@ instruction NOP <|@ <|@
      nr   -1  <|@ instruction NOP <|@ <|@
      nr   -1  <|@ instruction NOP <|@ <|@
      nr   -1  <|@ instruction NOP <|@ <|@
      nr   -1  <|@ instruction NOP <|@ <|@
      nr   -1  <|@ instruction NOP <|@ <|@
      nr   -1  <|@ instruction NOP <|@ <|@
      nr   -1  <|@ instruction NOP <|@ <|@
      nr   -1  <|@ instruction NOP <|@ <|@
      nr   -1  <|@ instruction NOP <|@ <|@
      nr   -1  <|@ instruction NOP <|@ <|@
      nr   -1  <|@ instruction NOP <|@ <|@
      nr   -1  <|@ instruction NOP <|@ <|@
      nr   -1  <|@ instruction NOP <|@ <|@
      nr   -1  <|@ instruction NOP <|@ <|@
      nr   -1  <|@ instruction NOP <|@ <|@
      nr   -1  <|@ instruction NOP <|@ <|@
      nr   -1  <|@ instruction NOP <|@ <|@
      nr   -1  <|@ instruction NOP <|@ <|@
      nr   -1  <|@ instruction NOP <|@ <|@
      nr   -1  <|@ instruction NOP <|@ <|@
      nr   -1  <|@ instruction NOP <|@ <|@
      nr   -1  <|@ instruction NOP <|@ <|@
      nr   -1  <|@ instruction NOP <|@ <|@
      nr   -1  <|@ instruction NOP <|@ <|@
      nr   -1  <|@ instruction NOP <|@ <|@
      nr   -1  <|@ instruction NOP <|@ <|@
      nr   -1  <|@ instruction NOP <|@ <|@
      nr   -1  <|@ instruction NOP <|@ <|@
      nr   -1  <|@ instruction NOP <|@ <|@
      nr   -1  <|@ instruction NOP <|@ <|@
      nr   -1  <|@ instruction NOP <|@ <|@
      nr   -1  <|@ instruction NOP <|@ <|@
      nr   -1  <|@ instruction NOP <|@ <|@
      nr   -1  <|@ instruction NOP <|@ <|@
      nr   -1  <|@ instruction NOP <|@ <|@
      nr   -1  <|@ instruction NOP <|@ <|@
      nr   -1  <|@ instruction NOP <|@ <|@
      nr   -1  <|@ instruction NOP <|@ <|@
      nr   -1  <|@ instruction NOP <|@ <|@
      nr   -1  <|@ instruction NOP <|@ <|@
      nr   -1  <|@ instruction NOP <|@ <|@
      nr   -1  <|@ instruction NOP <|@ <|@
      nr   -1  <|@ instruction NOP <|@ <|@
      nr   -1  <|@ instruction NOP <|@ <|@
      nr   -1  <|@ instruction NOP <|@ <|@
      nr   -1  <|@ instruction NOP <|@ <|@
      nr   -1  <|@ instruction NOP <|@ <|@
      nr   -1  <|@ instruction NOP <|@ <|@
      nr   -1  <|@ instruction NOP <|@ <|@
      nr   -1  <|@ instruction v6|QWORD = MOVE input: rbp|QWORD moveKind: QWORD <|@ <|@
      nr   -1  <|@ instruction [] = HOTSPOTLOCKSTACK frameMapBuilder: jdk.graal.compiler.hotspot.amd64.AMD64HotSpotFrameMapBuilder@59edbf8f slotKind: QWORD <|@ <|@
      nr   -1  <|@ instruction v0|QWORD[.] = MOVE input: rsi|QWORD[.] moveKind: QWORD <|@ <|@
      nr   -1  <|@ instruction MOV x: [v0|QWORD[.] + 12] y: 0 size: DWORD <|@ <|@
      nr   -1  <|@ instruction AMD64G1PREWRITEBARRIER (~address: [v0|QWORD[.] + 20], ~expectedObject: -) {temp: v1|QWORD, temp2: v2|QWORD, temp3: -} nonNull: false callTarget: Stub<write_barrier_pre-stack-only(Object)void>@0x7f78998c8200:CallingConvention[out:0|QWORD[.]]:CallingConvention[in:0|QWORD[.]] tool: jdk.graal.compiler.hotspot.amd64.g1.AMD64HotSpotG1BarrierSetLIRTool@33580fae <|@ <|@
      nr   -1  <|@ instruction MOV x: [v0|QWORD[.] + 20] y: -559030611 size: DWORD c: NarrowOop[Object[0]{}] <|@ <|@
      nr   -1  <|@ instruction v3|QWORD[.] = HOTSPOTLOADOBJECTCONSTANT input: Object[Object[0]{}] <|@ <|@
      nr   -1  <|@ instruction AMD64G1POSTWRITEBARRIER (~address: v0|QWORD[.], ~newValue: v3|QWORD[.]) {temp: v4|QWORD, temp2: v5|QWORD} nonNull: true callTarget: Stub<write_barrier_post-stack-only(Word)void>@0x7f78998ca380:CallingConvention[out:0|QWORD]:CallingConvention[in:0|QWORD] tool: jdk.graal.compiler.hotspot.amd64.g1.AMD64HotSpotG1BarrierSetLIRTool@33580fae <|@ <|@
      nr   -1  <|@ instruction RETURN (savedRbp: v6|QWORD, value: -) isStub: false requiresReservedStackAccessCheck: false thread: r15 scratchForSafepointOnReturn: rcx config: jdk.graal.compiler.hotspot.GraalHotSpotVMConfig@4817c460 <|@ <|@
    end_IR
  end_block
end_cfg
begin_bytecodes
     0: aload_0       
     1: invokespecial #0          // java.util.AbstractList.<init>:()void
     4: aload_0       
     5: getstatic     #8          // DEFAULTCAPACITY_EMPTY_ELEMENTDATA:java.lang.Object[]
     8: putfield      #1          // elementData:java.lang.Object[]
    11: return        
   <|@
end_bytecodes
begin_cfg
  name "After SaveCalleeSaveRegisters"
  begin_block
    name "B0"
    from_bci -1
    to_bci -1
    predecessors 
    successors 
    xhandlers
    flags 
    probability 4607182418800017408
    begin_IR
      LIR
      nr   -1  <|@ instruction [rsi|QWORD[.], rbp|QWORD] = LABEL alignment: 0 numbPhis: 0 label: ? <|@ <|@
      nr   -1  <|@ instruction NOP <|@ <|@
      nr   -1  <|@ instruction NOP <|@ <|@
      nr   -1  <|@ instruction NOP <|@ <|@
      nr   -1  <|@ instruction NOP <|@ <|@
      nr   -1  <|@ instruction NOP <|@ <|@
      nr   -1  <|@ instruction NOP <|@ <|@
      nr   -1  <|@ instruction NOP <|@ <|@
      nr   -1  <|@ instruction NOP <|@ <|@
      nr   -1  <|@ instruction NOP <|@ <|@
      nr   -1  <|@ instruction NOP <|@ <|@
      nr   -1  <|@ instruction NOP <|@ <|@
      nr   -1  <|@ instruction NOP <|@ <|@
      nr   -1  <|@ instruction NOP <|@ <|@
      nr   -1  <|@ instruction NOP <|@ <|@
      nr   -1  <|@ instruction NOP <|@ <|@
      nr   -1  <|@ instruction NOP <|@ <|@
      nr   -1  <|@ instruction NOP <|@ <|@
      nr   -1  <|@ instruction NOP <|@ <|@
      nr   -1  <|@ instruction NOP <|@ <|@
      nr   -1  <|@ instruction NOP <|@ <|@
      nr   -1  <|@ instruction NOP <|@ <|@
      nr   -1  <|@ instruction NOP <|@ <|@
      nr   -1  <|@ instruction NOP <|@ <|@
      nr   -1  <|@ instruction NOP <|@ <|@
      nr   -1  <|@ instruction NOP <|@ <|@
      nr   -1  <|@ instruction NOP <|@ <|@
      nr   -1  <|@ instruction NOP <|@ <|@
      nr   -1  <|@ instruction NOP <|@ <|@
      nr   -1  <|@ instruction NOP <|@ <|@
      nr   -1  <|@ instruction NOP <|@ <|@
      nr   -1  <|@ instruction NOP <|@ <|@
      nr   -1  <|@ instruction NOP <|@ <|@
      nr   -1  <|@ instruction NOP <|@ <|@
      nr   -1  <|@ instruction NOP <|@ <|@
      nr   -1  <|@ instruction NOP <|@ <|@
      nr   -1  <|@ instruction NOP <|@ <|@
      nr   -1  <|@ instruction NOP <|@ <|@
      nr   -1  <|@ instruction NOP <|@ <|@
      nr   -1  <|@ instruction NOP <|@ <|@
      nr   -1  <|@ instruction NOP <|@ <|@
      nr   -1  <|@ instruction NOP <|@ <|@
      nr   -1  <|@ instruction NOP <|@ <|@
      nr   -1  <|@ instruction NOP <|@ <|@
      nr   -1  <|@ instruction NOP <|@ <|@
      nr   -1  <|@ instruction NOP <|@ <|@
      nr   -1  <|@ instruction NOP <|@ <|@
      nr   -1  <|@ instruction NOP <|@ <|@
      nr   -1  <|@ instruction NOP <|@ <|@
      nr   -1  <|@ instruction NOP <|@ <|@
      nr   -1  <|@ instruction NOP <|@ <|@
      nr   -1  <|@ instruction NOP <|@ <|@
      nr   -1  <|@ instruction NOP <|@ <|@
      nr   -1  <|@ instruction NOP <|@ <|@
      nr   -1  <|@ instruction NOP <|@ <|@
      nr   -1  <|@ instruction NOP <|@ <|@
      nr   -1  <|@ instruction NOP <|@ <|@
      nr   -1  <|@ instruction NOP <|@ <|@
      nr   -1  <|@ instruction NOP <|@ <|@
      nr   -1  <|@ instruction NOP <|@ <|@
      nr   -1  <|@ instruction NOP <|@ <|@
      nr   -1  <|@ instruction NOP <|@ <|@
      nr   -1  <|@ instruction NOP <|@ <|@
      nr   -1  <|@ instruction NOP <|@ <|@
      nr   -1  <|@ instruction NOP <|@ <|@
      nr   -1  <|@ instruction v6|QWORD = MOVE input: rbp|QWORD moveKind: QWORD <|@ <|@
      nr   -1  <|@ instruction [] = HOTSPOTLOCKSTACK frameMapBuilder: jdk.graal.compiler.hotspot.amd64.AMD64HotSpotFrameMapBuilder@59edbf8f slotKind: QWORD <|@ <|@
      nr   -1  <|@ instruction v0|QWORD[.] = MOVE input: rsi|QWORD[.] moveKind: QWORD <|@ <|@
      nr   -1  <|@ instruction MOV x: [v0|QWORD[.] + 12] y: 0 size: DWORD <|@ <|@
      nr   -1  <|@ instruction AMD64G1PREWRITEBARRIER (~address: [v0|QWORD[.] + 20], ~expectedObject: -) {temp: v1|QWORD, temp2: v2|QWORD, temp3: -} nonNull: false callTarget: Stub<write_barrier_pre-stack-only(Object)void>@0x7f78998c8200:CallingConvention[out:0|QWORD[.]]:CallingConvention[in:0|QWORD[.]] tool: jdk.graal.compiler.hotspot.amd64.g1.AMD64HotSpotG1BarrierSetLIRTool@33580fae <|@ <|@
      nr   -1  <|@ instruction MOV x: [v0|QWORD[.] + 20] y: -559030611 size: DWORD c: NarrowOop[Object[0]{}] <|@ <|@
      nr   -1  <|@ instruction v3|QWORD[.] = HOTSPOTLOADOBJECTCONSTANT input: Object[Object[0]{}] <|@ <|@
      nr   -1  <|@ instruction AMD64G1POSTWRITEBARRIER (~address: v0|QWORD[.], ~newValue: v3|QWORD[.]) {temp: v4|QWORD, temp2: v5|QWORD} nonNull: true callTarget: Stub<write_barrier_post-stack-only(Word)void>@0x7f78998ca380:CallingConvention[out:0|QWORD]:CallingConvention[in:0|QWORD] tool: jdk.graal.compiler.hotspot.amd64.g1.AMD64HotSpotG1BarrierSetLIRTool@33580fae <|@ <|@
      nr   -1  <|@ instruction RETURN (savedRbp: v6|QWORD, value: -) isStub: false requiresReservedStackAccessCheck: false thread: r15 scratchForSafepointOnReturn: rcx config: jdk.graal.compiler.hotspot.GraalHotSpotVMConfig@4817c460 <|@ <|@
    end_IR
  end_block
end_cfg
begin_bytecodes
     0: aload_0       
     1: invokespecial #0          // java.util.AbstractList.<init>:()void
     4: aload_0       
     5: getstatic     #8          // DEFAULTCAPACITY_EMPTY_ELEMENTDATA:java.lang.Object[]
     8: putfield      #1          // elementData:java.lang.Object[]
    11: return        
   <|@
end_bytecodes
begin_cfg
  name "After PreAllocationOptimizationStage"
  begin_block
    name "B0"
    from_bci -1
    to_bci -1
    predecessors 
    successors 
    xhandlers
    flags 
    probability 4607182418800017408
    begin_IR
      LIR
      nr   -1  <|@ instruction [rsi|QWORD[.], rbp|QWORD] = LABEL alignment: 0 numbPhis: 0 label: ? <|@ <|@
      nr   -1  <|@ instruction NOP <|@ <|@
      nr   -1  <|@ instruction NOP <|@ <|@
      nr   -1  <|@ instruction NOP <|@ <|@
      nr   -1  <|@ instruction NOP <|@ <|@
      nr   -1  <|@ instruction NOP <|@ <|@
      nr   -1  <|@ instruction NOP <|@ <|@
      nr   -1  <|@ instruction NOP <|@ <|@
      nr   -1  <|@ instruction NOP <|@ <|@
      nr   -1  <|@ instruction NOP <|@ <|@
      nr   -1  <|@ instruction NOP <|@ <|@
      nr   -1  <|@ instruction NOP <|@ <|@
      nr   -1  <|@ instruction NOP <|@ <|@
      nr   -1  <|@ instruction NOP <|@ <|@
      nr   -1  <|@ instruction NOP <|@ <|@
      nr   -1  <|@ instruction NOP <|@ <|@
      nr   -1  <|@ instruction NOP <|@ <|@
      nr   -1  <|@ instruction NOP <|@ <|@
      nr   -1  <|@ instruction NOP <|@ <|@
      nr   -1  <|@ instruction NOP <|@ <|@
      nr   -1  <|@ instruction NOP <|@ <|@
      nr   -1  <|@ instruction NOP <|@ <|@
      nr   -1  <|@ instruction NOP <|@ <|@
      nr   -1  <|@ instruction NOP <|@ <|@
      nr   -1  <|@ instruction NOP <|@ <|@
      nr   -1  <|@ instruction NOP <|@ <|@
      nr   -1  <|@ instruction NOP <|@ <|@
      nr   -1  <|@ instruction NOP <|@ <|@
      nr   -1  <|@ instruction NOP <|@ <|@
      nr   -1  <|@ instruction NOP <|@ <|@
      nr   -1  <|@ instruction NOP <|@ <|@
      nr   -1  <|@ instruction NOP <|@ <|@
      nr   -1  <|@ instruction NOP <|@ <|@
      nr   -1  <|@ instruction NOP <|@ <|@
      nr   -1  <|@ instruction NOP <|@ <|@
      nr   -1  <|@ instruction NOP <|@ <|@
      nr   -1  <|@ instruction NOP <|@ <|@
      nr   -1  <|@ instruction NOP <|@ <|@
      nr   -1  <|@ instruction NOP <|@ <|@
      nr   -1  <|@ instruction NOP <|@ <|@
      nr   -1  <|@ instruction NOP <|@ <|@
      nr   -1  <|@ instruction NOP <|@ <|@
      nr   -1  <|@ instruction NOP <|@ <|@
      nr   -1  <|@ instruction NOP <|@ <|@
      nr   -1  <|@ instruction NOP <|@ <|@
      nr   -1  <|@ instruction NOP <|@ <|@
      nr   -1  <|@ instruction NOP <|@ <|@
      nr   -1  <|@ instruction NOP <|@ <|@
      nr   -1  <|@ instruction NOP <|@ <|@
      nr   -1  <|@ instruction NOP <|@ <|@
      nr   -1  <|@ instruction NOP <|@ <|@
      nr   -1  <|@ instruction NOP <|@ <|@
      nr   -1  <|@ instruction NOP <|@ <|@
      nr   -1  <|@ instruction NOP <|@ <|@
      nr   -1  <|@ instruction NOP <|@ <|@
      nr   -1  <|@ instruction NOP <|@ <|@
      nr   -1  <|@ instruction NOP <|@ <|@
      nr   -1  <|@ instruction NOP <|@ <|@
      nr   -1  <|@ instruction NOP <|@ <|@
      nr   -1  <|@ instruction NOP <|@ <|@
      nr   -1  <|@ instruction NOP <|@ <|@
      nr   -1  <|@ instruction NOP <|@ <|@
      nr   -1  <|@ instruction NOP <|@ <|@
      nr   -1  <|@ instruction NOP <|@ <|@
      nr   -1  <|@ instruction NOP <|@ <|@
      nr   -1  <|@ instruction v6|QWORD = MOVE input: rbp|QWORD moveKind: QWORD <|@ <|@
      nr   -1  <|@ instruction [] = HOTSPOTLOCKSTACK frameMapBuilder: jdk.graal.compiler.hotspot.amd64.AMD64HotSpotFrameMapBuilder@59edbf8f slotKind: QWORD <|@ <|@
      nr   -1  <|@ instruction v0|QWORD[.] = MOVE input: rsi|QWORD[.] moveKind: QWORD <|@ <|@
      nr   -1  <|@ instruction MOV x: [v0|QWORD[.] + 12] y: 0 size: DWORD <|@ <|@
      nr   -1  <|@ instruction AMD64G1PREWRITEBARRIER (~address: [v0|QWORD[.] + 20], ~expectedObject: -) {temp: v1|QWORD, temp2: v2|QWORD, temp3: -} nonNull: false callTarget: Stub<write_barrier_pre-stack-only(Object)void>@0x7f78998c8200:CallingConvention[out:0|QWORD[.]]:CallingConvention[in:0|QWORD[.]] tool: jdk.graal.compiler.hotspot.amd64.g1.AMD64HotSpotG1BarrierSetLIRTool@33580fae <|@ <|@
      nr   -1  <|@ instruction MOV x: [v0|QWORD[.] + 20] y: -559030611 size: DWORD c: NarrowOop[Object[0]{}] <|@ <|@
      nr   -1  <|@ instruction v3|QWORD[.] = HOTSPOTLOADOBJECTCONSTANT input: Object[Object[0]{}] <|@ <|@
      nr   -1  <|@ instruction AMD64G1POSTWRITEBARRIER (~address: v0|QWORD[.], ~newValue: v3|QWORD[.]) {temp: v4|QWORD, temp2: v5|QWORD} nonNull: true callTarget: Stub<write_barrier_post-stack-only(Word)void>@0x7f78998ca380:CallingConvention[out:0|QWORD]:CallingConvention[in:0|QWORD] tool: jdk.graal.compiler.hotspot.amd64.g1.AMD64HotSpotG1BarrierSetLIRTool@33580fae <|@ <|@
      nr   -1  <|@ instruction RETURN (savedRbp: v6|QWORD, value: -) isStub: false requiresReservedStackAccessCheck: false thread: r15 scratchForSafepointOnReturn: rcx config: jdk.graal.compiler.hotspot.GraalHotSpotVMConfig@4817c460 <|@ <|@
    end_IR
  end_block
end_cfg
begin_bytecodes
     0: aload_0       
     1: invokespecial #0          // java.util.AbstractList.<init>:()void
     4: aload_0       
     5: getstatic     #8          // DEFAULTCAPACITY_EMPTY_ELEMENTDATA:java.lang.Object[]
     8: putfield      #1          // elementData:java.lang.Object[]
    11: return        
   <|@
end_bytecodes
begin_cfg
  name "After MarkBasePointers"
  begin_block
    name "B0"
    from_bci -1
    to_bci -1
    predecessors 
    successors 
    xhandlers
    flags 
    probability 4607182418800017408
    begin_IR
      LIR
      nr   -1  <|@ instruction [rsi|QWORD[.], rbp|QWORD] = LABEL alignment: 0 numbPhis: 0 label: ? <|@ <|@
      nr   -1  <|@ instruction NOP <|@ <|@
      nr   -1  <|@ instruction NOP <|@ <|@
      nr   -1  <|@ instruction NOP <|@ <|@
      nr   -1  <|@ instruction NOP <|@ <|@
      nr   -1  <|@ instruction NOP <|@ <|@
      nr   -1  <|@ instruction NOP <|@ <|@
      nr   -1  <|@ instruction NOP <|@ <|@
      nr   -1  <|@ instruction NOP <|@ <|@
      nr   -1  <|@ instruction NOP <|@ <|@
      nr   -1  <|@ instruction NOP <|@ <|@
      nr   -1  <|@ instruction NOP <|@ <|@
      nr   -1  <|@ instruction NOP <|@ <|@
      nr   -1  <|@ instruction NOP <|@ <|@
      nr   -1  <|@ instruction NOP <|@ <|@
      nr   -1  <|@ instruction NOP <|@ <|@
      nr   -1  <|@ instruction NOP <|@ <|@
      nr   -1  <|@ instruction NOP <|@ <|@
      nr   -1  <|@ instruction NOP <|@ <|@
      nr   -1  <|@ instruction NOP <|@ <|@
      nr   -1  <|@ instruction NOP <|@ <|@
      nr   -1  <|@ instruction NOP <|@ <|@
      nr   -1  <|@ instruction NOP <|@ <|@
      nr   -1  <|@ instruction NOP <|@ <|@
      nr   -1  <|@ instruction NOP <|@ <|@
      nr   -1  <|@ instruction NOP <|@ <|@
      nr   -1  <|@ instruction NOP <|@ <|@
      nr   -1  <|@ instruction NOP <|@ <|@
      nr   -1  <|@ instruction NOP <|@ <|@
      nr   -1  <|@ instruction NOP <|@ <|@
      nr   -1  <|@ instruction NOP <|@ <|@
      nr   -1  <|@ instruction NOP <|@ <|@
      nr   -1  <|@ instruction NOP <|@ <|@
      nr   -1  <|@ instruction NOP <|@ <|@
      nr   -1  <|@ instruction NOP <|@ <|@
      nr   -1  <|@ instruction NOP <|@ <|@
      nr   -1  <|@ instruction NOP <|@ <|@
      nr   -1  <|@ instruction NOP <|@ <|@
      nr   -1  <|@ instruction NOP <|@ <|@
      nr   -1  <|@ instruction NOP <|@ <|@
      nr   -1  <|@ instruction NOP <|@ <|@
      nr   -1  <|@ instruction NOP <|@ <|@
      nr   -1  <|@ instruction NOP <|@ <|@
      nr   -1  <|@ instruction NOP <|@ <|@
      nr   -1  <|@ instruction NOP <|@ <|@
      nr   -1  <|@ instruction NOP <|@ <|@
      nr   -1  <|@ instruction NOP <|@ <|@
      nr   -1  <|@ instruction NOP <|@ <|@
      nr   -1  <|@ instruction NOP <|@ <|@
      nr   -1  <|@ instruction NOP <|@ <|@
      nr   -1  <|@ instruction NOP <|@ <|@
      nr   -1  <|@ instruction NOP <|@ <|@
      nr   -1  <|@ instruction NOP <|@ <|@
      nr   -1  <|@ instruction NOP <|@ <|@
      nr   -1  <|@ instruction NOP <|@ <|@
      nr   -1  <|@ instruction NOP <|@ <|@
      nr   -1  <|@ instruction NOP <|@ <|@
      nr   -1  <|@ instruction NOP <|@ <|@
      nr   -1  <|@ instruction NOP <|@ <|@
      nr   -1  <|@ instruction NOP <|@ <|@
      nr   -1  <|@ instruction NOP <|@ <|@
      nr   -1  <|@ instruction NOP <|@ <|@
      nr   -1  <|@ instruction NOP <|@ <|@
      nr   -1  <|@ instruction NOP <|@ <|@
      nr   -1  <|@ instruction NOP <|@ <|@
      nr   -1  <|@ instruction v6|QWORD = MOVE input: rbp|QWORD moveKind: QWORD <|@ <|@
      nr   -1  <|@ instruction [] = HOTSPOTLOCKSTACK frameMapBuilder: jdk.graal.compiler.hotspot.amd64.AMD64HotSpotFrameMapBuilder@59edbf8f slotKind: QWORD <|@ <|@
      nr   -1  <|@ instruction v0|QWORD[.] = MOVE input: rsi|QWORD[.] moveKind: QWORD <|@ <|@
      nr   -1  <|@ instruction MOV x: [v0|QWORD[.] + 12] y: 0 size: DWORD <|@ <|@
      nr   -1  <|@ instruction AMD64G1PREWRITEBARRIER (~address: [v0|QWORD[.] + 20], ~expectedObject: -) {temp: v1|QWORD, temp2: v2|QWORD, temp3: -} nonNull: false callTarget: Stub<write_barrier_pre-stack-only(Object)void>@0x7f78998c8200:CallingConvention[out:0|QWORD[.]]:CallingConvention[in:0|QWORD[.]] tool: jdk.graal.compiler.hotspot.amd64.g1.AMD64HotSpotG1BarrierSetLIRTool@33580fae <|@ <|@
      nr   -1  <|@ instruction MOV x: [v0|QWORD[.] + 20] y: -559030611 size: DWORD c: NarrowOop[Object[0]{}] <|@ <|@
      nr   -1  <|@ instruction v3|QWORD[.] = HOTSPOTLOADOBJECTCONSTANT input: Object[Object[0]{}] <|@ <|@
      nr   -1  <|@ instruction AMD64G1POSTWRITEBARRIER (~address: v0|QWORD[.], ~newValue: v3|QWORD[.]) {temp: v4|QWORD, temp2: v5|QWORD} nonNull: true callTarget: Stub<write_barrier_post-stack-only(Word)void>@0x7f78998ca380:CallingConvention[out:0|QWORD]:CallingConvention[in:0|QWORD] tool: jdk.graal.compiler.hotspot.amd64.g1.AMD64HotSpotG1BarrierSetLIRTool@33580fae <|@ <|@
      nr   -1  <|@ instruction RETURN (savedRbp: v6|QWORD, value: -) isStub: false requiresReservedStackAccessCheck: false thread: r15 scratchForSafepointOnReturn: rcx config: jdk.graal.compiler.hotspot.GraalHotSpotVMConfig@4817c460 <|@ <|@
    end_IR
  end_block
end_cfg
begin_bytecodes
     0: aload_0       
     1: invokespecial #0          // java.util.AbstractList.<init>:()void
     4: aload_0       
     5: getstatic     #8          // DEFAULTCAPACITY_EMPTY_ELEMENTDATA:java.lang.Object[]
     8: putfield      #1          // elementData:java.lang.Object[]
    11: return        
   <|@
end_bytecodes
begin_cfg
  name "Before register allocation"
  begin_block
    name "B0"
    from_bci -1
    to_bci -1
    predecessors 
    successors 
    xhandlers
    flags 
    probability 4607182418800017408
    begin_IR
      LIR
      nr    0  <|@ instruction [rsi|QWORD[.], rbp|QWORD] = LABEL alignment: 0 numbPhis: 0 label: ? <|@ <|@
      nr    2  <|@ instruction NOP <|@ <|@
      nr    4  <|@ instruction NOP <|@ <|@
      nr    6  <|@ instruction NOP <|@ <|@
      nr    8  <|@ instruction NOP <|@ <|@
      nr   10  <|@ instruction NOP <|@ <|@
      nr   12  <|@ instruction NOP <|@ <|@
      nr   14  <|@ instruction NOP <|@ <|@
      nr   16  <|@ instruction NOP <|@ <|@
      nr   18  <|@ instruction NOP <|@ <|@
      nr   20  <|@ instruction NOP <|@ <|@
      nr   22  <|@ instruction NOP <|@ <|@
      nr   24  <|@ instruction NOP <|@ <|@
      nr   26  <|@ instruction NOP <|@ <|@
      nr   28  <|@ instruction NOP <|@ <|@
      nr   30  <|@ instruction NOP <|@ <|@
      nr   32  <|@ instruction NOP <|@ <|@
      nr   34  <|@ instruction NOP <|@ <|@
      nr   36  <|@ instruction NOP <|@ <|@
      nr   38  <|@ instruction NOP <|@ <|@
      nr   40  <|@ instruction NOP <|@ <|@
      nr   42  <|@ instruction NOP <|@ <|@
      nr   44  <|@ instruction NOP <|@ <|@
      nr   46  <|@ instruction NOP <|@ <|@
      nr   48  <|@ instruction NOP <|@ <|@
      nr   50  <|@ instruction NOP <|@ <|@
      nr   52  <|@ instruction NOP <|@ <|@
      nr   54  <|@ instruction NOP <|@ <|@
      nr   56  <|@ instruction NOP <|@ <|@
      nr   58  <|@ instruction NOP <|@ <|@
      nr   60  <|@ instruction NOP <|@ <|@
      nr   62  <|@ instruction NOP <|@ <|@
      nr   64  <|@ instruction NOP <|@ <|@
      nr   66  <|@ instruction NOP <|@ <|@
      nr   68  <|@ instruction NOP <|@ <|@
      nr   70  <|@ instruction NOP <|@ <|@
      nr   72  <|@ instruction NOP <|@ <|@
      nr   74  <|@ instruction NOP <|@ <|@
      nr   76  <|@ instruction NOP <|@ <|@
      nr   78  <|@ instruction NOP <|@ <|@
      nr   80  <|@ instruction NOP <|@ <|@
      nr   82  <|@ instruction NOP <|@ <|@
      nr   84  <|@ instruction NOP <|@ <|@
      nr   86  <|@ instruction NOP <|@ <|@
      nr   88  <|@ instruction NOP <|@ <|@
      nr   90  <|@ instruction NOP <|@ <|@
      nr   92  <|@ instruction NOP <|@ <|@
      nr   94  <|@ instruction NOP <|@ <|@
      nr   96  <|@ instruction NOP <|@ <|@
      nr   98  <|@ instruction NOP <|@ <|@
      nr  100  <|@ instruction NOP <|@ <|@
      nr  102  <|@ instruction NOP <|@ <|@
      nr  104  <|@ instruction NOP <|@ <|@
      nr  106  <|@ instruction NOP <|@ <|@
      nr  108  <|@ instruction NOP <|@ <|@
      nr  110  <|@ instruction NOP <|@ <|@
      nr  112  <|@ instruction NOP <|@ <|@
      nr  114  <|@ instruction NOP <|@ <|@
      nr  116  <|@ instruction NOP <|@ <|@
      nr  118  <|@ instruction NOP <|@ <|@
      nr  120  <|@ instruction NOP <|@ <|@
      nr  122  <|@ instruction NOP <|@ <|@
      nr  124  <|@ instruction NOP <|@ <|@
      nr  126  <|@ instruction NOP <|@ <|@
      nr  128  <|@ instruction NOP <|@ <|@
      nr  130  <|@ instruction v6|QWORD = MOVE input: rbp|QWORD moveKind: QWORD <|@ <|@
      nr  132  <|@ instruction [] = HOTSPOTLOCKSTACK frameMapBuilder: jdk.graal.compiler.hotspot.amd64.AMD64HotSpotFrameMapBuilder@59edbf8f slotKind: QWORD <|@ <|@
      nr  134  <|@ instruction v0|QWORD[.] = MOVE input: rsi|QWORD[.] moveKind: QWORD <|@ <|@
      nr  136  <|@ instruction MOV x: [v0|QWORD[.] + 12] y: 0 size: DWORD <|@ <|@
      nr  138  <|@ instruction AMD64G1PREWRITEBARRIER (~address: [v0|QWORD[.] + 20], ~expectedObject: -) {temp: v1|QWORD, temp2: v2|QWORD, temp3: -} nonNull: false callTarget: Stub<write_barrier_pre-stack-only(Object)void>@0x7f78998c8200:CallingConvention[out:0|QWORD[.]]:CallingConvention[in:0|QWORD[.]] tool: jdk.graal.compiler.hotspot.amd64.g1.AMD64HotSpotG1BarrierSetLIRTool@33580fae <|@ <|@
      nr  140  <|@ instruction MOV x: [v0|QWORD[.] + 20] y: -559030611 size: DWORD c: NarrowOop[Object[0]{}] <|@ <|@
      nr  142  <|@ instruction v3|QWORD[.] = HOTSPOTLOADOBJECTCONSTANT input: Object[Object[0]{}] <|@ <|@
      nr  144  <|@ instruction AMD64G1POSTWRITEBARRIER (~address: v0|QWORD[.], ~newValue: v3|QWORD[.]) {temp: v4|QWORD, temp2: v5|QWORD} nonNull: true callTarget: Stub<write_barrier_post-stack-only(Word)void>@0x7f78998ca380:CallingConvention[out:0|QWORD]:CallingConvention[in:0|QWORD] tool: jdk.graal.compiler.hotspot.amd64.g1.AMD64HotSpotG1BarrierSetLIRTool@33580fae <|@ <|@
      nr  146  <|@ instruction RETURN (savedRbp: v6|QWORD, value: -) isStub: false requiresReservedStackAccessCheck: false thread: r15 scratchForSafepointOnReturn: rcx config: jdk.graal.compiler.hotspot.GraalHotSpotVMConfig@4817c460 <|@ <|@
    end_IR
  end_block
end_cfg
begin_bytecodes
     0: aload_0       
     1: invokespecial #0          // java.util.AbstractList.<init>:()void
     4: aload_0       
     5: getstatic     #8          // DEFAULTCAPACITY_EMPTY_ELEMENTDATA:java.lang.Object[]
     8: putfield      #1          // elementData:java.lang.Object[]
    11: return        
   <|@
end_bytecodes
begin_cfg
  name "After SSALinearScanLifetimeAnalysis"
  begin_block
    name "B0"
    from_bci -1
    to_bci -1
    predecessors 
    successors 
    xhandlers
    flags 
    probability 4607182418800017408
    begin_IR
      LIR
      nr    0  <|@ instruction [rsi|QWORD[.], rbp|QWORD] = LABEL alignment: 0 numbPhis: 0 label: ? <|@ <|@
      nr    2  <|@ instruction NOP <|@ <|@
      nr    4  <|@ instruction NOP <|@ <|@
      nr    6  <|@ instruction NOP <|@ <|@
      nr    8  <|@ instruction NOP <|@ <|@
      nr   10  <|@ instruction NOP <|@ <|@
      nr   12  <|@ instruction NOP <|@ <|@
      nr   14  <|@ instruction NOP <|@ <|@
      nr   16  <|@ instruction NOP <|@ <|@
      nr   18  <|@ instruction NOP <|@ <|@
      nr   20  <|@ instruction NOP <|@ <|@
      nr   22  <|@ instruction NOP <|@ <|@
      nr   24  <|@ instruction NOP <|@ <|@
      nr   26  <|@ instruction NOP <|@ <|@
      nr   28  <|@ instruction NOP <|@ <|@
      nr   30  <|@ instruction NOP <|@ <|@
      nr   32  <|@ instruction NOP <|@ <|@
      nr   34  <|@ instruction NOP <|@ <|@
      nr   36  <|@ instruction NOP <|@ <|@
      nr   38  <|@ instruction NOP <|@ <|@
      nr   40  <|@ instruction NOP <|@ <|@
      nr   42  <|@ instruction NOP <|@ <|@
      nr   44  <|@ instruction NOP <|@ <|@
      nr   46  <|@ instruction NOP <|@ <|@
      nr   48  <|@ instruction NOP <|@ <|@
      nr   50  <|@ instruction NOP <|@ <|@
      nr   52  <|@ instruction NOP <|@ <|@
      nr   54  <|@ instruction NOP <|@ <|@
      nr   56  <|@ instruction NOP <|@ <|@
      nr   58  <|@ instruction NOP <|@ <|@
      nr   60  <|@ instruction NOP <|@ <|@
      nr   62  <|@ instruction NOP <|@ <|@
      nr   64  <|@ instruction NOP <|@ <|@
      nr   66  <|@ instruction NOP <|@ <|@
      nr   68  <|@ instruction NOP <|@ <|@
      nr   70  <|@ instruction NOP <|@ <|@
      nr   72  <|@ instruction NOP <|@ <|@
      nr   74  <|@ instruction NOP <|@ <|@
      nr   76  <|@ instruction NOP <|@ <|@
      nr   78  <|@ instruction NOP <|@ <|@
      nr   80  <|@ instruction NOP <|@ <|@
      nr   82  <|@ instruction NOP <|@ <|@
      nr   84  <|@ instruction NOP <|@ <|@
      nr   86  <|@ instruction NOP <|@ <|@
      nr   88  <|@ instruction NOP <|@ <|@
      nr   90  <|@ instruction NOP <|@ <|@
      nr   92  <|@ instruction NOP <|@ <|@
      nr   94  <|@ instruction NOP <|@ <|@
      nr   96  <|@ instruction NOP <|@ <|@
      nr   98  <|@ instruction NOP <|@ <|@
      nr  100  <|@ instruction NOP <|@ <|@
      nr  102  <|@ instruction NOP <|@ <|@
      nr  104  <|@ instruction NOP <|@ <|@
      nr  106  <|@ instruction NOP <|@ <|@
      nr  108  <|@ instruction NOP <|@ <|@
      nr  110  <|@ instruction NOP <|@ <|@
      nr  112  <|@ instruction NOP <|@ <|@
      nr  114  <|@ instruction NOP <|@ <|@
      nr  116  <|@ instruction NOP <|@ <|@
      nr  118  <|@ instruction NOP <|@ <|@
      nr  120  <|@ instruction NOP <|@ <|@
      nr  122  <|@ instruction NOP <|@ <|@
      nr  124  <|@ instruction NOP <|@ <|@
      nr  126  <|@ instruction NOP <|@ <|@
      nr  128  <|@ instruction NOP <|@ <|@
      nr  130  <|@ instruction v6|QWORD = MOVE input: rbp|QWORD moveKind: QWORD <|@ <|@
      nr  132  <|@ instruction [] = HOTSPOTLOCKSTACK frameMapBuilder: jdk.graal.compiler.hotspot.amd64.AMD64HotSpotFrameMapBuilder@59edbf8f slotKind: QWORD <|@ <|@
      nr  134  <|@ instruction v0|QWORD[.] = MOVE input: rsi|QWORD[.] moveKind: QWORD <|@ <|@
      nr  136  <|@ instruction MOV x: [v0|QWORD[.] + 12] y: 0 size: DWORD <|@ <|@
      nr  138  <|@ instruction AMD64G1PREWRITEBARRIER (~address: [v0|QWORD[.] + 20], ~expectedObject: -) {temp: v1|QWORD, temp2: v2|QWORD, temp3: -} nonNull: false callTarget: Stub<write_barrier_pre-stack-only(Object)void>@0x7f78998c8200:CallingConvention[out:0|QWORD[.]]:CallingConvention[in:0|QWORD[.]] tool: jdk.graal.compiler.hotspot.amd64.g1.AMD64HotSpotG1BarrierSetLIRTool@33580fae <|@ <|@
      nr  140  <|@ instruction MOV x: [v0|QWORD[.] + 20] y: -559030611 size: DWORD c: NarrowOop[Object[0]{}] <|@ <|@
      nr  142  <|@ instruction v3|QWORD[.] = HOTSPOTLOADOBJECTCONSTANT input: Object[Object[0]{}] <|@ <|@
      nr  144  <|@ instruction AMD64G1POSTWRITEBARRIER (~address: v0|QWORD[.], ~newValue: v3|QWORD[.]) {temp: v4|QWORD, temp2: v5|QWORD} nonNull: true callTarget: Stub<write_barrier_post-stack-only(Word)void>@0x7f78998ca380:CallingConvention[out:0|QWORD]:CallingConvention[in:0|QWORD] tool: jdk.graal.compiler.hotspot.amd64.g1.AMD64HotSpotG1BarrierSetLIRTool@33580fae <|@ <|@
      nr  146  <|@ instruction RETURN (savedRbp: v6|QWORD, value: -) isStub: false requiresReservedStackAccessCheck: false thread: r15 scratchForSafepointOnReturn: rcx config: jdk.graal.compiler.hotspot.GraalHotSpotVMConfig@4817c460 <|@ <|@
    end_IR
  end_block
end_cfg
begin_bytecodes
     0: aload_0       
     1: invokespecial #0          // java.util.AbstractList.<init>:()void
     4: aload_0       
     5: getstatic     #8          // DEFAULTCAPACITY_EMPTY_ELEMENTDATA:java.lang.Object[]
     8: putfield      #1          // elementData:java.lang.Object[]
    11: return        
   <|@
end_bytecodes
begin_intervals
  name "Before register allocation"
  rbp|q fixed "[rbp|q]" rbp|q -1 [0, 130[ "NoSpillStore"
  rsi|q fixed "[rsi|q]" rsi|q -1 [0, 134[ "NoSpillStore"
  v0|q QWORD "[v0|q]" v0|q rsi|q [134, 145[134 MustHaveRegister 136 MustHaveRegister 138 MustHaveRegister 140 MustHaveRegister 144 MustHaveRegister  "NoSpillStore"
  v1|q QWORD "[v1|q]" v1|q -1 [138, 139[138 MustHaveRegister  "NoDefinitionFound"
  v2|q QWORD "[v2|q]" v2|q -1 [138, 139[138 MustHaveRegister  "NoDefinitionFound"
  v3|q QWORD "[v3|q]" v3|q -1 [142, 145[142 MustHaveRegister 144 MustHaveRegister  "NoSpillStore"
  v4|q QWORD "[v4|q]" v4|q -1 [144, 145[144 MustHaveRegister  "NoDefinitionFound"
  v5|q QWORD "[v5|q]" v5|q -1 [144, 145[144 MustHaveRegister  "NoDefinitionFound"
  v6|q QWORD "[v6|q]" v6|q rbp|q [130, 146[130 MustHaveRegister 146 ShouldHaveRegister  "NoSpillStore"
end_intervals
begin_intervals
  name "After register allocation"
  rbp|q fixed "[rbp|q]" rbp|q -1 [0, 130[ "NoSpillStore"
  rsi|q fixed "[rsi|q]" rsi|q -1 [0, 134[ "NoSpillStore"
  v0|q QWORD "[rsi|q]" v0|q rsi|q [134, 145[134 MustHaveRegister 136 MustHaveRegister 138 MustHaveRegister 140 MustHaveRegister 144 MustHaveRegister  "NoSpillStore"
  v1|q QWORD "[r10|q]" v1|q -1 [138, 139[138 MustHaveRegister  "NoDefinitionFound"
  v2|q QWORD "[r11|q]" v2|q -1 [138, 139[138 MustHaveRegister  "NoDefinitionFound"
  v3|q QWORD "[r10|q]" v3|q -1 [142, 145[142 MustHaveRegister 144 MustHaveRegister  "NoSpillStore"
  v4|q QWORD "[r11|q]" v4|q -1 [144, 145[144 MustHaveRegister  "NoDefinitionFound"
  v5|q QWORD "[r8|q]" v5|q -1 [144, 145[144 MustHaveRegister  "NoDefinitionFound"
  v6|q QWORD "[rbp|q]" v6|q rbp|q [130, 146[130 MustHaveRegister 146 ShouldHaveRegister  "NoSpillStore"
end_intervals
begin_cfg
  name "After LinearScanRegisterAllocation"
  begin_block
    name "B0"
    from_bci -1
    to_bci -1
    predecessors 
    successors 
    xhandlers
    flags 
    probability 4607182418800017408
    begin_IR
      LIR
      nr    0  <|@ instruction [rsi|QWORD[.], rbp|QWORD] = LABEL alignment: 0 numbPhis: 0 label: ? <|@ <|@
      nr    2  <|@ instruction NOP <|@ <|@
      nr    4  <|@ instruction NOP <|@ <|@
      nr    6  <|@ instruction NOP <|@ <|@
      nr    8  <|@ instruction NOP <|@ <|@
      nr   10  <|@ instruction NOP <|@ <|@
      nr   12  <|@ instruction NOP <|@ <|@
      nr   14  <|@ instruction NOP <|@ <|@
      nr   16  <|@ instruction NOP <|@ <|@
      nr   18  <|@ instruction NOP <|@ <|@
      nr   20  <|@ instruction NOP <|@ <|@
      nr   22  <|@ instruction NOP <|@ <|@
      nr   24  <|@ instruction NOP <|@ <|@
      nr   26  <|@ instruction NOP <|@ <|@
      nr   28  <|@ instruction NOP <|@ <|@
      nr   30  <|@ instruction NOP <|@ <|@
      nr   32  <|@ instruction NOP <|@ <|@
      nr   34  <|@ instruction NOP <|@ <|@
      nr   36  <|@ instruction NOP <|@ <|@
      nr   38  <|@ instruction NOP <|@ <|@
      nr   40  <|@ instruction NOP <|@ <|@
      nr   42  <|@ instruction NOP <|@ <|@
      nr   44  <|@ instruction NOP <|@ <|@
      nr   46  <|@ instruction NOP <|@ <|@
      nr   48  <|@ instruction NOP <|@ <|@
      nr   50  <|@ instruction NOP <|@ <|@
      nr   52  <|@ instruction NOP <|@ <|@
      nr   54  <|@ instruction NOP <|@ <|@
      nr   56  <|@ instruction NOP <|@ <|@
      nr   58  <|@ instruction NOP <|@ <|@
      nr   60  <|@ instruction NOP <|@ <|@
      nr   62  <|@ instruction NOP <|@ <|@
      nr   64  <|@ instruction NOP <|@ <|@
      nr   66  <|@ instruction NOP <|@ <|@
      nr   68  <|@ instruction NOP <|@ <|@
      nr   70  <|@ instruction NOP <|@ <|@
      nr   72  <|@ instruction NOP <|@ <|@
      nr   74  <|@ instruction NOP <|@ <|@
      nr   76  <|@ instruction NOP <|@ <|@
      nr   78  <|@ instruction NOP <|@ <|@
      nr   80  <|@ instruction NOP <|@ <|@
      nr   82  <|@ instruction NOP <|@ <|@
      nr   84  <|@ instruction NOP <|@ <|@
      nr   86  <|@ instruction NOP <|@ <|@
      nr   88  <|@ instruction NOP <|@ <|@
      nr   90  <|@ instruction NOP <|@ <|@
      nr   92  <|@ instruction NOP <|@ <|@
      nr   94  <|@ instruction NOP <|@ <|@
      nr   96  <|@ instruction NOP <|@ <|@
      nr   98  <|@ instruction NOP <|@ <|@
      nr  100  <|@ instruction NOP <|@ <|@
      nr  102  <|@ instruction NOP <|@ <|@
      nr  104  <|@ instruction NOP <|@ <|@
      nr  106  <|@ instruction NOP <|@ <|@
      nr  108  <|@ instruction NOP <|@ <|@
      nr  110  <|@ instruction NOP <|@ <|@
      nr  112  <|@ instruction NOP <|@ <|@
      nr  114  <|@ instruction NOP <|@ <|@
      nr  116  <|@ instruction NOP <|@ <|@
      nr  118  <|@ instruction NOP <|@ <|@
      nr  120  <|@ instruction NOP <|@ <|@
      nr  122  <|@ instruction NOP <|@ <|@
      nr  124  <|@ instruction NOP <|@ <|@
      nr  126  <|@ instruction NOP <|@ <|@
      nr  128  <|@ instruction NOP <|@ <|@
      nr  130  <|@ instruction v6|QWORD = MOVE input: rbp|QWORD moveKind: QWORD <|@ <|@
      nr  132  <|@ instruction [] = HOTSPOTLOCKSTACK frameMapBuilder: jdk.graal.compiler.hotspot.amd64.AMD64HotSpotFrameMapBuilder@59edbf8f slotKind: QWORD <|@ <|@
      nr  134  <|@ instruction v0|QWORD[.] = MOVE input: rsi|QWORD[.] moveKind: QWORD <|@ <|@
      nr  136  <|@ instruction MOV x: [v0|QWORD[.] + 12] y: 0 size: DWORD <|@ <|@
      nr  138  <|@ instruction AMD64G1PREWRITEBARRIER (~address: [v0|QWORD[.] + 20], ~expectedObject: -) {temp: v1|QWORD, temp2: v2|QWORD, temp3: -} nonNull: false callTarget: Stub<write_barrier_pre-stack-only(Object)void>@0x7f78998c8200:CallingConvention[out:0|QWORD[.]]:CallingConvention[in:0|QWORD[.]] tool: jdk.graal.compiler.hotspot.amd64.g1.AMD64HotSpotG1BarrierSetLIRTool@33580fae <|@ <|@
      nr  140  <|@ instruction MOV x: [v0|QWORD[.] + 20] y: -559030611 size: DWORD c: NarrowOop[Object[0]{}] <|@ <|@
      nr  142  <|@ instruction v3|QWORD[.] = HOTSPOTLOADOBJECTCONSTANT input: Object[Object[0]{}] <|@ <|@
      nr  144  <|@ instruction AMD64G1POSTWRITEBARRIER (~address: v0|QWORD[.], ~newValue: v3|QWORD[.]) {temp: v4|QWORD, temp2: v5|QWORD} nonNull: true callTarget: Stub<write_barrier_post-stack-only(Word)void>@0x7f78998ca380:CallingConvention[out:0|QWORD]:CallingConvention[in:0|QWORD] tool: jdk.graal.compiler.hotspot.amd64.g1.AMD64HotSpotG1BarrierSetLIRTool@33580fae <|@ <|@
      nr  146  <|@ instruction RETURN (savedRbp: v6|QWORD, value: -) isStub: false requiresReservedStackAccessCheck: false thread: r15 scratchForSafepointOnReturn: rcx config: jdk.graal.compiler.hotspot.GraalHotSpotVMConfig@4817c460 <|@ <|@
    end_IR
  end_block
end_cfg
begin_bytecodes
     0: aload_0       
     1: invokespecial #0          // java.util.AbstractList.<init>:()void
     4: aload_0       
     5: getstatic     #8          // DEFAULTCAPACITY_EMPTY_ELEMENTDATA:java.lang.Object[]
     8: putfield      #1          // elementData:java.lang.Object[]
    11: return        
   <|@
end_bytecodes
begin_intervals
  name "After optimize spill position"
  rbp|q fixed "[rbp|q]" rbp|q -1 [0, 130[ "NoSpillStore"
  rsi|q fixed "[rsi|q]" rsi|q -1 [0, 134[ "NoSpillStore"
  v0|q QWORD "[rsi|q]" v0|q rsi|q [134, 145[134 MustHaveRegister 136 MustHaveRegister 138 MustHaveRegister 140 MustHaveRegister 144 MustHaveRegister  "NoSpillStore"
  v1|q QWORD "[r10|q]" v1|q -1 [138, 139[138 MustHaveRegister  "NoDefinitionFound"
  v2|q QWORD "[r11|q]" v2|q -1 [138, 139[138 MustHaveRegister  "NoDefinitionFound"
  v3|q QWORD "[r10|q]" v3|q -1 [142, 145[142 MustHaveRegister 144 MustHaveRegister  "NoSpillStore"
  v4|q QWORD "[r11|q]" v4|q -1 [144, 145[144 MustHaveRegister  "NoDefinitionFound"
  v5|q QWORD "[r8|q]" v5|q -1 [144, 145[144 MustHaveRegister  "NoDefinitionFound"
  v6|q QWORD "[rbp|q]" v6|q rbp|q [130, 146[130 MustHaveRegister 146 ShouldHaveRegister  "NoSpillStore"
end_intervals
begin_cfg
  name "After LinearScanOptimizeSpillPosition"
  begin_block
    name "B0"
    from_bci -1
    to_bci -1
    predecessors 
    successors 
    xhandlers
    flags 
    probability 4607182418800017408
    begin_IR
      LIR
      nr    0  <|@ instruction [rsi|QWORD[.], rbp|QWORD] = LABEL alignment: 0 numbPhis: 0 label: ? <|@ <|@
      nr    2  <|@ instruction NOP <|@ <|@
      nr    4  <|@ instruction NOP <|@ <|@
      nr    6  <|@ instruction NOP <|@ <|@
      nr    8  <|@ instruction NOP <|@ <|@
      nr   10  <|@ instruction NOP <|@ <|@
      nr   12  <|@ instruction NOP <|@ <|@
      nr   14  <|@ instruction NOP <|@ <|@
      nr   16  <|@ instruction NOP <|@ <|@
      nr   18  <|@ instruction NOP <|@ <|@
      nr   20  <|@ instruction NOP <|@ <|@
      nr   22  <|@ instruction NOP <|@ <|@
      nr   24  <|@ instruction NOP <|@ <|@
      nr   26  <|@ instruction NOP <|@ <|@
      nr   28  <|@ instruction NOP <|@ <|@
      nr   30  <|@ instruction NOP <|@ <|@
      nr   32  <|@ instruction NOP <|@ <|@
      nr   34  <|@ instruction NOP <|@ <|@
      nr   36  <|@ instruction NOP <|@ <|@
      nr   38  <|@ instruction NOP <|@ <|@
      nr   40  <|@ instruction NOP <|@ <|@
      nr   42  <|@ instruction NOP <|@ <|@
      nr   44  <|@ instruction NOP <|@ <|@
      nr   46  <|@ instruction NOP <|@ <|@
      nr   48  <|@ instruction NOP <|@ <|@
      nr   50  <|@ instruction NOP <|@ <|@
      nr   52  <|@ instruction NOP <|@ <|@
      nr   54  <|@ instruction NOP <|@ <|@
      nr   56  <|@ instruction NOP <|@ <|@
      nr   58  <|@ instruction NOP <|@ <|@
      nr   60  <|@ instruction NOP <|@ <|@
      nr   62  <|@ instruction NOP <|@ <|@
      nr   64  <|@ instruction NOP <|@ <|@
      nr   66  <|@ instruction NOP <|@ <|@
      nr   68  <|@ instruction NOP <|@ <|@
      nr   70  <|@ instruction NOP <|@ <|@
      nr   72  <|@ instruction NOP <|@ <|@
      nr   74  <|@ instruction NOP <|@ <|@
      nr   76  <|@ instruction NOP <|@ <|@
      nr   78  <|@ instruction NOP <|@ <|@
      nr   80  <|@ instruction NOP <|@ <|@
      nr   82  <|@ instruction NOP <|@ <|@
      nr   84  <|@ instruction NOP <|@ <|@
      nr   86  <|@ instruction NOP <|@ <|@
      nr   88  <|@ instruction NOP <|@ <|@
      nr   90  <|@ instruction NOP <|@ <|@
      nr   92  <|@ instruction NOP <|@ <|@
      nr   94  <|@ instruction NOP <|@ <|@
      nr   96  <|@ instruction NOP <|@ <|@
      nr   98  <|@ instruction NOP <|@ <|@
      nr  100  <|@ instruction NOP <|@ <|@
      nr  102  <|@ instruction NOP <|@ <|@
      nr  104  <|@ instruction NOP <|@ <|@
      nr  106  <|@ instruction NOP <|@ <|@
      nr  108  <|@ instruction NOP <|@ <|@
      nr  110  <|@ instruction NOP <|@ <|@
      nr  112  <|@ instruction NOP <|@ <|@
      nr  114  <|@ instruction NOP <|@ <|@
      nr  116  <|@ instruction NOP <|@ <|@
      nr  118  <|@ instruction NOP <|@ <|@
      nr  120  <|@ instruction NOP <|@ <|@
      nr  122  <|@ instruction NOP <|@ <|@
      nr  124  <|@ instruction NOP <|@ <|@
      nr  126  <|@ instruction NOP <|@ <|@
      nr  128  <|@ instruction NOP <|@ <|@
      nr  130  <|@ instruction v6|QWORD = MOVE input: rbp|QWORD moveKind: QWORD <|@ <|@
      nr  132  <|@ instruction [] = HOTSPOTLOCKSTACK frameMapBuilder: jdk.graal.compiler.hotspot.amd64.AMD64HotSpotFrameMapBuilder@59edbf8f slotKind: QWORD <|@ <|@
      nr  134  <|@ instruction v0|QWORD[.] = MOVE input: rsi|QWORD[.] moveKind: QWORD <|@ <|@
      nr  136  <|@ instruction MOV x: [v0|QWORD[.] + 12] y: 0 size: DWORD <|@ <|@
      nr  138  <|@ instruction AMD64G1PREWRITEBARRIER (~address: [v0|QWORD[.] + 20], ~expectedObject: -) {temp: v1|QWORD, temp2: v2|QWORD, temp3: -} nonNull: false callTarget: Stub<write_barrier_pre-stack-only(Object)void>@0x7f78998c8200:CallingConvention[out:0|QWORD[.]]:CallingConvention[in:0|QWORD[.]] tool: jdk.graal.compiler.hotspot.amd64.g1.AMD64HotSpotG1BarrierSetLIRTool@33580fae <|@ <|@
      nr  140  <|@ instruction MOV x: [v0|QWORD[.] + 20] y: -559030611 size: DWORD c: NarrowOop[Object[0]{}] <|@ <|@
      nr  142  <|@ instruction v3|QWORD[.] = HOTSPOTLOADOBJECTCONSTANT input: Object[Object[0]{}] <|@ <|@
      nr  144  <|@ instruction AMD64G1POSTWRITEBARRIER (~address: v0|QWORD[.], ~newValue: v3|QWORD[.]) {temp: v4|QWORD, temp2: v5|QWORD} nonNull: true callTarget: Stub<write_barrier_post-stack-only(Word)void>@0x7f78998ca380:CallingConvention[out:0|QWORD]:CallingConvention[in:0|QWORD] tool: jdk.graal.compiler.hotspot.amd64.g1.AMD64HotSpotG1BarrierSetLIRTool@33580fae <|@ <|@
      nr  146  <|@ instruction RETURN (savedRbp: v6|QWORD, value: -) isStub: false requiresReservedStackAccessCheck: false thread: r15 scratchForSafepointOnReturn: rcx config: jdk.graal.compiler.hotspot.GraalHotSpotVMConfig@4817c460 <|@ <|@
    end_IR
  end_block
end_cfg
begin_bytecodes
     0: aload_0       
     1: invokespecial #0          // java.util.AbstractList.<init>:()void
     4: aload_0       
     5: getstatic     #8          // DEFAULTCAPACITY_EMPTY_ELEMENTDATA:java.lang.Object[]
     8: putfield      #1          // elementData:java.lang.Object[]
    11: return        
   <|@
end_bytecodes
begin_intervals
  name "After resolve data flow"
  rbp|q fixed "[rbp|q]" rbp|q -1 [0, 130[ "NoSpillStore"
  rsi|q fixed "[rsi|q]" rsi|q -1 [0, 134[ "NoSpillStore"
  v0|q QWORD "[rsi|q]" v0|q rsi|q [134, 145[134 MustHaveRegister 136 MustHaveRegister 138 MustHaveRegister 140 MustHaveRegister 144 MustHaveRegister  "NoSpillStore"
  v1|q QWORD "[r10|q]" v1|q -1 [138, 139[138 MustHaveRegister  "NoDefinitionFound"
  v2|q QWORD "[r11|q]" v2|q -1 [138, 139[138 MustHaveRegister  "NoDefinitionFound"
  v3|q QWORD "[r10|q]" v3|q -1 [142, 145[142 MustHaveRegister 144 MustHaveRegister  "NoSpillStore"
  v4|q QWORD "[r11|q]" v4|q -1 [144, 145[144 MustHaveRegister  "NoDefinitionFound"
  v5|q QWORD "[r8|q]" v5|q -1 [144, 145[144 MustHaveRegister  "NoDefinitionFound"
  v6|q QWORD "[rbp|q]" v6|q rbp|q [130, 146[130 MustHaveRegister 146 ShouldHaveRegister  "NoSpillStore"
end_intervals
begin_cfg
  name "After SSALinearScanResolveDataFlow"
  begin_block
    name "B0"
    from_bci -1
    to_bci -1
    predecessors 
    successors 
    xhandlers
    flags 
    probability 4607182418800017408
    begin_IR
      LIR
      nr    0  <|@ instruction [rsi|QWORD[.], rbp|QWORD] = LABEL alignment: 0 numbPhis: 0 label: ? <|@ <|@
      nr    2  <|@ instruction NOP <|@ <|@
      nr    4  <|@ instruction NOP <|@ <|@
      nr    6  <|@ instruction NOP <|@ <|@
      nr    8  <|@ instruction NOP <|@ <|@
      nr   10  <|@ instruction NOP <|@ <|@
      nr   12  <|@ instruction NOP <|@ <|@
      nr   14  <|@ instruction NOP <|@ <|@
      nr   16  <|@ instruction NOP <|@ <|@
      nr   18  <|@ instruction NOP <|@ <|@
      nr   20  <|@ instruction NOP <|@ <|@
      nr   22  <|@ instruction NOP <|@ <|@
      nr   24  <|@ instruction NOP <|@ <|@
      nr   26  <|@ instruction NOP <|@ <|@
      nr   28  <|@ instruction NOP <|@ <|@
      nr   30  <|@ instruction NOP <|@ <|@
      nr   32  <|@ instruction NOP <|@ <|@
      nr   34  <|@ instruction NOP <|@ <|@
      nr   36  <|@ instruction NOP <|@ <|@
      nr   38  <|@ instruction NOP <|@ <|@
      nr   40  <|@ instruction NOP <|@ <|@
      nr   42  <|@ instruction NOP <|@ <|@
      nr   44  <|@ instruction NOP <|@ <|@
      nr   46  <|@ instruction NOP <|@ <|@
      nr   48  <|@ instruction NOP <|@ <|@
      nr   50  <|@ instruction NOP <|@ <|@
      nr   52  <|@ instruction NOP <|@ <|@
      nr   54  <|@ instruction NOP <|@ <|@
      nr   56  <|@ instruction NOP <|@ <|@
      nr   58  <|@ instruction NOP <|@ <|@
      nr   60  <|@ instruction NOP <|@ <|@
      nr   62  <|@ instruction NOP <|@ <|@
      nr   64  <|@ instruction NOP <|@ <|@
      nr   66  <|@ instruction NOP <|@ <|@
      nr   68  <|@ instruction NOP <|@ <|@
      nr   70  <|@ instruction NOP <|@ <|@
      nr   72  <|@ instruction NOP <|@ <|@
      nr   74  <|@ instruction NOP <|@ <|@
      nr   76  <|@ instruction NOP <|@ <|@
      nr   78  <|@ instruction NOP <|@ <|@
      nr   80  <|@ instruction NOP <|@ <|@
      nr   82  <|@ instruction NOP <|@ <|@
      nr   84  <|@ instruction NOP <|@ <|@
      nr   86  <|@ instruction NOP <|@ <|@
      nr   88  <|@ instruction NOP <|@ <|@
      nr   90  <|@ instruction NOP <|@ <|@
      nr   92  <|@ instruction NOP <|@ <|@
      nr   94  <|@ instruction NOP <|@ <|@
      nr   96  <|@ instruction NOP <|@ <|@
      nr   98  <|@ instruction NOP <|@ <|@
      nr  100  <|@ instruction NOP <|@ <|@
      nr  102  <|@ instruction NOP <|@ <|@
      nr  104  <|@ instruction NOP <|@ <|@
      nr  106  <|@ instruction NOP <|@ <|@
      nr  108  <|@ instruction NOP <|@ <|@
      nr  110  <|@ instruction NOP <|@ <|@
      nr  112  <|@ instruction NOP <|@ <|@
      nr  114  <|@ instruction NOP <|@ <|@
      nr  116  <|@ instruction NOP <|@ <|@
      nr  118  <|@ instruction NOP <|@ <|@
      nr  120  <|@ instruction NOP <|@ <|@
      nr  122  <|@ instruction NOP <|@ <|@
      nr  124  <|@ instruction NOP <|@ <|@
      nr  126  <|@ instruction NOP <|@ <|@
      nr  128  <|@ instruction NOP <|@ <|@
      nr  130  <|@ instruction v6|QWORD = MOVE input: rbp|QWORD moveKind: QWORD <|@ <|@
      nr  132  <|@ instruction [] = HOTSPOTLOCKSTACK frameMapBuilder: jdk.graal.compiler.hotspot.amd64.AMD64HotSpotFrameMapBuilder@59edbf8f slotKind: QWORD <|@ <|@
      nr  134  <|@ instruction v0|QWORD[.] = MOVE input: rsi|QWORD[.] moveKind: QWORD <|@ <|@
      nr  136  <|@ instruction MOV x: [v0|QWORD[.] + 12] y: 0 size: DWORD <|@ <|@
      nr  138  <|@ instruction AMD64G1PREWRITEBARRIER (~address: [v0|QWORD[.] + 20], ~expectedObject: -) {temp: v1|QWORD, temp2: v2|QWORD, temp3: -} nonNull: false callTarget: Stub<write_barrier_pre-stack-only(Object)void>@0x7f78998c8200:CallingConvention[out:0|QWORD[.]]:CallingConvention[in:0|QWORD[.]] tool: jdk.graal.compiler.hotspot.amd64.g1.AMD64HotSpotG1BarrierSetLIRTool@33580fae <|@ <|@
      nr  140  <|@ instruction MOV x: [v0|QWORD[.] + 20] y: -559030611 size: DWORD c: NarrowOop[Object[0]{}] <|@ <|@
      nr  142  <|@ instruction v3|QWORD[.] = HOTSPOTLOADOBJECTCONSTANT input: Object[Object[0]{}] <|@ <|@
      nr  144  <|@ instruction AMD64G1POSTWRITEBARRIER (~address: v0|QWORD[.], ~newValue: v3|QWORD[.]) {temp: v4|QWORD, temp2: v5|QWORD} nonNull: true callTarget: Stub<write_barrier_post-stack-only(Word)void>@0x7f78998ca380:CallingConvention[out:0|QWORD]:CallingConvention[in:0|QWORD] tool: jdk.graal.compiler.hotspot.amd64.g1.AMD64HotSpotG1BarrierSetLIRTool@33580fae <|@ <|@
      nr  146  <|@ instruction RETURN (savedRbp: v6|QWORD, value: -) isStub: false requiresReservedStackAccessCheck: false thread: r15 scratchForSafepointOnReturn: rcx config: jdk.graal.compiler.hotspot.GraalHotSpotVMConfig@4817c460 <|@ <|@
    end_IR
  end_block
end_cfg
begin_bytecodes
     0: aload_0       
     1: invokespecial #0          // java.util.AbstractList.<init>:()void
     4: aload_0       
     5: getstatic     #8          // DEFAULTCAPACITY_EMPTY_ELEMENTDATA:java.lang.Object[]
     8: putfield      #1          // elementData:java.lang.Object[]
    11: return        
   <|@
end_bytecodes
begin_cfg
  name "After SSALinearScanEliminateSpillMove"
  begin_block
    name "B0"
    from_bci -1
    to_bci -1
    predecessors 
    successors 
    xhandlers
    flags 
    probability 4607182418800017408
    begin_IR
      LIR
      nr    0  <|@ instruction [rsi|QWORD[.], rbp|QWORD] = LABEL alignment: 0 numbPhis: 0 label: ? <|@ <|@
      nr    2  <|@ instruction NOP <|@ <|@
      nr    4  <|@ instruction NOP <|@ <|@
      nr    6  <|@ instruction NOP <|@ <|@
      nr    8  <|@ instruction NOP <|@ <|@
      nr   10  <|@ instruction NOP <|@ <|@
      nr   12  <|@ instruction NOP <|@ <|@
      nr   14  <|@ instruction NOP <|@ <|@
      nr   16  <|@ instruction NOP <|@ <|@
      nr   18  <|@ instruction NOP <|@ <|@
      nr   20  <|@ instruction NOP <|@ <|@
      nr   22  <|@ instruction NOP <|@ <|@
      nr   24  <|@ instruction NOP <|@ <|@
      nr   26  <|@ instruction NOP <|@ <|@
      nr   28  <|@ instruction NOP <|@ <|@
      nr   30  <|@ instruction NOP <|@ <|@
      nr   32  <|@ instruction NOP <|@ <|@
      nr   34  <|@ instruction NOP <|@ <|@
      nr   36  <|@ instruction NOP <|@ <|@
      nr   38  <|@ instruction NOP <|@ <|@
      nr   40  <|@ instruction NOP <|@ <|@
      nr   42  <|@ instruction NOP <|@ <|@
      nr   44  <|@ instruction NOP <|@ <|@
      nr   46  <|@ instruction NOP <|@ <|@
      nr   48  <|@ instruction NOP <|@ <|@
      nr   50  <|@ instruction NOP <|@ <|@
      nr   52  <|@ instruction NOP <|@ <|@
      nr   54  <|@ instruction NOP <|@ <|@
      nr   56  <|@ instruction NOP <|@ <|@
      nr   58  <|@ instruction NOP <|@ <|@
      nr   60  <|@ instruction NOP <|@ <|@
      nr   62  <|@ instruction NOP <|@ <|@
      nr   64  <|@ instruction NOP <|@ <|@
      nr   66  <|@ instruction NOP <|@ <|@
      nr   68  <|@ instruction NOP <|@ <|@
      nr   70  <|@ instruction NOP <|@ <|@
      nr   72  <|@ instruction NOP <|@ <|@
      nr   74  <|@ instruction NOP <|@ <|@
      nr   76  <|@ instruction NOP <|@ <|@
      nr   78  <|@ instruction NOP <|@ <|@
      nr   80  <|@ instruction NOP <|@ <|@
      nr   82  <|@ instruction NOP <|@ <|@
      nr   84  <|@ instruction NOP <|@ <|@
      nr   86  <|@ instruction NOP <|@ <|@
      nr   88  <|@ instruction NOP <|@ <|@
      nr   90  <|@ instruction NOP <|@ <|@
      nr   92  <|@ instruction NOP <|@ <|@
      nr   94  <|@ instruction NOP <|@ <|@
      nr   96  <|@ instruction NOP <|@ <|@
      nr   98  <|@ instruction NOP <|@ <|@
      nr  100  <|@ instruction NOP <|@ <|@
      nr  102  <|@ instruction NOP <|@ <|@
      nr  104  <|@ instruction NOP <|@ <|@
      nr  106  <|@ instruction NOP <|@ <|@
      nr  108  <|@ instruction NOP <|@ <|@
      nr  110  <|@ instruction NOP <|@ <|@
      nr  112  <|@ instruction NOP <|@ <|@
      nr  114  <|@ instruction NOP <|@ <|@
      nr  116  <|@ instruction NOP <|@ <|@
      nr  118  <|@ instruction NOP <|@ <|@
      nr  120  <|@ instruction NOP <|@ <|@
      nr  122  <|@ instruction NOP <|@ <|@
      nr  124  <|@ instruction NOP <|@ <|@
      nr  126  <|@ instruction NOP <|@ <|@
      nr  128  <|@ instruction NOP <|@ <|@
      nr  130  <|@ instruction v6|QWORD = MOVE input: rbp|QWORD moveKind: QWORD <|@ <|@
      nr  132  <|@ instruction [] = HOTSPOTLOCKSTACK frameMapBuilder: jdk.graal.compiler.hotspot.amd64.AMD64HotSpotFrameMapBuilder@59edbf8f slotKind: QWORD <|@ <|@
      nr  134  <|@ instruction v0|QWORD[.] = MOVE input: rsi|QWORD[.] moveKind: QWORD <|@ <|@
      nr  136  <|@ instruction MOV x: [v0|QWORD[.] + 12] y: 0 size: DWORD <|@ <|@
      nr  138  <|@ instruction AMD64G1PREWRITEBARRIER (~address: [v0|QWORD[.] + 20], ~expectedObject: -) {temp: v1|QWORD, temp2: v2|QWORD, temp3: -} nonNull: false callTarget: Stub<write_barrier_pre-stack-only(Object)void>@0x7f78998c8200:CallingConvention[out:0|QWORD[.]]:CallingConvention[in:0|QWORD[.]] tool: jdk.graal.compiler.hotspot.amd64.g1.AMD64HotSpotG1BarrierSetLIRTool@33580fae <|@ <|@
      nr  140  <|@ instruction MOV x: [v0|QWORD[.] + 20] y: -559030611 size: DWORD c: NarrowOop[Object[0]{}] <|@ <|@
      nr  142  <|@ instruction v3|QWORD[.] = HOTSPOTLOADOBJECTCONSTANT input: Object[Object[0]{}] <|@ <|@
      nr  144  <|@ instruction AMD64G1POSTWRITEBARRIER (~address: v0|QWORD[.], ~newValue: v3|QWORD[.]) {temp: v4|QWORD, temp2: v5|QWORD} nonNull: true callTarget: Stub<write_barrier_post-stack-only(Word)void>@0x7f78998ca380:CallingConvention[out:0|QWORD]:CallingConvention[in:0|QWORD] tool: jdk.graal.compiler.hotspot.amd64.g1.AMD64HotSpotG1BarrierSetLIRTool@33580fae <|@ <|@
      nr  146  <|@ instruction RETURN (savedRbp: v6|QWORD, value: -) isStub: false requiresReservedStackAccessCheck: false thread: r15 scratchForSafepointOnReturn: rcx config: jdk.graal.compiler.hotspot.GraalHotSpotVMConfig@4817c460 <|@ <|@
    end_IR
  end_block
end_cfg
begin_bytecodes
     0: aload_0       
     1: invokespecial #0          // java.util.AbstractList.<init>:()void
     4: aload_0       
     5: getstatic     #8          // DEFAULTCAPACITY_EMPTY_ELEMENTDATA:java.lang.Object[]
     8: putfield      #1          // elementData:java.lang.Object[]
    11: return        
   <|@
end_bytecodes
begin_cfg
  name "After LinearScanAssignLocations"
  begin_block
    name "B0"
    from_bci -1
    to_bci -1
    predecessors 
    successors 
    xhandlers
    flags 
    probability 4607182418800017408
    begin_IR
      LIR
      nr    0  <|@ instruction [rsi|QWORD[.], rbp|QWORD] = LABEL alignment: 0 numbPhis: 0 label: ? <|@ <|@
      nr    2  <|@ instruction NOP <|@ <|@
      nr    4  <|@ instruction NOP <|@ <|@
      nr    6  <|@ instruction NOP <|@ <|@
      nr    8  <|@ instruction NOP <|@ <|@
      nr   10  <|@ instruction NOP <|@ <|@
      nr   12  <|@ instruction NOP <|@ <|@
      nr   14  <|@ instruction NOP <|@ <|@
      nr   16  <|@ instruction NOP <|@ <|@
      nr   18  <|@ instruction NOP <|@ <|@
      nr   20  <|@ instruction NOP <|@ <|@
      nr   22  <|@ instruction NOP <|@ <|@
      nr   24  <|@ instruction NOP <|@ <|@
      nr   26  <|@ instruction NOP <|@ <|@
      nr   28  <|@ instruction NOP <|@ <|@
      nr   30  <|@ instruction NOP <|@ <|@
      nr   32  <|@ instruction NOP <|@ <|@
      nr   34  <|@ instruction NOP <|@ <|@
      nr   36  <|@ instruction NOP <|@ <|@
      nr   38  <|@ instruction NOP <|@ <|@
      nr   40  <|@ instruction NOP <|@ <|@
      nr   42  <|@ instruction NOP <|@ <|@
      nr   44  <|@ instruction NOP <|@ <|@
      nr   46  <|@ instruction NOP <|@ <|@
      nr   48  <|@ instruction NOP <|@ <|@
      nr   50  <|@ instruction NOP <|@ <|@
      nr   52  <|@ instruction NOP <|@ <|@
      nr   54  <|@ instruction NOP <|@ <|@
      nr   56  <|@ instruction NOP <|@ <|@
      nr   58  <|@ instruction NOP <|@ <|@
      nr   60  <|@ instruction NOP <|@ <|@
      nr   62  <|@ instruction NOP <|@ <|@
      nr   64  <|@ instruction NOP <|@ <|@
      nr   66  <|@ instruction NOP <|@ <|@
      nr   68  <|@ instruction NOP <|@ <|@
      nr   70  <|@ instruction NOP <|@ <|@
      nr   72  <|@ instruction NOP <|@ <|@
      nr   74  <|@ instruction NOP <|@ <|@
      nr   76  <|@ instruction NOP <|@ <|@
      nr   78  <|@ instruction NOP <|@ <|@
      nr   80  <|@ instruction NOP <|@ <|@
      nr   82  <|@ instruction NOP <|@ <|@
      nr   84  <|@ instruction NOP <|@ <|@
      nr   86  <|@ instruction NOP <|@ <|@
      nr   88  <|@ instruction NOP <|@ <|@
      nr   90  <|@ instruction NOP <|@ <|@
      nr   92  <|@ instruction NOP <|@ <|@
      nr   94  <|@ instruction NOP <|@ <|@
      nr   96  <|@ instruction NOP <|@ <|@
      nr   98  <|@ instruction NOP <|@ <|@
      nr  100  <|@ instruction NOP <|@ <|@
      nr  102  <|@ instruction NOP <|@ <|@
      nr  104  <|@ instruction NOP <|@ <|@
      nr  106  <|@ instruction NOP <|@ <|@
      nr  108  <|@ instruction NOP <|@ <|@
      nr  110  <|@ instruction NOP <|@ <|@
      nr  112  <|@ instruction NOP <|@ <|@
      nr  114  <|@ instruction NOP <|@ <|@
      nr  116  <|@ instruction NOP <|@ <|@
      nr  118  <|@ instruction NOP <|@ <|@
      nr  120  <|@ instruction NOP <|@ <|@
      nr  122  <|@ instruction NOP <|@ <|@
      nr  124  <|@ instruction NOP <|@ <|@
      nr  126  <|@ instruction NOP <|@ <|@
      nr  128  <|@ instruction NOP <|@ <|@
      nr  132  <|@ instruction [] = HOTSPOTLOCKSTACK frameMapBuilder: jdk.graal.compiler.hotspot.amd64.AMD64HotSpotFrameMapBuilder@59edbf8f slotKind: QWORD <|@ <|@
      nr  136  <|@ instruction MOV x: [rsi|QWORD[.] + 12] y: 0 size: DWORD <|@ <|@
      nr  138  <|@ instruction AMD64G1PREWRITEBARRIER (~address: [rsi|QWORD[.] + 20], ~expectedObject: -) {temp: r10|QWORD, temp2: r11|QWORD, temp3: -} nonNull: false callTarget: Stub<write_barrier_pre-stack-only(Object)void>@0x7f78998c8200:CallingConvention[out:0|QWORD[.]]:CallingConvention[in:0|QWORD[.]] tool: jdk.graal.compiler.hotspot.amd64.g1.AMD64HotSpotG1BarrierSetLIRTool@33580fae <|@ <|@
      nr  140  <|@ instruction MOV x: [rsi|QWORD[.] + 20] y: -559030611 size: DWORD c: NarrowOop[Object[0]{}] <|@ <|@
      nr  142  <|@ instruction r10|QWORD[.] = HOTSPOTLOADOBJECTCONSTANT input: Object[Object[0]{}] <|@ <|@
      nr  144  <|@ instruction AMD64G1POSTWRITEBARRIER (~address: rsi|QWORD[.], ~newValue: r10|QWORD[.]) {temp: r11|QWORD, temp2: r8|QWORD} nonNull: true callTarget: Stub<write_barrier_post-stack-only(Word)void>@0x7f78998ca380:CallingConvention[out:0|QWORD]:CallingConvention[in:0|QWORD] tool: jdk.graal.compiler.hotspot.amd64.g1.AMD64HotSpotG1BarrierSetLIRTool@33580fae <|@ <|@
      nr  146  <|@ instruction RETURN (savedRbp: rbp|QWORD, value: -) isStub: false requiresReservedStackAccessCheck: false thread: r15 scratchForSafepointOnReturn: rcx config: jdk.graal.compiler.hotspot.GraalHotSpotVMConfig@4817c460 <|@ <|@
    end_IR
  end_block
end_cfg
begin_bytecodes
     0: aload_0       
     1: invokespecial #0          // java.util.AbstractList.<init>:()void
     4: aload_0       
     5: getstatic     #8          // DEFAULTCAPACITY_EMPTY_ELEMENTDATA:java.lang.Object[]
     8: putfield      #1          // elementData:java.lang.Object[]
    11: return        
   <|@
end_bytecodes
begin_cfg
  name "After LinearScan"
  begin_block
    name "B0"
    from_bci -1
    to_bci -1
    predecessors 
    successors 
    xhandlers
    flags 
    probability 4607182418800017408
    begin_IR
      LIR
      nr    0  <|@ instruction [rsi|QWORD[.], rbp|QWORD] = LABEL alignment: 0 numbPhis: 0 label: ? <|@ <|@
      nr    2  <|@ instruction NOP <|@ <|@
      nr    4  <|@ instruction NOP <|@ <|@
      nr    6  <|@ instruction NOP <|@ <|@
      nr    8  <|@ instruction NOP <|@ <|@
      nr   10  <|@ instruction NOP <|@ <|@
      nr   12  <|@ instruction NOP <|@ <|@
      nr   14  <|@ instruction NOP <|@ <|@
      nr   16  <|@ instruction NOP <|@ <|@
      nr   18  <|@ instruction NOP <|@ <|@
      nr   20  <|@ instruction NOP <|@ <|@
      nr   22  <|@ instruction NOP <|@ <|@
      nr   24  <|@ instruction NOP <|@ <|@
      nr   26  <|@ instruction NOP <|@ <|@
      nr   28  <|@ instruction NOP <|@ <|@
      nr   30  <|@ instruction NOP <|@ <|@
      nr   32  <|@ instruction NOP <|@ <|@
      nr   34  <|@ instruction NOP <|@ <|@
      nr   36  <|@ instruction NOP <|@ <|@
      nr   38  <|@ instruction NOP <|@ <|@
      nr   40  <|@ instruction NOP <|@ <|@
      nr   42  <|@ instruction NOP <|@ <|@
      nr   44  <|@ instruction NOP <|@ <|@
      nr   46  <|@ instruction NOP <|@ <|@
      nr   48  <|@ instruction NOP <|@ <|@
      nr   50  <|@ instruction NOP <|@ <|@
      nr   52  <|@ instruction NOP <|@ <|@
      nr   54  <|@ instruction NOP <|@ <|@
      nr   56  <|@ instruction NOP <|@ <|@
      nr   58  <|@ instruction NOP <|@ <|@
      nr   60  <|@ instruction NOP <|@ <|@
      nr   62  <|@ instruction NOP <|@ <|@
      nr   64  <|@ instruction NOP <|@ <|@
      nr   66  <|@ instruction NOP <|@ <|@
      nr   68  <|@ instruction NOP <|@ <|@
      nr   70  <|@ instruction NOP <|@ <|@
      nr   72  <|@ instruction NOP <|@ <|@
      nr   74  <|@ instruction NOP <|@ <|@
      nr   76  <|@ instruction NOP <|@ <|@
      nr   78  <|@ instruction NOP <|@ <|@
      nr   80  <|@ instruction NOP <|@ <|@
      nr   82  <|@ instruction NOP <|@ <|@
      nr   84  <|@ instruction NOP <|@ <|@
      nr   86  <|@ instruction NOP <|@ <|@
      nr   88  <|@ instruction NOP <|@ <|@
      nr   90  <|@ instruction NOP <|@ <|@
      nr   92  <|@ instruction NOP <|@ <|@
      nr   94  <|@ instruction NOP <|@ <|@
      nr   96  <|@ instruction NOP <|@ <|@
      nr   98  <|@ instruction NOP <|@ <|@
      nr  100  <|@ instruction NOP <|@ <|@
      nr  102  <|@ instruction NOP <|@ <|@
      nr  104  <|@ instruction NOP <|@ <|@
      nr  106  <|@ instruction NOP <|@ <|@
      nr  108  <|@ instruction NOP <|@ <|@
      nr  110  <|@ instruction NOP <|@ <|@
      nr  112  <|@ instruction NOP <|@ <|@
      nr  114  <|@ instruction NOP <|@ <|@
      nr  116  <|@ instruction NOP <|@ <|@
      nr  118  <|@ instruction NOP <|@ <|@
      nr  120  <|@ instruction NOP <|@ <|@
      nr  122  <|@ instruction NOP <|@ <|@
      nr  124  <|@ instruction NOP <|@ <|@
      nr  126  <|@ instruction NOP <|@ <|@
      nr  128  <|@ instruction NOP <|@ <|@
      nr  132  <|@ instruction [] = HOTSPOTLOCKSTACK frameMapBuilder: jdk.graal.compiler.hotspot.amd64.AMD64HotSpotFrameMapBuilder@59edbf8f slotKind: QWORD <|@ <|@
      nr  136  <|@ instruction MOV x: [rsi|QWORD[.] + 12] y: 0 size: DWORD <|@ <|@
      nr  138  <|@ instruction AMD64G1PREWRITEBARRIER (~address: [rsi|QWORD[.] + 20], ~expectedObject: -) {temp: r10|QWORD, temp2: r11|QWORD, temp3: -} nonNull: false callTarget: Stub<write_barrier_pre-stack-only(Object)void>@0x7f78998c8200:CallingConvention[out:0|QWORD[.]]:CallingConvention[in:0|QWORD[.]] tool: jdk.graal.compiler.hotspot.amd64.g1.AMD64HotSpotG1BarrierSetLIRTool@33580fae <|@ <|@
      nr  140  <|@ instruction MOV x: [rsi|QWORD[.] + 20] y: -559030611 size: DWORD c: NarrowOop[Object[0]{}] <|@ <|@
      nr  142  <|@ instruction r10|QWORD[.] = HOTSPOTLOADOBJECTCONSTANT input: Object[Object[0]{}] <|@ <|@
      nr  144  <|@ instruction AMD64G1POSTWRITEBARRIER (~address: rsi|QWORD[.], ~newValue: r10|QWORD[.]) {temp: r11|QWORD, temp2: r8|QWORD} nonNull: true callTarget: Stub<write_barrier_post-stack-only(Word)void>@0x7f78998ca380:CallingConvention[out:0|QWORD]:CallingConvention[in:0|QWORD] tool: jdk.graal.compiler.hotspot.amd64.g1.AMD64HotSpotG1BarrierSetLIRTool@33580fae <|@ <|@
      nr  146  <|@ instruction RETURN (savedRbp: rbp|QWORD, value: -) isStub: false requiresReservedStackAccessCheck: false thread: r15 scratchForSafepointOnReturn: rcx config: jdk.graal.compiler.hotspot.GraalHotSpotVMConfig@4817c460 <|@ <|@
    end_IR
  end_block
end_cfg
begin_bytecodes
     0: aload_0       
     1: invokespecial #0          // java.util.AbstractList.<init>:()void
     4: aload_0       
     5: getstatic     #8          // DEFAULTCAPACITY_EMPTY_ELEMENTDATA:java.lang.Object[]
     8: putfield      #1          // elementData:java.lang.Object[]
    11: return        
   <|@
end_bytecodes
begin_cfg
  name "After LSStackSlotAllocator"
  begin_block
    name "B0"
    from_bci -1
    to_bci -1
    predecessors 
    successors 
    xhandlers
    flags 
    probability 4607182418800017408
    begin_IR
      LIR
      nr    0  <|@ instruction [rsi|QWORD[.], rbp|QWORD] = LABEL alignment: 0 numbPhis: 0 label: ? <|@ <|@
      nr    2  <|@ instruction NOP <|@ <|@
      nr    4  <|@ instruction NOP <|@ <|@
      nr    6  <|@ instruction NOP <|@ <|@
      nr    8  <|@ instruction NOP <|@ <|@
      nr   10  <|@ instruction NOP <|@ <|@
      nr   12  <|@ instruction NOP <|@ <|@
      nr   14  <|@ instruction NOP <|@ <|@
      nr   16  <|@ instruction NOP <|@ <|@
      nr   18  <|@ instruction NOP <|@ <|@
      nr   20  <|@ instruction NOP <|@ <|@
      nr   22  <|@ instruction NOP <|@ <|@
      nr   24  <|@ instruction NOP <|@ <|@
      nr   26  <|@ instruction NOP <|@ <|@
      nr   28  <|@ instruction NOP <|@ <|@
      nr   30  <|@ instruction NOP <|@ <|@
      nr   32  <|@ instruction NOP <|@ <|@
      nr   34  <|@ instruction NOP <|@ <|@
      nr   36  <|@ instruction NOP <|@ <|@
      nr   38  <|@ instruction NOP <|@ <|@
      nr   40  <|@ instruction NOP <|@ <|@
      nr   42  <|@ instruction NOP <|@ <|@
      nr   44  <|@ instruction NOP <|@ <|@
      nr   46  <|@ instruction NOP <|@ <|@
      nr   48  <|@ instruction NOP <|@ <|@
      nr   50  <|@ instruction NOP <|@ <|@
      nr   52  <|@ instruction NOP <|@ <|@
      nr   54  <|@ instruction NOP <|@ <|@
      nr   56  <|@ instruction NOP <|@ <|@
      nr   58  <|@ instruction NOP <|@ <|@
      nr   60  <|@ instruction NOP <|@ <|@
      nr   62  <|@ instruction NOP <|@ <|@
      nr   64  <|@ instruction NOP <|@ <|@
      nr   66  <|@ instruction NOP <|@ <|@
      nr   68  <|@ instruction NOP <|@ <|@
      nr   70  <|@ instruction NOP <|@ <|@
      nr   72  <|@ instruction NOP <|@ <|@
      nr   74  <|@ instruction NOP <|@ <|@
      nr   76  <|@ instruction NOP <|@ <|@
      nr   78  <|@ instruction NOP <|@ <|@
      nr   80  <|@ instruction NOP <|@ <|@
      nr   82  <|@ instruction NOP <|@ <|@
      nr   84  <|@ instruction NOP <|@ <|@
      nr   86  <|@ instruction NOP <|@ <|@
      nr   88  <|@ instruction NOP <|@ <|@
      nr   90  <|@ instruction NOP <|@ <|@
      nr   92  <|@ instruction NOP <|@ <|@
      nr   94  <|@ instruction NOP <|@ <|@
      nr   96  <|@ instruction NOP <|@ <|@
      nr   98  <|@ instruction NOP <|@ <|@
      nr  100  <|@ instruction NOP <|@ <|@
      nr  102  <|@ instruction NOP <|@ <|@
      nr  104  <|@ instruction NOP <|@ <|@
      nr  106  <|@ instruction NOP <|@ <|@
      nr  108  <|@ instruction NOP <|@ <|@
      nr  110  <|@ instruction NOP <|@ <|@
      nr  112  <|@ instruction NOP <|@ <|@
      nr  114  <|@ instruction NOP <|@ <|@
      nr  116  <|@ instruction NOP <|@ <|@
      nr  118  <|@ instruction NOP <|@ <|@
      nr  120  <|@ instruction NOP <|@ <|@
      nr  122  <|@ instruction NOP <|@ <|@
      nr  124  <|@ instruction NOP <|@ <|@
      nr  126  <|@ instruction NOP <|@ <|@
      nr  128  <|@ instruction NOP <|@ <|@
      nr  132  <|@ instruction [] = HOTSPOTLOCKSTACK frameMapBuilder: jdk.graal.compiler.hotspot.amd64.AMD64HotSpotFrameMapBuilder@59edbf8f slotKind: QWORD <|@ <|@
      nr  136  <|@ instruction MOV x: [rsi|QWORD[.] + 12] y: 0 size: DWORD <|@ <|@
      nr  138  <|@ instruction AMD64G1PREWRITEBARRIER (~address: [rsi|QWORD[.] + 20], ~expectedObject: -) {temp: r10|QWORD, temp2: r11|QWORD, temp3: -} nonNull: false callTarget: Stub<write_barrier_pre-stack-only(Object)void>@0x7f78998c8200:CallingConvention[out:0|QWORD[.]]:CallingConvention[in:0|QWORD[.]] tool: jdk.graal.compiler.hotspot.amd64.g1.AMD64HotSpotG1BarrierSetLIRTool@33580fae <|@ <|@
      nr  140  <|@ instruction MOV x: [rsi|QWORD[.] + 20] y: -559030611 size: DWORD c: NarrowOop[Object[0]{}] <|@ <|@
      nr  142  <|@ instruction r10|QWORD[.] = HOTSPOTLOADOBJECTCONSTANT input: Object[Object[0]{}] <|@ <|@
      nr  144  <|@ instruction AMD64G1POSTWRITEBARRIER (~address: rsi|QWORD[.], ~newValue: r10|QWORD[.]) {temp: r11|QWORD, temp2: r8|QWORD} nonNull: true callTarget: Stub<write_barrier_post-stack-only(Word)void>@0x7f78998ca380:CallingConvention[out:0|QWORD]:CallingConvention[in:0|QWORD] tool: jdk.graal.compiler.hotspot.amd64.g1.AMD64HotSpotG1BarrierSetLIRTool@33580fae <|@ <|@
      nr  146  <|@ instruction RETURN (savedRbp: rbp|QWORD, value: -) isStub: false requiresReservedStackAccessCheck: false thread: r15 scratchForSafepointOnReturn: rcx config: jdk.graal.compiler.hotspot.GraalHotSpotVMConfig@4817c460 <|@ <|@
    end_IR
  end_block
end_cfg
begin_bytecodes
     0: aload_0       
     1: invokespecial #0          // java.util.AbstractList.<init>:()void
     4: aload_0       
     5: getstatic     #8          // DEFAULTCAPACITY_EMPTY_ELEMENTDATA:java.lang.Object[]
     8: putfield      #1          // elementData:java.lang.Object[]
    11: return        
   <|@
end_bytecodes
begin_cfg
  name "After AllocationStage"
  begin_block
    name "B0"
    from_bci -1
    to_bci -1
    predecessors 
    successors 
    xhandlers
    flags 
    probability 4607182418800017408
    begin_IR
      LIR
      nr    0  <|@ instruction [rsi|QWORD[.], rbp|QWORD] = LABEL alignment: 0 numbPhis: 0 label: ? <|@ <|@
      nr    2  <|@ instruction NOP <|@ <|@
      nr    4  <|@ instruction NOP <|@ <|@
      nr    6  <|@ instruction NOP <|@ <|@
      nr    8  <|@ instruction NOP <|@ <|@
      nr   10  <|@ instruction NOP <|@ <|@
      nr   12  <|@ instruction NOP <|@ <|@
      nr   14  <|@ instruction NOP <|@ <|@
      nr   16  <|@ instruction NOP <|@ <|@
      nr   18  <|@ instruction NOP <|@ <|@
      nr   20  <|@ instruction NOP <|@ <|@
      nr   22  <|@ instruction NOP <|@ <|@
      nr   24  <|@ instruction NOP <|@ <|@
      nr   26  <|@ instruction NOP <|@ <|@
      nr   28  <|@ instruction NOP <|@ <|@
      nr   30  <|@ instruction NOP <|@ <|@
      nr   32  <|@ instruction NOP <|@ <|@
      nr   34  <|@ instruction NOP <|@ <|@
      nr   36  <|@ instruction NOP <|@ <|@
      nr   38  <|@ instruction NOP <|@ <|@
      nr   40  <|@ instruction NOP <|@ <|@
      nr   42  <|@ instruction NOP <|@ <|@
      nr   44  <|@ instruction NOP <|@ <|@
      nr   46  <|@ instruction NOP <|@ <|@
      nr   48  <|@ instruction NOP <|@ <|@
      nr   50  <|@ instruction NOP <|@ <|@
      nr   52  <|@ instruction NOP <|@ <|@
      nr   54  <|@ instruction NOP <|@ <|@
      nr   56  <|@ instruction NOP <|@ <|@
      nr   58  <|@ instruction NOP <|@ <|@
      nr   60  <|@ instruction NOP <|@ <|@
      nr   62  <|@ instruction NOP <|@ <|@
      nr   64  <|@ instruction NOP <|@ <|@
      nr   66  <|@ instruction NOP <|@ <|@
      nr   68  <|@ instruction NOP <|@ <|@
      nr   70  <|@ instruction NOP <|@ <|@
      nr   72  <|@ instruction NOP <|@ <|@
      nr   74  <|@ instruction NOP <|@ <|@
      nr   76  <|@ instruction NOP <|@ <|@
      nr   78  <|@ instruction NOP <|@ <|@
      nr   80  <|@ instruction NOP <|@ <|@
      nr   82  <|@ instruction NOP <|@ <|@
      nr   84  <|@ instruction NOP <|@ <|@
      nr   86  <|@ instruction NOP <|@ <|@
      nr   88  <|@ instruction NOP <|@ <|@
      nr   90  <|@ instruction NOP <|@ <|@
      nr   92  <|@ instruction NOP <|@ <|@
      nr   94  <|@ instruction NOP <|@ <|@
      nr   96  <|@ instruction NOP <|@ <|@
      nr   98  <|@ instruction NOP <|@ <|@
      nr  100  <|@ instruction NOP <|@ <|@
      nr  102  <|@ instruction NOP <|@ <|@
      nr  104  <|@ instruction NOP <|@ <|@
      nr  106  <|@ instruction NOP <|@ <|@
      nr  108  <|@ instruction NOP <|@ <|@
      nr  110  <|@ instruction NOP <|@ <|@
      nr  112  <|@ instruction NOP <|@ <|@
      nr  114  <|@ instruction NOP <|@ <|@
      nr  116  <|@ instruction NOP <|@ <|@
      nr  118  <|@ instruction NOP <|@ <|@
      nr  120  <|@ instruction NOP <|@ <|@
      nr  122  <|@ instruction NOP <|@ <|@
      nr  124  <|@ instruction NOP <|@ <|@
      nr  126  <|@ instruction NOP <|@ <|@
      nr  128  <|@ instruction NOP <|@ <|@
      nr  132  <|@ instruction [] = HOTSPOTLOCKSTACK frameMapBuilder: jdk.graal.compiler.hotspot.amd64.AMD64HotSpotFrameMapBuilder@59edbf8f slotKind: QWORD <|@ <|@
      nr  136  <|@ instruction MOV x: [rsi|QWORD[.] + 12] y: 0 size: DWORD <|@ <|@
      nr  138  <|@ instruction AMD64G1PREWRITEBARRIER (~address: [rsi|QWORD[.] + 20], ~expectedObject: -) {temp: r10|QWORD, temp2: r11|QWORD, temp3: -} nonNull: false callTarget: Stub<write_barrier_pre-stack-only(Object)void>@0x7f78998c8200:CallingConvention[out:0|QWORD[.]]:CallingConvention[in:0|QWORD[.]] tool: jdk.graal.compiler.hotspot.amd64.g1.AMD64HotSpotG1BarrierSetLIRTool@33580fae <|@ <|@
      nr  140  <|@ instruction MOV x: [rsi|QWORD[.] + 20] y: -559030611 size: DWORD c: NarrowOop[Object[0]{}] <|@ <|@
      nr  142  <|@ instruction r10|QWORD[.] = HOTSPOTLOADOBJECTCONSTANT input: Object[Object[0]{}] <|@ <|@
      nr  144  <|@ instruction AMD64G1POSTWRITEBARRIER (~address: rsi|QWORD[.], ~newValue: r10|QWORD[.]) {temp: r11|QWORD, temp2: r8|QWORD} nonNull: true callTarget: Stub<write_barrier_post-stack-only(Word)void>@0x7f78998ca380:CallingConvention[out:0|QWORD]:CallingConvention[in:0|QWORD] tool: jdk.graal.compiler.hotspot.amd64.g1.AMD64HotSpotG1BarrierSetLIRTool@33580fae <|@ <|@
      nr  146  <|@ instruction RETURN (savedRbp: rbp|QWORD, value: -) isStub: false requiresReservedStackAccessCheck: false thread: r15 scratchForSafepointOnReturn: rcx config: jdk.graal.compiler.hotspot.GraalHotSpotVMConfig@4817c460 <|@ <|@
    end_IR
  end_block
end_cfg
begin_bytecodes
     0: aload_0       
     1: invokespecial #0          // java.util.AbstractList.<init>:()void
     4: aload_0       
     5: getstatic     #8          // DEFAULTCAPACITY_EMPTY_ELEMENTDATA:java.lang.Object[]
     8: putfield      #1          // elementData:java.lang.Object[]
    11: return        
   <|@
end_bytecodes
begin_cfg
  name "After EdgeMoveOptimizer"
  begin_block
    name "B0"
    from_bci -1
    to_bci -1
    predecessors 
    successors 
    xhandlers
    flags 
    probability 4607182418800017408
    begin_IR
      LIR
      nr    0  <|@ instruction [rsi|QWORD[.], rbp|QWORD] = LABEL alignment: 0 numbPhis: 0 label: ? <|@ <|@
      nr    2  <|@ instruction NOP <|@ <|@
      nr    4  <|@ instruction NOP <|@ <|@
      nr    6  <|@ instruction NOP <|@ <|@
      nr    8  <|@ instruction NOP <|@ <|@
      nr   10  <|@ instruction NOP <|@ <|@
      nr   12  <|@ instruction NOP <|@ <|@
      nr   14  <|@ instruction NOP <|@ <|@
      nr   16  <|@ instruction NOP <|@ <|@
      nr   18  <|@ instruction NOP <|@ <|@
      nr   20  <|@ instruction NOP <|@ <|@
      nr   22  <|@ instruction NOP <|@ <|@
      nr   24  <|@ instruction NOP <|@ <|@
      nr   26  <|@ instruction NOP <|@ <|@
      nr   28  <|@ instruction NOP <|@ <|@
      nr   30  <|@ instruction NOP <|@ <|@
      nr   32  <|@ instruction NOP <|@ <|@
      nr   34  <|@ instruction NOP <|@ <|@
      nr   36  <|@ instruction NOP <|@ <|@
      nr   38  <|@ instruction NOP <|@ <|@
      nr   40  <|@ instruction NOP <|@ <|@
      nr   42  <|@ instruction NOP <|@ <|@
      nr   44  <|@ instruction NOP <|@ <|@
      nr   46  <|@ instruction NOP <|@ <|@
      nr   48  <|@ instruction NOP <|@ <|@
      nr   50  <|@ instruction NOP <|@ <|@
      nr   52  <|@ instruction NOP <|@ <|@
      nr   54  <|@ instruction NOP <|@ <|@
      nr   56  <|@ instruction NOP <|@ <|@
      nr   58  <|@ instruction NOP <|@ <|@
      nr   60  <|@ instruction NOP <|@ <|@
      nr   62  <|@ instruction NOP <|@ <|@
      nr   64  <|@ instruction NOP <|@ <|@
      nr   66  <|@ instruction NOP <|@ <|@
      nr   68  <|@ instruction NOP <|@ <|@
      nr   70  <|@ instruction NOP <|@ <|@
      nr   72  <|@ instruction NOP <|@ <|@
      nr   74  <|@ instruction NOP <|@ <|@
      nr   76  <|@ instruction NOP <|@ <|@
      nr   78  <|@ instruction NOP <|@ <|@
      nr   80  <|@ instruction NOP <|@ <|@
      nr   82  <|@ instruction NOP <|@ <|@
      nr   84  <|@ instruction NOP <|@ <|@
      nr   86  <|@ instruction NOP <|@ <|@
      nr   88  <|@ instruction NOP <|@ <|@
      nr   90  <|@ instruction NOP <|@ <|@
      nr   92  <|@ instruction NOP <|@ <|@
      nr   94  <|@ instruction NOP <|@ <|@
      nr   96  <|@ instruction NOP <|@ <|@
      nr   98  <|@ instruction NOP <|@ <|@
      nr  100  <|@ instruction NOP <|@ <|@
      nr  102  <|@ instruction NOP <|@ <|@
      nr  104  <|@ instruction NOP <|@ <|@
      nr  106  <|@ instruction NOP <|@ <|@
      nr  108  <|@ instruction NOP <|@ <|@
      nr  110  <|@ instruction NOP <|@ <|@
      nr  112  <|@ instruction NOP <|@ <|@
      nr  114  <|@ instruction NOP <|@ <|@
      nr  116  <|@ instruction NOP <|@ <|@
      nr  118  <|@ instruction NOP <|@ <|@
      nr  120  <|@ instruction NOP <|@ <|@
      nr  122  <|@ instruction NOP <|@ <|@
      nr  124  <|@ instruction NOP <|@ <|@
      nr  126  <|@ instruction NOP <|@ <|@
      nr  128  <|@ instruction NOP <|@ <|@
      nr  132  <|@ instruction [] = HOTSPOTLOCKSTACK frameMapBuilder: jdk.graal.compiler.hotspot.amd64.AMD64HotSpotFrameMapBuilder@59edbf8f slotKind: QWORD <|@ <|@
      nr  136  <|@ instruction MOV x: [rsi|QWORD[.] + 12] y: 0 size: DWORD <|@ <|@
      nr  138  <|@ instruction AMD64G1PREWRITEBARRIER (~address: [rsi|QWORD[.] + 20], ~expectedObject: -) {temp: r10|QWORD, temp2: r11|QWORD, temp3: -} nonNull: false callTarget: Stub<write_barrier_pre-stack-only(Object)void>@0x7f78998c8200:CallingConvention[out:0|QWORD[.]]:CallingConvention[in:0|QWORD[.]] tool: jdk.graal.compiler.hotspot.amd64.g1.AMD64HotSpotG1BarrierSetLIRTool@33580fae <|@ <|@
      nr  140  <|@ instruction MOV x: [rsi|QWORD[.] + 20] y: -559030611 size: DWORD c: NarrowOop[Object[0]{}] <|@ <|@
      nr  142  <|@ instruction r10|QWORD[.] = HOTSPOTLOADOBJECTCONSTANT input: Object[Object[0]{}] <|@ <|@
      nr  144  <|@ instruction AMD64G1POSTWRITEBARRIER (~address: rsi|QWORD[.], ~newValue: r10|QWORD[.]) {temp: r11|QWORD, temp2: r8|QWORD} nonNull: true callTarget: Stub<write_barrier_post-stack-only(Word)void>@0x7f78998ca380:CallingConvention[out:0|QWORD]:CallingConvention[in:0|QWORD] tool: jdk.graal.compiler.hotspot.amd64.g1.AMD64HotSpotG1BarrierSetLIRTool@33580fae <|@ <|@
      nr  146  <|@ instruction RETURN (savedRbp: rbp|QWORD, value: -) isStub: false requiresReservedStackAccessCheck: false thread: r15 scratchForSafepointOnReturn: rcx config: jdk.graal.compiler.hotspot.GraalHotSpotVMConfig@4817c460 <|@ <|@
    end_IR
  end_block
end_cfg
begin_bytecodes
     0: aload_0       
     1: invokespecial #0          // java.util.AbstractList.<init>:()void
     4: aload_0       
     5: getstatic     #8          // DEFAULTCAPACITY_EMPTY_ELEMENTDATA:java.lang.Object[]
     8: putfield      #1          // elementData:java.lang.Object[]
    11: return        
   <|@
end_bytecodes
begin_cfg
  name "After RedundantMoveElimination"
  begin_block
    name "B0"
    from_bci -1
    to_bci -1
    predecessors 
    successors 
    xhandlers
    flags 
    probability 4607182418800017408
    begin_IR
      LIR
      nr    0  <|@ instruction [rsi|QWORD[.], rbp|QWORD] = LABEL alignment: 0 numbPhis: 0 label: ? <|@ <|@
      nr    2  <|@ instruction NOP <|@ <|@
      nr    4  <|@ instruction NOP <|@ <|@
      nr    6  <|@ instruction NOP <|@ <|@
      nr    8  <|@ instruction NOP <|@ <|@
      nr   10  <|@ instruction NOP <|@ <|@
      nr   12  <|@ instruction NOP <|@ <|@
      nr   14  <|@ instruction NOP <|@ <|@
      nr   16  <|@ instruction NOP <|@ <|@
      nr   18  <|@ instruction NOP <|@ <|@
      nr   20  <|@ instruction NOP <|@ <|@
      nr   22  <|@ instruction NOP <|@ <|@
      nr   24  <|@ instruction NOP <|@ <|@
      nr   26  <|@ instruction NOP <|@ <|@
      nr   28  <|@ instruction NOP <|@ <|@
      nr   30  <|@ instruction NOP <|@ <|@
      nr   32  <|@ instruction NOP <|@ <|@
      nr   34  <|@ instruction NOP <|@ <|@
      nr   36  <|@ instruction NOP <|@ <|@
      nr   38  <|@ instruction NOP <|@ <|@
      nr   40  <|@ instruction NOP <|@ <|@
      nr   42  <|@ instruction NOP <|@ <|@
      nr   44  <|@ instruction NOP <|@ <|@
      nr   46  <|@ instruction NOP <|@ <|@
      nr   48  <|@ instruction NOP <|@ <|@
      nr   50  <|@ instruction NOP <|@ <|@
      nr   52  <|@ instruction NOP <|@ <|@
      nr   54  <|@ instruction NOP <|@ <|@
      nr   56  <|@ instruction NOP <|@ <|@
      nr   58  <|@ instruction NOP <|@ <|@
      nr   60  <|@ instruction NOP <|@ <|@
      nr   62  <|@ instruction NOP <|@ <|@
      nr   64  <|@ instruction NOP <|@ <|@
      nr   66  <|@ instruction NOP <|@ <|@
      nr   68  <|@ instruction NOP <|@ <|@
      nr   70  <|@ instruction NOP <|@ <|@
      nr   72  <|@ instruction NOP <|@ <|@
      nr   74  <|@ instruction NOP <|@ <|@
      nr   76  <|@ instruction NOP <|@ <|@
      nr   78  <|@ instruction NOP <|@ <|@
      nr   80  <|@ instruction NOP <|@ <|@
      nr   82  <|@ instruction NOP <|@ <|@
      nr   84  <|@ instruction NOP <|@ <|@
      nr   86  <|@ instruction NOP <|@ <|@
      nr   88  <|@ instruction NOP <|@ <|@
      nr   90  <|@ instruction NOP <|@ <|@
      nr   92  <|@ instruction NOP <|@ <|@
      nr   94  <|@ instruction NOP <|@ <|@
      nr   96  <|@ instruction NOP <|@ <|@
      nr   98  <|@ instruction NOP <|@ <|@
      nr  100  <|@ instruction NOP <|@ <|@
      nr  102  <|@ instruction NOP <|@ <|@
      nr  104  <|@ instruction NOP <|@ <|@
      nr  106  <|@ instruction NOP <|@ <|@
      nr  108  <|@ instruction NOP <|@ <|@
      nr  110  <|@ instruction NOP <|@ <|@
      nr  112  <|@ instruction NOP <|@ <|@
      nr  114  <|@ instruction NOP <|@ <|@
      nr  116  <|@ instruction NOP <|@ <|@
      nr  118  <|@ instruction NOP <|@ <|@
      nr  120  <|@ instruction NOP <|@ <|@
      nr  122  <|@ instruction NOP <|@ <|@
      nr  124  <|@ instruction NOP <|@ <|@
      nr  126  <|@ instruction NOP <|@ <|@
      nr  128  <|@ instruction NOP <|@ <|@
      nr  132  <|@ instruction [] = HOTSPOTLOCKSTACK frameMapBuilder: jdk.graal.compiler.hotspot.amd64.AMD64HotSpotFrameMapBuilder@59edbf8f slotKind: QWORD <|@ <|@
      nr  136  <|@ instruction MOV x: [rsi|QWORD[.] + 12] y: 0 size: DWORD <|@ <|@
      nr  138  <|@ instruction AMD64G1PREWRITEBARRIER (~address: [rsi|QWORD[.] + 20], ~expectedObject: -) {temp: r10|QWORD, temp2: r11|QWORD, temp3: -} nonNull: false callTarget: Stub<write_barrier_pre-stack-only(Object)void>@0x7f78998c8200:CallingConvention[out:0|QWORD[.]]:CallingConvention[in:0|QWORD[.]] tool: jdk.graal.compiler.hotspot.amd64.g1.AMD64HotSpotG1BarrierSetLIRTool@33580fae <|@ <|@
      nr  140  <|@ instruction MOV x: [rsi|QWORD[.] + 20] y: -559030611 size: DWORD c: NarrowOop[Object[0]{}] <|@ <|@
      nr  142  <|@ instruction r10|QWORD[.] = HOTSPOTLOADOBJECTCONSTANT input: Object[Object[0]{}] <|@ <|@
      nr  144  <|@ instruction AMD64G1POSTWRITEBARRIER (~address: rsi|QWORD[.], ~newValue: r10|QWORD[.]) {temp: r11|QWORD, temp2: r8|QWORD} nonNull: true callTarget: Stub<write_barrier_post-stack-only(Word)void>@0x7f78998ca380:CallingConvention[out:0|QWORD]:CallingConvention[in:0|QWORD] tool: jdk.graal.compiler.hotspot.amd64.g1.AMD64HotSpotG1BarrierSetLIRTool@33580fae <|@ <|@
      nr  146  <|@ instruction RETURN (savedRbp: rbp|QWORD, value: -) isStub: false requiresReservedStackAccessCheck: false thread: r15 scratchForSafepointOnReturn: rcx config: jdk.graal.compiler.hotspot.GraalHotSpotVMConfig@4817c460 <|@ <|@
    end_IR
  end_block
end_cfg
begin_bytecodes
     0: aload_0       
     1: invokespecial #0          // java.util.AbstractList.<init>:()void
     4: aload_0       
     5: getstatic     #8          // DEFAULTCAPACITY_EMPTY_ELEMENTDATA:java.lang.Object[]
     8: putfield      #1          // elementData:java.lang.Object[]
    11: return        
   <|@
end_bytecodes
begin_cfg
  name "After NullCheckOptimizer"
  begin_block
    name "B0"
    from_bci -1
    to_bci -1
    predecessors 
    successors 
    xhandlers
    flags 
    probability 4607182418800017408
    begin_IR
      LIR
      nr    0  <|@ instruction [rsi|QWORD[.], rbp|QWORD] = LABEL alignment: 0 numbPhis: 0 label: ? <|@ <|@
      nr    2  <|@ instruction NOP <|@ <|@
      nr    4  <|@ instruction NOP <|@ <|@
      nr    6  <|@ instruction NOP <|@ <|@
      nr    8  <|@ instruction NOP <|@ <|@
      nr   10  <|@ instruction NOP <|@ <|@
      nr   12  <|@ instruction NOP <|@ <|@
      nr   14  <|@ instruction NOP <|@ <|@
      nr   16  <|@ instruction NOP <|@ <|@
      nr   18  <|@ instruction NOP <|@ <|@
      nr   20  <|@ instruction NOP <|@ <|@
      nr   22  <|@ instruction NOP <|@ <|@
      nr   24  <|@ instruction NOP <|@ <|@
      nr   26  <|@ instruction NOP <|@ <|@
      nr   28  <|@ instruction NOP <|@ <|@
      nr   30  <|@ instruction NOP <|@ <|@
      nr   32  <|@ instruction NOP <|@ <|@
      nr   34  <|@ instruction NOP <|@ <|@
      nr   36  <|@ instruction NOP <|@ <|@
      nr   38  <|@ instruction NOP <|@ <|@
      nr   40  <|@ instruction NOP <|@ <|@
      nr   42  <|@ instruction NOP <|@ <|@
      nr   44  <|@ instruction NOP <|@ <|@
      nr   46  <|@ instruction NOP <|@ <|@
      nr   48  <|@ instruction NOP <|@ <|@
      nr   50  <|@ instruction NOP <|@ <|@
      nr   52  <|@ instruction NOP <|@ <|@
      nr   54  <|@ instruction NOP <|@ <|@
      nr   56  <|@ instruction NOP <|@ <|@
      nr   58  <|@ instruction NOP <|@ <|@
      nr   60  <|@ instruction NOP <|@ <|@
      nr   62  <|@ instruction NOP <|@ <|@
      nr   64  <|@ instruction NOP <|@ <|@
      nr   66  <|@ instruction NOP <|@ <|@
      nr   68  <|@ instruction NOP <|@ <|@
      nr   70  <|@ instruction NOP <|@ <|@
      nr   72  <|@ instruction NOP <|@ <|@
      nr   74  <|@ instruction NOP <|@ <|@
      nr   76  <|@ instruction NOP <|@ <|@
      nr   78  <|@ instruction NOP <|@ <|@
      nr   80  <|@ instruction NOP <|@ <|@
      nr   82  <|@ instruction NOP <|@ <|@
      nr   84  <|@ instruction NOP <|@ <|@
      nr   86  <|@ instruction NOP <|@ <|@
      nr   88  <|@ instruction NOP <|@ <|@
      nr   90  <|@ instruction NOP <|@ <|@
      nr   92  <|@ instruction NOP <|@ <|@
      nr   94  <|@ instruction NOP <|@ <|@
      nr   96  <|@ instruction NOP <|@ <|@
      nr   98  <|@ instruction NOP <|@ <|@
      nr  100  <|@ instruction NOP <|@ <|@
      nr  102  <|@ instruction NOP <|@ <|@
      nr  104  <|@ instruction NOP <|@ <|@
      nr  106  <|@ instruction NOP <|@ <|@
      nr  108  <|@ instruction NOP <|@ <|@
      nr  110  <|@ instruction NOP <|@ <|@
      nr  112  <|@ instruction NOP <|@ <|@
      nr  114  <|@ instruction NOP <|@ <|@
      nr  116  <|@ instruction NOP <|@ <|@
      nr  118  <|@ instruction NOP <|@ <|@
      nr  120  <|@ instruction NOP <|@ <|@
      nr  122  <|@ instruction NOP <|@ <|@
      nr  124  <|@ instruction NOP <|@ <|@
      nr  126  <|@ instruction NOP <|@ <|@
      nr  128  <|@ instruction NOP <|@ <|@
      nr  132  <|@ instruction [] = HOTSPOTLOCKSTACK frameMapBuilder: jdk.graal.compiler.hotspot.amd64.AMD64HotSpotFrameMapBuilder@59edbf8f slotKind: QWORD <|@ <|@
      nr  136  <|@ instruction MOV x: [rsi|QWORD[.] + 12] y: 0 size: DWORD <|@ <|@
      nr  138  <|@ instruction AMD64G1PREWRITEBARRIER (~address: [rsi|QWORD[.] + 20], ~expectedObject: -) {temp: r10|QWORD, temp2: r11|QWORD, temp3: -} nonNull: false callTarget: Stub<write_barrier_pre-stack-only(Object)void>@0x7f78998c8200:CallingConvention[out:0|QWORD[.]]:CallingConvention[in:0|QWORD[.]] tool: jdk.graal.compiler.hotspot.amd64.g1.AMD64HotSpotG1BarrierSetLIRTool@33580fae <|@ <|@
      nr  140  <|@ instruction MOV x: [rsi|QWORD[.] + 20] y: -559030611 size: DWORD c: NarrowOop[Object[0]{}] <|@ <|@
      nr  142  <|@ instruction r10|QWORD[.] = HOTSPOTLOADOBJECTCONSTANT input: Object[Object[0]{}] <|@ <|@
      nr  144  <|@ instruction AMD64G1POSTWRITEBARRIER (~address: rsi|QWORD[.], ~newValue: r10|QWORD[.]) {temp: r11|QWORD, temp2: r8|QWORD} nonNull: true callTarget: Stub<write_barrier_post-stack-only(Word)void>@0x7f78998ca380:CallingConvention[out:0|QWORD]:CallingConvention[in:0|QWORD] tool: jdk.graal.compiler.hotspot.amd64.g1.AMD64HotSpotG1BarrierSetLIRTool@33580fae <|@ <|@
      nr  146  <|@ instruction RETURN (savedRbp: rbp|QWORD, value: -) isStub: false requiresReservedStackAccessCheck: false thread: r15 scratchForSafepointOnReturn: rcx config: jdk.graal.compiler.hotspot.GraalHotSpotVMConfig@4817c460 <|@ <|@
    end_IR
  end_block
end_cfg
begin_bytecodes
     0: aload_0       
     1: invokespecial #0          // java.util.AbstractList.<init>:()void
     4: aload_0       
     5: getstatic     #8          // DEFAULTCAPACITY_EMPTY_ELEMENTDATA:java.lang.Object[]
     8: putfield      #1          // elementData:java.lang.Object[]
    11: return        
   <|@
end_bytecodes
begin_cfg
  name "After ControlFlowOptimizer"
  begin_block
    name "B0"
    from_bci -1
    to_bci -1
    predecessors 
    successors 
    xhandlers
    flags 
    probability 4607182418800017408
    begin_IR
      LIR
      nr    0  <|@ instruction [rsi|QWORD[.], rbp|QWORD] = LABEL alignment: 0 numbPhis: 0 label: ? <|@ <|@
      nr    2  <|@ instruction NOP <|@ <|@
      nr    4  <|@ instruction NOP <|@ <|@
      nr    6  <|@ instruction NOP <|@ <|@
      nr    8  <|@ instruction NOP <|@ <|@
      nr   10  <|@ instruction NOP <|@ <|@
      nr   12  <|@ instruction NOP <|@ <|@
      nr   14  <|@ instruction NOP <|@ <|@
      nr   16  <|@ instruction NOP <|@ <|@
      nr   18  <|@ instruction NOP <|@ <|@
      nr   20  <|@ instruction NOP <|@ <|@
      nr   22  <|@ instruction NOP <|@ <|@
      nr   24  <|@ instruction NOP <|@ <|@
      nr   26  <|@ instruction NOP <|@ <|@
      nr   28  <|@ instruction NOP <|@ <|@
      nr   30  <|@ instruction NOP <|@ <|@
      nr   32  <|@ instruction NOP <|@ <|@
      nr   34  <|@ instruction NOP <|@ <|@
      nr   36  <|@ instruction NOP <|@ <|@
      nr   38  <|@ instruction NOP <|@ <|@
      nr   40  <|@ instruction NOP <|@ <|@
      nr   42  <|@ instruction NOP <|@ <|@
      nr   44  <|@ instruction NOP <|@ <|@
      nr   46  <|@ instruction NOP <|@ <|@
      nr   48  <|@ instruction NOP <|@ <|@
      nr   50  <|@ instruction NOP <|@ <|@
      nr   52  <|@ instruction NOP <|@ <|@
      nr   54  <|@ instruction NOP <|@ <|@
      nr   56  <|@ instruction NOP <|@ <|@
      nr   58  <|@ instruction NOP <|@ <|@
      nr   60  <|@ instruction NOP <|@ <|@
      nr   62  <|@ instruction NOP <|@ <|@
      nr   64  <|@ instruction NOP <|@ <|@
      nr   66  <|@ instruction NOP <|@ <|@
      nr   68  <|@ instruction NOP <|@ <|@
      nr   70  <|@ instruction NOP <|@ <|@
      nr   72  <|@ instruction NOP <|@ <|@
      nr   74  <|@ instruction NOP <|@ <|@
      nr   76  <|@ instruction NOP <|@ <|@
      nr   78  <|@ instruction NOP <|@ <|@
      nr   80  <|@ instruction NOP <|@ <|@
      nr   82  <|@ instruction NOP <|@ <|@
      nr   84  <|@ instruction NOP <|@ <|@
      nr   86  <|@ instruction NOP <|@ <|@
      nr   88  <|@ instruction NOP <|@ <|@
      nr   90  <|@ instruction NOP <|@ <|@
      nr   92  <|@ instruction NOP <|@ <|@
      nr   94  <|@ instruction NOP <|@ <|@
      nr   96  <|@ instruction NOP <|@ <|@
      nr   98  <|@ instruction NOP <|@ <|@
      nr  100  <|@ instruction NOP <|@ <|@
      nr  102  <|@ instruction NOP <|@ <|@
      nr  104  <|@ instruction NOP <|@ <|@
      nr  106  <|@ instruction NOP <|@ <|@
      nr  108  <|@ instruction NOP <|@ <|@
      nr  110  <|@ instruction NOP <|@ <|@
      nr  112  <|@ instruction NOP <|@ <|@
      nr  114  <|@ instruction NOP <|@ <|@
      nr  116  <|@ instruction NOP <|@ <|@
      nr  118  <|@ instruction NOP <|@ <|@
      nr  120  <|@ instruction NOP <|@ <|@
      nr  122  <|@ instruction NOP <|@ <|@
      nr  124  <|@ instruction NOP <|@ <|@
      nr  126  <|@ instruction NOP <|@ <|@
      nr  128  <|@ instruction NOP <|@ <|@
      nr  132  <|@ instruction [] = HOTSPOTLOCKSTACK frameMapBuilder: jdk.graal.compiler.hotspot.amd64.AMD64HotSpotFrameMapBuilder@59edbf8f slotKind: QWORD <|@ <|@
      nr  136  <|@ instruction MOV x: [rsi|QWORD[.] + 12] y: 0 size: DWORD <|@ <|@
      nr  138  <|@ instruction AMD64G1PREWRITEBARRIER (~address: [rsi|QWORD[.] + 20], ~expectedObject: -) {temp: r10|QWORD, temp2: r11|QWORD, temp3: -} nonNull: false callTarget: Stub<write_barrier_pre-stack-only(Object)void>@0x7f78998c8200:CallingConvention[out:0|QWORD[.]]:CallingConvention[in:0|QWORD[.]] tool: jdk.graal.compiler.hotspot.amd64.g1.AMD64HotSpotG1BarrierSetLIRTool@33580fae <|@ <|@
      nr  140  <|@ instruction MOV x: [rsi|QWORD[.] + 20] y: -559030611 size: DWORD c: NarrowOop[Object[0]{}] <|@ <|@
      nr  142  <|@ instruction r10|QWORD[.] = HOTSPOTLOADOBJECTCONSTANT input: Object[Object[0]{}] <|@ <|@
      nr  144  <|@ instruction AMD64G1POSTWRITEBARRIER (~address: rsi|QWORD[.], ~newValue: r10|QWORD[.]) {temp: r11|QWORD, temp2: r8|QWORD} nonNull: true callTarget: Stub<write_barrier_post-stack-only(Word)void>@0x7f78998ca380:CallingConvention[out:0|QWORD]:CallingConvention[in:0|QWORD] tool: jdk.graal.compiler.hotspot.amd64.g1.AMD64HotSpotG1BarrierSetLIRTool@33580fae <|@ <|@
      nr  146  <|@ instruction RETURN (savedRbp: rbp|QWORD, value: -) isStub: false requiresReservedStackAccessCheck: false thread: r15 scratchForSafepointOnReturn: rcx config: jdk.graal.compiler.hotspot.GraalHotSpotVMConfig@4817c460 <|@ <|@
    end_IR
  end_block
end_cfg
begin_bytecodes
     0: aload_0       
     1: invokespecial #0          // java.util.AbstractList.<init>:()void
     4: aload_0       
     5: getstatic     #8          // DEFAULTCAPACITY_EMPTY_ELEMENTDATA:java.lang.Object[]
     8: putfield      #1          // elementData:java.lang.Object[]
    11: return        
   <|@
end_bytecodes
begin_cfg
  name "After ComputeCodeEmissionOrder"
  begin_block
    name "B0"
    from_bci -1
    to_bci -1
    predecessors 
    successors 
    xhandlers
    flags 
    probability 4607182418800017408
    begin_IR
      LIR
      nr    0  <|@ instruction [rsi|QWORD[.], rbp|QWORD] = LABEL alignment: 0 numbPhis: 0 label: ? <|@ <|@
      nr    2  <|@ instruction NOP <|@ <|@
      nr    4  <|@ instruction NOP <|@ <|@
      nr    6  <|@ instruction NOP <|@ <|@
      nr    8  <|@ instruction NOP <|@ <|@
      nr   10  <|@ instruction NOP <|@ <|@
      nr   12  <|@ instruction NOP <|@ <|@
      nr   14  <|@ instruction NOP <|@ <|@
      nr   16  <|@ instruction NOP <|@ <|@
      nr   18  <|@ instruction NOP <|@ <|@
      nr   20  <|@ instruction NOP <|@ <|@
      nr   22  <|@ instruction NOP <|@ <|@
      nr   24  <|@ instruction NOP <|@ <|@
      nr   26  <|@ instruction NOP <|@ <|@
      nr   28  <|@ instruction NOP <|@ <|@
      nr   30  <|@ instruction NOP <|@ <|@
      nr   32  <|@ instruction NOP <|@ <|@
      nr   34  <|@ instruction NOP <|@ <|@
      nr   36  <|@ instruction NOP <|@ <|@
      nr   38  <|@ instruction NOP <|@ <|@
      nr   40  <|@ instruction NOP <|@ <|@
      nr   42  <|@ instruction NOP <|@ <|@
      nr   44  <|@ instruction NOP <|@ <|@
      nr   46  <|@ instruction NOP <|@ <|@
      nr   48  <|@ instruction NOP <|@ <|@
      nr   50  <|@ instruction NOP <|@ <|@
      nr   52  <|@ instruction NOP <|@ <|@
      nr   54  <|@ instruction NOP <|@ <|@
      nr   56  <|@ instruction NOP <|@ <|@
      nr   58  <|@ instruction NOP <|@ <|@
      nr   60  <|@ instruction NOP <|@ <|@
      nr   62  <|@ instruction NOP <|@ <|@
      nr   64  <|@ instruction NOP <|@ <|@
      nr   66  <|@ instruction NOP <|@ <|@
      nr   68  <|@ instruction NOP <|@ <|@
      nr   70  <|@ instruction NOP <|@ <|@
      nr   72  <|@ instruction NOP <|@ <|@
      nr   74  <|@ instruction NOP <|@ <|@
      nr   76  <|@ instruction NOP <|@ <|@
      nr   78  <|@ instruction NOP <|@ <|@
      nr   80  <|@ instruction NOP <|@ <|@
      nr   82  <|@ instruction NOP <|@ <|@
      nr   84  <|@ instruction NOP <|@ <|@
      nr   86  <|@ instruction NOP <|@ <|@
      nr   88  <|@ instruction NOP <|@ <|@
      nr   90  <|@ instruction NOP <|@ <|@
      nr   92  <|@ instruction NOP <|@ <|@
      nr   94  <|@ instruction NOP <|@ <|@
      nr   96  <|@ instruction NOP <|@ <|@
      nr   98  <|@ instruction NOP <|@ <|@
      nr  100  <|@ instruction NOP <|@ <|@
      nr  102  <|@ instruction NOP <|@ <|@
      nr  104  <|@ instruction NOP <|@ <|@
      nr  106  <|@ instruction NOP <|@ <|@
      nr  108  <|@ instruction NOP <|@ <|@
      nr  110  <|@ instruction NOP <|@ <|@
      nr  112  <|@ instruction NOP <|@ <|@
      nr  114  <|@ instruction NOP <|@ <|@
      nr  116  <|@ instruction NOP <|@ <|@
      nr  118  <|@ instruction NOP <|@ <|@
      nr  120  <|@ instruction NOP <|@ <|@
      nr  122  <|@ instruction NOP <|@ <|@
      nr  124  <|@ instruction NOP <|@ <|@
      nr  126  <|@ instruction NOP <|@ <|@
      nr  128  <|@ instruction NOP <|@ <|@
      nr  132  <|@ instruction [] = HOTSPOTLOCKSTACK frameMapBuilder: jdk.graal.compiler.hotspot.amd64.AMD64HotSpotFrameMapBuilder@59edbf8f slotKind: QWORD <|@ <|@
      nr  136  <|@ instruction MOV x: [rsi|QWORD[.] + 12] y: 0 size: DWORD <|@ <|@
      nr  138  <|@ instruction AMD64G1PREWRITEBARRIER (~address: [rsi|QWORD[.] + 20], ~expectedObject: -) {temp: r10|QWORD, temp2: r11|QWORD, temp3: -} nonNull: false callTarget: Stub<write_barrier_pre-stack-only(Object)void>@0x7f78998c8200:CallingConvention[out:0|QWORD[.]]:CallingConvention[in:0|QWORD[.]] tool: jdk.graal.compiler.hotspot.amd64.g1.AMD64HotSpotG1BarrierSetLIRTool@33580fae <|@ <|@
      nr  140  <|@ instruction MOV x: [rsi|QWORD[.] + 20] y: -559030611 size: DWORD c: NarrowOop[Object[0]{}] <|@ <|@
      nr  142  <|@ instruction r10|QWORD[.] = HOTSPOTLOADOBJECTCONSTANT input: Object[Object[0]{}] <|@ <|@
      nr  144  <|@ instruction AMD64G1POSTWRITEBARRIER (~address: rsi|QWORD[.], ~newValue: r10|QWORD[.]) {temp: r11|QWORD, temp2: r8|QWORD} nonNull: true callTarget: Stub<write_barrier_post-stack-only(Word)void>@0x7f78998ca380:CallingConvention[out:0|QWORD]:CallingConvention[in:0|QWORD] tool: jdk.graal.compiler.hotspot.amd64.g1.AMD64HotSpotG1BarrierSetLIRTool@33580fae <|@ <|@
      nr  146  <|@ instruction RETURN (savedRbp: rbp|QWORD, value: -) isStub: false requiresReservedStackAccessCheck: false thread: r15 scratchForSafepointOnReturn: rcx config: jdk.graal.compiler.hotspot.GraalHotSpotVMConfig@4817c460 <|@ <|@
    end_IR
  end_block
end_cfg
begin_bytecodes
     0: aload_0       
     1: invokespecial #0          // java.util.AbstractList.<init>:()void
     4: aload_0       
     5: getstatic     #8          // DEFAULTCAPACITY_EMPTY_ELEMENTDATA:java.lang.Object[]
     8: putfield      #1          // elementData:java.lang.Object[]
    11: return        
   <|@
end_bytecodes
begin_cfg
  name "After StackMoveOptimization"
  begin_block
    name "B0"
    from_bci -1
    to_bci -1
    predecessors 
    successors 
    xhandlers
    flags 
    probability 4607182418800017408
    begin_IR
      LIR
      nr    0  <|@ instruction [rsi|QWORD[.], rbp|QWORD] = LABEL alignment: 0 numbPhis: 0 label: ? <|@ <|@
      nr    2  <|@ instruction NOP <|@ <|@
      nr    4  <|@ instruction NOP <|@ <|@
      nr    6  <|@ instruction NOP <|@ <|@
      nr    8  <|@ instruction NOP <|@ <|@
      nr   10  <|@ instruction NOP <|@ <|@
      nr   12  <|@ instruction NOP <|@ <|@
      nr   14  <|@ instruction NOP <|@ <|@
      nr   16  <|@ instruction NOP <|@ <|@
      nr   18  <|@ instruction NOP <|@ <|@
      nr   20  <|@ instruction NOP <|@ <|@
      nr   22  <|@ instruction NOP <|@ <|@
      nr   24  <|@ instruction NOP <|@ <|@
      nr   26  <|@ instruction NOP <|@ <|@
      nr   28  <|@ instruction NOP <|@ <|@
      nr   30  <|@ instruction NOP <|@ <|@
      nr   32  <|@ instruction NOP <|@ <|@
      nr   34  <|@ instruction NOP <|@ <|@
      nr   36  <|@ instruction NOP <|@ <|@
      nr   38  <|@ instruction NOP <|@ <|@
      nr   40  <|@ instruction NOP <|@ <|@
      nr   42  <|@ instruction NOP <|@ <|@
      nr   44  <|@ instruction NOP <|@ <|@
      nr   46  <|@ instruction NOP <|@ <|@
      nr   48  <|@ instruction NOP <|@ <|@
      nr   50  <|@ instruction NOP <|@ <|@
      nr   52  <|@ instruction NOP <|@ <|@
      nr   54  <|@ instruction NOP <|@ <|@
      nr   56  <|@ instruction NOP <|@ <|@
      nr   58  <|@ instruction NOP <|@ <|@
      nr   60  <|@ instruction NOP <|@ <|@
      nr   62  <|@ instruction NOP <|@ <|@
      nr   64  <|@ instruction NOP <|@ <|@
      nr   66  <|@ instruction NOP <|@ <|@
      nr   68  <|@ instruction NOP <|@ <|@
      nr   70  <|@ instruction NOP <|@ <|@
      nr   72  <|@ instruction NOP <|@ <|@
      nr   74  <|@ instruction NOP <|@ <|@
      nr   76  <|@ instruction NOP <|@ <|@
      nr   78  <|@ instruction NOP <|@ <|@
      nr   80  <|@ instruction NOP <|@ <|@
      nr   82  <|@ instruction NOP <|@ <|@
      nr   84  <|@ instruction NOP <|@ <|@
      nr   86  <|@ instruction NOP <|@ <|@
      nr   88  <|@ instruction NOP <|@ <|@
      nr   90  <|@ instruction NOP <|@ <|@
      nr   92  <|@ instruction NOP <|@ <|@
      nr   94  <|@ instruction NOP <|@ <|@
      nr   96  <|@ instruction NOP <|@ <|@
      nr   98  <|@ instruction NOP <|@ <|@
      nr  100  <|@ instruction NOP <|@ <|@
      nr  102  <|@ instruction NOP <|@ <|@
      nr  104  <|@ instruction NOP <|@ <|@
      nr  106  <|@ instruction NOP <|@ <|@
      nr  108  <|@ instruction NOP <|@ <|@
      nr  110  <|@ instruction NOP <|@ <|@
      nr  112  <|@ instruction NOP <|@ <|@
      nr  114  <|@ instruction NOP <|@ <|@
      nr  116  <|@ instruction NOP <|@ <|@
      nr  118  <|@ instruction NOP <|@ <|@
      nr  120  <|@ instruction NOP <|@ <|@
      nr  122  <|@ instruction NOP <|@ <|@
      nr  124  <|@ instruction NOP <|@ <|@
      nr  126  <|@ instruction NOP <|@ <|@
      nr  128  <|@ instruction NOP <|@ <|@
      nr  132  <|@ instruction [] = HOTSPOTLOCKSTACK frameMapBuilder: jdk.graal.compiler.hotspot.amd64.AMD64HotSpotFrameMapBuilder@59edbf8f slotKind: QWORD <|@ <|@
      nr  136  <|@ instruction MOV x: [rsi|QWORD[.] + 12] y: 0 size: DWORD <|@ <|@
      nr  138  <|@ instruction AMD64G1PREWRITEBARRIER (~address: [rsi|QWORD[.] + 20], ~expectedObject: -) {temp: r10|QWORD, temp2: r11|QWORD, temp3: -} nonNull: false callTarget: Stub<write_barrier_pre-stack-only(Object)void>@0x7f78998c8200:CallingConvention[out:0|QWORD[.]]:CallingConvention[in:0|QWORD[.]] tool: jdk.graal.compiler.hotspot.amd64.g1.AMD64HotSpotG1BarrierSetLIRTool@33580fae <|@ <|@
      nr  140  <|@ instruction MOV x: [rsi|QWORD[.] + 20] y: -559030611 size: DWORD c: NarrowOop[Object[0]{}] <|@ <|@
      nr  142  <|@ instruction r10|QWORD[.] = HOTSPOTLOADOBJECTCONSTANT input: Object[Object[0]{}] <|@ <|@
      nr  144  <|@ instruction AMD64G1POSTWRITEBARRIER (~address: rsi|QWORD[.], ~newValue: r10|QWORD[.]) {temp: r11|QWORD, temp2: r8|QWORD} nonNull: true callTarget: Stub<write_barrier_post-stack-only(Word)void>@0x7f78998ca380:CallingConvention[out:0|QWORD]:CallingConvention[in:0|QWORD] tool: jdk.graal.compiler.hotspot.amd64.g1.AMD64HotSpotG1BarrierSetLIRTool@33580fae <|@ <|@
      nr  146  <|@ instruction RETURN (savedRbp: rbp|QWORD, value: -) isStub: false requiresReservedStackAccessCheck: false thread: r15 scratchForSafepointOnReturn: rcx config: jdk.graal.compiler.hotspot.GraalHotSpotVMConfig@4817c460 <|@ <|@
    end_IR
  end_block
end_cfg
begin_bytecodes
     0: aload_0       
     1: invokespecial #0          // java.util.AbstractList.<init>:()void
     4: aload_0       
     5: getstatic     #8          // DEFAULTCAPACITY_EMPTY_ELEMENTDATA:java.lang.Object[]
     8: putfield      #1          // elementData:java.lang.Object[]
    11: return        
   <|@
end_bytecodes
begin_cfg
  name "After PostAllocationOptimizationStage"
  begin_block
    name "B0"
    from_bci -1
    to_bci -1
    predecessors 
    successors 
    xhandlers
    flags 
    probability 4607182418800017408
    begin_IR
      LIR
      nr    0  <|@ instruction [rsi|QWORD[.], rbp|QWORD] = LABEL alignment: 0 numbPhis: 0 label: ? <|@ <|@
      nr    2  <|@ instruction NOP <|@ <|@
      nr    4  <|@ instruction NOP <|@ <|@
      nr    6  <|@ instruction NOP <|@ <|@
      nr    8  <|@ instruction NOP <|@ <|@
      nr   10  <|@ instruction NOP <|@ <|@
      nr   12  <|@ instruction NOP <|@ <|@
      nr   14  <|@ instruction NOP <|@ <|@
      nr   16  <|@ instruction NOP <|@ <|@
      nr   18  <|@ instruction NOP <|@ <|@
      nr   20  <|@ instruction NOP <|@ <|@
      nr   22  <|@ instruction NOP <|@ <|@
      nr   24  <|@ instruction NOP <|@ <|@
      nr   26  <|@ instruction NOP <|@ <|@
      nr   28  <|@ instruction NOP <|@ <|@
      nr   30  <|@ instruction NOP <|@ <|@
      nr   32  <|@ instruction NOP <|@ <|@
      nr   34  <|@ instruction NOP <|@ <|@
      nr   36  <|@ instruction NOP <|@ <|@
      nr   38  <|@ instruction NOP <|@ <|@
      nr   40  <|@ instruction NOP <|@ <|@
      nr   42  <|@ instruction NOP <|@ <|@
      nr   44  <|@ instruction NOP <|@ <|@
      nr   46  <|@ instruction NOP <|@ <|@
      nr   48  <|@ instruction NOP <|@ <|@
      nr   50  <|@ instruction NOP <|@ <|@
      nr   52  <|@ instruction NOP <|@ <|@
      nr   54  <|@ instruction NOP <|@ <|@
      nr   56  <|@ instruction NOP <|@ <|@
      nr   58  <|@ instruction NOP <|@ <|@
      nr   60  <|@ instruction NOP <|@ <|@
      nr   62  <|@ instruction NOP <|@ <|@
      nr   64  <|@ instruction NOP <|@ <|@
      nr   66  <|@ instruction NOP <|@ <|@
      nr   68  <|@ instruction NOP <|@ <|@
      nr   70  <|@ instruction NOP <|@ <|@
      nr   72  <|@ instruction NOP <|@ <|@
      nr   74  <|@ instruction NOP <|@ <|@
      nr   76  <|@ instruction NOP <|@ <|@
      nr   78  <|@ instruction NOP <|@ <|@
      nr   80  <|@ instruction NOP <|@ <|@
      nr   82  <|@ instruction NOP <|@ <|@
      nr   84  <|@ instruction NOP <|@ <|@
      nr   86  <|@ instruction NOP <|@ <|@
      nr   88  <|@ instruction NOP <|@ <|@
      nr   90  <|@ instruction NOP <|@ <|@
      nr   92  <|@ instruction NOP <|@ <|@
      nr   94  <|@ instruction NOP <|@ <|@
      nr   96  <|@ instruction NOP <|@ <|@
      nr   98  <|@ instruction NOP <|@ <|@
      nr  100  <|@ instruction NOP <|@ <|@
      nr  102  <|@ instruction NOP <|@ <|@
      nr  104  <|@ instruction NOP <|@ <|@
      nr  106  <|@ instruction NOP <|@ <|@
      nr  108  <|@ instruction NOP <|@ <|@
      nr  110  <|@ instruction NOP <|@ <|@
      nr  112  <|@ instruction NOP <|@ <|@
      nr  114  <|@ instruction NOP <|@ <|@
      nr  116  <|@ instruction NOP <|@ <|@
      nr  118  <|@ instruction NOP <|@ <|@
      nr  120  <|@ instruction NOP <|@ <|@
      nr  122  <|@ instruction NOP <|@ <|@
      nr  124  <|@ instruction NOP <|@ <|@
      nr  126  <|@ instruction NOP <|@ <|@
      nr  128  <|@ instruction NOP <|@ <|@
      nr  132  <|@ instruction [] = HOTSPOTLOCKSTACK frameMapBuilder: jdk.graal.compiler.hotspot.amd64.AMD64HotSpotFrameMapBuilder@59edbf8f slotKind: QWORD <|@ <|@
      nr  136  <|@ instruction MOV x: [rsi|QWORD[.] + 12] y: 0 size: DWORD <|@ <|@
      nr  138  <|@ instruction AMD64G1PREWRITEBARRIER (~address: [rsi|QWORD[.] + 20], ~expectedObject: -) {temp: r10|QWORD, temp2: r11|QWORD, temp3: -} nonNull: false callTarget: Stub<write_barrier_pre-stack-only(Object)void>@0x7f78998c8200:CallingConvention[out:0|QWORD[.]]:CallingConvention[in:0|QWORD[.]] tool: jdk.graal.compiler.hotspot.amd64.g1.AMD64HotSpotG1BarrierSetLIRTool@33580fae <|@ <|@
      nr  140  <|@ instruction MOV x: [rsi|QWORD[.] + 20] y: -559030611 size: DWORD c: NarrowOop[Object[0]{}] <|@ <|@
      nr  142  <|@ instruction r10|QWORD[.] = HOTSPOTLOADOBJECTCONSTANT input: Object[Object[0]{}] <|@ <|@
      nr  144  <|@ instruction AMD64G1POSTWRITEBARRIER (~address: rsi|QWORD[.], ~newValue: r10|QWORD[.]) {temp: r11|QWORD, temp2: r8|QWORD} nonNull: true callTarget: Stub<write_barrier_post-stack-only(Word)void>@0x7f78998ca380:CallingConvention[out:0|QWORD]:CallingConvention[in:0|QWORD] tool: jdk.graal.compiler.hotspot.amd64.g1.AMD64HotSpotG1BarrierSetLIRTool@33580fae <|@ <|@
      nr  146  <|@ instruction RETURN (savedRbp: rbp|QWORD, value: -) isStub: false requiresReservedStackAccessCheck: false thread: r15 scratchForSafepointOnReturn: rcx config: jdk.graal.compiler.hotspot.GraalHotSpotVMConfig@4817c460 <|@ <|@
    end_IR
  end_block
end_cfg
begin_bytecodes
     0: aload_0       
     1: invokespecial #0          // java.util.AbstractList.<init>:()void
     4: aload_0       
     5: getstatic     #8          // DEFAULTCAPACITY_EMPTY_ELEMENTDATA:java.lang.Object[]
     8: putfield      #1          // elementData:java.lang.Object[]
    11: return        
   <|@
end_bytecodes
begin_cfg
  name "After LocationMarker"
  begin_block
    name "B0"
    from_bci -1
    to_bci -1
    predecessors 
    successors 
    xhandlers
    flags 
    probability 4607182418800017408
    begin_IR
      LIR
      nr    0  <|@ instruction [rsi|QWORD[.], rbp|QWORD] = LABEL alignment: 0 numbPhis: 0 label: ? <|@ <|@
      nr    2  <|@ instruction NOP <|@ <|@
      nr    4  <|@ instruction NOP <|@ <|@
      nr    6  <|@ instruction NOP <|@ <|@
      nr    8  <|@ instruction NOP <|@ <|@
      nr   10  <|@ instruction NOP <|@ <|@
      nr   12  <|@ instruction NOP <|@ <|@
      nr   14  <|@ instruction NOP <|@ <|@
      nr   16  <|@ instruction NOP <|@ <|@
      nr   18  <|@ instruction NOP <|@ <|@
      nr   20  <|@ instruction NOP <|@ <|@
      nr   22  <|@ instruction NOP <|@ <|@
      nr   24  <|@ instruction NOP <|@ <|@
      nr   26  <|@ instruction NOP <|@ <|@
      nr   28  <|@ instruction NOP <|@ <|@
      nr   30  <|@ instruction NOP <|@ <|@
      nr   32  <|@ instruction NOP <|@ <|@
      nr   34  <|@ instruction NOP <|@ <|@
      nr   36  <|@ instruction NOP <|@ <|@
      nr   38  <|@ instruction NOP <|@ <|@
      nr   40  <|@ instruction NOP <|@ <|@
      nr   42  <|@ instruction NOP <|@ <|@
      nr   44  <|@ instruction NOP <|@ <|@
      nr   46  <|@ instruction NOP <|@ <|@
      nr   48  <|@ instruction NOP <|@ <|@
      nr   50  <|@ instruction NOP <|@ <|@
      nr   52  <|@ instruction NOP <|@ <|@
      nr   54  <|@ instruction NOP <|@ <|@
      nr   56  <|@ instruction NOP <|@ <|@
      nr   58  <|@ instruction NOP <|@ <|@
      nr   60  <|@ instruction NOP <|@ <|@
      nr   62  <|@ instruction NOP <|@ <|@
      nr   64  <|@ instruction NOP <|@ <|@
      nr   66  <|@ instruction NOP <|@ <|@
      nr   68  <|@ instruction NOP <|@ <|@
      nr   70  <|@ instruction NOP <|@ <|@
      nr   72  <|@ instruction NOP <|@ <|@
      nr   74  <|@ instruction NOP <|@ <|@
      nr   76  <|@ instruction NOP <|@ <|@
      nr   78  <|@ instruction NOP <|@ <|@
      nr   80  <|@ instruction NOP <|@ <|@
      nr   82  <|@ instruction NOP <|@ <|@
      nr   84  <|@ instruction NOP <|@ <|@
      nr   86  <|@ instruction NOP <|@ <|@
      nr   88  <|@ instruction NOP <|@ <|@
      nr   90  <|@ instruction NOP <|@ <|@
      nr   92  <|@ instruction NOP <|@ <|@
      nr   94  <|@ instruction NOP <|@ <|@
      nr   96  <|@ instruction NOP <|@ <|@
      nr   98  <|@ instruction NOP <|@ <|@
      nr  100  <|@ instruction NOP <|@ <|@
      nr  102  <|@ instruction NOP <|@ <|@
      nr  104  <|@ instruction NOP <|@ <|@
      nr  106  <|@ instruction NOP <|@ <|@
      nr  108  <|@ instruction NOP <|@ <|@
      nr  110  <|@ instruction NOP <|@ <|@
      nr  112  <|@ instruction NOP <|@ <|@
      nr  114  <|@ instruction NOP <|@ <|@
      nr  116  <|@ instruction NOP <|@ <|@
      nr  118  <|@ instruction NOP <|@ <|@
      nr  120  <|@ instruction NOP <|@ <|@
      nr  122  <|@ instruction NOP <|@ <|@
      nr  124  <|@ instruction NOP <|@ <|@
      nr  126  <|@ instruction NOP <|@ <|@
      nr  128  <|@ instruction NOP <|@ <|@
      nr  132  <|@ instruction [] = HOTSPOTLOCKSTACK frameMapBuilder: jdk.graal.compiler.hotspot.amd64.AMD64HotSpotFrameMapBuilder@59edbf8f slotKind: QWORD <|@ <|@
      nr  136  <|@ instruction MOV x: [rsi|QWORD[.] + 12] y: 0 size: DWORD <|@ <|@
      nr  138  <|@ instruction AMD64G1PREWRITEBARRIER (~address: [rsi|QWORD[.] + 20], ~expectedObject: -) {temp: r10|QWORD, temp2: r11|QWORD, temp3: -} nonNull: false callTarget: Stub<write_barrier_pre-stack-only(Object)void>@0x7f78998c8200:CallingConvention[out:0|QWORD[.]]:CallingConvention[in:0|QWORD[.]] tool: jdk.graal.compiler.hotspot.amd64.g1.AMD64HotSpotG1BarrierSetLIRTool@33580fae <|@ <|@
      nr  140  <|@ instruction MOV x: [rsi|QWORD[.] + 20] y: -559030611 size: DWORD c: NarrowOop[Object[0]{}] <|@ <|@
      nr  142  <|@ instruction r10|QWORD[.] = HOTSPOTLOADOBJECTCONSTANT input: Object[Object[0]{}] <|@ <|@
      nr  144  <|@ instruction AMD64G1POSTWRITEBARRIER (~address: rsi|QWORD[.], ~newValue: r10|QWORD[.]) {temp: r11|QWORD, temp2: r8|QWORD} nonNull: true callTarget: Stub<write_barrier_post-stack-only(Word)void>@0x7f78998ca380:CallingConvention[out:0|QWORD]:CallingConvention[in:0|QWORD] tool: jdk.graal.compiler.hotspot.amd64.g1.AMD64HotSpotG1BarrierSetLIRTool@33580fae <|@ <|@
      nr  146  <|@ instruction RETURN (savedRbp: rbp|QWORD, value: -) isStub: false requiresReservedStackAccessCheck: false thread: r15 scratchForSafepointOnReturn: rcx config: jdk.graal.compiler.hotspot.GraalHotSpotVMConfig@4817c460 <|@ <|@
    end_IR
  end_block
end_cfg
begin_bytecodes
     0: aload_0       
     1: invokespecial #0          // java.util.AbstractList.<init>:()void
     4: aload_0       
     5: getstatic     #8          // DEFAULTCAPACITY_EMPTY_ELEMENTDATA:java.lang.Object[]
     8: putfield      #1          // elementData:java.lang.Object[]
    11: return        
   <|@
end_bytecodes
begin_cfg
  name "After FinalCodeAnalysisStage"
  begin_block
    name "B0"
    from_bci -1
    to_bci -1
    predecessors 
    successors 
    xhandlers
    flags 
    probability 4607182418800017408
    begin_IR
      LIR
      nr    0  <|@ instruction [rsi|QWORD[.], rbp|QWORD] = LABEL alignment: 0 numbPhis: 0 label: ? <|@ <|@
      nr    2  <|@ instruction NOP <|@ <|@
      nr    4  <|@ instruction NOP <|@ <|@
      nr    6  <|@ instruction NOP <|@ <|@
      nr    8  <|@ instruction NOP <|@ <|@
      nr   10  <|@ instruction NOP <|@ <|@
      nr   12  <|@ instruction NOP <|@ <|@
      nr   14  <|@ instruction NOP <|@ <|@
      nr   16  <|@ instruction NOP <|@ <|@
      nr   18  <|@ instruction NOP <|@ <|@
      nr   20  <|@ instruction NOP <|@ <|@
      nr   22  <|@ instruction NOP <|@ <|@
      nr   24  <|@ instruction NOP <|@ <|@
      nr   26  <|@ instruction NOP <|@ <|@
      nr   28  <|@ instruction NOP <|@ <|@
      nr   30  <|@ instruction NOP <|@ <|@
      nr   32  <|@ instruction NOP <|@ <|@
      nr   34  <|@ instruction NOP <|@ <|@
      nr   36  <|@ instruction NOP <|@ <|@
      nr   38  <|@ instruction NOP <|@ <|@
      nr   40  <|@ instruction NOP <|@ <|@
      nr   42  <|@ instruction NOP <|@ <|@
      nr   44  <|@ instruction NOP <|@ <|@
      nr   46  <|@ instruction NOP <|@ <|@
      nr   48  <|@ instruction NOP <|@ <|@
      nr   50  <|@ instruction NOP <|@ <|@
      nr   52  <|@ instruction NOP <|@ <|@
      nr   54  <|@ instruction NOP <|@ <|@
      nr   56  <|@ instruction NOP <|@ <|@
      nr   58  <|@ instruction NOP <|@ <|@
      nr   60  <|@ instruction NOP <|@ <|@
      nr   62  <|@ instruction NOP <|@ <|@
      nr   64  <|@ instruction NOP <|@ <|@
      nr   66  <|@ instruction NOP <|@ <|@
      nr   68  <|@ instruction NOP <|@ <|@
      nr   70  <|@ instruction NOP <|@ <|@
      nr   72  <|@ instruction NOP <|@ <|@
      nr   74  <|@ instruction NOP <|@ <|@
      nr   76  <|@ instruction NOP <|@ <|@
      nr   78  <|@ instruction NOP <|@ <|@
      nr   80  <|@ instruction NOP <|@ <|@
      nr   82  <|@ instruction NOP <|@ <|@
      nr   84  <|@ instruction NOP <|@ <|@
      nr   86  <|@ instruction NOP <|@ <|@
      nr   88  <|@ instruction NOP <|@ <|@
      nr   90  <|@ instruction NOP <|@ <|@
      nr   92  <|@ instruction NOP <|@ <|@
      nr   94  <|@ instruction NOP <|@ <|@
      nr   96  <|@ instruction NOP <|@ <|@
      nr   98  <|@ instruction NOP <|@ <|@
      nr  100  <|@ instruction NOP <|@ <|@
      nr  102  <|@ instruction NOP <|@ <|@
      nr  104  <|@ instruction NOP <|@ <|@
      nr  106  <|@ instruction NOP <|@ <|@
      nr  108  <|@ instruction NOP <|@ <|@
      nr  110  <|@ instruction NOP <|@ <|@
      nr  112  <|@ instruction NOP <|@ <|@
      nr  114  <|@ instruction NOP <|@ <|@
      nr  116  <|@ instruction NOP <|@ <|@
      nr  118  <|@ instruction NOP <|@ <|@
      nr  120  <|@ instruction NOP <|@ <|@
      nr  122  <|@ instruction NOP <|@ <|@
      nr  124  <|@ instruction NOP <|@ <|@
      nr  126  <|@ instruction NOP <|@ <|@
      nr  128  <|@ instruction NOP <|@ <|@
      nr  132  <|@ instruction [] = HOTSPOTLOCKSTACK frameMapBuilder: jdk.graal.compiler.hotspot.amd64.AMD64HotSpotFrameMapBuilder@59edbf8f slotKind: QWORD <|@ <|@
      nr  136  <|@ instruction MOV x: [rsi|QWORD[.] + 12] y: 0 size: DWORD <|@ <|@
      nr  138  <|@ instruction AMD64G1PREWRITEBARRIER (~address: [rsi|QWORD[.] + 20], ~expectedObject: -) {temp: r10|QWORD, temp2: r11|QWORD, temp3: -} nonNull: false callTarget: Stub<write_barrier_pre-stack-only(Object)void>@0x7f78998c8200:CallingConvention[out:0|QWORD[.]]:CallingConvention[in:0|QWORD[.]] tool: jdk.graal.compiler.hotspot.amd64.g1.AMD64HotSpotG1BarrierSetLIRTool@33580fae <|@ <|@
      nr  140  <|@ instruction MOV x: [rsi|QWORD[.] + 20] y: -559030611 size: DWORD c: NarrowOop[Object[0]{}] <|@ <|@
      nr  142  <|@ instruction r10|QWORD[.] = HOTSPOTLOADOBJECTCONSTANT input: Object[Object[0]{}] <|@ <|@
      nr  144  <|@ instruction AMD64G1POSTWRITEBARRIER (~address: rsi|QWORD[.], ~newValue: r10|QWORD[.]) {temp: r11|QWORD, temp2: r8|QWORD} nonNull: true callTarget: Stub<write_barrier_post-stack-only(Word)void>@0x7f78998ca380:CallingConvention[out:0|QWORD]:CallingConvention[in:0|QWORD] tool: jdk.graal.compiler.hotspot.amd64.g1.AMD64HotSpotG1BarrierSetLIRTool@33580fae <|@ <|@
      nr  146  <|@ instruction RETURN (savedRbp: rbp|QWORD, value: -) isStub: false requiresReservedStackAccessCheck: false thread: r15 scratchForSafepointOnReturn: rcx config: jdk.graal.compiler.hotspot.GraalHotSpotVMConfig@4817c460 <|@ <|@
    end_IR
  end_block
end_cfg
begin_bytecodes
     0: aload_0       
     1: invokespecial #0          // java.util.AbstractList.<init>:()void
     4: aload_0       
     5: getstatic     #8          // DEFAULTCAPACITY_EMPTY_ELEMENTDATA:java.lang.Object[]
     8: putfield      #1          // elementData:java.lang.Object[]
    11: return        
   <|@
end_bytecodes
begin_cfg
  name "After code generation"
end_cfg
begin_nmethod
  <<<HexCodeFile
  Platform AMD64 64  <||@
  HexCode 0 448b560849bc0000002b787f00004d03d44d33e4493bc20f85e3ffffff66669089842400c0feff4883ec189041817f20000000000f85f800000090909090909090909090909090909090909090909090909090909090909090909090909090909090909090909090909090909090909090909090909090909090c7460c0000000041807f40000f842e000000448b5e1449c1e3034d85db0f841d0000004d8b57284983fa000f84970000004983ea084d8957284d0357384d891ac74614addeadde49baaddeaddeaddeadde4c8bde4d33da49c1eb160f84450000004c8bde49c1eb0949b800e0368d787f00004d03d841803b02742bf08304240041803b00742041c603004d8b47484d85c00f84400000004983e8084d8947484d0347584d89184883c418493ba7500400000f872c000000c348896c2410e800000000e9f9fefffff44c891c24e800000000e96afffffff44c891c24e800000000ebc4f4488d0dc0ffffff49898f68040000e990fefffff4e800000000f4e800000000f4  <||@
  Comment 0 UNVERIFIED_ENTRY  <||@
  Comment 23 {Field[name=CompilerToVM::Data::SharedRuntime_ic_miss_stub, type=address, offset=0, address=0x7f78b20335c8, value=140155947602048]:0x7f7899785080}  <||@
  Comment 32 [stack overflow check]  <||@
  Comment 32 VERIFIED_ENTRY  <||@
  Comment 44 FRAME_COMPLETE  <||@
  Comment 44 ENTRY_BARRIER_PATCH  <||@
  Comment 58 block B0 null  <||@
  Comment 58 0 [rsi|QWORD[.], rbp|QWORD] = LABEL alignment: 0 numbPhis: 0 label: ?  <||@
  Comment 58 2 NOP  <||@
  Comment 59 4 NOP  <||@
  Comment 60 6 NOP  <||@
  Comment 61 8 NOP  <||@
  Comment 62 10 NOP  <||@
  Comment 63 12 NOP  <||@
  Comment 64 14 NOP  <||@
  Comment 65 16 NOP  <||@
  Comment 66 18 NOP  <||@
  Comment 67 20 NOP  <||@
  Comment 68 22 NOP  <||@
  Comment 69 24 NOP  <||@
  Comment 70 26 NOP  <||@
  Comment 71 28 NOP  <||@
  Comment 72 30 NOP  <||@
  Comment 73 32 NOP  <||@
  Comment 74 34 NOP  <||@
  Comment 75 36 NOP  <||@
  Comment 76 38 NOP  <||@
  Comment 77 40 NOP  <||@
  Comment 78 42 NOP  <||@
  Comment 79 44 NOP  <||@
  Comment 80 46 NOP  <||@
  Comment 81 48 NOP  <||@
  Comment 82 50 NOP  <||@
  Comment 83 52 NOP  <||@
  Comment 84 54 NOP  <||@
  Comment 85 56 NOP  <||@
  Comment 86 58 NOP  <||@
  Comment 87 60 NOP  <||@
  Comment 88 62 NOP  <||@
  Comment 89 64 NOP  <||@
  Comment 90 66 NOP  <||@
  Comment 91 68 NOP  <||@
  Comment 92 70 NOP  <||@
  Comment 93 72 NOP  <||@
  Comment 94 74 NOP  <||@
  Comment 95 76 NOP  <||@
  Comment 96 78 NOP  <||@
  Comment 97 80 NOP  <||@
  Comment 98 82 NOP  <||@
  Comment 99 84 NOP  <||@
  Comment 100 86 NOP  <||@
  Comment 101 88 NOP  <||@
  Comment 102 90 NOP  <||@
  Comment 103 92 NOP  <||@
  Comment 104 94 NOP  <||@
  Comment 105 96 NOP  <||@
  Comment 106 98 NOP  <||@
  Comment 107 100 NOP  <||@
  Comment 108 102 NOP  <||@
  Comment 109 104 NOP  <||@
  Comment 110 106 NOP  <||@
  Comment 111 108 NOP  <||@
  Comment 112 110 NOP  <||@
  Comment 113 112 NOP  <||@
  Comment 114 114 NOP  <||@
  Comment 115 116 NOP  <||@
  Comment 116 118 NOP  <||@
  Comment 117 120 NOP  <||@
  Comment 118 122 NOP  <||@
  Comment 119 124 NOP  <||@
  Comment 120 126 NOP  <||@
  Comment 121 128 NOP  <||@
  Comment 122 132 [] = HOTSPOTLOCKSTACK frameMapBuilder: jdk.graal.compiler.hotspot.amd64.AMD64HotSpotFrameMapBuilder@59edbf8f slotKind: QWORD  <||@
  Comment 122 136 MOV x: [rsi|QWORD[.] + 12] y: 0 size: DWORD  <||@
  Comment 129 138 AMD64G1PREWRITEBARRIER (~address: [rsi|QWORD[.] + 20], ~expectedObject: -) {temp: r10|QWORD, temp2: r11|QWORD, temp3: -} nonNull: false callTarget: Stub<write_barrier_pre-stack-only(Object)void>@0x7f78998c8200:CallingConvention[out:0|QWORD[.]]:CallingConvention[in:0|QWORD[.]] tool: jdk.graal.compiler.hotspot.amd64.g1.AMD64HotSpotG1BarrierSetLIRTool@33580fae  <||@
  Comment 186 140 MOV x: [rsi|QWORD[.] + 20] y: -559030611 size: DWORD c: NarrowOop[Object[0]{}]  <||@
  Comment 186 {NarrowOop[Object[0]{}]}  <||@
  Comment 193 142 r10|QWORD[.] = HOTSPOTLOADOBJECTCONSTANT input: Object[Object[0]{}]  <||@
  Comment 193 {Object[Object[0]{}]}  <||@
  Comment 203 144 AMD64G1POSTWRITEBARRIER (~address: rsi|QWORD[.], ~newValue: r10|QWORD[.]) {temp: r11|QWORD, temp2: r8|QWORD} nonNull: true callTarget: Stub<write_barrier_post-stack-only(Word)void>@0x7f78998ca380:CallingConvention[out:0|QWORD]:CallingConvention[in:0|QWORD] tool: jdk.graal.compiler.hotspot.amd64.g1.AMD64HotSpotG1BarrierSetLIRTool@33580fae  <||@
  Comment 288 146 RETURN (savedRbp: rbp|QWORD, value: -) isStub: false requiresReservedStackAccessCheck: false thread: r15 scratchForSafepointOnReturn: rcx config: jdk.graal.compiler.hotspot.GraalHotSpotVMConfig@4817c460  <||@
  Comment 292 POLL_RETURN_FAR  <||@
  Comment 311 {Field[name=CompilerToVM::Data::nmethod_entry_barrier, type=address, offset=0, address=0x7f78b2033598, value=140155947495968]:0x7f789976b220}  <||@
  Comment 326 {Stub<write_barrier_pre-stack-only(Object)void>@0x7f78998c8200:CallingConvention[out:0|QWORD[.]]:CallingConvention[in:0|QWORD[.]]}  <||@
  Comment 341 {Stub<write_barrier_post-stack-only(Word)void>@0x7f78998ca380:CallingConvention[out:0|QWORD]:CallingConvention[in:0|QWORD]}  <||@
  Comment 363 {Field[name=CompilerToVM::Data::SharedRuntime_polling_page_return_handler, type=address, offset=0, address=0x7f78b20335a0, value=140155947630592]:0x7f789978c000}  <||@
  Comment 369 {Stub<ExceptionHandlerStub.exceptionHandler>@0x7f78998c5300:CallingConvention[rax|QWORD[.], rdx|QWORD]:CallingConvention[rax|QWORD[.], rdx|QWORD]; temps=rdi|ILLEGAL,xmm14|ILLEGAL,xmm15|ILLEGAL,xmm12|ILLEGAL,xmm13|ILLEGAL,xmm10|ILLEGAL,xmm11|ILLEGAL,xmm7|ILLEGAL,xmm8|ILLEGAL,xmm9|ILLEGAL,xmm0|ILLEGAL,xmm1|ILLEGAL,xmm2|ILLEGAL,xmm3|ILLEGAL,xmm4|ILLEGAL,xmm5|ILLEGAL,xmm6|ILLEGAL,rax|ILLEGAL,rcx|ILLEGAL,rdx|ILLEGAL,rsi|ILLEGAL,r8|ILLEGAL,r9|ILLEGAL,r10|ILLEGAL,r11|ILLEGAL}  <||@
  Comment 369 EXCEPTION_HANDLER_ENTRY  <||@
  Comment 375 {Field[name=CompilerToVM::Data::SharedRuntime_deopt_blob_unpack, type=address, offset=0, address=0x7f78b20335b8, value=140155947626272]:0x7f789978af20}  <||@
  Comment 375 DEOPT_HANDLER_ENTRY  <||@
  HexCodeFile>>> <|@
end_nmethod
begin_compilation
  name " HotSpotCompilation-6956[java.util.ArrayList.<init>()]"
  method "HotSpotCompilation-6956[java.util.ArrayList.<init>()]"
  date 1724269753845
end_compilation
begin_cfg
  name "After code installation"
end_cfg
begin_nmethod
  <<<HexCodeFile
  Platform AMD64 64  <||@
  HexCode 7f789aef0680 448b560849bc0000002b787f00004d03d44d33e4493bc20f85e34989fe66669089842400c0feff4883ec189041817f20000000000f85f800000090909090909090909090909090909090909090909090909090909090909090909090909090909090909090909090909090909090909090909090909090909090c7460c0000000041807f40000f842e000000448b5e1449c1e3034d85db0f841d0000004d8b57284983fa000f84970000004983ea084d8957284d0357384d891ac74614a984bbc549ba4825dc2d060000004c8bde4d33da49c1eb160f84450000004c8bde49c1eb0949b800e0368d787f00004d03d841803b02742bf08304240041803b00742041c603004d8b47484d85c00f84400000004983e8084d8947484d0347584d89184883c418493ba7500400000f872c000000c348896c2410e864aa87fee9f9fefffff44c891c24e8357a9dfee96afffffff44c891c24e8a69b9dfeebc4f4488d0dc0ffffff49898f68040000e910b889fef4e80a4b9dfef4e824a789fef4f4f4f4  <||@
  Comment 0 UNVERIFIED_ENTRY  <||@
  Comment 23 {Field[name=CompilerToVM::Data::SharedRuntime_ic_miss_stub, type=address, offset=0, address=0x7f78b20335c8, value=140155947602048]:0x7f7899785080}  <||@
  Comment 32 [stack overflow check]  <||@
  Comment 32 VERIFIED_ENTRY  <||@
  Comment 44 FRAME_COMPLETE  <||@
  Comment 44 ENTRY_BARRIER_PATCH  <||@
  Comment 58 block B0 null  <||@
  Comment 58 0 [rsi|QWORD[.], rbp|QWORD] = LABEL alignment: 0 numbPhis: 0 label: ?  <||@
  Comment 58 2 NOP  <||@
  Comment 59 4 NOP  <||@
  Comment 60 6 NOP  <||@
  Comment 61 8 NOP  <||@
  Comment 62 10 NOP  <||@
  Comment 63 12 NOP  <||@
  Comment 64 14 NOP  <||@
  Comment 65 16 NOP  <||@
  Comment 66 18 NOP  <||@
  Comment 67 20 NOP  <||@
  Comment 68 22 NOP  <||@
  Comment 69 24 NOP  <||@
  Comment 70 26 NOP  <||@
  Comment 71 28 NOP  <||@
  Comment 72 30 NOP  <||@
  Comment 73 32 NOP  <||@
  Comment 74 34 NOP  <||@
  Comment 75 36 NOP  <||@
  Comment 76 38 NOP  <||@
  Comment 77 40 NOP  <||@
  Comment 78 42 NOP  <||@
  Comment 79 44 NOP  <||@
  Comment 80 46 NOP  <||@
  Comment 81 48 NOP  <||@
  Comment 82 50 NOP  <||@
  Comment 83 52 NOP  <||@
  Comment 84 54 NOP  <||@
  Comment 85 56 NOP  <||@
  Comment 86 58 NOP  <||@
  Comment 87 60 NOP  <||@
  Comment 88 62 NOP  <||@
  Comment 89 64 NOP  <||@
  Comment 90 66 NOP  <||@
  Comment 91 68 NOP  <||@
  Comment 92 70 NOP  <||@
  Comment 93 72 NOP  <||@
  Comment 94 74 NOP  <||@
  Comment 95 76 NOP  <||@
  Comment 96 78 NOP  <||@
  Comment 97 80 NOP  <||@
  Comment 98 82 NOP  <||@
  Comment 99 84 NOP  <||@
  Comment 100 86 NOP  <||@
  Comment 101 88 NOP  <||@
  Comment 102 90 NOP  <||@
  Comment 103 92 NOP  <||@
  Comment 104 94 NOP  <||@
  Comment 105 96 NOP  <||@
  Comment 106 98 NOP  <||@
  Comment 107 100 NOP  <||@
  Comment 108 102 NOP  <||@
  Comment 109 104 NOP  <||@
  Comment 110 106 NOP  <||@
  Comment 111 108 NOP  <||@
  Comment 112 110 NOP  <||@
  Comment 113 112 NOP  <||@
  Comment 114 114 NOP  <||@
  Comment 115 116 NOP  <||@
  Comment 116 118 NOP  <||@
  Comment 117 120 NOP  <||@
  Comment 118 122 NOP  <||@
  Comment 119 124 NOP  <||@
  Comment 120 126 NOP  <||@
  Comment 121 128 NOP  <||@
  Comment 122 132 [] = HOTSPOTLOCKSTACK frameMapBuilder: jdk.graal.compiler.hotspot.amd64.AMD64HotSpotFrameMapBuilder@59edbf8f slotKind: QWORD  <||@
  Comment 122 136 MOV x: [rsi|QWORD[.] + 12] y: 0 size: DWORD  <||@
  Comment 129 138 AMD64G1PREWRITEBARRIER (~address: [rsi|QWORD[.] + 20], ~expectedObject: -) {temp: r10|QWORD, temp2: r11|QWORD, temp3: -} nonNull: false callTarget: Stub<write_barrier_pre-stack-only(Object)void>@0x7f78998c8200:CallingConvention[out:0|QWORD[.]]:CallingConvention[in:0|QWORD[.]] tool: jdk.graal.compiler.hotspot.amd64.g1.AMD64HotSpotG1BarrierSetLIRTool@33580fae  <||@
  Comment 186 140 MOV x: [rsi|QWORD[.] + 20] y: -559030611 size: DWORD c: NarrowOop[Object[0]{}]  <||@
  Comment 186 {NarrowOop[Object[0]{}]}  <||@
  Comment 193 142 r10|QWORD[.] = HOTSPOTLOADOBJECTCONSTANT input: Object[Object[0]{}]  <||@
  Comment 193 {Object[Object[0]{}]}  <||@
  Comment 203 144 AMD64G1POSTWRITEBARRIER (~address: rsi|QWORD[.], ~newValue: r10|QWORD[.]) {temp: r11|QWORD, temp2: r8|QWORD} nonNull: true callTarget: Stub<write_barrier_post-stack-only(Word)void>@0x7f78998ca380:CallingConvention[out:0|QWORD]:CallingConvention[in:0|QWORD] tool: jdk.graal.compiler.hotspot.amd64.g1.AMD64HotSpotG1BarrierSetLIRTool@33580fae  <||@
  Comment 288 146 RETURN (savedRbp: rbp|QWORD, value: -) isStub: false requiresReservedStackAccessCheck: false thread: r15 scratchForSafepointOnReturn: rcx config: jdk.graal.compiler.hotspot.GraalHotSpotVMConfig@4817c460  <||@
  Comment 292 POLL_RETURN_FAR  <||@
  Comment 311 {Field[name=CompilerToVM::Data::nmethod_entry_barrier, type=address, offset=0, address=0x7f78b2033598, value=140155947495968]:0x7f789976b220}  <||@
  Comment 326 {Stub<write_barrier_pre-stack-only(Object)void>@0x7f78998c8200:CallingConvention[out:0|QWORD[.]]:CallingConvention[in:0|QWORD[.]]}  <||@
  Comment 341 {Stub<write_barrier_post-stack-only(Word)void>@0x7f78998ca380:CallingConvention[out:0|QWORD]:CallingConvention[in:0|QWORD]}  <||@
  Comment 363 {Field[name=CompilerToVM::Data::SharedRuntime_polling_page_return_handler, type=address, offset=0, address=0x7f78b20335a0, value=140155947630592]:0x7f789978c000}  <||@
  Comment 369 {Stub<ExceptionHandlerStub.exceptionHandler>@0x7f78998c5300:CallingConvention[rax|QWORD[.], rdx|QWORD]:CallingConvention[rax|QWORD[.], rdx|QWORD]; temps=rdi|ILLEGAL,xmm14|ILLEGAL,xmm15|ILLEGAL,xmm12|ILLEGAL,xmm13|ILLEGAL,xmm10|ILLEGAL,xmm11|ILLEGAL,xmm7|ILLEGAL,xmm8|ILLEGAL,xmm9|ILLEGAL,xmm0|ILLEGAL,xmm1|ILLEGAL,xmm2|ILLEGAL,xmm3|ILLEGAL,xmm4|ILLEGAL,xmm5|ILLEGAL,xmm6|ILLEGAL,rax|ILLEGAL,rcx|ILLEGAL,rdx|ILLEGAL,rsi|ILLEGAL,r8|ILLEGAL,r9|ILLEGAL,r10|ILLEGAL,r11|ILLEGAL}  <||@
  Comment 369 EXCEPTION_HANDLER_ENTRY  <||@
  Comment 375 {Field[name=CompilerToVM::Data::SharedRuntime_deopt_blob_unpack, type=address, offset=0, address=0x7f78b20335b8, value=140155947626272]:0x7f789978af20}  <||@
  Comment 375 DEOPT_HANDLER_ENTRY  <||@
  HexCodeFile>>> <|@
end_nmethod
